Workbook

Sheet PLAN BUDGET SAMI-JF
A1: PT. SEMARANG AUTOCOMP MANUFACTURING INDONESIA
A2: BUDGET EXPENSE FORM | N2: EXCHANGE RATE TO USD
A3: PERIODE Jul-25 SD Jun-26 | N3: IDR | O3: 15798.6
A4: DEPARTMENT-SECTION : PGA-TRN | N4: JPY | O4: 151
N5: THB | O5: 34.373
N6: USD | O6: 1
N7: EUR | O7: 0.926
N8: CHF | O8: 0.872
A10: SECTION | B10: BUDGET REF NO | C10: PART_NO | D10: PART NAME | E10: DETAIL PART | F10: FUNGSI / TUJUAN | G10: SECTION CATEGORY | H10: ACC NO. | I10: ACCOUNT DESCRIPTION | J10: CATEGORY | K10: COST CENTER | L10: CARLINE | M10: CARMAKER | N10: UOM | O10: ORG CURR | P10: PRICE ORG CURR | AB10: PRICE USD | AN10: 202507 | AO10: 202508 | AP10: 202509 | AQ10: 202510 | AR10: 202511 | AS10: 202512 | AT10: 202601 | AU10: 202602 | AV10: 202603 | AW10: 202604 | AX10: 202605 | AY10: 202606 | AZ10: TOTAL | BA10: AVERAGE | BC10: 202507 | BD10: 202508 | BE10: 202509 | BF10: 202510 | BG10: 202511 | BH10: 202512 | BI10: 202601 | BJ10: 202602 | BK10: 202603 | BL10: 202604 | BM10: 202605 | BN10: 202606 | BO10: TOTAL | BP10: AVERAGE | BR10: SUB ACCOUNT | BS10: KODE PROSES | BT10: PURCHASING | BU10: LEADTIME
P11: 202507 | Q11: 202508 | R11: 202509 | S11: 202510 | T11: 202511 | U11: 202512 | V11: 202601 | W11: 202602 | X11: 202603 | Y11: 202604 | Z11: 202605 | AA11: 202606 | AB11: 202507 | AC11: 202508 | AD11: 202509 | AE11: 202510 | AF11: 202511 | AG11: 202512 | AH11: 202601 | AI11: 202602 | AJ11: 202603 | AK11: 202604 | AL11: 202605 | AM11: 202606 | AN11: QTY | AO11: QTY | AP11: QTY | AQ11: QTY | AR11: QTY | AS11: QTY | AT11: QTY | AU11: QTY | AV11: QTY | AW11: QTY | AX11: QTY | AY11: QTY | BC11: AMT | BD11: AMT | BE11: AMT | BF11: AMT | BG11: AMT | BH11: AMT | BI11: AMT | BJ11: AMT | BK11: AMT | BL11: AMT | BM11: AMT | BN11: AMT | BU11: PENAWARAN | BV11: PR | BW11: PO | BX11: KEDATANGAN | BY11: VP
A13: PGA-TRN | C13: A-03149 | D13: PLASTIK ID CARD | E13: PLASTIK ID CARD DEPAN SOBEK SAMPING | F13: INCLASS LICENSE | G13: OPEX | J13: RUTIN | K13: JPI000 | L13: ALL | M13: ALL | N13: PCS | O13: IDR | P13: 1670 | Q13: 1670 | R13: 1670 | S13: 1670 | T13: 1670 | U13: 1670 | V13: 1670 | W13: 1670 | X13: 1670 | Y13: 1670 | Z13: 1670 | AA13: 1670 | AB13: 0.10570557 | AC13: 0.10570557 | AD13: 0.10570557 | AE13: 0.10570557 | AF13: 0.10570557 | AG13: 0.10570557 | AH13: 0.10570557 | AI13: 0.10570557 | AJ13: 0.10570557 | AK13: 0.10570557 | AL13: 0.10570557 | AM13: 0.10570557 | AN13: 0 | AO13: 560 | AP13: 0 | AQ13: 0 | AR13: 552 | AS13: 0 | AT13: 0 | AU13: 0 | AV13: 300 | AW13: 0 | AX13: 0 | AY13: 300 | AZ13: =SUM(AN13:AY13) -> 1712 | BA13: =AZ13/12 -> 142.66667 | BC13: 0 | BD13: 59.195119 | BE13: 0 | BF13: 0 | BG13: 58.349474 | BH13: 0 | BI13: 0 | BJ13: 0 | BK13: 31.711671 | BL13: 0 | BM13: 0 | BN13: 31.711671 | BO13: =SUM(BC13:BN13) -> 180.96793 | BP13: =BO13/12 -> 15.080661 | BS13: C | BT13: GA | BU13: 15 | BV13: 10 | BW13: 5 | BX13: 20 | BY13: 5
A14: PGA-TRN | C14: A-03442 | D14: PERJALANAN DINAS | E14: HOTEL DALAM NEGERI (TRAVELING/MEETING) GOL IV | F14: KAIZEN FESTIVAL TMC | G14: OPEX | J14: RUTIN | K14: JPI000 | L14: ALL | M14: ALL | N14: DAY | O14: IDR | P14: 1200000 | Q14: 1200000 | R14: 1200000 | S14: 1200000 | T14: 1200000 | U14: 1200000 | V14: 1200000 | W14: 1200000 | X14: 1200000 | Y14: 1200000 | Z14: 1200000 | AA14: 1200000 | AB14: 75.956097 | AC14: 75.956097 | AD14: 75.956097 | AE14: 75.956097 | AF14: 75.956097 | AG14: 75.956097 | AH14: 75.956097 | AI14: 75.956097 | AJ14: 75.956097 | AK14: 75.956097 | AL14: 75.956097 | AM14: 75.956097 | AN14: 0 | AO14: 0 | AP14: 0 | AQ14: 0 | AR14: 2 | AS14: 0 | AT14: 0 | AU14: 0 | AV14: 0 | AW14: 0 | AX14: 0 | AY14: 0 | AZ14: =SUM(AN14:AY14) -> 2 | BA14: =AZ14/12 -> 0.16666667 | BC14: 0 | BD14: 0 | BE14: 0 | BF14: 0 | BG14: 151.91219 | BH14: 0 | BI14: 0 | BJ14: 0 | BK14: 0 | BL14: 0 | BM14: 0 | BN14: 0 | BO14: =SUM(BC14:BN14) -> 151.91219 | BP14: =BO14/12 -> 12.65935 | BS14: D | BT14: GA | BU14: 0 | BV14: 10 | BW14: 0 | BX14: 0 | BY14: 5
A15: PGA-TRN | C15: A-01223 | D15: POINTER | E15: POINTER | F15: INCLASS TRAINING KELAS | G15: OPEX | J15: RUTIN | K15: JPI000 | L15: ALL | M15: ALL | N15: PCS | O15: IDR | P15: 473800 | Q15: 473800 | R15: 473800 | S15: 473800 | T15: 473800 | U15: 473800 | V15: 473800 | W15: 473800 | X15: 473800 | Y15: 473800 | Z15: 473800 | AA15: 473800 | AB15: 29.989999 | AC15: 29.989999 | AD15: 29.989999 | AE15: 29.989999 | AF15: 29.989999 | AG15: 29.989999 | AH15: 29.989999 | AI15: 29.989999 | AJ15: 29.989999 | AK15: 29.989999 | AL15: 29.989999 | AM15: 29.989999 | AN15: 0 | AO15: 0 | AP15: 2 | AQ15: 0 | AR15: 0 | AS15: 0 | AT15: 0 | AU15: 0 | AV15: 0 | AW15: 0 | AX15: 0 | AY15: 0 | AZ15: =SUM(AN15:AY15) -> 2 | BA15: =AZ15/12 -> 0.16666667 | BC15: 0 | BD15: 0 | BE15: 59.979998 | BF15: 0 | BG15: 0 | BH15: 0 | BI15: 0 | BJ15: 0 | BK15: 0 | BL15: 0 | BM15: 0 | BN15: 0 | BO15: =SUM(BC15:BN15) -> 59.979998 | BP15: =BO15/12 -> 4.9983332 | BS15: C | BT15: GA | BU15: 15 | BV15: 10 | BW15: 5 | BX15: 20 | BY15: 5
A16: PGA-TRN | C16: A-03946 | D16: PERJALANAN DINAS | E16: UANG MAKAN SIANG PD DALAM NEGERI (TRAVELLING & MEETING) GOL III | F16: KAIZEN FESTIVAL TMC | G16: OPEX | J16: RUTIN | K16: JPI000 | L16: ALL | M16: ALL | N16: DAY | O16: IDR | P16: 20000 | Q16: 20000 | R16: 20000 | S16: 20000 | T16: 20000 | U16: 20000 | V16: 20000 | W16: 20000 | X16: 20000 | Y16: 20000 | Z16: 20000 | AA16: 20000 | AB16: 1.265935 | AC16: 1.265935 | AD16: 1.265935 | AE16: 1.265935 | AF16: 1.265935 | AG16: 1.265935 | AH16: 1.265935 | AI16: 1.265935 | AJ16: 1.265935 | AK16: 1.265935 | AL16: 1.265935 | AM16: 1.265935 | AN16: 0 | AO16: 0 | AP16: 0 | AQ16: 0 | AR16: 3 | AS16: 0 | AT16: 0 | AU16: 0 | AV16: 0 | AW16: 0 | AX16: 0 | AY16: 0 | AZ16: =SUM(AN16:AY16) -> 3 | BA16: =AZ16/12 -> 0.25 | BC16: 0 | BD16: 0 | BE16: 0 | BF16: 0 | BG16: 3.7978049 | BH16: 0 | BI16: 0 | BJ16: 0 | BK16: 0 | BL16: 0 | BM16: 0 | BN16: 0 | BO16: =SUM(BC16:BN16) -> 3.7978049 | BP16: =BO16/12 -> 0.31648374 | BS16: D | BT16: GA | BU16: 0 | BV16: 10 | BW16: 0 | BX16: 0 | BY16: 5
A17: PGA-TRN | C17: A-03959 | D17: PERJALANAN DINAS | E17: UANG MAKAN SIANG PD DALAM NEGERI (TRAVELLING & MEETING) GOL IV | F17: KAIZEN FESTIVAL TMC | G17: OPEX | J17: RUTIN | K17: JPI000 | L17: ALL | M17: ALL | N17: DAY | O17: IDR | P17: 27500 | Q17: 27500 | R17: 27500 | S17: 27500 | T17: 27500 | U17: 27500 | V17: 27500 | W17: 27500 | X17: 27500 | Y17: 27500 | Z17: 27500 | AA17: 27500 | AB17: 1.7406606 | AC17: 1.7406606 | AD17: 1.7406606 | AE17: 1.7406606 | AF17: 1.7406606 | AG17: 1.7406606 | AH17: 1.7406606 | AI17: 1.7406606 | AJ17: 1.7406606 | AK17: 1.7406606 | AL17: 1.7406606 | AM17: 1.7406606 | AN17: 0 | AO17: 0 | AP17: 0 | AQ17: 0 | AR17: 3 | AS17: 0 | AT17: 0 | AU17: 0 | AV17: 0 | AW17: 0 | AX17: 0 | AY17: 0 | AZ17: =SUM(AN17:AY17) -> 3 | BA17: =AZ17/12 -> 0.25 | BC17: 0 | BD17: 0 | BE17: 0 | BF17: 0 | BG17: 5.2219817 | BH17: 0 | BI17: 0 | BJ17: 0 | BK17: 0 | BL17: 0 | BM17: 0 | BN17: 0 | BO17: =SUM(BC17:BN17) -> 5.2219817 | BP17: =BO17/12 -> 0.43516514 | BS17: D | BT17: GA | BU17: 0 | BV17: 10 | BW17: 0 | BX17: 0 | BY17: 5
A18: PGA-TRN | C18: A-00704 | D18: MASKER | E18: SAFETY MASK CARBON ACTIVE - LONG | F18: NEOP SIMULASI B3 | G18: OPEX | J18: RUTIN | K18: JPI000 | L18: ALL | M18: ALL | N18: PCS | O18: IDR | P18: 33000 | Q18: 33000 | R18: 33000 | S18: 33000 | T18: 33000 | U18: 33000 | V18: 33000 | W18: 33000 | X18: 33000 | Y18: 33000 | Z18: 33000 | AA18: 33000 | AB18: 2.0887927 | AC18: 2.0887927 | AD18: 2.0887927 | AE18: 2.0887927 | AF18: 2.0887927 | AG18: 2.0887927 | AH18: 2.0887927 | AI18: 2.0887927 | AJ18: 2.0887927 | AK18: 2.0887927 | AL18: 2.0887927 | AM18: 2.0887927 | AN18: 0 | AO18: 0 | AP18: 13 | AQ18: 0 | AR18: 0 | AS18: 0 | AT18: 0 | AU18: 13 | AV18: 0 | AW18: 0 | AX18: 0 | AY18: 0 | AZ18: =SUM(AN18:AY18) -> 26 | BA18: =AZ18/12 -> 2.1666667 | BC18: 0 | BD18: 0 | BE18: 27.154305 | BF18: 0 | BG18: 0 | BH18: 0 | BI18: 0 | BJ18: 27.154305 | BK18: 0 | BL18: 0 | BM18: 0 | BN18: 0 | BO18: =SUM(BC18:BN18) -> 54.30861 | BP18: =BO18/12 -> 4.5257175 | BS18: C | BT18: GA | BU18: 15 | BV18: 10 | BW18: 5 | BX18: 20 | BY18: 5
A19: PGA-TRN | C19: A-03944 | D19: PERJALANAN DINAS | E19: UANG MAKAN PAGI PD DALAM NEGERI (TRAVELLING & MEETING) GOL III | F19: KAIZEN FESTIVAL TMC | G19: OPEX | J19: RUTIN | K19: JPI000 | L19: ALL | M19: ALL | N19: DAY | O19: IDR | P19: 12500 | Q19: 12500 | R19: 12500 | S19: 12500 | T19: 12500 | U19: 12500 | V19: 12500 | W19: 12500 | X19: 12500 | Y19: 12500 | Z19: 12500 | AA19: 12500 | AB19: 0.79120935 | AC19: 0.79120935 | AD19: 0.79120935 | AE19: 0.79120935 | AF19: 0.79120935 | AG19: 0.79120935 | AH19: 0.79120935 | AI19: 0.79120935 | AJ19: 0.79120935 | AK19: 0.79120935 | AL19: 0.79120935 | AM19: 0.79120935 | AN19: 0 | AO19: 0 | AP19: 0 | AQ19: 0 | AR19: 3 | AS19: 0 | AT19: 0 | AU19: 0 | AV19: 0 | AW19: 0 | AX19: 0 | AY19: 0 | AZ19: =SUM(AN19:AY19) -> 3 | BA19: =AZ19/12 -> 0.25 | BC19: 0 | BD19: 0 | BE19: 0 | BF19: 0 | BG19: 2.373628 | BH19: 0 | BI19: 0 | BJ19: 0 | BK19: 0 | BL19: 0 | BM19: 0 | BN19: 0 | BO19: =SUM(BC19:BN19) -> 2.373628 | BP19: =BO19/12 -> 0.19780234 | BS19: D | BT19: GA | BU19: 0 | BV19: 10 | BW19: 0 | BX19: 0 | BY19: 5
A20: PGA-TRN | C20: A-03961 | D20: PERJALANAN DINAS | E20: UANG MAKAN MALAM PD DALAM NEGERI (TRAVELLING & MEETING) GOL IV | F20: KAIZEN FESTIVAL TMC | G20: OPEX | J20: RUTIN | K20: JPI000 | L20: ALL | M20: ALL | N20: DAY | O20: IDR | P20: 27500 | Q20: 27500 | R20: 27500 | S20: 27500 | T20: 27500 | U20: 27500 | V20: 27500 | W20: 27500 | X20: 27500 | Y20: 27500 | Z20: 27500 | AA20: 27500 | AB20: 1.7406606 | AC20: 1.7406606 | AD20: 1.7406606 | AE20: 1.7406606 | AF20: 1.7406606 | AG20: 1.7406606 | AH20: 1.7406606 | AI20: 1.7406606 | AJ20: 1.7406606 | AK20: 1.7406606 | AL20: 1.7406606 | AM20: 1.7406606 | AN20: 0 | AO20: 0 | AP20: 0 | AQ20: 0 | AR20: 3 | AS20: 0 | AT20: 0 | AU20: 0 | AV20: 0 | AW20: 0 | AX20: 0 | AY20: 0 | AZ20: =SUM(AN20:AY20) -> 3 | BA20: =AZ20/12 -> 0.25 | BC20: 0 | BD20: 0 | BE20: 0 | BF20: 0 | BG20: 5.2219817 | BH20: 0 | BI20: 0 | BJ20: 0 | BK20: 0 | BL20: 0 | BM20: 0 | BN20: 0 | BO20: =SUM(BC20:BN20) -> 5.2219817 | BP20: =BO20/12 -> 0.43516514 | BS20: D | BT20: GA | BU20: 0 | BV20: 10 | BW20: 0 | BX20: 0 | BY20: 5
A21: PGA-TRN | C21: A-00451 | D21: FORM | E21: FORMULIR DAFTAR HADIR TRAINING | F21: RECORD TRAINING | G21: OPEX | J21: RUTIN | K21: JPI000 | L21: ALL | M21: ALL | N21: RIM | O21: IDR | P21: 200000 | Q21: 200000 | R21: 200000 | S21: 200000 | T21: 200000 | U21: 200000 | V21: 200000 | W21: 200000 | X21: 200000 | Y21: 200000 | Z21: 200000 | AA21: 200000 | AB21: 12.65935 | AC21: 12.65935 | AD21: 12.65935 | AE21: 12.65935 | AF21: 12.65935 | AG21: 12.65935 | AH21: 12.65935 | AI21: 12.65935 | AJ21: 12.65935 | AK21: 12.65935 | AL21: 12.65935 | AM21: 12.65935 | AN21: 0 | AO21: 0 | AP21: 0 | AQ21: 1 | AR21: 0 | AS21: 0 | AT21: 0 | AU21: 0 | AV21: 0 | AW21: 1 | AX21: 0 | AY21: 0 | AZ21: =SUM(AN21:AY21) -> 2 | BA21: =AZ21/12 -> 0.16666667 | BC21: 0 | BD21: 0 | BE21: 0 | BF21: 12.65935 | BG21: 0 | BH21: 0 | BI21: 0 | BJ21: 0 | BK21: 0 | BL21: 12.65935 | BM21: 0 | BN21: 0 | BO21: =SUM(BC21:BN21) -> 25.318699 | BP21: =BO21/12 -> 2.1098916 | BS21: C | BT21: GA | BU21: 15 | BV21: 10 | BW21: 5 | BX21: 20 | BY21: 5
A22: PGA-TRN | C22: A-00641 | D22: BATTERY | E22: BATTERY CR2032 3V | F22: NEOP BATERAI STOPWATCH | G22: OPEX | J22: RUTIN | K22: JPI000 | L22: ALL | M22: ALL | N22: PCS | O22: IDR | P22: 5000 | Q22: 5000 | R22: 5000 | S22: 5000 | T22: 5000 | U22: 5000 | V22: 5000 | W22: 5000 | X22: 5000 | Y22: 5000 | Z22: 5000 | AA22: 5000 | AB22: 0.31648374 | AC22: 0.31648374 | AD22: 0.31648374 | AE22: 0.31648374 | AF22: 0.31648374 | AG22: 0.31648374 | AH22: 0.31648374 | AI22: 0.31648374 | AJ22: 0.31648374 | AK22: 0.31648374 | AL22: 0.31648374 | AM22: 0.31648374 | AN22: 0 | AO22: 20 | AP22: 0 | AQ22: 0 | AR22: 0 | AS22: 0 | AT22: 20 | AU22: 0 | AV22: 0 | AW22: 0 | AX22: 0 | AY22: 0 | AZ22: =SUM(AN22:AY22) -> 40 | BA22: =AZ22/12 -> 3.3333333 | BC22: 0 | BD22: 6.3296748 | BE22: 0 | BF22: 0 | BG22: 0 | BH22: 0 | BI22: 6.3296748 | BJ22: 0 | BK22: 0 | BL22: 0 | BM22: 0 | BN22: 0 | BO22: =SUM(BC22:BN22) -> 12.65935 | BP22: =BO22/12 -> 1.0549458 | BS22: C | BT22: GA | BU22: 15 | BV22: 10 | BW22: 5 | BX22: 20 | BY22: 5
A23: PGA-TRN | C23: A-03050 | D23: TES BAHASA ASING | E23: JLPT N5 | F23: BAHASA JEPANG JLPT | G23: OPEX | J23: RUTIN | K23: JPI000 | L23: ALL | M23: ALL | N23: PEOPLE | O23: IDR | P23: 140000 | Q23: 140000 | R23: 140000 | S23: 140000 | T23: 140000 | U23: 140000 | V23: 140000 | W23: 140000 | X23: 140000 | Y23: 140000 | Z23: 140000 | AA23: 140000 | AB23: 8.8615447 | AC23: 8.8615447 | AD23: 8.8615447 | AE23: 8.8615447 | AF23: 8.8615447 | AG23: 8.8615447 | AH23: 8.8615447 | AI23: 8.8615447 | AJ23: 8.8615447 | AK23: 8.8615447 | AL23: 8.8615447 | AM23: 8.8615447 | AN23: 0 | AO23: 0 | AP23: 0 | AQ23: 0 | AR23: 0 | AS23: 0 | AT23: 0 | AU23: 0 | AV23: 10 | AW23: 0 | AX23: 0 | AY23: 0 | AZ23: =SUM(AN23:AY23) -> 10 | BA23: =AZ23/12 -> 0.83333333 | BC23: 0 | BD23: 0 | BE23: 0 | BF23: 0 | BG23: 0 | BH23: 0 | BI23: 0 | BJ23: 0 | BK23: 88.615447 | BL23: 0 | BM23: 0 | BN23: 0 | BO23: =SUM(BC23:BN23) -> 88.615447 | BP23: =BO23/12 -> 7.3846206 | BS23: B | BT23: GA | BU23: 0 | BV23: 5 | BW23: 0 | BX23: 15 | BY23: 15
A24: PGA-TRN | C24: A-03610 | D24: BULAN COMPLIANCE | E24: BULAN COMPLIANCE | F24: AKTIFITAS BULAN COMPLIANCE | G24: OPEX | J24: RUTIN | K24: JPI000 | L24: ALL | M24: ALL | N24: PAKET | O24: IDR | P24: 5000000 | Q24: 5000000 | R24: 5000000 | S24: 5000000 | T24: 5000000 | U24: 5000000 | V24: 5000000 | W24: 5000000 | X24: 5000000 | Y24: 5000000 | Z24: 5000000 | AA24: 5000000 | AB24: 316.48374 | AC24: 316.48374 | AD24: 316.48374 | AE24: 316.48374 | AF24: 316.48374 | AG24: 316.48374 | AH24: 316.48374 | AI24: 316.48374 | AJ24: 316.48374 | AK24: 316.48374 | AL24: 316.48374 | AM24: 316.48374 | AN24: 0 | AO24: 0 | AP24: 0 | AQ24: 0 | AR24: 0 | AS24: 0 | AT24: 0 | AU24: 0 | AV24: 0 | AW24: 0 | AX24: 0 | AY24: 1 | AZ24: =SUM(AN24:AY24) -> 1 | BA24: =AZ24/12 -> 0.083333333 | BC24: 0 | BD24: 0 | BE24: 0 | BF24: 0 | BG24: 0 | BH24: 0 | BI24: 0 | BJ24: 0 | BK24: 0 | BL24: 0 | BM24: 0 | BN24: 316.48374 | BO24: =SUM(BC24:BN24) -> 316.48374 | BP24: =BO24/12 -> 26.373645 | BS24: E | BT24: GA | BU24: 0 | BV24: 10 | BW24: 0 | BX24: 10 | BY24: 5
... A34: PGA-TRN | C34: A-02017 | D34: KERTAS | E34: KERTAS UKURAN A5 | F34: NEOP SERTIFIKAT | G34: OPEX | J34: RUTIN | K34: JPI000 | L34: ALL | M34: ALL | N34: RIM | O34: IDR | P34: 35000 | Q34: 35000 | R34: 35000 | S34: 35000 | T34: 35000 | U34: 35000 | V34: 35000 | W34: 35000 | X34: 35000 | Y34: 35000 | Z34: 35000 | AA34: 35000 | AB34: 2.2153862 | AC34: 2.2153862 | AD34: 2.2153862 | AE34: 2.2153862 | AF34: 2.2153862 | AG34: 2.2153862 | AH34: 2.2153862 | AI34: 2.2153862 | AJ34: 2.2153862 | AK34: 2.2153862 | AL34: 2.2153862 | AM34: 2.2153862 | AN34: 0 | AO34: 1 | AP34: 0 | AQ34: 0 | AR34: 1 | AS34: 0 | AT34: 0 | AU34: 1 | AV34: 0 | AW34: 0 | AX34: 1 | AY34: 0 | AZ34: =SUM(AN34:AY34) -> 4 | BA34: =AZ34/12 -> 0.33333333 | BC34: 0 | BD34: 2.2153862 | BE34: 0 | BF34: 0 | BG34: 2.2153862 | BH34: 0 | BI34: 0 | BJ34: 2.2153862 | BK34: 0 | BL34: 0 | BM34: 2.2153862 | BN34: 0 | BO34: =SUM(BC34:BN34) -> 8.8615447 | BP34: =BO34/12 -> 0.73846206 | BS34: C | BT34: GA | BU34: 15 | BV34: 10 | BW34: 5 | BX34: 20 | BY34: 5
A35: PGA-TRN | C35: A-03898 | D35: BIAYA TRAINING | E35: FALSE | F35: BAHASA JEPANG CONVERSATION | G35: OPEX | J35: RUTIN | K35: JPI000 | L35: ALL | M35: ALL | N35: PAX | O35: IDR | P35: 19770000 | Q35: 19770000 | R35: 19770000 | S35: 19770000 | T35: 19770000 | U35: 19770000 | V35: 19770000 | W35: 19770000 | X35: 19770000 | Y35: 19770000 | Z35: 19770000 | AA35: 19770000 | AB35: 1251.3767 | AC35: 1251.3767 | AD35: 1251.3767 | AE35: 1251.3767 | AF35: 1251.3767 | AG35: 1251.3767 | AH35: 1251.3767 | AI35: 1251.3767 | AJ35: 1251.3767 | AK35: 1251.3767 | AL35: 1251.3767 | AM35: 1251.3767 | AN35: 0 | AO35: 1 | AP35: 0 | AQ35: 0 | AR35: 0 | AS35: 1 | AT35: 0 | AU35: 0 | AV35: 0 | AW35: 0 | AX35: 0 | AY35: 0 | AZ35: =SUM(AN35:AY35) -> 2 | BA35: =AZ35/12 -> 0.16666667 | BC35: 0 | BD35: 1251.3767 | BE35: 0 | BF35: 0 | BG35: 0 | BH35: 1251.3767 | BI35: 0 | BJ35: 0 | BK35: 0 | BL35: 0 | BM35: 0 | BN35: 0 | BO35: =SUM(BC35:BN35) -> 2502.7534 | BP35: =BO35/12 -> 208.56278 | BS35: A | BT35: GA | BU35: 15 | BV35: 10 | BW35: 5 | BX35: 20 | BY35: 5
A36: PGA-TRN | C36: A-03890 | D36: LAMPU | E36: LAMPU LED STRIP 12 VOLT | F36: NEOP SIMULASI PRAKTEK | G36: OPEX | J36: RUTIN | K36: JPI000 | L36: ALL | M36: ALL | N36: PCS | O36: IDR | P36: 45000 | Q36: 45000 | R36: 45000 | S36: 45000 | T36: 45000 | U36: 45000 | V36: 45000 | W36: 45000 | X36: 45000 | Y36: 45000 | Z36: 45000 | AA36: 45000 | AB36: 2.8483537 | AC36: 2.8483537 | AD36: 2.8483537 | AE36: 2.8483537 | AF36: 2.8483537 | AG36: 2.8483537 | AH36: 2.8483537 | AI36: 2.8483537 | AJ36: 2.8483537 | AK36: 2.8483537 | AL36: 2.8483537 | AM36: 2.8483537 | AN36: 1 | AO36: 0 | AP36: 0 | AQ36: 0 | AR36: 0 | AS36: 0 | AT36: 0 | AU36: 0 | AV36: 0 | AW36: 0 | AX36: 0 | AY36: 0 | AZ36: =SUM(AN36:AY36) -> 1 | BA36: =AZ36/12 -> 0.083333333 | BC36: 2.8483537 | BD36: 0 | BE36: 0 | BF36: 0 | BG36: 0 | BH36: 0 | BI36: 0 | BJ36: 0 | BK36: 0 | BL36: 0 | BM36: 0 | BN36: 0 | BO36: =SUM(BC36:BN36) -> 2.8483537 | BP36: =BO36/12 -> 0.2373628 | BS36: C | BT36: GA | BU36: 15 | BV36: 10 | BW36: 5 | BX36: 20 | BY36: 5
A37: PGA-TRN | C37: A-03951 | D37: PERJALANAN DINAS | E37: UANG MAKAN MALAM PD DALAM NEGERI (TRAVELLING & MEETING) GOL III | F37: KAIZEN FESTIVAL TMC | G37: OPEX | J37: RUTIN | K37: JPI000 | L37: ALL | M37: ALL | N37: DAY | O37: IDR | P37: 20000 | Q37: 20000 | R37: 20000 | S37: 20000 | T37: 20000 | U37: 20000 | V37: 20000 | W37: 20000 | X37: 20000 | Y37: 20000 | Z37: 20000 | AA37: 20000 | AB37: 1.265935 | AC37: 1.265935 | AD37: 1.265935 | AE37: 1.265935 | AF37: 1.265935 | AG37: 1.265935 | AH37: 1.265935 | AI37: 1.265935 | AJ37: 1.265935 | AK37: 1.265935 | AL37: 1.265935 | AM37: 1.265935 | AN37: 0 | AO37: 0 | AP37: 0 | AQ37: 0 | AR37: 3 | AS37: 0 | AT37: 0 | AU37: 0 | AV37: 0 | AW37: 0 | AX37: 0 | AY37: 0 | AZ37: =SUM(AN37:AY37) -> 3 | BA37: =AZ37/12 -> 0.25 | BC37: 0 | BD37: 0 | BE37: 0 | BF37: 0 | BG37: 3.7978049 | BH37: 0 | BI37: 0 | BJ37: 0 | BK37: 0 | BL37: 0 | BM37: 0 | BN37: 0 | BO37: =SUM(BC37:BN37) -> 3.7978049 | BP37: =BO37/12 -> 0.31648374 | BS37: D | BT37: GA | BU37: 0 | BV37: 10 | BW37: 0 | BX37: 0 | BY37: 5
A38: PGA-TRN | C38: A-03378 | D38: STAND TABLET | E38: STAND TABLET | F38: INCLASS TRAINING KELAS | G38: OPEX | J38: RUTIN | K38: JPI000 | L38: ALL | M38: ALL | N38: PCS | O38: IDR | P38: 920000 | Q38: 920000 | R38: 920000 | S38: 920000 | T38: 920000 | U38: 920000 | V38: 920000 | W38: 920000 | X38: 920000 | Y38: 920000 | Z38: 920000 | AA38: 920000 | AB38: 58.233008 | AC38: 58.233008 | AD38: 58.233008 | AE38: 58.233008 | AF38: 58.233008 | AG38: 58.233008 | AH38: 58.233008 | AI38: 58.233008 | AJ38: 58.233008 | AK38: 58.233008 | AL38: 58.233008 | AM38: 58.233008 | AN38: 0 | AO38: 20 | AP38: 0 | AQ38: 0 | AR38: 0 | AS38: 0 | AT38: 0 | AU38: 0 | AV38: 0 | AW38: 0 | AX38: 0 | AY38: 0 | AZ38: =SUM(AN38:AY38) -> 20 | BA38: =AZ38/12 -> 1.6666667 | BC38: 0 | BD38: 1164.6602 | BE38: 0 | BF38: 0 | BG38: 0 | BH38: 0 | BI38: 0 | BJ38: 0 | BK38: 0 | BL38: 0 | BM38: 0 | BN38: 0 | BO38: =SUM(BC38:BN38) -> 1164.6602 | BP38: =BO38/12 -> 97.055013 | BS38: C | BT38: GA | BU38: 15 | BV38: 10 | BW38: 5 | BX38: 20 | BY38: 5
A39: PGA-TRN | C39: A-00636 | D39: BATTERY | E39: BATTERY AA | F39: INCLASS MOUSE | G39: OPEX | J39: RUTIN | K39: JPI000 | L39: ALL | M39: ALL | N39: SET | O39: IDR | P39: 13694 | Q39: 13694 | R39: 13694 | S39: 13694 | T39: 13694 | U39: 13694 | V39: 13694 | W39: 13694 | X39: 13694 | Y39: 13694 | Z39: 13694 | AA39: 13694 | AB39: 0.86678566 | AC39: 0.86678566 | AD39: 0.86678566 | AE39: 0.86678566 | AF39: 0.86678566 | AG39: 0.86678566 | AH39: 0.86678566 | AI39: 0.86678566 | AJ39: 0.86678566 | AK39: 0.86678566 | AL39: 0.86678566 | AM39: 0.86678566 | AN39: 0 | AO39: 6 | AP39: 0 | AQ39: 0 | AR39: 0 | AS39: 0 | AT39: 6 | AU39: 0 | AV39: 0 | AW39: 0 | AX39: 0 | AY39: 0 | AZ39: =SUM(AN39:AY39) -> 12 | BA39: =AZ39/12 -> 1 | BC39: 0 | BD39: 5.200714 | BE39: 0 | BF39: 0 | BG39: 0 | BH39: 0 | BI39: 5.200714 | BJ39: 0 | BK39: 0 | BL39: 0 | BM39: 0 | BN39: 0 | BO39: =SUM(BC39:BN39) -> 10.401428 | BP39: =BO39/12 -> 0.86678566 | BS39: C | BT39: GA | BU39: 15 | BV39: 10 | BW39: 5 | BX39: 20 | BY39: 5
A40: PGA-TRN | C40: A-00736 | D40: STOPWATCH | E40: STOPWATCH ROX | F40: NEOP SIMULASI CT | G40: OPEX | J40: RUTIN | K40: JPI000 | L40: ALL | M40: ALL | N40: PCS | O40: IDR | P40: 448050 | Q40: 448050 | R40: 448050 | S40: 448050 | T40: 448050 | U40: 448050 | V40: 448050 | W40: 448050 | X40: 448050 | Y40: 448050 | Z40: 448050 | AA40: 448050 | AB40: 28.360108 | AC40: 28.360108 | AD40: 28.360108 | AE40: 28.360108 | AF40: 28.360108 | AG40: 28.360108 | AH40: 28.360108 | AI40: 28.360108 | AJ40: 28.360108 | AK40: 28.360108 | AL40: 28.360108 | AM40: 28.360108 | AN40: 0 | AO40: 10 | AP40: 0 | AQ40: 0 | AR40: 0 | AS40: 0 | AT40: 0 | AU40: 0 | AV40: 0 | AW40: 0 | AX40: 0 | AY40: 0 | AZ40: =SUM(AN40:AY40) -> 10 | BA40: =AZ40/12 -> 0.83333333 | BC40: 0 | BD40: 283.60108 | BE40: 0 | BF40: 0 | BG40: 0 | BH40: 0 | BI40: 0 | BJ40: 0 | BK40: 0 | BL40: 0 | BM40: 0 | BN40: 0 | BO40: =SUM(BC40:BN40) -> 283.60108 | BP40: =BO40/12 -> 23.633423 | BS40: C | BT40: GA | BU40: 15 | BV40: 10 | BW40: 5 | BX40: 20 | BY40: 5
A41: PGA-TRN | C41: A-01272 | D41: BIAYA PROSES VISA | E41: VISA JEPANG (TRAINING) | F41: NEXT GENERATION FM | G41: OPEX | J41: INSIDENTAL | K41: JPI000 | L41: ALL | M41: ALL | N41: PEOPLE | O41: IDR | P41: 0 | Q41: 0 | R41: 0 | S41: 0 | T41: 0 | U41: 0 | V41: 0 | W41: 0 | X41: 0 | Y41: 0 | Z41: 560000 | AA41: 560000 | AB41: 0 | AC41: 0 | AD41: 0 | AE41: 0 | AF41: 0 | AG41: 0 | AH41: 0 | AI41: 0 | AJ41: 0 | AK41: 0 | AL41: 35.446179 | AM41: 35.446179 | AN41: 0 | AO41: 0 | AP41: 0 | AQ41: 0 | AR41: 0 | AS41: 0 | AT41: 0 | AU41: 0 | AV41: 0 | AW41: 0 | AX41: 0 | AY41: 0 | AZ41: =SUM(AN41:AY41) -> 0 | BA41: =AZ41/12 -> 0 | BC41: 0 | BD41: 0 | BE41: 0 | BF41: 0 | BG41: 0 | BH41: 0 | BI41: 0 | BJ41: 0 | BK41: 0 | BL41: 0 | BM41: 0 | BN41: 0 | BO41: =SUM(BC41:BN41) -> 0 | BP41: =BO41/12 -> 0 | BS41: B | BT41: GA | BU41: 0 | BV41: 5 | BW41: 0 | BX41: 15 | BY41: 15
A42: PGA-TRN | C42: A-00725 | D42: SAPU | E42: SAPU | F42: MZ04 | G42: OPEX | J42: PROJECT HVPT | K42: MZ04 | L42: MAZDA J69 | M42: Mazda - Mazda-Japan | N42: PCS | O42: IDR | P42: 57500 | Q42: 57500 | R42: 57500 | S42: 57500 | T42: 57500 | U42: 57500 | V42: 57500 | W42: 57500 | X42: 57500 | Y42: 57500 | Z42: 57500 | AA42: 57500 | AB42: 3.639563 | AC42: 3.639563 | AD42: 3.639563 | AE42: 3.639563 | AF42: 3.639563 | AG42: 3.639563 | AH42: 3.639563 | AI42: 3.639563 | AJ42: 3.639563 | AK42: 3.639563 | AL42: 3.639563 | AM42: 3.639563 | AN42: 0 | AO42: 36 | AP42: 0 | AQ42: 0 | AR42: 0 | AS42: 0 | AT42: 0 | AU42: 0 | AV42: 0 | AW42: 0 | AX42: 0 | AY42: 0 | AZ42: =SUM(AN42:AY42) -> 36 | BA42: =AZ42/12 -> 3 | BC42: 0 | BD42: 131.02427 | BE42: 0 | BF42: 0 | BG42: 0 | BH42: 0 | BI42: 0 | BJ42: 0 | BK42: 0 | BL42: 0 | BM42: 0 | BN42: 0 | BO42: =SUM(BC42:BN42) -> 131.02427 | BP42: =BO42/12 -> 10.918689 | BS42: C | BT42: GA | BU42: 15 | BV42: 10 | BW42: 5 | BX42: 20 | BY42: 5
A43: PGA-TRN | C43: A-00727 | D43: SEROKAN | E43: SEROKAN | F43: MZ04 | G43: OPEX | J43: PROJECT HVPT | K43: MZ04 | L43: MAZDA J69 | M43: Mazda - Mazda-Japan | N43: PCS | O43: IDR | P43: 7500 | Q43: 7500 | R43: 7500 | S43: 7500 | T43: 7500 | U43: 7500 | V43: 7500 | W43: 7500 | X43: 7500 | Y43: 7500 | Z43: 7500 | AA43: 7500 | AB43: 0.47472561 | AC43: 0.47472561 | AD43: 0.47472561 | AE43: 0.47472561 | AF43: 0.47472561 | AG43: 0.47472561 | AH43: 0.47472561 | AI43: 0.47472561 | AJ43: 0.47472561 | AK43: 0.47472561 | AL43: 0.47472561 | AM43: 0.47472561 | AN43: 0 | AO43: 6 | AP43: 0 | AQ43: 0 | AR43: 0 | AS43: 0 | AT43: 0 | AU43: 0 | AV43: 0 | AW43: 0 | AX43: 0 | AY43: 0 | AZ43: =SUM(AN43:AY43) -> 6 | BA43: =AZ43/12 -> 0.5 | BC43: 0 | BD43: 2.8483537 | BE43: 0 | BF43: 0 | BG43: 0 | BH43: 0 | BI43: 0 | BJ43: 0 | BK43: 0 | BL43: 0 | BM43: 0 | BN43: 0 | BO43: =SUM(BC43:BN43) -> 2.8483537 | BP43: =BO43/12 -> 0.2373628 | BS43: C | BT43: GA | BU43: 15 | BV43: 10 | BW43: 5 | BX43: 20 | BY43: 5
A44: PGA-TRN | C44: A-02960 | D44: VACUM CLEANER | E44: VACUM CLEANER MAYAKA | F44: PA MAZDA J69 | G44: OPEX | J44: PROJECT HVPT | K44: MJFPA | L44: MAZDA6, CX-3 | M44: Mazda - Mazda-Japan, Mazda - AAT: Auto Alliance Thailand (Mazda) | N44: UNIT | O44: IDR | P44: 1210000 | Q44: 1210000 | R44: 1210000 | S44: 1210000 | T44: 1210000 | U44: 1210000 | V44: 1210000 | W44: 1210000 | X44: 1210000 | Y44: 1210000 | Z44: 1210000 | AA44: 1210000 | AB44: 76.589065 | AC44: 76.589065 | AD44: 76.589065 | AE44: 76.589065 | AF44: 76.589065 | AG44: 76.589065 | AH44: 76.589065 | AI44: 76.589065 | AJ44: 76.589065 | AK44: 76.589065 | AL44: 76.589065 | AM44: 76.589065 | AN44: 0 | AO44: 1 | AP44: 0 | AQ44: 0 | AR44: 0 | AS44: 0 | AT44: 0 | AU44: 0 | AV44: 0 | AW44: 0 | AX44: 0 | AY44: 0 | AZ44: =SUM(AN44:AY44) -> 1 | BA44: =AZ44/12 -> 0.083333333 | BC44: 0 | BD44: 76.589065 | BE44: 0 | BF44: 0 | BG44: 0 | BH44: 0 | BI44: 0 | BJ44: 0 | BK44: 0 | BL44: 0 | BM44: 0 | BN44: 0 | BO44: =SUM(BC44:BN44) -> 76.589065 | BP44: =BO44/12 -> 6.3824221 | BS44: C | BT44: GA | BU44: 15 | BV44: 10 | BW44: 5 | BX44: 20 | BY44: 5
A45: PGA-TRN | C45: A-01312 | D45: HANDMOP | E45: HANDMOP | F45: MZ03 | G45: OPEX | J45: PROJECT HVPT | K45: MZ03 | L45: MAZDA J69 | M45: Mazda - Mazda-Japan | N45: PCS | O45: IDR | P45: 23063 | Q45: 23063 | R45: 23063 | S45: 23063 | T45: 23063 | U45: 23063 | V45: 23063 | W45: 23063 | X45: 23063 | Y45: 23063 | Z45: 23063 | AA45: 23063 | AB45: 1.4598129 | AC45: 1.4598129 | AD45: 1.4598129 | AE45: 1.4598129 | AF45: 1.4598129 | AG45: 1.4598129 | AH45: 1.4598129 | AI45: 1.4598129 | AJ45: 1.4598129 | AK45: 1.4598129 | AL45: 1.4598129 | AM45: 1.4598129 | AN45: 0 | AO45: 2 | AP45: 0 | AQ45: 0 | AR45: 0 | AS45: 0 | AT45: 0 | AU45: 0 | AV45: 0 | AW45: 0 | AX45: 0 | AY45: 0 | AZ45: =SUM(AN45:AY45) -> 2 | BA45: =AZ45/12 -> 0.16666667 | BC45: 0 | BD45: 2.9196258 | BE45: 0 | BF45: 0 | BG45: 0 | BH45: 0 | BI45: 0 | BJ45: 0 | BK45: 0 | BL45: 0 | BM45: 0 | BN45: 0 | BO45: =SUM(BC45:BN45) -> 2.9196258 | BP45: =BO45/12 -> 0.24330215 | BS45: C | BT45: GA | BU45: 15 | BV45: 10 | BW45: 5 | BX45: 20 | BY45: 5
A46: PGA-TRN | C46: A-01312 | D46: HANDMOP | E46: HANDMOP | F46: MZ04 | G46: OPEX | J46: PROJECT HVPT | K46: MZ04 | L46: MAZDA J69 | M46: Mazda - Mazda-Japan | N46: PCS | O46: IDR | P46: 23063 | Q46: 23063 | R46: 23063 | S46: 23063 | T46: 23063 | U46: 23063 | V46: 23063 | W46: 23063 | X46: 23063 | Y46: 23063 | Z46: 23063 | AA46: 23063 | AB46: 1.4598129 | AC46: 1.4598129 | AD46: 1.4598129 | AE46: 1.4598129 | AF46: 1.4598129 | AG46: 1.4598129 | AH46: 1.4598129 | AI46: 1.4598129 | AJ46: 1.4598129 | AK46: 1.4598129 | AL46: 1.4598129 | AM46: 1.4598129 | AN46: 0 | AO46: 2 | AP46: 0 | AQ46: 0 | AR46: 0 | AS46: 0 | AT46: 0 | AU46: 0 | AV46: 0 | AW46: 0 | AX46: 0 | AY46: 0 | AZ46: =SUM(AN46:AY46) -> 2 | BA46: =AZ46/12 -> 0.16666667 | BC46: 0 | BD46: 2.9196258 | BE46: 0 | BF46: 0 | BG46: 0 | BH46: 0 | BI46: 0 | BJ46: 0 | BK46: 0 | BL46: 0 | BM46: 0 | BN46: 0 | BO46: =SUM(BC46:BN46) -> 2.9196258 | BP46: =BO46/12 -> 0.24330215 | BS46: C | BT46: GA | BU46: 15 | BV46: 10 | BW46: 5 | BX46: 20 | BY46: 5
A47: PGA-TRN | C47: A-02960 | D47: VACUM CLEANER | E47: VACUM CLEANER MAYAKA | F47: MZ03 | G47: OPEX | J47: PROJECT HVPT | K47: MZ03 | L47: MAZDA J69 | M47: Mazda - Mazda-Japan | N47: UNIT | O47: IDR | P47: 1210000 | Q47: 1210000 | R47: 1210000 | S47: 1210000 | T47: 1210000 | U47: 1210000 | V47: 1210000 | W47: 1210000 | X47: 1210000 | Y47: 1210000 | Z47: 1210000 | AA47: 1210000 | AB47: 76.589065 | AC47: 76.589065 | AD47: 76.589065 | AE47: 76.589065 | AF47: 76.589065 | AG47: 76.589065 | AH47: 76.589065 | AI47: 76.589065 | AJ47: 76.589065 | AK47: 76.589065 | AL47: 76.589065 | AM47: 76.589065 | AN47: 0 | AO47: 1 | AP47: 0 | AQ47: 0 | AR47: 0 | AS47: 0 | AT47: 0 | AU47: 0 | AV47: 0 | AW47: 0 | AX47: 0 | AY47: 0 | AZ47: =SUM(AN47:AY47) -> 1 | BA47: =AZ47/12 -> 0.083333333 | BC47: 0 | BD47: 76.589065 | BE47: 0 | BF47: 0 | BG47: 0 | BH47: 0 | BI47: 0 | BJ47: 0 | BK47: 0 | BL47: 0 | BM47: 0 | BN47: 0 | BO47: =SUM(BC47:BN47) -> 76.589065 | BP47: =BO47/12 -> 6.3824221 | BS47: C | BT47: GA | BU47: 15 | BV47: 10 | BW47: 5 | BX47: 20 | BY47: 5
... A56: PGA-TRN | C56: A-00727 | D56: SEROKAN | E56: SEROKAN | F56: MZ03 | G56: OPEX | J56: PROJECT HVPT | K56: MZ03 | L56: MAZDA J69 | M56: Mazda - Mazda-Japan | N56: PCS | O56: IDR | P56: 7500 | Q56: 7500 | R56: 7500 | S56: 7500 | T56: 7500 | U56: 7500 | V56: 7500 | W56: 7500 | X56: 7500 | Y56: 7500 | Z56: 7500 | AA56: 7500 | AB56: 0.47472561 | AC56: 0.47472561 | AD56: 0.47472561 | AE56: 0.47472561 | AF56: 0.47472561 | AG56: 0.47472561 | AH56: 0.47472561 | AI56: 0.47472561 | AJ56: 0.47472561 | AK56: 0.47472561 | AL56: 0.47472561 | AM56: 0.47472561 | AN56: 0 | AO56: 6 | AP56: 0 | AQ56: 0 | AR56: 0 | AS56: 0 | AT56: 0 | AU56: 0 | AV56: 0 | AW56: 0 | AX56: 0 | AY56: 0 | AZ56: =SUM(AN56:AY56) -> 6 | BA56: =AZ56/12 -> 0.5 | BC56: 0 | BD56: 2.8483537 | BE56: 0 | BF56: 0 | BG56: 0 | BH56: 0 | BI56: 0 | BJ56: 0 | BK56: 0 | BL56: 0 | BM56: 0 | BN56: 0 | BO56: =SUM(BC56:BN56) -> 2.8483537 | BP56: =BO56/12 -> 0.2373628 | BS56: C | BT56: GA | BU56: 15 | BV56: 10 | BW56: 5 | BX56: 20 | BY56: 5

Sheet SUMMARY
E7: STP QTY | F7: STP QTY | G7: STP QTY | H7: STP QTY | I7: STP QTY | J7: STP QTY | K7: STP QTY | L7: STP QTY | M7: STP QTY | N7: STP QTY | O7: STP QTY | P7: STP QTY | Q7: STP AMT | R7: STP AMT | S7: STP AMT | T7: STP AMT | U7: STP AMT | V7: STP AMT | W7: STP AMT | X7: STP AMT | Y7: STP AMT | Z7: STP AMT | AA7: STP AMT | AB7: STP AMT | AC7: TERM 85 | AF7: TERM 84
A8: CATEGORY | B8: ACC NO | C8: ACC DESCRIPTION | D8: PART NAME | E8: Jul-25 | F8: Aug-25 | G8: Sep-25 | H8: Oct-25 | I8: Nov-25 | J8: Dec-25 | K8: Jan-26 | L8: Feb-26 | M8: Mar-26 | N8: Apr-26 | O8: May-26 | P8: Jun-26 | Q8: Jul-25 | R8: Aug-25 | S8: Sep-25 | T8: Oct-25 | U8: Nov-25 | V8: Dec-25 | W8: Jan-26 | X8: Feb-26 | Y8: Mar-26 | Z8: Apr-26 | AA8: May-26 | AB8: Jun-26 | AC8: TOTAL QTY | AD8: TOTAL AMT | AF8: TOTAL QTY | AG8: TOTAL AMT | AH8: PERCENTAGE QTY | AI8: PERCENTAGE AMT | AJ8: REMARKS
A9: RUTIN | D9: BATTERY | E9: =SUMIFS('PLAN BUDGET SAMI-JF'!AN13:AN100000,'PLAN BUDGET SAMI-JF'!D13:D100000,SUMMARY!D9,'PLAN BUDGET SAMI-JF'!J13:J100000,SUMMARY!A9&"*") -> 0 | F9: =SUMIFS('PLAN BUDGET SAMI-JF'!AO13:AO100000,'PLAN BUDGET SAMI-JF'!D13:D100000,SUMMARY!D9,'PLAN BUDGET SAMI-JF'!J13:J100000,SUMMARY!A9&"*") -> 34 | G9: =SUMIFS('PLAN BUDGET SAMI-JF'!AP13:AP100000,'PLAN BUDGET SAMI-JF'!D13:D100000,SUMMARY!D9,'PLAN BUDGET SAMI-JF'!J13:J100000,SUMMARY!A9&"*") -> 0 | H9: =SUMIFS('PLAN BUDGET SAMI-JF'!AQ13:AQ100000,'PLAN BUDGET SAMI-JF'!D13:D100000,SUMMARY!D9,'PLAN BUDGET SAMI-JF'!J13:J100000,SUMMARY!A9&"*") -> 0 | I9: =SUMIFS('PLAN BUDGET SAMI-JF'!AR13:AR100000,'PLAN BUDGET SAMI-JF'!D13:D100000,SUMMARY!D9,'PLAN BUDGET SAMI-JF'!J13:J100000,SUMMARY!A9&"*") -> 0 | J9: =SUMIFS('PLAN BUDGET SAMI-JF'!AS13:AS100000,'PLAN BUDGET SAMI-JF'!D13:D100000,SUMMARY!D9,'PLAN BUDGET SAMI-JF'!J13:J100000,SUMMARY!A9&"*") -> 0 | K9: =SUMIFS('PLAN BUDGET SAMI-JF'!AT13:AT100000,'PLAN BUDGET SAMI-JF'!D13:D100000,SUMMARY!D9,'PLAN BUDGET SAMI-JF'!J13:J100000,SUMMARY!A9&"*") -> 34 | L9: =SUMIFS('PLAN BUDGET SAMI-JF'!AU13:AU100000,'PLAN BUDGET SAMI-JF'!D13:D100000,SUMMARY!D9,'PLAN BUDGET SAMI-JF'!J13:J100000,SUMMARY!A9&"*") -> 0 | M9: =SUMIFS('PLAN BUDGET SAMI-JF'!AV13:AV100000,'PLAN BUDGET SAMI-JF'!D13:D100000,SUMMARY!D9,'PLAN BUDGET SAMI-JF'!J13:J100000,SUMMARY!A9&"*") -> 0 | N9: =SUMIFS('PLAN BUDGET SAMI-JF'!AW13:AW100000,'PLAN BUDGET SAMI-JF'!D13:D100000,SUMMARY!D9,'PLAN BUDGET SAMI-JF'!J13:J100000,SUMMARY!A9&"*") -> 0 | O9: =SUMIFS('PLAN BUDGET SAMI-JF'!AX13:AX100000,'PLAN BUDGET SAMI-JF'!D13:D100000,SUMMARY!D9,'PLAN BUDGET SAMI-JF'!J13:J100000,SUMMARY!A9&"*") -> 0 | P9: =SUMIFS('PLAN BUDGET SAMI-JF'!AY13:AY100000,'PLAN BUDGET SAMI-JF'!D13:D100000,SUMMARY!D9,'PLAN BUDGET SAMI-JF'!J13:J100000,SUMMARY!A9&"*") -> 0 | Q9: =SUMIFS('PLAN BUDGET SAMI-JF'!BC13:BC100000,'PLAN BUDGET SAMI-JF'!D13:D100000,SUMMARY!D9,'PLAN BUDGET SAMI-JF'!J13:J100000,SUMMARY!A9&"*") -> 0 | R9: =SUMIFS('PLAN BUDGET SAMI-JF'!BD13:BD100000,'PLAN BUDGET SAMI-JF'!D13:D100000,SUMMARY!D9,'PLAN BUDGET SAMI-JF'!J13:J100000,SUMMARY!A9&"*") -> 18.464674 | S9: =SUMIFS('PLAN BUDGET SAMI-JF'!BE13:BE100000,'PLAN BUDGET SAMI-JF'!D13:D100000,SUMMARY!D9,'PLAN BUDGET SAMI-JF'!J13:J100000,SUMMARY!A9&"*") -> 0 | T9: =SUMIFS('PLAN BUDGET SAMI-JF'!BF13:BF100000,'PLAN BUDGET SAMI-JF'!D13:D100000,SUMMARY!D9,'PLAN BUDGET SAMI-JF'!J13:J100000,SUMMARY!A9&"*") -> 0 | U9: =SUMIFS('PLAN BUDGET SAMI-JF'!BG13:BG100000,'PLAN BUDGET SAMI-JF'!D13:D100000,SUMMARY!D9,'PLAN BUDGET SAMI-JF'!J13:J100000,SUMMARY!A9&"*") -> 0 | V9: =SUMIFS('PLAN BUDGET SAMI-JF'!BH13:BH100000,'PLAN BUDGET SAMI-JF'!D13:D100000,SUMMARY!D9,'PLAN BUDGET SAMI-JF'!J13:J100000,SUMMARY!A9&"*") -> 0 | W9: =SUMIFS('PLAN BUDGET SAMI-JF'!BI13:BI100000,'PLAN BUDGET SAMI-JF'!D13:D100000,SUMMARY!D9,'PLAN BUDGET SAMI-JF'!J13:J100000,SUMMARY!A9&"*") -> 18.464674 | X9: =SUMIFS('PLAN BUDGET SAMI-JF'!BJ13:BJ100000,'PLAN BUDGET SAMI-JF'!D13:D100000,SUMMARY!D9,'PLAN BUDGET SAMI-JF'!J13:J100000,SUMMARY!A9&"*") -> 0 | Y9: =SUMIFS('PLAN BUDGET SAMI-JF'!BK13:BK100000,'PLAN BUDGET SAMI-JF'!D13:D100000,SUMMARY!D9,'PLAN BUDGET SAMI-JF'!J13:J100000,SUMMARY!A9&"*") -> 0 | Z9: =SUMIFS('PLAN BUDGET SAMI-JF'!BL13:BL100000,'PLAN BUDGET SAMI-JF'!D13:D100000,SUMMARY!D9,'PLAN BUDGET SAMI-JF'!J13:J100000,SUMMARY!A9&"*") -> 0 | AA9: =SUMIFS('PLAN BUDGET SAMI-JF'!BM13:BM100000,'PLAN BUDGET SAMI-JF'!D13:D100000,SUMMARY!D9,'PLAN BUDGET SAMI-JF'!J13:J100000,SUMMARY!A9&"*") -> 0 | AB9: =SUMIFS('PLAN BUDGET SAMI-JF'!BN13:BN100000,'PLAN BUDGET SAMI-JF'!D13:D100000,SUMMARY!D9,'PLAN BUDGET SAMI-JF'!J13:J100000,SUMMARY!A9&"*") -> 0 | AC9: =SUM(E9:P9) -> 68 | AD9: =SUM(Q9:AB9) -> 36.929348 | AF9: 59 | AG9: 29.829352 | AH9: =IFERROR((AC9-AF9)/AF9,1) -> 0.15254237 | AI9: =IFERROR((AD9-AG9)/AG9,1) -> 0.23802046 | AJ9: ada kenaikan penggunaan (di pinjam) section lain
A10: RUTIN | D10: POINTER | E10: =SUMIFS('PLAN BUDGET SAMI-JF'!AN13:AN100000,'PLAN BUDGET SAMI-JF'!D13:D100000,SUMMARY!D10,'PLAN BUDGET SAMI-JF'!J13:J100000,SUMMARY!A10&"*") -> 0 | F10: =SUMIFS('PLAN BUDGET SAMI-JF'!AO13:AO100000,'PLAN BUDGET SAMI-JF'!D13:D100000,SUMMARY!D10,'PLAN BUDGET SAMI-JF'!J13:J100000,SUMMARY!A10&"*") -> 0 | G10: =SUMIFS('PLAN BUDGET SAMI-JF'!AP13:AP100000,'PLAN BUDGET SAMI-JF'!D13:D100000,SUMMARY!D10,'PLAN BUDGET SAMI-JF'!J13:J100000,SUMMARY!A10&"*") -> 2 | H10: =SUMIFS('PLAN BUDGET SAMI-JF'!AQ13:AQ100000,'PLAN BUDGET SAMI-JF'!D13:D100000,SUMMARY!D10,'PLAN BUDGET SAMI-JF'!J13:J100000,SUMMARY!A10&"*") -> 0 | I10: =SUMIFS('PLAN BUDGET SAMI-JF'!AR13:AR100000,'PLAN BUDGET SAMI-JF'!D13:D100000,SUMMARY!D10,'PLAN BUDGET SAMI-JF'!J13:J100000,SUMMARY!A10&"*") -> 0 | J10: =SUMIFS('PLAN BUDGET SAMI-JF'!AS13:AS100000,'PLAN BUDGET SAMI-JF'!D13:D100000,SUMMARY!D10,'PLAN BUDGET SAMI-JF'!J13:J100000,SUMMARY!A10&"*") -> 0 | K10: =SUMIFS('PLAN BUDGET SAMI-JF'!AT13:AT100000,'PLAN BUDGET SAMI-JF'!D13:D100000,SUMMARY!D10,'PLAN BUDGET SAMI-JF'!J13:J100000,SUMMARY!A10&"*") -> 0 | L10: =SUMIFS('PLAN BUDGET SAMI-JF'!AU13:AU100000,'PLAN BUDGET SAMI-JF'!D13:D100000,SUMMARY!D10,'PLAN BUDGET SAMI-JF'!J13:J100000,SUMMARY!A10&"*") -> 0 | M10: =SUMIFS('PLAN BUDGET SAMI-JF'!AV13:AV100000,'PLAN BUDGET SAMI-JF'!D13:D100000,SUMMARY!D10,'PLAN BUDGET SAMI-JF'!J13:J100000,SUMMARY!A10&"*") -> 0 | N10: =SUMIFS('PLAN BUDGET SAMI-JF'!AW13:AW100000,'PLAN BUDGET SAMI-JF'!D13:D100000,SUMMARY!D10,'PLAN BUDGET SAMI-JF'!J13:J100000,SUMMARY!A10&"*") -> 0 | O10: =SUMIFS('PLAN BUDGET SAMI-JF'!AX13:AX100000,'PLAN BUDGET SAMI-JF'!D13:D100000,SUMMARY!D10,'PLAN BUDGET SAMI-JF'!J13:J100000,SUMMARY!A10&"*") -> 0 | P10: =SUMIFS('PLAN BUDGET SAMI-JF'!AY13:AY100000,'PLAN BUDGET SAMI-JF'!D13:D100000,SUMMARY!D10,'PLAN BUDGET SAMI-JF'!J13:J100000,SUMMARY!A10&"*") -> 0 | Q10: =SUMIFS('PLAN BUDGET SAMI-JF'!BC13:BC100000,'PLAN BUDGET SAMI-JF'!D13:D100000,SUMMARY!D10,'PLAN BUDGET SAMI-JF'!J13:J100000,SUMMARY!A10&"*") -> 0 | R10: =SUMIFS('PLAN BUDGET SAMI-JF'!BD13:BD100000,'PLAN BUDGET SAMI-JF'!D13:D100000,SUMMARY!D10,'PLAN BUDGET SAMI-JF'!J13:J100000,SUMMARY!A10&"*") -> 0 | S10: =SUMIFS('PLAN BUDGET SAMI-JF'!BE13:BE100000,'PLAN BUDGET SAMI-JF'!D13:D100000,SUMMARY!D10,'PLAN BUDGET SAMI-JF'!J13:J100000,SUMMARY!A10&"*") -> 59.979998 | T10: =SUMIFS('PLAN BUDGET SAMI-JF'!BF13:BF100000,'PLAN BUDGET SAMI-JF'!D13:D100000,SUMMARY!D10,'PLAN BUDGET SAMI-JF'!J13:J100000,SUMMARY!A10&"*") -> 0 | U10: =SUMIFS('PLAN BUDGET SAMI-JF'!BG13:BG100000,'PLAN BUDGET SAMI-JF'!D13:D100000,SUMMARY!D10,'PLAN BUDGET SAMI-JF'!J13:J100000,SUMMARY!A10&"*") -> 0 | V10: =SUMIFS('PLAN BUDGET SAMI-JF'!BH13:BH100000,'PLAN BUDGET SAMI-JF'!D13:D100000,SUMMARY!D10,'PLAN BUDGET SAMI-JF'!J13:J100000,SUMMARY!A10&"*") -> 0 | W10: =SUMIFS('PLAN BUDGET SAMI-JF'!BI13:BI100000,'PLAN BUDGET SAMI-JF'!D13:D100000,SUMMARY!D10,'PLAN BUDGET SAMI-JF'!J13:J100000,SUMMARY!A10&"*") -> 0 | X10: =SUMIFS('PLAN BUDGET SAMI-JF'!BJ13:BJ100000,'PLAN BUDGET SAMI-JF'!D13:D100000,SUMMARY!D10,'PLAN BUDGET SAMI-JF'!J13:J100000,SUMMARY!A10&"*") -> 0 | Y10: =SUMIFS('PLAN BUDGET SAMI-JF'!BK13:BK100000,'PLAN BUDGET SAMI-JF'!D13:D100000,SUMMARY!D10,'PLAN BUDGET SAMI-JF'!J13:J100000,SUMMARY!A10&"*") -> 0 | Z10: =SUMIFS('PLAN BUDGET SAMI-JF'!BL13:BL100000,'PLAN BUDGET SAMI-JF'!D13:D100000,SUMMARY!D10,'PLAN BUDGET SAMI-JF'!J13:J100000,SUMMARY!A10&"*") -> 0 | AA10: =SUMIFS('PLAN BUDGET SAMI-JF'!BM13:BM100000,'PLAN BUDGET SAMI-JF'!D13:D100000,SUMMARY!D10,'PLAN BUDGET SAMI-JF'!J13:J100000,SUMMARY!A10&"*") -> 0 | AB10: =SUMIFS('PLAN BUDGET SAMI-JF'!BN13:BN100000,'PLAN BUDGET SAMI-JF'!D13:D100000,SUMMARY!D10,'PLAN BUDGET SAMI-JF'!J13:J100000,SUMMARY!A10&"*") -> 0 | AC10: =SUM(E10:P10) -> 2 | AD10: =SUM(Q10:AB10) -> 59.979998 | AF10: 2 | AG10: 58.233008 | AH10: =IFERROR((AC10-AF10)/AF10,1) -> 0 | AI10: =IFERROR((AD10-AG10)/AG10,1) -> 0.03 | AJ10: kenaikan harga dari Vendor
A11: RUTIN | D11: PERJALANAN DINAS | E11: =SUMIFS('PLAN BUDGET SAMI-JF'!AN13:AN100000,'PLAN BUDGET SAMI-JF'!D13:D100000,SUMMARY!D11,'PLAN BUDGET SAMI-JF'!J13:J100000,SUMMARY!A11&"*") -> 0 | F11: =SUMIFS('PLAN BUDGET SAMI-JF'!AO13:AO100000,'PLAN BUDGET SAMI-JF'!D13:D100000,SUMMARY!D11,'PLAN BUDGET SAMI-JF'!J13:J100000,SUMMARY!A11&"*") -> 0 | G11: =SUMIFS('PLAN BUDGET SAMI-JF'!AP13:AP100000,'PLAN BUDGET SAMI-JF'!D13:D100000,SUMMARY!D11,'PLAN BUDGET SAMI-JF'!J13:J100000,SUMMARY!A11&"*") -> 0 | H11: =SUMIFS('PLAN BUDGET SAMI-JF'!AQ13:AQ100000,'PLAN BUDGET SAMI-JF'!D13:D100000,SUMMARY!D11,'PLAN BUDGET SAMI-JF'!J13:J100000,SUMMARY!A11&"*") -> 0 | I11: =SUMIFS('PLAN BUDGET SAMI-JF'!AR13:AR100000,'PLAN BUDGET SAMI-JF'!D13:D100000,SUMMARY!D11,'PLAN BUDGET SAMI-JF'!J13:J100000,SUMMARY!A11&"*") -> 24 | J11: =SUMIFS('PLAN BUDGET SAMI-JF'!AS13:AS100000,'PLAN BUDGET SAMI-JF'!D13:D100000,SUMMARY!D11,'PLAN BUDGET SAMI-JF'!J13:J100000,SUMMARY!A11&"*") -> 0 | K11: =SUMIFS('PLAN BUDGET SAMI-JF'!AT13:AT100000,'PLAN BUDGET SAMI-JF'!D13:D100000,SUMMARY!D11,'PLAN BUDGET SAMI-JF'!J13:J100000,SUMMARY!A11&"*") -> 0 | L11: =SUMIFS('PLAN BUDGET SAMI-JF'!AU13:AU100000,'PLAN BUDGET SAMI-JF'!D13:D100000,SUMMARY!D11,'PLAN BUDGET SAMI-JF'!J13:J100000,SUMMARY!A11&"*") -> 0 | M11: =SUMIFS('PLAN BUDGET SAMI-JF'!AV13:AV100000,'PLAN BUDGET SAMI-JF'!D13:D100000,SUMMARY!D11,'PLAN BUDGET SAMI-JF'!J13:J100000,SUMMARY!A11&"*") -> 0 | N11: =SUMIFS('PLAN BUDGET SAMI-JF'!AW13:AW100000,'PLAN BUDGET SAMI-JF'!D13:D100000,SUMMARY!D11,'PLAN BUDGET SAMI-JF'!J13:J100000,SUMMARY!A11&"*") -> 0 | O11: =SUMIFS('PLAN BUDGET SAMI-JF'!AX13:AX100000,'PLAN BUDGET SAMI-JF'!D13:D100000,SUMMARY!D11,'PLAN BUDGET SAMI-JF'!J13:J100000,SUMMARY!A11&"*") -> 0 | P11: =SUMIFS('PLAN BUDGET SAMI-JF'!AY13:AY100000,'PLAN BUDGET SAMI-JF'!D13:D100000,SUMMARY!D11,'PLAN BUDGET SAMI-JF'!J13:J100000,SUMMARY!A11&"*") -> 0 | Q11: =SUMIFS('PLAN BUDGET SAMI-JF'!BC13:BC100000,'PLAN BUDGET SAMI-JF'!D13:D100000,SUMMARY!D11,'PLAN BUDGET SAMI-JF'!J13:J100000,SUMMARY!A11&"*") -> 0 | R11: =SUMIFS('PLAN BUDGET SAMI-JF'!BD13:BD100000,'PLAN BUDGET SAMI-JF'!D13:D100000,SUMMARY!D11,'PLAN BUDGET SAMI-JF'!J13:J100000,SUMMARY!A11&"*") -> 0 | S11: =SUMIFS('PLAN BUDGET SAMI-JF'!BE13:BE100000,'PLAN BUDGET SAMI-JF'!D13:D100000,SUMMARY!D11,'PLAN BUDGET SAMI-JF'!J13:J100000,SUMMARY!A11&"*") -> 0 | T11: =SUMIFS('PLAN BUDGET SAMI-JF'!BF13:BF100000,'PLAN BUDGET SAMI-JF'!D13:D100000,SUMMARY!D11,'PLAN BUDGET SAMI-JF'!J13:J100000,SUMMARY!A11&"*") -> 0 | U11: =SUMIFS('PLAN BUDGET SAMI-JF'!BG13:BG100000,'PLAN BUDGET SAMI-JF'!D13:D100000,SUMMARY!D11,'PLAN BUDGET SAMI-JF'!J13:J100000,SUMMARY!A11&"*") -> 529.16081 | V11: =SUMIFS('PLAN BUDGET SAMI-JF'!BH13:BH100000,'PLAN BUDGET SAMI-JF'!D13:D100000,SUMMARY!D11,'PLAN BUDGET SAMI-JF'!J13:J100000,SUMMARY!A11&"*") -> 0 | W11: =SUMIFS('PLAN BUDGET SAMI-JF'!BI13:BI100000,'PLAN BUDGET SAMI-JF'!D13:D100000,SUMMARY!D11,'PLAN BUDGET SAMI-JF'!J13:J100000,SUMMARY!A11&"*") -> 0 | X11: =SUMIFS('PLAN BUDGET SAMI-JF'!BJ13:BJ100000,'PLAN BUDGET SAMI-JF'!D13:D100000,SUMMARY!D11,'PLAN BUDGET SAMI-JF'!J13:J100000,SUMMARY!A11&"*") -> 0 | Y11: =SUMIFS('PLAN BUDGET SAMI-JF'!BK13:BK100000,'PLAN BUDGET SAMI-JF'!D13:D100000,SUMMARY!D11,'PLAN BUDGET SAMI-JF'!J13:J100000,SUMMARY!A11&"*") -> 0 | Z11: =SUMIFS('PLAN BUDGET SAMI-JF'!BL13:BL100000,'PLAN BUDGET SAMI-JF'!D13:D100000,SUMMARY!D11,'PLAN BUDGET SAMI-JF'!J13:J100000,SUMMARY!A11&"*") -> 0 | AA11: =SUMIFS('PLAN BUDGET SAMI-JF'!BM13:BM100000,'PLAN BUDGET SAMI-JF'!D13:D100000,SUMMARY!D11,'PLAN BUDGET SAMI-JF'!J13:J100000,SUMMARY!A11&"*") -> 0 | AB11: =SUMIFS('PLAN BUDGET SAMI-JF'!BN13:BN100000,'PLAN BUDGET SAMI-JF'!D13:D100000,SUMMARY!D11,'PLAN BUDGET SAMI-JF'!J13:J100000,SUMMARY!A11&"*") -> 0 | AC11: =SUM(E11:P11) -> 24 | AD11: =SUM(Q11:AB11) -> 529.16081 | AF11: 0 | AG11: 0 | AH11: =IFERROR((AC11-AF11)/AF11,1) -> 1 | AI11: =IFERROR((AD11-AG11)/AG11,1) -> 1 | AJ11: Budget di Term 84 tidak ada, sedangkan di Term 85 ada.
A12: RUTIN | D12: SENAR | E12: =SUMIFS('PLAN BUDGET SAMI-JF'!AN13:AN100000,'PLAN BUDGET SAMI-JF'!D13:D100000,SUMMARY!D12,'PLAN BUDGET SAMI-JF'!J13:J100000,SUMMARY!A12&"*") -> 1 | F12: =SUMIFS('PLAN BUDGET SAMI-JF'!AO13:AO100000,'PLAN BUDGET SAMI-JF'!D13:D100000,SUMMARY!D12,'PLAN BUDGET SAMI-JF'!J13:J100000,SUMMARY!A12&"*") -> 0 | G12: =SUMIFS('PLAN BUDGET SAMI-JF'!AP13:AP100000,'PLAN BUDGET SAMI-JF'!D13:D100000,SUMMARY!D12,'PLAN BUDGET SAMI-JF'!J13:J100000,SUMMARY!A12&"*") -> 0 | H12: =SUMIFS('PLAN BUDGET SAMI-JF'!AQ13:AQ100000,'PLAN BUDGET SAMI-JF'!D13:D100000,SUMMARY!D12,'PLAN BUDGET SAMI-JF'!J13:J100000,SUMMARY!A12&"*") -> 0 | I12: =SUMIFS('PLAN BUDGET SAMI-JF'!AR13:AR100000,'PLAN BUDGET SAMI-JF'!D13:D100000,SUMMARY!D12,'PLAN BUDGET SAMI-JF'!J13:J100000,SUMMARY!A12&"*") -> 0 | J12: =SUMIFS('PLAN BUDGET SAMI-JF'!AS13:AS100000,'PLAN BUDGET SAMI-JF'!D13:D100000,SUMMARY!D12,'PLAN BUDGET SAMI-JF'!J13:J100000,SUMMARY!A12&"*") -> 0 | K12: =SUMIFS('PLAN BUDGET SAMI-JF'!AT13:AT100000,'PLAN BUDGET SAMI-JF'!D13:D100000,SUMMARY!D12,'PLAN BUDGET SAMI-JF'!J13:J100000,SUMMARY!A12&"*") -> 0 | L12: =SUMIFS('PLAN BUDGET SAMI-JF'!AU13:AU100000,'PLAN BUDGET SAMI-JF'!D13:D100000,SUMMARY!D12,'PLAN BUDGET SAMI-JF'!J13:J100000,SUMMARY!A12&"*") -> 0 | M12: =SUMIFS('PLAN BUDGET SAMI-JF'!AV13:AV100000,'PLAN BUDGET SAMI-JF'!D13:D100000,SUMMARY!D12,'PLAN BUDGET SAMI-JF'!J13:J100000,SUMMARY!A12&"*") -> 0 | N12: =SUMIFS('PLAN BUDGET SAMI-JF'!AW13:AW100000,'PLAN BUDGET SAMI-JF'!D13:D100000,SUMMARY!D12,'PLAN BUDGET SAMI-JF'!J13:J100000,SUMMARY!A12&"*") -> 0 | O12: =SUMIFS('PLAN BUDGET SAMI-JF'!AX13:AX100000,'PLAN BUDGET SAMI-JF'!D13:D100000,SUMMARY!D12,'PLAN BUDGET SAMI-JF'!J13:J100000,SUMMARY!A12&"*") -> 0 | P12: =SUMIFS('PLAN BUDGET SAMI-JF'!AY13:AY100000,'PLAN BUDGET SAMI-JF'!D13:D100000,SUMMARY!D12,'PLAN BUDGET SAMI-JF'!J13:J100000,SUMMARY!A12&"*") -> 0 | Q12: =SUMIFS('PLAN BUDGET SAMI-JF'!BC13:BC100000,'PLAN BUDGET SAMI-JF'!D13:D100000,SUMMARY!D12,'PLAN BUDGET SAMI-JF'!J13:J100000,SUMMARY!A12&"*") -> 2.2786829 | R12: =SUMIFS('PLAN BUDGET SAMI-JF'!BD13:BD100000,'PLAN BUDGET SAMI-JF'!D13:D100000,SUMMARY!D12,'PLAN BUDGET SAMI-JF'!J13:J100000,SUMMARY!A12&"*") -> 0 | S12: =SUMIFS('PLAN BUDGET SAMI-JF'!BE13:BE100000,'PLAN BUDGET SAMI-JF'!D13:D100000,SUMMARY!D12,'PLAN BUDGET SAMI-JF'!J13:J100000,SUMMARY!A12&"*") -> 0 | T12: =SUMIFS('PLAN BUDGET SAMI-JF'!BF13:BF100000,'PLAN BUDGET SAMI-JF'!D13:D100000,SUMMARY!D12,'PLAN BUDGET SAMI-JF'!J13:J100000,SUMMARY!A12&"*") -> 0 | U12: =SUMIFS('PLAN BUDGET SAMI-JF'!BG13:BG100000,'PLAN BUDGET SAMI-JF'!D13:D100000,SUMMARY!D12,'PLAN BUDGET SAMI-JF'!J13:J100000,SUMMARY!A12&"*") -> 0 | V12: =SUMIFS('PLAN BUDGET SAMI-JF'!BH13:BH100000,'PLAN BUDGET SAMI-JF'!D13:D100000,SUMMARY!D12,'PLAN BUDGET SAMI-JF'!J13:J100000,SUMMARY!A12&"*") -> 0 | W12: =SUMIFS('PLAN BUDGET SAMI-JF'!BI13:BI100000,'PLAN BUDGET SAMI-JF'!D13:D100000,SUMMARY!D12,'PLAN BUDGET SAMI-JF'!J13:J100000,SUMMARY!A12&"*") -> 0 | X12: =SUMIFS('PLAN BUDGET SAMI-JF'!BJ13:BJ100000,'PLAN BUDGET SAMI-JF'!D13:D100000,SUMMARY!D12,'PLAN BUDGET SAMI-JF'!J13:J100000,SUMMARY!A12&"*") -> 0 | Y12: =SUMIFS('PLAN BUDGET SAMI-JF'!BK13:BK100000,'PLAN BUDGET SAMI-JF'!D13:D100000,SUMMARY!D12,'PLAN BUDGET SAMI-JF'!J13:J100000,SUMMARY!A12&"*") -> 0 | Z12: =SUMIFS('PLAN BUDGET SAMI-JF'!BL13:BL100000,'PLAN BUDGET SAMI-JF'!D13:D100000,SUMMARY!D12,'PLAN BUDGET SAMI-JF'!J13:J100000,SUMMARY!A12&"*") -> 0 | AA12: =SUMIFS('PLAN BUDGET SAMI-JF'!BM13:BM100000,'PLAN BUDGET SAMI-JF'!D13:D100000,SUMMARY!D12,'PLAN BUDGET SAMI-JF'!J13:J100000,SUMMARY!A12&"*") -> 0 | AB12: =SUMIFS('PLAN BUDGET SAMI-JF'!BN13:BN100000,'PLAN BUDGET SAMI-JF'!D13:D100000,SUMMARY!D12,'PLAN BUDGET SAMI-JF'!J13:J100000,SUMMARY!A12&"*") -> 0 | AC12: =SUM(E12:P12) -> 1 | AD12: =SUM(Q12:AB12) -> 2.2786829 | AF12: 0 | AG12: 0 | AH12: =IFERROR((AC12-AF12)/AF12,1) -> 1 | AI12: =IFERROR((AD12-AG12)/AG12,1) -> 1 | AJ12: Budget di Term 84 tidak ada, sedangkan di Term 85 ada.
A13: RUTIN | D13: STOPWATCH | E13: =SUMIFS('PLAN BUDGET SAMI-JF'!AN13:AN100000,'PLAN BUDGET SAMI-JF'!D13:D100000,SUMMARY!D13,'PLAN BUDGET SAMI-JF'!J13:J100000,SUMMARY!A13&"*") -> 0 | F13: =SUMIFS('PLAN BUDGET SAMI-JF'!AO13:AO100000,'PLAN BUDGET SAMI-JF'!D13:D100000,SUMMARY!D13,'PLAN BUDGET SAMI-JF'!J13:J100000,SUMMARY!A13&"*") -> 10 | G13: =SUMIFS('PLAN BUDGET SAMI-JF'!AP13:AP100000,'PLAN BUDGET SAMI-JF'!D13:D100000,SUMMARY!D13,'PLAN BUDGET SAMI-JF'!J13:J100000,SUMMARY!A13&"*") -> 0 | H13: =SUMIFS('PLAN BUDGET SAMI-JF'!AQ13:AQ100000,'PLAN BUDGET SAMI-JF'!D13:D100000,SUMMARY!D13,'PLAN BUDGET SAMI-JF'!J13:J100000,SUMMARY!A13&"*") -> 0 | I13: =SUMIFS('PLAN BUDGET SAMI-JF'!AR13:AR100000,'PLAN BUDGET SAMI-JF'!D13:D100000,SUMMARY!D13,'PLAN BUDGET SAMI-JF'!J13:J100000,SUMMARY!A13&"*") -> 0 | J13: =SUMIFS('PLAN BUDGET SAMI-JF'!AS13:AS100000,'PLAN BUDGET SAMI-JF'!D13:D100000,SUMMARY!D13,'PLAN BUDGET SAMI-JF'!J13:J100000,SUMMARY!A13&"*") -> 0 | K13: =SUMIFS('PLAN BUDGET SAMI-JF'!AT13:AT100000,'PLAN BUDGET SAMI-JF'!D13:D100000,SUMMARY!D13,'PLAN BUDGET SAMI-JF'!J13:J100000,SUMMARY!A13&"*") -> 0 | L13: =SUMIFS('PLAN BUDGET SAMI-JF'!AU13:AU100000,'PLAN BUDGET SAMI-JF'!D13:D100000,SUMMARY!D13,'PLAN BUDGET SAMI-JF'!J13:J100000,SUMMARY!A13&"*") -> 0 | M13: =SUMIFS('PLAN BUDGET SAMI-JF'!AV13:AV100000,'PLAN BUDGET SAMI-JF'!D13:D100000,SUMMARY!D13,'PLAN BUDGET SAMI-JF'!J13:J100000,SUMMARY!A13&"*") -> 0 | N13: =SUMIFS('PLAN BUDGET SAMI-JF'!AW13:AW100000,'PLAN BUDGET SAMI-JF'!D13:D100000,SUMMARY!D13,'PLAN BUDGET SAMI-JF'!J13:J100000,SUMMARY!A13&"*") -> 0 | O13: =SUMIFS('PLAN BUDGET SAMI-JF'!AX13:AX100000,'PLAN BUDGET SAMI-JF'!D13:D100000,SUMMARY!D13,'PLAN BUDGET SAMI-JF'!J13:J100000,SUMMARY!A13&"*") -> 0 | P13: =SUMIFS('PLAN BUDGET SAMI-JF'!AY13:AY100000,'PLAN BUDGET SAMI-JF'!D13:D100000,SUMMARY!D13,'PLAN BUDGET SAMI-JF'!J13:J100000,SUMMARY!A13&"*") -> 0 | Q13: =SUMIFS('PLAN BUDGET SAMI-JF'!BC13:BC100000,'PLAN BUDGET SAMI-JF'!D13:D100000,SUMMARY!D13,'PLAN BUDGET SAMI-JF'!J13:J100000,SUMMARY!A13&"*") -> 0 | R13: =SUMIFS('PLAN BUDGET SAMI-JF'!BD13:BD100000,'PLAN BUDGET SAMI-JF'!D13:D100000,SUMMARY!D13,'PLAN BUDGET SAMI-JF'!J13:J100000,SUMMARY!A13&"*") -> 283.60108 | S13: =SUMIFS('PLAN BUDGET SAMI-JF'!BE13:BE100000,'PLAN BUDGET SAMI-JF'!D13:D100000,SUMMARY!D13,'PLAN BUDGET SAMI-JF'!J13:J100000,SUMMARY!A13&"*") -> 0 | T13: =SUMIFS('PLAN BUDGET SAMI-JF'!BF13:BF100000,'PLAN BUDGET SAMI-JF'!D13:D100000,SUMMARY!D13,'PLAN BUDGET SAMI-JF'!J13:J100000,SUMMARY!A13&"*") -> 0 | U13: =SUMIFS('PLAN BUDGET SAMI-JF'!BG13:BG100000,'PLAN BUDGET SAMI-JF'!D13:D100000,SUMMARY!D13,'PLAN BUDGET SAMI-JF'!J13:J100000,SUMMARY!A13&"*") -> 0 | V13: =SUMIFS('PLAN BUDGET SAMI-JF'!BH13:BH100000,'PLAN BUDGET SAMI-JF'!D13:D100000,SUMMARY!D13,'PLAN BUDGET SAMI-JF'!J13:J100000,SUMMARY!A13&"*") -> 0 | W13: =SUMIFS('PLAN BUDGET SAMI-JF'!BI13:BI100000,'PLAN BUDGET SAMI-JF'!D13:D100000,SUMMARY!D13,'PLAN BUDGET SAMI-JF'!J13:J100000,SUMMARY!A13&"*") -> 0 | X13: =SUMIFS('PLAN BUDGET SAMI-JF'!BJ13:BJ100000,'PLAN BUDGET SAMI-JF'!D13:D100000,SUMMARY!D13,'PLAN BUDGET SAMI-JF'!J13:J100000,SUMMARY!A13&"*") -> 0 | Y13: =SUMIFS('PLAN BUDGET SAMI-JF'!BK13:BK100000,'PLAN BUDGET SAMI-JF'!D13:D100000,SUMMARY!D13,'PLAN BUDGET SAMI-JF'!J13:J100000,SUMMARY!A13&"*") -> 0 | Z13: =SUMIFS('PLAN BUDGET SAMI-JF'!BL13:BL100000,'PLAN BUDGET SAMI-JF'!D13:D100000,SUMMARY!D13,'PLAN BUDGET SAMI-JF'!J13:J100000,SUMMARY!A13&"*") -> 0 | AA13: =SUMIFS('PLAN BUDGET SAMI-JF'!BM13:BM100000,'PLAN BUDGET SAMI-JF'!D13:D100000,SUMMARY!D13,'PLAN BUDGET SAMI-JF'!J13:J100000,SUMMARY!A13&"*") -> 0 | AB13: =SUMIFS('PLAN BUDGET SAMI-JF'!BN13:BN100000,'PLAN BUDGET SAMI-JF'!D13:D100000,SUMMARY!D13,'PLAN BUDGET SAMI-JF'!J13:J100000,SUMMARY!A13&"*") -> 0 | AC13: =SUM(E13:P13) -> 10 | AD13: =SUM(Q13:AB13) -> 283.60108 | AF13: 10 | AG13: 265.84634 | AH13: =IFERROR((AC13-AF13)/AF13,1) -> 0 | AI13: =IFERROR((AD13-AG13)/AG13,1) -> 0.066785714 | AJ13: kenaikan harga dari Vendor
A14: RUTIN | D14: ENTERTAIN | E14: =SUMIFS('PLAN BUDGET SAMI-JF'!AN13:AN100000,'PLAN BUDGET SAMI-JF'!D13:D100000,SUMMARY!D14,'PLAN BUDGET SAMI-JF'!J13:J100000,SUMMARY!A14&"*") -> 0 | F14: =SUMIFS('PLAN BUDGET SAMI-JF'!AO13:AO100000,'PLAN BUDGET SAMI-JF'!D13:D100000,SUMMARY!D14,'PLAN BUDGET SAMI-JF'!J13:J100000,SUMMARY!A14&"*") -> 0 | G14: =SUMIFS('PLAN BUDGET SAMI-JF'!AP13:AP100000,'PLAN BUDGET SAMI-JF'!D13:D100000,SUMMARY!D14,'PLAN BUDGET SAMI-JF'!J13:J100000,SUMMARY!A14&"*") -> 0 | H14: =SUMIFS('PLAN BUDGET SAMI-JF'!AQ13:AQ100000,'PLAN BUDGET SAMI-JF'!D13:D100000,SUMMARY!D14,'PLAN BUDGET SAMI-JF'!J13:J100000,SUMMARY!A14&"*") -> 0 | I14: =SUMIFS('PLAN BUDGET SAMI-JF'!AR13:AR100000,'PLAN BUDGET SAMI-JF'!D13:D100000,SUMMARY!D14,'PLAN BUDGET SAMI-JF'!J13:J100000,SUMMARY!A14&"*") -> 0 | J14: =SUMIFS('PLAN BUDGET SAMI-JF'!AS13:AS100000,'PLAN BUDGET SAMI-JF'!D13:D100000,SUMMARY!D14,'PLAN BUDGET SAMI-JF'!J13:J100000,SUMMARY!A14&"*") -> 0 | K14: =SUMIFS('PLAN BUDGET SAMI-JF'!AT13:AT100000,'PLAN BUDGET SAMI-JF'!D13:D100000,SUMMARY!D14,'PLAN BUDGET SAMI-JF'!J13:J100000,SUMMARY!A14&"*") -> 0 | L14: =SUMIFS('PLAN BUDGET SAMI-JF'!AU13:AU100000,'PLAN BUDGET SAMI-JF'!D13:D100000,SUMMARY!D14,'PLAN BUDGET SAMI-JF'!J13:J100000,SUMMARY!A14&"*") -> 0 | M14: =SUMIFS('PLAN BUDGET SAMI-JF'!AV13:AV100000,'PLAN BUDGET SAMI-JF'!D13:D100000,SUMMARY!D14,'PLAN BUDGET SAMI-JF'!J13:J100000,SUMMARY!A14&"*") -> 0 | N14: =SUMIFS('PLAN BUDGET SAMI-JF'!AW13:AW100000,'PLAN BUDGET SAMI-JF'!D13:D100000,SUMMARY!D14,'PLAN BUDGET SAMI-JF'!J13:J100000,SUMMARY!A14&"*") -> 0 | O14: =SUMIFS('PLAN BUDGET SAMI-JF'!AX13:AX100000,'PLAN BUDGET SAMI-JF'!D13:D100000,SUMMARY!D14,'PLAN BUDGET SAMI-JF'!J13:J100000,SUMMARY!A14&"*") -> 10 | P14: =SUMIFS('PLAN BUDGET SAMI-JF'!AY13:AY100000,'PLAN BUDGET SAMI-JF'!D13:D100000,SUMMARY!D14,'PLAN BUDGET SAMI-JF'!J13:J100000,SUMMARY!A14&"*") -> 0 | Q14: =SUMIFS('PLAN BUDGET SAMI-JF'!BC13:BC100000,'PLAN BUDGET SAMI-JF'!D13:D100000,SUMMARY!D14,'PLAN BUDGET SAMI-JF'!J13:J100000,SUMMARY!A14&"*") -> 0 | R14: =SUMIFS('PLAN BUDGET SAMI-JF'!BD13:BD100000,'PLAN BUDGET SAMI-JF'!D13:D100000,SUMMARY!D14,'PLAN BUDGET SAMI-JF'!J13:J100000,SUMMARY!A14&"*") -> 0 | S14: =SUMIFS('PLAN BUDGET SAMI-JF'!BE13:BE100000,'PLAN BUDGET SAMI-JF'!D13:D100000,SUMMARY!D14,'PLAN BUDGET SAMI-JF'!J13:J100000,SUMMARY!A14&"*") -> 0 | T14: =SUMIFS('PLAN BUDGET SAMI-JF'!BF13:BF100000,'PLAN BUDGET SAMI-JF'!D13:D100000,SUMMARY!D14,'PLAN BUDGET SAMI-JF'!J13:J100000,SUMMARY!A14&"*") -> 0 | U14: =SUMIFS('PLAN BUDGET SAMI-JF'!BG13:BG100000,'PLAN BUDGET SAMI-JF'!D13:D100000,SUMMARY!D14,'PLAN BUDGET SAMI-JF'!J13:J100000,SUMMARY!A14&"*") -> 0 | V14: =SUMIFS('PLAN BUDGET SAMI-JF'!BH13:BH100000,'PLAN BUDGET SAMI-JF'!D13:D100000,SUMMARY!D14,'PLAN BUDGET SAMI-JF'!J13:J100000,SUMMARY!A14&"*") -> 0 | W14: =SUMIFS('PLAN BUDGET SAMI-JF'!BI13:BI100000,'PLAN BUDGET SAMI-JF'!D13:D100000,SUMMARY!D14,'PLAN BUDGET SAMI-JF'!J13:J100000,SUMMARY!A14&"*") -> 0 | X14: =SUMIFS('PLAN BUDGET SAMI-JF'!BJ13:BJ100000,'PLAN BUDGET SAMI-JF'!D13:D100000,SUMMARY!D14,'PLAN BUDGET SAMI-JF'!J13:J100000,SUMMARY!A14&"*") -> 0 | Y14: =SUMIFS('PLAN BUDGET SAMI-JF'!BK13:BK100000,'PLAN BUDGET SAMI-JF'!D13:D100000,SUMMARY!D14,'PLAN BUDGET SAMI-JF'!J13:J100000,SUMMARY!A14&"*") -> 0 | Z14: =SUMIFS('PLAN BUDGET SAMI-JF'!BL13:BL100000,'PLAN BUDGET SAMI-JF'!D13:D100000,SUMMARY!D14,'PLAN BUDGET SAMI-JF'!J13:J100000,SUMMARY!A14&"*") -> 0 | AA14: =SUMIFS('PLAN BUDGET SAMI-JF'!BM13:BM100000,'PLAN BUDGET SAMI-JF'!D13:D100000,SUMMARY!D14,'PLAN BUDGET SAMI-JF'!J13:J100000,SUMMARY!A14&"*") -> 94.945122 | AB14: =SUMIFS('PLAN BUDGET SAMI-JF'!BN13:BN100000,'PLAN BUDGET SAMI-JF'!D13:D100000,SUMMARY!D14,'PLAN BUDGET SAMI-JF'!J13:J100000,SUMMARY!A14&"*") -> 0 | AC14: =SUM(E14:P14) -> 10 | AD14: =SUM(Q14:AB14) -> 94.945122 | AF14: 478 | AG14: 2079.2982 | AH14: =IFERROR((AC14-AF14)/AF14,1) -> -0.9790795 | AI14: =IFERROR((AD14-AG14)/AG14,1) -> -0.9543379 | AJ14: ada training eksternal di term 84 ada tapi di tem 85 tidak ada
A15: RUTIN | D15: MASKER | E15: =SUMIFS('PLAN BUDGET SAMI-JF'!AN13:AN100000,'PLAN BUDGET SAMI-JF'!D13:D100000,SUMMARY!D15,'PLAN BUDGET SAMI-JF'!J13:J100000,SUMMARY!A15&"*") -> 0 | F15: =SUMIFS('PLAN BUDGET SAMI-JF'!AO13:AO100000,'PLAN BUDGET SAMI-JF'!D13:D100000,SUMMARY!D15,'PLAN BUDGET SAMI-JF'!J13:J100000,SUMMARY!A15&"*") -> 0 | G15: =SUMIFS('PLAN BUDGET SAMI-JF'!AP13:AP100000,'PLAN BUDGET SAMI-JF'!D13:D100000,SUMMARY!D15,'PLAN BUDGET SAMI-JF'!J13:J100000,SUMMARY!A15&"*") -> 13 | H15: =SUMIFS('PLAN BUDGET SAMI-JF'!AQ13:AQ100000,'PLAN BUDGET SAMI-JF'!D13:D100000,SUMMARY!D15,'PLAN BUDGET SAMI-JF'!J13:J100000,SUMMARY!A15&"*") -> 0 | I15: =SUMIFS('PLAN BUDGET SAMI-JF'!AR13:AR100000,'PLAN BUDGET SAMI-JF'!D13:D100000,SUMMARY!D15,'PLAN BUDGET SAMI-JF'!J13:J100000,SUMMARY!A15&"*") -> 0 | J15: =SUMIFS('PLAN BUDGET SAMI-JF'!AS13:AS100000,'PLAN BUDGET SAMI-JF'!D13:D100000,SUMMARY!D15,'PLAN BUDGET SAMI-JF'!J13:J100000,SUMMARY!A15&"*") -> 0 | K15: =SUMIFS('PLAN BUDGET SAMI-JF'!AT13:AT100000,'PLAN BUDGET SAMI-JF'!D13:D100000,SUMMARY!D15,'PLAN BUDGET SAMI-JF'!J13:J100000,SUMMARY!A15&"*") -> 0 | L15: =SUMIFS('PLAN BUDGET SAMI-JF'!AU13:AU100000,'PLAN BUDGET SAMI-JF'!D13:D100000,SUMMARY!D15,'PLAN BUDGET SAMI-JF'!J13:J100000,SUMMARY!A15&"*") -> 13 | M15: =SUMIFS('PLAN BUDGET SAMI-JF'!AV13:AV100000,'PLAN BUDGET SAMI-JF'!D13:D100000,SUMMARY!D15,'PLAN BUDGET SAMI-JF'!J13:J100000,SUMMARY!A15&"*") -> 0 | N15: =SUMIFS('PLAN BUDGET SAMI-JF'!AW13:AW100000,'PLAN BUDGET SAMI-JF'!D13:D100000,SUMMARY!D15,'PLAN BUDGET SAMI-JF'!J13:J100000,SUMMARY!A15&"*") -> 0 | O15: =SUMIFS('PLAN BUDGET SAMI-JF'!AX13:AX100000,'PLAN BUDGET SAMI-JF'!D13:D100000,SUMMARY!D15,'PLAN BUDGET SAMI-JF'!J13:J100000,SUMMARY!A15&"*") -> 0 | P15: =SUMIFS('PLAN BUDGET SAMI-JF'!AY13:AY100000,'PLAN BUDGET SAMI-JF'!D13:D100000,SUMMARY!D15,'PLAN BUDGET SAMI-JF'!J13:J100000,SUMMARY!A15&"*") -> 0 | Q15: =SUMIFS('PLAN BUDGET SAMI-JF'!BC13:BC100000,'PLAN BUDGET SAMI-JF'!D13:D100000,SUMMARY!D15,'PLAN BUDGET SAMI-JF'!J13:J100000,SUMMARY!A15&"*") -> 0 | R15: =SUMIFS('PLAN BUDGET SAMI-JF'!BD13:BD100000,'PLAN BUDGET SAMI-JF'!D13:D100000,SUMMARY!D15,'PLAN BUDGET SAMI-JF'!J13:J100000,SUMMARY!A15&"*") -> 0 | S15: =SUMIFS('PLAN BUDGET SAMI-JF'!BE13:BE100000,'PLAN BUDGET SAMI-JF'!D13:D100000,SUMMARY!D15,'PLAN BUDGET SAMI-JF'!J13:J100000,SUMMARY!A15&"*") -> 27.154305 | T15: =SUMIFS('PLAN BUDGET SAMI-JF'!BF13:BF100000,'PLAN BUDGET SAMI-JF'!D13:D100000,SUMMARY!D15,'PLAN BUDGET SAMI-JF'!J13:J100000,SUMMARY!A15&"*") -> 0 | U15: =SUMIFS('PLAN BUDGET SAMI-JF'!BG13:BG100000,'PLAN BUDGET SAMI-JF'!D13:D100000,SUMMARY!D15,'PLAN BUDGET SAMI-JF'!J13:J100000,SUMMARY!A15&"*") -> 0 | V15: =SUMIFS('PLAN BUDGET SAMI-JF'!BH13:BH100000,'PLAN BUDGET SAMI-JF'!D13:D100000,SUMMARY!D15,'PLAN BUDGET SAMI-JF'!J13:J100000,SUMMARY!A15&"*") -> 0 | W15: =SUMIFS('PLAN BUDGET SAMI-JF'!BI13:BI100000,'PLAN BUDGET SAMI-JF'!D13:D100000,SUMMARY!D15,'PLAN BUDGET SAMI-JF'!J13:J100000,SUMMARY!A15&"*") -> 0 | X15: =SUMIFS('PLAN BUDGET SAMI-JF'!BJ13:BJ100000,'PLAN BUDGET SAMI-JF'!D13:D100000,SUMMARY!D15,'PLAN BUDGET SAMI-JF'!J13:J100000,SUMMARY!A15&"*") -> 27.154305 | Y15: =SUMIFS('PLAN BUDGET SAMI-JF'!BK13:BK100000,'PLAN BUDGET SAMI-JF'!D13:D100000,SUMMARY!D15,'PLAN BUDGET SAMI-JF'!J13:J100000,SUMMARY!A15&"*") -> 0 | Z15: =SUMIFS('PLAN BUDGET SAMI-JF'!BL13:BL100000,'PLAN BUDGET SAMI-JF'!D13:D100000,SUMMARY!D15,'PLAN BUDGET SAMI-JF'!J13:J100000,SUMMARY!A15&"*") -> 0 | AA15: =SUMIFS('PLAN BUDGET SAMI-JF'!BM13:BM100000,'PLAN BUDGET SAMI-JF'!D13:D100000,SUMMARY!D15,'PLAN BUDGET SAMI-JF'!J13:J100000,SUMMARY!A15&"*") -> 0 | AB15: =SUMIFS('PLAN BUDGET SAMI-JF'!BN13:BN100000,'PLAN BUDGET SAMI-JF'!D13:D100000,SUMMARY!D15,'PLAN BUDGET SAMI-JF'!J13:J100000,SUMMARY!A15&"*") -> 0 | AC15: =SUM(E15:P15) -> 26 | AD15: =SUM(Q15:AB15) -> 54.30861 | AF15: 12 | AG15: 22.027268 | AH15: =IFERROR((AC15-AF15)/AF15,1) -> 1.1666667 | AI15: =IFERROR((AD15-AG15)/AG15,1) -> 1.4655172 | AJ15: Budget di Term 84 tidak ada, sedangkan di Term 85 ada.
A16: RUTIN | D16: BULAN COMPLIANCE | E16: =SUMIFS('PLAN BUDGET SAMI-JF'!AN13:AN100000,'PLAN BUDGET SAMI-JF'!D13:D100000,SUMMARY!D16,'PLAN BUDGET SAMI-JF'!J13:J100000,SUMMARY!A16&"*") -> 0 | F16: =SUMIFS('PLAN BUDGET SAMI-JF'!AO13:AO100000,'PLAN BUDGET SAMI-JF'!D13:D100000,SUMMARY!D16,'PLAN BUDGET SAMI-JF'!J13:J100000,SUMMARY!A16&"*") -> 0 | G16: =SUMIFS('PLAN BUDGET SAMI-JF'!AP13:AP100000,'PLAN BUDGET SAMI-JF'!D13:D100000,SUMMARY!D16,'PLAN BUDGET SAMI-JF'!J13:J100000,SUMMARY!A16&"*") -> 0 | H16: =SUMIFS('PLAN BUDGET SAMI-JF'!AQ13:AQ100000,'PLAN BUDGET SAMI-JF'!D13:D100000,SUMMARY!D16,'PLAN BUDGET SAMI-JF'!J13:J100000,SUMMARY!A16&"*") -> 0 | I16: =SUMIFS('PLAN BUDGET SAMI-JF'!AR13:AR100000,'PLAN BUDGET SAMI-JF'!D13:D100000,SUMMARY!D16,'PLAN BUDGET SAMI-JF'!J13:J100000,SUMMARY!A16&"*") -> 0 | J16: =SUMIFS('PLAN BUDGET SAMI-JF'!AS13:AS100000,'PLAN BUDGET SAMI-JF'!D13:D100000,SUMMARY!D16,'PLAN BUDGET SAMI-JF'!J13:J100000,SUMMARY!A16&"*") -> 0 | K16: =SUMIFS('PLAN BUDGET SAMI-JF'!AT13:AT100000,'PLAN BUDGET SAMI-JF'!D13:D100000,SUMMARY!D16,'PLAN BUDGET SAMI-JF'!J13:J100000,SUMMARY!A16&"*") -> 0 | L16: =SUMIFS('PLAN BUDGET SAMI-JF'!AU13:AU100000,'PLAN BUDGET SAMI-JF'!D13:D100000,SUMMARY!D16,'PLAN BUDGET SAMI-JF'!J13:J100000,SUMMARY!A16&"*") -> 0 | M16: =SUMIFS('PLAN BUDGET SAMI-JF'!AV13:AV100000,'PLAN BUDGET SAMI-JF'!D13:D100000,SUMMARY!D16,'PLAN BUDGET SAMI-JF'!J13:J100000,SUMMARY!A16&"*") -> 0 | N16: =SUMIFS('PLAN BUDGET SAMI-JF'!AW13:AW100000,'PLAN BUDGET SAMI-JF'!D13:D100000,SUMMARY!D16,'PLAN BUDGET SAMI-JF'!J13:J100000,SUMMARY!A16&"*") -> 0 | O16: =SUMIFS('PLAN BUDGET SAMI-JF'!AX13:AX100000,'PLAN BUDGET SAMI-JF'!D13:D100000,SUMMARY!D16,'PLAN BUDGET SAMI-JF'!J13:J100000,SUMMARY!A16&"*") -> 0 | P16: =SUMIFS('PLAN BUDGET SAMI-JF'!AY13:AY100000,'PLAN BUDGET SAMI-JF'!D13:D100000,SUMMARY!D16,'PLAN BUDGET SAMI-JF'!J13:J100000,SUMMARY!A16&"*") -> 1 | Q16: =SUMIFS('PLAN BUDGET SAMI-JF'!BC13:BC100000,'PLAN BUDGET SAMI-JF'!D13:D100000,SUMMARY!D16,'PLAN BUDGET SAMI-JF'!J13:J100000,SUMMARY!A16&"*") -> 0 | R16: =SUMIFS('PLAN BUDGET SAMI-JF'!BD13:BD100000,'PLAN BUDGET SAMI-JF'!D13:D100000,SUMMARY!D16,'PLAN BUDGET SAMI-JF'!J13:J100000,SUMMARY!A16&"*") -> 0 | S16: =SUMIFS('PLAN BUDGET SAMI-JF'!BE13:BE100000,'PLAN BUDGET SAMI-JF'!D13:D100000,SUMMARY!D16,'PLAN BUDGET SAMI-JF'!J13:J100000,SUMMARY!A16&"*") -> 0 | T16: =SUMIFS('PLAN BUDGET SAMI-JF'!BF13:BF100000,'PLAN BUDGET SAMI-JF'!D13:D100000,SUMMARY!D16,'PLAN BUDGET SAMI-JF'!J13:J100000,SUMMARY!A16&"*") -> 0 | U16: =SUMIFS('PLAN BUDGET SAMI-JF'!BG13:BG100000,'PLAN BUDGET SAMI-JF'!D13:D100000,SUMMARY!D16,'PLAN BUDGET SAMI-JF'!J13:J100000,SUMMARY!A16&"*") -> 0 | V16: =SUMIFS('PLAN BUDGET SAMI-JF'!BH13:BH100000,'PLAN BUDGET SAMI-JF'!D13:D100000,SUMMARY!D16,'PLAN BUDGET SAMI-JF'!J13:J100000,SUMMARY!A16&"*") -> 0 | W16: =SUMIFS('PLAN BUDGET SAMI-JF'!BI13:BI100000,'PLAN BUDGET SAMI-JF'!D13:D100000,SUMMARY!D16,'PLAN BUDGET SAMI-JF'!J13:J100000,SUMMARY!A16&"*") -> 0 | X16: =SUMIFS('PLAN BUDGET SAMI-JF'!BJ13:BJ100000,'PLAN BUDGET SAMI-JF'!D13:D100000,SUMMARY!D16,'PLAN BUDGET SAMI-JF'!J13:J100000,SUMMARY!A16&"*") -> 0 | Y16: =SUMIFS('PLAN BUDGET SAMI-JF'!BK13:BK100000,'PLAN BUDGET SAMI-JF'!D13:D100000,SUMMARY!D16,'PLAN BUDGET SAMI-JF'!J13:J100000,SUMMARY!A16&"*") -> 0 | Z16: =SUMIFS('PLAN BUDGET SAMI-JF'!BL13:BL100000,'PLAN BUDGET SAMI-JF'!D13:D100000,SUMMARY!D16,'PLAN BUDGET SAMI-JF'!J13:J100000,SUMMARY!A16&"*") -> 0 | AA16: =SUMIFS('PLAN BUDGET SAMI-JF'!BM13:BM100000,'PLAN BUDGET SAMI-JF'!D13:D100000,SUMMARY!D16,'PLAN BUDGET SAMI-JF'!J13:J100000,SUMMARY!A16&"*") -> 0 | AB16: =SUMIFS('PLAN BUDGET SAMI-JF'!BN13:BN100000,'PLAN BUDGET SAMI-JF'!D13:D100000,SUMMARY!D16,'PLAN BUDGET SAMI-JF'!J13:J100000,SUMMARY!A16&"*") -> 316.48374 | AC16: =SUM(E16:P16) -> 1 | AD16: =SUM(Q16:AB16) -> 316.48374 | AF16: 0 | AG16: 0 | AH16: =IFERROR((AC16-AF16)/AF16,1) -> 1 | AI16: =IFERROR((AD16-AG16)/AG16,1) -> 1 | AJ16: Budget di Term 84 tidak ada, sedangkan di Term 85 ada.
A17: RUTIN | D17: LAMPU | E17: =SUMIFS('PLAN BUDGET SAMI-JF'!AN13:AN100000,'PLAN BUDGET SAMI-JF'!D13:D100000,SUMMARY!D17,'PLAN BUDGET SAMI-JF'!J13:J100000,SUMMARY!A17&"*") -> 1 | F17: =SUMIFS('PLAN BUDGET SAMI-JF'!AO13:AO100000,'PLAN BUDGET SAMI-JF'!D13:D100000,SUMMARY!D17,'PLAN BUDGET SAMI-JF'!J13:J100000,SUMMARY!A17&"*") -> 0 | G17: =SUMIFS('PLAN BUDGET SAMI-JF'!AP13:AP100000,'PLAN BUDGET SAMI-JF'!D13:D100000,SUMMARY!D17,'PLAN BUDGET SAMI-JF'!J13:J100000,SUMMARY!A17&"*") -> 0 | H17: =SUMIFS('PLAN BUDGET SAMI-JF'!AQ13:AQ100000,'PLAN BUDGET SAMI-JF'!D13:D100000,SUMMARY!D17,'PLAN BUDGET SAMI-JF'!J13:J100000,SUMMARY!A17&"*") -> 0 | I17: =SUMIFS('PLAN BUDGET SAMI-JF'!AR13:AR100000,'PLAN BUDGET SAMI-JF'!D13:D100000,SUMMARY!D17,'PLAN BUDGET SAMI-JF'!J13:J100000,SUMMARY!A17&"*") -> 0 | J17: =SUMIFS('PLAN BUDGET SAMI-JF'!AS13:AS100000,'PLAN BUDGET SAMI-JF'!D13:D100000,SUMMARY!D17,'PLAN BUDGET SAMI-JF'!J13:J100000,SUMMARY!A17&"*") -> 0 | K17: =SUMIFS('PLAN BUDGET SAMI-JF'!AT13:AT100000,'PLAN BUDGET SAMI-JF'!D13:D100000,SUMMARY!D17,'PLAN BUDGET SAMI-JF'!J13:J100000,SUMMARY!A17&"*") -> 0 | L17: =SUMIFS('PLAN BUDGET SAMI-JF'!AU13:AU100000,'PLAN BUDGET SAMI-JF'!D13:D100000,SUMMARY!D17,'PLAN BUDGET SAMI-JF'!J13:J100000,SUMMARY!A17&"*") -> 0 | M17: =SUMIFS('PLAN BUDGET SAMI-JF'!AV13:AV100000,'PLAN BUDGET SAMI-JF'!D13:D100000,SUMMARY!D17,'PLAN BUDGET SAMI-JF'!J13:J100000,SUMMARY!A17&"*") -> 0 | N17: =SUMIFS('PLAN BUDGET SAMI-JF'!AW13:AW100000,'PLAN BUDGET SAMI-JF'!D13:D100000,SUMMARY!D17,'PLAN BUDGET SAMI-JF'!J13:J100000,SUMMARY!A17&"*") -> 0 | O17: =SUMIFS('PLAN BUDGET SAMI-JF'!AX13:AX100000,'PLAN BUDGET SAMI-JF'!D13:D100000,SUMMARY!D17,'PLAN BUDGET SAMI-JF'!J13:J100000,SUMMARY!A17&"*") -> 0 | P17: =SUMIFS('PLAN BUDGET SAMI-JF'!AY13:AY100000,'PLAN BUDGET SAMI-JF'!D13:D100000,SUMMARY!D17,'PLAN BUDGET SAMI-JF'!J13:J100000,SUMMARY!A17&"*") -> 0 | Q17: =SUMIFS('PLAN BUDGET SAMI-JF'!BC13:BC100000,'PLAN BUDGET SAMI-JF'!D13:D100000,SUMMARY!D17,'PLAN BUDGET SAMI-JF'!J13:J100000,SUMMARY!A17&"*") -> 2.8483537 | R17: =SUMIFS('PLAN BUDGET SAMI-JF'!BD13:BD100000,'PLAN BUDGET SAMI-JF'!D13:D100000,SUMMARY!D17,'PLAN BUDGET SAMI-JF'!J13:J100000,SUMMARY!A17&"*") -> 0 | S17: =SUMIFS('PLAN BUDGET SAMI-JF'!BE13:BE100000,'PLAN BUDGET SAMI-JF'!D13:D100000,SUMMARY!D17,'PLAN BUDGET SAMI-JF'!J13:J100000,SUMMARY!A17&"*") -> 0 | T17: =SUMIFS('PLAN BUDGET SAMI-JF'!BF13:BF100000,'PLAN BUDGET SAMI-JF'!D13:D100000,SUMMARY!D17,'PLAN BUDGET SAMI-JF'!J13:J100000,SUMMARY!A17&"*") -> 0 | U17: =SUMIFS('PLAN BUDGET SAMI-JF'!BG13:BG100000,'PLAN BUDGET SAMI-JF'!D13:D100000,SUMMARY!D17,'PLAN BUDGET SAMI-JF'!J13:J100000,SUMMARY!A17&"*") -> 0 | V17: =SUMIFS('PLAN BUDGET SAMI-JF'!BH13:BH100000,'PLAN BUDGET SAMI-JF'!D13:D100000,SUMMARY!D17,'PLAN BUDGET SAMI-JF'!J13:J100000,SUMMARY!A17&"*") -> 0 | W17: =SUMIFS('PLAN BUDGET SAMI-JF'!BI13:BI100000,'PLAN BUDGET SAMI-JF'!D13:D100000,SUMMARY!D17,'PLAN BUDGET SAMI-JF'!J13:J100000,SUMMARY!A17&"*") -> 0 | X17: =SUMIFS('PLAN BUDGET SAMI-JF'!BJ13:BJ100000,'PLAN BUDGET SAMI-JF'!D13:D100000,SUMMARY!D17,'PLAN BUDGET SAMI-JF'!J13:J100000,SUMMARY!A17&"*") -> 0 | Y17: =SUMIFS('PLAN BUDGET SAMI-JF'!BK13:BK100000,'PLAN BUDGET SAMI-JF'!D13:D100000,SUMMARY!D17,'PLAN BUDGET SAMI-JF'!J13:J100000,SUMMARY!A17&"*") -> 0 | Z17: =SUMIFS('PLAN BUDGET SAMI-JF'!BL13:BL100000,'PLAN BUDGET SAMI-JF'!D13:D100000,SUMMARY!D17,'PLAN BUDGET SAMI-JF'!J13:J100000,SUMMARY!A17&"*") -> 0 | AA17: =SUMIFS('PLAN BUDGET SAMI-JF'!BM13:BM100000,'PLAN BUDGET SAMI-JF'!D13:D100000,SUMMARY!D17,'PLAN BUDGET SAMI-JF'!J13:J100000,SUMMARY!A17&"*") -> 0 | AB17: =SUMIFS('PLAN BUDGET SAMI-JF'!BN13:BN100000,'PLAN BUDGET SAMI-JF'!D13:D100000,SUMMARY!D17,'PLAN BUDGET SAMI-JF'!J13:J100000,SUMMARY!A17&"*") -> 0 | AC17: =SUM(E17:P17) -> 1 | AD17: =SUM(Q17:AB17) -> 2.8483537 | AF17: 0 | AG17: 0 | AH17: =IFERROR((AC17-AF17)/AF17,1) -> 1 | AI17: =IFERROR((AD17-AG17)/AG17,1) -> 1 | AJ17: Budget di Term 84 tidak ada, sedangkan di Term 85 ada.
A18: RUTIN | D18: TES BAHASA ASING | E18: =SUMIFS('PLAN BUDGET SAMI-JF'!AN13:AN100000,'PLAN BUDGET SAMI-JF'!D13:D100000,SUMMARY!D18,'PLAN BUDGET SAMI-JF'!J13:J100000,SUMMARY!A18&"*") -> 0 | F18: =SUMIFS('PLAN BUDGET SAMI-JF'!AO13:AO100000,'PLAN BUDGET SAMI-JF'!D13:D100000,SUMMARY!D18,'PLAN BUDGET SAMI-JF'!J13:J100000,SUMMARY!A18&"*") -> 0 | G18: =SUMIFS('PLAN BUDGET SAMI-JF'!AP13:AP100000,'PLAN BUDGET SAMI-JF'!D13:D100000,SUMMARY!D18,'PLAN BUDGET SAMI-JF'!J13:J100000,SUMMARY!A18&"*") -> 0 | H18: =SUMIFS('PLAN BUDGET SAMI-JF'!AQ13:AQ100000,'PLAN BUDGET SAMI-JF'!D13:D100000,SUMMARY!D18,'PLAN BUDGET SAMI-JF'!J13:J100000,SUMMARY!A18&"*") -> 0 | I18: =SUMIFS('PLAN BUDGET SAMI-JF'!AR13:AR100000,'PLAN BUDGET SAMI-JF'!D13:D100000,SUMMARY!D18,'PLAN BUDGET SAMI-JF'!J13:J100000,SUMMARY!A18&"*") -> 0 | J18: =SUMIFS('PLAN BUDGET SAMI-JF'!AS13:AS100000,'PLAN BUDGET SAMI-JF'!D13:D100000,SUMMARY!D18,'PLAN BUDGET SAMI-JF'!J13:J100000,SUMMARY!A18&"*") -> 0 | K18: =SUMIFS('PLAN BUDGET SAMI-JF'!AT13:AT100000,'PLAN BUDGET SAMI-JF'!D13:D100000,SUMMARY!D18,'PLAN BUDGET SAMI-JF'!J13:J100000,SUMMARY!A18&"*") -> 0 | L18: =SUMIFS('PLAN BUDGET SAMI-JF'!AU13:AU100000,'PLAN BUDGET SAMI-JF'!D13:D100000,SUMMARY!D18,'PLAN BUDGET SAMI-JF'!J13:J100000,SUMMARY!A18&"*") -> 0 | M18: =SUMIFS('PLAN BUDGET SAMI-JF'!AV13:AV100000,'PLAN BUDGET SAMI-JF'!D13:D100000,SUMMARY!D18,'PLAN BUDGET SAMI-JF'!J13:J100000,SUMMARY!A18&"*") -> 10 | N18: =SUMIFS('PLAN BUDGET SAMI-JF'!AW13:AW100000,'PLAN BUDGET SAMI-JF'!D13:D100000,SUMMARY!D18,'PLAN BUDGET SAMI-JF'!J13:J100000,SUMMARY!A18&"*") -> 0 | O18: =SUMIFS('PLAN BUDGET SAMI-JF'!AX13:AX100000,'PLAN BUDGET SAMI-JF'!D13:D100000,SUMMARY!D18,'PLAN BUDGET SAMI-JF'!J13:J100000,SUMMARY!A18&"*") -> 0 | P18: =SUMIFS('PLAN BUDGET SAMI-JF'!AY13:AY100000,'PLAN BUDGET SAMI-JF'!D13:D100000,SUMMARY!D18,'PLAN BUDGET SAMI-JF'!J13:J100000,SUMMARY!A18&"*") -> 0 | Q18: =SUMIFS('PLAN BUDGET SAMI-JF'!BC13:BC100000,'PLAN BUDGET SAMI-JF'!D13:D100000,SUMMARY!D18,'PLAN BUDGET SAMI-JF'!J13:J100000,SUMMARY!A18&"*") -> 0 | R18: =SUMIFS('PLAN BUDGET SAMI-JF'!BD13:BD100000,'PLAN BUDGET SAMI-JF'!D13:D100000,SUMMARY!D18,'PLAN BUDGET SAMI-JF'!J13:J100000,SUMMARY!A18&"*") -> 0 | S18: =SUMIFS('PLAN BUDGET SAMI-JF'!BE13:BE100000,'PLAN BUDGET SAMI-JF'!D13:D100000,SUMMARY!D18,'PLAN BUDGET SAMI-JF'!J13:J100000,SUMMARY!A18&"*") -> 0 | T18: =SUMIFS('PLAN BUDGET SAMI-JF'!BF13:BF100000,'PLAN BUDGET SAMI-JF'!D13:D100000,SUMMARY!D18,'PLAN BUDGET SAMI-JF'!J13:J100000,SUMMARY!A18&"*") -> 0 | U18: =SUMIFS('PLAN BUDGET SAMI-JF'!BG13:BG100000,'PLAN BUDGET SAMI-JF'!D13:D100000,SUMMARY!D18,'PLAN BUDGET SAMI-JF'!J13:J100000,SUMMARY!A18&"*") -> 0 | V18: =SUMIFS('PLAN BUDGET SAMI-JF'!BH13:BH100000,'PLAN BUDGET SAMI-JF'!D13:D100000,SUMMARY!D18,'PLAN BUDGET SAMI-JF'!J13:J100000,SUMMARY!A18&"*") -> 0 | W18: =SUMIFS('PLAN BUDGET SAMI-JF'!BI13:BI100000,'PLAN BUDGET SAMI-JF'!D13:D100000,SUMMARY!D18,'PLAN BUDGET SAMI-JF'!J13:J100000,SUMMARY!A18&"*") -> 0 | X18: =SUMIFS('PLAN BUDGET SAMI-JF'!BJ13:BJ100000,'PLAN BUDGET SAMI-JF'!D13:D100000,SUMMARY!D18,'PLAN BUDGET SAMI-JF'!J13:J100000,SUMMARY!A18&"*") -> 0 | Y18: =SUMIFS('PLAN BUDGET SAMI-JF'!BK13:BK100000,'PLAN BUDGET SAMI-JF'!D13:D100000,SUMMARY!D18,'PLAN BUDGET SAMI-JF'!J13:J100000,SUMMARY!A18&"*") -> 88.615447 | Z18: =SUMIFS('PLAN BUDGET SAMI-JF'!BL13:BL100000,'PLAN BUDGET SAMI-JF'!D13:D100000,SUMMARY!D18,'PLAN BUDGET SAMI-JF'!J13:J100000,SUMMARY!A18&"*") -> 0 | AA18: =SUMIFS('PLAN BUDGET SAMI-JF'!BM13:BM100000,'PLAN BUDGET SAMI-JF'!D13:D100000,SUMMARY!D18,'PLAN BUDGET SAMI-JF'!J13:J100000,SUMMARY!A18&"*") -> 0 | AB18: =SUMIFS('PLAN BUDGET SAMI-JF'!BN13:BN100000,'PLAN BUDGET SAMI-JF'!D13:D100000,SUMMARY!D18,'PLAN BUDGET SAMI-JF'!J13:J100000,SUMMARY!A18&"*") -> 0 | AC18: =SUM(E18:P18) -> 10 | AD18: =SUM(Q18:AB18) -> 88.615447 | AF18: 10 | AG18: 88.615447 | AH18: =IFERROR((AC18-AF18)/AF18,1) -> 0 | AI18: =IFERROR((AD18-AG18)/AG18,1) -> 0
A19: RUTIN | D19: BENCHMARK QCC | E19: =SUMIFS('PLAN BUDGET SAMI-JF'!AN13:AN100000,'PLAN BUDGET SAMI-JF'!D13:D100000,SUMMARY!D19,'PLAN BUDGET SAMI-JF'!J13:J100000,SUMMARY!A19&"*") -> 0 | F19: =SUMIFS('PLAN BUDGET SAMI-JF'!AO13:AO100000,'PLAN BUDGET SAMI-JF'!D13:D100000,SUMMARY!D19,'PLAN BUDGET SAMI-JF'!J13:J100000,SUMMARY!A19&"*") -> 0 | G19: =SUMIFS('PLAN BUDGET SAMI-JF'!AP13:AP100000,'PLAN BUDGET SAMI-JF'!D13:D100000,SUMMARY!D19,'PLAN BUDGET SAMI-JF'!J13:J100000,SUMMARY!A19&"*") -> 0 | H19: =SUMIFS('PLAN BUDGET SAMI-JF'!AQ13:AQ100000,'PLAN BUDGET SAMI-JF'!D13:D100000,SUMMARY!D19,'PLAN BUDGET SAMI-JF'!J13:J100000,SUMMARY!A19&"*") -> 0 | I19: =SUMIFS('PLAN BUDGET SAMI-JF'!AR13:AR100000,'PLAN BUDGET SAMI-JF'!D13:D100000,SUMMARY!D19,'PLAN BUDGET SAMI-JF'!J13:J100000,SUMMARY!A19&"*") -> 2 | J19: =SUMIFS('PLAN BUDGET SAMI-JF'!AS13:AS100000,'PLAN BUDGET SAMI-JF'!D13:D100000,SUMMARY!D19,'PLAN BUDGET SAMI-JF'!J13:J100000,SUMMARY!A19&"*") -> 0 | K19: =SUMIFS('PLAN BUDGET SAMI-JF'!AT13:AT100000,'PLAN BUDGET SAMI-JF'!D13:D100000,SUMMARY!D19,'PLAN BUDGET SAMI-JF'!J13:J100000,SUMMARY!A19&"*") -> 0 | L19: =SUMIFS('PLAN BUDGET SAMI-JF'!AU13:AU100000,'PLAN BUDGET SAMI-JF'!D13:D100000,SUMMARY!D19,'PLAN BUDGET SAMI-JF'!J13:J100000,SUMMARY!A19&"*") -> 0 | M19: =SUMIFS('PLAN BUDGET SAMI-JF'!AV13:AV100000,'PLAN BUDGET SAMI-JF'!D13:D100000,SUMMARY!D19,'PLAN BUDGET SAMI-JF'!J13:J100000,SUMMARY!A19&"*") -> 0 | N19: =SUMIFS('PLAN BUDGET SAMI-JF'!AW13:AW100000,'PLAN BUDGET SAMI-JF'!D13:D100000,SUMMARY!D19,'PLAN BUDGET SAMI-JF'!J13:J100000,SUMMARY!A19&"*") -> 0 | O19: =SUMIFS('PLAN BUDGET SAMI-JF'!AX13:AX100000,'PLAN BUDGET SAMI-JF'!D13:D100000,SUMMARY!D19,'PLAN BUDGET SAMI-JF'!J13:J100000,SUMMARY!A19&"*") -> 0 | P19: =SUMIFS('PLAN BUDGET SAMI-JF'!AY13:AY100000,'PLAN BUDGET SAMI-JF'!D13:D100000,SUMMARY!D19,'PLAN BUDGET SAMI-JF'!J13:J100000,SUMMARY!A19&"*") -> 0 | Q19: =SUMIFS('PLAN BUDGET SAMI-JF'!BC13:BC100000,'PLAN BUDGET SAMI-JF'!D13:D100000,SUMMARY!D19,'PLAN BUDGET SAMI-JF'!J13:J100000,SUMMARY!A19&"*") -> 0 | R19: =SUMIFS('PLAN BUDGET SAMI-JF'!BD13:BD100000,'PLAN BUDGET SAMI-JF'!D13:D100000,SUMMARY!D19,'PLAN BUDGET SAMI-JF'!J13:J100000,SUMMARY!A19&"*") -> 0 | S19: =SUMIFS('PLAN BUDGET SAMI-JF'!BE13:BE100000,'PLAN BUDGET SAMI-JF'!D13:D100000,SUMMARY!D19,'PLAN BUDGET SAMI-JF'!J13:J100000,SUMMARY!A19&"*") -> 0 | T19: =SUMIFS('PLAN BUDGET SAMI-JF'!BF13:BF100000,'PLAN BUDGET SAMI-JF'!D13:D100000,SUMMARY!D19,'PLAN BUDGET SAMI-JF'!J13:J100000,SUMMARY!A19&"*") -> 0 | U19: =SUMIFS('PLAN BUDGET SAMI-JF'!BG13:BG100000,'PLAN BUDGET SAMI-JF'!D13:D100000,SUMMARY!D19,'PLAN BUDGET SAMI-JF'!J13:J100000,SUMMARY!A19&"*") -> 63.296748 | V19: =SUMIFS('PLAN BUDGET SAMI-JF'!BH13:BH100000,'PLAN BUDGET SAMI-JF'!D13:D100000,SUMMARY!D19,'PLAN BUDGET SAMI-JF'!J13:J100000,SUMMARY!A19&"*") -> 0 | W19: =SUMIFS('PLAN BUDGET SAMI-JF'!BI13:BI100000,'PLAN BUDGET SAMI-JF'!D13:D100000,SUMMARY!D19,'PLAN BUDGET SAMI-JF'!J13:J100000,SUMMARY!A19&"*") -> 0 | X19: =SUMIFS('PLAN BUDGET SAMI-JF'!BJ13:BJ100000,'PLAN BUDGET SAMI-JF'!D13:D100000,SUMMARY!D19,'PLAN BUDGET SAMI-JF'!J13:J100000,SUMMARY!A19&"*") -> 0 | Y19: =SUMIFS('PLAN BUDGET SAMI-JF'!BK13:BK100000,'PLAN BUDGET SAMI-JF'!D13:D100000,SUMMARY!D19,'PLAN BUDGET SAMI-JF'!J13:J100000,SUMMARY!A19&"*") -> 0 | Z19: =SUMIFS('PLAN BUDGET SAMI-JF'!BL13:BL100000,'PLAN BUDGET SAMI-JF'!D13:D100000,SUMMARY!D19,'PLAN BUDGET SAMI-JF'!J13:J100000,SUMMARY!A19&"*") -> 0 | AA19: =SUMIFS('PLAN BUDGET SAMI-JF'!BM13:BM100000,'PLAN BUDGET SAMI-JF'!D13:D100000,SUMMARY!D19,'PLAN BUDGET SAMI-JF'!J13:J100000,SUMMARY!A19&"*") -> 0 | AB19: =SUMIFS('PLAN BUDGET SAMI-JF'!BN13:BN100000,'PLAN BUDGET SAMI-JF'!D13:D100000,SUMMARY!D19,'PLAN BUDGET SAMI-JF'!J13:J100000,SUMMARY!A19&"*") -> 0 | AC19: =SUM(E19:P19) -> 2 | AD19: =SUM(Q19:AB19) -> 63.296748 | AF19: 4 | AG19: 88.615447 | AH19: =IFERROR((AC19-AF19)/AF19,1) -> -0.5 | AI19: =IFERROR((AD19-AG19)/AG19,1) -> -0.28571429 | AJ19: kenaikan harga dari Vendor
A20: RUTIN | D20: BIAYA TRAINING | E20: =SUMIFS('PLAN BUDGET SAMI-JF'!AN13:AN100000,'PLAN BUDGET SAMI-JF'!D13:D100000,SUMMARY!D20,'PLAN BUDGET SAMI-JF'!J13:J100000,SUMMARY!A20&"*") -> 0 | F20: =SUMIFS('PLAN BUDGET SAMI-JF'!AO13:AO100000,'PLAN BUDGET SAMI-JF'!D13:D100000,SUMMARY!D20,'PLAN BUDGET SAMI-JF'!J13:J100000,SUMMARY!A20&"*") -> 1 | G20: =SUMIFS('PLAN BUDGET SAMI-JF'!AP13:AP100000,'PLAN BUDGET SAMI-JF'!D13:D100000,SUMMARY!D20,'PLAN BUDGET SAMI-JF'!J13:J100000,SUMMARY!A20&"*") -> 0 | H20: =SUMIFS('PLAN BUDGET SAMI-JF'!AQ13:AQ100000,'PLAN BUDGET SAMI-JF'!D13:D100000,SUMMARY!D20,'PLAN BUDGET SAMI-JF'!J13:J100000,SUMMARY!A20&"*") -> 1 | I20: =SUMIFS('PLAN BUDGET SAMI-JF'!AR13:AR100000,'PLAN BUDGET SAMI-JF'!D13:D100000,SUMMARY!D20,'PLAN BUDGET SAMI-JF'!J13:J100000,SUMMARY!A20&"*") -> 0 | J20: =SUMIFS('PLAN BUDGET SAMI-JF'!AS13:AS100000,'PLAN BUDGET SAMI-JF'!D13:D100000,SUMMARY!D20,'PLAN BUDGET SAMI-JF'!J13:J100000,SUMMARY!A20&"*") -> 1 | K20: =SUMIFS('PLAN BUDGET SAMI-JF'!AT13:AT100000,'PLAN BUDGET SAMI-JF'!D13:D100000,SUMMARY!D20,'PLAN BUDGET SAMI-JF'!J13:J100000,SUMMARY!A20&"*") -> 0 | L20: =SUMIFS('PLAN BUDGET SAMI-JF'!AU13:AU100000,'PLAN BUDGET SAMI-JF'!D13:D100000,SUMMARY!D20,'PLAN BUDGET SAMI-JF'!J13:J100000,SUMMARY!A20&"*") -> 1 | M20: =SUMIFS('PLAN BUDGET SAMI-JF'!AV13:AV100000,'PLAN BUDGET SAMI-JF'!D13:D100000,SUMMARY!D20,'PLAN BUDGET SAMI-JF'!J13:J100000,SUMMARY!A20&"*") -> 0 | N20: =SUMIFS('PLAN BUDGET SAMI-JF'!AW13:AW100000,'PLAN BUDGET SAMI-JF'!D13:D100000,SUMMARY!D20,'PLAN BUDGET SAMI-JF'!J13:J100000,SUMMARY!A20&"*") -> 0 | O20: =SUMIFS('PLAN BUDGET SAMI-JF'!AX13:AX100000,'PLAN BUDGET SAMI-JF'!D13:D100000,SUMMARY!D20,'PLAN BUDGET SAMI-JF'!J13:J100000,SUMMARY!A20&"*") -> 0 | P20: =SUMIFS('PLAN BUDGET SAMI-JF'!AY13:AY100000,'PLAN BUDGET SAMI-JF'!D13:D100000,SUMMARY!D20,'PLAN BUDGET SAMI-JF'!J13:J100000,SUMMARY!A20&"*") -> 0 | Q20: =SUMIFS('PLAN BUDGET SAMI-JF'!BC13:BC100000,'PLAN BUDGET SAMI-JF'!D13:D100000,SUMMARY!D20,'PLAN BUDGET SAMI-JF'!J13:J100000,SUMMARY!A20&"*") -> 0 | R20: =SUMIFS('PLAN BUDGET SAMI-JF'!BD13:BD100000,'PLAN BUDGET SAMI-JF'!D13:D100000,SUMMARY!D20,'PLAN BUDGET SAMI-JF'!J13:J100000,SUMMARY!A20&"*") -> 1251.3767 | S20: =SUMIFS('PLAN BUDGET SAMI-JF'!BE13:BE100000,'PLAN BUDGET SAMI-JF'!D13:D100000,SUMMARY!D20,'PLAN BUDGET SAMI-JF'!J13:J100000,SUMMARY!A20&"*") -> 0 | T20: =SUMIFS('PLAN BUDGET SAMI-JF'!BF13:BF100000,'PLAN BUDGET SAMI-JF'!D13:D100000,SUMMARY!D20,'PLAN BUDGET SAMI-JF'!J13:J100000,SUMMARY!A20&"*") -> 1466.5856 | U20: =SUMIFS('PLAN BUDGET SAMI-JF'!BG13:BG100000,'PLAN BUDGET SAMI-JF'!D13:D100000,SUMMARY!D20,'PLAN BUDGET SAMI-JF'!J13:J100000,SUMMARY!A20&"*") -> 0 | V20: =SUMIFS('PLAN BUDGET SAMI-JF'!BH13:BH100000,'PLAN BUDGET SAMI-JF'!D13:D100000,SUMMARY!D20,'PLAN BUDGET SAMI-JF'!J13:J100000,SUMMARY!A20&"*") -> 1251.3767 | W20: =SUMIFS('PLAN BUDGET SAMI-JF'!BI13:BI100000,'PLAN BUDGET SAMI-JF'!D13:D100000,SUMMARY!D20,'PLAN BUDGET SAMI-JF'!J13:J100000,SUMMARY!A20&"*") -> 0 | X20: =SUMIFS('PLAN BUDGET SAMI-JF'!BJ13:BJ100000,'PLAN BUDGET SAMI-JF'!D13:D100000,SUMMARY!D20,'PLAN BUDGET SAMI-JF'!J13:J100000,SUMMARY!A20&"*") -> 1466.5856 | Y20: =SUMIFS('PLAN BUDGET SAMI-JF'!BK13:BK100000,'PLAN BUDGET SAMI-JF'!D13:D100000,SUMMARY!D20,'PLAN BUDGET SAMI-JF'!J13:J100000,SUMMARY!A20&"*") -> 0 | Z20: =SUMIFS('PLAN BUDGET SAMI-JF'!BL13:BL100000,'PLAN BUDGET SAMI-JF'!D13:D100000,SUMMARY!D20,'PLAN BUDGET SAMI-JF'!J13:J100000,SUMMARY!A20&"*") -> 0 | AA20: =SUMIFS('PLAN BUDGET SAMI-JF'!BM13:BM100000,'PLAN BUDGET SAMI-JF'!D13:D100000,SUMMARY!D20,'PLAN BUDGET SAMI-JF'!J13:J100000,SUMMARY!A20&"*") -> 0 | AB20: =SUMIFS('PLAN BUDGET SAMI-JF'!BN13:BN100000,'PLAN BUDGET SAMI-JF'!D13:D100000,SUMMARY!D20,'PLAN BUDGET SAMI-JF'!J13:J100000,SUMMARY!A20&"*") -> 0 | AC20: =SUM(E20:P20) -> 4 | AD20: =SUM(Q20:AB20) -> 5435.9247 | AF20: 30 | AG20: 35152.443 | AH20: =IFERROR((AC20-AF20)/AF20,1) -> -0.86666667 | AI20: =IFERROR((AD20-AG20)/AG20,1) -> -0.84536139 | AJ20: ada training eksternal di term 84 ada tapi di tem 85 tidak ada
A21: RUTIN | D21: FORM | E21: =SUMIFS('PLAN BUDGET SAMI-JF'!AN13:AN100000,'PLAN BUDGET SAMI-JF'!D13:D100000,SUMMARY!D21,'PLAN BUDGET SAMI-JF'!J13:J100000,SUMMARY!A21&"*") -> 0 | F21: =SUMIFS('PLAN BUDGET SAMI-JF'!AO13:AO100000,'PLAN BUDGET SAMI-JF'!D13:D100000,SUMMARY!D21,'PLAN BUDGET SAMI-JF'!J13:J100000,SUMMARY!A21&"*") -> 0 | G21: =SUMIFS('PLAN BUDGET SAMI-JF'!AP13:AP100000,'PLAN BUDGET SAMI-JF'!D13:D100000,SUMMARY!D21,'PLAN BUDGET SAMI-JF'!J13:J100000,SUMMARY!A21&"*") -> 0 | H21: =SUMIFS('PLAN BUDGET SAMI-JF'!AQ13:AQ100000,'PLAN BUDGET SAMI-JF'!D13:D100000,SUMMARY!D21,'PLAN BUDGET SAMI-JF'!J13:J100000,SUMMARY!A21&"*") -> 1 | I21: =SUMIFS('PLAN BUDGET SAMI-JF'!AR13:AR100000,'PLAN BUDGET SAMI-JF'!D13:D100000,SUMMARY!D21,'PLAN BUDGET SAMI-JF'!J13:J100000,SUMMARY!A21&"*") -> 0 | J21: =SUMIFS('PLAN BUDGET SAMI-JF'!AS13:AS100000,'PLAN BUDGET SAMI-JF'!D13:D100000,SUMMARY!D21,'PLAN BUDGET SAMI-JF'!J13:J100000,SUMMARY!A21&"*") -> 0 | K21: =SUMIFS('PLAN BUDGET SAMI-JF'!AT13:AT100000,'PLAN BUDGET SAMI-JF'!D13:D100000,SUMMARY!D21,'PLAN BUDGET SAMI-JF'!J13:J100000,SUMMARY!A21&"*") -> 0 | L21: =SUMIFS('PLAN BUDGET SAMI-JF'!AU13:AU100000,'PLAN BUDGET SAMI-JF'!D13:D100000,SUMMARY!D21,'PLAN BUDGET SAMI-JF'!J13:J100000,SUMMARY!A21&"*") -> 0 | M21: =SUMIFS('PLAN BUDGET SAMI-JF'!AV13:AV100000,'PLAN BUDGET SAMI-JF'!D13:D100000,SUMMARY!D21,'PLAN BUDGET SAMI-JF'!J13:J100000,SUMMARY!A21&"*") -> 0 | N21: =SUMIFS('PLAN BUDGET SAMI-JF'!AW13:AW100000,'PLAN BUDGET SAMI-JF'!D13:D100000,SUMMARY!D21,'PLAN BUDGET SAMI-JF'!J13:J100000,SUMMARY!A21&"*") -> 1 | O21: =SUMIFS('PLAN BUDGET SAMI-JF'!AX13:AX100000,'PLAN BUDGET SAMI-JF'!D13:D100000,SUMMARY!D21,'PLAN BUDGET SAMI-JF'!J13:J100000,SUMMARY!A21&"*") -> 0 | P21: =SUMIFS('PLAN BUDGET SAMI-JF'!AY13:AY100000,'PLAN BUDGET SAMI-JF'!D13:D100000,SUMMARY!D21,'PLAN BUDGET SAMI-JF'!J13:J100000,SUMMARY!A21&"*") -> 0 | Q21: =SUMIFS('PLAN BUDGET SAMI-JF'!BC13:BC100000,'PLAN BUDGET SAMI-JF'!D13:D100000,SUMMARY!D21,'PLAN BUDGET SAMI-JF'!J13:J100000,SUMMARY!A21&"*") -> 0 | R21: =SUMIFS('PLAN BUDGET SAMI-JF'!BD13:BD100000,'PLAN BUDGET SAMI-JF'!D13:D100000,SUMMARY!D21,'PLAN BUDGET SAMI-JF'!J13:J100000,SUMMARY!A21&"*") -> 0 | S21: =SUMIFS('PLAN BUDGET SAMI-JF'!BE13:BE100000,'PLAN BUDGET SAMI-JF'!D13:D100000,SUMMARY!D21,'PLAN BUDGET SAMI-JF'!J13:J100000,SUMMARY!A21&"*") -> 0 | T21: =SUMIFS('PLAN BUDGET SAMI-JF'!BF13:BF100000,'PLAN BUDGET SAMI-JF'!D13:D100000,SUMMARY!D21,'PLAN BUDGET SAMI-JF'!J13:J100000,SUMMARY!A21&"*") -> 12.65935 | U21: =SUMIFS('PLAN BUDGET SAMI-JF'!BG13:BG100000,'PLAN BUDGET SAMI-JF'!D13:D100000,SUMMARY!D21,'PLAN BUDGET SAMI-JF'!J13:J100000,SUMMARY!A21&"*") -> 0 | V21: =SUMIFS('PLAN BUDGET SAMI-JF'!BH13:BH100000,'PLAN BUDGET SAMI-JF'!D13:D100000,SUMMARY!D21,'PLAN BUDGET SAMI-JF'!J13:J100000,SUMMARY!A21&"*") -> 0 | W21: =SUMIFS('PLAN BUDGET SAMI-JF'!BI13:BI100000,'PLAN BUDGET SAMI-JF'!D13:D100000,SUMMARY!D21,'PLAN BUDGET SAMI-JF'!J13:J100000,SUMMARY!A21&"*") -> 0 | X21: =SUMIFS('PLAN BUDGET SAMI-JF'!BJ13:BJ100000,'PLAN BUDGET SAMI-JF'!D13:D100000,SUMMARY!D21,'PLAN BUDGET SAMI-JF'!J13:J100000,SUMMARY!A21&"*") -> 0 | Y21: =SUMIFS('PLAN BUDGET SAMI-JF'!BK13:BK100000,'PLAN BUDGET SAMI-JF'!D13:D100000,SUMMARY!D21,'PLAN BUDGET SAMI-JF'!J13:J100000,SUMMARY!A21&"*") -> 0 | Z21: =SUMIFS('PLAN BUDGET SAMI-JF'!BL13:BL100000,'PLAN BUDGET SAMI-JF'!D13:D100000,SUMMARY!D21,'PLAN BUDGET SAMI-JF'!J13:J100000,SUMMARY!A21&"*") -> 12.65935 | AA21: =SUMIFS('PLAN BUDGET SAMI-JF'!BM13:BM100000,'PLAN BUDGET SAMI-JF'!D13:D100000,SUMMARY!D21,'PLAN BUDGET SAMI-JF'!J13:J100000,SUMMARY!A21&"*") -> 0 | AB21: =SUMIFS('PLAN BUDGET SAMI-JF'!BN13:BN100000,'PLAN BUDGET SAMI-JF'!D13:D100000,SUMMARY!D21,'PLAN BUDGET SAMI-JF'!J13:J100000,SUMMARY!A21&"*") -> 0 | AC21: =SUM(E21:P21) -> 2 | AD21: =SUM(Q21:AB21) -> 25.318699 | AF21: 13 | AG21: 94.628638 | AH21: =IFERROR((AC21-AF21)/AF21,1) -> -0.84615385 | AI21: =IFERROR((AD21-AG21)/AG21,1) -> -0.73244147
A22: RUTIN | D22: STAND TABLET | E22: =SUMIFS('PLAN BUDGET SAMI-JF'!AN13:AN100000,'PLAN BUDGET SAMI-JF'!D13:D100000,SUMMARY!D22,'PLAN BUDGET SAMI-JF'!J13:J100000,SUMMARY!A22&"*") -> 0 | F22: =SUMIFS('PLAN BUDGET SAMI-JF'!AO13:AO100000,'PLAN BUDGET SAMI-JF'!D13:D100000,SUMMARY!D22,'PLAN BUDGET SAMI-JF'!J13:J100000,SUMMARY!A22&"*") -> 20 | G22: =SUMIFS('PLAN BUDGET SAMI-JF'!AP13:AP100000,'PLAN BUDGET SAMI-JF'!D13:D100000,SUMMARY!D22,'PLAN BUDGET SAMI-JF'!J13:J100000,SUMMARY!A22&"*") -> 0 | H22: =SUMIFS('PLAN BUDGET SAMI-JF'!AQ13:AQ100000,'PLAN BUDGET SAMI-JF'!D13:D100000,SUMMARY!D22,'PLAN BUDGET SAMI-JF'!J13:J100000,SUMMARY!A22&"*") -> 0 | I22: =SUMIFS('PLAN BUDGET SAMI-JF'!AR13:AR100000,'PLAN BUDGET SAMI-JF'!D13:D100000,SUMMARY!D22,'PLAN BUDGET SAMI-JF'!J13:J100000,SUMMARY!A22&"*") -> 0 | J22: =SUMIFS('PLAN BUDGET SAMI-JF'!AS13:AS100000,'PLAN BUDGET SAMI-JF'!D13:D100000,SUMMARY!D22,'PLAN BUDGET SAMI-JF'!J13:J100000,SUMMARY!A22&"*") -> 0 | K22: =SUMIFS('PLAN BUDGET SAMI-JF'!AT13:AT100000,'PLAN BUDGET SAMI-JF'!D13:D100000,SUMMARY!D22,'PLAN BUDGET SAMI-JF'!J13:J100000,SUMMARY!A22&"*") -> 0 | L22: =SUMIFS('PLAN BUDGET SAMI-JF'!AU13:AU100000,'PLAN BUDGET SAMI-JF'!D13:D100000,SUMMARY!D22,'PLAN BUDGET SAMI-JF'!J13:J100000,SUMMARY!A22&"*") -> 0 | M22: =SUMIFS('PLAN BUDGET SAMI-JF'!AV13:AV100000,'PLAN BUDGET SAMI-JF'!D13:D100000,SUMMARY!D22,'PLAN BUDGET SAMI-JF'!J13:J100000,SUMMARY!A22&"*") -> 0 | N22: =SUMIFS('PLAN BUDGET SAMI-JF'!AW13:AW100000,'PLAN BUDGET SAMI-JF'!D13:D100000,SUMMARY!D22,'PLAN BUDGET SAMI-JF'!J13:J100000,SUMMARY!A22&"*") -> 0 | O22: =SUMIFS('PLAN BUDGET SAMI-JF'!AX13:AX100000,'PLAN BUDGET SAMI-JF'!D13:D100000,SUMMARY!D22,'PLAN BUDGET SAMI-JF'!J13:J100000,SUMMARY!A22&"*") -> 0 | P22: =SUMIFS('PLAN BUDGET SAMI-JF'!AY13:AY100000,'PLAN BUDGET SAMI-JF'!D13:D100000,SUMMARY!D22,'PLAN BUDGET SAMI-JF'!J13:J100000,SUMMARY!A22&"*") -> 0 | Q22: =SUMIFS('PLAN BUDGET SAMI-JF'!BC13:BC100000,'PLAN BUDGET SAMI-JF'!D13:D100000,SUMMARY!D22,'PLAN BUDGET SAMI-JF'!J13:J100000,SUMMARY!A22&"*") -> 0 | R22: =SUMIFS('PLAN BUDGET SAMI-JF'!BD13:BD100000,'PLAN BUDGET SAMI-JF'!D13:D100000,SUMMARY!D22,'PLAN BUDGET SAMI-JF'!J13:J100000,SUMMARY!A22&"*") -> 1164.6602 | S22: =SUMIFS('PLAN BUDGET SAMI-JF'!BE13:BE100000,'PLAN BUDGET SAMI-JF'!D13:D100000,SUMMARY!D22,'PLAN BUDGET SAMI-JF'!J13:J100000,SUMMARY!A22&"*") -> 0 | T22: =SUMIFS('PLAN BUDGET SAMI-JF'!BF13:BF100000,'PLAN BUDGET SAMI-JF'!D13:D100000,SUMMARY!D22,'PLAN BUDGET SAMI-JF'!J13:J100000,SUMMARY!A22&"*") -> 0 | U22: =SUMIFS('PLAN BUDGET SAMI-JF'!BG13:BG100000,'PLAN BUDGET SAMI-JF'!D13:D100000,SUMMARY!D22,'PLAN BUDGET SAMI-JF'!J13:J100000,SUMMARY!A22&"*") -> 0 | V22: =SUMIFS('PLAN BUDGET SAMI-JF'!BH13:BH100000,'PLAN BUDGET SAMI-JF'!D13:D100000,SUMMARY!D22,'PLAN BUDGET SAMI-JF'!J13:J100000,SUMMARY!A22&"*") -> 0 | W22: =SUMIFS('PLAN BUDGET SAMI-JF'!BI13:BI100000,'PLAN BUDGET SAMI-JF'!D13:D100000,SUMMARY!D22,'PLAN BUDGET SAMI-JF'!J13:J100000,SUMMARY!A22&"*") -> 0 | X22: =SUMIFS('PLAN BUDGET SAMI-JF'!BJ13:BJ100000,'PLAN BUDGET SAMI-JF'!D13:D100000,SUMMARY!D22,'PLAN BUDGET SAMI-JF'!J13:J100000,SUMMARY!A22&"*") -> 0 | Y22: =SUMIFS('PLAN BUDGET SAMI-JF'!BK13:BK100000,'PLAN BUDGET SAMI-JF'!D13:D100000,SUMMARY!D22,'PLAN BUDGET SAMI-JF'!J13:J100000,SUMMARY!A22&"*") -> 0 | Z22: =SUMIFS('PLAN BUDGET SAMI-JF'!BL13:BL100000,'PLAN BUDGET SAMI-JF'!D13:D100000,SUMMARY!D22,'PLAN BUDGET SAMI-JF'!J13:J100000,SUMMARY!A22&"*") -> 0 | AA22: =SUMIFS('PLAN BUDGET SAMI-JF'!BM13:BM100000,'PLAN BUDGET SAMI-JF'!D13:D100000,SUMMARY!D22,'PLAN BUDGET SAMI-JF'!J13:J100000,SUMMARY!A22&"*") -> 0 | AB22: =SUMIFS('PLAN BUDGET SAMI-JF'!BN13:BN100000,'PLAN BUDGET SAMI-JF'!D13:D100000,SUMMARY!D22,'PLAN BUDGET SAMI-JF'!J13:J100000,SUMMARY!A22&"*") -> 0 | AC22: =SUM(E22:P22) -> 20 | AD22: =SUM(Q22:AB22) -> 1164.6602 | AF22: 0 | AG22: 0 | AH22: =IFERROR((AC22-AF22)/AF22,1) -> 1 | AI22: =IFERROR((AD22-AG22)/AG22,1) -> 1 | AJ22: Budget di Term 84 tidak ada, sedangkan di Term 85 ada.
A23: RUTIN | D23: PLASTIK ID CARD | E23: =SUMIFS('PLAN BUDGET SAMI-JF'!AN13:AN100000,'PLAN BUDGET SAMI-JF'!D13:D100000,SUMMARY!D23,'PLAN BUDGET SAMI-JF'!J13:J100000,SUMMARY!A23&"*") -> 0 | F23: =SUMIFS('PLAN BUDGET SAMI-JF'!AO13:AO100000,'PLAN BUDGET SAMI-JF'!D13:D100000,SUMMARY!D23,'PLAN BUDGET SAMI-JF'!J13:J100000,SUMMARY!A23&"*") -> 560 | G23: =SUMIFS('PLAN BUDGET SAMI-JF'!AP13:AP100000,'PLAN BUDGET SAMI-JF'!D13:D100000,SUMMARY!D23,'PLAN BUDGET SAMI-JF'!J13:J100000,SUMMARY!A23&"*") -> 0 | H23: =SUMIFS('PLAN BUDGET SAMI-JF'!AQ13:AQ100000,'PLAN BUDGET SAMI-JF'!D13:D100000,SUMMARY!D23,'PLAN BUDGET SAMI-JF'!J13:J100000,SUMMARY!A23&"*") -> 0 | I23: =SUMIFS('PLAN BUDGET SAMI-JF'!AR13:AR100000,'PLAN BUDGET SAMI-JF'!D13:D100000,SUMMARY!D23,'PLAN BUDGET SAMI-JF'!J13:J100000,SUMMARY!A23&"*") -> 552 | J23: =SUMIFS('PLAN BUDGET SAMI-JF'!AS13:AS100000,'PLAN BUDGET SAMI-JF'!D13:D100000,SUMMARY!D23,'PLAN BUDGET SAMI-JF'!J13:J100000,SUMMARY!A23&"*") -> 0 | K23: =SUMIFS('PLAN BUDGET SAMI-JF'!AT13:AT100000,'PLAN BUDGET SAMI-JF'!D13:D100000,SUMMARY!D23,'PLAN BUDGET SAMI-JF'!J13:J100000,SUMMARY!A23&"*") -> 0 | L23: =SUMIFS('PLAN BUDGET SAMI-JF'!AU13:AU100000,'PLAN BUDGET SAMI-JF'!D13:D100000,SUMMARY!D23,'PLAN BUDGET SAMI-JF'!J13:J100000,SUMMARY!A23&"*") -> 0 | M23: =SUMIFS('PLAN BUDGET SAMI-JF'!AV13:AV100000,'PLAN BUDGET SAMI-JF'!D13:D100000,SUMMARY!D23,'PLAN BUDGET SAMI-JF'!J13:J100000,SUMMARY!A23&"*") -> 300 | N23: =SUMIFS('PLAN BUDGET SAMI-JF'!AW13:AW100000,'PLAN BUDGET SAMI-JF'!D13:D100000,SUMMARY!D23,'PLAN BUDGET SAMI-JF'!J13:J100000,SUMMARY!A23&"*") -> 0 | O23: =SUMIFS('PLAN BUDGET SAMI-JF'!AX13:AX100000,'PLAN BUDGET SAMI-JF'!D13:D100000,SUMMARY!D23,'PLAN BUDGET SAMI-JF'!J13:J100000,SUMMARY!A23&"*") -> 0 | P23: =SUMIFS('PLAN BUDGET SAMI-JF'!AY13:AY100000,'PLAN BUDGET SAMI-JF'!D13:D100000,SUMMARY!D23,'PLAN BUDGET SAMI-JF'!J13:J100000,SUMMARY!A23&"*") -> 300 | Q23: =SUMIFS('PLAN BUDGET SAMI-JF'!BC13:BC100000,'PLAN BUDGET SAMI-JF'!D13:D100000,SUMMARY!D23,'PLAN BUDGET SAMI-JF'!J13:J100000,SUMMARY!A23&"*") -> 0 | R23: =SUMIFS('PLAN BUDGET SAMI-JF'!BD13:BD100000,'PLAN BUDGET SAMI-JF'!D13:D100000,SUMMARY!D23,'PLAN BUDGET SAMI-JF'!J13:J100000,SUMMARY!A23&"*") -> 59.195119 | S23: =SUMIFS('PLAN BUDGET SAMI-JF'!BE13:BE100000,'PLAN BUDGET SAMI-JF'!D13:D100000,SUMMARY!D23,'PLAN BUDGET SAMI-JF'!J13:J100000,SUMMARY!A23&"*") -> 0 | T23: =SUMIFS('PLAN BUDGET SAMI-JF'!BF13:BF100000,'PLAN BUDGET SAMI-JF'!D13:D100000,SUMMARY!D23,'PLAN BUDGET SAMI-JF'!J13:J100000,SUMMARY!A23&"*") -> 0 | U23: =SUMIFS('PLAN BUDGET SAMI-JF'!BG13:BG100000,'PLAN BUDGET SAMI-JF'!D13:D100000,SUMMARY!D23,'PLAN BUDGET SAMI-JF'!J13:J100000,SUMMARY!A23&"*") -> 58.349474 | V23: =SUMIFS('PLAN BUDGET SAMI-JF'!BH13:BH100000,'PLAN BUDGET SAMI-JF'!D13:D100000,SUMMARY!D23,'PLAN BUDGET SAMI-JF'!J13:J100000,SUMMARY!A23&"*") -> 0 | W23: =SUMIFS('PLAN BUDGET SAMI-JF'!BI13:BI100000,'PLAN BUDGET SAMI-JF'!D13:D100000,SUMMARY!D23,'PLAN BUDGET SAMI-JF'!J13:J100000,SUMMARY!A23&"*") -> 0 | X23: =SUMIFS('PLAN BUDGET SAMI-JF'!BJ13:BJ100000,'PLAN BUDGET SAMI-JF'!D13:D100000,SUMMARY!D23,'PLAN BUDGET SAMI-JF'!J13:J100000,SUMMARY!A23&"*") -> 0 | Y23: =SUMIFS('PLAN BUDGET SAMI-JF'!BK13:BK100000,'PLAN BUDGET SAMI-JF'!D13:D100000,SUMMARY!D23,'PLAN BUDGET SAMI-JF'!J13:J100000,SUMMARY!A23&"*") -> 31.711671 | Z23: =SUMIFS('PLAN BUDGET SAMI-JF'!BL13:BL100000,'PLAN BUDGET SAMI-JF'!D13:D100000,SUMMARY!D23,'PLAN BUDGET SAMI-JF'!J13:J100000,SUMMARY!A23&"*") -> 0 | AA23: =SUMIFS('PLAN BUDGET SAMI-JF'!BM13:BM100000,'PLAN BUDGET SAMI-JF'!D13:D100000,SUMMARY!D23,'PLAN BUDGET SAMI-JF'!J13:J100000,SUMMARY!A23&"*") -> 0 | AB23: =SUMIFS('PLAN BUDGET SAMI-JF'!BN13:BN100000,'PLAN BUDGET SAMI-JF'!D13:D100000,SUMMARY!D23,'PLAN BUDGET SAMI-JF'!J13:J100000,SUMMARY!A23&"*") -> 31.711671 | AC23: =SUM(E23:P23) -> 1712 | AD23: =SUM(Q23:AB23) -> 180.96793 | AF23: 1971 | AG23: 186.01401 | AH23: =IFERROR((AC23-AF23)/AF23,1) -> -0.13140538 | AI23: =IFERROR((AD23-AG23)/AG23,1) -> -0.027127419
A24: RUTIN | D24: KERTAS | E24: =SUMIFS('PLAN BUDGET SAMI-JF'!AN13:AN100000,'PLAN BUDGET SAMI-JF'!D13:D100000,SUMMARY!D24,'PLAN BUDGET SAMI-JF'!J13:J100000,SUMMARY!A24&"*") -> 0 | F24: =SUMIFS('PLAN BUDGET SAMI-JF'!AO13:AO100000,'PLAN BUDGET SAMI-JF'!D13:D100000,SUMMARY!D24,'PLAN BUDGET SAMI-JF'!J13:J100000,SUMMARY!A24&"*") -> 1 | G24: =SUMIFS('PLAN BUDGET SAMI-JF'!AP13:AP100000,'PLAN BUDGET SAMI-JF'!D13:D100000,SUMMARY!D24,'PLAN BUDGET SAMI-JF'!J13:J100000,SUMMARY!A24&"*") -> 0 | H24: =SUMIFS('PLAN BUDGET SAMI-JF'!AQ13:AQ100000,'PLAN BUDGET SAMI-JF'!D13:D100000,SUMMARY!D24,'PLAN BUDGET SAMI-JF'!J13:J100000,SUMMARY!A24&"*") -> 0 | I24: =SUMIFS('PLAN BUDGET SAMI-JF'!AR13:AR100000,'PLAN BUDGET SAMI-JF'!D13:D100000,SUMMARY!D24,'PLAN BUDGET SAMI-JF'!J13:J100000,SUMMARY!A24&"*") -> 1 | J24: =SUMIFS('PLAN BUDGET SAMI-JF'!AS13:AS100000,'PLAN BUDGET SAMI-JF'!D13:D100000,SUMMARY!D24,'PLAN BUDGET SAMI-JF'!J13:J100000,SUMMARY!A24&"*") -> 0 | K24: =SUMIFS('PLAN BUDGET SAMI-JF'!AT13:AT100000,'PLAN BUDGET SAMI-JF'!D13:D100000,SUMMARY!D24,'PLAN BUDGET SAMI-JF'!J13:J100000,SUMMARY!A24&"*") -> 0 | L24: =SUMIFS('PLAN BUDGET SAMI-JF'!AU13:AU100000,'PLAN BUDGET SAMI-JF'!D13:D100000,SUMMARY!D24,'PLAN BUDGET SAMI-JF'!J13:J100000,SUMMARY!A24&"*") -> 1 | M24: =SUMIFS('PLAN BUDGET SAMI-JF'!AV13:AV100000,'PLAN BUDGET SAMI-JF'!D13:D100000,SUMMARY!D24,'PLAN BUDGET SAMI-JF'!J13:J100000,SUMMARY!A24&"*") -> 0 | N24: =SUMIFS('PLAN BUDGET SAMI-JF'!AW13:AW100000,'PLAN BUDGET SAMI-JF'!D13:D100000,SUMMARY!D24,'PLAN BUDGET SAMI-JF'!J13:J100000,SUMMARY!A24&"*") -> 0 | O24: =SUMIFS('PLAN BUDGET SAMI-JF'!AX13:AX100000,'PLAN BUDGET SAMI-JF'!D13:D100000,SUMMARY!D24,'PLAN BUDGET SAMI-JF'!J13:J100000,SUMMARY!A24&"*") -> 1 | P24: =SUMIFS('PLAN BUDGET SAMI-JF'!AY13:AY100000,'PLAN BUDGET SAMI-JF'!D13:D100000,SUMMARY!D24,'PLAN BUDGET SAMI-JF'!J13:J100000,SUMMARY!A24&"*") -> 0 | Q24: =SUMIFS('PLAN BUDGET SAMI-JF'!BC13:BC100000,'PLAN BUDGET SAMI-JF'!D13:D100000,SUMMARY!D24,'PLAN BUDGET SAMI-JF'!J13:J100000,SUMMARY!A24&"*") -> 0 | R24: =SUMIFS('PLAN BUDGET SAMI-JF'!BD13:BD100000,'PLAN BUDGET SAMI-JF'!D13:D100000,SUMMARY!D24,'PLAN BUDGET SAMI-JF'!J13:J100000,SUMMARY!A24&"*") -> 2.2153862 | S24: =SUMIFS('PLAN BUDGET SAMI-JF'!BE13:BE100000,'PLAN BUDGET SAMI-JF'!D13:D100000,SUMMARY!D24,'PLAN BUDGET SAMI-JF'!J13:J100000,SUMMARY!A24&"*") -> 0 | T24: =SUMIFS('PLAN BUDGET SAMI-JF'!BF13:BF100000,'PLAN BUDGET SAMI-JF'!D13:D100000,SUMMARY!D24,'PLAN BUDGET SAMI-JF'!J13:J100000,SUMMARY!A24&"*") -> 0 | U24: =SUMIFS('PLAN BUDGET SAMI-JF'!BG13:BG100000,'PLAN BUDGET SAMI-JF'!D13:D100000,SUMMARY!D24,'PLAN BUDGET SAMI-JF'!J13:J100000,SUMMARY!A24&"*") -> 2.2153862 | V24: =SUMIFS('PLAN BUDGET SAMI-JF'!BH13:BH100000,'PLAN BUDGET SAMI-JF'!D13:D100000,SUMMARY!D24,'PLAN BUDGET SAMI-JF'!J13:J100000,SUMMARY!A24&"*") -> 0 | W24: =SUMIFS('PLAN BUDGET SAMI-JF'!BI13:BI100000,'PLAN BUDGET SAMI-JF'!D13:D100000,SUMMARY!D24,'PLAN BUDGET SAMI-JF'!J13:J100000,SUMMARY!A24&"*") -> 0 | X24: =SUMIFS('PLAN BUDGET SAMI-JF'!BJ13:BJ100000,'PLAN BUDGET SAMI-JF'!D13:D100000,SUMMARY!D24,'PLAN BUDGET SAMI-JF'!J13:J100000,SUMMARY!A24&"*") -> 2.2153862 | Y24: =SUMIFS('PLAN BUDGET SAMI-JF'!BK13:BK100000,'PLAN BUDGET SAMI-JF'!D13:D100000,SUMMARY!D24,'PLAN BUDGET SAMI-JF'!J13:J100000,SUMMARY!A24&"*") -> 0 | Z24: =SUMIFS('PLAN BUDGET SAMI-JF'!BL13:BL100000,'PLAN BUDGET SAMI-JF'!D13:D100000,SUMMARY!D24,'PLAN BUDGET SAMI-JF'!J13:J100000,SUMMARY!A24&"*") -> 0 | AA24: =SUMIFS('PLAN BUDGET SAMI-JF'!BM13:BM100000,'PLAN BUDGET SAMI-JF'!D13:D100000,SUMMARY!D24,'PLAN BUDGET SAMI-JF'!J13:J100000,SUMMARY!A24&"*") -> 2.2153862 | AB24: =SUMIFS('PLAN BUDGET SAMI-JF'!BN13:BN100000,'PLAN BUDGET SAMI-JF'!D13:D100000,SUMMARY!D24,'PLAN BUDGET SAMI-JF'!J13:J100000,SUMMARY!A24&"*") -> 0 | AC24: =SUM(E24:P24) -> 4 | AD24: =SUM(Q24:AB24) -> 8.8615447 | AF24: 4 | AG24: 22.470345 | AH24: =IFERROR((AC24-AF24)/AF24,1) -> 0 | AI24: =IFERROR((AD24-AG24)/AG24,1) -> -0.6056338
A25: RUTIN | D25: SELANG | E25: =SUMIFS('PLAN BUDGET SAMI-JF'!AN13:AN100000,'PLAN BUDGET SAMI-JF'!D13:D100000,SUMMARY!D25,'PLAN BUDGET SAMI-JF'!J13:J100000,SUMMARY!A25&"*") -> 1 | F25: =SUMIFS('PLAN BUDGET SAMI-JF'!AO13:AO100000,'PLAN BUDGET SAMI-JF'!D13:D100000,SUMMARY!D25,'PLAN BUDGET SAMI-JF'!J13:J100000,SUMMARY!A25&"*") -> 0 | G25: =SUMIFS('PLAN BUDGET SAMI-JF'!AP13:AP100000,'PLAN BUDGET SAMI-JF'!D13:D100000,SUMMARY!D25,'PLAN BUDGET SAMI-JF'!J13:J100000,SUMMARY!A25&"*") -> 0 | H25: =SUMIFS('PLAN BUDGET SAMI-JF'!AQ13:AQ100000,'PLAN BUDGET SAMI-JF'!D13:D100000,SUMMARY!D25,'PLAN BUDGET SAMI-JF'!J13:J100000,SUMMARY!A25&"*") -> 0 | I25: =SUMIFS('PLAN BUDGET SAMI-JF'!AR13:AR100000,'PLAN BUDGET SAMI-JF'!D13:D100000,SUMMARY!D25,'PLAN BUDGET SAMI-JF'!J13:J100000,SUMMARY!A25&"*") -> 0 | J25: =SUMIFS('PLAN BUDGET SAMI-JF'!AS13:AS100000,'PLAN BUDGET SAMI-JF'!D13:D100000,SUMMARY!D25,'PLAN BUDGET SAMI-JF'!J13:J100000,SUMMARY!A25&"*") -> 0 | K25: =SUMIFS('PLAN BUDGET SAMI-JF'!AT13:AT100000,'PLAN BUDGET SAMI-JF'!D13:D100000,SUMMARY!D25,'PLAN BUDGET SAMI-JF'!J13:J100000,SUMMARY!A25&"*") -> 0 | L25: =SUMIFS('PLAN BUDGET SAMI-JF'!AU13:AU100000,'PLAN BUDGET SAMI-JF'!D13:D100000,SUMMARY!D25,'PLAN BUDGET SAMI-JF'!J13:J100000,SUMMARY!A25&"*") -> 0 | M25: =SUMIFS('PLAN BUDGET SAMI-JF'!AV13:AV100000,'PLAN BUDGET SAMI-JF'!D13:D100000,SUMMARY!D25,'PLAN BUDGET SAMI-JF'!J13:J100000,SUMMARY!A25&"*") -> 0 | N25: =SUMIFS('PLAN BUDGET SAMI-JF'!AW13:AW100000,'PLAN BUDGET SAMI-JF'!D13:D100000,SUMMARY!D25,'PLAN BUDGET SAMI-JF'!J13:J100000,SUMMARY!A25&"*") -> 0 | O25: =SUMIFS('PLAN BUDGET SAMI-JF'!AX13:AX100000,'PLAN BUDGET SAMI-JF'!D13:D100000,SUMMARY!D25,'PLAN BUDGET SAMI-JF'!J13:J100000,SUMMARY!A25&"*") -> 0 | P25: =SUMIFS('PLAN BUDGET SAMI-JF'!AY13:AY100000,'PLAN BUDGET SAMI-JF'!D13:D100000,SUMMARY!D25,'PLAN BUDGET SAMI-JF'!J13:J100000,SUMMARY!A25&"*") -> 0 | Q25: =SUMIFS('PLAN BUDGET SAMI-JF'!BC13:BC100000,'PLAN BUDGET SAMI-JF'!D13:D100000,SUMMARY!D25,'PLAN BUDGET SAMI-JF'!J13:J100000,SUMMARY!A25&"*") -> 110.76931 | R25: =SUMIFS('PLAN BUDGET SAMI-JF'!BD13:BD100000,'PLAN BUDGET SAMI-JF'!D13:D100000,SUMMARY!D25,'PLAN BUDGET SAMI-JF'!J13:J100000,SUMMARY!A25&"*") -> 0 | S25: =SUMIFS('PLAN BUDGET SAMI-JF'!BE13:BE100000,'PLAN BUDGET SAMI-JF'!D13:D100000,SUMMARY!D25,'PLAN BUDGET SAMI-JF'!J13:J100000,SUMMARY!A25&"*") -> 0 | T25: =SUMIFS('PLAN BUDGET SAMI-JF'!BF13:BF100000,'PLAN BUDGET SAMI-JF'!D13:D100000,SUMMARY!D25,'PLAN BUDGET SAMI-JF'!J13:J100000,SUMMARY!A25&"*") -> 0 | U25: =SUMIFS('PLAN BUDGET SAMI-JF'!BG13:BG100000,'PLAN BUDGET SAMI-JF'!D13:D100000,SUMMARY!D25,'PLAN BUDGET SAMI-JF'!J13:J100000,SUMMARY!A25&"*") -> 0 | V25: =SUMIFS('PLAN BUDGET SAMI-JF'!BH13:BH100000,'PLAN BUDGET SAMI-JF'!D13:D100000,SUMMARY!D25,'PLAN BUDGET SAMI-JF'!J13:J100000,SUMMARY!A25&"*") -> 0 | W25: =SUMIFS('PLAN BUDGET SAMI-JF'!BI13:BI100000,'PLAN BUDGET SAMI-JF'!D13:D100000,SUMMARY!D25,'PLAN BUDGET SAMI-JF'!J13:J100000,SUMMARY!A25&"*") -> 0 | X25: =SUMIFS('PLAN BUDGET SAMI-JF'!BJ13:BJ100000,'PLAN BUDGET SAMI-JF'!D13:D100000,SUMMARY!D25,'PLAN BUDGET SAMI-JF'!J13:J100000,SUMMARY!A25&"*") -> 0 | Y25: =SUMIFS('PLAN BUDGET SAMI-JF'!BK13:BK100000,'PLAN BUDGET SAMI-JF'!D13:D100000,SUMMARY!D25,'PLAN BUDGET SAMI-JF'!J13:J100000,SUMMARY!A25&"*") -> 0 | Z25: =SUMIFS('PLAN BUDGET SAMI-JF'!BL13:BL100000,'PLAN BUDGET SAMI-JF'!D13:D100000,SUMMARY!D25,'PLAN BUDGET SAMI-JF'!J13:J100000,SUMMARY!A25&"*") -> 0 | AA25: =SUMIFS('PLAN BUDGET SAMI-JF'!BM13:BM100000,'PLAN BUDGET SAMI-JF'!D13:D100000,SUMMARY!D25,'PLAN BUDGET SAMI-JF'!J13:J100000,SUMMARY!A25&"*") -> 0 | AB25: =SUMIFS('PLAN BUDGET SAMI-JF'!BN13:BN100000,'PLAN BUDGET SAMI-JF'!D13:D100000,SUMMARY!D25,'PLAN BUDGET SAMI-JF'!J13:J100000,SUMMARY!A25&"*") -> 0 | AC25: =SUM(E25:P25) -> 1 | AD25: =SUM(Q25:AB25) -> 110.76931 | AF25: 0 | AG25: 0 | AH25: =IFERROR((AC25-AF25)/AF25,1) -> 1 | AI25: =IFERROR((AD25-AG25)/AG25,1) -> 1 | AJ25: Budget di Term 84 tidak ada, sedangkan di Term 85 ada.
A26: INSIDENTAL | D26: BIAYA PROSES VISA | E26: =SUMIFS('PLAN BUDGET SAMI-JF'!AN13:AN100000,'PLAN BUDGET SAMI-JF'!D13:D100000,SUMMARY!D26,'PLAN BUDGET SAMI-JF'!J13:J100000,SUMMARY!A26&"*") -> 0 | F26: =SUMIFS('PLAN BUDGET SAMI-JF'!AO13:AO100000,'PLAN BUDGET SAMI-JF'!D13:D100000,SUMMARY!D26,'PLAN BUDGET SAMI-JF'!J13:J100000,SUMMARY!A26&"*") -> 0 | G26: =SUMIFS('PLAN BUDGET SAMI-JF'!AP13:AP100000,'PLAN BUDGET SAMI-JF'!D13:D100000,SUMMARY!D26,'PLAN BUDGET SAMI-JF'!J13:J100000,SUMMARY!A26&"*") -> 0 | H26: =SUMIFS('PLAN BUDGET SAMI-JF'!AQ13:AQ100000,'PLAN BUDGET SAMI-JF'!D13:D100000,SUMMARY!D26,'PLAN BUDGET SAMI-JF'!J13:J100000,SUMMARY!A26&"*") -> 0 | I26: =SUMIFS('PLAN BUDGET SAMI-JF'!AR13:AR100000,'PLAN BUDGET SAMI-JF'!D13:D100000,SUMMARY!D26,'PLAN BUDGET SAMI-JF'!J13:J100000,SUMMARY!A26&"*") -> 0 | J26: =SUMIFS('PLAN BUDGET SAMI-JF'!AS13:AS100000,'PLAN BUDGET SAMI-JF'!D13:D100000,SUMMARY!D26,'PLAN BUDGET SAMI-JF'!J13:J100000,SUMMARY!A26&"*") -> 0 | K26: =SUMIFS('PLAN BUDGET SAMI-JF'!AT13:AT100000,'PLAN BUDGET SAMI-JF'!D13:D100000,SUMMARY!D26,'PLAN BUDGET SAMI-JF'!J13:J100000,SUMMARY!A26&"*") -> 0 | L26: =SUMIFS('PLAN BUDGET SAMI-JF'!AU13:AU100000,'PLAN BUDGET SAMI-JF'!D13:D100000,SUMMARY!D26,'PLAN BUDGET SAMI-JF'!J13:J100000,SUMMARY!A26&"*") -> 0 | M26: =SUMIFS('PLAN BUDGET SAMI-JF'!AV13:AV100000,'PLAN BUDGET SAMI-JF'!D13:D100000,SUMMARY!D26,'PLAN BUDGET SAMI-JF'!J13:J100000,SUMMARY!A26&"*") -> 0 | N26: =SUMIFS('PLAN BUDGET SAMI-JF'!AW13:AW100000,'PLAN BUDGET SAMI-JF'!D13:D100000,SUMMARY!D26,'PLAN BUDGET SAMI-JF'!J13:J100000,SUMMARY!A26&"*") -> 0 | O26: =SUMIFS('PLAN BUDGET SAMI-JF'!AX13:AX100000,'PLAN BUDGET SAMI-JF'!D13:D100000,SUMMARY!D26,'PLAN BUDGET SAMI-JF'!J13:J100000,SUMMARY!A26&"*") -> 0 | P26: =SUMIFS('PLAN BUDGET SAMI-JF'!AY13:AY100000,'PLAN BUDGET SAMI-JF'!D13:D100000,SUMMARY!D26,'PLAN BUDGET SAMI-JF'!J13:J100000,SUMMARY!A26&"*") -> 0 | Q26: =SUMIFS('PLAN BUDGET SAMI-JF'!BC13:BC100000,'PLAN BUDGET SAMI-JF'!D13:D100000,SUMMARY!D26,'PLAN BUDGET SAMI-JF'!J13:J100000,SUMMARY!A26&"*") -> 0 | R26: =SUMIFS('PLAN BUDGET SAMI-JF'!BD13:BD100000,'PLAN BUDGET SAMI-JF'!D13:D100000,SUMMARY!D26,'PLAN BUDGET SAMI-JF'!J13:J100000,SUMMARY!A26&"*") -> 0 | S26: =SUMIFS('PLAN BUDGET SAMI-JF'!BE13:BE100000,'PLAN BUDGET SAMI-JF'!D13:D100000,SUMMARY!D26,'PLAN BUDGET SAMI-JF'!J13:J100000,SUMMARY!A26&"*") -> 0 | T26: =SUMIFS('PLAN BUDGET SAMI-JF'!BF13:BF100000,'PLAN BUDGET SAMI-JF'!D13:D100000,SUMMARY!D26,'PLAN BUDGET SAMI-JF'!J13:J100000,SUMMARY!A26&"*") -> 0 | U26: =SUMIFS('PLAN BUDGET SAMI-JF'!BG13:BG100000,'PLAN BUDGET SAMI-JF'!D13:D100000,SUMMARY!D26,'PLAN BUDGET SAMI-JF'!J13:J100000,SUMMARY!A26&"*") -> 0 | V26: =SUMIFS('PLAN BUDGET SAMI-JF'!BH13:BH100000,'PLAN BUDGET SAMI-JF'!D13:D100000,SUMMARY!D26,'PLAN BUDGET SAMI-JF'!J13:J100000,SUMMARY!A26&"*") -> 0 | W26: =SUMIFS('PLAN BUDGET SAMI-JF'!BI13:BI100000,'PLAN BUDGET SAMI-JF'!D13:D100000,SUMMARY!D26,'PLAN BUDGET SAMI-JF'!J13:J100000,SUMMARY!A26&"*") -> 0 | X26: =SUMIFS('PLAN BUDGET SAMI-JF'!BJ13:BJ100000,'PLAN BUDGET SAMI-JF'!D13:D100000,SUMMARY!D26,'PLAN BUDGET SAMI-JF'!J13:J100000,SUMMARY!A26&"*") -> 0 | Y26: =SUMIFS('PLAN BUDGET SAMI-JF'!BK13:BK100000,'PLAN BUDGET SAMI-JF'!D13:D100000,SUMMARY!D26,'PLAN BUDGET SAMI-JF'!J13:J100000,SUMMARY!A26&"*") -> 0 | Z26: =SUMIFS('PLAN BUDGET SAMI-JF'!BL13:BL100000,'PLAN BUDGET SAMI-JF'!D13:D100000,SUMMARY!D26,'PLAN BUDGET SAMI-JF'!J13:J100000,SUMMARY!A26&"*") -> 0 | AA26: =SUMIFS('PLAN BUDGET SAMI-JF'!BM13:BM100000,'PLAN BUDGET SAMI-JF'!D13:D100000,SUMMARY!D26,'PLAN BUDGET SAMI-JF'!J13:J100000,SUMMARY!A26&"*") -> 0 | AB26: =SUMIFS('PLAN BUDGET SAMI-JF'!BN13:BN100000,'PLAN BUDGET SAMI-JF'!D13:D100000,SUMMARY!D26,'PLAN BUDGET SAMI-JF'!J13:J100000,SUMMARY!A26&"*") -> 0 | AC26: =SUM(E26:P26) -> 0 | AD26: =SUM(Q26:AB26) -> 0 | AF26: 0 | AG26: 0 | AH26: =IFERROR((AC26-AF26)/AF26,1) -> 1 | AI26: =IFERROR((AD26-AG26)/AG26,1) -> 1 | AJ26: Budget di Term 84 tidak ada, sedangkan di Term 85 ada.
A27: PROJECT | D27: SEROKAN | E27: =SUMIFS('PLAN BUDGET SAMI-JF'!AN13:AN100000,'PLAN BUDGET SAMI-JF'!D13:D100000,SUMMARY!D27,'PLAN BUDGET SAMI-JF'!J13:J100000,SUMMARY!A27&"*") -> 0 | F27: =SUMIFS('PLAN BUDGET SAMI-JF'!AO13:AO100000,'PLAN BUDGET SAMI-JF'!D13:D100000,SUMMARY!D27,'PLAN BUDGET SAMI-JF'!J13:J100000,SUMMARY!A27&"*") -> 18 | G27: =SUMIFS('PLAN BUDGET SAMI-JF'!AP13:AP100000,'PLAN BUDGET SAMI-JF'!D13:D100000,SUMMARY!D27,'PLAN BUDGET SAMI-JF'!J13:J100000,SUMMARY!A27&"*") -> 0 | H27: =SUMIFS('PLAN BUDGET SAMI-JF'!AQ13:AQ100000,'PLAN BUDGET SAMI-JF'!D13:D100000,SUMMARY!D27,'PLAN BUDGET SAMI-JF'!J13:J100000,SUMMARY!A27&"*") -> 0 | I27: =SUMIFS('PLAN BUDGET SAMI-JF'!AR13:AR100000,'PLAN BUDGET SAMI-JF'!D13:D100000,SUMMARY!D27,'PLAN BUDGET SAMI-JF'!J13:J100000,SUMMARY!A27&"*") -> 0 | J27: =SUMIFS('PLAN BUDGET SAMI-JF'!AS13:AS100000,'PLAN BUDGET SAMI-JF'!D13:D100000,SUMMARY!D27,'PLAN BUDGET SAMI-JF'!J13:J100000,SUMMARY!A27&"*") -> 0 | K27: =SUMIFS('PLAN BUDGET SAMI-JF'!AT13:AT100000,'PLAN BUDGET SAMI-JF'!D13:D100000,SUMMARY!D27,'PLAN BUDGET SAMI-JF'!J13:J100000,SUMMARY!A27&"*") -> 0 | L27: =SUMIFS('PLAN BUDGET SAMI-JF'!AU13:AU100000,'PLAN BUDGET SAMI-JF'!D13:D100000,SUMMARY!D27,'PLAN BUDGET SAMI-JF'!J13:J100000,SUMMARY!A27&"*") -> 0 | M27: =SUMIFS('PLAN BUDGET SAMI-JF'!AV13:AV100000,'PLAN BUDGET SAMI-JF'!D13:D100000,SUMMARY!D27,'PLAN BUDGET SAMI-JF'!J13:J100000,SUMMARY!A27&"*") -> 0 | N27: =SUMIFS('PLAN BUDGET SAMI-JF'!AW13:AW100000,'PLAN BUDGET SAMI-JF'!D13:D100000,SUMMARY!D27,'PLAN BUDGET SAMI-JF'!J13:J100000,SUMMARY!A27&"*") -> 0 | O27: =SUMIFS('PLAN BUDGET SAMI-JF'!AX13:AX100000,'PLAN BUDGET SAMI-JF'!D13:D100000,SUMMARY!D27,'PLAN BUDGET SAMI-JF'!J13:J100000,SUMMARY!A27&"*") -> 0 | P27: =SUMIFS('PLAN BUDGET SAMI-JF'!AY13:AY100000,'PLAN BUDGET SAMI-JF'!D13:D100000,SUMMARY!D27,'PLAN BUDGET SAMI-JF'!J13:J100000,SUMMARY!A27&"*") -> 0 | Q27: =SUMIFS('PLAN BUDGET SAMI-JF'!BC13:BC100000,'PLAN BUDGET SAMI-JF'!D13:D100000,SUMMARY!D27,'PLAN BUDGET SAMI-JF'!J13:J100000,SUMMARY!A27&"*") -> 0 | R27: =SUMIFS('PLAN BUDGET SAMI-JF'!BD13:BD100000,'PLAN BUDGET SAMI-JF'!D13:D100000,SUMMARY!D27,'PLAN BUDGET SAMI-JF'!J13:J100000,SUMMARY!A27&"*") -> 8.545061 | S27: =SUMIFS('PLAN BUDGET SAMI-JF'!BE13:BE100000,'PLAN BUDGET SAMI-JF'!D13:D100000,SUMMARY!D27,'PLAN BUDGET SAMI-JF'!J13:J100000,SUMMARY!A27&"*") -> 0 | T27: =SUMIFS('PLAN BUDGET SAMI-JF'!BF13:BF100000,'PLAN BUDGET SAMI-JF'!D13:D100000,SUMMARY!D27,'PLAN BUDGET SAMI-JF'!J13:J100000,SUMMARY!A27&"*") -> 0 | U27: =SUMIFS('PLAN BUDGET SAMI-JF'!BG13:BG100000,'PLAN BUDGET SAMI-JF'!D13:D100000,SUMMARY!D27,'PLAN BUDGET SAMI-JF'!J13:J100000,SUMMARY!A27&"*") -> 0 | V27: =SUMIFS('PLAN BUDGET SAMI-JF'!BH13:BH100000,'PLAN BUDGET SAMI-JF'!D13:D100000,SUMMARY!D27,'PLAN BUDGET SAMI-JF'!J13:J100000,SUMMARY!A27&"*") -> 0 | W27: =SUMIFS('PLAN BUDGET SAMI-JF'!BI13:BI100000,'PLAN BUDGET SAMI-JF'!D13:D100000,SUMMARY!D27,'PLAN BUDGET SAMI-JF'!J13:J100000,SUMMARY!A27&"*") -> 0 | X27: =SUMIFS('PLAN BUDGET SAMI-JF'!BJ13:BJ100000,'PLAN BUDGET SAMI-JF'!D13:D100000,SUMMARY!D27,'PLAN BUDGET SAMI-JF'!J13:J100000,SUMMARY!A27&"*") -> 0 | Y27: =SUMIFS('PLAN BUDGET SAMI-JF'!BK13:BK100000,'PLAN BUDGET SAMI-JF'!D13:D100000,SUMMARY!D27,'PLAN BUDGET SAMI-JF'!J13:J100000,SUMMARY!A27&"*") -> 0 | Z27: =SUMIFS('PLAN BUDGET SAMI-JF'!BL13:BL100000,'PLAN BUDGET SAMI-JF'!D13:D100000,SUMMARY!D27,'PLAN BUDGET SAMI-JF'!J13:J100000,SUMMARY!A27&"*") -> 0 | AA27: =SUMIFS('PLAN BUDGET SAMI-JF'!BM13:BM100000,'PLAN BUDGET SAMI-JF'!D13:D100000,SUMMARY!D27,'PLAN BUDGET SAMI-JF'!J13:J100000,SUMMARY!A27&"*") -> 0 | AB27: =SUMIFS('PLAN BUDGET SAMI-JF'!BN13:BN100000,'PLAN BUDGET SAMI-JF'!D13:D100000,SUMMARY!D27,'PLAN BUDGET SAMI-JF'!J13:J100000,SUMMARY!A27&"*") -> 0 | AC27: =SUM(E27:P27) -> 18 | AD27: =SUM(Q27:AB27) -> 8.545061 | AF27: 0 | AG27: 0 | AH27: =IFERROR((AC27-AF27)/AF27,1) -> 1 | AI27: =IFERROR((AD27-AG27)/AG27,1) -> 1 | AJ27: Budget di Term 84 tidak ada, sedangkan di Term 85 ada.
A28: PROJECT | D28: SAPU | E28: =SUMIFS('PLAN BUDGET SAMI-JF'!AN13:AN100000,'PLAN BUDGET SAMI-JF'!D13:D100000,SUMMARY!D28,'PLAN BUDGET SAMI-JF'!J13:J100000,SUMMARY!A28&"*") -> 0 | F28: =SUMIFS('PLAN BUDGET SAMI-JF'!AO13:AO100000,'PLAN BUDGET SAMI-JF'!D13:D100000,SUMMARY!D28,'PLAN BUDGET SAMI-JF'!J13:J100000,SUMMARY!A28&"*") -> 108 | G28: =SUMIFS('PLAN BUDGET SAMI-JF'!AP13:AP100000,'PLAN BUDGET SAMI-JF'!D13:D100000,SUMMARY!D28,'PLAN BUDGET SAMI-JF'!J13:J100000,SUMMARY!A28&"*") -> 0 | H28: =SUMIFS('PLAN BUDGET SAMI-JF'!AQ13:AQ100000,'PLAN BUDGET SAMI-JF'!D13:D100000,SUMMARY!D28,'PLAN BUDGET SAMI-JF'!J13:J100000,SUMMARY!A28&"*") -> 0 | I28: =SUMIFS('PLAN BUDGET SAMI-JF'!AR13:AR100000,'PLAN BUDGET SAMI-JF'!D13:D100000,SUMMARY!D28,'PLAN BUDGET SAMI-JF'!J13:J100000,SUMMARY!A28&"*") -> 0 | J28: =SUMIFS('PLAN BUDGET SAMI-JF'!AS13:AS100000,'PLAN BUDGET SAMI-JF'!D13:D100000,SUMMARY!D28,'PLAN BUDGET SAMI-JF'!J13:J100000,SUMMARY!A28&"*") -> 0 | K28: =SUMIFS('PLAN BUDGET SAMI-JF'!AT13:AT100000,'PLAN BUDGET SAMI-JF'!D13:D100000,SUMMARY!D28,'PLAN BUDGET SAMI-JF'!J13:J100000,SUMMARY!A28&"*") -> 0 | L28: =SUMIFS('PLAN BUDGET SAMI-JF'!AU13:AU100000,'PLAN BUDGET SAMI-JF'!D13:D100000,SUMMARY!D28,'PLAN BUDGET SAMI-JF'!J13:J100000,SUMMARY!A28&"*") -> 0 | M28: =SUMIFS('PLAN BUDGET SAMI-JF'!AV13:AV100000,'PLAN BUDGET SAMI-JF'!D13:D100000,SUMMARY!D28,'PLAN BUDGET SAMI-JF'!J13:J100000,SUMMARY!A28&"*") -> 0 | N28: =SUMIFS('PLAN BUDGET SAMI-JF'!AW13:AW100000,'PLAN BUDGET SAMI-JF'!D13:D100000,SUMMARY!D28,'PLAN BUDGET SAMI-JF'!J13:J100000,SUMMARY!A28&"*") -> 0 | O28: =SUMIFS('PLAN BUDGET SAMI-JF'!AX13:AX100000,'PLAN BUDGET SAMI-JF'!D13:D100000,SUMMARY!D28,'PLAN BUDGET SAMI-JF'!J13:J100000,SUMMARY!A28&"*") -> 0 | P28: =SUMIFS('PLAN BUDGET SAMI-JF'!AY13:AY100000,'PLAN BUDGET SAMI-JF'!D13:D100000,SUMMARY!D28,'PLAN BUDGET SAMI-JF'!J13:J100000,SUMMARY!A28&"*") -> 0 | Q28: =SUMIFS('PLAN BUDGET SAMI-JF'!BC13:BC100000,'PLAN BUDGET SAMI-JF'!D13:D100000,SUMMARY!D28,'PLAN BUDGET SAMI-JF'!J13:J100000,SUMMARY!A28&"*") -> 0 | R28: =SUMIFS('PLAN BUDGET SAMI-JF'!BD13:BD100000,'PLAN BUDGET SAMI-JF'!D13:D100000,SUMMARY!D28,'PLAN BUDGET SAMI-JF'!J13:J100000,SUMMARY!A28&"*") -> 393.0728 | S28: =SUMIFS('PLAN BUDGET SAMI-JF'!BE13:BE100000,'PLAN BUDGET SAMI-JF'!D13:D100000,SUMMARY!D28,'PLAN BUDGET SAMI-JF'!J13:J100000,SUMMARY!A28&"*") -> 0 | T28: =SUMIFS('PLAN BUDGET SAMI-JF'!BF13:BF100000,'PLAN BUDGET SAMI-JF'!D13:D100000,SUMMARY!D28,'PLAN BUDGET SAMI-JF'!J13:J100000,SUMMARY!A28&"*") -> 0 | U28: =SUMIFS('PLAN BUDGET SAMI-JF'!BG13:BG100000,'PLAN BUDGET SAMI-JF'!D13:D100000,SUMMARY!D28,'PLAN BUDGET SAMI-JF'!J13:J100000,SUMMARY!A28&"*") -> 0 | V28: =SUMIFS('PLAN BUDGET SAMI-JF'!BH13:BH100000,'PLAN BUDGET SAMI-JF'!D13:D100000,SUMMARY!D28,'PLAN BUDGET SAMI-JF'!J13:J100000,SUMMARY!A28&"*") -> 0 | W28: =SUMIFS('PLAN BUDGET SAMI-JF'!BI13:BI100000,'PLAN BUDGET SAMI-JF'!D13:D100000,SUMMARY!D28,'PLAN BUDGET SAMI-JF'!J13:J100000,SUMMARY!A28&"*") -> 0 | X28: =SUMIFS('PLAN BUDGET SAMI-JF'!BJ13:BJ100000,'PLAN BUDGET SAMI-JF'!D13:D100000,SUMMARY!D28,'PLAN BUDGET SAMI-JF'!J13:J100000,SUMMARY!A28&"*") -> 0 | Y28: =SUMIFS('PLAN BUDGET SAMI-JF'!BK13:BK100000,'PLAN BUDGET SAMI-JF'!D13:D100000,SUMMARY!D28,'PLAN BUDGET SAMI-JF'!J13:J100000,SUMMARY!A28&"*") -> 0 | Z28: =SUMIFS('PLAN BUDGET SAMI-JF'!BL13:BL100000,'PLAN BUDGET SAMI-JF'!D13:D100000,SUMMARY!D28,'PLAN BUDGET SAMI-JF'!J13:J100000,SUMMARY!A28&"*") -> 0 | AA28: =SUMIFS('PLAN BUDGET SAMI-JF'!BM13:BM100000,'PLAN BUDGET SAMI-JF'!D13:D100000,SUMMARY!D28,'PLAN BUDGET SAMI-JF'!J13:J100000,SUMMARY!A28&"*") -> 0 | AB28: =SUMIFS('PLAN BUDGET SAMI-JF'!BN13:BN100000,'PLAN BUDGET SAMI-JF'!D13:D100000,SUMMARY!D28,'PLAN BUDGET SAMI-JF'!J13:J100000,SUMMARY!A28&"*") -> 0 | AC28: =SUM(E28:P28) -> 108 | AD28: =SUM(Q28:AB28) -> 393.0728 | AF28: 72 | AG28: 120.01063 | AH28: =IFERROR((AC28-AF28)/AF28,1) -> 0.5 | AI28: =IFERROR((AD28-AG28)/AG28,1) -> 2.2753165 | AJ28: Budget di Term 84 tidak ada, sedangkan di Term 85 ada.
A29: PROJECT | D29: VACUM CLEANER | E29: =SUMIFS('PLAN BUDGET SAMI-JF'!AN13:AN100000,'PLAN BUDGET SAMI-JF'!D13:D100000,SUMMARY!D29,'PLAN BUDGET SAMI-JF'!J13:J100000,SUMMARY!A29&"*") -> 0 | F29: =SUMIFS('PLAN BUDGET SAMI-JF'!AO13:AO100000,'PLAN BUDGET SAMI-JF'!D13:D100000,SUMMARY!D29,'PLAN BUDGET SAMI-JF'!J13:J100000,SUMMARY!A29&"*") -> 3 | G29: =SUMIFS('PLAN BUDGET SAMI-JF'!AP13:AP100000,'PLAN BUDGET SAMI-JF'!D13:D100000,SUMMARY!D29,'PLAN BUDGET SAMI-JF'!J13:J100000,SUMMARY!A29&"*") -> 0 | H29: =SUMIFS('PLAN BUDGET SAMI-JF'!AQ13:AQ100000,'PLAN BUDGET SAMI-JF'!D13:D100000,SUMMARY!D29,'PLAN BUDGET SAMI-JF'!J13:J100000,SUMMARY!A29&"*") -> 0 | I29: =SUMIFS('PLAN BUDGET SAMI-JF'!AR13:AR100000,'PLAN BUDGET SAMI-JF'!D13:D100000,SUMMARY!D29,'PLAN BUDGET SAMI-JF'!J13:J100000,SUMMARY!A29&"*") -> 0 | J29: =SUMIFS('PLAN BUDGET SAMI-JF'!AS13:AS100000,'PLAN BUDGET SAMI-JF'!D13:D100000,SUMMARY!D29,'PLAN BUDGET SAMI-JF'!J13:J100000,SUMMARY!A29&"*") -> 0 | K29: =SUMIFS('PLAN BUDGET SAMI-JF'!AT13:AT100000,'PLAN BUDGET SAMI-JF'!D13:D100000,SUMMARY!D29,'PLAN BUDGET SAMI-JF'!J13:J100000,SUMMARY!A29&"*") -> 0 | L29: =SUMIFS('PLAN BUDGET SAMI-JF'!AU13:AU100000,'PLAN BUDGET SAMI-JF'!D13:D100000,SUMMARY!D29,'PLAN BUDGET SAMI-JF'!J13:J100000,SUMMARY!A29&"*") -> 0 | M29: =SUMIFS('PLAN BUDGET SAMI-JF'!AV13:AV100000,'PLAN BUDGET SAMI-JF'!D13:D100000,SUMMARY!D29,'PLAN BUDGET SAMI-JF'!J13:J100000,SUMMARY!A29&"*") -> 0 | N29: =SUMIFS('PLAN BUDGET SAMI-JF'!AW13:AW100000,'PLAN BUDGET SAMI-JF'!D13:D100000,SUMMARY!D29,'PLAN BUDGET SAMI-JF'!J13:J100000,SUMMARY!A29&"*") -> 0 | O29: =SUMIFS('PLAN BUDGET SAMI-JF'!AX13:AX100000,'PLAN BUDGET SAMI-JF'!D13:D100000,SUMMARY!D29,'PLAN BUDGET SAMI-JF'!J13:J100000,SUMMARY!A29&"*") -> 0 | P29: =SUMIFS('PLAN BUDGET SAMI-JF'!AY13:AY100000,'PLAN BUDGET SAMI-JF'!D13:D100000,SUMMARY!D29,'PLAN BUDGET SAMI-JF'!J13:J100000,SUMMARY!A29&"*") -> 0 | Q29: =SUMIFS('PLAN BUDGET SAMI-JF'!BC13:BC100000,'PLAN BUDGET SAMI-JF'!D13:D100000,SUMMARY!D29,'PLAN BUDGET SAMI-JF'!J13:J100000,SUMMARY!A29&"*") -> 0 | R29: =SUMIFS('PLAN BUDGET SAMI-JF'!BD13:BD100000,'PLAN BUDGET SAMI-JF'!D13:D100000,SUMMARY!D29,'PLAN BUDGET SAMI-JF'!J13:J100000,SUMMARY!A29&"*") -> 229.76719 | S29: =SUMIFS('PLAN BUDGET SAMI-JF'!BE13:BE100000,'PLAN BUDGET SAMI-JF'!D13:D100000,SUMMARY!D29,'PLAN BUDGET SAMI-JF'!J13:J100000,SUMMARY!A29&"*") -> 0 | T29: =SUMIFS('PLAN BUDGET SAMI-JF'!BF13:BF100000,'PLAN BUDGET SAMI-JF'!D13:D100000,SUMMARY!D29,'PLAN BUDGET SAMI-JF'!J13:J100000,SUMMARY!A29&"*") -> 0 | U29: =SUMIFS('PLAN BUDGET SAMI-JF'!BG13:BG100000,'PLAN BUDGET SAMI-JF'!D13:D100000,SUMMARY!D29,'PLAN BUDGET SAMI-JF'!J13:J100000,SUMMARY!A29&"*") -> 0 | V29: =SUMIFS('PLAN BUDGET SAMI-JF'!BH13:BH100000,'PLAN BUDGET SAMI-JF'!D13:D100000,SUMMARY!D29,'PLAN BUDGET SAMI-JF'!J13:J100000,SUMMARY!A29&"*") -> 0 | W29: =SUMIFS('PLAN BUDGET SAMI-JF'!BI13:BI100000,'PLAN BUDGET SAMI-JF'!D13:D100000,SUMMARY!D29,'PLAN BUDGET SAMI-JF'!J13:J100000,SUMMARY!A29&"*") -> 0 | X29: =SUMIFS('PLAN BUDGET SAMI-JF'!BJ13:BJ100000,'PLAN BUDGET SAMI-JF'!D13:D100000,SUMMARY!D29,'PLAN BUDGET SAMI-JF'!J13:J100000,SUMMARY!A29&"*") -> 0 | Y29: =SUMIFS('PLAN BUDGET SAMI-JF'!BK13:BK100000,'PLAN BUDGET SAMI-JF'!D13:D100000,SUMMARY!D29,'PLAN BUDGET SAMI-JF'!J13:J100000,SUMMARY!A29&"*") -> 0 | Z29: =SUMIFS('PLAN BUDGET SAMI-JF'!BL13:BL100000,'PLAN BUDGET SAMI-JF'!D13:D100000,SUMMARY!D29,'PLAN BUDGET SAMI-JF'!J13:J100000,SUMMARY!A29&"*") -> 0 | AA29: =SUMIFS('PLAN BUDGET SAMI-JF'!BM13:BM100000,'PLAN BUDGET SAMI-JF'!D13:D100000,SUMMARY!D29,'PLAN BUDGET SAMI-JF'!J13:J100000,SUMMARY!A29&"*") -> 0 | AB29: =SUMIFS('PLAN BUDGET SAMI-JF'!BN13:BN100000,'PLAN BUDGET SAMI-JF'!D13:D100000,SUMMARY!D29,'PLAN BUDGET SAMI-JF'!J13:J100000,SUMMARY!A29&"*") -> 0 | AC29: =SUM(E29:P29) -> 3 | AD29: =SUM(Q29:AB29) -> 229.76719 | AF29: 3 | AG29: 255.46567 | AH29: =IFERROR((AC29-AF29)/AF29,1) -> 0 | AI29: =IFERROR((AD29-AG29)/AG29,1) -> -0.10059465
A30: PROJECT | D30: TEMPAT SAMPAH | E30: =SUMIFS('PLAN BUDGET SAMI-JF'!AN13:AN100000,'PLAN BUDGET SAMI-JF'!D13:D100000,SUMMARY!D30,'PLAN BUDGET SAMI-JF'!J13:J100000,SUMMARY!A30&"*") -> 0 | F30: =SUMIFS('PLAN BUDGET SAMI-JF'!AO13:AO100000,'PLAN BUDGET SAMI-JF'!D13:D100000,SUMMARY!D30,'PLAN BUDGET SAMI-JF'!J13:J100000,SUMMARY!A30&"*") -> 3 | G30: =SUMIFS('PLAN BUDGET SAMI-JF'!AP13:AP100000,'PLAN BUDGET SAMI-JF'!D13:D100000,SUMMARY!D30,'PLAN BUDGET SAMI-JF'!J13:J100000,SUMMARY!A30&"*") -> 0 | H30: =SUMIFS('PLAN BUDGET SAMI-JF'!AQ13:AQ100000,'PLAN BUDGET SAMI-JF'!D13:D100000,SUMMARY!D30,'PLAN BUDGET SAMI-JF'!J13:J100000,SUMMARY!A30&"*") -> 0 | I30: =SUMIFS('PLAN BUDGET SAMI-JF'!AR13:AR100000,'PLAN BUDGET SAMI-JF'!D13:D100000,SUMMARY!D30,'PLAN BUDGET SAMI-JF'!J13:J100000,SUMMARY!A30&"*") -> 0 | J30: =SUMIFS('PLAN BUDGET SAMI-JF'!AS13:AS100000,'PLAN BUDGET SAMI-JF'!D13:D100000,SUMMARY!D30,'PLAN BUDGET SAMI-JF'!J13:J100000,SUMMARY!A30&"*") -> 0 | K30: =SUMIFS('PLAN BUDGET SAMI-JF'!AT13:AT100000,'PLAN BUDGET SAMI-JF'!D13:D100000,SUMMARY!D30,'PLAN BUDGET SAMI-JF'!J13:J100000,SUMMARY!A30&"*") -> 0 | L30: =SUMIFS('PLAN BUDGET SAMI-JF'!AU13:AU100000,'PLAN BUDGET SAMI-JF'!D13:D100000,SUMMARY!D30,'PLAN BUDGET SAMI-JF'!J13:J100000,SUMMARY!A30&"*") -> 0 | M30: =SUMIFS('PLAN BUDGET SAMI-JF'!AV13:AV100000,'PLAN BUDGET SAMI-JF'!D13:D100000,SUMMARY!D30,'PLAN BUDGET SAMI-JF'!J13:J100000,SUMMARY!A30&"*") -> 0 | N30: =SUMIFS('PLAN BUDGET SAMI-JF'!AW13:AW100000,'PLAN BUDGET SAMI-JF'!D13:D100000,SUMMARY!D30,'PLAN BUDGET SAMI-JF'!J13:J100000,SUMMARY!A30&"*") -> 0 | O30: =SUMIFS('PLAN BUDGET SAMI-JF'!AX13:AX100000,'PLAN BUDGET SAMI-JF'!D13:D100000,SUMMARY!D30,'PLAN BUDGET SAMI-JF'!J13:J100000,SUMMARY!A30&"*") -> 0 | P30: =SUMIFS('PLAN BUDGET SAMI-JF'!AY13:AY100000,'PLAN BUDGET SAMI-JF'!D13:D100000,SUMMARY!D30,'PLAN BUDGET SAMI-JF'!J13:J100000,SUMMARY!A30&"*") -> 0 | Q30: =SUMIFS('PLAN BUDGET SAMI-JF'!BC13:BC100000,'PLAN BUDGET SAMI-JF'!D13:D100000,SUMMARY!D30,'PLAN BUDGET SAMI-JF'!J13:J100000,SUMMARY!A30&"*") -> 0 | R30: =SUMIFS('PLAN BUDGET SAMI-JF'!BD13:BD100000,'PLAN BUDGET SAMI-JF'!D13:D100000,SUMMARY!D30,'PLAN BUDGET SAMI-JF'!J13:J100000,SUMMARY!A30&"*") -> 22.131708 | S30: =SUMIFS('PLAN BUDGET SAMI-JF'!BE13:BE100000,'PLAN BUDGET SAMI-JF'!D13:D100000,SUMMARY!D30,'PLAN BUDGET SAMI-JF'!J13:J100000,SUMMARY!A30&"*") -> 0 | T30: =SUMIFS('PLAN BUDGET SAMI-JF'!BF13:BF100000,'PLAN BUDGET SAMI-JF'!D13:D100000,SUMMARY!D30,'PLAN BUDGET SAMI-JF'!J13:J100000,SUMMARY!A30&"*") -> 0 | U30: =SUMIFS('PLAN BUDGET SAMI-JF'!BG13:BG100000,'PLAN BUDGET SAMI-JF'!D13:D100000,SUMMARY!D30,'PLAN BUDGET SAMI-JF'!J13:J100000,SUMMARY!A30&"*") -> 0 | V30: =SUMIFS('PLAN BUDGET SAMI-JF'!BH13:BH100000,'PLAN BUDGET SAMI-JF'!D13:D100000,SUMMARY!D30,'PLAN BUDGET SAMI-JF'!J13:J100000,SUMMARY!A30&"*") -> 0 | W30: =SUMIFS('PLAN BUDGET SAMI-JF'!BI13:BI100000,'PLAN BUDGET SAMI-JF'!D13:D100000,SUMMARY!D30,'PLAN BUDGET SAMI-JF'!J13:J100000,SUMMARY!A30&"*") -> 0 | X30: =SUMIFS('PLAN BUDGET SAMI-JF'!BJ13:BJ100000,'PLAN BUDGET SAMI-JF'!D13:D100000,SUMMARY!D30,'PLAN BUDGET SAMI-JF'!J13:J100000,SUMMARY!A30&"*") -> 0 | Y30: =SUMIFS('PLAN BUDGET SAMI-JF'!BK13:BK100000,'PLAN BUDGET SAMI-JF'!D13:D100000,SUMMARY!D30,'PLAN BUDGET SAMI-JF'!J13:J100000,SUMMARY!A30&"*") -> 0 | Z30: =SUMIFS('PLAN BUDGET SAMI-JF'!BL13:BL100000,'PLAN BUDGET SAMI-JF'!D13:D100000,SUMMARY!D30,'PLAN BUDGET SAMI-JF'!J13:J100000,SUMMARY!A30&"*") -> 0 | AA30: =SUMIFS('PLAN BUDGET SAMI-JF'!BM13:BM100000,'PLAN BUDGET SAMI-JF'!D13:D100000,SUMMARY!D30,'PLAN BUDGET SAMI-JF'!J13:J100000,SUMMARY!A30&"*") -> 0 | AB30: =SUMIFS('PLAN BUDGET SAMI-JF'!BN13:BN100000,'PLAN BUDGET SAMI-JF'!D13:D100000,SUMMARY!D30,'PLAN BUDGET SAMI-JF'!J13:J100000,SUMMARY!A30&"*") -> 0 | AC30: =SUM(E30:P30) -> 3 | AD30: =SUM(Q30:AB30) -> 22.131708 | AF30: 17 | AG30: 68.676971 | AH30: =IFERROR((AC30-AF30)/AF30,1) -> -0.82352941 | AI30: =IFERROR((AD30-AG30)/AG30,1) -> -0.67774194
A31: PROJECT | D31: HANDMOP | E31: =SUMIFS('PLAN BUDGET SAMI-JF'!AN13:AN100000,'PLAN BUDGET SAMI-JF'!D13:D100000,SUMMARY!D31,'PLAN BUDGET SAMI-JF'!J13:J100000,SUMMARY!A31&"*") -> 0 | F31: =SUMIFS('PLAN BUDGET SAMI-JF'!AO13:AO100000,'PLAN BUDGET SAMI-JF'!D13:D100000,SUMMARY!D31,'PLAN BUDGET SAMI-JF'!J13:J100000,SUMMARY!A31&"*") -> 6 | G31: =SUMIFS('PLAN BUDGET SAMI-JF'!AP13:AP100000,'PLAN BUDGET SAMI-JF'!D13:D100000,SUMMARY!D31,'PLAN BUDGET SAMI-JF'!J13:J100000,SUMMARY!A31&"*") -> 0 | H31: =SUMIFS('PLAN BUDGET SAMI-JF'!AQ13:AQ100000,'PLAN BUDGET SAMI-JF'!D13:D100000,SUMMARY!D31,'PLAN BUDGET SAMI-JF'!J13:J100000,SUMMARY!A31&"*") -> 0 | I31: =SUMIFS('PLAN BUDGET SAMI-JF'!AR13:AR100000,'PLAN BUDGET SAMI-JF'!D13:D100000,SUMMARY!D31,'PLAN BUDGET SAMI-JF'!J13:J100000,SUMMARY!A31&"*") -> 0 | J31: =SUMIFS('PLAN BUDGET SAMI-JF'!AS13:AS100000,'PLAN BUDGET SAMI-JF'!D13:D100000,SUMMARY!D31,'PLAN BUDGET SAMI-JF'!J13:J100000,SUMMARY!A31&"*") -> 0 | K31: =SUMIFS('PLAN BUDGET SAMI-JF'!AT13:AT100000,'PLAN BUDGET SAMI-JF'!D13:D100000,SUMMARY!D31,'PLAN BUDGET SAMI-JF'!J13:J100000,SUMMARY!A31&"*") -> 0 | L31: =SUMIFS('PLAN BUDGET SAMI-JF'!AU13:AU100000,'PLAN BUDGET SAMI-JF'!D13:D100000,SUMMARY!D31,'PLAN BUDGET SAMI-JF'!J13:J100000,SUMMARY!A31&"*") -> 0 | M31: =SUMIFS('PLAN BUDGET SAMI-JF'!AV13:AV100000,'PLAN BUDGET SAMI-JF'!D13:D100000,SUMMARY!D31,'PLAN BUDGET SAMI-JF'!J13:J100000,SUMMARY!A31&"*") -> 0 | N31: =SUMIFS('PLAN BUDGET SAMI-JF'!AW13:AW100000,'PLAN BUDGET SAMI-JF'!D13:D100000,SUMMARY!D31,'PLAN BUDGET SAMI-JF'!J13:J100000,SUMMARY!A31&"*") -> 0 | O31: =SUMIFS('PLAN BUDGET SAMI-JF'!AX13:AX100000,'PLAN BUDGET SAMI-JF'!D13:D100000,SUMMARY!D31,'PLAN BUDGET SAMI-JF'!J13:J100000,SUMMARY!A31&"*") -> 0 | P31: =SUMIFS('PLAN BUDGET SAMI-JF'!AY13:AY100000,'PLAN BUDGET SAMI-JF'!D13:D100000,SUMMARY!D31,'PLAN BUDGET SAMI-JF'!J13:J100000,SUMMARY!A31&"*") -> 0 | Q31: =SUMIFS('PLAN BUDGET SAMI-JF'!BC13:BC100000,'PLAN BUDGET SAMI-JF'!D13:D100000,SUMMARY!D31,'PLAN BUDGET SAMI-JF'!J13:J100000,SUMMARY!A31&"*") -> 0 | R31: =SUMIFS('PLAN BUDGET SAMI-JF'!BD13:BD100000,'PLAN BUDGET SAMI-JF'!D13:D100000,SUMMARY!D31,'PLAN BUDGET SAMI-JF'!J13:J100000,SUMMARY!A31&"*") -> 8.7588774 | S31: =SUMIFS('PLAN BUDGET SAMI-JF'!BE13:BE100000,'PLAN BUDGET SAMI-JF'!D13:D100000,SUMMARY!D31,'PLAN BUDGET SAMI-JF'!J13:J100000,SUMMARY!A31&"*") -> 0 | T31: =SUMIFS('PLAN BUDGET SAMI-JF'!BF13:BF100000,'PLAN BUDGET SAMI-JF'!D13:D100000,SUMMARY!D31,'PLAN BUDGET SAMI-JF'!J13:J100000,SUMMARY!A31&"*") -> 0 | U31: =SUMIFS('PLAN BUDGET SAMI-JF'!BG13:BG100000,'PLAN BUDGET SAMI-JF'!D13:D100000,SUMMARY!D31,'PLAN BUDGET SAMI-JF'!J13:J100000,SUMMARY!A31&"*") -> 0 | V31: =SUMIFS('PLAN BUDGET SAMI-JF'!BH13:BH100000,'PLAN BUDGET SAMI-JF'!D13:D100000,SUMMARY!D31,'PLAN BUDGET SAMI-JF'!J13:J100000,SUMMARY!A31&"*") -> 0 | W31: =SUMIFS('PLAN BUDGET SAMI-JF'!BI13:BI100000,'PLAN BUDGET SAMI-JF'!D13:D100000,SUMMARY!D31,'PLAN BUDGET SAMI-JF'!J13:J100000,SUMMARY!A31&"*") -> 0 | X31: =SUMIFS('PLAN BUDGET SAMI-JF'!BJ13:BJ100000,'PLAN BUDGET SAMI-JF'!D13:D100000,SUMMARY!D31,'PLAN BUDGET SAMI-JF'!J13:J100000,SUMMARY!A31&"*") -> 0 | Y31: =SUMIFS('PLAN BUDGET SAMI-JF'!BK13:BK100000,'PLAN BUDGET SAMI-JF'!D13:D100000,SUMMARY!D31,'PLAN BUDGET SAMI-JF'!J13:J100000,SUMMARY!A31&"*") -> 0 | Z31: =SUMIFS('PLAN BUDGET SAMI-JF'!BL13:BL100000,'PLAN BUDGET SAMI-JF'!D13:D100000,SUMMARY!D31,'PLAN BUDGET SAMI-JF'!J13:J100000,SUMMARY!A31&"*") -> 0 | AA31: =SUMIFS('PLAN BUDGET SAMI-JF'!BM13:BM100000,'PLAN BUDGET SAMI-JF'!D13:D100000,SUMMARY!D31,'PLAN BUDGET SAMI-JF'!J13:J100000,SUMMARY!A31&"*") -> 0 | AB31: =SUMIFS('PLAN BUDGET SAMI-JF'!BN13:BN100000,'PLAN BUDGET SAMI-JF'!D13:D100000,SUMMARY!D31,'PLAN BUDGET SAMI-JF'!J13:J100000,SUMMARY!A31&"*") -> 0 | AC31: =SUM(E31:P31) -> 6 | AD31: =SUM(Q31:AB31) -> 8.7588774 | AF31: 14 | AG31: 24.685732 | AH31: =IFERROR((AC31-AF31)/AF31,1) -> -0.57142857 | AI31: =IFERROR((AD31-AG31)/AG31,1) -> -0.64518462
A32: IMPROVEMENT | D32: TABLET | E32: =SUMIFS('PLAN BUDGET SAMI-JF'!AN13:AN100000,'PLAN BUDGET SAMI-JF'!D13:D100000,SUMMARY!D32,'PLAN BUDGET SAMI-JF'!J13:J100000,SUMMARY!A32&"*") -> 0 | F32: =SUMIFS('PLAN BUDGET SAMI-JF'!AO13:AO100000,'PLAN BUDGET SAMI-JF'!D13:D100000,SUMMARY!D32,'PLAN BUDGET SAMI-JF'!J13:J100000,SUMMARY!A32&"*") -> 0 | G32: =SUMIFS('PLAN BUDGET SAMI-JF'!AP13:AP100000,'PLAN BUDGET SAMI-JF'!D13:D100000,SUMMARY!D32,'PLAN BUDGET SAMI-JF'!J13:J100000,SUMMARY!A32&"*") -> 0 | H32: =SUMIFS('PLAN BUDGET SAMI-JF'!AQ13:AQ100000,'PLAN BUDGET SAMI-JF'!D13:D100000,SUMMARY!D32,'PLAN BUDGET SAMI-JF'!J13:J100000,SUMMARY!A32&"*") -> 0 | I32: =SUMIFS('PLAN BUDGET SAMI-JF'!AR13:AR100000,'PLAN BUDGET SAMI-JF'!D13:D100000,SUMMARY!D32,'PLAN BUDGET SAMI-JF'!J13:J100000,SUMMARY!A32&"*") -> 0 | J32: =SUMIFS('PLAN BUDGET SAMI-JF'!AS13:AS100000,'PLAN BUDGET SAMI-JF'!D13:D100000,SUMMARY!D32,'PLAN BUDGET SAMI-JF'!J13:J100000,SUMMARY!A32&"*") -> 0 | K32: =SUMIFS('PLAN BUDGET SAMI-JF'!AT13:AT100000,'PLAN BUDGET SAMI-JF'!D13:D100000,SUMMARY!D32,'PLAN BUDGET SAMI-JF'!J13:J100000,SUMMARY!A32&"*") -> 0 | L32: =SUMIFS('PLAN BUDGET SAMI-JF'!AU13:AU100000,'PLAN BUDGET SAMI-JF'!D13:D100000,SUMMARY!D32,'PLAN BUDGET SAMI-JF'!J13:J100000,SUMMARY!A32&"*") -> 0 | M32: =SUMIFS('PLAN BUDGET SAMI-JF'!AV13:AV100000,'PLAN BUDGET SAMI-JF'!D13:D100000,SUMMARY!D32,'PLAN BUDGET SAMI-JF'!J13:J100000,SUMMARY!A32&"*") -> 0 | N32: =SUMIFS('PLAN BUDGET SAMI-JF'!AW13:AW100000,'PLAN BUDGET SAMI-JF'!D13:D100000,SUMMARY!D32,'PLAN BUDGET SAMI-JF'!J13:J100000,SUMMARY!A32&"*") -> 0 | O32: =SUMIFS('PLAN BUDGET SAMI-JF'!AX13:AX100000,'PLAN BUDGET SAMI-JF'!D13:D100000,SUMMARY!D32,'PLAN BUDGET SAMI-JF'!J13:J100000,SUMMARY!A32&"*") -> 0 | P32: =SUMIFS('PLAN BUDGET SAMI-JF'!AY13:AY100000,'PLAN BUDGET SAMI-JF'!D13:D100000,SUMMARY!D32,'PLAN BUDGET SAMI-JF'!J13:J100000,SUMMARY!A32&"*") -> 0 | Q32: =SUMIFS('PLAN BUDGET SAMI-JF'!BC13:BC100000,'PLAN BUDGET SAMI-JF'!D13:D100000,SUMMARY!D32,'PLAN BUDGET SAMI-JF'!J13:J100000,SUMMARY!A32&"*") -> 0 | R32: =SUMIFS('PLAN BUDGET SAMI-JF'!BD13:BD100000,'PLAN BUDGET SAMI-JF'!D13:D100000,SUMMARY!D32,'PLAN BUDGET SAMI-JF'!J13:J100000,SUMMARY!A32&"*") -> 0 | S32: =SUMIFS('PLAN BUDGET SAMI-JF'!BE13:BE100000,'PLAN BUDGET SAMI-JF'!D13:D100000,SUMMARY!D32,'PLAN BUDGET SAMI-JF'!J13:J100000,SUMMARY!A32&"*") -> 0 | T32: =SUMIFS('PLAN BUDGET SAMI-JF'!BF13:BF100000,'PLAN BUDGET SAMI-JF'!D13:D100000,SUMMARY!D32,'PLAN BUDGET SAMI-JF'!J13:J100000,SUMMARY!A32&"*") -> 0 | U32: =SUMIFS('PLAN BUDGET SAMI-JF'!BG13:BG100000,'PLAN BUDGET SAMI-JF'!D13:D100000,SUMMARY!D32,'PLAN BUDGET SAMI-JF'!J13:J100000,SUMMARY!A32&"*") -> 0 | V32: =SUMIFS('PLAN BUDGET SAMI-JF'!BH13:BH100000,'PLAN BUDGET SAMI-JF'!D13:D100000,SUMMARY!D32,'PLAN BUDGET SAMI-JF'!J13:J100000,SUMMARY!A32&"*") -> 0 | W32: =SUMIFS('PLAN BUDGET SAMI-JF'!BI13:BI100000,'PLAN BUDGET SAMI-JF'!D13:D100000,SUMMARY!D32,'PLAN BUDGET SAMI-JF'!J13:J100000,SUMMARY!A32&"*") -> 0 | X32: =SUMIFS('PLAN BUDGET SAMI-JF'!BJ13:BJ100000,'PLAN BUDGET SAMI-JF'!D13:D100000,SUMMARY!D32,'PLAN BUDGET SAMI-JF'!J13:J100000,SUMMARY!A32&"*") -> 0 | Y32: =SUMIFS('PLAN BUDGET SAMI-JF'!BK13:BK100000,'PLAN BUDGET SAMI-JF'!D13:D100000,SUMMARY!D32,'PLAN BUDGET SAMI-JF'!J13:J100000,SUMMARY!A32&"*") -> 0 | Z32: =SUMIFS('PLAN BUDGET SAMI-JF'!BL13:BL100000,'PLAN BUDGET SAMI-JF'!D13:D100000,SUMMARY!D32,'PLAN BUDGET SAMI-JF'!J13:J100000,SUMMARY!A32&"*") -> 0 | AA32: =SUMIFS('PLAN BUDGET SAMI-JF'!BM13:BM100000,'PLAN BUDGET SAMI-JF'!D13:D100000,SUMMARY!D32,'PLAN BUDGET SAMI-JF'!J13:J100000,SUMMARY!A32&"*") -> 0 | AB32: =SUMIFS('PLAN BUDGET SAMI-JF'!BN13:BN100000,'PLAN BUDGET SAMI-JF'!D13:D100000,SUMMARY!D32,'PLAN BUDGET SAMI-JF'!J13:J100000,SUMMARY!A32&"*") -> 0 | AC32: =SUM(E32:P32) -> 0 | AD32: =SUM(Q32:AB32) -> 0 | AF32: 45 | AG32: 24524.325 | AH32: =IFERROR((AC32-AF32)/AF32,1) -> -1 | AI32: =IFERROR((AD32-AG32)/AG32,1) -> -1 | AJ32: Budget di Term 85 tidak ada, sedangkan di Term 84 ada.
A33: INSIDENTAL | D33: ACRYLIC | E33: =SUMIFS('PLAN BUDGET SAMI-JF'!AN13:AN100000,'PLAN BUDGET SAMI-JF'!D13:D100000,SUMMARY!D33,'PLAN BUDGET SAMI-JF'!J13:J100000,SUMMARY!A33&"*") -> 0 | F33: =SUMIFS('PLAN BUDGET SAMI-JF'!AO13:AO100000,'PLAN BUDGET SAMI-JF'!D13:D100000,SUMMARY!D33,'PLAN BUDGET SAMI-JF'!J13:J100000,SUMMARY!A33&"*") -> 0 | G33: =SUMIFS('PLAN BUDGET SAMI-JF'!AP13:AP100000,'PLAN BUDGET SAMI-JF'!D13:D100000,SUMMARY!D33,'PLAN BUDGET SAMI-JF'!J13:J100000,SUMMARY!A33&"*") -> 0 | H33: =SUMIFS('PLAN BUDGET SAMI-JF'!AQ13:AQ100000,'PLAN BUDGET SAMI-JF'!D13:D100000,SUMMARY!D33,'PLAN BUDGET SAMI-JF'!J13:J100000,SUMMARY!A33&"*") -> 0 | I33: =SUMIFS('PLAN BUDGET SAMI-JF'!AR13:AR100000,'PLAN BUDGET SAMI-JF'!D13:D100000,SUMMARY!D33,'PLAN BUDGET SAMI-JF'!J13:J100000,SUMMARY!A33&"*") -> 0 | J33: =SUMIFS('PLAN BUDGET SAMI-JF'!AS13:AS100000,'PLAN BUDGET SAMI-JF'!D13:D100000,SUMMARY!D33,'PLAN BUDGET SAMI-JF'!J13:J100000,SUMMARY!A33&"*") -> 0 | K33: =SUMIFS('PLAN BUDGET SAMI-JF'!AT13:AT100000,'PLAN BUDGET SAMI-JF'!D13:D100000,SUMMARY!D33,'PLAN BUDGET SAMI-JF'!J13:J100000,SUMMARY!A33&"*") -> 0 | L33: =SUMIFS('PLAN BUDGET SAMI-JF'!AU13:AU100000,'PLAN BUDGET SAMI-JF'!D13:D100000,SUMMARY!D33,'PLAN BUDGET SAMI-JF'!J13:J100000,SUMMARY!A33&"*") -> 0 | M33: =SUMIFS('PLAN BUDGET SAMI-JF'!AV13:AV100000,'PLAN BUDGET SAMI-JF'!D13:D100000,SUMMARY!D33,'PLAN BUDGET SAMI-JF'!J13:J100000,SUMMARY!A33&"*") -> 0 | N33: =SUMIFS('PLAN BUDGET SAMI-JF'!AW13:AW100000,'PLAN BUDGET SAMI-JF'!D13:D100000,SUMMARY!D33,'PLAN BUDGET SAMI-JF'!J13:J100000,SUMMARY!A33&"*") -> 0 | O33: =SUMIFS('PLAN BUDGET SAMI-JF'!AX13:AX100000,'PLAN BUDGET SAMI-JF'!D13:D100000,SUMMARY!D33,'PLAN BUDGET SAMI-JF'!J13:J100000,SUMMARY!A33&"*") -> 0 | P33: =SUMIFS('PLAN BUDGET SAMI-JF'!AY13:AY100000,'PLAN BUDGET SAMI-JF'!D13:D100000,SUMMARY!D33,'PLAN BUDGET SAMI-JF'!J13:J100000,SUMMARY!A33&"*") -> 0 | Q33: =SUMIFS('PLAN BUDGET SAMI-JF'!BC13:BC100000,'PLAN BUDGET SAMI-JF'!D13:D100000,SUMMARY!D33,'PLAN BUDGET SAMI-JF'!J13:J100000,SUMMARY!A33&"*") -> 0 | R33: =SUMIFS('PLAN BUDGET SAMI-JF'!BD13:BD100000,'PLAN BUDGET SAMI-JF'!D13:D100000,SUMMARY!D33,'PLAN BUDGET SAMI-JF'!J13:J100000,SUMMARY!A33&"*") -> 0 | S33: =SUMIFS('PLAN BUDGET SAMI-JF'!BE13:BE100000,'PLAN BUDGET SAMI-JF'!D13:D100000,SUMMARY!D33,'PLAN BUDGET SAMI-JF'!J13:J100000,SUMMARY!A33&"*") -> 0 | T33: =SUMIFS('PLAN BUDGET SAMI-JF'!BF13:BF100000,'PLAN BUDGET SAMI-JF'!D13:D100000,SUMMARY!D33,'PLAN BUDGET SAMI-JF'!J13:J100000,SUMMARY!A33&"*") -> 0 | U33: =SUMIFS('PLAN BUDGET SAMI-JF'!BG13:BG100000,'PLAN BUDGET SAMI-JF'!D13:D100000,SUMMARY!D33,'PLAN BUDGET SAMI-JF'!J13:J100000,SUMMARY!A33&"*") -> 0 | V33: =SUMIFS('PLAN BUDGET SAMI-JF'!BH13:BH100000,'PLAN BUDGET SAMI-JF'!D13:D100000,SUMMARY!D33,'PLAN BUDGET SAMI-JF'!J13:J100000,SUMMARY!A33&"*") -> 0 | W33: =SUMIFS('PLAN BUDGET SAMI-JF'!BI13:BI100000,'PLAN BUDGET SAMI-JF'!D13:D100000,SUMMARY!D33,'PLAN BUDGET SAMI-JF'!J13:J100000,SUMMARY!A33&"*") -> 0 | X33: =SUMIFS('PLAN BUDGET SAMI-JF'!BJ13:BJ100000,'PLAN BUDGET SAMI-JF'!D13:D100000,SUMMARY!D33,'PLAN BUDGET SAMI-JF'!J13:J100000,SUMMARY!A33&"*") -> 0 | Y33: =SUMIFS('PLAN BUDGET SAMI-JF'!BK13:BK100000,'PLAN BUDGET SAMI-JF'!D13:D100000,SUMMARY!D33,'PLAN BUDGET SAMI-JF'!J13:J100000,SUMMARY!A33&"*") -> 0 | Z33: =SUMIFS('PLAN BUDGET SAMI-JF'!BL13:BL100000,'PLAN BUDGET SAMI-JF'!D13:D100000,SUMMARY!D33,'PLAN BUDGET SAMI-JF'!J13:J100000,SUMMARY!A33&"*") -> 0 | AA33: =SUMIFS('PLAN BUDGET SAMI-JF'!BM13:BM100000,'PLAN BUDGET SAMI-JF'!D13:D100000,SUMMARY!D33,'PLAN BUDGET SAMI-JF'!J13:J100000,SUMMARY!A33&"*") -> 0 | AB33: =SUMIFS('PLAN BUDGET SAMI-JF'!BN13:BN100000,'PLAN BUDGET SAMI-JF'!D13:D100000,SUMMARY!D33,'PLAN BUDGET SAMI-JF'!J13:J100000,SUMMARY!A33&"*") -> 0 | AC33: =SUM(E33:P33) -> 0 | AD33: =SUM(Q33:AB33) -> 0 | AF33: 4 | AG33: 124.06163 | AH33: =IFERROR((AC33-AF33)/AF33,1) -> -1 | AI33: =IFERROR((AD33-AG33)/AG33,1) -> -1 | AJ33: Budget di Term 85 tidak ada, sedangkan di Term 84 ada.
A34: INSIDENTAL | D34: BATERAY | E34: =SUMIFS('PLAN BUDGET SAMI-JF'!AN13:AN100000,'PLAN BUDGET SAMI-JF'!D13:D100000,SUMMARY!D34,'PLAN BUDGET SAMI-JF'!J13:J100000,SUMMARY!A34&"*") -> 0 | F34: =SUMIFS('PLAN BUDGET SAMI-JF'!AO13:AO100000,'PLAN BUDGET SAMI-JF'!D13:D100000,SUMMARY!D34,'PLAN BUDGET SAMI-JF'!J13:J100000,SUMMARY!A34&"*") -> 0 | G34: =SUMIFS('PLAN BUDGET SAMI-JF'!AP13:AP100000,'PLAN BUDGET SAMI-JF'!D13:D100000,SUMMARY!D34,'PLAN BUDGET SAMI-JF'!J13:J100000,SUMMARY!A34&"*") -> 0 | H34: =SUMIFS('PLAN BUDGET SAMI-JF'!AQ13:AQ100000,'PLAN BUDGET SAMI-JF'!D13:D100000,SUMMARY!D34,'PLAN BUDGET SAMI-JF'!J13:J100000,SUMMARY!A34&"*") -> 0 | I34: =SUMIFS('PLAN BUDGET SAMI-JF'!AR13:AR100000,'PLAN BUDGET SAMI-JF'!D13:D100000,SUMMARY!D34,'PLAN BUDGET SAMI-JF'!J13:J100000,SUMMARY!A34&"*") -> 0 | J34: =SUMIFS('PLAN BUDGET SAMI-JF'!AS13:AS100000,'PLAN BUDGET SAMI-JF'!D13:D100000,SUMMARY!D34,'PLAN BUDGET SAMI-JF'!J13:J100000,SUMMARY!A34&"*") -> 0 | K34: =SUMIFS('PLAN BUDGET SAMI-JF'!AT13:AT100000,'PLAN BUDGET SAMI-JF'!D13:D100000,SUMMARY!D34,'PLAN BUDGET SAMI-JF'!J13:J100000,SUMMARY!A34&"*") -> 0 | L34: =SUMIFS('PLAN BUDGET SAMI-JF'!AU13:AU100000,'PLAN BUDGET SAMI-JF'!D13:D100000,SUMMARY!D34,'PLAN BUDGET SAMI-JF'!J13:J100000,SUMMARY!A34&"*") -> 0 | M34: =SUMIFS('PLAN BUDGET SAMI-JF'!AV13:AV100000,'PLAN BUDGET SAMI-JF'!D13:D100000,SUMMARY!D34,'PLAN BUDGET SAMI-JF'!J13:J100000,SUMMARY!A34&"*") -> 0 | N34: =SUMIFS('PLAN BUDGET SAMI-JF'!AW13:AW100000,'PLAN BUDGET SAMI-JF'!D13:D100000,SUMMARY!D34,'PLAN BUDGET SAMI-JF'!J13:J100000,SUMMARY!A34&"*") -> 0 | O34: =SUMIFS('PLAN BUDGET SAMI-JF'!AX13:AX100000,'PLAN BUDGET SAMI-JF'!D13:D100000,SUMMARY!D34,'PLAN BUDGET SAMI-JF'!J13:J100000,SUMMARY!A34&"*") -> 0 | P34: =SUMIFS('PLAN BUDGET SAMI-JF'!AY13:AY100000,'PLAN BUDGET SAMI-JF'!D13:D100000,SUMMARY!D34,'PLAN BUDGET SAMI-JF'!J13:J100000,SUMMARY!A34&"*") -> 0 | Q34: =SUMIFS('PLAN BUDGET SAMI-JF'!BC13:BC100000,'PLAN BUDGET SAMI-JF'!D13:D100000,SUMMARY!D34,'PLAN BUDGET SAMI-JF'!J13:J100000,SUMMARY!A34&"*") -> 0 | R34: =SUMIFS('PLAN BUDGET SAMI-JF'!BD13:BD100000,'PLAN BUDGET SAMI-JF'!D13:D100000,SUMMARY!D34,'PLAN BUDGET SAMI-JF'!J13:J100000,SUMMARY!A34&"*") -> 0 | S34: =SUMIFS('PLAN BUDGET SAMI-JF'!BE13:BE100000,'PLAN BUDGET SAMI-JF'!D13:D100000,SUMMARY!D34,'PLAN BUDGET SAMI-JF'!J13:J100000,SUMMARY!A34&"*") -> 0 | T34: =SUMIFS('PLAN BUDGET SAMI-JF'!BF13:BF100000,'PLAN BUDGET SAMI-JF'!D13:D100000,SUMMARY!D34,'PLAN BUDGET SAMI-JF'!J13:J100000,SUMMARY!A34&"*") -> 0 | U34: =SUMIFS('PLAN BUDGET SAMI-JF'!BG13:BG100000,'PLAN BUDGET SAMI-JF'!D13:D100000,SUMMARY!D34,'PLAN BUDGET SAMI-JF'!J13:J100000,SUMMARY!A34&"*") -> 0 | V34: =SUMIFS('PLAN BUDGET SAMI-JF'!BH13:BH100000,'PLAN BUDGET SAMI-JF'!D13:D100000,SUMMARY!D34,'PLAN BUDGET SAMI-JF'!J13:J100000,SUMMARY!A34&"*") -> 0 | W34: =SUMIFS('PLAN BUDGET SAMI-JF'!BI13:BI100000,'PLAN BUDGET SAMI-JF'!D13:D100000,SUMMARY!D34,'PLAN BUDGET SAMI-JF'!J13:J100000,SUMMARY!A34&"*") -> 0 | X34: =SUMIFS('PLAN BUDGET SAMI-JF'!BJ13:BJ100000,'PLAN BUDGET SAMI-JF'!D13:D100000,SUMMARY!D34,'PLAN BUDGET SAMI-JF'!J13:J100000,SUMMARY!A34&"*") -> 0 | Y34: =SUMIFS('PLAN BUDGET SAMI-JF'!BK13:BK100000,'PLAN BUDGET SAMI-JF'!D13:D100000,SUMMARY!D34,'PLAN BUDGET SAMI-JF'!J13:J100000,SUMMARY!A34&"*") -> 0 | Z34: =SUMIFS('PLAN BUDGET SAMI-JF'!BL13:BL100000,'PLAN BUDGET SAMI-JF'!D13:D100000,SUMMARY!D34,'PLAN BUDGET SAMI-JF'!J13:J100000,SUMMARY!A34&"*") -> 0 | AA34: =SUMIFS('PLAN BUDGET SAMI-JF'!BM13:BM100000,'PLAN BUDGET SAMI-JF'!D13:D100000,SUMMARY!D34,'PLAN BUDGET SAMI-JF'!J13:J100000,SUMMARY!A34&"*") -> 0 | AB34: =SUMIFS('PLAN BUDGET SAMI-JF'!BN13:BN100000,'PLAN BUDGET SAMI-JF'!D13:D100000,SUMMARY!D34,'PLAN BUDGET SAMI-JF'!J13:J100000,SUMMARY!A34&"*") -> 0 | AC34: =SUM(E34:P34) -> 0 | AD34: =SUM(Q34:AB34) -> 0 | AF34: 1 | AG34: 46.52311 | AH34: =IFERROR((AC34-AF34)/AF34,1) -> -1 | AI34: =IFERROR((AD34-AG34)/AG34,1) -> -1 | AJ34: Budget di Term 85 tidak ada, sedangkan di Term 84 ada.
A35: INSIDENTAL | D35: BATTERY CAMERA | E35: =SUMIFS('PLAN BUDGET SAMI-JF'!AN13:AN100000,'PLAN BUDGET SAMI-JF'!D13:D100000,SUMMARY!D35,'PLAN BUDGET SAMI-JF'!J13:J100000,SUMMARY!A35&"*") -> 0 | F35: =SUMIFS('PLAN BUDGET SAMI-JF'!AO13:AO100000,'PLAN BUDGET SAMI-JF'!D13:D100000,SUMMARY!D35,'PLAN BUDGET SAMI-JF'!J13:J100000,SUMMARY!A35&"*") -> 0 | G35: =SUMIFS('PLAN BUDGET SAMI-JF'!AP13:AP100000,'PLAN BUDGET SAMI-JF'!D13:D100000,SUMMARY!D35,'PLAN BUDGET SAMI-JF'!J13:J100000,SUMMARY!A35&"*") -> 0 | H35: =SUMIFS('PLAN BUDGET SAMI-JF'!AQ13:AQ100000,'PLAN BUDGET SAMI-JF'!D13:D100000,SUMMARY!D35,'PLAN BUDGET SAMI-JF'!J13:J100000,SUMMARY!A35&"*") -> 0 | I35: =SUMIFS('PLAN BUDGET SAMI-JF'!AR13:AR100000,'PLAN BUDGET SAMI-JF'!D13:D100000,SUMMARY!D35,'PLAN BUDGET SAMI-JF'!J13:J100000,SUMMARY!A35&"*") -> 0 | J35: =SUMIFS('PLAN BUDGET SAMI-JF'!AS13:AS100000,'PLAN BUDGET SAMI-JF'!D13:D100000,SUMMARY!D35,'PLAN BUDGET SAMI-JF'!J13:J100000,SUMMARY!A35&"*") -> 0 | K35: =SUMIFS('PLAN BUDGET SAMI-JF'!AT13:AT100000,'PLAN BUDGET SAMI-JF'!D13:D100000,SUMMARY!D35,'PLAN BUDGET SAMI-JF'!J13:J100000,SUMMARY!A35&"*") -> 0 | L35: =SUMIFS('PLAN BUDGET SAMI-JF'!AU13:AU100000,'PLAN BUDGET SAMI-JF'!D13:D100000,SUMMARY!D35,'PLAN BUDGET SAMI-JF'!J13:J100000,SUMMARY!A35&"*") -> 0 | M35: =SUMIFS('PLAN BUDGET SAMI-JF'!AV13:AV100000,'PLAN BUDGET SAMI-JF'!D13:D100000,SUMMARY!D35,'PLAN BUDGET SAMI-JF'!J13:J100000,SUMMARY!A35&"*") -> 0 | N35: =SUMIFS('PLAN BUDGET SAMI-JF'!AW13:AW100000,'PLAN BUDGET SAMI-JF'!D13:D100000,SUMMARY!D35,'PLAN BUDGET SAMI-JF'!J13:J100000,SUMMARY!A35&"*") -> 0 | O35: =SUMIFS('PLAN BUDGET SAMI-JF'!AX13:AX100000,'PLAN BUDGET SAMI-JF'!D13:D100000,SUMMARY!D35,'PLAN BUDGET SAMI-JF'!J13:J100000,SUMMARY!A35&"*") -> 0 | P35: =SUMIFS('PLAN BUDGET SAMI-JF'!AY13:AY100000,'PLAN BUDGET SAMI-JF'!D13:D100000,SUMMARY!D35,'PLAN BUDGET SAMI-JF'!J13:J100000,SUMMARY!A35&"*") -> 0 | Q35: =SUMIFS('PLAN BUDGET SAMI-JF'!BC13:BC100000,'PLAN BUDGET SAMI-JF'!D13:D100000,SUMMARY!D35,'PLAN BUDGET SAMI-JF'!J13:J100000,SUMMARY!A35&"*") -> 0 | R35: =SUMIFS('PLAN BUDGET SAMI-JF'!BD13:BD100000,'PLAN BUDGET SAMI-JF'!D13:D100000,SUMMARY!D35,'PLAN BUDGET SAMI-JF'!J13:J100000,SUMMARY!A35&"*") -> 0 | S35: =SUMIFS('PLAN BUDGET SAMI-JF'!BE13:BE100000,'PLAN BUDGET SAMI-JF'!D13:D100000,SUMMARY!D35,'PLAN BUDGET SAMI-JF'!J13:J100000,SUMMARY!A35&"*") -> 0 | T35: =SUMIFS('PLAN BUDGET SAMI-JF'!BF13:BF100000,'PLAN BUDGET SAMI-JF'!D13:D100000,SUMMARY!D35,'PLAN BUDGET SAMI-JF'!J13:J100000,SUMMARY!A35&"*") -> 0 | U35: =SUMIFS('PLAN BUDGET SAMI-JF'!BG13:BG100000,'PLAN BUDGET SAMI-JF'!D13:D100000,SUMMARY!D35,'PLAN BUDGET SAMI-JF'!J13:J100000,SUMMARY!A35&"*") -> 0 | V35: =SUMIFS('PLAN BUDGET SAMI-JF'!BH13:BH100000,'PLAN BUDGET SAMI-JF'!D13:D100000,SUMMARY!D35,'PLAN BUDGET SAMI-JF'!J13:J100000,SUMMARY!A35&"*") -> 0 | W35: =SUMIFS('PLAN BUDGET SAMI-JF'!BI13:BI100000,'PLAN BUDGET SAMI-JF'!D13:D100000,SUMMARY!D35,'PLAN BUDGET SAMI-JF'!J13:J100000,SUMMARY!A35&"*") -> 0 | X35: =SUMIFS('PLAN BUDGET SAMI-JF'!BJ13:BJ100000,'PLAN BUDGET SAMI-JF'!D13:D100000,SUMMARY!D35,'PLAN BUDGET SAMI-JF'!J13:J100000,SUMMARY!A35&"*") -> 0 | Y35: =SUMIFS('PLAN BUDGET SAMI-JF'!BK13:BK100000,'PLAN BUDGET SAMI-JF'!D13:D100000,SUMMARY!D35,'PLAN BUDGET SAMI-JF'!J13:J100000,SUMMARY!A35&"*") -> 0 | Z35: =SUMIFS('PLAN BUDGET SAMI-JF'!BL13:BL100000,'PLAN BUDGET SAMI-JF'!D13:D100000,SUMMARY!D35,'PLAN BUDGET SAMI-JF'!J13:J100000,SUMMARY!A35&"*") -> 0 | AA35: =SUMIFS('PLAN BUDGET SAMI-JF'!BM13:BM100000,'PLAN BUDGET SAMI-JF'!D13:D100000,SUMMARY!D35,'PLAN BUDGET SAMI-JF'!J13:J100000,SUMMARY!A35&"*") -> 0 | AB35: =SUMIFS('PLAN BUDGET SAMI-JF'!BN13:BN100000,'PLAN BUDGET SAMI-JF'!D13:D100000,SUMMARY!D35,'PLAN BUDGET SAMI-JF'!J13:J100000,SUMMARY!A35&"*") -> 0 | AC35: =SUM(E35:P35) -> 0 | AD35: =SUM(Q35:AB35) -> 0 | AF35: 1 | AG35: 28.483537 | AH35: =IFERROR((AC35-AF35)/AF35,1) -> -1 | AI35: =IFERROR((AD35-AG35)/AG35,1) -> -1 | AJ35: Budget di Term 85 tidak ada, sedangkan di Term 84 ada.
A36: INSIDENTAL | D36: BIAYA PENGAMBILAN PAKET DOKUMEN | E36: =SUMIFS('PLAN BUDGET SAMI-JF'!AN13:AN100000,'PLAN BUDGET SAMI-JF'!D13:D100000,SUMMARY!D36,'PLAN BUDGET SAMI-JF'!J13:J100000,SUMMARY!A36&"*") -> 0 | F36: =SUMIFS('PLAN BUDGET SAMI-JF'!AO13:AO100000,'PLAN BUDGET SAMI-JF'!D13:D100000,SUMMARY!D36,'PLAN BUDGET SAMI-JF'!J13:J100000,SUMMARY!A36&"*") -> 0 | G36: =SUMIFS('PLAN BUDGET SAMI-JF'!AP13:AP100000,'PLAN BUDGET SAMI-JF'!D13:D100000,SUMMARY!D36,'PLAN BUDGET SAMI-JF'!J13:J100000,SUMMARY!A36&"*") -> 0 | H36: =SUMIFS('PLAN BUDGET SAMI-JF'!AQ13:AQ100000,'PLAN BUDGET SAMI-JF'!D13:D100000,SUMMARY!D36,'PLAN BUDGET SAMI-JF'!J13:J100000,SUMMARY!A36&"*") -> 0 | I36: =SUMIFS('PLAN BUDGET SAMI-JF'!AR13:AR100000,'PLAN BUDGET SAMI-JF'!D13:D100000,SUMMARY!D36,'PLAN BUDGET SAMI-JF'!J13:J100000,SUMMARY!A36&"*") -> 0 | J36: =SUMIFS('PLAN BUDGET SAMI-JF'!AS13:AS100000,'PLAN BUDGET SAMI-JF'!D13:D100000,SUMMARY!D36,'PLAN BUDGET SAMI-JF'!J13:J100000,SUMMARY!A36&"*") -> 0 | K36: =SUMIFS('PLAN BUDGET SAMI-JF'!AT13:AT100000,'PLAN BUDGET SAMI-JF'!D13:D100000,SUMMARY!D36,'PLAN BUDGET SAMI-JF'!J13:J100000,SUMMARY!A36&"*") -> 0 | L36: =SUMIFS('PLAN BUDGET SAMI-JF'!AU13:AU100000,'PLAN BUDGET SAMI-JF'!D13:D100000,SUMMARY!D36,'PLAN BUDGET SAMI-JF'!J13:J100000,SUMMARY!A36&"*") -> 0 | M36: =SUMIFS('PLAN BUDGET SAMI-JF'!AV13:AV100000,'PLAN BUDGET SAMI-JF'!D13:D100000,SUMMARY!D36,'PLAN BUDGET SAMI-JF'!J13:J100000,SUMMARY!A36&"*") -> 0 | N36: =SUMIFS('PLAN BUDGET SAMI-JF'!AW13:AW100000,'PLAN BUDGET SAMI-JF'!D13:D100000,SUMMARY!D36,'PLAN BUDGET SAMI-JF'!J13:J100000,SUMMARY!A36&"*") -> 0 | O36: =SUMIFS('PLAN BUDGET SAMI-JF'!AX13:AX100000,'PLAN BUDGET SAMI-JF'!D13:D100000,SUMMARY!D36,'PLAN BUDGET SAMI-JF'!J13:J100000,SUMMARY!A36&"*") -> 0 | P36: =SUMIFS('PLAN BUDGET SAMI-JF'!AY13:AY100000,'PLAN BUDGET SAMI-JF'!D13:D100000,SUMMARY!D36,'PLAN BUDGET SAMI-JF'!J13:J100000,SUMMARY!A36&"*") -> 0 | Q36: =SUMIFS('PLAN BUDGET SAMI-JF'!BC13:BC100000,'PLAN BUDGET SAMI-JF'!D13:D100000,SUMMARY!D36,'PLAN BUDGET SAMI-JF'!J13:J100000,SUMMARY!A36&"*") -> 0 | R36: =SUMIFS('PLAN BUDGET SAMI-JF'!BD13:BD100000,'PLAN BUDGET SAMI-JF'!D13:D100000,SUMMARY!D36,'PLAN BUDGET SAMI-JF'!J13:J100000,SUMMARY!A36&"*") -> 0 | S36: =SUMIFS('PLAN BUDGET SAMI-JF'!BE13:BE100000,'PLAN BUDGET SAMI-JF'!D13:D100000,SUMMARY!D36,'PLAN BUDGET SAMI-JF'!J13:J100000,SUMMARY!A36&"*") -> 0 | T36: =SUMIFS('PLAN BUDGET SAMI-JF'!BF13:BF100000,'PLAN BUDGET SAMI-JF'!D13:D100000,SUMMARY!D36,'PLAN BUDGET SAMI-JF'!J13:J100000,SUMMARY!A36&"*") -> 0 | U36: =SUMIFS('PLAN BUDGET SAMI-JF'!BG13:BG100000,'PLAN BUDGET SAMI-JF'!D13:D100000,SUMMARY!D36,'PLAN BUDGET SAMI-JF'!J13:J100000,SUMMARY!A36&"*") -> 0 | V36: =SUMIFS('PLAN BUDGET SAMI-JF'!BH13:BH100000,'PLAN BUDGET SAMI-JF'!D13:D100000,SUMMARY!D36,'PLAN BUDGET SAMI-JF'!J13:J100000,SUMMARY!A36&"*") -> 0 | W36: =SUMIFS('PLAN BUDGET SAMI-JF'!BI13:BI100000,'PLAN BUDGET SAMI-JF'!D13:D100000,SUMMARY!D36,'PLAN BUDGET SAMI-JF'!J13:J100000,SUMMARY!A36&"*") -> 0 | X36: =SUMIFS('PLAN BUDGET SAMI-JF'!BJ13:BJ100000,'PLAN BUDGET SAMI-JF'!D13:D100000,SUMMARY!D36,'PLAN BUDGET SAMI-JF'!J13:J100000,SUMMARY!A36&"*") -> 0 | Y36: =SUMIFS('PLAN BUDGET SAMI-JF'!BK13:BK100000,'PLAN BUDGET SAMI-JF'!D13:D100000,SUMMARY!D36,'PLAN BUDGET SAMI-JF'!J13:J100000,SUMMARY!A36&"*") -> 0 | Z36: =SUMIFS('PLAN BUDGET SAMI-JF'!BL13:BL100000,'PLAN BUDGET SAMI-JF'!D13:D100000,SUMMARY!D36,'PLAN BUDGET SAMI-JF'!J13:J100000,SUMMARY!A36&"*") -> 0 | AA36: =SUMIFS('PLAN BUDGET SAMI-JF'!BM13:BM100000,'PLAN BUDGET SAMI-JF'!D13:D100000,SUMMARY!D36,'PLAN BUDGET SAMI-JF'!J13:J100000,SUMMARY!A36&"*") -> 0 | AB36: =SUMIFS('PLAN BUDGET SAMI-JF'!BN13:BN100000,'PLAN BUDGET SAMI-JF'!D13:D100000,SUMMARY!D36,'PLAN BUDGET SAMI-JF'!J13:J100000,SUMMARY!A36&"*") -> 0 | AC36: =SUM(E36:P36) -> 0 | AD36: =SUM(Q36:AB36) -> 0 | AF36: 1 | AG36: 2.8103756 | AH36: =IFERROR((AC36-AF36)/AF36,1) -> -1 | AI36: =IFERROR((AD36-AG36)/AG36,1) -> -1 | AJ36: Budget di Term 85 tidak ada, sedangkan di Term 84 ada.
A37: INSIDENTAL | D37: BUTTON | E37: =SUMIFS('PLAN BUDGET SAMI-JF'!AN13:AN100000,'PLAN BUDGET SAMI-JF'!D13:D100000,SUMMARY!D37,'PLAN BUDGET SAMI-JF'!J13:J100000,SUMMARY!A37&"*") -> 0 | F37: =SUMIFS('PLAN BUDGET SAMI-JF'!AO13:AO100000,'PLAN BUDGET SAMI-JF'!D13:D100000,SUMMARY!D37,'PLAN BUDGET SAMI-JF'!J13:J100000,SUMMARY!A37&"*") -> 0 | G37: =SUMIFS('PLAN BUDGET SAMI-JF'!AP13:AP100000,'PLAN BUDGET SAMI-JF'!D13:D100000,SUMMARY!D37,'PLAN BUDGET SAMI-JF'!J13:J100000,SUMMARY!A37&"*") -> 0 | H37: =SUMIFS('PLAN BUDGET SAMI-JF'!AQ13:AQ100000,'PLAN BUDGET SAMI-JF'!D13:D100000,SUMMARY!D37,'PLAN BUDGET SAMI-JF'!J13:J100000,SUMMARY!A37&"*") -> 0 | I37: =SUMIFS('PLAN BUDGET SAMI-JF'!AR13:AR100000,'PLAN BUDGET SAMI-JF'!D13:D100000,SUMMARY!D37,'PLAN BUDGET SAMI-JF'!J13:J100000,SUMMARY!A37&"*") -> 0 | J37: =SUMIFS('PLAN BUDGET SAMI-JF'!AS13:AS100000,'PLAN BUDGET SAMI-JF'!D13:D100000,SUMMARY!D37,'PLAN BUDGET SAMI-JF'!J13:J100000,SUMMARY!A37&"*") -> 0 | K37: =SUMIFS('PLAN BUDGET SAMI-JF'!AT13:AT100000,'PLAN BUDGET SAMI-JF'!D13:D100000,SUMMARY!D37,'PLAN BUDGET SAMI-JF'!J13:J100000,SUMMARY!A37&"*") -> 0 | L37: =SUMIFS('PLAN BUDGET SAMI-JF'!AU13:AU100000,'PLAN BUDGET SAMI-JF'!D13:D100000,SUMMARY!D37,'PLAN BUDGET SAMI-JF'!J13:J100000,SUMMARY!A37&"*") -> 0 | M37: =SUMIFS('PLAN BUDGET SAMI-JF'!AV13:AV100000,'PLAN BUDGET SAMI-JF'!D13:D100000,SUMMARY!D37,'PLAN BUDGET SAMI-JF'!J13:J100000,SUMMARY!A37&"*") -> 0 | N37: =SUMIFS('PLAN BUDGET SAMI-JF'!AW13:AW100000,'PLAN BUDGET SAMI-JF'!D13:D100000,SUMMARY!D37,'PLAN BUDGET SAMI-JF'!J13:J100000,SUMMARY!A37&"*") -> 0 | O37: =SUMIFS('PLAN BUDGET SAMI-JF'!AX13:AX100000,'PLAN BUDGET SAMI-JF'!D13:D100000,SUMMARY!D37,'PLAN BUDGET SAMI-JF'!J13:J100000,SUMMARY!A37&"*") -> 0 | P37: =SUMIFS('PLAN BUDGET SAMI-JF'!AY13:AY100000,'PLAN BUDGET SAMI-JF'!D13:D100000,SUMMARY!D37,'PLAN BUDGET SAMI-JF'!J13:J100000,SUMMARY!A37&"*") -> 0 | Q37: =SUMIFS('PLAN BUDGET SAMI-JF'!BC13:BC100000,'PLAN BUDGET SAMI-JF'!D13:D100000,SUMMARY!D37,'PLAN BUDGET SAMI-JF'!J13:J100000,SUMMARY!A37&"*") -> 0 | R37: =SUMIFS('PLAN BUDGET SAMI-JF'!BD13:BD100000,'PLAN BUDGET SAMI-JF'!D13:D100000,SUMMARY!D37,'PLAN BUDGET SAMI-JF'!J13:J100000,SUMMARY!A37&"*") -> 0 | S37: =SUMIFS('PLAN BUDGET SAMI-JF'!BE13:BE100000,'PLAN BUDGET SAMI-JF'!D13:D100000,SUMMARY!D37,'PLAN BUDGET SAMI-JF'!J13:J100000,SUMMARY!A37&"*") -> 0 | T37: =SUMIFS('PLAN BUDGET SAMI-JF'!BF13:BF100000,'PLAN BUDGET SAMI-JF'!D13:D100000,SUMMARY!D37,'PLAN BUDGET SAMI-JF'!J13:J100000,SUMMARY!A37&"*") -> 0 | U37: =SUMIFS('PLAN BUDGET SAMI-JF'!BG13:BG100000,'PLAN BUDGET SAMI-JF'!D13:D100000,SUMMARY!D37,'PLAN BUDGET SAMI-JF'!J13:J100000,SUMMARY!A37&"*") -> 0 | V37: =SUMIFS('PLAN BUDGET SAMI-JF'!BH13:BH100000,'PLAN BUDGET SAMI-JF'!D13:D100000,SUMMARY!D37,'PLAN BUDGET SAMI-JF'!J13:J100000,SUMMARY!A37&"*") -> 0 | W37: =SUMIFS('PLAN BUDGET SAMI-JF'!BI13:BI100000,'PLAN BUDGET SAMI-JF'!D13:D100000,SUMMARY!D37,'PLAN BUDGET SAMI-JF'!J13:J100000,SUMMARY!A37&"*") -> 0 | X37: =SUMIFS('PLAN BUDGET SAMI-JF'!BJ13:BJ100000,'PLAN BUDGET SAMI-JF'!D13:D100000,SUMMARY!D37,'PLAN BUDGET SAMI-JF'!J13:J100000,SUMMARY!A37&"*") -> 0 | Y37: =SUMIFS('PLAN BUDGET SAMI-JF'!BK13:BK100000,'PLAN BUDGET SAMI-JF'!D13:D100000,SUMMARY!D37,'PLAN BUDGET SAMI-JF'!J13:J100000,SUMMARY!A37&"*") -> 0 | Z37: =SUMIFS('PLAN BUDGET SAMI-JF'!BL13:BL100000,'PLAN BUDGET SAMI-JF'!D13:D100000,SUMMARY!D37,'PLAN BUDGET SAMI-JF'!J13:J100000,SUMMARY!A37&"*") -> 0 | AA37: =SUMIFS('PLAN BUDGET SAMI-JF'!BM13:BM100000,'PLAN BUDGET SAMI-JF'!D13:D100000,SUMMARY!D37,'PLAN BUDGET SAMI-JF'!J13:J100000,SUMMARY!A37&"*") -> 0 | AB37: =SUMIFS('PLAN BUDGET SAMI-JF'!BN13:BN100000,'PLAN BUDGET SAMI-JF'!D13:D100000,SUMMARY!D37,'PLAN BUDGET SAMI-JF'!J13:J100000,SUMMARY!A37&"*") -> 0 | AC37: =SUM(E37:P37) -> 0 | AD37: =SUM(Q37:AB37) -> 0 | AF37: 10 | AG37: 8.3551707 | AH37: =IFERROR((AC37-AF37)/AF37,1) -> -1 | AI37: =IFERROR((AD37-AG37)/AG37,1) -> -1 | AJ37: Budget di Term 85 tidak ada, sedangkan di Term 84 ada.
A38: INSIDENTAL | D38: CAMERA | E38: =SUMIFS('PLAN BUDGET SAMI-JF'!AN13:AN100000,'PLAN BUDGET SAMI-JF'!D13:D100000,SUMMARY!D38,'PLAN BUDGET SAMI-JF'!J13:J100000,SUMMARY!A38&"*") -> 0 | F38: =SUMIFS('PLAN BUDGET SAMI-JF'!AO13:AO100000,'PLAN BUDGET SAMI-JF'!D13:D100000,SUMMARY!D38,'PLAN BUDGET SAMI-JF'!J13:J100000,SUMMARY!A38&"*") -> 0 | G38: =SUMIFS('PLAN BUDGET SAMI-JF'!AP13:AP100000,'PLAN BUDGET SAMI-JF'!D13:D100000,SUMMARY!D38,'PLAN BUDGET SAMI-JF'!J13:J100000,SUMMARY!A38&"*") -> 0 | H38: =SUMIFS('PLAN BUDGET SAMI-JF'!AQ13:AQ100000,'PLAN BUDGET SAMI-JF'!D13:D100000,SUMMARY!D38,'PLAN BUDGET SAMI-JF'!J13:J100000,SUMMARY!A38&"*") -> 0 | I38: =SUMIFS('PLAN BUDGET SAMI-JF'!AR13:AR100000,'PLAN BUDGET SAMI-JF'!D13:D100000,SUMMARY!D38,'PLAN BUDGET SAMI-JF'!J13:J100000,SUMMARY!A38&"*") -> 0 | J38: =SUMIFS('PLAN BUDGET SAMI-JF'!AS13:AS100000,'PLAN BUDGET SAMI-JF'!D13:D100000,SUMMARY!D38,'PLAN BUDGET SAMI-JF'!J13:J100000,SUMMARY!A38&"*") -> 0 | K38: =SUMIFS('PLAN BUDGET SAMI-JF'!AT13:AT100000,'PLAN BUDGET SAMI-JF'!D13:D100000,SUMMARY!D38,'PLAN BUDGET SAMI-JF'!J13:J100000,SUMMARY!A38&"*") -> 0 | L38: =SUMIFS('PLAN BUDGET SAMI-JF'!AU13:AU100000,'PLAN BUDGET SAMI-JF'!D13:D100000,SUMMARY!D38,'PLAN BUDGET SAMI-JF'!J13:J100000,SUMMARY!A38&"*") -> 0 | M38: =SUMIFS('PLAN BUDGET SAMI-JF'!AV13:AV100000,'PLAN BUDGET SAMI-JF'!D13:D100000,SUMMARY!D38,'PLAN BUDGET SAMI-JF'!J13:J100000,SUMMARY!A38&"*") -> 0 | N38: =SUMIFS('PLAN BUDGET SAMI-JF'!AW13:AW100000,'PLAN BUDGET SAMI-JF'!D13:D100000,SUMMARY!D38,'PLAN BUDGET SAMI-JF'!J13:J100000,SUMMARY!A38&"*") -> 0 | O38: =SUMIFS('PLAN BUDGET SAMI-JF'!AX13:AX100000,'PLAN BUDGET SAMI-JF'!D13:D100000,SUMMARY!D38,'PLAN BUDGET SAMI-JF'!J13:J100000,SUMMARY!A38&"*") -> 0 | P38: =SUMIFS('PLAN BUDGET SAMI-JF'!AY13:AY100000,'PLAN BUDGET SAMI-JF'!D13:D100000,SUMMARY!D38,'PLAN BUDGET SAMI-JF'!J13:J100000,SUMMARY!A38&"*") -> 0 | Q38: =SUMIFS('PLAN BUDGET SAMI-JF'!BC13:BC100000,'PLAN BUDGET SAMI-JF'!D13:D100000,SUMMARY!D38,'PLAN BUDGET SAMI-JF'!J13:J100000,SUMMARY!A38&"*") -> 0 | R38: =SUMIFS('PLAN BUDGET SAMI-JF'!BD13:BD100000,'PLAN BUDGET SAMI-JF'!D13:D100000,SUMMARY!D38,'PLAN BUDGET SAMI-JF'!J13:J100000,SUMMARY!A38&"*") -> 0 | S38: =SUMIFS('PLAN BUDGET SAMI-JF'!BE13:BE100000,'PLAN BUDGET SAMI-JF'!D13:D100000,SUMMARY!D38,'PLAN BUDGET SAMI-JF'!J13:J100000,SUMMARY!A38&"*") -> 0 | T38: =SUMIFS('PLAN BUDGET SAMI-JF'!BF13:BF100000,'PLAN BUDGET SAMI-JF'!D13:D100000,SUMMARY!D38,'PLAN BUDGET SAMI-JF'!J13:J100000,SUMMARY!A38&"*") -> 0 | U38: =SUMIFS('PLAN BUDGET SAMI-JF'!BG13:BG100000,'PLAN BUDGET SAMI-JF'!D13:D100000,SUMMARY!D38,'PLAN BUDGET SAMI-JF'!J13:J100000,SUMMARY!A38&"*") -> 0 | V38: =SUMIFS('PLAN BUDGET SAMI-JF'!BH13:BH100000,'PLAN BUDGET SAMI-JF'!D13:D100000,SUMMARY!D38,'PLAN BUDGET SAMI-JF'!J13:J100000,SUMMARY!A38&"*") -> 0 | W38: =SUMIFS('PLAN BUDGET SAMI-JF'!BI13:BI100000,'PLAN BUDGET SAMI-JF'!D13:D100000,SUMMARY!D38,'PLAN BUDGET SAMI-JF'!J13:J100000,SUMMARY!A38&"*") -> 0 | X38: =SUMIFS('PLAN BUDGET SAMI-JF'!BJ13:BJ100000,'PLAN BUDGET SAMI-JF'!D13:D100000,SUMMARY!D38,'PLAN BUDGET SAMI-JF'!J13:J100000,SUMMARY!A38&"*") -> 0 | Y38: =SUMIFS('PLAN BUDGET SAMI-JF'!BK13:BK100000,'PLAN BUDGET SAMI-JF'!D13:D100000,SUMMARY!D38,'PLAN BUDGET SAMI-JF'!J13:J100000,SUMMARY!A38&"*") -> 0 | Z38: =SUMIFS('PLAN BUDGET SAMI-JF'!BL13:BL100000,'PLAN BUDGET SAMI-JF'!D13:D100000,SUMMARY!D38,'PLAN BUDGET SAMI-JF'!J13:J100000,SUMMARY!A38&"*") -> 0 | AA38: =SUMIFS('PLAN BUDGET SAMI-JF'!BM13:BM100000,'PLAN BUDGET SAMI-JF'!D13:D100000,SUMMARY!D38,'PLAN BUDGET SAMI-JF'!J13:J100000,SUMMARY!A38&"*") -> 0 | AB38: =SUMIFS('PLAN BUDGET SAMI-JF'!BN13:BN100000,'PLAN BUDGET SAMI-JF'!D13:D100000,SUMMARY!D38,'PLAN BUDGET SAMI-JF'!J13:J100000,SUMMARY!A38&"*") -> 0 | AC38: =SUM(E38:P38) -> 0 | AD38: =SUM(Q38:AB38) -> 0 | AF38: 2 | AG38: 1170.9898 | AH38: =IFERROR((AC38-AF38)/AF38,1) -> -1 | AI38: =IFERROR((AD38-AG38)/AG38,1) -> -1 | AJ38: Budget di Term 85 tidak ada, sedangkan di Term 84 ada.
A39: INSIDENTAL | D39: EXTENDER | E39: =SUMIFS('PLAN BUDGET SAMI-JF'!AN13:AN100000,'PLAN BUDGET SAMI-JF'!D13:D100000,SUMMARY!D39,'PLAN BUDGET SAMI-JF'!J13:J100000,SUMMARY!A39&"*") -> 0 | F39: =SUMIFS('PLAN BUDGET SAMI-JF'!AO13:AO100000,'PLAN BUDGET SAMI-JF'!D13:D100000,SUMMARY!D39,'PLAN BUDGET SAMI-JF'!J13:J100000,SUMMARY!A39&"*") -> 0 | G39: =SUMIFS('PLAN BUDGET SAMI-JF'!AP13:AP100000,'PLAN BUDGET SAMI-JF'!D13:D100000,SUMMARY!D39,'PLAN BUDGET SAMI-JF'!J13:J100000,SUMMARY!A39&"*") -> 0 | H39: =SUMIFS('PLAN BUDGET SAMI-JF'!AQ13:AQ100000,'PLAN BUDGET SAMI-JF'!D13:D100000,SUMMARY!D39,'PLAN BUDGET SAMI-JF'!J13:J100000,SUMMARY!A39&"*") -> 0 | I39: =SUMIFS('PLAN BUDGET SAMI-JF'!AR13:AR100000,'PLAN BUDGET SAMI-JF'!D13:D100000,SUMMARY!D39,'PLAN BUDGET SAMI-JF'!J13:J100000,SUMMARY!A39&"*") -> 0 | J39: =SUMIFS('PLAN BUDGET SAMI-JF'!AS13:AS100000,'PLAN BUDGET SAMI-JF'!D13:D100000,SUMMARY!D39,'PLAN BUDGET SAMI-JF'!J13:J100000,SUMMARY!A39&"*") -> 0 | K39: =SUMIFS('PLAN BUDGET SAMI-JF'!AT13:AT100000,'PLAN BUDGET SAMI-JF'!D13:D100000,SUMMARY!D39,'PLAN BUDGET SAMI-JF'!J13:J100000,SUMMARY!A39&"*") -> 0 | L39: =SUMIFS('PLAN BUDGET SAMI-JF'!AU13:AU100000,'PLAN BUDGET SAMI-JF'!D13:D100000,SUMMARY!D39,'PLAN BUDGET SAMI-JF'!J13:J100000,SUMMARY!A39&"*") -> 0 | M39: =SUMIFS('PLAN BUDGET SAMI-JF'!AV13:AV100000,'PLAN BUDGET SAMI-JF'!D13:D100000,SUMMARY!D39,'PLAN BUDGET SAMI-JF'!J13:J100000,SUMMARY!A39&"*") -> 0 | N39: =SUMIFS('PLAN BUDGET SAMI-JF'!AW13:AW100000,'PLAN BUDGET SAMI-JF'!D13:D100000,SUMMARY!D39,'PLAN BUDGET SAMI-JF'!J13:J100000,SUMMARY!A39&"*") -> 0 | O39: =SUMIFS('PLAN BUDGET SAMI-JF'!AX13:AX100000,'PLAN BUDGET SAMI-JF'!D13:D100000,SUMMARY!D39,'PLAN BUDGET SAMI-JF'!J13:J100000,SUMMARY!A39&"*") -> 0 | P39: =SUMIFS('PLAN BUDGET SAMI-JF'!AY13:AY100000,'PLAN BUDGET SAMI-JF'!D13:D100000,SUMMARY!D39,'PLAN BUDGET SAMI-JF'!J13:J100000,SUMMARY!A39&"*") -> 0 | Q39: =SUMIFS('PLAN BUDGET SAMI-JF'!BC13:BC100000,'PLAN BUDGET SAMI-JF'!D13:D100000,SUMMARY!D39,'PLAN BUDGET SAMI-JF'!J13:J100000,SUMMARY!A39&"*") -> 0 | R39: =SUMIFS('PLAN BUDGET SAMI-JF'!BD13:BD100000,'PLAN BUDGET SAMI-JF'!D13:D100000,SUMMARY!D39,'PLAN BUDGET SAMI-JF'!J13:J100000,SUMMARY!A39&"*") -> 0 | S39: =SUMIFS('PLAN BUDGET SAMI-JF'!BE13:BE100000,'PLAN BUDGET SAMI-JF'!D13:D100000,SUMMARY!D39,'PLAN BUDGET SAMI-JF'!J13:J100000,SUMMARY!A39&"*") -> 0 | T39: =SUMIFS('PLAN BUDGET SAMI-JF'!BF13:BF100000,'PLAN BUDGET SAMI-JF'!D13:D100000,SUMMARY!D39,'PLAN BUDGET SAMI-JF'!J13:J100000,SUMMARY!A39&"*") -> 0 | U39: =SUMIFS('PLAN BUDGET SAMI-JF'!BG13:BG100000,'PLAN BUDGET SAMI-JF'!D13:D100000,SUMMARY!D39,'PLAN BUDGET SAMI-JF'!J13:J100000,SUMMARY!A39&"*") -> 0 | V39: =SUMIFS('PLAN BUDGET SAMI-JF'!BH13:BH100000,'PLAN BUDGET SAMI-JF'!D13:D100000,SUMMARY!D39,'PLAN BUDGET SAMI-JF'!J13:J100000,SUMMARY!A39&"*") -> 0 | W39: =SUMIFS('PLAN BUDGET SAMI-JF'!BI13:BI100000,'PLAN BUDGET SAMI-JF'!D13:D100000,SUMMARY!D39,'PLAN BUDGET SAMI-JF'!J13:J100000,SUMMARY!A39&"*") -> 0 | X39: =SUMIFS('PLAN BUDGET SAMI-JF'!BJ13:BJ100000,'PLAN BUDGET SAMI-JF'!D13:D100000,SUMMARY!D39,'PLAN BUDGET SAMI-JF'!J13:J100000,SUMMARY!A39&"*") -> 0 | Y39: =SUMIFS('PLAN BUDGET SAMI-JF'!BK13:BK100000,'PLAN BUDGET SAMI-JF'!D13:D100000,SUMMARY!D39,'PLAN BUDGET SAMI-JF'!J13:J100000,SUMMARY!A39&"*") -> 0 | Z39: =SUMIFS('PLAN BUDGET SAMI-JF'!BL13:BL100000,'PLAN BUDGET SAMI-JF'!D13:D100000,SUMMARY!D39,'PLAN BUDGET SAMI-JF'!J13:J100000,SUMMARY!A39&"*") -> 0 | AA39: =SUMIFS('PLAN BUDGET SAMI-JF'!BM13:BM100000,'PLAN BUDGET SAMI-JF'!D13:D100000,SUMMARY!D39,'PLAN BUDGET SAMI-JF'!J13:J100000,SUMMARY!A39&"*") -> 0 | AB39: =SUMIFS('PLAN BUDGET SAMI-JF'!BN13:BN100000,'PLAN BUDGET SAMI-JF'!D13:D100000,SUMMARY!D39,'PLAN BUDGET SAMI-JF'!J13:J100000,SUMMARY!A39&"*") -> 0 | AC39: =SUM(E39:P39) -> 0 | AD39: =SUM(Q39:AB39) -> 0 | AF39: 1 | AG39: 50.637398 | AH39: =IFERROR((AC39-AF39)/AF39,1) -> -1 | AI39: =IFERROR((AD39-AG39)/AG39,1) -> -1 | AJ39: Budget di Term 85 tidak ada, sedangkan di Term 84 ada.
A40: INSIDENTAL | D40: HDMI | E40: =SUMIFS('PLAN BUDGET SAMI-JF'!AN13:AN100000,'PLAN BUDGET SAMI-JF'!D13:D100000,SUMMARY!D40,'PLAN BUDGET SAMI-JF'!J13:J100000,SUMMARY!A40&"*") -> 0 | F40: =SUMIFS('PLAN BUDGET SAMI-JF'!AO13:AO100000,'PLAN BUDGET SAMI-JF'!D13:D100000,SUMMARY!D40,'PLAN BUDGET SAMI-JF'!J13:J100000,SUMMARY!A40&"*") -> 0 | G40: =SUMIFS('PLAN BUDGET SAMI-JF'!AP13:AP100000,'PLAN BUDGET SAMI-JF'!D13:D100000,SUMMARY!D40,'PLAN BUDGET SAMI-JF'!J13:J100000,SUMMARY!A40&"*") -> 0 | H40: =SUMIFS('PLAN BUDGET SAMI-JF'!AQ13:AQ100000,'PLAN BUDGET SAMI-JF'!D13:D100000,SUMMARY!D40,'PLAN BUDGET SAMI-JF'!J13:J100000,SUMMARY!A40&"*") -> 0 | I40: =SUMIFS('PLAN BUDGET SAMI-JF'!AR13:AR100000,'PLAN BUDGET SAMI-JF'!D13:D100000,SUMMARY!D40,'PLAN BUDGET SAMI-JF'!J13:J100000,SUMMARY!A40&"*") -> 0 | J40: =SUMIFS('PLAN BUDGET SAMI-JF'!AS13:AS100000,'PLAN BUDGET SAMI-JF'!D13:D100000,SUMMARY!D40,'PLAN BUDGET SAMI-JF'!J13:J100000,SUMMARY!A40&"*") -> 0 | K40: =SUMIFS('PLAN BUDGET SAMI-JF'!AT13:AT100000,'PLAN BUDGET SAMI-JF'!D13:D100000,SUMMARY!D40,'PLAN BUDGET SAMI-JF'!J13:J100000,SUMMARY!A40&"*") -> 0 | L40: =SUMIFS('PLAN BUDGET SAMI-JF'!AU13:AU100000,'PLAN BUDGET SAMI-JF'!D13:D100000,SUMMARY!D40,'PLAN BUDGET SAMI-JF'!J13:J100000,SUMMARY!A40&"*") -> 0 | M40: =SUMIFS('PLAN BUDGET SAMI-JF'!AV13:AV100000,'PLAN BUDGET SAMI-JF'!D13:D100000,SUMMARY!D40,'PLAN BUDGET SAMI-JF'!J13:J100000,SUMMARY!A40&"*") -> 0 | N40: =SUMIFS('PLAN BUDGET SAMI-JF'!AW13:AW100000,'PLAN BUDGET SAMI-JF'!D13:D100000,SUMMARY!D40,'PLAN BUDGET SAMI-JF'!J13:J100000,SUMMARY!A40&"*") -> 0 | O40: =SUMIFS('PLAN BUDGET SAMI-JF'!AX13:AX100000,'PLAN BUDGET SAMI-JF'!D13:D100000,SUMMARY!D40,'PLAN BUDGET SAMI-JF'!J13:J100000,SUMMARY!A40&"*") -> 0 | P40: =SUMIFS('PLAN BUDGET SAMI-JF'!AY13:AY100000,'PLAN BUDGET SAMI-JF'!D13:D100000,SUMMARY!D40,'PLAN BUDGET SAMI-JF'!J13:J100000,SUMMARY!A40&"*") -> 0 | Q40: =SUMIFS('PLAN BUDGET SAMI-JF'!BC13:BC100000,'PLAN BUDGET SAMI-JF'!D13:D100000,SUMMARY!D40,'PLAN BUDGET SAMI-JF'!J13:J100000,SUMMARY!A40&"*") -> 0 | R40: =SUMIFS('PLAN BUDGET SAMI-JF'!BD13:BD100000,'PLAN BUDGET SAMI-JF'!D13:D100000,SUMMARY!D40,'PLAN BUDGET SAMI-JF'!J13:J100000,SUMMARY!A40&"*") -> 0 | S40: =SUMIFS('PLAN BUDGET SAMI-JF'!BE13:BE100000,'PLAN BUDGET SAMI-JF'!D13:D100000,SUMMARY!D40,'PLAN BUDGET SAMI-JF'!J13:J100000,SUMMARY!A40&"*") -> 0 | T40: =SUMIFS('PLAN BUDGET SAMI-JF'!BF13:BF100000,'PLAN BUDGET SAMI-JF'!D13:D100000,SUMMARY!D40,'PLAN BUDGET SAMI-JF'!J13:J100000,SUMMARY!A40&"*") -> 0 | U40: =SUMIFS('PLAN BUDGET SAMI-JF'!BG13:BG100000,'PLAN BUDGET SAMI-JF'!D13:D100000,SUMMARY!D40,'PLAN BUDGET SAMI-JF'!J13:J100000,SUMMARY!A40&"*") -> 0 | V40: =SUMIFS('PLAN BUDGET SAMI-JF'!BH13:BH100000,'PLAN BUDGET SAMI-JF'!D13:D100000,SUMMARY!D40,'PLAN BUDGET SAMI-JF'!J13:J100000,SUMMARY!A40&"*") -> 0 | W40: =SUMIFS('PLAN BUDGET SAMI-JF'!BI13:BI100000,'PLAN BUDGET SAMI-JF'!D13:D100000,SUMMARY!D40,'PLAN BUDGET SAMI-JF'!J13:J100000,SUMMARY!A40&"*") -> 0 | X40: =SUMIFS('PLAN BUDGET SAMI-JF'!BJ13:BJ100000,'PLAN BUDGET SAMI-JF'!D13:D100000,SUMMARY!D40,'PLAN BUDGET SAMI-JF'!J13:J100000,SUMMARY!A40&"*") -> 0 | Y40: =SUMIFS('PLAN BUDGET SAMI-JF'!BK13:BK100000,'PLAN BUDGET SAMI-JF'!D13:D100000,SUMMARY!D40,'PLAN BUDGET SAMI-JF'!J13:J100000,SUMMARY!A40&"*") -> 0 | Z40: =SUMIFS('PLAN BUDGET SAMI-JF'!BL13:BL100000,'PLAN BUDGET SAMI-JF'!D13:D100000,SUMMARY!D40,'PLAN BUDGET SAMI-JF'!J13:J100000,SUMMARY!A40&"*") -> 0 | AA40: =SUMIFS('PLAN BUDGET SAMI-JF'!BM13:BM100000,'PLAN BUDGET SAMI-JF'!D13:D100000,SUMMARY!D40,'PLAN BUDGET SAMI-JF'!J13:J100000,SUMMARY!A40&"*") -> 0 | AB40: =SUMIFS('PLAN BUDGET SAMI-JF'!BN13:BN100000,'PLAN BUDGET SAMI-JF'!D13:D100000,SUMMARY!D40,'PLAN BUDGET SAMI-JF'!J13:J100000,SUMMARY!A40&"*") -> 0 | AC40: =SUM(E40:P40) -> 0 | AD40: =SUM(Q40:AB40) -> 0 | AF40: 1 | AG40: 11.393415 | AH40: =IFERROR((AC40-AF40)/AF40,1) -> -1 | AI40: =IFERROR((AD40-AG40)/AG40,1) -> -1 | AJ40: Budget di Term 85 tidak ada, sedangkan di Term 84 ada.
A41: INSIDENTAL | D41: HOTEL | E41: =SUMIFS('PLAN BUDGET SAMI-JF'!AN13:AN100000,'PLAN BUDGET SAMI-JF'!D13:D100000,SUMMARY!D41,'PLAN BUDGET SAMI-JF'!J13:J100000,SUMMARY!A41&"*") -> 0 | F41: =SUMIFS('PLAN BUDGET SAMI-JF'!AO13:AO100000,'PLAN BUDGET SAMI-JF'!D13:D100000,SUMMARY!D41,'PLAN BUDGET SAMI-JF'!J13:J100000,SUMMARY!A41&"*") -> 0 | G41: =SUMIFS('PLAN BUDGET SAMI-JF'!AP13:AP100000,'PLAN BUDGET SAMI-JF'!D13:D100000,SUMMARY!D41,'PLAN BUDGET SAMI-JF'!J13:J100000,SUMMARY!A41&"*") -> 0 | H41: =SUMIFS('PLAN BUDGET SAMI-JF'!AQ13:AQ100000,'PLAN BUDGET SAMI-JF'!D13:D100000,SUMMARY!D41,'PLAN BUDGET SAMI-JF'!J13:J100000,SUMMARY!A41&"*") -> 0 | I41: =SUMIFS('PLAN BUDGET SAMI-JF'!AR13:AR100000,'PLAN BUDGET SAMI-JF'!D13:D100000,SUMMARY!D41,'PLAN BUDGET SAMI-JF'!J13:J100000,SUMMARY!A41&"*") -> 0 | J41: =SUMIFS('PLAN BUDGET SAMI-JF'!AS13:AS100000,'PLAN BUDGET SAMI-JF'!D13:D100000,SUMMARY!D41,'PLAN BUDGET SAMI-JF'!J13:J100000,SUMMARY!A41&"*") -> 0 | K41: =SUMIFS('PLAN BUDGET SAMI-JF'!AT13:AT100000,'PLAN BUDGET SAMI-JF'!D13:D100000,SUMMARY!D41,'PLAN BUDGET SAMI-JF'!J13:J100000,SUMMARY!A41&"*") -> 0 | L41: =SUMIFS('PLAN BUDGET SAMI-JF'!AU13:AU100000,'PLAN BUDGET SAMI-JF'!D13:D100000,SUMMARY!D41,'PLAN BUDGET SAMI-JF'!J13:J100000,SUMMARY!A41&"*") -> 0 | M41: =SUMIFS('PLAN BUDGET SAMI-JF'!AV13:AV100000,'PLAN BUDGET SAMI-JF'!D13:D100000,SUMMARY!D41,'PLAN BUDGET SAMI-JF'!J13:J100000,SUMMARY!A41&"*") -> 0 | N41: =SUMIFS('PLAN BUDGET SAMI-JF'!AW13:AW100000,'PLAN BUDGET SAMI-JF'!D13:D100000,SUMMARY!D41,'PLAN BUDGET SAMI-JF'!J13:J100000,SUMMARY!A41&"*") -> 0 | O41: =SUMIFS('PLAN BUDGET SAMI-JF'!AX13:AX100000,'PLAN BUDGET SAMI-JF'!D13:D100000,SUMMARY!D41,'PLAN BUDGET SAMI-JF'!J13:J100000,SUMMARY!A41&"*") -> 0 | P41: =SUMIFS('PLAN BUDGET SAMI-JF'!AY13:AY100000,'PLAN BUDGET SAMI-JF'!D13:D100000,SUMMARY!D41,'PLAN BUDGET SAMI-JF'!J13:J100000,SUMMARY!A41&"*") -> 0 | Q41: =SUMIFS('PLAN BUDGET SAMI-JF'!BC13:BC100000,'PLAN BUDGET SAMI-JF'!D13:D100000,SUMMARY!D41,'PLAN BUDGET SAMI-JF'!J13:J100000,SUMMARY!A41&"*") -> 0 | R41: =SUMIFS('PLAN BUDGET SAMI-JF'!BD13:BD100000,'PLAN BUDGET SAMI-JF'!D13:D100000,SUMMARY!D41,'PLAN BUDGET SAMI-JF'!J13:J100000,SUMMARY!A41&"*") -> 0 | S41: =SUMIFS('PLAN BUDGET SAMI-JF'!BE13:BE100000,'PLAN BUDGET SAMI-JF'!D13:D100000,SUMMARY!D41,'PLAN BUDGET SAMI-JF'!J13:J100000,SUMMARY!A41&"*") -> 0 | T41: =SUMIFS('PLAN BUDGET SAMI-JF'!BF13:BF100000,'PLAN BUDGET SAMI-JF'!D13:D100000,SUMMARY!D41,'PLAN BUDGET SAMI-JF'!J13:J100000,SUMMARY!A41&"*") -> 0 | U41: =SUMIFS('PLAN BUDGET SAMI-JF'!BG13:BG100000,'PLAN BUDGET SAMI-JF'!D13:D100000,SUMMARY!D41,'PLAN BUDGET SAMI-JF'!J13:J100000,SUMMARY!A41&"*") -> 0 | V41: =SUMIFS('PLAN BUDGET SAMI-JF'!BH13:BH100000,'PLAN BUDGET SAMI-JF'!D13:D100000,SUMMARY!D41,'PLAN BUDGET SAMI-JF'!J13:J100000,SUMMARY!A41&"*") -> 0 | W41: =SUMIFS('PLAN BUDGET SAMI-JF'!BI13:BI100000,'PLAN BUDGET SAMI-JF'!D13:D100000,SUMMARY!D41,'PLAN BUDGET SAMI-JF'!J13:J100000,SUMMARY!A41&"*") -> 0 | X41: =SUMIFS('PLAN BUDGET SAMI-JF'!BJ13:BJ100000,'PLAN BUDGET SAMI-JF'!D13:D100000,SUMMARY!D41,'PLAN BUDGET SAMI-JF'!J13:J100000,SUMMARY!A41&"*") -> 0 | Y41: =SUMIFS('PLAN BUDGET SAMI-JF'!BK13:BK100000,'PLAN BUDGET SAMI-JF'!D13:D100000,SUMMARY!D41,'PLAN BUDGET SAMI-JF'!J13:J100000,SUMMARY!A41&"*") -> 0 | Z41: =SUMIFS('PLAN BUDGET SAMI-JF'!BL13:BL100000,'PLAN BUDGET SAMI-JF'!D13:D100000,SUMMARY!D41,'PLAN BUDGET SAMI-JF'!J13:J100000,SUMMARY!A41&"*") -> 0 | AA41: =SUMIFS('PLAN BUDGET SAMI-JF'!BM13:BM100000,'PLAN BUDGET SAMI-JF'!D13:D100000,SUMMARY!D41,'PLAN BUDGET SAMI-JF'!J13:J100000,SUMMARY!A41&"*") -> 0 | AB41: =SUMIFS('PLAN BUDGET SAMI-JF'!BN13:BN100000,'PLAN BUDGET SAMI-JF'!D13:D100000,SUMMARY!D41,'PLAN BUDGET SAMI-JF'!J13:J100000,SUMMARY!A41&"*") -> 0 | AC41: =SUM(E41:P41) -> 0 | AD41: =SUM(Q41:AB41) -> 0 | AF41: 5 | AG41: 303.82439 | AH41: =IFERROR((AC41-AF41)/AF41,1) -> -1 | AI41: =IFERROR((AD41-AG41)/AG41,1) -> -1 | AJ41: Budget di Term 85 tidak ada, sedangkan di Term 84 ada.
A42: INSIDENTAL | D42: KURSI | E42: =SUMIFS('PLAN BUDGET SAMI-JF'!AN13:AN100000,'PLAN BUDGET SAMI-JF'!D13:D100000,SUMMARY!D42,'PLAN BUDGET SAMI-JF'!J13:J100000,SUMMARY!A42&"*") -> 0 | F42: =SUMIFS('PLAN BUDGET SAMI-JF'!AO13:AO100000,'PLAN BUDGET SAMI-JF'!D13:D100000,SUMMARY!D42,'PLAN BUDGET SAMI-JF'!J13:J100000,SUMMARY!A42&"*") -> 0 | G42: =SUMIFS('PLAN BUDGET SAMI-JF'!AP13:AP100000,'PLAN BUDGET SAMI-JF'!D13:D100000,SUMMARY!D42,'PLAN BUDGET SAMI-JF'!J13:J100000,SUMMARY!A42&"*") -> 0 | H42: =SUMIFS('PLAN BUDGET SAMI-JF'!AQ13:AQ100000,'PLAN BUDGET SAMI-JF'!D13:D100000,SUMMARY!D42,'PLAN BUDGET SAMI-JF'!J13:J100000,SUMMARY!A42&"*") -> 0 | I42: =SUMIFS('PLAN BUDGET SAMI-JF'!AR13:AR100000,'PLAN BUDGET SAMI-JF'!D13:D100000,SUMMARY!D42,'PLAN BUDGET SAMI-JF'!J13:J100000,SUMMARY!A42&"*") -> 0 | J42: =SUMIFS('PLAN BUDGET SAMI-JF'!AS13:AS100000,'PLAN BUDGET SAMI-JF'!D13:D100000,SUMMARY!D42,'PLAN BUDGET SAMI-JF'!J13:J100000,SUMMARY!A42&"*") -> 0 | K42: =SUMIFS('PLAN BUDGET SAMI-JF'!AT13:AT100000,'PLAN BUDGET SAMI-JF'!D13:D100000,SUMMARY!D42,'PLAN BUDGET SAMI-JF'!J13:J100000,SUMMARY!A42&"*") -> 0 | L42: =SUMIFS('PLAN BUDGET SAMI-JF'!AU13:AU100000,'PLAN BUDGET SAMI-JF'!D13:D100000,SUMMARY!D42,'PLAN BUDGET SAMI-JF'!J13:J100000,SUMMARY!A42&"*") -> 0 | M42: =SUMIFS('PLAN BUDGET SAMI-JF'!AV13:AV100000,'PLAN BUDGET SAMI-JF'!D13:D100000,SUMMARY!D42,'PLAN BUDGET SAMI-JF'!J13:J100000,SUMMARY!A42&"*") -> 0 | N42: =SUMIFS('PLAN BUDGET SAMI-JF'!AW13:AW100000,'PLAN BUDGET SAMI-JF'!D13:D100000,SUMMARY!D42,'PLAN BUDGET SAMI-JF'!J13:J100000,SUMMARY!A42&"*") -> 0 | O42: =SUMIFS('PLAN BUDGET SAMI-JF'!AX13:AX100000,'PLAN BUDGET SAMI-JF'!D13:D100000,SUMMARY!D42,'PLAN BUDGET SAMI-JF'!J13:J100000,SUMMARY!A42&"*") -> 0 | P42: =SUMIFS('PLAN BUDGET SAMI-JF'!AY13:AY100000,'PLAN BUDGET SAMI-JF'!D13:D100000,SUMMARY!D42,'PLAN BUDGET SAMI-JF'!J13:J100000,SUMMARY!A42&"*") -> 0 | Q42: =SUMIFS('PLAN BUDGET SAMI-JF'!BC13:BC100000,'PLAN BUDGET SAMI-JF'!D13:D100000,SUMMARY!D42,'PLAN BUDGET SAMI-JF'!J13:J100000,SUMMARY!A42&"*") -> 0 | R42: =SUMIFS('PLAN BUDGET SAMI-JF'!BD13:BD100000,'PLAN BUDGET SAMI-JF'!D13:D100000,SUMMARY!D42,'PLAN BUDGET SAMI-JF'!J13:J100000,SUMMARY!A42&"*") -> 0 | S42: =SUMIFS('PLAN BUDGET SAMI-JF'!BE13:BE100000,'PLAN BUDGET SAMI-JF'!D13:D100000,SUMMARY!D42,'PLAN BUDGET SAMI-JF'!J13:J100000,SUMMARY!A42&"*") -> 0 | T42: =SUMIFS('PLAN BUDGET SAMI-JF'!BF13:BF100000,'PLAN BUDGET SAMI-JF'!D13:D100000,SUMMARY!D42,'PLAN BUDGET SAMI-JF'!J13:J100000,SUMMARY!A42&"*") -> 0 | U42: =SUMIFS('PLAN BUDGET SAMI-JF'!BG13:BG100000,'PLAN BUDGET SAMI-JF'!D13:D100000,SUMMARY!D42,'PLAN BUDGET SAMI-JF'!J13:J100000,SUMMARY!A42&"*") -> 0 | V42: =SUMIFS('PLAN BUDGET SAMI-JF'!BH13:BH100000,'PLAN BUDGET SAMI-JF'!D13:D100000,SUMMARY!D42,'PLAN BUDGET SAMI-JF'!J13:J100000,SUMMARY!A42&"*") -> 0 | W42: =SUMIFS('PLAN BUDGET SAMI-JF'!BI13:BI100000,'PLAN BUDGET SAMI-JF'!D13:D100000,SUMMARY!D42,'PLAN BUDGET SAMI-JF'!J13:J100000,SUMMARY!A42&"*") -> 0 | X42: =SUMIFS('PLAN BUDGET SAMI-JF'!BJ13:BJ100000,'PLAN BUDGET SAMI-JF'!D13:D100000,SUMMARY!D42,'PLAN BUDGET SAMI-JF'!J13:J100000,SUMMARY!A42&"*") -> 0 | Y42: =SUMIFS('PLAN BUDGET SAMI-JF'!BK13:BK100000,'PLAN BUDGET SAMI-JF'!D13:D100000,SUMMARY!D42,'PLAN BUDGET SAMI-JF'!J13:J100000,SUMMARY!A42&"*") -> 0 | Z42: =SUMIFS('PLAN BUDGET SAMI-JF'!BL13:BL100000,'PLAN BUDGET SAMI-JF'!D13:D100000,SUMMARY!D42,'PLAN BUDGET SAMI-JF'!J13:J100000,SUMMARY!A42&"*") -> 0 | AA42: =SUMIFS('PLAN BUDGET SAMI-JF'!BM13:BM100000,'PLAN BUDGET SAMI-JF'!D13:D100000,SUMMARY!D42,'PLAN BUDGET SAMI-JF'!J13:J100000,SUMMARY!A42&"*") -> 0 | AB42: =SUMIFS('PLAN BUDGET SAMI-JF'!BN13:BN100000,'PLAN BUDGET SAMI-JF'!D13:D100000,SUMMARY!D42,'PLAN BUDGET SAMI-JF'!J13:J100000,SUMMARY!A42&"*") -> 0 | AC42: =SUM(E42:P42) -> 0 | AD42: =SUM(Q42:AB42) -> 0 | AF42: 50 | AG42: 1788.1331 | AH42: =IFERROR((AC42-AF42)/AF42,1) -> -1 | AI42: =IFERROR((AD42-AG42)/AG42,1) -> -1 | AJ42: Budget di Term 85 tidak ada, sedangkan di Term 84 ada.
A43: INSIDENTAL | D43: MESIN SCREW BATERAY | E43: =SUMIFS('PLAN BUDGET SAMI-JF'!AN13:AN100000,'PLAN BUDGET SAMI-JF'!D13:D100000,SUMMARY!D43,'PLAN BUDGET SAMI-JF'!J13:J100000,SUMMARY!A43&"*") -> 0 | F43: =SUMIFS('PLAN BUDGET SAMI-JF'!AO13:AO100000,'PLAN BUDGET SAMI-JF'!D13:D100000,SUMMARY!D43,'PLAN BUDGET SAMI-JF'!J13:J100000,SUMMARY!A43&"*") -> 0 | G43: =SUMIFS('PLAN BUDGET SAMI-JF'!AP13:AP100000,'PLAN BUDGET SAMI-JF'!D13:D100000,SUMMARY!D43,'PLAN BUDGET SAMI-JF'!J13:J100000,SUMMARY!A43&"*") -> 0 | H43: =SUMIFS('PLAN BUDGET SAMI-JF'!AQ13:AQ100000,'PLAN BUDGET SAMI-JF'!D13:D100000,SUMMARY!D43,'PLAN BUDGET SAMI-JF'!J13:J100000,SUMMARY!A43&"*") -> 0 | I43: =SUMIFS('PLAN BUDGET SAMI-JF'!AR13:AR100000,'PLAN BUDGET SAMI-JF'!D13:D100000,SUMMARY!D43,'PLAN BUDGET SAMI-JF'!J13:J100000,SUMMARY!A43&"*") -> 0 | J43: =SUMIFS('PLAN BUDGET SAMI-JF'!AS13:AS100000,'PLAN BUDGET SAMI-JF'!D13:D100000,SUMMARY!D43,'PLAN BUDGET SAMI-JF'!J13:J100000,SUMMARY!A43&"*") -> 0 | K43: =SUMIFS('PLAN BUDGET SAMI-JF'!AT13:AT100000,'PLAN BUDGET SAMI-JF'!D13:D100000,SUMMARY!D43,'PLAN BUDGET SAMI-JF'!J13:J100000,SUMMARY!A43&"*") -> 0 | L43: =SUMIFS('PLAN BUDGET SAMI-JF'!AU13:AU100000,'PLAN BUDGET SAMI-JF'!D13:D100000,SUMMARY!D43,'PLAN BUDGET SAMI-JF'!J13:J100000,SUMMARY!A43&"*") -> 0 | M43: =SUMIFS('PLAN BUDGET SAMI-JF'!AV13:AV100000,'PLAN BUDGET SAMI-JF'!D13:D100000,SUMMARY!D43,'PLAN BUDGET SAMI-JF'!J13:J100000,SUMMARY!A43&"*") -> 0 | N43: =SUMIFS('PLAN BUDGET SAMI-JF'!AW13:AW100000,'PLAN BUDGET SAMI-JF'!D13:D100000,SUMMARY!D43,'PLAN BUDGET SAMI-JF'!J13:J100000,SUMMARY!A43&"*") -> 0 | O43: =SUMIFS('PLAN BUDGET SAMI-JF'!AX13:AX100000,'PLAN BUDGET SAMI-JF'!D13:D100000,SUMMARY!D43,'PLAN BUDGET SAMI-JF'!J13:J100000,SUMMARY!A43&"*") -> 0 | P43: =SUMIFS('PLAN BUDGET SAMI-JF'!AY13:AY100000,'PLAN BUDGET SAMI-JF'!D13:D100000,SUMMARY!D43,'PLAN BUDGET SAMI-JF'!J13:J100000,SUMMARY!A43&"*") -> 0 | Q43: =SUMIFS('PLAN BUDGET SAMI-JF'!BC13:BC100000,'PLAN BUDGET SAMI-JF'!D13:D100000,SUMMARY!D43,'PLAN BUDGET SAMI-JF'!J13:J100000,SUMMARY!A43&"*") -> 0 | R43: =SUMIFS('PLAN BUDGET SAMI-JF'!BD13:BD100000,'PLAN BUDGET SAMI-JF'!D13:D100000,SUMMARY!D43,'PLAN BUDGET SAMI-JF'!J13:J100000,SUMMARY!A43&"*") -> 0 | S43: =SUMIFS('PLAN BUDGET SAMI-JF'!BE13:BE100000,'PLAN BUDGET SAMI-JF'!D13:D100000,SUMMARY!D43,'PLAN BUDGET SAMI-JF'!J13:J100000,SUMMARY!A43&"*") -> 0 | T43: =SUMIFS('PLAN BUDGET SAMI-JF'!BF13:BF100000,'PLAN BUDGET SAMI-JF'!D13:D100000,SUMMARY!D43,'PLAN BUDGET SAMI-JF'!J13:J100000,SUMMARY!A43&"*") -> 0 | U43: =SUMIFS('PLAN BUDGET SAMI-JF'!BG13:BG100000,'PLAN BUDGET SAMI-JF'!D13:D100000,SUMMARY!D43,'PLAN BUDGET SAMI-JF'!J13:J100000,SUMMARY!A43&"*") -> 0 | V43: =SUMIFS('PLAN BUDGET SAMI-JF'!BH13:BH100000,'PLAN BUDGET SAMI-JF'!D13:D100000,SUMMARY!D43,'PLAN BUDGET SAMI-JF'!J13:J100000,SUMMARY!A43&"*") -> 0 | W43: =SUMIFS('PLAN BUDGET SAMI-JF'!BI13:BI100000,'PLAN BUDGET SAMI-JF'!D13:D100000,SUMMARY!D43,'PLAN BUDGET SAMI-JF'!J13:J100000,SUMMARY!A43&"*") -> 0 | X43: =SUMIFS('PLAN BUDGET SAMI-JF'!BJ13:BJ100000,'PLAN BUDGET SAMI-JF'!D13:D100000,SUMMARY!D43,'PLAN BUDGET SAMI-JF'!J13:J100000,SUMMARY!A43&"*") -> 0 | Y43: =SUMIFS('PLAN BUDGET SAMI-JF'!BK13:BK100000,'PLAN BUDGET SAMI-JF'!D13:D100000,SUMMARY!D43,'PLAN BUDGET SAMI-JF'!J13:J100000,SUMMARY!A43&"*") -> 0 | Z43: =SUMIFS('PLAN BUDGET SAMI-JF'!BL13:BL100000,'PLAN BUDGET SAMI-JF'!D13:D100000,SUMMARY!D43,'PLAN BUDGET SAMI-JF'!J13:J100000,SUMMARY!A43&"*") -> 0 | AA43: =SUMIFS('PLAN BUDGET SAMI-JF'!BM13:BM100000,'PLAN BUDGET SAMI-JF'!D13:D100000,SUMMARY!D43,'PLAN BUDGET SAMI-JF'!J13:J100000,SUMMARY!A43&"*") -> 0 | AB43: =SUMIFS('PLAN BUDGET SAMI-JF'!BN13:BN100000,'PLAN BUDGET SAMI-JF'!D13:D100000,SUMMARY!D43,'PLAN BUDGET SAMI-JF'!J13:J100000,SUMMARY!A43&"*") -> 0 | AC43: =SUM(E43:P43) -> 0 | AD43: =SUM(Q43:AB43) -> 0 | AF43: 1 | AG43: 175.96496 | AH43: =IFERROR((AC43-AF43)/AF43,1) -> -1 | AI43: =IFERROR((AD43-AG43)/AG43,1) -> -1 | AJ43: Budget di Term 85 tidak ada, sedangkan di Term 84 ada.
A44: INSIDENTAL | D44: SCANNER | E44: =SUMIFS('PLAN BUDGET SAMI-JF'!AN13:AN100000,'PLAN BUDGET SAMI-JF'!D13:D100000,SUMMARY!D44,'PLAN BUDGET SAMI-JF'!J13:J100000,SUMMARY!A44&"*") -> 0 | F44: =SUMIFS('PLAN BUDGET SAMI-JF'!AO13:AO100000,'PLAN BUDGET SAMI-JF'!D13:D100000,SUMMARY!D44,'PLAN BUDGET SAMI-JF'!J13:J100000,SUMMARY!A44&"*") -> 0 | G44: =SUMIFS('PLAN BUDGET SAMI-JF'!AP13:AP100000,'PLAN BUDGET SAMI-JF'!D13:D100000,SUMMARY!D44,'PLAN BUDGET SAMI-JF'!J13:J100000,SUMMARY!A44&"*") -> 0 | H44: =SUMIFS('PLAN BUDGET SAMI-JF'!AQ13:AQ100000,'PLAN BUDGET SAMI-JF'!D13:D100000,SUMMARY!D44,'PLAN BUDGET SAMI-JF'!J13:J100000,SUMMARY!A44&"*") -> 0 | I44: =SUMIFS('PLAN BUDGET SAMI-JF'!AR13:AR100000,'PLAN BUDGET SAMI-JF'!D13:D100000,SUMMARY!D44,'PLAN BUDGET SAMI-JF'!J13:J100000,SUMMARY!A44&"*") -> 0 | J44: =SUMIFS('PLAN BUDGET SAMI-JF'!AS13:AS100000,'PLAN BUDGET SAMI-JF'!D13:D100000,SUMMARY!D44,'PLAN BUDGET SAMI-JF'!J13:J100000,SUMMARY!A44&"*") -> 0 | K44: =SUMIFS('PLAN BUDGET SAMI-JF'!AT13:AT100000,'PLAN BUDGET SAMI-JF'!D13:D100000,SUMMARY!D44,'PLAN BUDGET SAMI-JF'!J13:J100000,SUMMARY!A44&"*") -> 0 | L44: =SUMIFS('PLAN BUDGET SAMI-JF'!AU13:AU100000,'PLAN BUDGET SAMI-JF'!D13:D100000,SUMMARY!D44,'PLAN BUDGET SAMI-JF'!J13:J100000,SUMMARY!A44&"*") -> 0 | M44: =SUMIFS('PLAN BUDGET SAMI-JF'!AV13:AV100000,'PLAN BUDGET SAMI-JF'!D13:D100000,SUMMARY!D44,'PLAN BUDGET SAMI-JF'!J13:J100000,SUMMARY!A44&"*") -> 0 | N44: =SUMIFS('PLAN BUDGET SAMI-JF'!AW13:AW100000,'PLAN BUDGET SAMI-JF'!D13:D100000,SUMMARY!D44,'PLAN BUDGET SAMI-JF'!J13:J100000,SUMMARY!A44&"*") -> 0 | O44: =SUMIFS('PLAN BUDGET SAMI-JF'!AX13:AX100000,'PLAN BUDGET SAMI-JF'!D13:D100000,SUMMARY!D44,'PLAN BUDGET SAMI-JF'!J13:J100000,SUMMARY!A44&"*") -> 0 | P44: =SUMIFS('PLAN BUDGET SAMI-JF'!AY13:AY100000,'PLAN BUDGET SAMI-JF'!D13:D100000,SUMMARY!D44,'PLAN BUDGET SAMI-JF'!J13:J100000,SUMMARY!A44&"*") -> 0 | Q44: =SUMIFS('PLAN BUDGET SAMI-JF'!BC13:BC100000,'PLAN BUDGET SAMI-JF'!D13:D100000,SUMMARY!D44,'PLAN BUDGET SAMI-JF'!J13:J100000,SUMMARY!A44&"*") -> 0 | R44: =SUMIFS('PLAN BUDGET SAMI-JF'!BD13:BD100000,'PLAN BUDGET SAMI-JF'!D13:D100000,SUMMARY!D44,'PLAN BUDGET SAMI-JF'!J13:J100000,SUMMARY!A44&"*") -> 0 | S44: =SUMIFS('PLAN BUDGET SAMI-JF'!BE13:BE100000,'PLAN BUDGET SAMI-JF'!D13:D100000,SUMMARY!D44,'PLAN BUDGET SAMI-JF'!J13:J100000,SUMMARY!A44&"*") -> 0 | T44: =SUMIFS('PLAN BUDGET SAMI-JF'!BF13:BF100000,'PLAN BUDGET SAMI-JF'!D13:D100000,SUMMARY!D44,'PLAN BUDGET SAMI-JF'!J13:J100000,SUMMARY!A44&"*") -> 0 | U44: =SUMIFS('PLAN BUDGET SAMI-JF'!BG13:BG100000,'PLAN BUDGET SAMI-JF'!D13:D100000,SUMMARY!D44,'PLAN BUDGET SAMI-JF'!J13:J100000,SUMMARY!A44&"*") -> 0 | V44: =SUMIFS('PLAN BUDGET SAMI-JF'!BH13:BH100000,'PLAN BUDGET SAMI-JF'!D13:D100000,SUMMARY!D44,'PLAN BUDGET SAMI-JF'!J13:J100000,SUMMARY!A44&"*") -> 0 | W44: =SUMIFS('PLAN BUDGET SAMI-JF'!BI13:BI100000,'PLAN BUDGET SAMI-JF'!D13:D100000,SUMMARY!D44,'PLAN BUDGET SAMI-JF'!J13:J100000,SUMMARY!A44&"*") -> 0 | X44: =SUMIFS('PLAN BUDGET SAMI-JF'!BJ13:BJ100000,'PLAN BUDGET SAMI-JF'!D13:D100000,SUMMARY!D44,'PLAN BUDGET SAMI-JF'!J13:J100000,SUMMARY!A44&"*") -> 0 | Y44: =SUMIFS('PLAN BUDGET SAMI-JF'!BK13:BK100000,'PLAN BUDGET SAMI-JF'!D13:D100000,SUMMARY!D44,'PLAN BUDGET SAMI-JF'!J13:J100000,SUMMARY!A44&"*") -> 0 | Z44: =SUMIFS('PLAN BUDGET SAMI-JF'!BL13:BL100000,'PLAN BUDGET SAMI-JF'!D13:D100000,SUMMARY!D44,'PLAN BUDGET SAMI-JF'!J13:J100000,SUMMARY!A44&"*") -> 0 | AA44: =SUMIFS('PLAN BUDGET SAMI-JF'!BM13:BM100000,'PLAN BUDGET SAMI-JF'!D13:D100000,SUMMARY!D44,'PLAN BUDGET SAMI-JF'!J13:J100000,SUMMARY!A44&"*") -> 0 | AB44: =SUMIFS('PLAN BUDGET SAMI-JF'!BN13:BN100000,'PLAN BUDGET SAMI-JF'!D13:D100000,SUMMARY!D44,'PLAN BUDGET SAMI-JF'!J13:J100000,SUMMARY!A44&"*") -> 0 | AC44: =SUM(E44:P44) -> 0 | AD44: =SUM(Q44:AB44) -> 0 | AF44: 1 | AG44: 696.26423 | AH44: =IFERROR((AC44-AF44)/AF44,1) -> -1 | AI44: =IFERROR((AD44-AG44)/AG44,1) -> -1 | AJ44: Budget di Term 85 tidak ada, sedangkan di Term 84 ada.
A45: INSIDENTAL | D45: SOFTCASE | E45: =SUMIFS('PLAN BUDGET SAMI-JF'!AN13:AN100000,'PLAN BUDGET SAMI-JF'!D13:D100000,SUMMARY!D45,'PLAN BUDGET SAMI-JF'!J13:J100000,SUMMARY!A45&"*") -> 0 | F45: =SUMIFS('PLAN BUDGET SAMI-JF'!AO13:AO100000,'PLAN BUDGET SAMI-JF'!D13:D100000,SUMMARY!D45,'PLAN BUDGET SAMI-JF'!J13:J100000,SUMMARY!A45&"*") -> 0 | G45: =SUMIFS('PLAN BUDGET SAMI-JF'!AP13:AP100000,'PLAN BUDGET SAMI-JF'!D13:D100000,SUMMARY!D45,'PLAN BUDGET SAMI-JF'!J13:J100000,SUMMARY!A45&"*") -> 0 | H45: =SUMIFS('PLAN BUDGET SAMI-JF'!AQ13:AQ100000,'PLAN BUDGET SAMI-JF'!D13:D100000,SUMMARY!D45,'PLAN BUDGET SAMI-JF'!J13:J100000,SUMMARY!A45&"*") -> 0 | I45: =SUMIFS('PLAN BUDGET SAMI-JF'!AR13:AR100000,'PLAN BUDGET SAMI-JF'!D13:D100000,SUMMARY!D45,'PLAN BUDGET SAMI-JF'!J13:J100000,SUMMARY!A45&"*") -> 0 | J45: =SUMIFS('PLAN BUDGET SAMI-JF'!AS13:AS100000,'PLAN BUDGET SAMI-JF'!D13:D100000,SUMMARY!D45,'PLAN BUDGET SAMI-JF'!J13:J100000,SUMMARY!A45&"*") -> 0 | K45: =SUMIFS('PLAN BUDGET SAMI-JF'!AT13:AT100000,'PLAN BUDGET SAMI-JF'!D13:D100000,SUMMARY!D45,'PLAN BUDGET SAMI-JF'!J13:J100000,SUMMARY!A45&"*") -> 0 | L45: =SUMIFS('PLAN BUDGET SAMI-JF'!AU13:AU100000,'PLAN BUDGET SAMI-JF'!D13:D100000,SUMMARY!D45,'PLAN BUDGET SAMI-JF'!J13:J100000,SUMMARY!A45&"*") -> 0 | M45: =SUMIFS('PLAN BUDGET SAMI-JF'!AV13:AV100000,'PLAN BUDGET SAMI-JF'!D13:D100000,SUMMARY!D45,'PLAN BUDGET SAMI-JF'!J13:J100000,SUMMARY!A45&"*") -> 0 | N45: =SUMIFS('PLAN BUDGET SAMI-JF'!AW13:AW100000,'PLAN BUDGET SAMI-JF'!D13:D100000,SUMMARY!D45,'PLAN BUDGET SAMI-JF'!J13:J100000,SUMMARY!A45&"*") -> 0 | O45: =SUMIFS('PLAN BUDGET SAMI-JF'!AX13:AX100000,'PLAN BUDGET SAMI-JF'!D13:D100000,SUMMARY!D45,'PLAN BUDGET SAMI-JF'!J13:J100000,SUMMARY!A45&"*") -> 0 | P45: =SUMIFS('PLAN BUDGET SAMI-JF'!AY13:AY100000,'PLAN BUDGET SAMI-JF'!D13:D100000,SUMMARY!D45,'PLAN BUDGET SAMI-JF'!J13:J100000,SUMMARY!A45&"*") -> 0 | Q45: =SUMIFS('PLAN BUDGET SAMI-JF'!BC13:BC100000,'PLAN BUDGET SAMI-JF'!D13:D100000,SUMMARY!D45,'PLAN BUDGET SAMI-JF'!J13:J100000,SUMMARY!A45&"*") -> 0 | R45: =SUMIFS('PLAN BUDGET SAMI-JF'!BD13:BD100000,'PLAN BUDGET SAMI-JF'!D13:D100000,SUMMARY!D45,'PLAN BUDGET SAMI-JF'!J13:J100000,SUMMARY!A45&"*") -> 0 | S45: =SUMIFS('PLAN BUDGET SAMI-JF'!BE13:BE100000,'PLAN BUDGET SAMI-JF'!D13:D100000,SUMMARY!D45,'PLAN BUDGET SAMI-JF'!J13:J100000,SUMMARY!A45&"*") -> 0 | T45: =SUMIFS('PLAN BUDGET SAMI-JF'!BF13:BF100000,'PLAN BUDGET SAMI-JF'!D13:D100000,SUMMARY!D45,'PLAN BUDGET SAMI-JF'!J13:J100000,SUMMARY!A45&"*") -> 0 | U45: =SUMIFS('PLAN BUDGET SAMI-JF'!BG13:BG100000,'PLAN BUDGET SAMI-JF'!D13:D100000,SUMMARY!D45,'PLAN BUDGET SAMI-JF'!J13:J100000,SUMMARY!A45&"*") -> 0 | V45: =SUMIFS('PLAN BUDGET SAMI-JF'!BH13:BH100000,'PLAN BUDGET SAMI-JF'!D13:D100000,SUMMARY!D45,'PLAN BUDGET SAMI-JF'!J13:J100000,SUMMARY!A45&"*") -> 0 | W45: =SUMIFS('PLAN BUDGET SAMI-JF'!BI13:BI100000,'PLAN BUDGET SAMI-JF'!D13:D100000,SUMMARY!D45,'PLAN BUDGET SAMI-JF'!J13:J100000,SUMMARY!A45&"*") -> 0 | X45: =SUMIFS('PLAN BUDGET SAMI-JF'!BJ13:BJ100000,'PLAN BUDGET SAMI-JF'!D13:D100000,SUMMARY!D45,'PLAN BUDGET SAMI-JF'!J13:J100000,SUMMARY!A45&"*") -> 0 | Y45: =SUMIFS('PLAN BUDGET SAMI-JF'!BK13:BK100000,'PLAN BUDGET SAMI-JF'!D13:D100000,SUMMARY!D45,'PLAN BUDGET SAMI-JF'!J13:J100000,SUMMARY!A45&"*") -> 0 | Z45: =SUMIFS('PLAN BUDGET SAMI-JF'!BL13:BL100000,'PLAN BUDGET SAMI-JF'!D13:D100000,SUMMARY!D45,'PLAN BUDGET SAMI-JF'!J13:J100000,SUMMARY!A45&"*") -> 0 | AA45: =SUMIFS('PLAN BUDGET SAMI-JF'!BM13:BM100000,'PLAN BUDGET SAMI-JF'!D13:D100000,SUMMARY!D45,'PLAN BUDGET SAMI-JF'!J13:J100000,SUMMARY!A45&"*") -> 0 | AB45: =SUMIFS('PLAN BUDGET SAMI-JF'!BN13:BN100000,'PLAN BUDGET SAMI-JF'!D13:D100000,SUMMARY!D45,'PLAN BUDGET SAMI-JF'!J13:J100000,SUMMARY!A45&"*") -> 0 | AC45: =SUM(E45:P45) -> 0 | AD45: =SUM(Q45:AB45) -> 0 | AF45: 30 | AG45: 1784.9683 | AH45: =IFERROR((AC45-AF45)/AF45,1) -> -1 | AI45: =IFERROR((AD45-AG45)/AG45,1) -> -1 | AJ45: Budget di Term 85 tidak ada, sedangkan di Term 84 ada.
A46: INSIDENTAL | D46: STABILIZER | E46: =SUMIFS('PLAN BUDGET SAMI-JF'!AN13:AN100000,'PLAN BUDGET SAMI-JF'!D13:D100000,SUMMARY!D46,'PLAN BUDGET SAMI-JF'!J13:J100000,SUMMARY!A46&"*") -> 0 | F46: =SUMIFS('PLAN BUDGET SAMI-JF'!AO13:AO100000,'PLAN BUDGET SAMI-JF'!D13:D100000,SUMMARY!D46,'PLAN BUDGET SAMI-JF'!J13:J100000,SUMMARY!A46&"*") -> 0 | G46: =SUMIFS('PLAN BUDGET SAMI-JF'!AP13:AP100000,'PLAN BUDGET SAMI-JF'!D13:D100000,SUMMARY!D46,'PLAN BUDGET SAMI-JF'!J13:J100000,SUMMARY!A46&"*") -> 0 | H46: =SUMIFS('PLAN BUDGET SAMI-JF'!AQ13:AQ100000,'PLAN BUDGET SAMI-JF'!D13:D100000,SUMMARY!D46,'PLAN BUDGET SAMI-JF'!J13:J100000,SUMMARY!A46&"*") -> 0 | I46: =SUMIFS('PLAN BUDGET SAMI-JF'!AR13:AR100000,'PLAN BUDGET SAMI-JF'!D13:D100000,SUMMARY!D46,'PLAN BUDGET SAMI-JF'!J13:J100000,SUMMARY!A46&"*") -> 0 | J46: =SUMIFS('PLAN BUDGET SAMI-JF'!AS13:AS100000,'PLAN BUDGET SAMI-JF'!D13:D100000,SUMMARY!D46,'PLAN BUDGET SAMI-JF'!J13:J100000,SUMMARY!A46&"*") -> 0 | K46: =SUMIFS('PLAN BUDGET SAMI-JF'!AT13:AT100000,'PLAN BUDGET SAMI-JF'!D13:D100000,SUMMARY!D46,'PLAN BUDGET SAMI-JF'!J13:J100000,SUMMARY!A46&"*") -> 0 | L46: =SUMIFS('PLAN BUDGET SAMI-JF'!AU13:AU100000,'PLAN BUDGET SAMI-JF'!D13:D100000,SUMMARY!D46,'PLAN BUDGET SAMI-JF'!J13:J100000,SUMMARY!A46&"*") -> 0 | M46: =SUMIFS('PLAN BUDGET SAMI-JF'!AV13:AV100000,'PLAN BUDGET SAMI-JF'!D13:D100000,SUMMARY!D46,'PLAN BUDGET SAMI-JF'!J13:J100000,SUMMARY!A46&"*") -> 0 | N46: =SUMIFS('PLAN BUDGET SAMI-JF'!AW13:AW100000,'PLAN BUDGET SAMI-JF'!D13:D100000,SUMMARY!D46,'PLAN BUDGET SAMI-JF'!J13:J100000,SUMMARY!A46&"*") -> 0 | O46: =SUMIFS('PLAN BUDGET SAMI-JF'!AX13:AX100000,'PLAN BUDGET SAMI-JF'!D13:D100000,SUMMARY!D46,'PLAN BUDGET SAMI-JF'!J13:J100000,SUMMARY!A46&"*") -> 0 | P46: =SUMIFS('PLAN BUDGET SAMI-JF'!AY13:AY100000,'PLAN BUDGET SAMI-JF'!D13:D100000,SUMMARY!D46,'PLAN BUDGET SAMI-JF'!J13:J100000,SUMMARY!A46&"*") -> 0 | Q46: =SUMIFS('PLAN BUDGET SAMI-JF'!BC13:BC100000,'PLAN BUDGET SAMI-JF'!D13:D100000,SUMMARY!D46,'PLAN BUDGET SAMI-JF'!J13:J100000,SUMMARY!A46&"*") -> 0 | R46: =SUMIFS('PLAN BUDGET SAMI-JF'!BD13:BD100000,'PLAN BUDGET SAMI-JF'!D13:D100000,SUMMARY!D46,'PLAN BUDGET SAMI-JF'!J13:J100000,SUMMARY!A46&"*") -> 0 | S46: =SUMIFS('PLAN BUDGET SAMI-JF'!BE13:BE100000,'PLAN BUDGET SAMI-JF'!D13:D100000,SUMMARY!D46,'PLAN BUDGET SAMI-JF'!J13:J100000,SUMMARY!A46&"*") -> 0 | T46: =SUMIFS('PLAN BUDGET SAMI-JF'!BF13:BF100000,'PLAN BUDGET SAMI-JF'!D13:D100000,SUMMARY!D46,'PLAN BUDGET SAMI-JF'!J13:J100000,SUMMARY!A46&"*") -> 0 | U46: =SUMIFS('PLAN BUDGET SAMI-JF'!BG13:BG100000,'PLAN BUDGET SAMI-JF'!D13:D100000,SUMMARY!D46,'PLAN BUDGET SAMI-JF'!J13:J100000,SUMMARY!A46&"*") -> 0 | V46: =SUMIFS('PLAN BUDGET SAMI-JF'!BH13:BH100000,'PLAN BUDGET SAMI-JF'!D13:D100000,SUMMARY!D46,'PLAN BUDGET SAMI-JF'!J13:J100000,SUMMARY!A46&"*") -> 0 | W46: =SUMIFS('PLAN BUDGET SAMI-JF'!BI13:BI100000,'PLAN BUDGET SAMI-JF'!D13:D100000,SUMMARY!D46,'PLAN BUDGET SAMI-JF'!J13:J100000,SUMMARY!A46&"*") -> 0 | X46: =SUMIFS('PLAN BUDGET SAMI-JF'!BJ13:BJ100000,'PLAN BUDGET SAMI-JF'!D13:D100000,SUMMARY!D46,'PLAN BUDGET SAMI-JF'!J13:J100000,SUMMARY!A46&"*") -> 0 | Y46: =SUMIFS('PLAN BUDGET SAMI-JF'!BK13:BK100000,'PLAN BUDGET SAMI-JF'!D13:D100000,SUMMARY!D46,'PLAN BUDGET SAMI-JF'!J13:J100000,SUMMARY!A46&"*") -> 0 | Z46: =SUMIFS('PLAN BUDGET SAMI-JF'!BL13:BL100000,'PLAN BUDGET SAMI-JF'!D13:D100000,SUMMARY!D46,'PLAN BUDGET SAMI-JF'!J13:J100000,SUMMARY!A46&"*") -> 0 | AA46: =SUMIFS('PLAN BUDGET SAMI-JF'!BM13:BM100000,'PLAN BUDGET SAMI-JF'!D13:D100000,SUMMARY!D46,'PLAN BUDGET SAMI-JF'!J13:J100000,SUMMARY!A46&"*") -> 0 | AB46: =SUMIFS('PLAN BUDGET SAMI-JF'!BN13:BN100000,'PLAN BUDGET SAMI-JF'!D13:D100000,SUMMARY!D46,'PLAN BUDGET SAMI-JF'!J13:J100000,SUMMARY!A46&"*") -> 0 | AC46: =SUM(E46:P46) -> 0 | AD46: =SUM(Q46:AB46) -> 0 | AF46: 1 | AG46: 224.70345 | AH46: =IFERROR((AC46-AF46)/AF46,1) -> -1 | AI46: =IFERROR((AD46-AG46)/AG46,1) -> -1 | AJ46: Budget di Term 85 tidak ada, sedangkan di Term 84 ada.
A47: INSIDENTAL | D47: STAND TABLET | E47: =SUMIFS('PLAN BUDGET SAMI-JF'!AN13:AN100000,'PLAN BUDGET SAMI-JF'!D13:D100000,SUMMARY!D47,'PLAN BUDGET SAMI-JF'!J13:J100000,SUMMARY!A47&"*") -> 0 | F47: =SUMIFS('PLAN BUDGET SAMI-JF'!AO13:AO100000,'PLAN BUDGET SAMI-JF'!D13:D100000,SUMMARY!D47,'PLAN BUDGET SAMI-JF'!J13:J100000,SUMMARY!A47&"*") -> 0 | G47: =SUMIFS('PLAN BUDGET SAMI-JF'!AP13:AP100000,'PLAN BUDGET SAMI-JF'!D13:D100000,SUMMARY!D47,'PLAN BUDGET SAMI-JF'!J13:J100000,SUMMARY!A47&"*") -> 0 | H47: =SUMIFS('PLAN BUDGET SAMI-JF'!AQ13:AQ100000,'PLAN BUDGET SAMI-JF'!D13:D100000,SUMMARY!D47,'PLAN BUDGET SAMI-JF'!J13:J100000,SUMMARY!A47&"*") -> 0 | I47: =SUMIFS('PLAN BUDGET SAMI-JF'!AR13:AR100000,'PLAN BUDGET SAMI-JF'!D13:D100000,SUMMARY!D47,'PLAN BUDGET SAMI-JF'!J13:J100000,SUMMARY!A47&"*") -> 0 | J47: =SUMIFS('PLAN BUDGET SAMI-JF'!AS13:AS100000,'PLAN BUDGET SAMI-JF'!D13:D100000,SUMMARY!D47,'PLAN BUDGET SAMI-JF'!J13:J100000,SUMMARY!A47&"*") -> 0 | K47: =SUMIFS('PLAN BUDGET SAMI-JF'!AT13:AT100000,'PLAN BUDGET SAMI-JF'!D13:D100000,SUMMARY!D47,'PLAN BUDGET SAMI-JF'!J13:J100000,SUMMARY!A47&"*") -> 0 | L47: =SUMIFS('PLAN BUDGET SAMI-JF'!AU13:AU100000,'PLAN BUDGET SAMI-JF'!D13:D100000,SUMMARY!D47,'PLAN BUDGET SAMI-JF'!J13:J100000,SUMMARY!A47&"*") -> 0 | M47: =SUMIFS('PLAN BUDGET SAMI-JF'!AV13:AV100000,'PLAN BUDGET SAMI-JF'!D13:D100000,SUMMARY!D47,'PLAN BUDGET SAMI-JF'!J13:J100000,SUMMARY!A47&"*") -> 0 | N47: =SUMIFS('PLAN BUDGET SAMI-JF'!AW13:AW100000,'PLAN BUDGET SAMI-JF'!D13:D100000,SUMMARY!D47,'PLAN BUDGET SAMI-JF'!J13:J100000,SUMMARY!A47&"*") -> 0 | O47: =SUMIFS('PLAN BUDGET SAMI-JF'!AX13:AX100000,'PLAN BUDGET SAMI-JF'!D13:D100000,SUMMARY!D47,'PLAN BUDGET SAMI-JF'!J13:J100000,SUMMARY!A47&"*") -> 0 | P47: =SUMIFS('PLAN BUDGET SAMI-JF'!AY13:AY100000,'PLAN BUDGET SAMI-JF'!D13:D100000,SUMMARY!D47,'PLAN BUDGET SAMI-JF'!J13:J100000,SUMMARY!A47&"*") -> 0 | Q47: =SUMIFS('PLAN BUDGET SAMI-JF'!BC13:BC100000,'PLAN BUDGET SAMI-JF'!D13:D100000,SUMMARY!D47,'PLAN BUDGET SAMI-JF'!J13:J100000,SUMMARY!A47&"*") -> 0 | R47: =SUMIFS('PLAN BUDGET SAMI-JF'!BD13:BD100000,'PLAN BUDGET SAMI-JF'!D13:D100000,SUMMARY!D47,'PLAN BUDGET SAMI-JF'!J13:J100000,SUMMARY!A47&"*") -> 0 | S47: =SUMIFS('PLAN BUDGET SAMI-JF'!BE13:BE100000,'PLAN BUDGET SAMI-JF'!D13:D100000,SUMMARY!D47,'PLAN BUDGET SAMI-JF'!J13:J100000,SUMMARY!A47&"*") -> 0 | T47: =SUMIFS('PLAN BUDGET SAMI-JF'!BF13:BF100000,'PLAN BUDGET SAMI-JF'!D13:D100000,SUMMARY!D47,'PLAN BUDGET SAMI-JF'!J13:J100000,SUMMARY!A47&"*") -> 0 | U47: =SUMIFS('PLAN BUDGET SAMI-JF'!BG13:BG100000,'PLAN BUDGET SAMI-JF'!D13:D100000,SUMMARY!D47,'PLAN BUDGET SAMI-JF'!J13:J100000,SUMMARY!A47&"*") -> 0 | V47: =SUMIFS('PLAN BUDGET SAMI-JF'!BH13:BH100000,'PLAN BUDGET SAMI-JF'!D13:D100000,SUMMARY!D47,'PLAN BUDGET SAMI-JF'!J13:J100000,SUMMARY!A47&"*") -> 0 | W47: =SUMIFS('PLAN BUDGET SAMI-JF'!BI13:BI100000,'PLAN BUDGET SAMI-JF'!D13:D100000,SUMMARY!D47,'PLAN BUDGET SAMI-JF'!J13:J100000,SUMMARY!A47&"*") -> 0 | X47: =SUMIFS('PLAN BUDGET SAMI-JF'!BJ13:BJ100000,'PLAN BUDGET SAMI-JF'!D13:D100000,SUMMARY!D47,'PLAN BUDGET SAMI-JF'!J13:J100000,SUMMARY!A47&"*") -> 0 | Y47: =SUMIFS('PLAN BUDGET SAMI-JF'!BK13:BK100000,'PLAN BUDGET SAMI-JF'!D13:D100000,SUMMARY!D47,'PLAN BUDGET SAMI-JF'!J13:J100000,SUMMARY!A47&"*") -> 0 | Z47: =SUMIFS('PLAN BUDGET SAMI-JF'!BL13:BL100000,'PLAN BUDGET SAMI-JF'!D13:D100000,SUMMARY!D47,'PLAN BUDGET SAMI-JF'!J13:J100000,SUMMARY!A47&"*") -> 0 | AA47: =SUMIFS('PLAN BUDGET SAMI-JF'!BM13:BM100000,'PLAN BUDGET SAMI-JF'!D13:D100000,SUMMARY!D47,'PLAN BUDGET SAMI-JF'!J13:J100000,SUMMARY!A47&"*") -> 0 | AB47: =SUMIFS('PLAN BUDGET SAMI-JF'!BN13:BN100000,'PLAN BUDGET SAMI-JF'!D13:D100000,SUMMARY!D47,'PLAN BUDGET SAMI-JF'!J13:J100000,SUMMARY!A47&"*") -> 0 | AC47: =SUM(E47:P47) -> 0 | AD47: =SUM(Q47:AB47) -> 0 | AF47: 30 | AG47: 1746.9902 | AH47: =IFERROR((AC47-AF47)/AF47,1) -> -1 | AI47: =IFERROR((AD47-AG47)/AG47,1) -> -1 | AJ47: Budget di Term 85 tidak ada, sedangkan di Term 84 ada.
A48: INSIDENTAL | D48: TIKET PERJALANAN DINAS | E48: =SUMIFS('PLAN BUDGET SAMI-JF'!AN13:AN100000,'PLAN BUDGET SAMI-JF'!D13:D100000,SUMMARY!D48,'PLAN BUDGET SAMI-JF'!J13:J100000,SUMMARY!A48&"*") -> 0 | F48: =SUMIFS('PLAN BUDGET SAMI-JF'!AO13:AO100000,'PLAN BUDGET SAMI-JF'!D13:D100000,SUMMARY!D48,'PLAN BUDGET SAMI-JF'!J13:J100000,SUMMARY!A48&"*") -> 0 | G48: =SUMIFS('PLAN BUDGET SAMI-JF'!AP13:AP100000,'PLAN BUDGET SAMI-JF'!D13:D100000,SUMMARY!D48,'PLAN BUDGET SAMI-JF'!J13:J100000,SUMMARY!A48&"*") -> 0 | H48: =SUMIFS('PLAN BUDGET SAMI-JF'!AQ13:AQ100000,'PLAN BUDGET SAMI-JF'!D13:D100000,SUMMARY!D48,'PLAN BUDGET SAMI-JF'!J13:J100000,SUMMARY!A48&"*") -> 0 | I48: =SUMIFS('PLAN BUDGET SAMI-JF'!AR13:AR100000,'PLAN BUDGET SAMI-JF'!D13:D100000,SUMMARY!D48,'PLAN BUDGET SAMI-JF'!J13:J100000,SUMMARY!A48&"*") -> 0 | J48: =SUMIFS('PLAN BUDGET SAMI-JF'!AS13:AS100000,'PLAN BUDGET SAMI-JF'!D13:D100000,SUMMARY!D48,'PLAN BUDGET SAMI-JF'!J13:J100000,SUMMARY!A48&"*") -> 0 | K48: =SUMIFS('PLAN BUDGET SAMI-JF'!AT13:AT100000,'PLAN BUDGET SAMI-JF'!D13:D100000,SUMMARY!D48,'PLAN BUDGET SAMI-JF'!J13:J100000,SUMMARY!A48&"*") -> 0 | L48: =SUMIFS('PLAN BUDGET SAMI-JF'!AU13:AU100000,'PLAN BUDGET SAMI-JF'!D13:D100000,SUMMARY!D48,'PLAN BUDGET SAMI-JF'!J13:J100000,SUMMARY!A48&"*") -> 0 | M48: =SUMIFS('PLAN BUDGET SAMI-JF'!AV13:AV100000,'PLAN BUDGET SAMI-JF'!D13:D100000,SUMMARY!D48,'PLAN BUDGET SAMI-JF'!J13:J100000,SUMMARY!A48&"*") -> 0 | N48: =SUMIFS('PLAN BUDGET SAMI-JF'!AW13:AW100000,'PLAN BUDGET SAMI-JF'!D13:D100000,SUMMARY!D48,'PLAN BUDGET SAMI-JF'!J13:J100000,SUMMARY!A48&"*") -> 0 | O48: =SUMIFS('PLAN BUDGET SAMI-JF'!AX13:AX100000,'PLAN BUDGET SAMI-JF'!D13:D100000,SUMMARY!D48,'PLAN BUDGET SAMI-JF'!J13:J100000,SUMMARY!A48&"*") -> 0 | P48: =SUMIFS('PLAN BUDGET SAMI-JF'!AY13:AY100000,'PLAN BUDGET SAMI-JF'!D13:D100000,SUMMARY!D48,'PLAN BUDGET SAMI-JF'!J13:J100000,SUMMARY!A48&"*") -> 0 | Q48: =SUMIFS('PLAN BUDGET SAMI-JF'!BC13:BC100000,'PLAN BUDGET SAMI-JF'!D13:D100000,SUMMARY!D48,'PLAN BUDGET SAMI-JF'!J13:J100000,SUMMARY!A48&"*") -> 0 | R48: =SUMIFS('PLAN BUDGET SAMI-JF'!BD13:BD100000,'PLAN BUDGET SAMI-JF'!D13:D100000,SUMMARY!D48,'PLAN BUDGET SAMI-JF'!J13:J100000,SUMMARY!A48&"*") -> 0 | S48: =SUMIFS('PLAN BUDGET SAMI-JF'!BE13:BE100000,'PLAN BUDGET SAMI-JF'!D13:D100000,SUMMARY!D48,'PLAN BUDGET SAMI-JF'!J13:J100000,SUMMARY!A48&"*") -> 0 | T48: =SUMIFS('PLAN BUDGET SAMI-JF'!BF13:BF100000,'PLAN BUDGET SAMI-JF'!D13:D100000,SUMMARY!D48,'PLAN BUDGET SAMI-JF'!J13:J100000,SUMMARY!A48&"*") -> 0 | U48: =SUMIFS('PLAN BUDGET SAMI-JF'!BG13:BG100000,'PLAN BUDGET SAMI-JF'!D13:D100000,SUMMARY!D48,'PLAN BUDGET SAMI-JF'!J13:J100000,SUMMARY!A48&"*") -> 0 | V48: =SUMIFS('PLAN BUDGET SAMI-JF'!BH13:BH100000,'PLAN BUDGET SAMI-JF'!D13:D100000,SUMMARY!D48,'PLAN BUDGET SAMI-JF'!J13:J100000,SUMMARY!A48&"*") -> 0 | W48: =SUMIFS('PLAN BUDGET SAMI-JF'!BI13:BI100000,'PLAN BUDGET SAMI-JF'!D13:D100000,SUMMARY!D48,'PLAN BUDGET SAMI-JF'!J13:J100000,SUMMARY!A48&"*") -> 0 | X48: =SUMIFS('PLAN BUDGET SAMI-JF'!BJ13:BJ100000,'PLAN BUDGET SAMI-JF'!D13:D100000,SUMMARY!D48,'PLAN BUDGET SAMI-JF'!J13:J100000,SUMMARY!A48&"*") -> 0 | Y48: =SUMIFS('PLAN BUDGET SAMI-JF'!BK13:BK100000,'PLAN BUDGET SAMI-JF'!D13:D100000,SUMMARY!D48,'PLAN BUDGET SAMI-JF'!J13:J100000,SUMMARY!A48&"*") -> 0 | Z48: =SUMIFS('PLAN BUDGET SAMI-JF'!BL13:BL100000,'PLAN BUDGET SAMI-JF'!D13:D100000,SUMMARY!D48,'PLAN BUDGET SAMI-JF'!J13:J100000,SUMMARY!A48&"*") -> 0 | AA48: =SUMIFS('PLAN BUDGET SAMI-JF'!BM13:BM100000,'PLAN BUDGET SAMI-JF'!D13:D100000,SUMMARY!D48,'PLAN BUDGET SAMI-JF'!J13:J100000,SUMMARY!A48&"*") -> 0 | AB48: =SUMIFS('PLAN BUDGET SAMI-JF'!BN13:BN100000,'PLAN BUDGET SAMI-JF'!D13:D100000,SUMMARY!D48,'PLAN BUDGET SAMI-JF'!J13:J100000,SUMMARY!A48&"*") -> 0 | AC48: =SUM(E48:P48) -> 0 | AD48: =SUM(Q48:AB48) -> 0 | AF48: 1 | AG48: 39.598445 | AH48: =IFERROR((AC48-AF48)/AF48,1) -> -1 | AI48: =IFERROR((AD48-AG48)/AG48,1) -> -1 | AJ48: Budget di Term 85 tidak ada, sedangkan di Term 84 ada.
A49: INSIDENTAL | D49: TRIPOD | E49: =SUMIFS('PLAN BUDGET SAMI-JF'!AN13:AN100000,'PLAN BUDGET SAMI-JF'!D13:D100000,SUMMARY!D49,'PLAN BUDGET SAMI-JF'!J13:J100000,SUMMARY!A49&"*") -> 0 | F49: =SUMIFS('PLAN BUDGET SAMI-JF'!AO13:AO100000,'PLAN BUDGET SAMI-JF'!D13:D100000,SUMMARY!D49,'PLAN BUDGET SAMI-JF'!J13:J100000,SUMMARY!A49&"*") -> 0 | G49: =SUMIFS('PLAN BUDGET SAMI-JF'!AP13:AP100000,'PLAN BUDGET SAMI-JF'!D13:D100000,SUMMARY!D49,'PLAN BUDGET SAMI-JF'!J13:J100000,SUMMARY!A49&"*") -> 0 | H49: =SUMIFS('PLAN BUDGET SAMI-JF'!AQ13:AQ100000,'PLAN BUDGET SAMI-JF'!D13:D100000,SUMMARY!D49,'PLAN BUDGET SAMI-JF'!J13:J100000,SUMMARY!A49&"*") -> 0 | I49: =SUMIFS('PLAN BUDGET SAMI-JF'!AR13:AR100000,'PLAN BUDGET SAMI-JF'!D13:D100000,SUMMARY!D49,'PLAN BUDGET SAMI-JF'!J13:J100000,SUMMARY!A49&"*") -> 0 | J49: =SUMIFS('PLAN BUDGET SAMI-JF'!AS13:AS100000,'PLAN BUDGET SAMI-JF'!D13:D100000,SUMMARY!D49,'PLAN BUDGET SAMI-JF'!J13:J100000,SUMMARY!A49&"*") -> 0 | K49: =SUMIFS('PLAN BUDGET SAMI-JF'!AT13:AT100000,'PLAN BUDGET SAMI-JF'!D13:D100000,SUMMARY!D49,'PLAN BUDGET SAMI-JF'!J13:J100000,SUMMARY!A49&"*") -> 0 | L49: =SUMIFS('PLAN BUDGET SAMI-JF'!AU13:AU100000,'PLAN BUDGET SAMI-JF'!D13:D100000,SUMMARY!D49,'PLAN BUDGET SAMI-JF'!J13:J100000,SUMMARY!A49&"*") -> 0 | M49: =SUMIFS('PLAN BUDGET SAMI-JF'!AV13:AV100000,'PLAN BUDGET SAMI-JF'!D13:D100000,SUMMARY!D49,'PLAN BUDGET SAMI-JF'!J13:J100000,SUMMARY!A49&"*") -> 0 | N49: =SUMIFS('PLAN BUDGET SAMI-JF'!AW13:AW100000,'PLAN BUDGET SAMI-JF'!D13:D100000,SUMMARY!D49,'PLAN BUDGET SAMI-JF'!J13:J100000,SUMMARY!A49&"*") -> 0 | O49: =SUMIFS('PLAN BUDGET SAMI-JF'!AX13:AX100000,'PLAN BUDGET SAMI-JF'!D13:D100000,SUMMARY!D49,'PLAN BUDGET SAMI-JF'!J13:J100000,SUMMARY!A49&"*") -> 0 | P49: =SUMIFS('PLAN BUDGET SAMI-JF'!AY13:AY100000,'PLAN BUDGET SAMI-JF'!D13:D100000,SUMMARY!D49,'PLAN BUDGET SAMI-JF'!J13:J100000,SUMMARY!A49&"*") -> 0 | Q49: =SUMIFS('PLAN BUDGET SAMI-JF'!BC13:BC100000,'PLAN BUDGET SAMI-JF'!D13:D100000,SUMMARY!D49,'PLAN BUDGET SAMI-JF'!J13:J100000,SUMMARY!A49&"*") -> 0 | R49: =SUMIFS('PLAN BUDGET SAMI-JF'!BD13:BD100000,'PLAN BUDGET SAMI-JF'!D13:D100000,SUMMARY!D49,'PLAN BUDGET SAMI-JF'!J13:J100000,SUMMARY!A49&"*") -> 0 | S49: =SUMIFS('PLAN BUDGET SAMI-JF'!BE13:BE100000,'PLAN BUDGET SAMI-JF'!D13:D100000,SUMMARY!D49,'PLAN BUDGET SAMI-JF'!J13:J100000,SUMMARY!A49&"*") -> 0 | T49: =SUMIFS('PLAN BUDGET SAMI-JF'!BF13:BF100000,'PLAN BUDGET SAMI-JF'!D13:D100000,SUMMARY!D49,'PLAN BUDGET SAMI-JF'!J13:J100000,SUMMARY!A49&"*") -> 0 | U49: =SUMIFS('PLAN BUDGET SAMI-JF'!BG13:BG100000,'PLAN BUDGET SAMI-JF'!D13:D100000,SUMMARY!D49,'PLAN BUDGET SAMI-JF'!J13:J100000,SUMMARY!A49&"*") -> 0 | V49: =SUMIFS('PLAN BUDGET SAMI-JF'!BH13:BH100000,'PLAN BUDGET SAMI-JF'!D13:D100000,SUMMARY!D49,'PLAN BUDGET SAMI-JF'!J13:J100000,SUMMARY!A49&"*") -> 0 | W49: =SUMIFS('PLAN BUDGET SAMI-JF'!BI13:BI100000,'PLAN BUDGET SAMI-JF'!D13:D100000,SUMMARY!D49,'PLAN BUDGET SAMI-JF'!J13:J100000,SUMMARY!A49&"*") -> 0 | X49: =SUMIFS('PLAN BUDGET SAMI-JF'!BJ13:BJ100000,'PLAN BUDGET SAMI-JF'!D13:D100000,SUMMARY!D49,'PLAN BUDGET SAMI-JF'!J13:J100000,SUMMARY!A49&"*") -> 0 | Y49: =SUMIFS('PLAN BUDGET SAMI-JF'!BK13:BK100000,'PLAN BUDGET SAMI-JF'!D13:D100000,SUMMARY!D49,'PLAN BUDGET SAMI-JF'!J13:J100000,SUMMARY!A49&"*") -> 0 | Z49: =SUMIFS('PLAN BUDGET SAMI-JF'!BL13:BL100000,'PLAN BUDGET SAMI-JF'!D13:D100000,SUMMARY!D49,'PLAN BUDGET SAMI-JF'!J13:J100000,SUMMARY!A49&"*") -> 0 | AA49: =SUMIFS('PLAN BUDGET SAMI-JF'!BM13:BM100000,'PLAN BUDGET SAMI-JF'!D13:D100000,SUMMARY!D49,'PLAN BUDGET SAMI-JF'!J13:J100000,SUMMARY!A49&"*") -> 0 | AB49: =SUMIFS('PLAN BUDGET SAMI-JF'!BN13:BN100000,'PLAN BUDGET SAMI-JF'!D13:D100000,SUMMARY!D49,'PLAN BUDGET SAMI-JF'!J13:J100000,SUMMARY!A49&"*") -> 0 | AC49: =SUM(E49:P49) -> 0 | AD49: =SUM(Q49:AB49) -> 0 | AF49: 1 | AG49: 104.43963 | AH49: =IFERROR((AC49-AF49)/AF49,1) -> -1 | AI49: =IFERROR((AD49-AG49)/AG49,1) -> -1 | AJ49: Budget di Term 85 tidak ada, sedangkan di Term 84 ada.
A50: INSIDENTAL | D50: UANG SAKU PERJALANAN DINAS | E50: =SUMIFS('PLAN BUDGET SAMI-JF'!AN13:AN100000,'PLAN BUDGET SAMI-JF'!D13:D100000,SUMMARY!D50,'PLAN BUDGET SAMI-JF'!J13:J100000,SUMMARY!A50&"*") -> 0 | F50: =SUMIFS('PLAN BUDGET SAMI-JF'!AO13:AO100000,'PLAN BUDGET SAMI-JF'!D13:D100000,SUMMARY!D50,'PLAN BUDGET SAMI-JF'!J13:J100000,SUMMARY!A50&"*") -> 0 | G50: =SUMIFS('PLAN BUDGET SAMI-JF'!AP13:AP100000,'PLAN BUDGET SAMI-JF'!D13:D100000,SUMMARY!D50,'PLAN BUDGET SAMI-JF'!J13:J100000,SUMMARY!A50&"*") -> 0 | H50: =SUMIFS('PLAN BUDGET SAMI-JF'!AQ13:AQ100000,'PLAN BUDGET SAMI-JF'!D13:D100000,SUMMARY!D50,'PLAN BUDGET SAMI-JF'!J13:J100000,SUMMARY!A50&"*") -> 0 | I50: =SUMIFS('PLAN BUDGET SAMI-JF'!AR13:AR100000,'PLAN BUDGET SAMI-JF'!D13:D100000,SUMMARY!D50,'PLAN BUDGET SAMI-JF'!J13:J100000,SUMMARY!A50&"*") -> 0 | J50: =SUMIFS('PLAN BUDGET SAMI-JF'!AS13:AS100000,'PLAN BUDGET SAMI-JF'!D13:D100000,SUMMARY!D50,'PLAN BUDGET SAMI-JF'!J13:J100000,SUMMARY!A50&"*") -> 0 | K50: =SUMIFS('PLAN BUDGET SAMI-JF'!AT13:AT100000,'PLAN BUDGET SAMI-JF'!D13:D100000,SUMMARY!D50,'PLAN BUDGET SAMI-JF'!J13:J100000,SUMMARY!A50&"*") -> 0 | L50: =SUMIFS('PLAN BUDGET SAMI-JF'!AU13:AU100000,'PLAN BUDGET SAMI-JF'!D13:D100000,SUMMARY!D50,'PLAN BUDGET SAMI-JF'!J13:J100000,SUMMARY!A50&"*") -> 0 | M50: =SUMIFS('PLAN BUDGET SAMI-JF'!AV13:AV100000,'PLAN BUDGET SAMI-JF'!D13:D100000,SUMMARY!D50,'PLAN BUDGET SAMI-JF'!J13:J100000,SUMMARY!A50&"*") -> 0 | N50: =SUMIFS('PLAN BUDGET SAMI-JF'!AW13:AW100000,'PLAN BUDGET SAMI-JF'!D13:D100000,SUMMARY!D50,'PLAN BUDGET SAMI-JF'!J13:J100000,SUMMARY!A50&"*") -> 0 | O50: =SUMIFS('PLAN BUDGET SAMI-JF'!AX13:AX100000,'PLAN BUDGET SAMI-JF'!D13:D100000,SUMMARY!D50,'PLAN BUDGET SAMI-JF'!J13:J100000,SUMMARY!A50&"*") -> 0 | P50: =SUMIFS('PLAN BUDGET SAMI-JF'!AY13:AY100000,'PLAN BUDGET SAMI-JF'!D13:D100000,SUMMARY!D50,'PLAN BUDGET SAMI-JF'!J13:J100000,SUMMARY!A50&"*") -> 0 | Q50: =SUMIFS('PLAN BUDGET SAMI-JF'!BC13:BC100000,'PLAN BUDGET SAMI-JF'!D13:D100000,SUMMARY!D50,'PLAN BUDGET SAMI-JF'!J13:J100000,SUMMARY!A50&"*") -> 0 | R50: =SUMIFS('PLAN BUDGET SAMI-JF'!BD13:BD100000,'PLAN BUDGET SAMI-JF'!D13:D100000,SUMMARY!D50,'PLAN BUDGET SAMI-JF'!J13:J100000,SUMMARY!A50&"*") -> 0 | S50: =SUMIFS('PLAN BUDGET SAMI-JF'!BE13:BE100000,'PLAN BUDGET SAMI-JF'!D13:D100000,SUMMARY!D50,'PLAN BUDGET SAMI-JF'!J13:J100000,SUMMARY!A50&"*") -> 0 | T50: =SUMIFS('PLAN BUDGET SAMI-JF'!BF13:BF100000,'PLAN BUDGET SAMI-JF'!D13:D100000,SUMMARY!D50,'PLAN BUDGET SAMI-JF'!J13:J100000,SUMMARY!A50&"*") -> 0 | U50: =SUMIFS('PLAN BUDGET SAMI-JF'!BG13:BG100000,'PLAN BUDGET SAMI-JF'!D13:D100000,SUMMARY!D50,'PLAN BUDGET SAMI-JF'!J13:J100000,SUMMARY!A50&"*") -> 0 | V50: =SUMIFS('PLAN BUDGET SAMI-JF'!BH13:BH100000,'PLAN BUDGET SAMI-JF'!D13:D100000,SUMMARY!D50,'PLAN BUDGET SAMI-JF'!J13:J100000,SUMMARY!A50&"*") -> 0 | W50: =SUMIFS('PLAN BUDGET SAMI-JF'!BI13:BI100000,'PLAN BUDGET SAMI-JF'!D13:D100000,SUMMARY!D50,'PLAN BUDGET SAMI-JF'!J13:J100000,SUMMARY!A50&"*") -> 0 | X50: =SUMIFS('PLAN BUDGET SAMI-JF'!BJ13:BJ100000,'PLAN BUDGET SAMI-JF'!D13:D100000,SUMMARY!D50,'PLAN BUDGET SAMI-JF'!J13:J100000,SUMMARY!A50&"*") -> 0 | Y50: =SUMIFS('PLAN BUDGET SAMI-JF'!BK13:BK100000,'PLAN BUDGET SAMI-JF'!D13:D100000,SUMMARY!D50,'PLAN BUDGET SAMI-JF'!J13:J100000,SUMMARY!A50&"*") -> 0 | Z50: =SUMIFS('PLAN BUDGET SAMI-JF'!BL13:BL100000,'PLAN BUDGET SAMI-JF'!D13:D100000,SUMMARY!D50,'PLAN BUDGET SAMI-JF'!J13:J100000,SUMMARY!A50&"*") -> 0 | AA50: =SUMIFS('PLAN BUDGET SAMI-JF'!BM13:BM100000,'PLAN BUDGET SAMI-JF'!D13:D100000,SUMMARY!D50,'PLAN BUDGET SAMI-JF'!J13:J100000,SUMMARY!A50&"*") -> 0 | AB50: =SUMIFS('PLAN BUDGET SAMI-JF'!BN13:BN100000,'PLAN BUDGET SAMI-JF'!D13:D100000,SUMMARY!D50,'PLAN BUDGET SAMI-JF'!J13:J100000,SUMMARY!A50&"*") -> 0 | AC50: =SUM(E50:P50) -> 0 | AD50: =SUM(Q50:AB50) -> 0 | AF50: 57 | AG50: 345.63189 | AH50: =IFERROR((AC50-AF50)/AF50,1) -> -1 | AI50: =IFERROR((AD50-AG50)/AG50,1) -> -1 | AJ50: Budget di Term 85 tidak ada, sedangkan di Term 84 ada.
A51: PROJECT | D51: PLASTIK FOTO 4M | E51: =SUMIFS('PLAN BUDGET SAMI-JF'!AN13:AN100000,'PLAN BUDGET SAMI-JF'!D13:D100000,SUMMARY!D51,'PLAN BUDGET SAMI-JF'!J13:J100000,SUMMARY!A51&"*") -> 0 | F51: =SUMIFS('PLAN BUDGET SAMI-JF'!AO13:AO100000,'PLAN BUDGET SAMI-JF'!D13:D100000,SUMMARY!D51,'PLAN BUDGET SAMI-JF'!J13:J100000,SUMMARY!A51&"*") -> 0 | G51: =SUMIFS('PLAN BUDGET SAMI-JF'!AP13:AP100000,'PLAN BUDGET SAMI-JF'!D13:D100000,SUMMARY!D51,'PLAN BUDGET SAMI-JF'!J13:J100000,SUMMARY!A51&"*") -> 0 | H51: =SUMIFS('PLAN BUDGET SAMI-JF'!AQ13:AQ100000,'PLAN BUDGET SAMI-JF'!D13:D100000,SUMMARY!D51,'PLAN BUDGET SAMI-JF'!J13:J100000,SUMMARY!A51&"*") -> 0 | I51: =SUMIFS('PLAN BUDGET SAMI-JF'!AR13:AR100000,'PLAN BUDGET SAMI-JF'!D13:D100000,SUMMARY!D51,'PLAN BUDGET SAMI-JF'!J13:J100000,SUMMARY!A51&"*") -> 0 | J51: =SUMIFS('PLAN BUDGET SAMI-JF'!AS13:AS100000,'PLAN BUDGET SAMI-JF'!D13:D100000,SUMMARY!D51,'PLAN BUDGET SAMI-JF'!J13:J100000,SUMMARY!A51&"*") -> 0 | K51: =SUMIFS('PLAN BUDGET SAMI-JF'!AT13:AT100000,'PLAN BUDGET SAMI-JF'!D13:D100000,SUMMARY!D51,'PLAN BUDGET SAMI-JF'!J13:J100000,SUMMARY!A51&"*") -> 0 | L51: =SUMIFS('PLAN BUDGET SAMI-JF'!AU13:AU100000,'PLAN BUDGET SAMI-JF'!D13:D100000,SUMMARY!D51,'PLAN BUDGET SAMI-JF'!J13:J100000,SUMMARY!A51&"*") -> 0 | M51: =SUMIFS('PLAN BUDGET SAMI-JF'!AV13:AV100000,'PLAN BUDGET SAMI-JF'!D13:D100000,SUMMARY!D51,'PLAN BUDGET SAMI-JF'!J13:J100000,SUMMARY!A51&"*") -> 0 | N51: =SUMIFS('PLAN BUDGET SAMI-JF'!AW13:AW100000,'PLAN BUDGET SAMI-JF'!D13:D100000,SUMMARY!D51,'PLAN BUDGET SAMI-JF'!J13:J100000,SUMMARY!A51&"*") -> 0 | O51: =SUMIFS('PLAN BUDGET SAMI-JF'!AX13:AX100000,'PLAN BUDGET SAMI-JF'!D13:D100000,SUMMARY!D51,'PLAN BUDGET SAMI-JF'!J13:J100000,SUMMARY!A51&"*") -> 0 | P51: =SUMIFS('PLAN BUDGET SAMI-JF'!AY13:AY100000,'PLAN BUDGET SAMI-JF'!D13:D100000,SUMMARY!D51,'PLAN BUDGET SAMI-JF'!J13:J100000,SUMMARY!A51&"*") -> 0 | Q51: =SUMIFS('PLAN BUDGET SAMI-JF'!BC13:BC100000,'PLAN BUDGET SAMI-JF'!D13:D100000,SUMMARY!D51,'PLAN BUDGET SAMI-JF'!J13:J100000,SUMMARY!A51&"*") -> 0 | R51: =SUMIFS('PLAN BUDGET SAMI-JF'!BD13:BD100000,'PLAN BUDGET SAMI-JF'!D13:D100000,SUMMARY!D51,'PLAN BUDGET SAMI-JF'!J13:J100000,SUMMARY!A51&"*") -> 0 | S51: =SUMIFS('PLAN BUDGET SAMI-JF'!BE13:BE100000,'PLAN BUDGET SAMI-JF'!D13:D100000,SUMMARY!D51,'PLAN BUDGET SAMI-JF'!J13:J100000,SUMMARY!A51&"*") -> 0 | T51: =SUMIFS('PLAN BUDGET SAMI-JF'!BF13:BF100000,'PLAN BUDGET SAMI-JF'!D13:D100000,SUMMARY!D51,'PLAN BUDGET SAMI-JF'!J13:J100000,SUMMARY!A51&"*") -> 0 | U51: =SUMIFS('PLAN BUDGET SAMI-JF'!BG13:BG100000,'PLAN BUDGET SAMI-JF'!D13:D100000,SUMMARY!D51,'PLAN BUDGET SAMI-JF'!J13:J100000,SUMMARY!A51&"*") -> 0 | V51: =SUMIFS('PLAN BUDGET SAMI-JF'!BH13:BH100000,'PLAN BUDGET SAMI-JF'!D13:D100000,SUMMARY!D51,'PLAN BUDGET SAMI-JF'!J13:J100000,SUMMARY!A51&"*") -> 0 | W51: =SUMIFS('PLAN BUDGET SAMI-JF'!BI13:BI100000,'PLAN BUDGET SAMI-JF'!D13:D100000,SUMMARY!D51,'PLAN BUDGET SAMI-JF'!J13:J100000,SUMMARY!A51&"*") -> 0 | X51: =SUMIFS('PLAN BUDGET SAMI-JF'!BJ13:BJ100000,'PLAN BUDGET SAMI-JF'!D13:D100000,SUMMARY!D51,'PLAN BUDGET SAMI-JF'!J13:J100000,SUMMARY!A51&"*") -> 0 | Y51: =SUMIFS('PLAN BUDGET SAMI-JF'!BK13:BK100000,'PLAN BUDGET SAMI-JF'!D13:D100000,SUMMARY!D51,'PLAN BUDGET SAMI-JF'!J13:J100000,SUMMARY!A51&"*") -> 0 | Z51: =SUMIFS('PLAN BUDGET SAMI-JF'!BL13:BL100000,'PLAN BUDGET SAMI-JF'!D13:D100000,SUMMARY!D51,'PLAN BUDGET SAMI-JF'!J13:J100000,SUMMARY!A51&"*") -> 0 | AA51: =SUMIFS('PLAN BUDGET SAMI-JF'!BM13:BM100000,'PLAN BUDGET SAMI-JF'!D13:D100000,SUMMARY!D51,'PLAN BUDGET SAMI-JF'!J13:J100000,SUMMARY!A51&"*") -> 0 | AB51: =SUMIFS('PLAN BUDGET SAMI-JF'!BN13:BN100000,'PLAN BUDGET SAMI-JF'!D13:D100000,SUMMARY!D51,'PLAN BUDGET SAMI-JF'!J13:J100000,SUMMARY!A51&"*") -> 0 | AC51: =SUM(E51:P51) -> 0 | AD51: =SUM(Q51:AB51) -> 0 | AF51: 351 | AG51: 99.831757 | AH51: =IFERROR((AC51-AF51)/AF51,1) -> -1 | AI51: =IFERROR((AD51-AG51)/AG51,1) -> -1 | AJ51: Budget di Term 85 tidak ada, sedangkan di Term 84 ada.
