Workbook

Sheet PLAN BUDGET SAMI-TF
A1: PT. SEMARANG AUTOCOMP MANUFACTURING INDONESIA
A2: BUDGET EXPENSE FORM | N2: EXCHANGE RATE TO USD
A3: PERIODE Jul-25 SD Jun-26 | N3: IDR | O3: 15798.6
A4: DEPARTMENT-SECTION : PGA-TRN | N4: JPY | O4: 151
N5: PHP | O5: 57.671
N6: THB | O6: 34.373
N7: USD | O7: 1
N8: EUR | O8: 0.926
N9: CHF | O9: 0.872
A10: SECTION | B10: BUDGET REF NO | C10: PART_NO | D10: PART NAME | E10: DETAIL PART | F10: FUNGSI / TUJUAN | G10: SECTION CATEGORY | H10: ACC NO. | I10: ACCOUNT DESCRIPTION | J10: CATEGORY | K10: COST CENTER | L10: CARLINE | M10: CARMAKER | N10: UOM | O10: ORG CURR | P10: PRICE ORG CURR | AB10: PRICE USD | AN10: 202507 | AO10: 202508 | AP10: 202509 | AQ10: 202510 | AR10: 202511 | AS10: 202512 | AT10: 202601 | AU10: 202602 | AV10: 202603 | AW10: 202604 | AX10: 202605 | AY10: 202606 | AZ10: TOTAL | BA10: AVERAGE | BC10: 202507 | BD10: 202508 | BE10: 202509 | BF10: 202510 | BG10: 202511 | BH10: 202512 | BI10: 202601 | BJ10: 202602 | BK10: 202603 | BL10: 202604 | BM10: 202605 | BN10: 202606 | BO10: TOTAL | BP10: AVERAGE | BR10: SUB ACCOUNT | BS10: KODE PROSES | BT10: PURCHASING | BU10: LEADTIME
P11: 202507 | Q11: 202508 | R11: 202509 | S11: 202510 | T11: 202511 | U11: 202512 | V11: 202601 | W11: 202602 | X11: 202603 | Y11: 202604 | Z11: 202605 | AA11: 202606 | AB11: 202507 | AC11: 202508 | AD11: 202509 | AE11: 202510 | AF11: 202511 | AG11: 202512 | AH11: 202601 | AI11: 202602 | AJ11: 202603 | AK11: 202604 | AL11: 202605 | AM11: 202606 | AN11: QTY | AO11: QTY | AP11: QTY | AQ11: QTY | AR11: QTY | AS11: QTY | AT11: QTY | AU11: QTY | AV11: QTY | AW11: QTY | AX11: QTY | AY11: QTY | BC11: AMT | BD11: AMT | BE11: AMT | BF11: AMT | BG11: AMT | BH11: AMT | BI11: AMT | BJ11: AMT | BK11: AMT | BL11: AMT | BM11: AMT | BN11: AMT | BU11: PENAWARAN | BV11: PR | BW11: PO | BX11: KEDATANGAN | BY11: VP
A12: PGA-TRN | C12: ATK025 | D12: BALLPOINT | E12: BALLPOINT STANDARD AE7 | F12: Untuk notulen | G12: OPEX | J12: RUTIN | K12: ALL | L12: ALL | M12: ALL | N12: PCS | O12: IDR | P12: 1486 | Q12: 1486 | R12: 1486 | S12: 1486 | T12: 1486 | U12: 1486 | V12: 1486 | W12: 1486 | X12: 1486 | Y12: 1486 | Z12: 1486 | AA12: 1486 | AB12: 9.4058967250262679E-2 | AC12: 9.4058967250262679E-2 | AD12: 9.4058967250262679E-2 | AE12: 9.4058967250262679E-2 | AF12: 9.4058967250262679E-2 | AG12: 9.4058967250262679E-2 | AH12: 9.4058967250262679E-2 | AI12: 9.4058967250262679E-2 | AJ12: 9.4058967250262679E-2 | AK12: 9.4058967250262679E-2 | AL12: 9.4058967250262679E-2 | AM12: 9.4058967250262679E-2 | AN12: 1 | AO12: 0 | AP12: 0 | AQ12: 1 | AR12: 0 | AS12: 0 | AT12: 1 | AU12: 0 | AV12: 0 | AW12: 1 | AX12: 0 | AY12: 0 | AZ12: =SUM(AN12:AY12) -> 4 | BA12: =AZ12/12 -> 0.33333333 | BC12: 9.4058967250262679E-2 | BD12: 0 | BE12: 0 | BF12: 9.4058967250262679E-2 | BG12: 0 | BH12: 0 | BI12: 9.4058967250262679E-2 | BJ12: 0 | BK12: 0 | BL12: 9.4058967250262679E-2 | BM12: 0 | BN12: 0 | BO12: =SUM(BC12:BN12) -> 0 | BP12: =BO12/12 -> 0 | BS12: C | BT12: GA | BU12: 0 | BV12: 0 | BW12: 0 | BX12: 0 | BY12: 0
A13: PGA-TRN | C13: ATK051 | D13: DOUBLE TAPE | E13: DOUBLE TAPE 1/2" NACHI | F13: Untuk perlengkapan 4M | G13: OPEX | J13: RUTIN | K13: ALL | L13: ALL | M13: ALL | N13: ROL | O13: IDR | P13: 2432 | Q13: 2432 | R13: 2432 | S13: 2432 | T13: 2432 | U13: 2432 | V13: 2432 | W13: 2432 | X13: 2432 | Y13: 2432 | Z13: 2432 | AA13: 2432 | AB13: 0.15393769 | AC13: 0.15393769 | AD13: 0.15393769 | AE13: 0.15393769 | AF13: 0.15393769 | AG13: 0.15393769 | AH13: 0.15393769 | AI13: 0.15393769 | AJ13: 0.15393769 | AK13: 0.15393769 | AL13: 0.15393769 | AM13: 0.15393769 | AN13: 3 | AO13: 0 | AP13: 4 | AQ13: 0 | AR13: 3 | AS13: 0 | AT13: 4 | AU13: 0 | AV13: 3 | AW13: 0 | AX13: 4 | AY13: 0 | AZ13: =SUM(AN13:AY13) -> 21 | BA13: =AZ13/12 -> 1.75 | BC13: 0.46181307 | BD13: 0 | BE13: 0.61575076 | BF13: 0 | BG13: 0.46181307 | BH13: 0 | BI13: 0.61575076 | BJ13: 0 | BK13: 0.46181307 | BL13: 0 | BM13: 0.61575076 | BN13: 0 | BO13: =SUM(BC13:BN13) -> 3.2326915 | BP13: =BO13/12 -> 0.26939096 | BS13: C | BT13: GA | BU13: 0 | BV13: 0 | BW13: 0 | BX13: 0 | BY13: 0
A14: PGA-TRN | C14: ATK052 | D14: DOUBLE TAPE | E14: DOUBLE TAPE HIJAU | F14: Untuk perlengkapan 4M | G14: OPEX | J14: RUTIN | K14: ALL | L14: ALL | M14: ALL | N14: ROL | O14: IDR | P14: 21036 | Q14: 21036 | R14: 21036 | S14: 21036 | T14: 21036 | U14: 21036 | V14: 21036 | W14: 21036 | X14: 21036 | Y14: 21036 | Z14: 21036 | AA14: 21036 | AB14: 1.3315104 | AC14: 1.3315104 | AD14: 1.3315104 | AE14: 1.3315104 | AF14: 1.3315104 | AG14: 1.3315104 | AH14: 1.3315104 | AI14: 1.3315104 | AJ14: 1.3315104 | AK14: 1.3315104 | AL14: 1.3315104 | AM14: 1.3315104 | AN14: 0 | AO14: 0 | AP14: 0 | AQ14: 0 | AR14: 0 | AS14: 0 | AT14: 0 | AU14: 1 | AV14: 0 | AW14: 0 | AX14: 0 | AY14: 0 | AZ14: =SUM(AN14:AY14) -> 1 | BA14: =AZ14/12 -> 0.083333333 | BC14: 0 | BD14: 0 | BE14: 0 | BF14: 0 | BG14: 0 | BH14: 0 | BI14: 0 | BJ14: 1.3315104 | BK14: 0 | BL14: 0 | BM14: 0 | BN14: 0 | BO14: =SUM(BC14:BN14) -> 1.3315104 | BP14: =BO14/12 -> 0.1109592 | BS14: C | BT14: GA | BU14: 0 | BV14: 0 | BW14: 0 | BX14: 0 | BY14: 0
A15: PGA-TRN | C15: ATK079 | D15: MIKA LAMINATING | E15: MIKA LAMINATING A3 | F15: Untuk perlengkapan 4M | G15: OPEX | J15: RUTIN | K15: ALL | L15: ALL | M15: ALL | N15: PAK | O15: IDR | P15: 230270 | Q15: 230270 | R15: 230270 | S15: 230270 | T15: 230270 | U15: 230270 | V15: 230270 | W15: 230270 | X15: 230270 | Y15: 230270 | Z15: 230270 | AA15: 230270 | AB15: 14.575342 | AC15: 14.575342 | AD15: 14.575342 | AE15: 14.575342 | AF15: 14.575342 | AG15: 14.575342 | AH15: 14.575342 | AI15: 14.575342 | AJ15: 14.575342 | AK15: 14.575342 | AL15: 14.575342 | AM15: 14.575342 | AN15: 1 | AO15: 0 | AP15: 0 | AQ15: 0 | AR15: 0 | AS15: 0 | AT15: 1 | AU15: 0 | AV15: 0 | AW15: 0 | AX15: 0 | AY15: 0 | AZ15: =SUM(AN15:AY15) -> 2 | BA15: =AZ15/12 -> 0.16666667 | BC15: 14.575342 | BD15: 0 | BE15: 0 | BF15: 0 | BG15: 0 | BH15: 0 | BI15: 14.575342 | BJ15: 0 | BK15: 0 | BL15: 0 | BM15: 0 | BN15: 0 | BO15: =SUM(BC15:BN15) -> 29.150684 | BP15: =BO15/12 -> 2.4292237 | BS15: C | BT15: GA | BU15: 0 | BV15: 0 | BW15: 0 | BX15: 0 | BY15: 0
A16: PGA-TRN | C16: ATK111 | D16: STABILO | E16: STABILO BOSS | F16: Marking undangan training & C/S audit | G16: OPEX | J16: RUTIN | K16: ALL | L16: ALL | M16: ALL | N16: PCS | O16: IDR | P16: 9550 | Q16: 9550 | R16: 9550 | S16: 9550 | T16: 9550 | U16: 9550 | V16: 9550 | W16: 9550 | X16: 9550 | Y16: 9550 | Z16: 9550 | AA16: 9550 | AB16: 0.60448394 | AC16: 0.60448394 | AD16: 0.60448394 | AE16: 0.60448394 | AF16: 0.60448394 | AG16: 0.60448394 | AH16: 0.60448394 | AI16: 0.60448394 | AJ16: 0.60448394 | AK16: 0.60448394 | AL16: 0.60448394 | AM16: 0.60448394 | AN16: 0 | AO16: 0 | AP16: 1 | AQ16: 0 | AR16: 0 | AS16: 1 | AT16: 0 | AU16: 0 | AV16: 1 | AW16: 0 | AX16: 0 | AY16: 1 | AZ16: =SUM(AN16:AY16) -> 4 | BA16: =AZ16/12 -> 0.33333333 | BC16: 0 | BD16: 0 | BE16: 0.60448394 | BF16: 0 | BG16: 0 | BH16: 0.60448394 | BI16: 0 | BJ16: 0 | BK16: 0.60448394 | BL16: 0 | BM16: 0 | BN16: 0.60448394 | BO16: =SUM(BC16:BN16) -> 2.4179358 | BP16: =BO16/12 -> 0.20149465 | BS16: C | BT16: GA | BU16: 0 | BV16: 0 | BW16: 0 | BX16: 0 | BY16: 0
A17: PGA-TRN | C17: ATK155 | D17: LAKBAN | E17: LAKBAN OPP TAPE SIZE 48MM X 45MIC X 72Y BENING | F17: Untuk laminasi identitas | G17: OPEX | J17: RUTIN | K17: ALL | L17: ALL | M17: ALL | N17: ROLL | O17: IDR | P17: 8144.65 | Q17: 8144.65 | R17: 8144.65 | S17: 8144.65 | T17: 8144.65 | U17: 8144.65 | V17: 8144.65 | W17: 8144.65 | X17: 8144.65 | Y17: 8144.65 | Z17: 8144.65 | AA17: 8144.65 | AB17: 0.51552986 | AC17: 0.51552986 | AD17: 0.51552986 | AE17: 0.51552986 | AF17: 0.51552986 | AG17: 0.51552986 | AH17: 0.51552986 | AI17: 0.51552986 | AJ17: 0.51552986 | AK17: 0.51552986 | AL17: 0.51552986 | AM17: 0.51552986 | AN17: 0 | AO17: 1 | AP17: 0 | AQ17: 1 | AR17: 0 | AS17: 1 | AT17: 0 | AU17: 1 | AV17: 0 | AW17: 1 | AX17: 0 | AY17: 1 | AZ17: =SUM(AN17:AY17) -> 6 | BA17: =AZ17/12 -> 0.5 | BC17: 0 | BD17: 0.51552986 | BE17: 0 | BF17: 0.51552986 | BG17: 0 | BH17: 0.51552986 | BI17: 0 | BJ17: 0.51552986 | BK17: 0 | BL17: 0.51552986 | BM17: 0 | BN17: 0.51552986 | BO17: =SUM(BC17:BN17) -> 3.0931791 | BP17: =BO17/12 -> 0.25776493 | BS17: C | BT17: GA | BU17: 0 | BV17: 0 | BW17: 0 | BX17: 0 | BY17: 0
A18: PGA-TRN | C18: CSB021 | D18: PENGKI | E18: PENGKI GAGANG PANJANG | F18: Alat 7S di Produksi | G18: OPEX | J18: RUTIN | K18: ALL | L18: ALL | M18: ALL | N18: PCS | O18: IDR | P18: 7688 | Q18: 7688 | R18: 7688 | S18: 7688 | T18: 7688 | U18: 7688 | V18: 7688 | W18: 7688 | X18: 7688 | Y18: 7688 | Z18: 7688 | AA18: 7688 | AB18: 0.4866254 | AC18: 0.4866254 | AD18: 0.4866254 | AE18: 0.4866254 | AF18: 0.4866254 | AG18: 0.4866254 | AH18: 0.4866254 | AI18: 0.4866254 | AJ18: 0.4866254 | AK18: 0.4866254 | AL18: 0.4866254 | AM18: 0.4866254 | AN18: 1 | AO18: 0 | AP18: 1 | AQ18: 0 | AR18: 1 | AS18: 0 | AT18: 1 | AU18: 0 | AV18: 1 | AW18: 0 | AX18: 1 | AY18: 0 | AZ18: =SUM(AN18:AY18) -> 6 | BA18: =AZ18/12 -> 0.5 | BC18: 0.4866254 | BD18: 0 | BE18: 0.4866254 | BF18: 0 | BG18: 0.4866254 | BH18: 0 | BI18: 0.4866254 | BJ18: 0 | BK18: 0.4866254 | BL18: 0 | BM18: 0.4866254 | BN18: 0 | BO18: =SUM(BC18:BN18) -> 2.9197524 | BP18: =BO18/12 -> 0.2433127 | BS18: C | BT18: GA | BU18: 0 | BV18: 0 | BW18: 0 | BX18: 0 | BY18: 0
A19: PGA-TRN | C19: CSB035 | D19: TEMPAT SAMPAH | E19: TEMPAT SAMPAH GREY 42 LITER | F19: Tempat sentralisasi sampah di Produksi | G19: OPEX | J19: RUTIN | K19: ALL | L19: ALL | M19: ALL | N19: PCS | O19: IDR | P19: 76875 | Q19: 76875 | R19: 76875 | S19: 76875 | T19: 76875 | U19: 76875 | V19: 76875 | W19: 76875 | X19: 76875 | Y19: 76875 | Z19: 76875 | AA19: 76875 | AB19: 4.8659375 | AC19: 4.8659375 | AD19: 4.8659375 | AE19: 4.8659375 | AF19: 4.8659375 | AG19: 4.8659375 | AH19: 4.8659375 | AI19: 4.8659375 | AJ19: 4.8659375 | AK19: 4.8659375 | AL19: 4.8659375 | AM19: 4.8659375 | AN19: 5 | AO19: 5 | AP19: 5 | AQ19: 5 | AR19: 5 | AS19: 5 | AT19: 5 | AU19: 5 | AV19: 5 | AW19: 5 | AX19: 5 | AY19: 5 | AZ19: =SUM(AN19:AY19) -> 60 | BA19: =AZ19/12 -> 5 | BC19: 24.329687 | BD19: 24.329687 | BE19: 24.329687 | BF19: 24.329687 | BG19: 24.329687 | BH19: 24.329687 | BI19: 24.329687 | BJ19: 24.329687 | BK19: 24.329687 | BL19: 24.329687 | BM19: 24.329687 | BN19: 24.329687 | BO19: =SUM(BC19:BN19) -> 291.95625 | BP19: =BO19/12 -> 24.329687 | BS19: C | BT19: GA | BU19: 0 | BV19: 0 | BW19: 0 | BX19: 0 | BY19: 0
A20: PGA-TRN | C20: CSB106 | D20: KURSI | E20: PERBAIKAN KURSI TRAINING | F20: Untuk perbaikan kursi di area TRN | G20: OPEX | J20: RUTIN | K20: ALL | L20: ALL | M20: ALL | N20: PCS | O20: IDR | P20: 153750 | Q20: 153750 | R20: 153750 | S20: 153750 | T20: 153750 | U20: 153750 | V20: 153750 | W20: 153750 | X20: 153750 | Y20: 153750 | Z20: 153750 | AA20: 153750 | AB20: 9.731875 | AC20: 9.731875 | AD20: 9.731875 | AE20: 9.731875 | AF20: 9.731875 | AG20: 9.731875 | AH20: 9.731875 | AI20: 9.731875 | AJ20: 9.731875 | AK20: 9.731875 | AL20: 9.731875 | AM20: 9.731875 | AN20: 50 | AO20: 0 | AP20: 0 | AQ20: 0 | AR20: 0 | AS20: 0 | AT20: 50 | AU20: 0 | AV20: 0 | AW20: 0 | AX20: 0 | AY20: 0 | AZ20: =SUM(AN20:AY20) -> 100 | BA20: =AZ20/12 -> 8.3333333 | BC20: 486.59375 | BD20: 0 | BE20: 0 | BF20: 0 | BG20: 0 | BH20: 0 | BI20: 486.59375 | BJ20: 0 | BK20: 0 | BL20: 0 | BM20: 0 | BN20: 0 | BO20: =SUM(BC20:BN20) -> 973.1875 | BP20: =BO20/12 -> 81.098958 | BS20: C | BT20: GA | BU20: 0 | BV20: 0 | BW20: 0 | BX20: 0 | BY20: 0
A21: PGA-TRN | C21: CSB204 | D21: SAPU | E21: SAPU IJUK NYLON | F21: Alat 7S di Produksi | G21: OPEX | J21: RUTIN | K21: ALL | L21: ALL | M21: ALL | N21: Pcs | O21: IDR | P21: 58938 | Q21: 58938 | R21: 58938 | S21: 58938 | T21: 58938 | U21: 58938 | V21: 58938 | W21: 58938 | X21: 58938 | Y21: 58938 | Z21: 58938 | AA21: 58938 | AB21: 3.7305837 | AC21: 3.7305837 | AD21: 3.7305837 | AE21: 3.7305837 | AF21: 3.7305837 | AG21: 3.7305837 | AH21: 3.7305837 | AI21: 3.7305837 | AJ21: 3.7305837 | AK21: 3.7305837 | AL21: 3.7305837 | AM21: 3.7305837 | AN21: 40 | AO21: 40 | AP21: 40 | AQ21: 40 | AR21: 40 | AS21: 40 | AT21: 40 | AU21: 40 | AV21: 40 | AW21: 40 | AX21: 40 | AY21: 40 | AZ21: =SUM(AN21:AY21) -> 480 | BA21: =AZ21/12 -> 40 | BC21: 149.22335 | BD21: 149.22335 | BE21: 149.22335 | BF21: 149.22335 | BG21: 149.22335 | BH21: 149.22335 | BI21: 149.22335 | BJ21: 149.22335 | BK21: 149.22335 | BL21: 149.22335 | BM21: 149.22335 | BN21: 149.22335 | BO21: =SUM(BC21:BN21) -> 1790.6802 | BP21: =BO21/12 -> 149.22335 | BS21: C | BT21: GA | BU21: 0 | BV21: 0 | BW21: 0 | BX21: 0 | BY21: 0
A22: PGA-TRN | C22: GAGS021 | D22: PERJALANAN DINAS LUAR NEGERI | E22: INTERNET ROAMING | F22: Training Renewal promotor OLS | G22: OPEX | J22: RUTIN | K22: ALL | L22: ALL | M22: ALL | N22: PAKET | O22: IDR | P22: 512500 | Q22: 512500 | R22: 512500 | S22: 512500 | T22: 512500 | U22: 512500 | V22: 512500 | W22: 512500 | X22: 512500 | Y22: 512500 | Z22: 512500 | AA22: 512500 | AB22: 32.439583 | AC22: 32.439583 | AD22: 32.439583 | AE22: 32.439583 | AF22: 32.439583 | AG22: 32.439583 | AH22: 32.439583 | AI22: 32.439583 | AJ22: 32.439583 | AK22: 32.439583 | AL22: 32.439583 | AM22: 32.439583 | AN22: 0 | AO22: 0 | AP22: 2 | AQ22: 0 | AR22: 0 | AS22: 0 | AT22: 0 | AU22: 0 | AV22: 0 | AW22: 0 | AX22: 0 | AY22: 0 | AZ22: =SUM(AN22:AY22) -> 2 | BA22: =AZ22/12 -> 0.16666667 | BC22: 0 | BD22: 0 | BE22: 64.879167 | BF22: 0 | BG22: 0 | BH22: 0 | BI22: 0 | BJ22: 0 | BK22: 0 | BL22: 0 | BM22: 0 | BN22: 0 | BO22: =SUM(BC22:BN22) -> 64.879167 | BP22: =BO22/12 -> 5.4065972 | BS22: D | BT22: GA | BU22: 0 | BV22: 0 | BW22: 0 | BX22: 0 | BY22: 0
A23: PGA-TRN | C23: MCU006 | D23: MCU | E23: MCU KARYAWAN CALON MAGANG JEPANG(NMC) | F23: Magang Jepang Operator | G23: OPEX | J23: RUTIN | K23: ALL | L23: ALL | M23: ALL | N23: ORANG | O23: IDR | P23: 0 | Q23: 0 | R23: 0 | S23: 0 | T23: 0 | U23: 0 | V23: 0 | W23: 0 | X23: 0 | Y23: 0 | Z23: 0 | AA23: 0 | AB23: 0 | AC23: 0 | AD23: 0 | AE23: 0 | AF23: 0 | AG23: 0 | AH23: 0 | AI23: 0 | AJ23: 0 | AK23: 0 | AL23: 0 | AM23: 0 | AN23: 0 | AO23: 0 | AP23: 0 | AQ23: 0 | AR23: 0 | AS23: 6 | AT23: 0 | AU23: 0 | AV23: 0 | AW23: 0 | AX23: 0 | AY23: 0 | AZ23: =SUM(AN23:AY23) -> 6 | BA23: =AZ23/12 -> 0.5 | BC23: 0 | BD23: 0 | BE23: 0 | BF23: 0 | BG23: 0 | BH23: 0 | BI23: 0 | BJ23: 0 | BK23: 0 | BL23: 0 | BM23: 0 | BN23: 0 | BO23: =SUM(BC23:BN23) -> 0 | BP23: =BO23/12 -> 0 | BS23: B | BT23: GA | BU23: 0 | BV23: 0 | BW23: 0 | BX23: 0 | BY23: 0
A24: PGA-TRN | C24: MCU006 | D24: MCU | E24: MCU KARYAWAN CALON MAGANG JEPANG(NMC) | F24: MAGANG JEPANG TRAINING SKILL UP (NEW MEMBER) | G24: OPEX | J24: RUTIN | K24: ALL | L24: ALL | M24: ALL | N24: ORANG | O24: IDR | P24: 0 | Q24: 0 | R24: 0 | S24: 0 | T24: 0 | U24: 0 | V24: 0 | W24: 0 | X24: 0 | Y24: 0 | Z24: 0 | AA24: 0 | AB24: 0 | AC24: 0 | AD24: 0 | AE24: 0 | AF24: 0 | AG24: 0 | AH24: 0 | AI24: 0 | AJ24: 0 | AK24: 0 | AL24: 0 | AM24: 0 | AN24: 0 | AO24: 1 | AP24: 0 | AQ24: 0 | AR24: 0 | AS24: 0 | AT24: 0 | AU24: 0 | AV24: 0 | AW24: 0 | AX24: 0 | AY24: 0 | AZ24: =SUM(AN24:AY24) -> 1 | BA24: =AZ24/12 -> 0.083333333 | BC24: 0 | BD24: 0 | BE24: 0 | BF24: 0 | BG24: 0 | BH24: 0 | BI24: 0 | BJ24: 0 | BK24: 0 | BL24: 0 | BM24: 0 | BN24: 0 | BO24: =SUM(BC24:BN24) -> 0 | BP24: =BO24/12 -> 0 | BS24: B | BT24: GA | BU24: 0 | BV24: 0 | BW24: 0 | BX24: 0 | BY24: 0
... A188: PGA-TRN | C188: ATK054 | D188: GUNTING | E188: GUNTING BESAR | F188: Untuk pengganti gunting yang rusak | G188: OPEX | J188: RUTIN | K188: ALL | L188: ALL | M188: ALL | N188: PCS | O188: IDR | P188: 9775 | Q188: 9775 | R188: 9775 | S188: 9775 | T188: 9775 | U188: 9775 | V188: 9775 | W188: 9775 | X188: 9775 | Y188: 9775 | Z188: 9775 | AA188: 9775 | AB188: 0.61872571 | AC188: 0.61872571 | AD188: 0.61872571 | AE188: 0.61872571 | AF188: 0.61872571 | AG188: 0.61872571 | AH188: 0.61872571 | AI188: 0.61872571 | AJ188: 0.61872571 | AK188: 0.61872571 | AL188: 0.61872571 | AM188: 0.61872571 | AN188: 0 | AO188: 1 | AP188: 0 | AQ188: 0 | AR188: 0 | AS188: 0 | AT188: 0 | AU188: 0 | AV188: 0 | AW188: 0 | AX188: 0 | AY188: 0 | AZ188: =SUM(AN188:AY188) -> 1 | BA188: =AZ188/12 -> 0.083333333 | BC188: 0 | BD188: 0.61872571 | BE188: 0 | BF188: 0 | BG188: 0 | BH188: 0 | BI188: 0 | BJ188: 0 | BK188: 0 | BL188: 0 | BM188: 0 | BN188: 0 | BO188: =SUM(BC188:BN188) -> 0.61872571 | BP188: =BO188/12 -> 0.051560476 | BS188: C | BT188: GA | BU188: 0 | BV188: 0 | BW188: 0 | BX188: 0 | BY188: 0
A189: PGA-TRN | C189: ATK056 | D189: ISI BALLPOINT | E189: ISI BALLPOINT SNOWMAN V1V2 | F189: Untuk notulen | G189: OPEX | J189: RUTIN | K189: ALL | L189: ALL | M189: ALL | N189: PCS | O189: IDR | P189: 901 | Q189: 901 | R189: 901 | S189: 901 | T189: 901 | U189: 901 | V189: 901 | W189: 901 | X189: 901 | Y189: 901 | Z189: 901 | AA189: 901 | AB189: 5.7030369779600722E-2 | AC189: 5.7030369779600722E-2 | AD189: 5.7030369779600722E-2 | AE189: 5.7030369779600722E-2 | AF189: 5.7030369779600722E-2 | AG189: 5.7030369779600722E-2 | AH189: 5.7030369779600722E-2 | AI189: 5.7030369779600722E-2 | AJ189: 5.7030369779600722E-2 | AK189: 5.7030369779600722E-2 | AL189: 5.7030369779600722E-2 | AM189: 5.7030369779600722E-2 | AN189: 0 | AO189: 0 | AP189: 12 | AQ189: 0 | AR189: 0 | AS189: 12 | AT189: 0 | AU189: 0 | AV189: 12 | AW189: 0 | AX189: 0 | AY189: 6 | AZ189: =SUM(AN189:AY189) -> 42 | BA189: =AZ189/12 -> 3.5 | BC189: 0 | BD189: 0 | BE189: 0.68436444 | BF189: 0 | BG189: 0 | BH189: 0.68436444 | BI189: 0 | BJ189: 0 | BK189: 0.68436444 | BL189: 0 | BM189: 0 | BN189: 0.34218222 | BO189: =SUM(BC189:BN189) -> 2.3952755 | BP189: =BO189/12 -> 0.19960629 | BS189: C | BT189: GA | BU189: 0 | BV189: 0 | BW189: 0 | BX189: 0 | BY189: 0
A190: PGA-TRN | C190: MJM025 | D190: MAGANG JEPANG MANAGEMENT | E190: BIAYA PENERBITAN KARTU PENDUDUK RESIDENT CARD | F190: MAGANG JEPANG TRAINING SKILL UP (NEW MEMBER) | G190: OPEX | J190: RUTIN | K190: ALL | L190: ALL | M190: ALL | N190: ORANG | O190: JPY | P190: 0 | Q190: 0 | R190: 0 | S190: 0 | T190: 0 | U190: 0 | V190: 0 | W190: 0 | X190: 0 | Y190: 0 | Z190: 0 | AA190: 0 | AB190: 0 | AC190: 0 | AD190: 0 | AE190: 0 | AF190: 0 | AG190: 0 | AH190: 0 | AI190: 0 | AJ190: 0 | AK190: 0 | AL190: 0 | AM190: 0 | AN190: 0 | AO190: 0 | AP190: 0 | AQ190: 0 | AR190: 0 | AS190: 0 | AT190: 1 | AU190: 0 | AV190: 0 | AW190: 0 | AX190: 0 | AY190: 0 | AZ190: =SUM(AN190:AY190) -> 1 | BA190: =AZ190/12 -> 0.083333333 | BC190: 0 | BD190: 0 | BE190: 0 | BF190: 0 | BG190: 0 | BH190: 0 | BI190: 0 | BJ190: 0 | BK190: 0 | BL190: 0 | BM190: 0 | BN190: 0 | BO190: =SUM(BC190:BN190) -> 0 | BP190: =BO190/12 -> 0 | BS190: B | BT190: GA | BU190: 0 | BV190: 0 | BW190: 0 | BX190: 0 | BY190: 0
A191: PGA-TRN | C191: MJTP11 | D191: MAGANG JEPANG TRAINING PREPARATION | E191: BIAYA PERJALANAN DI DALAM JEPANG SELAMA MENINGGALKAN RUMAH DAN KEGIATAN LAINNYA. | F191: MAGANG JEPANG TRAINING PREPARATION (ARO-PP MEMBER) | G191: OPEX | J191: RUTIN | K191: ALL | L191: ALL | M191: ALL | N191: ORANG | O191: JPY | P191: 0 | Q191: 0 | R191: 0 | S191: 0 | T191: 0 | U191: 0 | V191: 0 | W191: 0 | X191: 0 | Y191: 0 | Z191: 0 | AA191: 0 | AB191: 0 | AC191: 0 | AD191: 0 | AE191: 0 | AF191: 0 | AG191: 0 | AH191: 0 | AI191: 0 | AJ191: 0 | AK191: 0 | AL191: 0 | AM191: 0 | AN191: 1 | AO191: 1 | AP191: 1 | AQ191: 1 | AR191: 1 | AS191: 1 | AT191: 0 | AU191: 0 | AV191: 0 | AW191: 0 | AX191: 0 | AY191: 0 | AZ191: =SUM(AN191:AY191) -> 6 | BA191: =AZ191/12 -> 0.5 | BC191: 0 | BD191: 0 | BE191: 0 | BF191: 0 | BG191: 0 | BH191: 0 | BI191: 0 | BJ191: 0 | BK191: 0 | BL191: 0 | BM191: 0 | BN191: 0 | BO191: =SUM(BC191:BN191) -> 0 | BP191: =BO191/12 -> 0 | BS191: D | BT191: GA | BU191: 0 | BV191: 0 | BW191: 0 | BX191: 0 | BY191: 0
A192: PGA-TRN | C192: MJTP11 | D192: MAGANG JEPANG TRAINING PREPARATION | E192: BIAYA PERJALANAN DI DALAM JEPANG SELAMA MENINGGALKAN RUMAH DAN KEGIATAN LAINNYA. | F192: MAGANG JEPANG TRAINING SKILL UP (NEW MEMBER) | G192: OPEX | J192: RUTIN | K192: ALL | L192: ALL | M192: ALL | N192: ORANG | O192: JPY | P192: 0 | Q192: 0 | R192: 0 | S192: 0 | T192: 0 | U192: 0 | V192: 0 | W192: 0 | X192: 0 | Y192: 0 | Z192: 0 | AA192: 0 | AB192: 0 | AC192: 0 | AD192: 0 | AE192: 0 | AF192: 0 | AG192: 0 | AH192: 0 | AI192: 0 | AJ192: 0 | AK192: 0 | AL192: 0 | AM192: 0 | AN192: 0 | AO192: 0 | AP192: 0 | AQ192: 0 | AR192: 0 | AS192: 0 | AT192: 1 | AU192: 0 | AV192: 0 | AW192: 1 | AX192: 0 | AY192: 0 | AZ192: =SUM(AN192:AY192) -> 2 | BA192: =AZ192/12 -> 0.16666667 | BC192: 0 | BD192: 0 | BE192: 0 | BF192: 0 | BG192: 0 | BH192: 0 | BI192: 0 | BJ192: 0 | BK192: 0 | BL192: 0 | BM192: 0 | BN192: 0 | BO192: =SUM(BC192:BN192) -> 0 | BP192: =BO192/12 -> 0 | BS192: D | BT192: GA | BU192: 0 | BV192: 0 | BW192: 0 | BX192: 0 | BY192: 0
A193: PGA-TRN | C193: MJTP7 | D193: MAGANG JEPANG TRAINING PREPARATION | E193: BIAYA LISTRIK, GAS DAN AIR | F193: MAGANG JEPANG TRAINING SKILL UP (NEW MEMBER) | G193: OPEX | J193: RUTIN | K193: ALL | L193: ALL | M193: ALL | N193: ORANG | O193: JPY | P193: 0 | Q193: 0 | R193: 0 | S193: 0 | T193: 0 | U193: 0 | V193: 0 | W193: 0 | X193: 0 | Y193: 0 | Z193: 0 | AA193: 0 | AB193: 0 | AC193: 0 | AD193: 0 | AE193: 0 | AF193: 0 | AG193: 0 | AH193: 0 | AI193: 0 | AJ193: 0 | AK193: 0 | AL193: 0 | AM193: 0 | AN193: 0 | AO193: 0 | AP193: 0 | AQ193: 0 | AR193: 0 | AS193: 0 | AT193: 1 | AU193: 1 | AV193: 1 | AW193: 1 | AX193: 1 | AY193: 1 | AZ193: =SUM(AN193:AY193) -> 6 | BA193: =AZ193/12 -> 0.5 | BC193: 0 | BD193: 0 | BE193: 0 | BF193: 0 | BG193: 0 | BH193: 0 | BI193: 0 | BJ193: 0 | BK193: 0 | BL193: 0 | BM193: 0 | BN193: 0 | BO193: =SUM(BC193:BN193) -> 0 | BP193: =BO193/12 -> 0 | BS193: D | BT193: GA | BU193: 0 | BV193: 0 | BW193: 0 | BX193: 0 | BY193: 0
A194: PGA-TRN | C194: MOTO003 | D194: REWARD | E194: REWARD MOTO KATEGORI AREA OFFICE TERBAIK | F194: Aktivitas bulan MOTO | G194: OPEX | J194: RUTIN | K194: ALL | L194: ALL | M194: ALL | N194: Team | O194: IDR | P194: 307500 | Q194: 307500 | R194: 307500 | S194: 307500 | T194: 307500 | U194: 307500 | V194: 307500 | W194: 307500 | X194: 307500 | Y194: 307500 | Z194: 307500 | AA194: 307500 | AB194: 19.46375 | AC194: 19.46375 | AD194: 19.46375 | AE194: 19.46375 | AF194: 19.46375 | AG194: 19.46375 | AH194: 19.46375 | AI194: 19.46375 | AJ194: 19.46375 | AK194: 19.46375 | AL194: 19.46375 | AM194: 19.46375 | AN194: 0 | AO194: 0 | AP194: 0 | AQ194: 0 | AR194: 0 | AS194: 0 | AT194: 0 | AU194: 0 | AV194: 0 | AW194: 0 | AX194: 2 | AY194: 0 | AZ194: =SUM(AN194:AY194) -> 2 | BA194: =AZ194/12 -> 0.16666667 | BC194: 0 | BD194: 0 | BE194: 0 | BF194: 0 | BG194: 0 | BH194: 0 | BI194: 0 | BJ194: 0 | BK194: 0 | BL194: 0 | BM194: 38.9275 | BN194: 0 | BO194: =SUM(BC194:BN194) -> 38.9275 | BP194: =BO194/12 -> 3.2439583 | BS194: D | BT194: GA | BU194: 0 | BV194: 0 | BW194: 0 | BX194: 0 | BY194: 0
A195: PGA-TRN | C195: QCC001 | D195: REWARD | E195: REWARD KEHADIRAN QCC | F195: Acara konvensi internal QCC | G195: OPEX | J195: RUTIN | K195: ALL | L195: ALL | M195: ALL | N195: ORANG | O195: IDR | P195: 10250 | Q195: 10250 | R195: 10250 | S195: 10250 | T195: 10250 | U195: 10250 | V195: 10250 | W195: 10250 | X195: 10250 | Y195: 10250 | Z195: 10250 | AA195: 10250 | AB195: 0.64879167 | AC195: 0.64879167 | AD195: 0.64879167 | AE195: 0.64879167 | AF195: 0.64879167 | AG195: 0.64879167 | AH195: 0.64879167 | AI195: 0.64879167 | AJ195: 0.64879167 | AK195: 0.64879167 | AL195: 0.64879167 | AM195: 0.64879167 | AN195: 0 | AO195: 0 | AP195: 2772 | AQ195: 0 | AR195: 0 | AS195: 0 | AT195: 0 | AU195: 0 | AV195: 2772 | AW195: 0 | AX195: 0 | AY195: 0 | AZ195: =SUM(AN195:AY195) -> 5544 | BA195: =AZ195/12 -> 462 | BC195: 0 | BD195: 0 | BE195: 1798.4505 | BF195: 0 | BG195: 0 | BH195: 0 | BI195: 0 | BJ195: 0 | BK195: 1798.4505 | BL195: 0 | BM195: 0 | BN195: 0 | BO195: =SUM(BC195:BN195) -> 3596.901 | BP195: =BO195/12 -> 299.74175 | BS195: D | BT195: GA | BU195: 0 | BV195: 0 | BW195: 0 | BX195: 0 | BY195: 0
A196: PGA-TRN | C196: SVR001 | D196: PERJALANAN DINAS | E196: SOVENIR AFILLIATE | F196: Training Renewal promotor OLS | G196: OPEX | J196: RUTIN | K196: ALL | L196: ALL | M196: ALL | N196: SET | O196: IDR | P196: 1000000 | Q196: 1000000 | R196: 1000000 | S196: 1000000 | T196: 1000000 | U196: 1000000 | V196: 1000000 | W196: 1000000 | X196: 1000000 | Y196: 1000000 | Z196: 1000000 | AA196: 1000000 | AB196: 63.296748 | AC196: 63.296748 | AD196: 63.296748 | AE196: 63.296748 | AF196: 63.296748 | AG196: 63.296748 | AH196: 63.296748 | AI196: 63.296748 | AJ196: 63.296748 | AK196: 63.296748 | AL196: 63.296748 | AM196: 63.296748 | AN196: 0 | AO196: 0 | AP196: 1 | AQ196: 0 | AR196: 0 | AS196: 0 | AT196: 0 | AU196: 0 | AV196: 0 | AW196: 0 | AX196: 0 | AY196: 0 | AZ196: =SUM(AN196:AY196) -> 1 | BA196: =AZ196/12 -> 0.083333333 | BC196: 0 | BD196: 0 | BE196: 63.296748 | BF196: 0 | BG196: 0 | BH196: 0 | BI196: 0 | BJ196: 0 | BK196: 0 | BL196: 0 | BM196: 0 | BN196: 0 | BO196: =SUM(BC196:BN196) -> 63.296748 | BP196: =BO196/12 -> 5.274729 | BS196: D | BT196: GA | BU196: 0 | BV196: 0 | BW196: 0 | BX196: 0 | BY196: 0
A197: PGA-TRN | C197: TMJ003 | D197: TRAINING MAGANG JEPANG | E197: TRAINING MAGANG JEPANG TRAINING BAHASA JEPANG | F197: Magang Jepang Operator | G197: OPEX | J197: RUTIN | K197: ALL | L197: ALL | M197: ALL | N197: ORANG | O197: IDR | P197: 2562500 | Q197: 2562500 | R197: 2562500 | S197: 2562500 | T197: 2562500 | U197: 2562500 | V197: 2562500 | W197: 2562500 | X197: 2562500 | Y197: 2562500 | Z197: 2562500 | AA197: 2562500 | AB197: 162.19792 | AC197: 162.19792 | AD197: 162.19792 | AE197: 162.19792 | AF197: 162.19792 | AG197: 162.19792 | AH197: 162.19792 | AI197: 162.19792 | AJ197: 162.19792 | AK197: 162.19792 | AL197: 162.19792 | AM197: 162.19792 | AN197: 0 | AO197: 0 | AP197: 0 | AQ197: 0 | AR197: 0 | AS197: 0 | AT197: 0 | AU197: 0 | AV197: 0 | AW197: 0 | AX197: 1 | AY197: 0 | AZ197: =SUM(AN197:AY197) -> 1 | BA197: =AZ197/12 -> 0.083333333 | BC197: 0 | BD197: 0 | BE197: 0 | BF197: 0 | BG197: 0 | BH197: 0 | BI197: 0 | BJ197: 0 | BK197: 0 | BL197: 0 | BM197: 162.19792 | BN197: 0 | BO197: =SUM(BC197:BN197) -> 162.19792 | BP197: =BO197/12 -> 13.516493 | BS197: D | BT197: GA | BU197: 0 | BV197: 0 | BW197: 0 | BX197: 0 | BY197: 0
A198: PGA-TRN | C198: TMJ022 | D198: TRAINING MAGANG JEPANG | E198: ASURANSI SEPEDA | F198: PD ke MKH,HIROSHIMA (Training Development) AFTER BOBBY | G198: OPEX | J198: RUTIN | K198: ALL | L198: ALL | M198: ALL | N198: ORANG | O198: JPY | P198: 0 | Q198: 0 | R198: 0 | S198: 0 | T198: 0 | U198: 0 | V198: 0 | W198: 0 | X198: 0 | Y198: 0 | Z198: 0 | AA198: 0 | AB198: 0 | AC198: 0 | AD198: 0 | AE198: 0 | AF198: 0 | AG198: 0 | AH198: 0 | AI198: 0 | AJ198: 0 | AK198: 0 | AL198: 0 | AM198: 0 | AN198: 0 | AO198: 0 | AP198: 0 | AQ198: 1 | AR198: 0 | AS198: 0 | AT198: 0 | AU198: 0 | AV198: 0 | AW198: 0 | AX198: 0 | AY198: 0 | AZ198: =SUM(AN198:AY198) -> 1 | BA198: =AZ198/12 -> 0.083333333 | BC198: 0 | BD198: 0 | BE198: 0 | BF198: 0 | BG198: 0 | BH198: 0 | BI198: 0 | BJ198: 0 | BK198: 0 | BL198: 0 | BM198: 0 | BN198: 0 | BO198: =SUM(BC198:BN198) -> 0 | BP198: =BO198/12 -> 0 | BS198: D | BT198: GA | BU198: 0 | BV198: 0 | BW198: 0 | BX198: 0 | BY198: 0
A199: PGA-TRN | C199: TO004 | D199: PERJALANAN DINAS | E199: TIKET PESAWAT MEETING/BENCHMARK GOL V EKONOMI (DALAM NEGERI) | F199: Konvensi QCC YIG | G199: OPEX | J199: RUTIN | K199: ALL | L199: ALL | M199: ALL | N199: ORANG | O199: IDR | P199: 2500000 | Q199: 2500000 | R199: 2500000 | S199: 2500000 | T199: 2500000 | U199: 2500000 | V199: 2500000 | W199: 2500000 | X199: 2500000 | Y199: 2500000 | Z199: 2500000 | AA199: 2500000 | AB199: 158.24187 | AC199: 158.24187 | AD199: 158.24187 | AE199: 158.24187 | AF199: 158.24187 | AG199: 158.24187 | AH199: 158.24187 | AI199: 158.24187 | AJ199: 158.24187 | AK199: 158.24187 | AL199: 158.24187 | AM199: 158.24187 | AN199: 0 | AO199: 0 | AP199: 0 | AQ199: 0 | AR199: 2 | AS199: 0 | AT199: 0 | AU199: 0 | AV199: 0 | AW199: 0 | AX199: 0 | AY199: 0 | AZ199: =SUM(AN199:AY199) -> 2 | BA199: =AZ199/12 -> 0.16666667 | BC199: 0 | BD199: 0 | BE199: 0 | BF199: 0 | BG199: 316.48374 | BH199: 0 | BI199: 0 | BJ199: 0 | BK199: 0 | BL199: 0 | BM199: 0 | BN199: 0 | BO199: =SUM(BC199:BN199) -> 316.48374 | BP199: =BO199/12 -> 26.373645 | BS199: D | BT199: GA | BU199: 0 | BV199: 0 | BW199: 0 | BX199: 0 | BY199: 0
A200: PGA-TRN | C200: TO124 | D200: PERJALANAN DINAS | E200: TIKET PESAWAT TRAINING LUAR NEGERI (JEPANG) GOL I-III | F200: PD ke MKH,HIROSHIMA (Training Development) AFTER BOBBY | G200: OPEX | J200: RUTIN | K200: ALL | L200: ALL | M200: ALL | N200: ORANG | O200: IDR | P200: 25000000 | Q200: 25000000 | R200: 25000000 | S200: 25000000 | T200: 25000000 | U200: 25000000 | V200: 25000000 | W200: 25000000 | X200: 25000000 | Y200: 25000000 | Z200: 25000000 | AA200: 25000000 | AB200: 1582.4187 | AC200: 1582.4187 | AD200: 1582.4187 | AE200: 1582.4187 | AF200: 1582.4187 | AG200: 1582.4187 | AH200: 1582.4187 | AI200: 1582.4187 | AJ200: 1582.4187 | AK200: 1582.4187 | AL200: 1582.4187 | AM200: 1582.4187 | AN200: 0 | AO200: 1 | AP200: 0 | AQ200: 0 | AR200: 0 | AS200: 0 | AT200: 0 | AU200: 0 | AV200: 0 | AW200: 0 | AX200: 0 | AY200: 0 | AZ200: =SUM(AN200:AY200) -> 1 | BA200: =AZ200/12 -> 0.083333333 | BC200: 0 | BD200: 1582.4187 | BE200: 0 | BF200: 0 | BG200: 0 | BH200: 0 | BI200: 0 | BJ200: 0 | BK200: 0 | BL200: 0 | BM200: 0 | BN200: 0 | BO200: =SUM(BC200:BN200) -> 1582.4187 | BP200: =BO200/12 -> 131.86822 | BS200: D | BT200: GA | BU200: 0 | BV200: 0 | BW200: 0 | BX200: 0 | BY200: 0
A201: PGA-TRN | C201: TRANS004 | D201: LOCAL TRANSPORT | E201: PERJALANAN DINAS LUAR NEGERI(ASIA KECUALI JEPANG)GOL IV | F201: Training Renewal promotor OLS | G201: OPEX | J201: RUTIN | K201: ALL | L201: ALL | M201: ALL | N201: HARI | O201: USD | P201: 42 | Q201: 42 | R201: 42 | S201: 42 | T201: 42 | U201: 42 | V201: 42 | W201: 42 | X201: 42 | Y201: 42 | Z201: 42 | AA201: 42 | AB201: 42 | AC201: 42 | AD201: 42 | AE201: 42 | AF201: 42 | AG201: 42 | AH201: 42 | AI201: 42 | AJ201: 42 | AK201: 42 | AL201: 42 | AM201: 42 | AN201: 0 | AO201: 0 | AP201: 14 | AQ201: 0 | AR201: 0 | AS201: 0 | AT201: 0 | AU201: 0 | AV201: 0 | AW201: 0 | AX201: 0 | AY201: 0 | AZ201: =SUM(AN201:AY201) -> 14 | BA201: =AZ201/12 -> 1.1666667 | BC201: 0 | BD201: 0 | BE201: 588 | BF201: 0 | BG201: 0 | BH201: 0 | BI201: 0 | BJ201: 0 | BK201: 0 | BL201: 0 | BM201: 0 | BN201: 0 | BO201: =SUM(BC201:BN201) -> 588 | BP201: =BO201/12 -> 49 | BS201: D | BT201: GA | BU201: 0 | BV201: 0 | BW201: 0 | BX201: 0 | BY201: 0
... A280: PGA-TRN | C280: ELC807 | D280: ALAT KEJUT | E280: ALAT KEJUT LISTRIK | F280: Untuk membuat taikan safety Dojo | G280: OPEX | J280: IMPROVEMENT | K280: ALL | L280: ALL | M280: ALL | N280: PCS | O280: IDR | P280: 275000 | Q280: 275000 | R280: 275000 | S280: 275000 | T280: 275000 | U280: 275000 | V280: 275000 | W280: 275000 | X280: 275000 | Y280: 275000 | Z280: 275000 | AA280: 275000 | AB280: 17.406606 | AC280: 17.406606 | AD280: 17.406606 | AE280: 17.406606 | AF280: 17.406606 | AG280: 17.406606 | AH280: 17.406606 | AI280: 17.406606 | AJ280: 17.406606 | AK280: 17.406606 | AL280: 17.406606 | AM280: 17.406606 | AN280: 0 | AO280: 0 | AP280: 3 | AQ280: 0 | AR280: 0 | AS280: 0 | AT280: 0 | AU280: 0 | AV280: 0 | AW280: 0 | AX280: 0 | AY280: 0 | AZ280: =SUM(AN280:AY280) -> 3 | BA280: =AZ280/12 -> 0.25 | BC280: 0 | BD280: 0 | BE280: 52.219817 | BF280: 0 | BG280: 0 | BH280: 0 | BI280: 0 | BJ280: 0 | BK280: 0 | BL280: 0 | BM280: 0 | BN280: 0 | BO280: =SUM(BC280:BN280) -> 52.219817 | BP280: =BO280/12 -> 4.3516514 | BS280: C | BT280: GA | BU280: 0 | BV280: 0 | BW280: 0 | BX280: 0 | BY280: 0

Sheet SUMMARY
E7: STP QTY | F7: STP QTY | G7: STP QTY | H7: STP QTY | I7: STP QTY | J7: STP QTY | K7: STP QTY | L7: STP QTY | M7: STP QTY | N7: STP QTY | O7: STP QTY | P7: STP QTY | Q7: STP AMT | R7: STP AMT | S7: STP AMT | T7: STP AMT | U7: STP AMT | V7: STP AMT | W7: STP AMT | X7: STP AMT | Y7: STP AMT | Z7: STP AMT | AA7: STP AMT | AB7: STP AMT | AC7: TERM 85 | AF7: TERM 84
A8: CATEGORY | B8: ACC NO | C8: ACC DESCRIPTION | D8: PART NAME | E8: Jul-25 | F8: Aug-25 | G8: Sep-25 | H8: Oct-25 | I8: Nov-25 | J8: Dec-25 | K8: Jan-26 | L8: Feb-26 | M8: Mar-26 | N8: Apr-26 | O8: May-26 | P8: Jun-26 | Q8: Jul-25 | R8: Aug-25 | S8: Sep-25 | T8: Oct-25 | U8: Nov-25 | V8: Dec-25 | W8: Jan-26 | X8: Feb-26 | Y8: Mar-26 | Z8: Apr-26 | AA8: May-26 | AB8: Jun-26 | AC8: TOTAL QTY | AD8: TOTAL AMT | AF8: TOTAL QTY | AG8: TOTAL AMT | AH8: PERCENTAGE QTY | AI8: PERCENTAGE AMT | AJ8: REMARKS
A9: RUTIN | D9: MAGANG JEPANG MANAGEMENT | E9: =SUMIFS('PLAN BUDGET SAMI-TF'!AN12:AN99999,'PLAN BUDGET SAMI-TF'!D12:D99999,SUMMARY!D9,'PLAN BUDGET SAMI-TF'!J12:J99999,SUMMARY!A9&"*") -> 0 | F9: =SUMIFS('PLAN BUDGET SAMI-TF'!AO12:AO99999,'PLAN BUDGET SAMI-TF'!D12:D99999,SUMMARY!D9,'PLAN BUDGET SAMI-TF'!J12:J99999,SUMMARY!A9&"*") -> 0 | G9: =SUMIFS('PLAN BUDGET SAMI-TF'!AP12:AP99999,'PLAN BUDGET SAMI-TF'!D12:D99999,SUMMARY!D9,'PLAN BUDGET SAMI-TF'!J12:J99999,SUMMARY!A9&"*") -> 0 | H9: =SUMIFS('PLAN BUDGET SAMI-TF'!AQ12:AQ99999,'PLAN BUDGET SAMI-TF'!D12:D99999,SUMMARY!D9,'PLAN BUDGET SAMI-TF'!J12:J99999,SUMMARY!A9&"*") -> 0 | I9: =SUMIFS('PLAN BUDGET SAMI-TF'!AR12:AR99999,'PLAN BUDGET SAMI-TF'!D12:D99999,SUMMARY!D9,'PLAN BUDGET SAMI-TF'!J12:J99999,SUMMARY!A9&"*") -> 0 | J9: =SUMIFS('PLAN BUDGET SAMI-TF'!AS12:AS99999,'PLAN BUDGET SAMI-TF'!D12:D99999,SUMMARY!D9,'PLAN BUDGET SAMI-TF'!J12:J99999,SUMMARY!A9&"*") -> 0 | K9: =SUMIFS('PLAN BUDGET SAMI-TF'!AT12:AT99999,'PLAN BUDGET SAMI-TF'!D12:D99999,SUMMARY!D9,'PLAN BUDGET SAMI-TF'!J12:J99999,SUMMARY!A9&"*") -> 4 | L9: =SUMIFS('PLAN BUDGET SAMI-TF'!AU12:AU99999,'PLAN BUDGET SAMI-TF'!D12:D99999,SUMMARY!D9,'PLAN BUDGET SAMI-TF'!J12:J99999,SUMMARY!A9&"*") -> 0 | M9: =SUMIFS('PLAN BUDGET SAMI-TF'!AV12:AV99999,'PLAN BUDGET SAMI-TF'!D12:D99999,SUMMARY!D9,'PLAN BUDGET SAMI-TF'!J12:J99999,SUMMARY!A9&"*") -> 0 | N9: =SUMIFS('PLAN BUDGET SAMI-TF'!AW12:AW99999,'PLAN BUDGET SAMI-TF'!D12:D99999,SUMMARY!D9,'PLAN BUDGET SAMI-TF'!J12:J99999,SUMMARY!A9&"*") -> 0 | O9: =SUMIFS('PLAN BUDGET SAMI-TF'!AX12:AX99999,'PLAN BUDGET SAMI-TF'!D12:D99999,SUMMARY!D9,'PLAN BUDGET SAMI-TF'!J12:J99999,SUMMARY!A9&"*") -> 0 | P9: =SUMIFS('PLAN BUDGET SAMI-TF'!AY12:AY99999,'PLAN BUDGET SAMI-TF'!D12:D99999,SUMMARY!D9,'PLAN BUDGET SAMI-TF'!J12:J99999,SUMMARY!A9&"*") -> 0 | Q9: =SUMIFS('PLAN BUDGET SAMI-TF'!BC12:BC99999,'PLAN BUDGET SAMI-TF'!D12:D99999,SUMMARY!D9,'PLAN BUDGET SAMI-TF'!J12:J99999,SUMMARY!A9&"*") -> 0 | R9: =SUMIFS('PLAN BUDGET SAMI-TF'!BD12:BD99999,'PLAN BUDGET SAMI-TF'!D12:D99999,SUMMARY!D9,'PLAN BUDGET SAMI-TF'!J12:J99999,SUMMARY!A9&"*") -> 0 | S9: =SUMIFS('PLAN BUDGET SAMI-TF'!BE12:BE99999,'PLAN BUDGET SAMI-TF'!D12:D99999,SUMMARY!D9,'PLAN BUDGET SAMI-TF'!J12:J99999,SUMMARY!A9&"*") -> 0 | T9: =SUMIFS('PLAN BUDGET SAMI-TF'!BF12:BF99999,'PLAN BUDGET SAMI-TF'!D12:D99999,SUMMARY!D9,'PLAN BUDGET SAMI-TF'!J12:J99999,SUMMARY!A9&"*") -> 0 | U9: =SUMIFS('PLAN BUDGET SAMI-TF'!BG12:BG99999,'PLAN BUDGET SAMI-TF'!D12:D99999,SUMMARY!D9,'PLAN BUDGET SAMI-TF'!J12:J99999,SUMMARY!A9&"*") -> 0 | V9: =SUMIFS('PLAN BUDGET SAMI-TF'!BH12:BH99999,'PLAN BUDGET SAMI-TF'!D12:D99999,SUMMARY!D9,'PLAN BUDGET SAMI-TF'!J12:J99999,SUMMARY!A9&"*") -> 0 | W9: =SUMIFS('PLAN BUDGET SAMI-TF'!BI12:BI99999,'PLAN BUDGET SAMI-TF'!D12:D99999,SUMMARY!D9,'PLAN BUDGET SAMI-TF'!J12:J99999,SUMMARY!A9&"*") -> 0 | X9: =SUMIFS('PLAN BUDGET SAMI-TF'!BJ12:BJ99999,'PLAN BUDGET SAMI-TF'!D12:D99999,SUMMARY!D9,'PLAN BUDGET SAMI-TF'!J12:J99999,SUMMARY!A9&"*") -> 0 | Y9: =SUMIFS('PLAN BUDGET SAMI-TF'!BK12:BK99999,'PLAN BUDGET SAMI-TF'!D12:D99999,SUMMARY!D9,'PLAN BUDGET SAMI-TF'!J12:J99999,SUMMARY!A9&"*") -> 0 | Z9: =SUMIFS('PLAN BUDGET SAMI-TF'!BL12:BL99999,'PLAN BUDGET SAMI-TF'!D12:D99999,SUMMARY!D9,'PLAN BUDGET SAMI-TF'!J12:J99999,SUMMARY!A9&"*") -> 0 | AA9: =SUMIFS('PLAN BUDGET SAMI-TF'!BM12:BM99999,'PLAN BUDGET SAMI-TF'!D12:D99999,SUMMARY!D9,'PLAN BUDGET SAMI-TF'!J12:J99999,SUMMARY!A9&"*") -> 0 | AB9: =SUMIFS('PLAN BUDGET SAMI-TF'!BN12:BN99999,'PLAN BUDGET SAMI-TF'!D12:D99999,SUMMARY!D9,'PLAN BUDGET SAMI-TF'!J12:J99999,SUMMARY!A9&"*") -> 0 | AC9: =SUM(E9:P9) -> 4 | AD9: =SUM(Q9:AB9) -> 0 | AF9: 25 | AG9: 11996.788 | AH9: =IFERROR((AC9-AF9)/AF9,1) -> -0.84 | AI9: =IFERROR((AD9-AG9)/AG9,1) -> -1 | AJ9: Budget magang Jepang managemen ganti part name di th 85
A10: RUTIN | D10: BALLPOINT | E10: =SUMIFS('PLAN BUDGET SAMI-TF'!AN12:AN99999,'PLAN BUDGET SAMI-TF'!D12:D99999,SUMMARY!D10,'PLAN BUDGET SAMI-TF'!J12:J99999,SUMMARY!A10&"*") -> 1 | F10: =SUMIFS('PLAN BUDGET SAMI-TF'!AO12:AO99999,'PLAN BUDGET SAMI-TF'!D12:D99999,SUMMARY!D10,'PLAN BUDGET SAMI-TF'!J12:J99999,SUMMARY!A10&"*") -> 12 | G10: =SUMIFS('PLAN BUDGET SAMI-TF'!AP12:AP99999,'PLAN BUDGET SAMI-TF'!D12:D99999,SUMMARY!D10,'PLAN BUDGET SAMI-TF'!J12:J99999,SUMMARY!A10&"*") -> 0 | H10: =SUMIFS('PLAN BUDGET SAMI-TF'!AQ12:AQ99999,'PLAN BUDGET SAMI-TF'!D12:D99999,SUMMARY!D10,'PLAN BUDGET SAMI-TF'!J12:J99999,SUMMARY!A10&"*") -> 1 | I10: =SUMIFS('PLAN BUDGET SAMI-TF'!AR12:AR99999,'PLAN BUDGET SAMI-TF'!D12:D99999,SUMMARY!D10,'PLAN BUDGET SAMI-TF'!J12:J99999,SUMMARY!A10&"*") -> 0 | J10: =SUMIFS('PLAN BUDGET SAMI-TF'!AS12:AS99999,'PLAN BUDGET SAMI-TF'!D12:D99999,SUMMARY!D10,'PLAN BUDGET SAMI-TF'!J12:J99999,SUMMARY!A10&"*") -> 0 | K10: =SUMIFS('PLAN BUDGET SAMI-TF'!AT12:AT99999,'PLAN BUDGET SAMI-TF'!D12:D99999,SUMMARY!D10,'PLAN BUDGET SAMI-TF'!J12:J99999,SUMMARY!A10&"*") -> 1 | L10: =SUMIFS('PLAN BUDGET SAMI-TF'!AU12:AU99999,'PLAN BUDGET SAMI-TF'!D12:D99999,SUMMARY!D10,'PLAN BUDGET SAMI-TF'!J12:J99999,SUMMARY!A10&"*") -> 0 | M10: =SUMIFS('PLAN BUDGET SAMI-TF'!AV12:AV99999,'PLAN BUDGET SAMI-TF'!D12:D99999,SUMMARY!D10,'PLAN BUDGET SAMI-TF'!J12:J99999,SUMMARY!A10&"*") -> 0 | N10: =SUMIFS('PLAN BUDGET SAMI-TF'!AW12:AW99999,'PLAN BUDGET SAMI-TF'!D12:D99999,SUMMARY!D10,'PLAN BUDGET SAMI-TF'!J12:J99999,SUMMARY!A10&"*") -> 1 | O10: =SUMIFS('PLAN BUDGET SAMI-TF'!AX12:AX99999,'PLAN BUDGET SAMI-TF'!D12:D99999,SUMMARY!D10,'PLAN BUDGET SAMI-TF'!J12:J99999,SUMMARY!A10&"*") -> 0 | P10: =SUMIFS('PLAN BUDGET SAMI-TF'!AY12:AY99999,'PLAN BUDGET SAMI-TF'!D12:D99999,SUMMARY!D10,'PLAN BUDGET SAMI-TF'!J12:J99999,SUMMARY!A10&"*") -> 0 | Q10: =SUMIFS('PLAN BUDGET SAMI-TF'!BC12:BC99999,'PLAN BUDGET SAMI-TF'!D12:D99999,SUMMARY!D10,'PLAN BUDGET SAMI-TF'!J12:J99999,SUMMARY!A10&"*") -> 0 | R10: =SUMIFS('PLAN BUDGET SAMI-TF'!BD12:BD99999,'PLAN BUDGET SAMI-TF'!D12:D99999,SUMMARY!D10,'PLAN BUDGET SAMI-TF'!J12:J99999,SUMMARY!A10&"*") -> 1.3687289 | S10: =SUMIFS('PLAN BUDGET SAMI-TF'!BE12:BE99999,'PLAN BUDGET SAMI-TF'!D12:D99999,SUMMARY!D10,'PLAN BUDGET SAMI-TF'!J12:J99999,SUMMARY!A10&"*") -> 0 | T10: =SUMIFS('PLAN BUDGET SAMI-TF'!BF12:BF99999,'PLAN BUDGET SAMI-TF'!D12:D99999,SUMMARY!D10,'PLAN BUDGET SAMI-TF'!J12:J99999,SUMMARY!A10&"*") -> 0 | U10: =SUMIFS('PLAN BUDGET SAMI-TF'!BG12:BG99999,'PLAN BUDGET SAMI-TF'!D12:D99999,SUMMARY!D10,'PLAN BUDGET SAMI-TF'!J12:J99999,SUMMARY!A10&"*") -> 0 | V10: =SUMIFS('PLAN BUDGET SAMI-TF'!BH12:BH99999,'PLAN BUDGET SAMI-TF'!D12:D99999,SUMMARY!D10,'PLAN BUDGET SAMI-TF'!J12:J99999,SUMMARY!A10&"*") -> 0 | W10: =SUMIFS('PLAN BUDGET SAMI-TF'!BI12:BI99999,'PLAN BUDGET SAMI-TF'!D12:D99999,SUMMARY!D10,'PLAN BUDGET SAMI-TF'!J12:J99999,SUMMARY!A10&"*") -> 0 | X10: =SUMIFS('PLAN BUDGET SAMI-TF'!BJ12:BJ99999,'PLAN BUDGET SAMI-TF'!D12:D99999,SUMMARY!D10,'PLAN BUDGET SAMI-TF'!J12:J99999,SUMMARY!A10&"*") -> 0 | Y10: =SUMIFS('PLAN BUDGET SAMI-TF'!BK12:BK99999,'PLAN BUDGET SAMI-TF'!D12:D99999,SUMMARY!D10,'PLAN BUDGET SAMI-TF'!J12:J99999,SUMMARY!A10&"*") -> 0 | Z10: =SUMIFS('PLAN BUDGET SAMI-TF'!BL12:BL99999,'PLAN BUDGET SAMI-TF'!D12:D99999,SUMMARY!D10,'PLAN BUDGET SAMI-TF'!J12:J99999,SUMMARY!A10&"*") -> 0 | AA10: =SUMIFS('PLAN BUDGET SAMI-TF'!BM12:BM99999,'PLAN BUDGET SAMI-TF'!D12:D99999,SUMMARY!D10,'PLAN BUDGET SAMI-TF'!J12:J99999,SUMMARY!A10&"*") -> 0 | AB10: =SUMIFS('PLAN BUDGET SAMI-TF'!BN12:BN99999,'PLAN BUDGET SAMI-TF'!D12:D99999,SUMMARY!D10,'PLAN BUDGET SAMI-TF'!J12:J99999,SUMMARY!A10&"*") -> 0 | AC10: =SUM(E10:P10) -> 16 | AD10: =SUM(Q10:AB10) -> 1.3687289 | AF10: 4 | AG10: 0.35091717 | AH10: =IFERROR((AC10-AF10)/AF10,1) -> 3 | AI10: =IFERROR((AD10-AG10)/AG10,1) -> 2.9004329 | AJ10: Di th 85 penggantian ballpoint yang rusak
A11: RUTIN | D11: BENCHMARK QCC | E11: =SUMIFS('PLAN BUDGET SAMI-TF'!AN12:AN99999,'PLAN BUDGET SAMI-TF'!D12:D99999,SUMMARY!D11,'PLAN BUDGET SAMI-TF'!J12:J99999,SUMMARY!A11&"*") -> 0 | F11: =SUMIFS('PLAN BUDGET SAMI-TF'!AO12:AO99999,'PLAN BUDGET SAMI-TF'!D12:D99999,SUMMARY!D11,'PLAN BUDGET SAMI-TF'!J12:J99999,SUMMARY!A11&"*") -> 0 | G11: =SUMIFS('PLAN BUDGET SAMI-TF'!AP12:AP99999,'PLAN BUDGET SAMI-TF'!D12:D99999,SUMMARY!D11,'PLAN BUDGET SAMI-TF'!J12:J99999,SUMMARY!A11&"*") -> 0 | H11: =SUMIFS('PLAN BUDGET SAMI-TF'!AQ12:AQ99999,'PLAN BUDGET SAMI-TF'!D12:D99999,SUMMARY!D11,'PLAN BUDGET SAMI-TF'!J12:J99999,SUMMARY!A11&"*") -> 0 | I11: =SUMIFS('PLAN BUDGET SAMI-TF'!AR12:AR99999,'PLAN BUDGET SAMI-TF'!D12:D99999,SUMMARY!D11,'PLAN BUDGET SAMI-TF'!J12:J99999,SUMMARY!A11&"*") -> 4 | J11: =SUMIFS('PLAN BUDGET SAMI-TF'!AS12:AS99999,'PLAN BUDGET SAMI-TF'!D12:D99999,SUMMARY!D11,'PLAN BUDGET SAMI-TF'!J12:J99999,SUMMARY!A11&"*") -> 0 | K11: =SUMIFS('PLAN BUDGET SAMI-TF'!AT12:AT99999,'PLAN BUDGET SAMI-TF'!D12:D99999,SUMMARY!D11,'PLAN BUDGET SAMI-TF'!J12:J99999,SUMMARY!A11&"*") -> 0 | L11: =SUMIFS('PLAN BUDGET SAMI-TF'!AU12:AU99999,'PLAN BUDGET SAMI-TF'!D12:D99999,SUMMARY!D11,'PLAN BUDGET SAMI-TF'!J12:J99999,SUMMARY!A11&"*") -> 0 | M11: =SUMIFS('PLAN BUDGET SAMI-TF'!AV12:AV99999,'PLAN BUDGET SAMI-TF'!D12:D99999,SUMMARY!D11,'PLAN BUDGET SAMI-TF'!J12:J99999,SUMMARY!A11&"*") -> 0 | N11: =SUMIFS('PLAN BUDGET SAMI-TF'!AW12:AW99999,'PLAN BUDGET SAMI-TF'!D12:D99999,SUMMARY!D11,'PLAN BUDGET SAMI-TF'!J12:J99999,SUMMARY!A11&"*") -> 0 | O11: =SUMIFS('PLAN BUDGET SAMI-TF'!AX12:AX99999,'PLAN BUDGET SAMI-TF'!D12:D99999,SUMMARY!D11,'PLAN BUDGET SAMI-TF'!J12:J99999,SUMMARY!A11&"*") -> 0 | P11: =SUMIFS('PLAN BUDGET SAMI-TF'!AY12:AY99999,'PLAN BUDGET SAMI-TF'!D12:D99999,SUMMARY!D11,'PLAN BUDGET SAMI-TF'!J12:J99999,SUMMARY!A11&"*") -> 0 | Q11: =SUMIFS('PLAN BUDGET SAMI-TF'!BC12:BC99999,'PLAN BUDGET SAMI-TF'!D12:D99999,SUMMARY!D11,'PLAN BUDGET SAMI-TF'!J12:J99999,SUMMARY!A11&"*") -> 0 | R11: =SUMIFS('PLAN BUDGET SAMI-TF'!BD12:BD99999,'PLAN BUDGET SAMI-TF'!D12:D99999,SUMMARY!D11,'PLAN BUDGET SAMI-TF'!J12:J99999,SUMMARY!A11&"*") -> 0 | S11: =SUMIFS('PLAN BUDGET SAMI-TF'!BE12:BE99999,'PLAN BUDGET SAMI-TF'!D12:D99999,SUMMARY!D11,'PLAN BUDGET SAMI-TF'!J12:J99999,SUMMARY!A11&"*") -> 0 | T11: =SUMIFS('PLAN BUDGET SAMI-TF'!BF12:BF99999,'PLAN BUDGET SAMI-TF'!D12:D99999,SUMMARY!D11,'PLAN BUDGET SAMI-TF'!J12:J99999,SUMMARY!A11&"*") -> 0 | U11: =SUMIFS('PLAN BUDGET SAMI-TF'!BG12:BG99999,'PLAN BUDGET SAMI-TF'!D12:D99999,SUMMARY!D11,'PLAN BUDGET SAMI-TF'!J12:J99999,SUMMARY!A11&"*") -> 126.5935 | V11: =SUMIFS('PLAN BUDGET SAMI-TF'!BH12:BH99999,'PLAN BUDGET SAMI-TF'!D12:D99999,SUMMARY!D11,'PLAN BUDGET SAMI-TF'!J12:J99999,SUMMARY!A11&"*") -> 0 | W11: =SUMIFS('PLAN BUDGET SAMI-TF'!BI12:BI99999,'PLAN BUDGET SAMI-TF'!D12:D99999,SUMMARY!D11,'PLAN BUDGET SAMI-TF'!J12:J99999,SUMMARY!A11&"*") -> 0 | X11: =SUMIFS('PLAN BUDGET SAMI-TF'!BJ12:BJ99999,'PLAN BUDGET SAMI-TF'!D12:D99999,SUMMARY!D11,'PLAN BUDGET SAMI-TF'!J12:J99999,SUMMARY!A11&"*") -> 0 | Y11: =SUMIFS('PLAN BUDGET SAMI-TF'!BK12:BK99999,'PLAN BUDGET SAMI-TF'!D12:D99999,SUMMARY!D11,'PLAN BUDGET SAMI-TF'!J12:J99999,SUMMARY!A11&"*") -> 0 | Z11: =SUMIFS('PLAN BUDGET SAMI-TF'!BL12:BL99999,'PLAN BUDGET SAMI-TF'!D12:D99999,SUMMARY!D11,'PLAN BUDGET SAMI-TF'!J12:J99999,SUMMARY!A11&"*") -> 0 | AA11: =SUMIFS('PLAN BUDGET SAMI-TF'!BM12:BM99999,'PLAN BUDGET SAMI-TF'!D12:D99999,SUMMARY!D11,'PLAN BUDGET SAMI-TF'!J12:J99999,SUMMARY!A11&"*") -> 0 | AB11: =SUMIFS('PLAN BUDGET SAMI-TF'!BN12:BN99999,'PLAN BUDGET SAMI-TF'!D12:D99999,SUMMARY!D11,'PLAN BUDGET SAMI-TF'!J12:J99999,SUMMARY!A11&"*") -> 0 | AC11: =SUM(E11:P11) -> 4 | AD11: =SUM(Q11:AB11) -> 126.5935 | AF11: 0 | AG11: 0 | AH11: =IFERROR((AC11-AF11)/AF11,1) -> 1 | AI11: =IFERROR((AD11-AG11)/AG11,1) -> 1 | AJ11: Ada perubahan part name di th 85
A12: RUTIN | D12: ACRYLIC | E12: =SUMIFS('PLAN BUDGET SAMI-TF'!AN12:AN99999,'PLAN BUDGET SAMI-TF'!D12:D99999,SUMMARY!D12,'PLAN BUDGET SAMI-TF'!J12:J99999,SUMMARY!A12&"*") -> 0 | F12: =SUMIFS('PLAN BUDGET SAMI-TF'!AO12:AO99999,'PLAN BUDGET SAMI-TF'!D12:D99999,SUMMARY!D12,'PLAN BUDGET SAMI-TF'!J12:J99999,SUMMARY!A12&"*") -> 0 | G12: =SUMIFS('PLAN BUDGET SAMI-TF'!AP12:AP99999,'PLAN BUDGET SAMI-TF'!D12:D99999,SUMMARY!D12,'PLAN BUDGET SAMI-TF'!J12:J99999,SUMMARY!A12&"*") -> 0 | H12: =SUMIFS('PLAN BUDGET SAMI-TF'!AQ12:AQ99999,'PLAN BUDGET SAMI-TF'!D12:D99999,SUMMARY!D12,'PLAN BUDGET SAMI-TF'!J12:J99999,SUMMARY!A12&"*") -> 1 | I12: =SUMIFS('PLAN BUDGET SAMI-TF'!AR12:AR99999,'PLAN BUDGET SAMI-TF'!D12:D99999,SUMMARY!D12,'PLAN BUDGET SAMI-TF'!J12:J99999,SUMMARY!A12&"*") -> 0 | J12: =SUMIFS('PLAN BUDGET SAMI-TF'!AS12:AS99999,'PLAN BUDGET SAMI-TF'!D12:D99999,SUMMARY!D12,'PLAN BUDGET SAMI-TF'!J12:J99999,SUMMARY!A12&"*") -> 0 | K12: =SUMIFS('PLAN BUDGET SAMI-TF'!AT12:AT99999,'PLAN BUDGET SAMI-TF'!D12:D99999,SUMMARY!D12,'PLAN BUDGET SAMI-TF'!J12:J99999,SUMMARY!A12&"*") -> 0 | L12: =SUMIFS('PLAN BUDGET SAMI-TF'!AU12:AU99999,'PLAN BUDGET SAMI-TF'!D12:D99999,SUMMARY!D12,'PLAN BUDGET SAMI-TF'!J12:J99999,SUMMARY!A12&"*") -> 0 | M12: =SUMIFS('PLAN BUDGET SAMI-TF'!AV12:AV99999,'PLAN BUDGET SAMI-TF'!D12:D99999,SUMMARY!D12,'PLAN BUDGET SAMI-TF'!J12:J99999,SUMMARY!A12&"*") -> 1 | N12: =SUMIFS('PLAN BUDGET SAMI-TF'!AW12:AW99999,'PLAN BUDGET SAMI-TF'!D12:D99999,SUMMARY!D12,'PLAN BUDGET SAMI-TF'!J12:J99999,SUMMARY!A12&"*") -> 0 | O12: =SUMIFS('PLAN BUDGET SAMI-TF'!AX12:AX99999,'PLAN BUDGET SAMI-TF'!D12:D99999,SUMMARY!D12,'PLAN BUDGET SAMI-TF'!J12:J99999,SUMMARY!A12&"*") -> 0 | P12: =SUMIFS('PLAN BUDGET SAMI-TF'!AY12:AY99999,'PLAN BUDGET SAMI-TF'!D12:D99999,SUMMARY!D12,'PLAN BUDGET SAMI-TF'!J12:J99999,SUMMARY!A12&"*") -> 0 | Q12: =SUMIFS('PLAN BUDGET SAMI-TF'!BC12:BC99999,'PLAN BUDGET SAMI-TF'!D12:D99999,SUMMARY!D12,'PLAN BUDGET SAMI-TF'!J12:J99999,SUMMARY!A12&"*") -> 0 | R12: =SUMIFS('PLAN BUDGET SAMI-TF'!BD12:BD99999,'PLAN BUDGET SAMI-TF'!D12:D99999,SUMMARY!D12,'PLAN BUDGET SAMI-TF'!J12:J99999,SUMMARY!A12&"*") -> 0 | S12: =SUMIFS('PLAN BUDGET SAMI-TF'!BE12:BE99999,'PLAN BUDGET SAMI-TF'!D12:D99999,SUMMARY!D12,'PLAN BUDGET SAMI-TF'!J12:J99999,SUMMARY!A12&"*") -> 0 | T12: =SUMIFS('PLAN BUDGET SAMI-TF'!BF12:BF99999,'PLAN BUDGET SAMI-TF'!D12:D99999,SUMMARY!D12,'PLAN BUDGET SAMI-TF'!J12:J99999,SUMMARY!A12&"*") -> 71.367083 | U12: =SUMIFS('PLAN BUDGET SAMI-TF'!BG12:BG99999,'PLAN BUDGET SAMI-TF'!D12:D99999,SUMMARY!D12,'PLAN BUDGET SAMI-TF'!J12:J99999,SUMMARY!A12&"*") -> 0 | V12: =SUMIFS('PLAN BUDGET SAMI-TF'!BH12:BH99999,'PLAN BUDGET SAMI-TF'!D12:D99999,SUMMARY!D12,'PLAN BUDGET SAMI-TF'!J12:J99999,SUMMARY!A12&"*") -> 0 | W12: =SUMIFS('PLAN BUDGET SAMI-TF'!BI12:BI99999,'PLAN BUDGET SAMI-TF'!D12:D99999,SUMMARY!D12,'PLAN BUDGET SAMI-TF'!J12:J99999,SUMMARY!A12&"*") -> 0 | X12: =SUMIFS('PLAN BUDGET SAMI-TF'!BJ12:BJ99999,'PLAN BUDGET SAMI-TF'!D12:D99999,SUMMARY!D12,'PLAN BUDGET SAMI-TF'!J12:J99999,SUMMARY!A12&"*") -> 0 | Y12: =SUMIFS('PLAN BUDGET SAMI-TF'!BK12:BK99999,'PLAN BUDGET SAMI-TF'!D12:D99999,SUMMARY!D12,'PLAN BUDGET SAMI-TF'!J12:J99999,SUMMARY!A12&"*") -> 73.864931 | Z12: =SUMIFS('PLAN BUDGET SAMI-TF'!BL12:BL99999,'PLAN BUDGET SAMI-TF'!D12:D99999,SUMMARY!D12,'PLAN BUDGET SAMI-TF'!J12:J99999,SUMMARY!A12&"*") -> 0 | AA12: =SUMIFS('PLAN BUDGET SAMI-TF'!BM12:BM99999,'PLAN BUDGET SAMI-TF'!D12:D99999,SUMMARY!D12,'PLAN BUDGET SAMI-TF'!J12:J99999,SUMMARY!A12&"*") -> 0 | AB12: =SUMIFS('PLAN BUDGET SAMI-TF'!BN12:BN99999,'PLAN BUDGET SAMI-TF'!D12:D99999,SUMMARY!D12,'PLAN BUDGET SAMI-TF'!J12:J99999,SUMMARY!A12&"*") -> 0 | AC12: =SUM(E12:P12) -> 2 | AD12: =SUM(Q12:AB12) -> 145.23201 | AF12: 2 | AG12: 141.48089 | AH12: =IFERROR((AC12-AF12)/AF12,1) -> 0 | AI12: =IFERROR((AD12-AG12)/AG12,1) -> 0.026513287 | AJ12: Ada kenaikan harga
A13: RUTIN | D13: BUKU | E13: =SUMIFS('PLAN BUDGET SAMI-TF'!AN12:AN99999,'PLAN BUDGET SAMI-TF'!D12:D99999,SUMMARY!D13,'PLAN BUDGET SAMI-TF'!J12:J99999,SUMMARY!A13&"*") -> 60 | F13: =SUMIFS('PLAN BUDGET SAMI-TF'!AO12:AO99999,'PLAN BUDGET SAMI-TF'!D12:D99999,SUMMARY!D13,'PLAN BUDGET SAMI-TF'!J12:J99999,SUMMARY!A13&"*") -> 158 | G13: =SUMIFS('PLAN BUDGET SAMI-TF'!AP12:AP99999,'PLAN BUDGET SAMI-TF'!D12:D99999,SUMMARY!D13,'PLAN BUDGET SAMI-TF'!J12:J99999,SUMMARY!A13&"*") -> 167 | H13: =SUMIFS('PLAN BUDGET SAMI-TF'!AQ12:AQ99999,'PLAN BUDGET SAMI-TF'!D12:D99999,SUMMARY!D13,'PLAN BUDGET SAMI-TF'!J12:J99999,SUMMARY!A13&"*") -> 190 | I13: =SUMIFS('PLAN BUDGET SAMI-TF'!AR12:AR99999,'PLAN BUDGET SAMI-TF'!D12:D99999,SUMMARY!D13,'PLAN BUDGET SAMI-TF'!J12:J99999,SUMMARY!A13&"*") -> 163 | J13: =SUMIFS('PLAN BUDGET SAMI-TF'!AS12:AS99999,'PLAN BUDGET SAMI-TF'!D12:D99999,SUMMARY!D13,'PLAN BUDGET SAMI-TF'!J12:J99999,SUMMARY!A13&"*") -> 126 | K13: =SUMIFS('PLAN BUDGET SAMI-TF'!AT12:AT99999,'PLAN BUDGET SAMI-TF'!D12:D99999,SUMMARY!D13,'PLAN BUDGET SAMI-TF'!J12:J99999,SUMMARY!A13&"*") -> 47 | L13: =SUMIFS('PLAN BUDGET SAMI-TF'!AU12:AU99999,'PLAN BUDGET SAMI-TF'!D12:D99999,SUMMARY!D13,'PLAN BUDGET SAMI-TF'!J12:J99999,SUMMARY!A13&"*") -> 28 | M13: =SUMIFS('PLAN BUDGET SAMI-TF'!AV12:AV99999,'PLAN BUDGET SAMI-TF'!D12:D99999,SUMMARY!D13,'PLAN BUDGET SAMI-TF'!J12:J99999,SUMMARY!A13&"*") -> 39 | N13: =SUMIFS('PLAN BUDGET SAMI-TF'!AW12:AW99999,'PLAN BUDGET SAMI-TF'!D12:D99999,SUMMARY!D13,'PLAN BUDGET SAMI-TF'!J12:J99999,SUMMARY!A13&"*") -> 141 | O13: =SUMIFS('PLAN BUDGET SAMI-TF'!AX12:AX99999,'PLAN BUDGET SAMI-TF'!D12:D99999,SUMMARY!D13,'PLAN BUDGET SAMI-TF'!J12:J99999,SUMMARY!A13&"*") -> 129 | P13: =SUMIFS('PLAN BUDGET SAMI-TF'!AY12:AY99999,'PLAN BUDGET SAMI-TF'!D12:D99999,SUMMARY!D13,'PLAN BUDGET SAMI-TF'!J12:J99999,SUMMARY!A13&"*") -> 25 | Q13: =SUMIFS('PLAN BUDGET SAMI-TF'!BC12:BC99999,'PLAN BUDGET SAMI-TF'!D12:D99999,SUMMARY!D13,'PLAN BUDGET SAMI-TF'!J12:J99999,SUMMARY!A13&"*") -> 6.8360488 | R13: =SUMIFS('PLAN BUDGET SAMI-TF'!BD12:BD99999,'PLAN BUDGET SAMI-TF'!D12:D99999,SUMMARY!D13,'PLAN BUDGET SAMI-TF'!J12:J99999,SUMMARY!A13&"*") -> 18.839961 | S13: =SUMIFS('PLAN BUDGET SAMI-TF'!BE12:BE99999,'PLAN BUDGET SAMI-TF'!D12:D99999,SUMMARY!D13,'PLAN BUDGET SAMI-TF'!J12:J99999,SUMMARY!A13&"*") -> 19.027002 | T13: =SUMIFS('PLAN BUDGET SAMI-TF'!BF12:BF99999,'PLAN BUDGET SAMI-TF'!D12:D99999,SUMMARY!D13,'PLAN BUDGET SAMI-TF'!J12:J99999,SUMMARY!A13&"*") -> 21.647488 | U13: =SUMIFS('PLAN BUDGET SAMI-TF'!BG12:BG99999,'PLAN BUDGET SAMI-TF'!D12:D99999,SUMMARY!D13,'PLAN BUDGET SAMI-TF'!J12:J99999,SUMMARY!A13&"*") -> 18.99048 | V13: =SUMIFS('PLAN BUDGET SAMI-TF'!BH12:BH99999,'PLAN BUDGET SAMI-TF'!D12:D99999,SUMMARY!D13,'PLAN BUDGET SAMI-TF'!J12:J99999,SUMMARY!A13&"*") -> 14.355702 | W13: =SUMIFS('PLAN BUDGET SAMI-TF'!BI12:BI99999,'PLAN BUDGET SAMI-TF'!D12:D99999,SUMMARY!D13,'PLAN BUDGET SAMI-TF'!J12:J99999,SUMMARY!A13&"*") -> 5.3549049 | X13: =SUMIFS('PLAN BUDGET SAMI-TF'!BJ12:BJ99999,'PLAN BUDGET SAMI-TF'!D12:D99999,SUMMARY!D13,'PLAN BUDGET SAMI-TF'!J12:J99999,SUMMARY!A13&"*") -> 4.0285215 | Y13: =SUMIFS('PLAN BUDGET SAMI-TF'!BK12:BK99999,'PLAN BUDGET SAMI-TF'!D12:D99999,SUMMARY!D13,'PLAN BUDGET SAMI-TF'!J12:J99999,SUMMARY!A13&"*") -> 4.4434317 | Z13: =SUMIFS('PLAN BUDGET SAMI-TF'!BL12:BL99999,'PLAN BUDGET SAMI-TF'!D12:D99999,SUMMARY!D13,'PLAN BUDGET SAMI-TF'!J12:J99999,SUMMARY!A13&"*") -> 16.483929 | AA13: =SUMIFS('PLAN BUDGET SAMI-TF'!BM12:BM99999,'PLAN BUDGET SAMI-TF'!D12:D99999,SUMMARY!D13,'PLAN BUDGET SAMI-TF'!J12:J99999,SUMMARY!A13&"*") -> 14.697505 | AB13: =SUMIFS('PLAN BUDGET SAMI-TF'!BN12:BN99999,'PLAN BUDGET SAMI-TF'!D12:D99999,SUMMARY!D13,'PLAN BUDGET SAMI-TF'!J12:J99999,SUMMARY!A13&"*") -> 2.8483537 | AC13: =SUM(E13:P13) -> 1273 | AD13: =SUM(Q13:AB13) -> 147.55333 | AF13: 1066 | AG13: 204.47267 | AH13: =IFERROR((AC13-AF13)/AF13,1) -> 0.19418386 | AI13: =IFERROR((AD13-AG13)/AG13,1) -> -0.27837141 | AJ13: Plan rekrut NEOP di th 85 mengalami kenaikan dibandingkan aktual di th 84
A14: RUTIN | D14: DOUBLE TAPE | E14: =SUMIFS('PLAN BUDGET SAMI-TF'!AN12:AN99999,'PLAN BUDGET SAMI-TF'!D12:D99999,SUMMARY!D14,'PLAN BUDGET SAMI-TF'!J12:J99999,SUMMARY!A14&"*") -> 3 | F14: =SUMIFS('PLAN BUDGET SAMI-TF'!AO12:AO99999,'PLAN BUDGET SAMI-TF'!D12:D99999,SUMMARY!D14,'PLAN BUDGET SAMI-TF'!J12:J99999,SUMMARY!A14&"*") -> 0 | G14: =SUMIFS('PLAN BUDGET SAMI-TF'!AP12:AP99999,'PLAN BUDGET SAMI-TF'!D12:D99999,SUMMARY!D14,'PLAN BUDGET SAMI-TF'!J12:J99999,SUMMARY!A14&"*") -> 4 | H14: =SUMIFS('PLAN BUDGET SAMI-TF'!AQ12:AQ99999,'PLAN BUDGET SAMI-TF'!D12:D99999,SUMMARY!D14,'PLAN BUDGET SAMI-TF'!J12:J99999,SUMMARY!A14&"*") -> 0 | I14: =SUMIFS('PLAN BUDGET SAMI-TF'!AR12:AR99999,'PLAN BUDGET SAMI-TF'!D12:D99999,SUMMARY!D14,'PLAN BUDGET SAMI-TF'!J12:J99999,SUMMARY!A14&"*") -> 3 | J14: =SUMIFS('PLAN BUDGET SAMI-TF'!AS12:AS99999,'PLAN BUDGET SAMI-TF'!D12:D99999,SUMMARY!D14,'PLAN BUDGET SAMI-TF'!J12:J99999,SUMMARY!A14&"*") -> 0 | K14: =SUMIFS('PLAN BUDGET SAMI-TF'!AT12:AT99999,'PLAN BUDGET SAMI-TF'!D12:D99999,SUMMARY!D14,'PLAN BUDGET SAMI-TF'!J12:J99999,SUMMARY!A14&"*") -> 4 | L14: =SUMIFS('PLAN BUDGET SAMI-TF'!AU12:AU99999,'PLAN BUDGET SAMI-TF'!D12:D99999,SUMMARY!D14,'PLAN BUDGET SAMI-TF'!J12:J99999,SUMMARY!A14&"*") -> 1 | M14: =SUMIFS('PLAN BUDGET SAMI-TF'!AV12:AV99999,'PLAN BUDGET SAMI-TF'!D12:D99999,SUMMARY!D14,'PLAN BUDGET SAMI-TF'!J12:J99999,SUMMARY!A14&"*") -> 3 | N14: =SUMIFS('PLAN BUDGET SAMI-TF'!AW12:AW99999,'PLAN BUDGET SAMI-TF'!D12:D99999,SUMMARY!D14,'PLAN BUDGET SAMI-TF'!J12:J99999,SUMMARY!A14&"*") -> 0 | O14: =SUMIFS('PLAN BUDGET SAMI-TF'!AX12:AX99999,'PLAN BUDGET SAMI-TF'!D12:D99999,SUMMARY!D14,'PLAN BUDGET SAMI-TF'!J12:J99999,SUMMARY!A14&"*") -> 4 | P14: =SUMIFS('PLAN BUDGET SAMI-TF'!AY12:AY99999,'PLAN BUDGET SAMI-TF'!D12:D99999,SUMMARY!D14,'PLAN BUDGET SAMI-TF'!J12:J99999,SUMMARY!A14&"*") -> 0 | Q14: =SUMIFS('PLAN BUDGET SAMI-TF'!BC12:BC99999,'PLAN BUDGET SAMI-TF'!D12:D99999,SUMMARY!D14,'PLAN BUDGET SAMI-TF'!J12:J99999,SUMMARY!A14&"*") -> 0.46181307 | R14: =SUMIFS('PLAN BUDGET SAMI-TF'!BD12:BD99999,'PLAN BUDGET SAMI-TF'!D12:D99999,SUMMARY!D14,'PLAN BUDGET SAMI-TF'!J12:J99999,SUMMARY!A14&"*") -> 0 | S14: =SUMIFS('PLAN BUDGET SAMI-TF'!BE12:BE99999,'PLAN BUDGET SAMI-TF'!D12:D99999,SUMMARY!D14,'PLAN BUDGET SAMI-TF'!J12:J99999,SUMMARY!A14&"*") -> 0.61575076 | T14: =SUMIFS('PLAN BUDGET SAMI-TF'!BF12:BF99999,'PLAN BUDGET SAMI-TF'!D12:D99999,SUMMARY!D14,'PLAN BUDGET SAMI-TF'!J12:J99999,SUMMARY!A14&"*") -> 0 | U14: =SUMIFS('PLAN BUDGET SAMI-TF'!BG12:BG99999,'PLAN BUDGET SAMI-TF'!D12:D99999,SUMMARY!D14,'PLAN BUDGET SAMI-TF'!J12:J99999,SUMMARY!A14&"*") -> 0.46181307 | V14: =SUMIFS('PLAN BUDGET SAMI-TF'!BH12:BH99999,'PLAN BUDGET SAMI-TF'!D12:D99999,SUMMARY!D14,'PLAN BUDGET SAMI-TF'!J12:J99999,SUMMARY!A14&"*") -> 0 | W14: =SUMIFS('PLAN BUDGET SAMI-TF'!BI12:BI99999,'PLAN BUDGET SAMI-TF'!D12:D99999,SUMMARY!D14,'PLAN BUDGET SAMI-TF'!J12:J99999,SUMMARY!A14&"*") -> 0.61575076 | X14: =SUMIFS('PLAN BUDGET SAMI-TF'!BJ12:BJ99999,'PLAN BUDGET SAMI-TF'!D12:D99999,SUMMARY!D14,'PLAN BUDGET SAMI-TF'!J12:J99999,SUMMARY!A14&"*") -> 1.3315104 | Y14: =SUMIFS('PLAN BUDGET SAMI-TF'!BK12:BK99999,'PLAN BUDGET SAMI-TF'!D12:D99999,SUMMARY!D14,'PLAN BUDGET SAMI-TF'!J12:J99999,SUMMARY!A14&"*") -> 0.46181307 | Z14: =SUMIFS('PLAN BUDGET SAMI-TF'!BL12:BL99999,'PLAN BUDGET SAMI-TF'!D12:D99999,SUMMARY!D14,'PLAN BUDGET SAMI-TF'!J12:J99999,SUMMARY!A14&"*") -> 0 | AA14: =SUMIFS('PLAN BUDGET SAMI-TF'!BM12:BM99999,'PLAN BUDGET SAMI-TF'!D12:D99999,SUMMARY!D14,'PLAN BUDGET SAMI-TF'!J12:J99999,SUMMARY!A14&"*") -> 0.61575076 | AB14: =SUMIFS('PLAN BUDGET SAMI-TF'!BN12:BN99999,'PLAN BUDGET SAMI-TF'!D12:D99999,SUMMARY!D14,'PLAN BUDGET SAMI-TF'!J12:J99999,SUMMARY!A14&"*") -> 0 | AC14: =SUM(E14:P14) -> 22 | AD14: =SUM(Q14:AB14) -> 4.5642019 | AF14: 22 | AG14: 4.3262061 | AH14: =IFERROR((AC14-AF14)/AF14,1) -> 0 | AI14: =IFERROR((AD14-AG14)/AG14,1) -> 0.055012583 | AJ14: Ada kenaikan harga
A15: RUTIN | D15: MCU | E15: =SUMIFS('PLAN BUDGET SAMI-TF'!AN12:AN99999,'PLAN BUDGET SAMI-TF'!D12:D99999,SUMMARY!D15,'PLAN BUDGET SAMI-TF'!J12:J99999,SUMMARY!A15&"*") -> 0 | F15: =SUMIFS('PLAN BUDGET SAMI-TF'!AO12:AO99999,'PLAN BUDGET SAMI-TF'!D12:D99999,SUMMARY!D15,'PLAN BUDGET SAMI-TF'!J12:J99999,SUMMARY!A15&"*") -> 1 | G15: =SUMIFS('PLAN BUDGET SAMI-TF'!AP12:AP99999,'PLAN BUDGET SAMI-TF'!D12:D99999,SUMMARY!D15,'PLAN BUDGET SAMI-TF'!J12:J99999,SUMMARY!A15&"*") -> 0 | H15: =SUMIFS('PLAN BUDGET SAMI-TF'!AQ12:AQ99999,'PLAN BUDGET SAMI-TF'!D12:D99999,SUMMARY!D15,'PLAN BUDGET SAMI-TF'!J12:J99999,SUMMARY!A15&"*") -> 0 | I15: =SUMIFS('PLAN BUDGET SAMI-TF'!AR12:AR99999,'PLAN BUDGET SAMI-TF'!D12:D99999,SUMMARY!D15,'PLAN BUDGET SAMI-TF'!J12:J99999,SUMMARY!A15&"*") -> 0 | J15: =SUMIFS('PLAN BUDGET SAMI-TF'!AS12:AS99999,'PLAN BUDGET SAMI-TF'!D12:D99999,SUMMARY!D15,'PLAN BUDGET SAMI-TF'!J12:J99999,SUMMARY!A15&"*") -> 6 | K15: =SUMIFS('PLAN BUDGET SAMI-TF'!AT12:AT99999,'PLAN BUDGET SAMI-TF'!D12:D99999,SUMMARY!D15,'PLAN BUDGET SAMI-TF'!J12:J99999,SUMMARY!A15&"*") -> 0 | L15: =SUMIFS('PLAN BUDGET SAMI-TF'!AU12:AU99999,'PLAN BUDGET SAMI-TF'!D12:D99999,SUMMARY!D15,'PLAN BUDGET SAMI-TF'!J12:J99999,SUMMARY!A15&"*") -> 0 | M15: =SUMIFS('PLAN BUDGET SAMI-TF'!AV12:AV99999,'PLAN BUDGET SAMI-TF'!D12:D99999,SUMMARY!D15,'PLAN BUDGET SAMI-TF'!J12:J99999,SUMMARY!A15&"*") -> 0 | N15: =SUMIFS('PLAN BUDGET SAMI-TF'!AW12:AW99999,'PLAN BUDGET SAMI-TF'!D12:D99999,SUMMARY!D15,'PLAN BUDGET SAMI-TF'!J12:J99999,SUMMARY!A15&"*") -> 0 | O15: =SUMIFS('PLAN BUDGET SAMI-TF'!AX12:AX99999,'PLAN BUDGET SAMI-TF'!D12:D99999,SUMMARY!D15,'PLAN BUDGET SAMI-TF'!J12:J99999,SUMMARY!A15&"*") -> 0 | P15: =SUMIFS('PLAN BUDGET SAMI-TF'!AY12:AY99999,'PLAN BUDGET SAMI-TF'!D12:D99999,SUMMARY!D15,'PLAN BUDGET SAMI-TF'!J12:J99999,SUMMARY!A15&"*") -> 0 | Q15: =SUMIFS('PLAN BUDGET SAMI-TF'!BC12:BC99999,'PLAN BUDGET SAMI-TF'!D12:D99999,SUMMARY!D15,'PLAN BUDGET SAMI-TF'!J12:J99999,SUMMARY!A15&"*") -> 0 | R15: =SUMIFS('PLAN BUDGET SAMI-TF'!BD12:BD99999,'PLAN BUDGET SAMI-TF'!D12:D99999,SUMMARY!D15,'PLAN BUDGET SAMI-TF'!J12:J99999,SUMMARY!A15&"*") -> 0 | S15: =SUMIFS('PLAN BUDGET SAMI-TF'!BE12:BE99999,'PLAN BUDGET SAMI-TF'!D12:D99999,SUMMARY!D15,'PLAN BUDGET SAMI-TF'!J12:J99999,SUMMARY!A15&"*") -> 0 | T15: =SUMIFS('PLAN BUDGET SAMI-TF'!BF12:BF99999,'PLAN BUDGET SAMI-TF'!D12:D99999,SUMMARY!D15,'PLAN BUDGET SAMI-TF'!J12:J99999,SUMMARY!A15&"*") -> 0 | U15: =SUMIFS('PLAN BUDGET SAMI-TF'!BG12:BG99999,'PLAN BUDGET SAMI-TF'!D12:D99999,SUMMARY!D15,'PLAN BUDGET SAMI-TF'!J12:J99999,SUMMARY!A15&"*") -> 0 | V15: =SUMIFS('PLAN BUDGET SAMI-TF'!BH12:BH99999,'PLAN BUDGET SAMI-TF'!D12:D99999,SUMMARY!D15,'PLAN BUDGET SAMI-TF'!J12:J99999,SUMMARY!A15&"*") -> 0 | W15: =SUMIFS('PLAN BUDGET SAMI-TF'!BI12:BI99999,'PLAN BUDGET SAMI-TF'!D12:D99999,SUMMARY!D15,'PLAN BUDGET SAMI-TF'!J12:J99999,SUMMARY!A15&"*") -> 0 | X15: =SUMIFS('PLAN BUDGET SAMI-TF'!BJ12:BJ99999,'PLAN BUDGET SAMI-TF'!D12:D99999,SUMMARY!D15,'PLAN BUDGET SAMI-TF'!J12:J99999,SUMMARY!A15&"*") -> 0 | Y15: =SUMIFS('PLAN BUDGET SAMI-TF'!BK12:BK99999,'PLAN BUDGET SAMI-TF'!D12:D99999,SUMMARY!D15,'PLAN BUDGET SAMI-TF'!J12:J99999,SUMMARY!A15&"*") -> 0 | Z15: =SUMIFS('PLAN BUDGET SAMI-TF'!BL12:BL99999,'PLAN BUDGET SAMI-TF'!D12:D99999,SUMMARY!D15,'PLAN BUDGET SAMI-TF'!J12:J99999,SUMMARY!A15&"*") -> 0 | AA15: =SUMIFS('PLAN BUDGET SAMI-TF'!BM12:BM99999,'PLAN BUDGET SAMI-TF'!D12:D99999,SUMMARY!D15,'PLAN BUDGET SAMI-TF'!J12:J99999,SUMMARY!A15&"*") -> 0 | AB15: =SUMIFS('PLAN BUDGET SAMI-TF'!BN12:BN99999,'PLAN BUDGET SAMI-TF'!D12:D99999,SUMMARY!D15,'PLAN BUDGET SAMI-TF'!J12:J99999,SUMMARY!A15&"*") -> 0 | AC15: =SUM(E15:P15) -> 7 | AD15: =SUM(Q15:AB15) -> 0 | AF15: 2 | AG15: 265.84634 | AH15: =IFERROR((AC15-AF15)/AF15,1) -> 2.5 | AI15: =IFERROR((AD15-AG15)/AG15,1) -> -1 | AJ15: Di th 84 tidak ada seleksi calon magang operator ke Jepang karena menggunakan cadangan dari batch sebelumnya
A16: RUTIN | D16: MIKA LAMINATING | E16: =SUMIFS('PLAN BUDGET SAMI-TF'!AN12:AN99999,'PLAN BUDGET SAMI-TF'!D12:D99999,SUMMARY!D16,'PLAN BUDGET SAMI-TF'!J12:J99999,SUMMARY!A16&"*") -> 1 | F16: =SUMIFS('PLAN BUDGET SAMI-TF'!AO12:AO99999,'PLAN BUDGET SAMI-TF'!D12:D99999,SUMMARY!D16,'PLAN BUDGET SAMI-TF'!J12:J99999,SUMMARY!A16&"*") -> 0 | G16: =SUMIFS('PLAN BUDGET SAMI-TF'!AP12:AP99999,'PLAN BUDGET SAMI-TF'!D12:D99999,SUMMARY!D16,'PLAN BUDGET SAMI-TF'!J12:J99999,SUMMARY!A16&"*") -> 0 | H16: =SUMIFS('PLAN BUDGET SAMI-TF'!AQ12:AQ99999,'PLAN BUDGET SAMI-TF'!D12:D99999,SUMMARY!D16,'PLAN BUDGET SAMI-TF'!J12:J99999,SUMMARY!A16&"*") -> 0 | I16: =SUMIFS('PLAN BUDGET SAMI-TF'!AR12:AR99999,'PLAN BUDGET SAMI-TF'!D12:D99999,SUMMARY!D16,'PLAN BUDGET SAMI-TF'!J12:J99999,SUMMARY!A16&"*") -> 0 | J16: =SUMIFS('PLAN BUDGET SAMI-TF'!AS12:AS99999,'PLAN BUDGET SAMI-TF'!D12:D99999,SUMMARY!D16,'PLAN BUDGET SAMI-TF'!J12:J99999,SUMMARY!A16&"*") -> 0 | K16: =SUMIFS('PLAN BUDGET SAMI-TF'!AT12:AT99999,'PLAN BUDGET SAMI-TF'!D12:D99999,SUMMARY!D16,'PLAN BUDGET SAMI-TF'!J12:J99999,SUMMARY!A16&"*") -> 1 | L16: =SUMIFS('PLAN BUDGET SAMI-TF'!AU12:AU99999,'PLAN BUDGET SAMI-TF'!D12:D99999,SUMMARY!D16,'PLAN BUDGET SAMI-TF'!J12:J99999,SUMMARY!A16&"*") -> 0 | M16: =SUMIFS('PLAN BUDGET SAMI-TF'!AV12:AV99999,'PLAN BUDGET SAMI-TF'!D12:D99999,SUMMARY!D16,'PLAN BUDGET SAMI-TF'!J12:J99999,SUMMARY!A16&"*") -> 0 | N16: =SUMIFS('PLAN BUDGET SAMI-TF'!AW12:AW99999,'PLAN BUDGET SAMI-TF'!D12:D99999,SUMMARY!D16,'PLAN BUDGET SAMI-TF'!J12:J99999,SUMMARY!A16&"*") -> 0 | O16: =SUMIFS('PLAN BUDGET SAMI-TF'!AX12:AX99999,'PLAN BUDGET SAMI-TF'!D12:D99999,SUMMARY!D16,'PLAN BUDGET SAMI-TF'!J12:J99999,SUMMARY!A16&"*") -> 0 | P16: =SUMIFS('PLAN BUDGET SAMI-TF'!AY12:AY99999,'PLAN BUDGET SAMI-TF'!D12:D99999,SUMMARY!D16,'PLAN BUDGET SAMI-TF'!J12:J99999,SUMMARY!A16&"*") -> 0 | Q16: =SUMIFS('PLAN BUDGET SAMI-TF'!BC12:BC99999,'PLAN BUDGET SAMI-TF'!D12:D99999,SUMMARY!D16,'PLAN BUDGET SAMI-TF'!J12:J99999,SUMMARY!A16&"*") -> 14.575342 | R16: =SUMIFS('PLAN BUDGET SAMI-TF'!BD12:BD99999,'PLAN BUDGET SAMI-TF'!D12:D99999,SUMMARY!D16,'PLAN BUDGET SAMI-TF'!J12:J99999,SUMMARY!A16&"*") -> 0 | S16: =SUMIFS('PLAN BUDGET SAMI-TF'!BE12:BE99999,'PLAN BUDGET SAMI-TF'!D12:D99999,SUMMARY!D16,'PLAN BUDGET SAMI-TF'!J12:J99999,SUMMARY!A16&"*") -> 0 | T16: =SUMIFS('PLAN BUDGET SAMI-TF'!BF12:BF99999,'PLAN BUDGET SAMI-TF'!D12:D99999,SUMMARY!D16,'PLAN BUDGET SAMI-TF'!J12:J99999,SUMMARY!A16&"*") -> 0 | U16: =SUMIFS('PLAN BUDGET SAMI-TF'!BG12:BG99999,'PLAN BUDGET SAMI-TF'!D12:D99999,SUMMARY!D16,'PLAN BUDGET SAMI-TF'!J12:J99999,SUMMARY!A16&"*") -> 0 | V16: =SUMIFS('PLAN BUDGET SAMI-TF'!BH12:BH99999,'PLAN BUDGET SAMI-TF'!D12:D99999,SUMMARY!D16,'PLAN BUDGET SAMI-TF'!J12:J99999,SUMMARY!A16&"*") -> 0 | W16: =SUMIFS('PLAN BUDGET SAMI-TF'!BI12:BI99999,'PLAN BUDGET SAMI-TF'!D12:D99999,SUMMARY!D16,'PLAN BUDGET SAMI-TF'!J12:J99999,SUMMARY!A16&"*") -> 14.575342 | X16: =SUMIFS('PLAN BUDGET SAMI-TF'!BJ12:BJ99999,'PLAN BUDGET SAMI-TF'!D12:D99999,SUMMARY!D16,'PLAN BUDGET SAMI-TF'!J12:J99999,SUMMARY!A16&"*") -> 0 | Y16: =SUMIFS('PLAN BUDGET SAMI-TF'!BK12:BK99999,'PLAN BUDGET SAMI-TF'!D12:D99999,SUMMARY!D16,'PLAN BUDGET SAMI-TF'!J12:J99999,SUMMARY!A16&"*") -> 0 | Z16: =SUMIFS('PLAN BUDGET SAMI-TF'!BL12:BL99999,'PLAN BUDGET SAMI-TF'!D12:D99999,SUMMARY!D16,'PLAN BUDGET SAMI-TF'!J12:J99999,SUMMARY!A16&"*") -> 0 | AA16: =SUMIFS('PLAN BUDGET SAMI-TF'!BM12:BM99999,'PLAN BUDGET SAMI-TF'!D12:D99999,SUMMARY!D16,'PLAN BUDGET SAMI-TF'!J12:J99999,SUMMARY!A16&"*") -> 0 | AB16: =SUMIFS('PLAN BUDGET SAMI-TF'!BN12:BN99999,'PLAN BUDGET SAMI-TF'!D12:D99999,SUMMARY!D16,'PLAN BUDGET SAMI-TF'!J12:J99999,SUMMARY!A16&"*") -> 0 | AC16: =SUM(E16:P16) -> 2 | AD16: =SUM(Q16:AB16) -> 29.150684 | AF16: 2 | AG16: 27.611687 | AH16: =IFERROR((AC16-AF16)/AF16,1) -> 0 | AI16: =IFERROR((AD16-AG16)/AG16,1) -> 0.055737164 | AJ16: Ada kenaikan harga
A17: RUTIN | D17: SAPU | E17: =SUMIFS('PLAN BUDGET SAMI-TF'!AN12:AN99999,'PLAN BUDGET SAMI-TF'!D12:D99999,SUMMARY!D17,'PLAN BUDGET SAMI-TF'!J12:J99999,SUMMARY!A17&"*") -> 40 | F17: =SUMIFS('PLAN BUDGET SAMI-TF'!AO12:AO99999,'PLAN BUDGET SAMI-TF'!D12:D99999,SUMMARY!D17,'PLAN BUDGET SAMI-TF'!J12:J99999,SUMMARY!A17&"*") -> 40 | G17: =SUMIFS('PLAN BUDGET SAMI-TF'!AP12:AP99999,'PLAN BUDGET SAMI-TF'!D12:D99999,SUMMARY!D17,'PLAN BUDGET SAMI-TF'!J12:J99999,SUMMARY!A17&"*") -> 40 | H17: =SUMIFS('PLAN BUDGET SAMI-TF'!AQ12:AQ99999,'PLAN BUDGET SAMI-TF'!D12:D99999,SUMMARY!D17,'PLAN BUDGET SAMI-TF'!J12:J99999,SUMMARY!A17&"*") -> 40 | I17: =SUMIFS('PLAN BUDGET SAMI-TF'!AR12:AR99999,'PLAN BUDGET SAMI-TF'!D12:D99999,SUMMARY!D17,'PLAN BUDGET SAMI-TF'!J12:J99999,SUMMARY!A17&"*") -> 40 | J17: =SUMIFS('PLAN BUDGET SAMI-TF'!AS12:AS99999,'PLAN BUDGET SAMI-TF'!D12:D99999,SUMMARY!D17,'PLAN BUDGET SAMI-TF'!J12:J99999,SUMMARY!A17&"*") -> 40 | K17: =SUMIFS('PLAN BUDGET SAMI-TF'!AT12:AT99999,'PLAN BUDGET SAMI-TF'!D12:D99999,SUMMARY!D17,'PLAN BUDGET SAMI-TF'!J12:J99999,SUMMARY!A17&"*") -> 40 | L17: =SUMIFS('PLAN BUDGET SAMI-TF'!AU12:AU99999,'PLAN BUDGET SAMI-TF'!D12:D99999,SUMMARY!D17,'PLAN BUDGET SAMI-TF'!J12:J99999,SUMMARY!A17&"*") -> 40 | M17: =SUMIFS('PLAN BUDGET SAMI-TF'!AV12:AV99999,'PLAN BUDGET SAMI-TF'!D12:D99999,SUMMARY!D17,'PLAN BUDGET SAMI-TF'!J12:J99999,SUMMARY!A17&"*") -> 40 | N17: =SUMIFS('PLAN BUDGET SAMI-TF'!AW12:AW99999,'PLAN BUDGET SAMI-TF'!D12:D99999,SUMMARY!D17,'PLAN BUDGET SAMI-TF'!J12:J99999,SUMMARY!A17&"*") -> 40 | O17: =SUMIFS('PLAN BUDGET SAMI-TF'!AX12:AX99999,'PLAN BUDGET SAMI-TF'!D12:D99999,SUMMARY!D17,'PLAN BUDGET SAMI-TF'!J12:J99999,SUMMARY!A17&"*") -> 40 | P17: =SUMIFS('PLAN BUDGET SAMI-TF'!AY12:AY99999,'PLAN BUDGET SAMI-TF'!D12:D99999,SUMMARY!D17,'PLAN BUDGET SAMI-TF'!J12:J99999,SUMMARY!A17&"*") -> 40 | Q17: =SUMIFS('PLAN BUDGET SAMI-TF'!BC12:BC99999,'PLAN BUDGET SAMI-TF'!D12:D99999,SUMMARY!D17,'PLAN BUDGET SAMI-TF'!J12:J99999,SUMMARY!A17&"*") -> 149.22335 | R17: =SUMIFS('PLAN BUDGET SAMI-TF'!BD12:BD99999,'PLAN BUDGET SAMI-TF'!D12:D99999,SUMMARY!D17,'PLAN BUDGET SAMI-TF'!J12:J99999,SUMMARY!A17&"*") -> 149.22335 | S17: =SUMIFS('PLAN BUDGET SAMI-TF'!BE12:BE99999,'PLAN BUDGET SAMI-TF'!D12:D99999,SUMMARY!D17,'PLAN BUDGET SAMI-TF'!J12:J99999,SUMMARY!A17&"*") -> 149.22335 | T17: =SUMIFS('PLAN BUDGET SAMI-TF'!BF12:BF99999,'PLAN BUDGET SAMI-TF'!D12:D99999,SUMMARY!D17,'PLAN BUDGET SAMI-TF'!J12:J99999,SUMMARY!A17&"*") -> 149.22335 | U17: =SUMIFS('PLAN BUDGET SAMI-TF'!BG12:BG99999,'PLAN BUDGET SAMI-TF'!D12:D99999,SUMMARY!D17,'PLAN BUDGET SAMI-TF'!J12:J99999,SUMMARY!A17&"*") -> 149.22335 | V17: =SUMIFS('PLAN BUDGET SAMI-TF'!BH12:BH99999,'PLAN BUDGET SAMI-TF'!D12:D99999,SUMMARY!D17,'PLAN BUDGET SAMI-TF'!J12:J99999,SUMMARY!A17&"*") -> 149.22335 | W17: =SUMIFS('PLAN BUDGET SAMI-TF'!BI12:BI99999,'PLAN BUDGET SAMI-TF'!D12:D99999,SUMMARY!D17,'PLAN BUDGET SAMI-TF'!J12:J99999,SUMMARY!A17&"*") -> 149.22335 | X17: =SUMIFS('PLAN BUDGET SAMI-TF'!BJ12:BJ99999,'PLAN BUDGET SAMI-TF'!D12:D99999,SUMMARY!D17,'PLAN BUDGET SAMI-TF'!J12:J99999,SUMMARY!A17&"*") -> 149.22335 | Y17: =SUMIFS('PLAN BUDGET SAMI-TF'!BK12:BK99999,'PLAN BUDGET SAMI-TF'!D12:D99999,SUMMARY!D17,'PLAN BUDGET SAMI-TF'!J12:J99999,SUMMARY!A17&"*") -> 149.22335 | Z17: =SUMIFS('PLAN BUDGET SAMI-TF'!BL12:BL99999,'PLAN BUDGET SAMI-TF'!D12:D99999,SUMMARY!D17,'PLAN BUDGET SAMI-TF'!J12:J99999,SUMMARY!A17&"*") -> 149.22335 | AA17: =SUMIFS('PLAN BUDGET SAMI-TF'!BM12:BM99999,'PLAN BUDGET SAMI-TF'!D12:D99999,SUMMARY!D17,'PLAN BUDGET SAMI-TF'!J12:J99999,SUMMARY!A17&"*") -> 149.22335 | AB17: =SUMIFS('PLAN BUDGET SAMI-TF'!BN12:BN99999,'PLAN BUDGET SAMI-TF'!D12:D99999,SUMMARY!D17,'PLAN BUDGET SAMI-TF'!J12:J99999,SUMMARY!A17&"*") -> 149.22335 | AC17: =SUM(E17:P17) -> 480 | AD17: =SUM(Q17:AB17) -> 1790.6802 | AF17: 438 | AG17: 1499.1835 | AH17: =IFERROR((AC17-AF17)/AF17,1) -> 0.095890411 | AI17: =IFERROR((AD17-AG17)/AG17,1) -> 0.19443699 | AJ17: Ada penambahan qty karena ada penambahan jumlah kebutuhan sapu dari term 84
A18: RUTIN | D18: TES BAHASA JEPANG | E18: =SUMIFS('PLAN BUDGET SAMI-TF'!AN12:AN99999,'PLAN BUDGET SAMI-TF'!D12:D99999,SUMMARY!D18,'PLAN BUDGET SAMI-TF'!J12:J99999,SUMMARY!A18&"*") -> 0 | F18: =SUMIFS('PLAN BUDGET SAMI-TF'!AO12:AO99999,'PLAN BUDGET SAMI-TF'!D12:D99999,SUMMARY!D18,'PLAN BUDGET SAMI-TF'!J12:J99999,SUMMARY!A18&"*") -> 0 | G18: =SUMIFS('PLAN BUDGET SAMI-TF'!AP12:AP99999,'PLAN BUDGET SAMI-TF'!D12:D99999,SUMMARY!D18,'PLAN BUDGET SAMI-TF'!J12:J99999,SUMMARY!A18&"*") -> 0 | H18: =SUMIFS('PLAN BUDGET SAMI-TF'!AQ12:AQ99999,'PLAN BUDGET SAMI-TF'!D12:D99999,SUMMARY!D18,'PLAN BUDGET SAMI-TF'!J12:J99999,SUMMARY!A18&"*") -> 0 | I18: =SUMIFS('PLAN BUDGET SAMI-TF'!AR12:AR99999,'PLAN BUDGET SAMI-TF'!D12:D99999,SUMMARY!D18,'PLAN BUDGET SAMI-TF'!J12:J99999,SUMMARY!A18&"*") -> 0 | J18: =SUMIFS('PLAN BUDGET SAMI-TF'!AS12:AS99999,'PLAN BUDGET SAMI-TF'!D12:D99999,SUMMARY!D18,'PLAN BUDGET SAMI-TF'!J12:J99999,SUMMARY!A18&"*") -> 0 | K18: =SUMIFS('PLAN BUDGET SAMI-TF'!AT12:AT99999,'PLAN BUDGET SAMI-TF'!D12:D99999,SUMMARY!D18,'PLAN BUDGET SAMI-TF'!J12:J99999,SUMMARY!A18&"*") -> 0 | L18: =SUMIFS('PLAN BUDGET SAMI-TF'!AU12:AU99999,'PLAN BUDGET SAMI-TF'!D12:D99999,SUMMARY!D18,'PLAN BUDGET SAMI-TF'!J12:J99999,SUMMARY!A18&"*") -> 0 | M18: =SUMIFS('PLAN BUDGET SAMI-TF'!AV12:AV99999,'PLAN BUDGET SAMI-TF'!D12:D99999,SUMMARY!D18,'PLAN BUDGET SAMI-TF'!J12:J99999,SUMMARY!A18&"*") -> 10 | N18: =SUMIFS('PLAN BUDGET SAMI-TF'!AW12:AW99999,'PLAN BUDGET SAMI-TF'!D12:D99999,SUMMARY!D18,'PLAN BUDGET SAMI-TF'!J12:J99999,SUMMARY!A18&"*") -> 0 | O18: =SUMIFS('PLAN BUDGET SAMI-TF'!AX12:AX99999,'PLAN BUDGET SAMI-TF'!D12:D99999,SUMMARY!D18,'PLAN BUDGET SAMI-TF'!J12:J99999,SUMMARY!A18&"*") -> 0 | P18: =SUMIFS('PLAN BUDGET SAMI-TF'!AY12:AY99999,'PLAN BUDGET SAMI-TF'!D12:D99999,SUMMARY!D18,'PLAN BUDGET SAMI-TF'!J12:J99999,SUMMARY!A18&"*") -> 0 | Q18: =SUMIFS('PLAN BUDGET SAMI-TF'!BC12:BC99999,'PLAN BUDGET SAMI-TF'!D12:D99999,SUMMARY!D18,'PLAN BUDGET SAMI-TF'!J12:J99999,SUMMARY!A18&"*") -> 0 | R18: =SUMIFS('PLAN BUDGET SAMI-TF'!BD12:BD99999,'PLAN BUDGET SAMI-TF'!D12:D99999,SUMMARY!D18,'PLAN BUDGET SAMI-TF'!J12:J99999,SUMMARY!A18&"*") -> 0 | S18: =SUMIFS('PLAN BUDGET SAMI-TF'!BE12:BE99999,'PLAN BUDGET SAMI-TF'!D12:D99999,SUMMARY!D18,'PLAN BUDGET SAMI-TF'!J12:J99999,SUMMARY!A18&"*") -> 0 | T18: =SUMIFS('PLAN BUDGET SAMI-TF'!BF12:BF99999,'PLAN BUDGET SAMI-TF'!D12:D99999,SUMMARY!D18,'PLAN BUDGET SAMI-TF'!J12:J99999,SUMMARY!A18&"*") -> 0 | U18: =SUMIFS('PLAN BUDGET SAMI-TF'!BG12:BG99999,'PLAN BUDGET SAMI-TF'!D12:D99999,SUMMARY!D18,'PLAN BUDGET SAMI-TF'!J12:J99999,SUMMARY!A18&"*") -> 0 | V18: =SUMIFS('PLAN BUDGET SAMI-TF'!BH12:BH99999,'PLAN BUDGET SAMI-TF'!D12:D99999,SUMMARY!D18,'PLAN BUDGET SAMI-TF'!J12:J99999,SUMMARY!A18&"*") -> 0 | W18: =SUMIFS('PLAN BUDGET SAMI-TF'!BI12:BI99999,'PLAN BUDGET SAMI-TF'!D12:D99999,SUMMARY!D18,'PLAN BUDGET SAMI-TF'!J12:J99999,SUMMARY!A18&"*") -> 0 | X18: =SUMIFS('PLAN BUDGET SAMI-TF'!BJ12:BJ99999,'PLAN BUDGET SAMI-TF'!D12:D99999,SUMMARY!D18,'PLAN BUDGET SAMI-TF'!J12:J99999,SUMMARY!A18&"*") -> 0 | Y18: =SUMIFS('PLAN BUDGET SAMI-TF'!BK12:BK99999,'PLAN BUDGET SAMI-TF'!D12:D99999,SUMMARY!D18,'PLAN BUDGET SAMI-TF'!J12:J99999,SUMMARY!A18&"*") -> 97.31875 | Z18: =SUMIFS('PLAN BUDGET SAMI-TF'!BL12:BL99999,'PLAN BUDGET SAMI-TF'!D12:D99999,SUMMARY!D18,'PLAN BUDGET SAMI-TF'!J12:J99999,SUMMARY!A18&"*") -> 0 | AA18: =SUMIFS('PLAN BUDGET SAMI-TF'!BM12:BM99999,'PLAN BUDGET SAMI-TF'!D12:D99999,SUMMARY!D18,'PLAN BUDGET SAMI-TF'!J12:J99999,SUMMARY!A18&"*") -> 0 | AB18: =SUMIFS('PLAN BUDGET SAMI-TF'!BN12:BN99999,'PLAN BUDGET SAMI-TF'!D12:D99999,SUMMARY!D18,'PLAN BUDGET SAMI-TF'!J12:J99999,SUMMARY!A18&"*") -> 0 | AC18: =SUM(E18:P18) -> 10 | AD18: =SUM(Q18:AB18) -> 97.31875 | AF18: 31 | AG18: 288.03755 | AH18: =IFERROR((AC18-AF18)/AF18,1) -> -0.67741935 | AI18: =IFERROR((AD18-AG18)/AG18,1) -> -0.66213172 | AJ18: Di th 85 tidak ada plan training nihonggo N4, hanya nihonggo N5
A19: RUTIN | D19: TRAINING | E19: =SUMIFS('PLAN BUDGET SAMI-TF'!AN12:AN99999,'PLAN BUDGET SAMI-TF'!D12:D99999,SUMMARY!D19,'PLAN BUDGET SAMI-TF'!J12:J99999,SUMMARY!A19&"*") -> 0 | F19: =SUMIFS('PLAN BUDGET SAMI-TF'!AO12:AO99999,'PLAN BUDGET SAMI-TF'!D12:D99999,SUMMARY!D19,'PLAN BUDGET SAMI-TF'!J12:J99999,SUMMARY!A19&"*") -> 1 | G19: =SUMIFS('PLAN BUDGET SAMI-TF'!AP12:AP99999,'PLAN BUDGET SAMI-TF'!D12:D99999,SUMMARY!D19,'PLAN BUDGET SAMI-TF'!J12:J99999,SUMMARY!A19&"*") -> 0 | H19: =SUMIFS('PLAN BUDGET SAMI-TF'!AQ12:AQ99999,'PLAN BUDGET SAMI-TF'!D12:D99999,SUMMARY!D19,'PLAN BUDGET SAMI-TF'!J12:J99999,SUMMARY!A19&"*") -> 1 | I19: =SUMIFS('PLAN BUDGET SAMI-TF'!AR12:AR99999,'PLAN BUDGET SAMI-TF'!D12:D99999,SUMMARY!D19,'PLAN BUDGET SAMI-TF'!J12:J99999,SUMMARY!A19&"*") -> 0 | J19: =SUMIFS('PLAN BUDGET SAMI-TF'!AS12:AS99999,'PLAN BUDGET SAMI-TF'!D12:D99999,SUMMARY!D19,'PLAN BUDGET SAMI-TF'!J12:J99999,SUMMARY!A19&"*") -> 1 | K19: =SUMIFS('PLAN BUDGET SAMI-TF'!AT12:AT99999,'PLAN BUDGET SAMI-TF'!D12:D99999,SUMMARY!D19,'PLAN BUDGET SAMI-TF'!J12:J99999,SUMMARY!A19&"*") -> 1 | L19: =SUMIFS('PLAN BUDGET SAMI-TF'!AU12:AU99999,'PLAN BUDGET SAMI-TF'!D12:D99999,SUMMARY!D19,'PLAN BUDGET SAMI-TF'!J12:J99999,SUMMARY!A19&"*") -> 0 | M19: =SUMIFS('PLAN BUDGET SAMI-TF'!AV12:AV99999,'PLAN BUDGET SAMI-TF'!D12:D99999,SUMMARY!D19,'PLAN BUDGET SAMI-TF'!J12:J99999,SUMMARY!A19&"*") -> 0 | N19: =SUMIFS('PLAN BUDGET SAMI-TF'!AW12:AW99999,'PLAN BUDGET SAMI-TF'!D12:D99999,SUMMARY!D19,'PLAN BUDGET SAMI-TF'!J12:J99999,SUMMARY!A19&"*") -> 0 | O19: =SUMIFS('PLAN BUDGET SAMI-TF'!AX12:AX99999,'PLAN BUDGET SAMI-TF'!D12:D99999,SUMMARY!D19,'PLAN BUDGET SAMI-TF'!J12:J99999,SUMMARY!A19&"*") -> 0 | P19: =SUMIFS('PLAN BUDGET SAMI-TF'!AY12:AY99999,'PLAN BUDGET SAMI-TF'!D12:D99999,SUMMARY!D19,'PLAN BUDGET SAMI-TF'!J12:J99999,SUMMARY!A19&"*") -> 0 | Q19: =SUMIFS('PLAN BUDGET SAMI-TF'!BC12:BC99999,'PLAN BUDGET SAMI-TF'!D12:D99999,SUMMARY!D19,'PLAN BUDGET SAMI-TF'!J12:J99999,SUMMARY!A19&"*") -> 0 | R19: =SUMIFS('PLAN BUDGET SAMI-TF'!BD12:BD99999,'PLAN BUDGET SAMI-TF'!D12:D99999,SUMMARY!D19,'PLAN BUDGET SAMI-TF'!J12:J99999,SUMMARY!A19&"*") -> 1226.3492 | S19: =SUMIFS('PLAN BUDGET SAMI-TF'!BE12:BE99999,'PLAN BUDGET SAMI-TF'!D12:D99999,SUMMARY!D19,'PLAN BUDGET SAMI-TF'!J12:J99999,SUMMARY!A19&"*") -> 0 | T19: =SUMIFS('PLAN BUDGET SAMI-TF'!BF12:BF99999,'PLAN BUDGET SAMI-TF'!D12:D99999,SUMMARY!D19,'PLAN BUDGET SAMI-TF'!J12:J99999,SUMMARY!A19&"*") -> 1466.5856 | U19: =SUMIFS('PLAN BUDGET SAMI-TF'!BG12:BG99999,'PLAN BUDGET SAMI-TF'!D12:D99999,SUMMARY!D19,'PLAN BUDGET SAMI-TF'!J12:J99999,SUMMARY!A19&"*") -> 0 | V19: =SUMIFS('PLAN BUDGET SAMI-TF'!BH12:BH99999,'PLAN BUDGET SAMI-TF'!D12:D99999,SUMMARY!D19,'PLAN BUDGET SAMI-TF'!J12:J99999,SUMMARY!A19&"*") -> 1226.3492 | W19: =SUMIFS('PLAN BUDGET SAMI-TF'!BI12:BI99999,'PLAN BUDGET SAMI-TF'!D12:D99999,SUMMARY!D19,'PLAN BUDGET SAMI-TF'!J12:J99999,SUMMARY!A19&"*") -> 1466.5856 | X19: =SUMIFS('PLAN BUDGET SAMI-TF'!BJ12:BJ99999,'PLAN BUDGET SAMI-TF'!D12:D99999,SUMMARY!D19,'PLAN BUDGET SAMI-TF'!J12:J99999,SUMMARY!A19&"*") -> 0 | Y19: =SUMIFS('PLAN BUDGET SAMI-TF'!BK12:BK99999,'PLAN BUDGET SAMI-TF'!D12:D99999,SUMMARY!D19,'PLAN BUDGET SAMI-TF'!J12:J99999,SUMMARY!A19&"*") -> 0 | Z19: =SUMIFS('PLAN BUDGET SAMI-TF'!BL12:BL99999,'PLAN BUDGET SAMI-TF'!D12:D99999,SUMMARY!D19,'PLAN BUDGET SAMI-TF'!J12:J99999,SUMMARY!A19&"*") -> 0 | AA19: =SUMIFS('PLAN BUDGET SAMI-TF'!BM12:BM99999,'PLAN BUDGET SAMI-TF'!D12:D99999,SUMMARY!D19,'PLAN BUDGET SAMI-TF'!J12:J99999,SUMMARY!A19&"*") -> 0 | AB19: =SUMIFS('PLAN BUDGET SAMI-TF'!BN12:BN99999,'PLAN BUDGET SAMI-TF'!D12:D99999,SUMMARY!D19,'PLAN BUDGET SAMI-TF'!J12:J99999,SUMMARY!A19&"*") -> 0 | AC19: =SUM(E19:P19) -> 4 | AD19: =SUM(Q19:AB19) -> 5385.8696 | AF19: 7 | AG19: 3416.1255 | AH19: =IFERROR((AC19-AF19)/AF19,1) -> -0.42857143 | AI19: =IFERROR((AD19-AG19)/AG19,1) -> 0.57660182 | AJ19: Di th 85 tidak ada plan training bahasa Inggris TOEIC
A20: RUTIN | D20: VACUM | E20: =SUMIFS('PLAN BUDGET SAMI-TF'!AN12:AN99999,'PLAN BUDGET SAMI-TF'!D12:D99999,SUMMARY!D20,'PLAN BUDGET SAMI-TF'!J12:J99999,SUMMARY!A20&"*") -> 0 | F20: =SUMIFS('PLAN BUDGET SAMI-TF'!AO12:AO99999,'PLAN BUDGET SAMI-TF'!D12:D99999,SUMMARY!D20,'PLAN BUDGET SAMI-TF'!J12:J99999,SUMMARY!A20&"*") -> 0 | G20: =SUMIFS('PLAN BUDGET SAMI-TF'!AP12:AP99999,'PLAN BUDGET SAMI-TF'!D12:D99999,SUMMARY!D20,'PLAN BUDGET SAMI-TF'!J12:J99999,SUMMARY!A20&"*") -> 0 | H20: =SUMIFS('PLAN BUDGET SAMI-TF'!AQ12:AQ99999,'PLAN BUDGET SAMI-TF'!D12:D99999,SUMMARY!D20,'PLAN BUDGET SAMI-TF'!J12:J99999,SUMMARY!A20&"*") -> 0 | I20: =SUMIFS('PLAN BUDGET SAMI-TF'!AR12:AR99999,'PLAN BUDGET SAMI-TF'!D12:D99999,SUMMARY!D20,'PLAN BUDGET SAMI-TF'!J12:J99999,SUMMARY!A20&"*") -> 1 | J20: =SUMIFS('PLAN BUDGET SAMI-TF'!AS12:AS99999,'PLAN BUDGET SAMI-TF'!D12:D99999,SUMMARY!D20,'PLAN BUDGET SAMI-TF'!J12:J99999,SUMMARY!A20&"*") -> 0 | K20: =SUMIFS('PLAN BUDGET SAMI-TF'!AT12:AT99999,'PLAN BUDGET SAMI-TF'!D12:D99999,SUMMARY!D20,'PLAN BUDGET SAMI-TF'!J12:J99999,SUMMARY!A20&"*") -> 0 | L20: =SUMIFS('PLAN BUDGET SAMI-TF'!AU12:AU99999,'PLAN BUDGET SAMI-TF'!D12:D99999,SUMMARY!D20,'PLAN BUDGET SAMI-TF'!J12:J99999,SUMMARY!A20&"*") -> 0 | M20: =SUMIFS('PLAN BUDGET SAMI-TF'!AV12:AV99999,'PLAN BUDGET SAMI-TF'!D12:D99999,SUMMARY!D20,'PLAN BUDGET SAMI-TF'!J12:J99999,SUMMARY!A20&"*") -> 1 | N20: =SUMIFS('PLAN BUDGET SAMI-TF'!AW12:AW99999,'PLAN BUDGET SAMI-TF'!D12:D99999,SUMMARY!D20,'PLAN BUDGET SAMI-TF'!J12:J99999,SUMMARY!A20&"*") -> 0 | O20: =SUMIFS('PLAN BUDGET SAMI-TF'!AX12:AX99999,'PLAN BUDGET SAMI-TF'!D12:D99999,SUMMARY!D20,'PLAN BUDGET SAMI-TF'!J12:J99999,SUMMARY!A20&"*") -> 0 | P20: =SUMIFS('PLAN BUDGET SAMI-TF'!AY12:AY99999,'PLAN BUDGET SAMI-TF'!D12:D99999,SUMMARY!D20,'PLAN BUDGET SAMI-TF'!J12:J99999,SUMMARY!A20&"*") -> 1 | Q20: =SUMIFS('PLAN BUDGET SAMI-TF'!BC12:BC99999,'PLAN BUDGET SAMI-TF'!D12:D99999,SUMMARY!D20,'PLAN BUDGET SAMI-TF'!J12:J99999,SUMMARY!A20&"*") -> 0 | R20: =SUMIFS('PLAN BUDGET SAMI-TF'!BD12:BD99999,'PLAN BUDGET SAMI-TF'!D12:D99999,SUMMARY!D20,'PLAN BUDGET SAMI-TF'!J12:J99999,SUMMARY!A20&"*") -> 0 | S20: =SUMIFS('PLAN BUDGET SAMI-TF'!BE12:BE99999,'PLAN BUDGET SAMI-TF'!D12:D99999,SUMMARY!D20,'PLAN BUDGET SAMI-TF'!J12:J99999,SUMMARY!A20&"*") -> 0 | T20: =SUMIFS('PLAN BUDGET SAMI-TF'!BF12:BF99999,'PLAN BUDGET SAMI-TF'!D12:D99999,SUMMARY!D20,'PLAN BUDGET SAMI-TF'!J12:J99999,SUMMARY!A20&"*") -> 0 | U20: =SUMIFS('PLAN BUDGET SAMI-TF'!BG12:BG99999,'PLAN BUDGET SAMI-TF'!D12:D99999,SUMMARY!D20,'PLAN BUDGET SAMI-TF'!J12:J99999,SUMMARY!A20&"*") -> 71.367083 | V20: =SUMIFS('PLAN BUDGET SAMI-TF'!BH12:BH99999,'PLAN BUDGET SAMI-TF'!D12:D99999,SUMMARY!D20,'PLAN BUDGET SAMI-TF'!J12:J99999,SUMMARY!A20&"*") -> 0 | W20: =SUMIFS('PLAN BUDGET SAMI-TF'!BI12:BI99999,'PLAN BUDGET SAMI-TF'!D12:D99999,SUMMARY!D20,'PLAN BUDGET SAMI-TF'!J12:J99999,SUMMARY!A20&"*") -> 0 | X20: =SUMIFS('PLAN BUDGET SAMI-TF'!BJ12:BJ99999,'PLAN BUDGET SAMI-TF'!D12:D99999,SUMMARY!D20,'PLAN BUDGET SAMI-TF'!J12:J99999,SUMMARY!A20&"*") -> 0 | Y20: =SUMIFS('PLAN BUDGET SAMI-TF'!BK12:BK99999,'PLAN BUDGET SAMI-TF'!D12:D99999,SUMMARY!D20,'PLAN BUDGET SAMI-TF'!J12:J99999,SUMMARY!A20&"*") -> 71.367083 | Z20: =SUMIFS('PLAN BUDGET SAMI-TF'!BL12:BL99999,'PLAN BUDGET SAMI-TF'!D12:D99999,SUMMARY!D20,'PLAN BUDGET SAMI-TF'!J12:J99999,SUMMARY!A20&"*") -> 0 | AA20: =SUMIFS('PLAN BUDGET SAMI-TF'!BM12:BM99999,'PLAN BUDGET SAMI-TF'!D12:D99999,SUMMARY!D20,'PLAN BUDGET SAMI-TF'!J12:J99999,SUMMARY!A20&"*") -> 0 | AB20: =SUMIFS('PLAN BUDGET SAMI-TF'!BN12:BN99999,'PLAN BUDGET SAMI-TF'!D12:D99999,SUMMARY!D20,'PLAN BUDGET SAMI-TF'!J12:J99999,SUMMARY!A20&"*") -> 71.367083 | AC20: =SUM(E20:P20) -> 3 | AD20: =SUM(Q20:AB20) -> 214.10125 | AF20: 3 | AG20: 227.86829 | AH20: =IFERROR((AC20-AF20)/AF20,1) -> 0 | AI20: =IFERROR((AD20-AG20)/AG20,1) -> -0.060416667 | AJ20: Ada penurunan harga
A21: RUTIN | D21: CLIP | E21: =SUMIFS('PLAN BUDGET SAMI-TF'!AN12:AN99999,'PLAN BUDGET SAMI-TF'!D12:D99999,SUMMARY!D21,'PLAN BUDGET SAMI-TF'!J12:J99999,SUMMARY!A21&"*") -> 0 | F21: =SUMIFS('PLAN BUDGET SAMI-TF'!AO12:AO99999,'PLAN BUDGET SAMI-TF'!D12:D99999,SUMMARY!D21,'PLAN BUDGET SAMI-TF'!J12:J99999,SUMMARY!A21&"*") -> 0 | G21: =SUMIFS('PLAN BUDGET SAMI-TF'!AP12:AP99999,'PLAN BUDGET SAMI-TF'!D12:D99999,SUMMARY!D21,'PLAN BUDGET SAMI-TF'!J12:J99999,SUMMARY!A21&"*") -> 0 | H21: =SUMIFS('PLAN BUDGET SAMI-TF'!AQ12:AQ99999,'PLAN BUDGET SAMI-TF'!D12:D99999,SUMMARY!D21,'PLAN BUDGET SAMI-TF'!J12:J99999,SUMMARY!A21&"*") -> 0 | I21: =SUMIFS('PLAN BUDGET SAMI-TF'!AR12:AR99999,'PLAN BUDGET SAMI-TF'!D12:D99999,SUMMARY!D21,'PLAN BUDGET SAMI-TF'!J12:J99999,SUMMARY!A21&"*") -> 0 | J21: =SUMIFS('PLAN BUDGET SAMI-TF'!AS12:AS99999,'PLAN BUDGET SAMI-TF'!D12:D99999,SUMMARY!D21,'PLAN BUDGET SAMI-TF'!J12:J99999,SUMMARY!A21&"*") -> 1 | K21: =SUMIFS('PLAN BUDGET SAMI-TF'!AT12:AT99999,'PLAN BUDGET SAMI-TF'!D12:D99999,SUMMARY!D21,'PLAN BUDGET SAMI-TF'!J12:J99999,SUMMARY!A21&"*") -> 0 | L21: =SUMIFS('PLAN BUDGET SAMI-TF'!AU12:AU99999,'PLAN BUDGET SAMI-TF'!D12:D99999,SUMMARY!D21,'PLAN BUDGET SAMI-TF'!J12:J99999,SUMMARY!A21&"*") -> 0 | M21: =SUMIFS('PLAN BUDGET SAMI-TF'!AV12:AV99999,'PLAN BUDGET SAMI-TF'!D12:D99999,SUMMARY!D21,'PLAN BUDGET SAMI-TF'!J12:J99999,SUMMARY!A21&"*") -> 0 | N21: =SUMIFS('PLAN BUDGET SAMI-TF'!AW12:AW99999,'PLAN BUDGET SAMI-TF'!D12:D99999,SUMMARY!D21,'PLAN BUDGET SAMI-TF'!J12:J99999,SUMMARY!A21&"*") -> 0 | O21: =SUMIFS('PLAN BUDGET SAMI-TF'!AX12:AX99999,'PLAN BUDGET SAMI-TF'!D12:D99999,SUMMARY!D21,'PLAN BUDGET SAMI-TF'!J12:J99999,SUMMARY!A21&"*") -> 0 | P21: =SUMIFS('PLAN BUDGET SAMI-TF'!AY12:AY99999,'PLAN BUDGET SAMI-TF'!D12:D99999,SUMMARY!D21,'PLAN BUDGET SAMI-TF'!J12:J99999,SUMMARY!A21&"*") -> 0 | Q21: =SUMIFS('PLAN BUDGET SAMI-TF'!BC12:BC99999,'PLAN BUDGET SAMI-TF'!D12:D99999,SUMMARY!D21,'PLAN BUDGET SAMI-TF'!J12:J99999,SUMMARY!A21&"*") -> 0 | R21: =SUMIFS('PLAN BUDGET SAMI-TF'!BD12:BD99999,'PLAN BUDGET SAMI-TF'!D12:D99999,SUMMARY!D21,'PLAN BUDGET SAMI-TF'!J12:J99999,SUMMARY!A21&"*") -> 0 | S21: =SUMIFS('PLAN BUDGET SAMI-TF'!BE12:BE99999,'PLAN BUDGET SAMI-TF'!D12:D99999,SUMMARY!D21,'PLAN BUDGET SAMI-TF'!J12:J99999,SUMMARY!A21&"*") -> 0 | T21: =SUMIFS('PLAN BUDGET SAMI-TF'!BF12:BF99999,'PLAN BUDGET SAMI-TF'!D12:D99999,SUMMARY!D21,'PLAN BUDGET SAMI-TF'!J12:J99999,SUMMARY!A21&"*") -> 0 | U21: =SUMIFS('PLAN BUDGET SAMI-TF'!BG12:BG99999,'PLAN BUDGET SAMI-TF'!D12:D99999,SUMMARY!D21,'PLAN BUDGET SAMI-TF'!J12:J99999,SUMMARY!A21&"*") -> 0 | V21: =SUMIFS('PLAN BUDGET SAMI-TF'!BH12:BH99999,'PLAN BUDGET SAMI-TF'!D12:D99999,SUMMARY!D21,'PLAN BUDGET SAMI-TF'!J12:J99999,SUMMARY!A21&"*") -> 1.5824187 | W21: =SUMIFS('PLAN BUDGET SAMI-TF'!BI12:BI99999,'PLAN BUDGET SAMI-TF'!D12:D99999,SUMMARY!D21,'PLAN BUDGET SAMI-TF'!J12:J99999,SUMMARY!A21&"*") -> 0 | X21: =SUMIFS('PLAN BUDGET SAMI-TF'!BJ12:BJ99999,'PLAN BUDGET SAMI-TF'!D12:D99999,SUMMARY!D21,'PLAN BUDGET SAMI-TF'!J12:J99999,SUMMARY!A21&"*") -> 0 | Y21: =SUMIFS('PLAN BUDGET SAMI-TF'!BK12:BK99999,'PLAN BUDGET SAMI-TF'!D12:D99999,SUMMARY!D21,'PLAN BUDGET SAMI-TF'!J12:J99999,SUMMARY!A21&"*") -> 0 | Z21: =SUMIFS('PLAN BUDGET SAMI-TF'!BL12:BL99999,'PLAN BUDGET SAMI-TF'!D12:D99999,SUMMARY!D21,'PLAN BUDGET SAMI-TF'!J12:J99999,SUMMARY!A21&"*") -> 0 | AA21: =SUMIFS('PLAN BUDGET SAMI-TF'!BM12:BM99999,'PLAN BUDGET SAMI-TF'!D12:D99999,SUMMARY!D21,'PLAN BUDGET SAMI-TF'!J12:J99999,SUMMARY!A21&"*") -> 0 | AB21: =SUMIFS('PLAN BUDGET SAMI-TF'!BN12:BN99999,'PLAN BUDGET SAMI-TF'!D12:D99999,SUMMARY!D21,'PLAN BUDGET SAMI-TF'!J12:J99999,SUMMARY!A21&"*") -> 0 | AC21: =SUM(E21:P21) -> 1 | AD21: =SUM(Q21:AB21) -> 1.5824187 | AF21: 1 | AG21: 1.1764967 | AH21: =IFERROR((AC21-AF21)/AF21,1) -> 0 | AI21: =IFERROR((AD21-AG21)/AG21,1) -> 0.34502609 | AJ21: Ada kenaikan harga
A22: RUTIN | D22: ISI CUTTER | E22: =SUMIFS('PLAN BUDGET SAMI-TF'!AN12:AN99999,'PLAN BUDGET SAMI-TF'!D12:D99999,SUMMARY!D22,'PLAN BUDGET SAMI-TF'!J12:J99999,SUMMARY!A22&"*") -> 0 | F22: =SUMIFS('PLAN BUDGET SAMI-TF'!AO12:AO99999,'PLAN BUDGET SAMI-TF'!D12:D99999,SUMMARY!D22,'PLAN BUDGET SAMI-TF'!J12:J99999,SUMMARY!A22&"*") -> 0 | G22: =SUMIFS('PLAN BUDGET SAMI-TF'!AP12:AP99999,'PLAN BUDGET SAMI-TF'!D12:D99999,SUMMARY!D22,'PLAN BUDGET SAMI-TF'!J12:J99999,SUMMARY!A22&"*") -> 0 | H22: =SUMIFS('PLAN BUDGET SAMI-TF'!AQ12:AQ99999,'PLAN BUDGET SAMI-TF'!D12:D99999,SUMMARY!D22,'PLAN BUDGET SAMI-TF'!J12:J99999,SUMMARY!A22&"*") -> 0 | I22: =SUMIFS('PLAN BUDGET SAMI-TF'!AR12:AR99999,'PLAN BUDGET SAMI-TF'!D12:D99999,SUMMARY!D22,'PLAN BUDGET SAMI-TF'!J12:J99999,SUMMARY!A22&"*") -> 0 | J22: =SUMIFS('PLAN BUDGET SAMI-TF'!AS12:AS99999,'PLAN BUDGET SAMI-TF'!D12:D99999,SUMMARY!D22,'PLAN BUDGET SAMI-TF'!J12:J99999,SUMMARY!A22&"*") -> 1 | K22: =SUMIFS('PLAN BUDGET SAMI-TF'!AT12:AT99999,'PLAN BUDGET SAMI-TF'!D12:D99999,SUMMARY!D22,'PLAN BUDGET SAMI-TF'!J12:J99999,SUMMARY!A22&"*") -> 0 | L22: =SUMIFS('PLAN BUDGET SAMI-TF'!AU12:AU99999,'PLAN BUDGET SAMI-TF'!D12:D99999,SUMMARY!D22,'PLAN BUDGET SAMI-TF'!J12:J99999,SUMMARY!A22&"*") -> 0 | M22: =SUMIFS('PLAN BUDGET SAMI-TF'!AV12:AV99999,'PLAN BUDGET SAMI-TF'!D12:D99999,SUMMARY!D22,'PLAN BUDGET SAMI-TF'!J12:J99999,SUMMARY!A22&"*") -> 0 | N22: =SUMIFS('PLAN BUDGET SAMI-TF'!AW12:AW99999,'PLAN BUDGET SAMI-TF'!D12:D99999,SUMMARY!D22,'PLAN BUDGET SAMI-TF'!J12:J99999,SUMMARY!A22&"*") -> 0 | O22: =SUMIFS('PLAN BUDGET SAMI-TF'!AX12:AX99999,'PLAN BUDGET SAMI-TF'!D12:D99999,SUMMARY!D22,'PLAN BUDGET SAMI-TF'!J12:J99999,SUMMARY!A22&"*") -> 0 | P22: =SUMIFS('PLAN BUDGET SAMI-TF'!AY12:AY99999,'PLAN BUDGET SAMI-TF'!D12:D99999,SUMMARY!D22,'PLAN BUDGET SAMI-TF'!J12:J99999,SUMMARY!A22&"*") -> 0 | Q22: =SUMIFS('PLAN BUDGET SAMI-TF'!BC12:BC99999,'PLAN BUDGET SAMI-TF'!D12:D99999,SUMMARY!D22,'PLAN BUDGET SAMI-TF'!J12:J99999,SUMMARY!A22&"*") -> 0 | R22: =SUMIFS('PLAN BUDGET SAMI-TF'!BD12:BD99999,'PLAN BUDGET SAMI-TF'!D12:D99999,SUMMARY!D22,'PLAN BUDGET SAMI-TF'!J12:J99999,SUMMARY!A22&"*") -> 0 | S22: =SUMIFS('PLAN BUDGET SAMI-TF'!BE12:BE99999,'PLAN BUDGET SAMI-TF'!D12:D99999,SUMMARY!D22,'PLAN BUDGET SAMI-TF'!J12:J99999,SUMMARY!A22&"*") -> 0 | T22: =SUMIFS('PLAN BUDGET SAMI-TF'!BF12:BF99999,'PLAN BUDGET SAMI-TF'!D12:D99999,SUMMARY!D22,'PLAN BUDGET SAMI-TF'!J12:J99999,SUMMARY!A22&"*") -> 0 | U22: =SUMIFS('PLAN BUDGET SAMI-TF'!BG12:BG99999,'PLAN BUDGET SAMI-TF'!D12:D99999,SUMMARY!D22,'PLAN BUDGET SAMI-TF'!J12:J99999,SUMMARY!A22&"*") -> 0 | V22: =SUMIFS('PLAN BUDGET SAMI-TF'!BH12:BH99999,'PLAN BUDGET SAMI-TF'!D12:D99999,SUMMARY!D22,'PLAN BUDGET SAMI-TF'!J12:J99999,SUMMARY!A22&"*") -> 0.34211892 | W22: =SUMIFS('PLAN BUDGET SAMI-TF'!BI12:BI99999,'PLAN BUDGET SAMI-TF'!D12:D99999,SUMMARY!D22,'PLAN BUDGET SAMI-TF'!J12:J99999,SUMMARY!A22&"*") -> 0 | X22: =SUMIFS('PLAN BUDGET SAMI-TF'!BJ12:BJ99999,'PLAN BUDGET SAMI-TF'!D12:D99999,SUMMARY!D22,'PLAN BUDGET SAMI-TF'!J12:J99999,SUMMARY!A22&"*") -> 0 | Y22: =SUMIFS('PLAN BUDGET SAMI-TF'!BK12:BK99999,'PLAN BUDGET SAMI-TF'!D12:D99999,SUMMARY!D22,'PLAN BUDGET SAMI-TF'!J12:J99999,SUMMARY!A22&"*") -> 0 | Z22: =SUMIFS('PLAN BUDGET SAMI-TF'!BL12:BL99999,'PLAN BUDGET SAMI-TF'!D12:D99999,SUMMARY!D22,'PLAN BUDGET SAMI-TF'!J12:J99999,SUMMARY!A22&"*") -> 0 | AA22: =SUMIFS('PLAN BUDGET SAMI-TF'!BM12:BM99999,'PLAN BUDGET SAMI-TF'!D12:D99999,SUMMARY!D22,'PLAN BUDGET SAMI-TF'!J12:J99999,SUMMARY!A22&"*") -> 0 | AB22: =SUMIFS('PLAN BUDGET SAMI-TF'!BN12:BN99999,'PLAN BUDGET SAMI-TF'!D12:D99999,SUMMARY!D22,'PLAN BUDGET SAMI-TF'!J12:J99999,SUMMARY!A22&"*") -> 0 | AC22: =SUM(E22:P22) -> 1 | AD22: =SUM(Q22:AB22) -> 0.34211892 | AF22: 1 | AG22: 0.32414265 | AH22: =IFERROR((AC22-AF22)/AF22,1) -> 0 | AI22: =IFERROR((AD22-AG22)/AG22,1) -> 0.055457918 | AJ22: -
A23: RUTIN | D23: PENGHAPUS | E23: =SUMIFS('PLAN BUDGET SAMI-TF'!AN12:AN99999,'PLAN BUDGET SAMI-TF'!D12:D99999,SUMMARY!D23,'PLAN BUDGET SAMI-TF'!J12:J99999,SUMMARY!A23&"*") -> 0 | F23: =SUMIFS('PLAN BUDGET SAMI-TF'!AO12:AO99999,'PLAN BUDGET SAMI-TF'!D12:D99999,SUMMARY!D23,'PLAN BUDGET SAMI-TF'!J12:J99999,SUMMARY!A23&"*") -> 0 | G23: =SUMIFS('PLAN BUDGET SAMI-TF'!AP12:AP99999,'PLAN BUDGET SAMI-TF'!D12:D99999,SUMMARY!D23,'PLAN BUDGET SAMI-TF'!J12:J99999,SUMMARY!A23&"*") -> 3 | H23: =SUMIFS('PLAN BUDGET SAMI-TF'!AQ12:AQ99999,'PLAN BUDGET SAMI-TF'!D12:D99999,SUMMARY!D23,'PLAN BUDGET SAMI-TF'!J12:J99999,SUMMARY!A23&"*") -> 0 | I23: =SUMIFS('PLAN BUDGET SAMI-TF'!AR12:AR99999,'PLAN BUDGET SAMI-TF'!D12:D99999,SUMMARY!D23,'PLAN BUDGET SAMI-TF'!J12:J99999,SUMMARY!A23&"*") -> 0 | J23: =SUMIFS('PLAN BUDGET SAMI-TF'!AS12:AS99999,'PLAN BUDGET SAMI-TF'!D12:D99999,SUMMARY!D23,'PLAN BUDGET SAMI-TF'!J12:J99999,SUMMARY!A23&"*") -> 0 | K23: =SUMIFS('PLAN BUDGET SAMI-TF'!AT12:AT99999,'PLAN BUDGET SAMI-TF'!D12:D99999,SUMMARY!D23,'PLAN BUDGET SAMI-TF'!J12:J99999,SUMMARY!A23&"*") -> 0 | L23: =SUMIFS('PLAN BUDGET SAMI-TF'!AU12:AU99999,'PLAN BUDGET SAMI-TF'!D12:D99999,SUMMARY!D23,'PLAN BUDGET SAMI-TF'!J12:J99999,SUMMARY!A23&"*") -> 0 | M23: =SUMIFS('PLAN BUDGET SAMI-TF'!AV12:AV99999,'PLAN BUDGET SAMI-TF'!D12:D99999,SUMMARY!D23,'PLAN BUDGET SAMI-TF'!J12:J99999,SUMMARY!A23&"*") -> 0 | N23: =SUMIFS('PLAN BUDGET SAMI-TF'!AW12:AW99999,'PLAN BUDGET SAMI-TF'!D12:D99999,SUMMARY!D23,'PLAN BUDGET SAMI-TF'!J12:J99999,SUMMARY!A23&"*") -> 0 | O23: =SUMIFS('PLAN BUDGET SAMI-TF'!AX12:AX99999,'PLAN BUDGET SAMI-TF'!D12:D99999,SUMMARY!D23,'PLAN BUDGET SAMI-TF'!J12:J99999,SUMMARY!A23&"*") -> 0 | P23: =SUMIFS('PLAN BUDGET SAMI-TF'!AY12:AY99999,'PLAN BUDGET SAMI-TF'!D12:D99999,SUMMARY!D23,'PLAN BUDGET SAMI-TF'!J12:J99999,SUMMARY!A23&"*") -> 0 | Q23: =SUMIFS('PLAN BUDGET SAMI-TF'!BC12:BC99999,'PLAN BUDGET SAMI-TF'!D12:D99999,SUMMARY!D23,'PLAN BUDGET SAMI-TF'!J12:J99999,SUMMARY!A23&"*") -> 0 | R23: =SUMIFS('PLAN BUDGET SAMI-TF'!BD12:BD99999,'PLAN BUDGET SAMI-TF'!D12:D99999,SUMMARY!D23,'PLAN BUDGET SAMI-TF'!J12:J99999,SUMMARY!A23&"*") -> 0 | S23: =SUMIFS('PLAN BUDGET SAMI-TF'!BE12:BE99999,'PLAN BUDGET SAMI-TF'!D12:D99999,SUMMARY!D23,'PLAN BUDGET SAMI-TF'!J12:J99999,SUMMARY!A23&"*") -> 0.47035813 | T23: =SUMIFS('PLAN BUDGET SAMI-TF'!BF12:BF99999,'PLAN BUDGET SAMI-TF'!D12:D99999,SUMMARY!D23,'PLAN BUDGET SAMI-TF'!J12:J99999,SUMMARY!A23&"*") -> 0 | U23: =SUMIFS('PLAN BUDGET SAMI-TF'!BG12:BG99999,'PLAN BUDGET SAMI-TF'!D12:D99999,SUMMARY!D23,'PLAN BUDGET SAMI-TF'!J12:J99999,SUMMARY!A23&"*") -> 0 | V23: =SUMIFS('PLAN BUDGET SAMI-TF'!BH12:BH99999,'PLAN BUDGET SAMI-TF'!D12:D99999,SUMMARY!D23,'PLAN BUDGET SAMI-TF'!J12:J99999,SUMMARY!A23&"*") -> 0 | W23: =SUMIFS('PLAN BUDGET SAMI-TF'!BI12:BI99999,'PLAN BUDGET SAMI-TF'!D12:D99999,SUMMARY!D23,'PLAN BUDGET SAMI-TF'!J12:J99999,SUMMARY!A23&"*") -> 0 | X23: =SUMIFS('PLAN BUDGET SAMI-TF'!BJ12:BJ99999,'PLAN BUDGET SAMI-TF'!D12:D99999,SUMMARY!D23,'PLAN BUDGET SAMI-TF'!J12:J99999,SUMMARY!A23&"*") -> 0 | Y23: =SUMIFS('PLAN BUDGET SAMI-TF'!BK12:BK99999,'PLAN BUDGET SAMI-TF'!D12:D99999,SUMMARY!D23,'PLAN BUDGET SAMI-TF'!J12:J99999,SUMMARY!A23&"*") -> 0 | Z23: =SUMIFS('PLAN BUDGET SAMI-TF'!BL12:BL99999,'PLAN BUDGET SAMI-TF'!D12:D99999,SUMMARY!D23,'PLAN BUDGET SAMI-TF'!J12:J99999,SUMMARY!A23&"*") -> 0 | AA23: =SUMIFS('PLAN BUDGET SAMI-TF'!BM12:BM99999,'PLAN BUDGET SAMI-TF'!D12:D99999,SUMMARY!D23,'PLAN BUDGET SAMI-TF'!J12:J99999,SUMMARY!A23&"*") -> 0 | AB23: =SUMIFS('PLAN BUDGET SAMI-TF'!BN12:BN99999,'PLAN BUDGET SAMI-TF'!D12:D99999,SUMMARY!D23,'PLAN BUDGET SAMI-TF'!J12:J99999,SUMMARY!A23&"*") -> 0 | AC23: =SUM(E23:P23) -> 3 | AD23: =SUM(Q23:AB23) -> 0.47035813 | AF23: 9 | AG23: 1.0533212 | AH23: =IFERROR((AC23-AF23)/AF23,1) -> -0.66666667 | AI23: =IFERROR((AD23-AG23)/AG23,1) -> -0.55345232 | AJ23: Di th 85 tidak ada pembelian penghapus white board
A24: RUTIN | D24: TAPE | E24: =SUMIFS('PLAN BUDGET SAMI-TF'!AN12:AN99999,'PLAN BUDGET SAMI-TF'!D12:D99999,SUMMARY!D24,'PLAN BUDGET SAMI-TF'!J12:J99999,SUMMARY!A24&"*") -> 1 | F24: =SUMIFS('PLAN BUDGET SAMI-TF'!AO12:AO99999,'PLAN BUDGET SAMI-TF'!D12:D99999,SUMMARY!D24,'PLAN BUDGET SAMI-TF'!J12:J99999,SUMMARY!A24&"*") -> 1 | G24: =SUMIFS('PLAN BUDGET SAMI-TF'!AP12:AP99999,'PLAN BUDGET SAMI-TF'!D12:D99999,SUMMARY!D24,'PLAN BUDGET SAMI-TF'!J12:J99999,SUMMARY!A24&"*") -> 1 | H24: =SUMIFS('PLAN BUDGET SAMI-TF'!AQ12:AQ99999,'PLAN BUDGET SAMI-TF'!D12:D99999,SUMMARY!D24,'PLAN BUDGET SAMI-TF'!J12:J99999,SUMMARY!A24&"*") -> 1 | I24: =SUMIFS('PLAN BUDGET SAMI-TF'!AR12:AR99999,'PLAN BUDGET SAMI-TF'!D12:D99999,SUMMARY!D24,'PLAN BUDGET SAMI-TF'!J12:J99999,SUMMARY!A24&"*") -> 1 | J24: =SUMIFS('PLAN BUDGET SAMI-TF'!AS12:AS99999,'PLAN BUDGET SAMI-TF'!D12:D99999,SUMMARY!D24,'PLAN BUDGET SAMI-TF'!J12:J99999,SUMMARY!A24&"*") -> 1 | K24: =SUMIFS('PLAN BUDGET SAMI-TF'!AT12:AT99999,'PLAN BUDGET SAMI-TF'!D12:D99999,SUMMARY!D24,'PLAN BUDGET SAMI-TF'!J12:J99999,SUMMARY!A24&"*") -> 1 | L24: =SUMIFS('PLAN BUDGET SAMI-TF'!AU12:AU99999,'PLAN BUDGET SAMI-TF'!D12:D99999,SUMMARY!D24,'PLAN BUDGET SAMI-TF'!J12:J99999,SUMMARY!A24&"*") -> 1 | M24: =SUMIFS('PLAN BUDGET SAMI-TF'!AV12:AV99999,'PLAN BUDGET SAMI-TF'!D12:D99999,SUMMARY!D24,'PLAN BUDGET SAMI-TF'!J12:J99999,SUMMARY!A24&"*") -> 1 | N24: =SUMIFS('PLAN BUDGET SAMI-TF'!AW12:AW99999,'PLAN BUDGET SAMI-TF'!D12:D99999,SUMMARY!D24,'PLAN BUDGET SAMI-TF'!J12:J99999,SUMMARY!A24&"*") -> 1 | O24: =SUMIFS('PLAN BUDGET SAMI-TF'!AX12:AX99999,'PLAN BUDGET SAMI-TF'!D12:D99999,SUMMARY!D24,'PLAN BUDGET SAMI-TF'!J12:J99999,SUMMARY!A24&"*") -> 1 | P24: =SUMIFS('PLAN BUDGET SAMI-TF'!AY12:AY99999,'PLAN BUDGET SAMI-TF'!D12:D99999,SUMMARY!D24,'PLAN BUDGET SAMI-TF'!J12:J99999,SUMMARY!A24&"*") -> 1 | Q24: =SUMIFS('PLAN BUDGET SAMI-TF'!BC12:BC99999,'PLAN BUDGET SAMI-TF'!D12:D99999,SUMMARY!D24,'PLAN BUDGET SAMI-TF'!J12:J99999,SUMMARY!A24&"*") -> 0.15969769 | R24: =SUMIFS('PLAN BUDGET SAMI-TF'!BD12:BD99999,'PLAN BUDGET SAMI-TF'!D12:D99999,SUMMARY!D24,'PLAN BUDGET SAMI-TF'!J12:J99999,SUMMARY!A24&"*") -> 0.15969769 | S24: =SUMIFS('PLAN BUDGET SAMI-TF'!BE12:BE99999,'PLAN BUDGET SAMI-TF'!D12:D99999,SUMMARY!D24,'PLAN BUDGET SAMI-TF'!J12:J99999,SUMMARY!A24&"*") -> 0.15969769 | T24: =SUMIFS('PLAN BUDGET SAMI-TF'!BF12:BF99999,'PLAN BUDGET SAMI-TF'!D12:D99999,SUMMARY!D24,'PLAN BUDGET SAMI-TF'!J12:J99999,SUMMARY!A24&"*") -> 0.15969769 | U24: =SUMIFS('PLAN BUDGET SAMI-TF'!BG12:BG99999,'PLAN BUDGET SAMI-TF'!D12:D99999,SUMMARY!D24,'PLAN BUDGET SAMI-TF'!J12:J99999,SUMMARY!A24&"*") -> 0.15969769 | V24: =SUMIFS('PLAN BUDGET SAMI-TF'!BH12:BH99999,'PLAN BUDGET SAMI-TF'!D12:D99999,SUMMARY!D24,'PLAN BUDGET SAMI-TF'!J12:J99999,SUMMARY!A24&"*") -> 0.15969769 | W24: =SUMIFS('PLAN BUDGET SAMI-TF'!BI12:BI99999,'PLAN BUDGET SAMI-TF'!D12:D99999,SUMMARY!D24,'PLAN BUDGET SAMI-TF'!J12:J99999,SUMMARY!A24&"*") -> 0.15969769 | X24: =SUMIFS('PLAN BUDGET SAMI-TF'!BJ12:BJ99999,'PLAN BUDGET SAMI-TF'!D12:D99999,SUMMARY!D24,'PLAN BUDGET SAMI-TF'!J12:J99999,SUMMARY!A24&"*") -> 0.15969769 | Y24: =SUMIFS('PLAN BUDGET SAMI-TF'!BK12:BK99999,'PLAN BUDGET SAMI-TF'!D12:D99999,SUMMARY!D24,'PLAN BUDGET SAMI-TF'!J12:J99999,SUMMARY!A24&"*") -> 0.15969769 | Z24: =SUMIFS('PLAN BUDGET SAMI-TF'!BL12:BL99999,'PLAN BUDGET SAMI-TF'!D12:D99999,SUMMARY!D24,'PLAN BUDGET SAMI-TF'!J12:J99999,SUMMARY!A24&"*") -> 0.15969769 | AA24: =SUMIFS('PLAN BUDGET SAMI-TF'!BM12:BM99999,'PLAN BUDGET SAMI-TF'!D12:D99999,SUMMARY!D24,'PLAN BUDGET SAMI-TF'!J12:J99999,SUMMARY!A24&"*") -> 0.15969769 | AB24: =SUMIFS('PLAN BUDGET SAMI-TF'!BN12:BN99999,'PLAN BUDGET SAMI-TF'!D12:D99999,SUMMARY!D24,'PLAN BUDGET SAMI-TF'!J12:J99999,SUMMARY!A24&"*") -> 0.15969769 | AC24: =SUM(E24:P24) -> 12 | AD24: =SUM(Q24:AB24) -> 1.9163723 | AF24: 12 | AG24: 1.8009191 | AH24: =IFERROR((AC24-AF24)/AF24,1) -> 0 | AI24: =IFERROR((AD24-AG24)/AG24,1) -> 0.064107971 | AJ24: Ada kenaikan harga
A25: RUTIN | D25: TEMPAT SAMPAH | E25: =SUMIFS('PLAN BUDGET SAMI-TF'!AN12:AN99999,'PLAN BUDGET SAMI-TF'!D12:D99999,SUMMARY!D25,'PLAN BUDGET SAMI-TF'!J12:J99999,SUMMARY!A25&"*") -> 5 | F25: =SUMIFS('PLAN BUDGET SAMI-TF'!AO12:AO99999,'PLAN BUDGET SAMI-TF'!D12:D99999,SUMMARY!D25,'PLAN BUDGET SAMI-TF'!J12:J99999,SUMMARY!A25&"*") -> 5 | G25: =SUMIFS('PLAN BUDGET SAMI-TF'!AP12:AP99999,'PLAN BUDGET SAMI-TF'!D12:D99999,SUMMARY!D25,'PLAN BUDGET SAMI-TF'!J12:J99999,SUMMARY!A25&"*") -> 5 | H25: =SUMIFS('PLAN BUDGET SAMI-TF'!AQ12:AQ99999,'PLAN BUDGET SAMI-TF'!D12:D99999,SUMMARY!D25,'PLAN BUDGET SAMI-TF'!J12:J99999,SUMMARY!A25&"*") -> 6 | I25: =SUMIFS('PLAN BUDGET SAMI-TF'!AR12:AR99999,'PLAN BUDGET SAMI-TF'!D12:D99999,SUMMARY!D25,'PLAN BUDGET SAMI-TF'!J12:J99999,SUMMARY!A25&"*") -> 5 | J25: =SUMIFS('PLAN BUDGET SAMI-TF'!AS12:AS99999,'PLAN BUDGET SAMI-TF'!D12:D99999,SUMMARY!D25,'PLAN BUDGET SAMI-TF'!J12:J99999,SUMMARY!A25&"*") -> 5 | K25: =SUMIFS('PLAN BUDGET SAMI-TF'!AT12:AT99999,'PLAN BUDGET SAMI-TF'!D12:D99999,SUMMARY!D25,'PLAN BUDGET SAMI-TF'!J12:J99999,SUMMARY!A25&"*") -> 5 | L25: =SUMIFS('PLAN BUDGET SAMI-TF'!AU12:AU99999,'PLAN BUDGET SAMI-TF'!D12:D99999,SUMMARY!D25,'PLAN BUDGET SAMI-TF'!J12:J99999,SUMMARY!A25&"*") -> 6 | M25: =SUMIFS('PLAN BUDGET SAMI-TF'!AV12:AV99999,'PLAN BUDGET SAMI-TF'!D12:D99999,SUMMARY!D25,'PLAN BUDGET SAMI-TF'!J12:J99999,SUMMARY!A25&"*") -> 5 | N25: =SUMIFS('PLAN BUDGET SAMI-TF'!AW12:AW99999,'PLAN BUDGET SAMI-TF'!D12:D99999,SUMMARY!D25,'PLAN BUDGET SAMI-TF'!J12:J99999,SUMMARY!A25&"*") -> 5 | O25: =SUMIFS('PLAN BUDGET SAMI-TF'!AX12:AX99999,'PLAN BUDGET SAMI-TF'!D12:D99999,SUMMARY!D25,'PLAN BUDGET SAMI-TF'!J12:J99999,SUMMARY!A25&"*") -> 5 | P25: =SUMIFS('PLAN BUDGET SAMI-TF'!AY12:AY99999,'PLAN BUDGET SAMI-TF'!D12:D99999,SUMMARY!D25,'PLAN BUDGET SAMI-TF'!J12:J99999,SUMMARY!A25&"*") -> 6 | Q25: =SUMIFS('PLAN BUDGET SAMI-TF'!BC12:BC99999,'PLAN BUDGET SAMI-TF'!D12:D99999,SUMMARY!D25,'PLAN BUDGET SAMI-TF'!J12:J99999,SUMMARY!A25&"*") -> 24.329687 | R25: =SUMIFS('PLAN BUDGET SAMI-TF'!BD12:BD99999,'PLAN BUDGET SAMI-TF'!D12:D99999,SUMMARY!D25,'PLAN BUDGET SAMI-TF'!J12:J99999,SUMMARY!A25&"*") -> 24.329687 | S25: =SUMIFS('PLAN BUDGET SAMI-TF'!BE12:BE99999,'PLAN BUDGET SAMI-TF'!D12:D99999,SUMMARY!D25,'PLAN BUDGET SAMI-TF'!J12:J99999,SUMMARY!A25&"*") -> 24.329687 | T25: =SUMIFS('PLAN BUDGET SAMI-TF'!BF12:BF99999,'PLAN BUDGET SAMI-TF'!D12:D99999,SUMMARY!D25,'PLAN BUDGET SAMI-TF'!J12:J99999,SUMMARY!A25&"*") -> 26.438292 | U25: =SUMIFS('PLAN BUDGET SAMI-TF'!BG12:BG99999,'PLAN BUDGET SAMI-TF'!D12:D99999,SUMMARY!D25,'PLAN BUDGET SAMI-TF'!J12:J99999,SUMMARY!A25&"*") -> 24.329687 | V25: =SUMIFS('PLAN BUDGET SAMI-TF'!BH12:BH99999,'PLAN BUDGET SAMI-TF'!D12:D99999,SUMMARY!D25,'PLAN BUDGET SAMI-TF'!J12:J99999,SUMMARY!A25&"*") -> 24.329687 | W25: =SUMIFS('PLAN BUDGET SAMI-TF'!BI12:BI99999,'PLAN BUDGET SAMI-TF'!D12:D99999,SUMMARY!D25,'PLAN BUDGET SAMI-TF'!J12:J99999,SUMMARY!A25&"*") -> 24.329687 | X25: =SUMIFS('PLAN BUDGET SAMI-TF'!BJ12:BJ99999,'PLAN BUDGET SAMI-TF'!D12:D99999,SUMMARY!D25,'PLAN BUDGET SAMI-TF'!J12:J99999,SUMMARY!A25&"*") -> 26.438292 | Y25: =SUMIFS('PLAN BUDGET SAMI-TF'!BK12:BK99999,'PLAN BUDGET SAMI-TF'!D12:D99999,SUMMARY!D25,'PLAN BUDGET SAMI-TF'!J12:J99999,SUMMARY!A25&"*") -> 24.329687 | Z25: =SUMIFS('PLAN BUDGET SAMI-TF'!BL12:BL99999,'PLAN BUDGET SAMI-TF'!D12:D99999,SUMMARY!D25,'PLAN BUDGET SAMI-TF'!J12:J99999,SUMMARY!A25&"*") -> 24.329687 | AA25: =SUMIFS('PLAN BUDGET SAMI-TF'!BM12:BM99999,'PLAN BUDGET SAMI-TF'!D12:D99999,SUMMARY!D25,'PLAN BUDGET SAMI-TF'!J12:J99999,SUMMARY!A25&"*") -> 24.329687 | AB25: =SUMIFS('PLAN BUDGET SAMI-TF'!BN12:BN99999,'PLAN BUDGET SAMI-TF'!D12:D99999,SUMMARY!D25,'PLAN BUDGET SAMI-TF'!J12:J99999,SUMMARY!A25&"*") -> 26.438292 | AC25: =SUM(E25:P25) -> 63 | AD25: =SUM(Q25:AB25) -> 298.28206 | AF25: 11 | AG25: 44.888788 | AH25: =IFERROR((AC25-AF25)/AF25,1) -> 4.7272727 | AI25: =IFERROR((AD25-AG25)/AG25,1) -> 5.6449124 | AJ25: Di th 85 plan penggantian tempat sampah B3
A26: RUTIN | D26: GUNTING | E26: =SUMIFS('PLAN BUDGET SAMI-TF'!AN12:AN99999,'PLAN BUDGET SAMI-TF'!D12:D99999,SUMMARY!D26,'PLAN BUDGET SAMI-TF'!J12:J99999,SUMMARY!A26&"*") -> 0 | F26: =SUMIFS('PLAN BUDGET SAMI-TF'!AO12:AO99999,'PLAN BUDGET SAMI-TF'!D12:D99999,SUMMARY!D26,'PLAN BUDGET SAMI-TF'!J12:J99999,SUMMARY!A26&"*") -> 1 | G26: =SUMIFS('PLAN BUDGET SAMI-TF'!AP12:AP99999,'PLAN BUDGET SAMI-TF'!D12:D99999,SUMMARY!D26,'PLAN BUDGET SAMI-TF'!J12:J99999,SUMMARY!A26&"*") -> 0 | H26: =SUMIFS('PLAN BUDGET SAMI-TF'!AQ12:AQ99999,'PLAN BUDGET SAMI-TF'!D12:D99999,SUMMARY!D26,'PLAN BUDGET SAMI-TF'!J12:J99999,SUMMARY!A26&"*") -> 0 | I26: =SUMIFS('PLAN BUDGET SAMI-TF'!AR12:AR99999,'PLAN BUDGET SAMI-TF'!D12:D99999,SUMMARY!D26,'PLAN BUDGET SAMI-TF'!J12:J99999,SUMMARY!A26&"*") -> 0 | J26: =SUMIFS('PLAN BUDGET SAMI-TF'!AS12:AS99999,'PLAN BUDGET SAMI-TF'!D12:D99999,SUMMARY!D26,'PLAN BUDGET SAMI-TF'!J12:J99999,SUMMARY!A26&"*") -> 0 | K26: =SUMIFS('PLAN BUDGET SAMI-TF'!AT12:AT99999,'PLAN BUDGET SAMI-TF'!D12:D99999,SUMMARY!D26,'PLAN BUDGET SAMI-TF'!J12:J99999,SUMMARY!A26&"*") -> 0 | L26: =SUMIFS('PLAN BUDGET SAMI-TF'!AU12:AU99999,'PLAN BUDGET SAMI-TF'!D12:D99999,SUMMARY!D26,'PLAN BUDGET SAMI-TF'!J12:J99999,SUMMARY!A26&"*") -> 0 | M26: =SUMIFS('PLAN BUDGET SAMI-TF'!AV12:AV99999,'PLAN BUDGET SAMI-TF'!D12:D99999,SUMMARY!D26,'PLAN BUDGET SAMI-TF'!J12:J99999,SUMMARY!A26&"*") -> 0 | N26: =SUMIFS('PLAN BUDGET SAMI-TF'!AW12:AW99999,'PLAN BUDGET SAMI-TF'!D12:D99999,SUMMARY!D26,'PLAN BUDGET SAMI-TF'!J12:J99999,SUMMARY!A26&"*") -> 0 | O26: =SUMIFS('PLAN BUDGET SAMI-TF'!AX12:AX99999,'PLAN BUDGET SAMI-TF'!D12:D99999,SUMMARY!D26,'PLAN BUDGET SAMI-TF'!J12:J99999,SUMMARY!A26&"*") -> 0 | P26: =SUMIFS('PLAN BUDGET SAMI-TF'!AY12:AY99999,'PLAN BUDGET SAMI-TF'!D12:D99999,SUMMARY!D26,'PLAN BUDGET SAMI-TF'!J12:J99999,SUMMARY!A26&"*") -> 0 | Q26: =SUMIFS('PLAN BUDGET SAMI-TF'!BC12:BC99999,'PLAN BUDGET SAMI-TF'!D12:D99999,SUMMARY!D26,'PLAN BUDGET SAMI-TF'!J12:J99999,SUMMARY!A26&"*") -> 0 | R26: =SUMIFS('PLAN BUDGET SAMI-TF'!BD12:BD99999,'PLAN BUDGET SAMI-TF'!D12:D99999,SUMMARY!D26,'PLAN BUDGET SAMI-TF'!J12:J99999,SUMMARY!A26&"*") -> 0.61872571 | S26: =SUMIFS('PLAN BUDGET SAMI-TF'!BE12:BE99999,'PLAN BUDGET SAMI-TF'!D12:D99999,SUMMARY!D26,'PLAN BUDGET SAMI-TF'!J12:J99999,SUMMARY!A26&"*") -> 0 | T26: =SUMIFS('PLAN BUDGET SAMI-TF'!BF12:BF99999,'PLAN BUDGET SAMI-TF'!D12:D99999,SUMMARY!D26,'PLAN BUDGET SAMI-TF'!J12:J99999,SUMMARY!A26&"*") -> 0 | U26: =SUMIFS('PLAN BUDGET SAMI-TF'!BG12:BG99999,'PLAN BUDGET SAMI-TF'!D12:D99999,SUMMARY!D26,'PLAN BUDGET SAMI-TF'!J12:J99999,SUMMARY!A26&"*") -> 0 | V26: =SUMIFS('PLAN BUDGET SAMI-TF'!BH12:BH99999,'PLAN BUDGET SAMI-TF'!D12:D99999,SUMMARY!D26,'PLAN BUDGET SAMI-TF'!J12:J99999,SUMMARY!A26&"*") -> 0 | W26: =SUMIFS('PLAN BUDGET SAMI-TF'!BI12:BI99999,'PLAN BUDGET SAMI-TF'!D12:D99999,SUMMARY!D26,'PLAN BUDGET SAMI-TF'!J12:J99999,SUMMARY!A26&"*") -> 0 | X26: =SUMIFS('PLAN BUDGET SAMI-TF'!BJ12:BJ99999,'PLAN BUDGET SAMI-TF'!D12:D99999,SUMMARY!D26,'PLAN BUDGET SAMI-TF'!J12:J99999,SUMMARY!A26&"*") -> 0 | Y26: =SUMIFS('PLAN BUDGET SAMI-TF'!BK12:BK99999,'PLAN BUDGET SAMI-TF'!D12:D99999,SUMMARY!D26,'PLAN BUDGET SAMI-TF'!J12:J99999,SUMMARY!A26&"*") -> 0 | Z26: =SUMIFS('PLAN BUDGET SAMI-TF'!BL12:BL99999,'PLAN BUDGET SAMI-TF'!D12:D99999,SUMMARY!D26,'PLAN BUDGET SAMI-TF'!J12:J99999,SUMMARY!A26&"*") -> 0 | AA26: =SUMIFS('PLAN BUDGET SAMI-TF'!BM12:BM99999,'PLAN BUDGET SAMI-TF'!D12:D99999,SUMMARY!D26,'PLAN BUDGET SAMI-TF'!J12:J99999,SUMMARY!A26&"*") -> 0 | AB26: =SUMIFS('PLAN BUDGET SAMI-TF'!BN12:BN99999,'PLAN BUDGET SAMI-TF'!D12:D99999,SUMMARY!D26,'PLAN BUDGET SAMI-TF'!J12:J99999,SUMMARY!A26&"*") -> 0 | AC26: =SUM(E26:P26) -> 1 | AD26: =SUM(Q26:AB26) -> 0.61872571 | AF26: 2 | AG26: 1.1704835 | AH26: =IFERROR((AC26-AF26)/AF26,1) -> -0.5 | AI26: =IFERROR((AD26-AG26)/AG26,1) -> -0.47139303 | AJ26: Di th 85 penggantian gunting yang rusak saja
A27: RUTIN | D27: KEMOCENG | E27: =SUMIFS('PLAN BUDGET SAMI-TF'!AN12:AN99999,'PLAN BUDGET SAMI-TF'!D12:D99999,SUMMARY!D27,'PLAN BUDGET SAMI-TF'!J12:J99999,SUMMARY!A27&"*") -> 2 | F27: =SUMIFS('PLAN BUDGET SAMI-TF'!AO12:AO99999,'PLAN BUDGET SAMI-TF'!D12:D99999,SUMMARY!D27,'PLAN BUDGET SAMI-TF'!J12:J99999,SUMMARY!A27&"*") -> 2 | G27: =SUMIFS('PLAN BUDGET SAMI-TF'!AP12:AP99999,'PLAN BUDGET SAMI-TF'!D12:D99999,SUMMARY!D27,'PLAN BUDGET SAMI-TF'!J12:J99999,SUMMARY!A27&"*") -> 2 | H27: =SUMIFS('PLAN BUDGET SAMI-TF'!AQ12:AQ99999,'PLAN BUDGET SAMI-TF'!D12:D99999,SUMMARY!D27,'PLAN BUDGET SAMI-TF'!J12:J99999,SUMMARY!A27&"*") -> 2 | I27: =SUMIFS('PLAN BUDGET SAMI-TF'!AR12:AR99999,'PLAN BUDGET SAMI-TF'!D12:D99999,SUMMARY!D27,'PLAN BUDGET SAMI-TF'!J12:J99999,SUMMARY!A27&"*") -> 2 | J27: =SUMIFS('PLAN BUDGET SAMI-TF'!AS12:AS99999,'PLAN BUDGET SAMI-TF'!D12:D99999,SUMMARY!D27,'PLAN BUDGET SAMI-TF'!J12:J99999,SUMMARY!A27&"*") -> 2 | K27: =SUMIFS('PLAN BUDGET SAMI-TF'!AT12:AT99999,'PLAN BUDGET SAMI-TF'!D12:D99999,SUMMARY!D27,'PLAN BUDGET SAMI-TF'!J12:J99999,SUMMARY!A27&"*") -> 2 | L27: =SUMIFS('PLAN BUDGET SAMI-TF'!AU12:AU99999,'PLAN BUDGET SAMI-TF'!D12:D99999,SUMMARY!D27,'PLAN BUDGET SAMI-TF'!J12:J99999,SUMMARY!A27&"*") -> 2 | M27: =SUMIFS('PLAN BUDGET SAMI-TF'!AV12:AV99999,'PLAN BUDGET SAMI-TF'!D12:D99999,SUMMARY!D27,'PLAN BUDGET SAMI-TF'!J12:J99999,SUMMARY!A27&"*") -> 2 | N27: =SUMIFS('PLAN BUDGET SAMI-TF'!AW12:AW99999,'PLAN BUDGET SAMI-TF'!D12:D99999,SUMMARY!D27,'PLAN BUDGET SAMI-TF'!J12:J99999,SUMMARY!A27&"*") -> 2 | O27: =SUMIFS('PLAN BUDGET SAMI-TF'!AX12:AX99999,'PLAN BUDGET SAMI-TF'!D12:D99999,SUMMARY!D27,'PLAN BUDGET SAMI-TF'!J12:J99999,SUMMARY!A27&"*") -> 2 | P27: =SUMIFS('PLAN BUDGET SAMI-TF'!AY12:AY99999,'PLAN BUDGET SAMI-TF'!D12:D99999,SUMMARY!D27,'PLAN BUDGET SAMI-TF'!J12:J99999,SUMMARY!A27&"*") -> 2 | Q27: =SUMIFS('PLAN BUDGET SAMI-TF'!BC12:BC99999,'PLAN BUDGET SAMI-TF'!D12:D99999,SUMMARY!D27,'PLAN BUDGET SAMI-TF'!J12:J99999,SUMMARY!A27&"*") -> 1.946375 | R27: =SUMIFS('PLAN BUDGET SAMI-TF'!BD12:BD99999,'PLAN BUDGET SAMI-TF'!D12:D99999,SUMMARY!D27,'PLAN BUDGET SAMI-TF'!J12:J99999,SUMMARY!A27&"*") -> 1.946375 | S27: =SUMIFS('PLAN BUDGET SAMI-TF'!BE12:BE99999,'PLAN BUDGET SAMI-TF'!D12:D99999,SUMMARY!D27,'PLAN BUDGET SAMI-TF'!J12:J99999,SUMMARY!A27&"*") -> 1.946375 | T27: =SUMIFS('PLAN BUDGET SAMI-TF'!BF12:BF99999,'PLAN BUDGET SAMI-TF'!D12:D99999,SUMMARY!D27,'PLAN BUDGET SAMI-TF'!J12:J99999,SUMMARY!A27&"*") -> 1.946375 | U27: =SUMIFS('PLAN BUDGET SAMI-TF'!BG12:BG99999,'PLAN BUDGET SAMI-TF'!D12:D99999,SUMMARY!D27,'PLAN BUDGET SAMI-TF'!J12:J99999,SUMMARY!A27&"*") -> 1.946375 | V27: =SUMIFS('PLAN BUDGET SAMI-TF'!BH12:BH99999,'PLAN BUDGET SAMI-TF'!D12:D99999,SUMMARY!D27,'PLAN BUDGET SAMI-TF'!J12:J99999,SUMMARY!A27&"*") -> 1.946375 | W27: =SUMIFS('PLAN BUDGET SAMI-TF'!BI12:BI99999,'PLAN BUDGET SAMI-TF'!D12:D99999,SUMMARY!D27,'PLAN BUDGET SAMI-TF'!J12:J99999,SUMMARY!A27&"*") -> 1.946375 | X27: =SUMIFS('PLAN BUDGET SAMI-TF'!BJ12:BJ99999,'PLAN BUDGET SAMI-TF'!D12:D99999,SUMMARY!D27,'PLAN BUDGET SAMI-TF'!J12:J99999,SUMMARY!A27&"*") -> 1.946375 | Y27: =SUMIFS('PLAN BUDGET SAMI-TF'!BK12:BK99999,'PLAN BUDGET SAMI-TF'!D12:D99999,SUMMARY!D27,'PLAN BUDGET SAMI-TF'!J12:J99999,SUMMARY!A27&"*") -> 1.946375 | Z27: =SUMIFS('PLAN BUDGET SAMI-TF'!BL12:BL99999,'PLAN BUDGET SAMI-TF'!D12:D99999,SUMMARY!D27,'PLAN BUDGET SAMI-TF'!J12:J99999,SUMMARY!A27&"*") -> 1.946375 | AA27: =SUMIFS('PLAN BUDGET SAMI-TF'!BM12:BM99999,'PLAN BUDGET SAMI-TF'!D12:D99999,SUMMARY!D27,'PLAN BUDGET SAMI-TF'!J12:J99999,SUMMARY!A27&"*") -> 1.946375 | AB27: =SUMIFS('PLAN BUDGET SAMI-TF'!BN12:BN99999,'PLAN BUDGET SAMI-TF'!D12:D99999,SUMMARY!D27,'PLAN BUDGET SAMI-TF'!J12:J99999,SUMMARY!A27&"*") -> 1.946375 | AC27: =SUM(E27:P27) -> 24 | AD27: =SUM(Q27:AB27) -> 23.3565 | AF27: 24 | AG27: 23.090654 | AH27: =IFERROR((AC27-AF27)/AF27,1) -> 0 | AI27: =IFERROR((AD27-AG27)/AG27,1) -> 0.011513158 | AJ27: Ada kenaikan harga
A28: RUTIN | D28: LAKBAN | E28: =SUMIFS('PLAN BUDGET SAMI-TF'!AN12:AN99999,'PLAN BUDGET SAMI-TF'!D12:D99999,SUMMARY!D28,'PLAN BUDGET SAMI-TF'!J12:J99999,SUMMARY!A28&"*") -> 0 | F28: =SUMIFS('PLAN BUDGET SAMI-TF'!AO12:AO99999,'PLAN BUDGET SAMI-TF'!D12:D99999,SUMMARY!D28,'PLAN BUDGET SAMI-TF'!J12:J99999,SUMMARY!A28&"*") -> 1 | G28: =SUMIFS('PLAN BUDGET SAMI-TF'!AP12:AP99999,'PLAN BUDGET SAMI-TF'!D12:D99999,SUMMARY!D28,'PLAN BUDGET SAMI-TF'!J12:J99999,SUMMARY!A28&"*") -> 0 | H28: =SUMIFS('PLAN BUDGET SAMI-TF'!AQ12:AQ99999,'PLAN BUDGET SAMI-TF'!D12:D99999,SUMMARY!D28,'PLAN BUDGET SAMI-TF'!J12:J99999,SUMMARY!A28&"*") -> 1 | I28: =SUMIFS('PLAN BUDGET SAMI-TF'!AR12:AR99999,'PLAN BUDGET SAMI-TF'!D12:D99999,SUMMARY!D28,'PLAN BUDGET SAMI-TF'!J12:J99999,SUMMARY!A28&"*") -> 0 | J28: =SUMIFS('PLAN BUDGET SAMI-TF'!AS12:AS99999,'PLAN BUDGET SAMI-TF'!D12:D99999,SUMMARY!D28,'PLAN BUDGET SAMI-TF'!J12:J99999,SUMMARY!A28&"*") -> 1 | K28: =SUMIFS('PLAN BUDGET SAMI-TF'!AT12:AT99999,'PLAN BUDGET SAMI-TF'!D12:D99999,SUMMARY!D28,'PLAN BUDGET SAMI-TF'!J12:J99999,SUMMARY!A28&"*") -> 0 | L28: =SUMIFS('PLAN BUDGET SAMI-TF'!AU12:AU99999,'PLAN BUDGET SAMI-TF'!D12:D99999,SUMMARY!D28,'PLAN BUDGET SAMI-TF'!J12:J99999,SUMMARY!A28&"*") -> 1 | M28: =SUMIFS('PLAN BUDGET SAMI-TF'!AV12:AV99999,'PLAN BUDGET SAMI-TF'!D12:D99999,SUMMARY!D28,'PLAN BUDGET SAMI-TF'!J12:J99999,SUMMARY!A28&"*") -> 0 | N28: =SUMIFS('PLAN BUDGET SAMI-TF'!AW12:AW99999,'PLAN BUDGET SAMI-TF'!D12:D99999,SUMMARY!D28,'PLAN BUDGET SAMI-TF'!J12:J99999,SUMMARY!A28&"*") -> 1 | O28: =SUMIFS('PLAN BUDGET SAMI-TF'!AX12:AX99999,'PLAN BUDGET SAMI-TF'!D12:D99999,SUMMARY!D28,'PLAN BUDGET SAMI-TF'!J12:J99999,SUMMARY!A28&"*") -> 0 | P28: =SUMIFS('PLAN BUDGET SAMI-TF'!AY12:AY99999,'PLAN BUDGET SAMI-TF'!D12:D99999,SUMMARY!D28,'PLAN BUDGET SAMI-TF'!J12:J99999,SUMMARY!A28&"*") -> 1 | Q28: =SUMIFS('PLAN BUDGET SAMI-TF'!BC12:BC99999,'PLAN BUDGET SAMI-TF'!D12:D99999,SUMMARY!D28,'PLAN BUDGET SAMI-TF'!J12:J99999,SUMMARY!A28&"*") -> 0 | R28: =SUMIFS('PLAN BUDGET SAMI-TF'!BD12:BD99999,'PLAN BUDGET SAMI-TF'!D12:D99999,SUMMARY!D28,'PLAN BUDGET SAMI-TF'!J12:J99999,SUMMARY!A28&"*") -> 0.51552986 | S28: =SUMIFS('PLAN BUDGET SAMI-TF'!BE12:BE99999,'PLAN BUDGET SAMI-TF'!D12:D99999,SUMMARY!D28,'PLAN BUDGET SAMI-TF'!J12:J99999,SUMMARY!A28&"*") -> 0 | T28: =SUMIFS('PLAN BUDGET SAMI-TF'!BF12:BF99999,'PLAN BUDGET SAMI-TF'!D12:D99999,SUMMARY!D28,'PLAN BUDGET SAMI-TF'!J12:J99999,SUMMARY!A28&"*") -> 0.51552986 | U28: =SUMIFS('PLAN BUDGET SAMI-TF'!BG12:BG99999,'PLAN BUDGET SAMI-TF'!D12:D99999,SUMMARY!D28,'PLAN BUDGET SAMI-TF'!J12:J99999,SUMMARY!A28&"*") -> 0 | V28: =SUMIFS('PLAN BUDGET SAMI-TF'!BH12:BH99999,'PLAN BUDGET SAMI-TF'!D12:D99999,SUMMARY!D28,'PLAN BUDGET SAMI-TF'!J12:J99999,SUMMARY!A28&"*") -> 0.51552986 | W28: =SUMIFS('PLAN BUDGET SAMI-TF'!BI12:BI99999,'PLAN BUDGET SAMI-TF'!D12:D99999,SUMMARY!D28,'PLAN BUDGET SAMI-TF'!J12:J99999,SUMMARY!A28&"*") -> 0 | X28: =SUMIFS('PLAN BUDGET SAMI-TF'!BJ12:BJ99999,'PLAN BUDGET SAMI-TF'!D12:D99999,SUMMARY!D28,'PLAN BUDGET SAMI-TF'!J12:J99999,SUMMARY!A28&"*") -> 0.51552986 | Y28: =SUMIFS('PLAN BUDGET SAMI-TF'!BK12:BK99999,'PLAN BUDGET SAMI-TF'!D12:D99999,SUMMARY!D28,'PLAN BUDGET SAMI-TF'!J12:J99999,SUMMARY!A28&"*") -> 0 | Z28: =SUMIFS('PLAN BUDGET SAMI-TF'!BL12:BL99999,'PLAN BUDGET SAMI-TF'!D12:D99999,SUMMARY!D28,'PLAN BUDGET SAMI-TF'!J12:J99999,SUMMARY!A28&"*") -> 0.51552986 | AA28: =SUMIFS('PLAN BUDGET SAMI-TF'!BM12:BM99999,'PLAN BUDGET SAMI-TF'!D12:D99999,SUMMARY!D28,'PLAN BUDGET SAMI-TF'!J12:J99999,SUMMARY!A28&"*") -> 0 | AB28: =SUMIFS('PLAN BUDGET SAMI-TF'!BN12:BN99999,'PLAN BUDGET SAMI-TF'!D12:D99999,SUMMARY!D28,'PLAN BUDGET SAMI-TF'!J12:J99999,SUMMARY!A28&"*") -> 0.51552986 | AC28: =SUM(E28:P28) -> 6 | AD28: =SUM(Q28:AB28) -> 3.0931791 | AF28: 6 | AG28: 2.9140557 | AH28: =IFERROR((AC28-AF28)/AF28,1) -> 0 | AI28: =IFERROR((AD28-AG28)/AG28,1) -> 0.061468787 | AJ28: Ada kenaikan harga
A29: RUTIN | D29: LIQUID | E29: =SUMIFS('PLAN BUDGET SAMI-TF'!AN12:AN99999,'PLAN BUDGET SAMI-TF'!D12:D99999,SUMMARY!D29,'PLAN BUDGET SAMI-TF'!J12:J99999,SUMMARY!A29&"*") -> 0 | F29: =SUMIFS('PLAN BUDGET SAMI-TF'!AO12:AO99999,'PLAN BUDGET SAMI-TF'!D12:D99999,SUMMARY!D29,'PLAN BUDGET SAMI-TF'!J12:J99999,SUMMARY!A29&"*") -> 0 | G29: =SUMIFS('PLAN BUDGET SAMI-TF'!AP12:AP99999,'PLAN BUDGET SAMI-TF'!D12:D99999,SUMMARY!D29,'PLAN BUDGET SAMI-TF'!J12:J99999,SUMMARY!A29&"*") -> 0 | H29: =SUMIFS('PLAN BUDGET SAMI-TF'!AQ12:AQ99999,'PLAN BUDGET SAMI-TF'!D12:D99999,SUMMARY!D29,'PLAN BUDGET SAMI-TF'!J12:J99999,SUMMARY!A29&"*") -> 0 | I29: =SUMIFS('PLAN BUDGET SAMI-TF'!AR12:AR99999,'PLAN BUDGET SAMI-TF'!D12:D99999,SUMMARY!D29,'PLAN BUDGET SAMI-TF'!J12:J99999,SUMMARY!A29&"*") -> 0 | J29: =SUMIFS('PLAN BUDGET SAMI-TF'!AS12:AS99999,'PLAN BUDGET SAMI-TF'!D12:D99999,SUMMARY!D29,'PLAN BUDGET SAMI-TF'!J12:J99999,SUMMARY!A29&"*") -> 0 | K29: =SUMIFS('PLAN BUDGET SAMI-TF'!AT12:AT99999,'PLAN BUDGET SAMI-TF'!D12:D99999,SUMMARY!D29,'PLAN BUDGET SAMI-TF'!J12:J99999,SUMMARY!A29&"*") -> 0 | L29: =SUMIFS('PLAN BUDGET SAMI-TF'!AU12:AU99999,'PLAN BUDGET SAMI-TF'!D12:D99999,SUMMARY!D29,'PLAN BUDGET SAMI-TF'!J12:J99999,SUMMARY!A29&"*") -> 0 | M29: =SUMIFS('PLAN BUDGET SAMI-TF'!AV12:AV99999,'PLAN BUDGET SAMI-TF'!D12:D99999,SUMMARY!D29,'PLAN BUDGET SAMI-TF'!J12:J99999,SUMMARY!A29&"*") -> 5 | N29: =SUMIFS('PLAN BUDGET SAMI-TF'!AW12:AW99999,'PLAN BUDGET SAMI-TF'!D12:D99999,SUMMARY!D29,'PLAN BUDGET SAMI-TF'!J12:J99999,SUMMARY!A29&"*") -> 0 | O29: =SUMIFS('PLAN BUDGET SAMI-TF'!AX12:AX99999,'PLAN BUDGET SAMI-TF'!D12:D99999,SUMMARY!D29,'PLAN BUDGET SAMI-TF'!J12:J99999,SUMMARY!A29&"*") -> 0 | P29: =SUMIFS('PLAN BUDGET SAMI-TF'!AY12:AY99999,'PLAN BUDGET SAMI-TF'!D12:D99999,SUMMARY!D29,'PLAN BUDGET SAMI-TF'!J12:J99999,SUMMARY!A29&"*") -> 0 | Q29: =SUMIFS('PLAN BUDGET SAMI-TF'!BC12:BC99999,'PLAN BUDGET SAMI-TF'!D12:D99999,SUMMARY!D29,'PLAN BUDGET SAMI-TF'!J12:J99999,SUMMARY!A29&"*") -> 0 | R29: =SUMIFS('PLAN BUDGET SAMI-TF'!BD12:BD99999,'PLAN BUDGET SAMI-TF'!D12:D99999,SUMMARY!D29,'PLAN BUDGET SAMI-TF'!J12:J99999,SUMMARY!A29&"*") -> 0 | S29: =SUMIFS('PLAN BUDGET SAMI-TF'!BE12:BE99999,'PLAN BUDGET SAMI-TF'!D12:D99999,SUMMARY!D29,'PLAN BUDGET SAMI-TF'!J12:J99999,SUMMARY!A29&"*") -> 0 | T29: =SUMIFS('PLAN BUDGET SAMI-TF'!BF12:BF99999,'PLAN BUDGET SAMI-TF'!D12:D99999,SUMMARY!D29,'PLAN BUDGET SAMI-TF'!J12:J99999,SUMMARY!A29&"*") -> 0 | U29: =SUMIFS('PLAN BUDGET SAMI-TF'!BG12:BG99999,'PLAN BUDGET SAMI-TF'!D12:D99999,SUMMARY!D29,'PLAN BUDGET SAMI-TF'!J12:J99999,SUMMARY!A29&"*") -> 0 | V29: =SUMIFS('PLAN BUDGET SAMI-TF'!BH12:BH99999,'PLAN BUDGET SAMI-TF'!D12:D99999,SUMMARY!D29,'PLAN BUDGET SAMI-TF'!J12:J99999,SUMMARY!A29&"*") -> 0 | W29: =SUMIFS('PLAN BUDGET SAMI-TF'!BI12:BI99999,'PLAN BUDGET SAMI-TF'!D12:D99999,SUMMARY!D29,'PLAN BUDGET SAMI-TF'!J12:J99999,SUMMARY!A29&"*") -> 0 | X29: =SUMIFS('PLAN BUDGET SAMI-TF'!BJ12:BJ99999,'PLAN BUDGET SAMI-TF'!D12:D99999,SUMMARY!D29,'PLAN BUDGET SAMI-TF'!J12:J99999,SUMMARY!A29&"*") -> 0 | Y29: =SUMIFS('PLAN BUDGET SAMI-TF'!BK12:BK99999,'PLAN BUDGET SAMI-TF'!D12:D99999,SUMMARY!D29,'PLAN BUDGET SAMI-TF'!J12:J99999,SUMMARY!A29&"*") -> 147.16494 | Z29: =SUMIFS('PLAN BUDGET SAMI-TF'!BL12:BL99999,'PLAN BUDGET SAMI-TF'!D12:D99999,SUMMARY!D29,'PLAN BUDGET SAMI-TF'!J12:J99999,SUMMARY!A29&"*") -> 0 | AA29: =SUMIFS('PLAN BUDGET SAMI-TF'!BM12:BM99999,'PLAN BUDGET SAMI-TF'!D12:D99999,SUMMARY!D29,'PLAN BUDGET SAMI-TF'!J12:J99999,SUMMARY!A29&"*") -> 0 | AB29: =SUMIFS('PLAN BUDGET SAMI-TF'!BN12:BN99999,'PLAN BUDGET SAMI-TF'!D12:D99999,SUMMARY!D29,'PLAN BUDGET SAMI-TF'!J12:J99999,SUMMARY!A29&"*") -> 0 | AC29: =SUM(E29:P29) -> 5 | AD29: =SUM(Q29:AB29) -> 147.16494 | AF29: 5 | AG29: 120.02962 | AH29: =IFERROR((AC29-AF29)/AF29,1) -> 0 | AI29: =IFERROR((AD29-AG29)/AG29,1) -> 0.22607182 | AJ29: Ada kenaikan harga
A30: RUTIN | D30: LOCAL TRANSPORT PD | E30: =SUMIFS('PLAN BUDGET SAMI-TF'!AN12:AN99999,'PLAN BUDGET SAMI-TF'!D12:D99999,SUMMARY!D30,'PLAN BUDGET SAMI-TF'!J12:J99999,SUMMARY!A30&"*") -> 0 | F30: =SUMIFS('PLAN BUDGET SAMI-TF'!AO12:AO99999,'PLAN BUDGET SAMI-TF'!D12:D99999,SUMMARY!D30,'PLAN BUDGET SAMI-TF'!J12:J99999,SUMMARY!A30&"*") -> 0 | G30: =SUMIFS('PLAN BUDGET SAMI-TF'!AP12:AP99999,'PLAN BUDGET SAMI-TF'!D12:D99999,SUMMARY!D30,'PLAN BUDGET SAMI-TF'!J12:J99999,SUMMARY!A30&"*") -> 0 | H30: =SUMIFS('PLAN BUDGET SAMI-TF'!AQ12:AQ99999,'PLAN BUDGET SAMI-TF'!D12:D99999,SUMMARY!D30,'PLAN BUDGET SAMI-TF'!J12:J99999,SUMMARY!A30&"*") -> 0 | I30: =SUMIFS('PLAN BUDGET SAMI-TF'!AR12:AR99999,'PLAN BUDGET SAMI-TF'!D12:D99999,SUMMARY!D30,'PLAN BUDGET SAMI-TF'!J12:J99999,SUMMARY!A30&"*") -> 12 | J30: =SUMIFS('PLAN BUDGET SAMI-TF'!AS12:AS99999,'PLAN BUDGET SAMI-TF'!D12:D99999,SUMMARY!D30,'PLAN BUDGET SAMI-TF'!J12:J99999,SUMMARY!A30&"*") -> 0 | K30: =SUMIFS('PLAN BUDGET SAMI-TF'!AT12:AT99999,'PLAN BUDGET SAMI-TF'!D12:D99999,SUMMARY!D30,'PLAN BUDGET SAMI-TF'!J12:J99999,SUMMARY!A30&"*") -> 0 | L30: =SUMIFS('PLAN BUDGET SAMI-TF'!AU12:AU99999,'PLAN BUDGET SAMI-TF'!D12:D99999,SUMMARY!D30,'PLAN BUDGET SAMI-TF'!J12:J99999,SUMMARY!A30&"*") -> 0 | M30: =SUMIFS('PLAN BUDGET SAMI-TF'!AV12:AV99999,'PLAN BUDGET SAMI-TF'!D12:D99999,SUMMARY!D30,'PLAN BUDGET SAMI-TF'!J12:J99999,SUMMARY!A30&"*") -> 0 | N30: =SUMIFS('PLAN BUDGET SAMI-TF'!AW12:AW99999,'PLAN BUDGET SAMI-TF'!D12:D99999,SUMMARY!D30,'PLAN BUDGET SAMI-TF'!J12:J99999,SUMMARY!A30&"*") -> 0 | O30: =SUMIFS('PLAN BUDGET SAMI-TF'!AX12:AX99999,'PLAN BUDGET SAMI-TF'!D12:D99999,SUMMARY!D30,'PLAN BUDGET SAMI-TF'!J12:J99999,SUMMARY!A30&"*") -> 0 | P30: =SUMIFS('PLAN BUDGET SAMI-TF'!AY12:AY99999,'PLAN BUDGET SAMI-TF'!D12:D99999,SUMMARY!D30,'PLAN BUDGET SAMI-TF'!J12:J99999,SUMMARY!A30&"*") -> 0 | Q30: =SUMIFS('PLAN BUDGET SAMI-TF'!BC12:BC99999,'PLAN BUDGET SAMI-TF'!D12:D99999,SUMMARY!D30,'PLAN BUDGET SAMI-TF'!J12:J99999,SUMMARY!A30&"*") -> 0 | R30: =SUMIFS('PLAN BUDGET SAMI-TF'!BD12:BD99999,'PLAN BUDGET SAMI-TF'!D12:D99999,SUMMARY!D30,'PLAN BUDGET SAMI-TF'!J12:J99999,SUMMARY!A30&"*") -> 0 | S30: =SUMIFS('PLAN BUDGET SAMI-TF'!BE12:BE99999,'PLAN BUDGET SAMI-TF'!D12:D99999,SUMMARY!D30,'PLAN BUDGET SAMI-TF'!J12:J99999,SUMMARY!A30&"*") -> 0 | T30: =SUMIFS('PLAN BUDGET SAMI-TF'!BF12:BF99999,'PLAN BUDGET SAMI-TF'!D12:D99999,SUMMARY!D30,'PLAN BUDGET SAMI-TF'!J12:J99999,SUMMARY!A30&"*") -> 0 | U30: =SUMIFS('PLAN BUDGET SAMI-TF'!BG12:BG99999,'PLAN BUDGET SAMI-TF'!D12:D99999,SUMMARY!D30,'PLAN BUDGET SAMI-TF'!J12:J99999,SUMMARY!A30&"*") -> 227.86829 | V30: =SUMIFS('PLAN BUDGET SAMI-TF'!BH12:BH99999,'PLAN BUDGET SAMI-TF'!D12:D99999,SUMMARY!D30,'PLAN BUDGET SAMI-TF'!J12:J99999,SUMMARY!A30&"*") -> 0 | W30: =SUMIFS('PLAN BUDGET SAMI-TF'!BI12:BI99999,'PLAN BUDGET SAMI-TF'!D12:D99999,SUMMARY!D30,'PLAN BUDGET SAMI-TF'!J12:J99999,SUMMARY!A30&"*") -> 0 | X30: =SUMIFS('PLAN BUDGET SAMI-TF'!BJ12:BJ99999,'PLAN BUDGET SAMI-TF'!D12:D99999,SUMMARY!D30,'PLAN BUDGET SAMI-TF'!J12:J99999,SUMMARY!A30&"*") -> 0 | Y30: =SUMIFS('PLAN BUDGET SAMI-TF'!BK12:BK99999,'PLAN BUDGET SAMI-TF'!D12:D99999,SUMMARY!D30,'PLAN BUDGET SAMI-TF'!J12:J99999,SUMMARY!A30&"*") -> 0 | Z30: =SUMIFS('PLAN BUDGET SAMI-TF'!BL12:BL99999,'PLAN BUDGET SAMI-TF'!D12:D99999,SUMMARY!D30,'PLAN BUDGET SAMI-TF'!J12:J99999,SUMMARY!A30&"*") -> 0 | AA30: =SUMIFS('PLAN BUDGET SAMI-TF'!BM12:BM99999,'PLAN BUDGET SAMI-TF'!D12:D99999,SUMMARY!D30,'PLAN BUDGET SAMI-TF'!J12:J99999,SUMMARY!A30&"*") -> 0 | AB30: =SUMIFS('PLAN BUDGET SAMI-TF'!BN12:BN99999,'PLAN BUDGET SAMI-TF'!D12:D99999,SUMMARY!D30,'PLAN BUDGET SAMI-TF'!J12:J99999,SUMMARY!A30&"*") -> 0 | AC30: =SUM(E30:P30) -> 12 | AD30: =SUM(Q30:AB30) -> 227.86829 | AF30: 12 | AG30: 142.05298 | AH30: =IFERROR((AC30-AF30)/AF30,1) -> 0 | AI30: =IFERROR((AD30-AG30)/AG30,1) -> 0.60410779 | AJ30: Ada kenaikan harga
A31: RUTIN | D31: PERJALANAN DINAS LUAR NEGERI | E31: =SUMIFS('PLAN BUDGET SAMI-TF'!AN12:AN99999,'PLAN BUDGET SAMI-TF'!D12:D99999,SUMMARY!D31,'PLAN BUDGET SAMI-TF'!J12:J99999,SUMMARY!A31&"*") -> 0 | F31: =SUMIFS('PLAN BUDGET SAMI-TF'!AO12:AO99999,'PLAN BUDGET SAMI-TF'!D12:D99999,SUMMARY!D31,'PLAN BUDGET SAMI-TF'!J12:J99999,SUMMARY!A31&"*") -> 0 | G31: =SUMIFS('PLAN BUDGET SAMI-TF'!AP12:AP99999,'PLAN BUDGET SAMI-TF'!D12:D99999,SUMMARY!D31,'PLAN BUDGET SAMI-TF'!J12:J99999,SUMMARY!A31&"*") -> 2 | H31: =SUMIFS('PLAN BUDGET SAMI-TF'!AQ12:AQ99999,'PLAN BUDGET SAMI-TF'!D12:D99999,SUMMARY!D31,'PLAN BUDGET SAMI-TF'!J12:J99999,SUMMARY!A31&"*") -> 0 | I31: =SUMIFS('PLAN BUDGET SAMI-TF'!AR12:AR99999,'PLAN BUDGET SAMI-TF'!D12:D99999,SUMMARY!D31,'PLAN BUDGET SAMI-TF'!J12:J99999,SUMMARY!A31&"*") -> 0 | J31: =SUMIFS('PLAN BUDGET SAMI-TF'!AS12:AS99999,'PLAN BUDGET SAMI-TF'!D12:D99999,SUMMARY!D31,'PLAN BUDGET SAMI-TF'!J12:J99999,SUMMARY!A31&"*") -> 0 | K31: =SUMIFS('PLAN BUDGET SAMI-TF'!AT12:AT99999,'PLAN BUDGET SAMI-TF'!D12:D99999,SUMMARY!D31,'PLAN BUDGET SAMI-TF'!J12:J99999,SUMMARY!A31&"*") -> 0 | L31: =SUMIFS('PLAN BUDGET SAMI-TF'!AU12:AU99999,'PLAN BUDGET SAMI-TF'!D12:D99999,SUMMARY!D31,'PLAN BUDGET SAMI-TF'!J12:J99999,SUMMARY!A31&"*") -> 0 | M31: =SUMIFS('PLAN BUDGET SAMI-TF'!AV12:AV99999,'PLAN BUDGET SAMI-TF'!D12:D99999,SUMMARY!D31,'PLAN BUDGET SAMI-TF'!J12:J99999,SUMMARY!A31&"*") -> 0 | N31: =SUMIFS('PLAN BUDGET SAMI-TF'!AW12:AW99999,'PLAN BUDGET SAMI-TF'!D12:D99999,SUMMARY!D31,'PLAN BUDGET SAMI-TF'!J12:J99999,SUMMARY!A31&"*") -> 0 | O31: =SUMIFS('PLAN BUDGET SAMI-TF'!AX12:AX99999,'PLAN BUDGET SAMI-TF'!D12:D99999,SUMMARY!D31,'PLAN BUDGET SAMI-TF'!J12:J99999,SUMMARY!A31&"*") -> 0 | P31: =SUMIFS('PLAN BUDGET SAMI-TF'!AY12:AY99999,'PLAN BUDGET SAMI-TF'!D12:D99999,SUMMARY!D31,'PLAN BUDGET SAMI-TF'!J12:J99999,SUMMARY!A31&"*") -> 0 | Q31: =SUMIFS('PLAN BUDGET SAMI-TF'!BC12:BC99999,'PLAN BUDGET SAMI-TF'!D12:D99999,SUMMARY!D31,'PLAN BUDGET SAMI-TF'!J12:J99999,SUMMARY!A31&"*") -> 0 | R31: =SUMIFS('PLAN BUDGET SAMI-TF'!BD12:BD99999,'PLAN BUDGET SAMI-TF'!D12:D99999,SUMMARY!D31,'PLAN BUDGET SAMI-TF'!J12:J99999,SUMMARY!A31&"*") -> 0 | S31: =SUMIFS('PLAN BUDGET SAMI-TF'!BE12:BE99999,'PLAN BUDGET SAMI-TF'!D12:D99999,SUMMARY!D31,'PLAN BUDGET SAMI-TF'!J12:J99999,SUMMARY!A31&"*") -> 64.879167 | T31: =SUMIFS('PLAN BUDGET SAMI-TF'!BF12:BF99999,'PLAN BUDGET SAMI-TF'!D12:D99999,SUMMARY!D31,'PLAN BUDGET SAMI-TF'!J12:J99999,SUMMARY!A31&"*") -> 0 | U31: =SUMIFS('PLAN BUDGET SAMI-TF'!BG12:BG99999,'PLAN BUDGET SAMI-TF'!D12:D99999,SUMMARY!D31,'PLAN BUDGET SAMI-TF'!J12:J99999,SUMMARY!A31&"*") -> 0 | V31: =SUMIFS('PLAN BUDGET SAMI-TF'!BH12:BH99999,'PLAN BUDGET SAMI-TF'!D12:D99999,SUMMARY!D31,'PLAN BUDGET SAMI-TF'!J12:J99999,SUMMARY!A31&"*") -> 0 | W31: =SUMIFS('PLAN BUDGET SAMI-TF'!BI12:BI99999,'PLAN BUDGET SAMI-TF'!D12:D99999,SUMMARY!D31,'PLAN BUDGET SAMI-TF'!J12:J99999,SUMMARY!A31&"*") -> 0 | X31: =SUMIFS('PLAN BUDGET SAMI-TF'!BJ12:BJ99999,'PLAN BUDGET SAMI-TF'!D12:D99999,SUMMARY!D31,'PLAN BUDGET SAMI-TF'!J12:J99999,SUMMARY!A31&"*") -> 0 | Y31: =SUMIFS('PLAN BUDGET SAMI-TF'!BK12:BK99999,'PLAN BUDGET SAMI-TF'!D12:D99999,SUMMARY!D31,'PLAN BUDGET SAMI-TF'!J12:J99999,SUMMARY!A31&"*") -> 0 | Z31: =SUMIFS('PLAN BUDGET SAMI-TF'!BL12:BL99999,'PLAN BUDGET SAMI-TF'!D12:D99999,SUMMARY!D31,'PLAN BUDGET SAMI-TF'!J12:J99999,SUMMARY!A31&"*") -> 0 | AA31: =SUMIFS('PLAN BUDGET SAMI-TF'!BM12:BM99999,'PLAN BUDGET SAMI-TF'!D12:D99999,SUMMARY!D31,'PLAN BUDGET SAMI-TF'!J12:J99999,SUMMARY!A31&"*") -> 0 | AB31: =SUMIFS('PLAN BUDGET SAMI-TF'!BN12:BN99999,'PLAN BUDGET SAMI-TF'!D12:D99999,SUMMARY!D31,'PLAN BUDGET SAMI-TF'!J12:J99999,SUMMARY!A31&"*") -> 0 | AC31: =SUM(E31:P31) -> 2 | AD31: =SUM(Q31:AB31) -> 64.879167 | AF31: 2 | AG31: 50.700695 | AH31: =IFERROR((AC31-AF31)/AF31,1) -> 0 | AI31: =IFERROR((AD31-AG31)/AG31,1) -> 0.27965044 | AJ31: Ada kenaikan harga
A32: RUTIN | D32: POST IT | E32: =SUMIFS('PLAN BUDGET SAMI-TF'!AN12:AN99999,'PLAN BUDGET SAMI-TF'!D12:D99999,SUMMARY!D32,'PLAN BUDGET SAMI-TF'!J12:J99999,SUMMARY!A32&"*") -> 0 | F32: =SUMIFS('PLAN BUDGET SAMI-TF'!AO12:AO99999,'PLAN BUDGET SAMI-TF'!D12:D99999,SUMMARY!D32,'PLAN BUDGET SAMI-TF'!J12:J99999,SUMMARY!A32&"*") -> 0 | G32: =SUMIFS('PLAN BUDGET SAMI-TF'!AP12:AP99999,'PLAN BUDGET SAMI-TF'!D12:D99999,SUMMARY!D32,'PLAN BUDGET SAMI-TF'!J12:J99999,SUMMARY!A32&"*") -> 1 | H32: =SUMIFS('PLAN BUDGET SAMI-TF'!AQ12:AQ99999,'PLAN BUDGET SAMI-TF'!D12:D99999,SUMMARY!D32,'PLAN BUDGET SAMI-TF'!J12:J99999,SUMMARY!A32&"*") -> 0 | I32: =SUMIFS('PLAN BUDGET SAMI-TF'!AR12:AR99999,'PLAN BUDGET SAMI-TF'!D12:D99999,SUMMARY!D32,'PLAN BUDGET SAMI-TF'!J12:J99999,SUMMARY!A32&"*") -> 0 | J32: =SUMIFS('PLAN BUDGET SAMI-TF'!AS12:AS99999,'PLAN BUDGET SAMI-TF'!D12:D99999,SUMMARY!D32,'PLAN BUDGET SAMI-TF'!J12:J99999,SUMMARY!A32&"*") -> 1 | K32: =SUMIFS('PLAN BUDGET SAMI-TF'!AT12:AT99999,'PLAN BUDGET SAMI-TF'!D12:D99999,SUMMARY!D32,'PLAN BUDGET SAMI-TF'!J12:J99999,SUMMARY!A32&"*") -> 0 | L32: =SUMIFS('PLAN BUDGET SAMI-TF'!AU12:AU99999,'PLAN BUDGET SAMI-TF'!D12:D99999,SUMMARY!D32,'PLAN BUDGET SAMI-TF'!J12:J99999,SUMMARY!A32&"*") -> 0 | M32: =SUMIFS('PLAN BUDGET SAMI-TF'!AV12:AV99999,'PLAN BUDGET SAMI-TF'!D12:D99999,SUMMARY!D32,'PLAN BUDGET SAMI-TF'!J12:J99999,SUMMARY!A32&"*") -> 0 | N32: =SUMIFS('PLAN BUDGET SAMI-TF'!AW12:AW99999,'PLAN BUDGET SAMI-TF'!D12:D99999,SUMMARY!D32,'PLAN BUDGET SAMI-TF'!J12:J99999,SUMMARY!A32&"*") -> 0 | O32: =SUMIFS('PLAN BUDGET SAMI-TF'!AX12:AX99999,'PLAN BUDGET SAMI-TF'!D12:D99999,SUMMARY!D32,'PLAN BUDGET SAMI-TF'!J12:J99999,SUMMARY!A32&"*") -> 0 | P32: =SUMIFS('PLAN BUDGET SAMI-TF'!AY12:AY99999,'PLAN BUDGET SAMI-TF'!D12:D99999,SUMMARY!D32,'PLAN BUDGET SAMI-TF'!J12:J99999,SUMMARY!A32&"*") -> 0 | Q32: =SUMIFS('PLAN BUDGET SAMI-TF'!BC12:BC99999,'PLAN BUDGET SAMI-TF'!D12:D99999,SUMMARY!D32,'PLAN BUDGET SAMI-TF'!J12:J99999,SUMMARY!A32&"*") -> 0 | R32: =SUMIFS('PLAN BUDGET SAMI-TF'!BD12:BD99999,'PLAN BUDGET SAMI-TF'!D12:D99999,SUMMARY!D32,'PLAN BUDGET SAMI-TF'!J12:J99999,SUMMARY!A32&"*") -> 0 | S32: =SUMIFS('PLAN BUDGET SAMI-TF'!BE12:BE99999,'PLAN BUDGET SAMI-TF'!D12:D99999,SUMMARY!D32,'PLAN BUDGET SAMI-TF'!J12:J99999,SUMMARY!A32&"*") -> 0.33927057 | T32: =SUMIFS('PLAN BUDGET SAMI-TF'!BF12:BF99999,'PLAN BUDGET SAMI-TF'!D12:D99999,SUMMARY!D32,'PLAN BUDGET SAMI-TF'!J12:J99999,SUMMARY!A32&"*") -> 0 | U32: =SUMIFS('PLAN BUDGET SAMI-TF'!BG12:BG99999,'PLAN BUDGET SAMI-TF'!D12:D99999,SUMMARY!D32,'PLAN BUDGET SAMI-TF'!J12:J99999,SUMMARY!A32&"*") -> 0 | V32: =SUMIFS('PLAN BUDGET SAMI-TF'!BH12:BH99999,'PLAN BUDGET SAMI-TF'!D12:D99999,SUMMARY!D32,'PLAN BUDGET SAMI-TF'!J12:J99999,SUMMARY!A32&"*") -> 0.33927057 | W32: =SUMIFS('PLAN BUDGET SAMI-TF'!BI12:BI99999,'PLAN BUDGET SAMI-TF'!D12:D99999,SUMMARY!D32,'PLAN BUDGET SAMI-TF'!J12:J99999,SUMMARY!A32&"*") -> 0 | X32: =SUMIFS('PLAN BUDGET SAMI-TF'!BJ12:BJ99999,'PLAN BUDGET SAMI-TF'!D12:D99999,SUMMARY!D32,'PLAN BUDGET SAMI-TF'!J12:J99999,SUMMARY!A32&"*") -> 0 | Y32: =SUMIFS('PLAN BUDGET SAMI-TF'!BK12:BK99999,'PLAN BUDGET SAMI-TF'!D12:D99999,SUMMARY!D32,'PLAN BUDGET SAMI-TF'!J12:J99999,SUMMARY!A32&"*") -> 0 | Z32: =SUMIFS('PLAN BUDGET SAMI-TF'!BL12:BL99999,'PLAN BUDGET SAMI-TF'!D12:D99999,SUMMARY!D32,'PLAN BUDGET SAMI-TF'!J12:J99999,SUMMARY!A32&"*") -> 0 | AA32: =SUMIFS('PLAN BUDGET SAMI-TF'!BM12:BM99999,'PLAN BUDGET SAMI-TF'!D12:D99999,SUMMARY!D32,'PLAN BUDGET SAMI-TF'!J12:J99999,SUMMARY!A32&"*") -> 0 | AB32: =SUMIFS('PLAN BUDGET SAMI-TF'!BN12:BN99999,'PLAN BUDGET SAMI-TF'!D12:D99999,SUMMARY!D32,'PLAN BUDGET SAMI-TF'!J12:J99999,SUMMARY!A32&"*") -> 0 | AC32: =SUM(E32:P32) -> 2 | AD32: =SUM(Q32:AB32) -> 0.67854114 | AF32: 2 | AG32: 0.6422088 | AH32: =IFERROR((AC32-AF32)/AF32,1) -> 0 | AI32: =IFERROR((AD32-AG32)/AG32,1) -> 0.056574019 | AJ32: Ada kenaikan harga
A33: RUTIN | D33: REWARD | E33: =SUMIFS('PLAN BUDGET SAMI-TF'!AN12:AN99999,'PLAN BUDGET SAMI-TF'!D12:D99999,SUMMARY!D33,'PLAN BUDGET SAMI-TF'!J12:J99999,SUMMARY!A33&"*") -> 102 | F33: =SUMIFS('PLAN BUDGET SAMI-TF'!AO12:AO99999,'PLAN BUDGET SAMI-TF'!D12:D99999,SUMMARY!D33,'PLAN BUDGET SAMI-TF'!J12:J99999,SUMMARY!A33&"*") -> 185 | G33: =SUMIFS('PLAN BUDGET SAMI-TF'!AP12:AP99999,'PLAN BUDGET SAMI-TF'!D12:D99999,SUMMARY!D33,'PLAN BUDGET SAMI-TF'!J12:J99999,SUMMARY!A33&"*") -> 2927 | H33: =SUMIFS('PLAN BUDGET SAMI-TF'!AQ12:AQ99999,'PLAN BUDGET SAMI-TF'!D12:D99999,SUMMARY!D33,'PLAN BUDGET SAMI-TF'!J12:J99999,SUMMARY!A33&"*") -> 101 | I33: =SUMIFS('PLAN BUDGET SAMI-TF'!AR12:AR99999,'PLAN BUDGET SAMI-TF'!D12:D99999,SUMMARY!D33,'PLAN BUDGET SAMI-TF'!J12:J99999,SUMMARY!A33&"*") -> 95 | J33: =SUMIFS('PLAN BUDGET SAMI-TF'!AS12:AS99999,'PLAN BUDGET SAMI-TF'!D12:D99999,SUMMARY!D33,'PLAN BUDGET SAMI-TF'!J12:J99999,SUMMARY!A33&"*") -> 95 | K33: =SUMIFS('PLAN BUDGET SAMI-TF'!AT12:AT99999,'PLAN BUDGET SAMI-TF'!D12:D99999,SUMMARY!D33,'PLAN BUDGET SAMI-TF'!J12:J99999,SUMMARY!A33&"*") -> 101 | L33: =SUMIFS('PLAN BUDGET SAMI-TF'!AU12:AU99999,'PLAN BUDGET SAMI-TF'!D12:D99999,SUMMARY!D33,'PLAN BUDGET SAMI-TF'!J12:J99999,SUMMARY!A33&"*") -> 185 | M33: =SUMIFS('PLAN BUDGET SAMI-TF'!AV12:AV99999,'PLAN BUDGET SAMI-TF'!D12:D99999,SUMMARY!D33,'PLAN BUDGET SAMI-TF'!J12:J99999,SUMMARY!A33&"*") -> 2900 | N33: =SUMIFS('PLAN BUDGET SAMI-TF'!AW12:AW99999,'PLAN BUDGET SAMI-TF'!D12:D99999,SUMMARY!D33,'PLAN BUDGET SAMI-TF'!J12:J99999,SUMMARY!A33&"*") -> 101 | O33: =SUMIFS('PLAN BUDGET SAMI-TF'!AX12:AX99999,'PLAN BUDGET SAMI-TF'!D12:D99999,SUMMARY!D33,'PLAN BUDGET SAMI-TF'!J12:J99999,SUMMARY!A33&"*") -> 182 | P33: =SUMIFS('PLAN BUDGET SAMI-TF'!AY12:AY99999,'PLAN BUDGET SAMI-TF'!D12:D99999,SUMMARY!D33,'PLAN BUDGET SAMI-TF'!J12:J99999,SUMMARY!A33&"*") -> 95 | Q33: =SUMIFS('PLAN BUDGET SAMI-TF'!BC12:BC99999,'PLAN BUDGET SAMI-TF'!D12:D99999,SUMMARY!D33,'PLAN BUDGET SAMI-TF'!J12:J99999,SUMMARY!A33&"*") -> 228.22434 | R33: =SUMIFS('PLAN BUDGET SAMI-TF'!BD12:BD99999,'PLAN BUDGET SAMI-TF'!D12:D99999,SUMMARY!D33,'PLAN BUDGET SAMI-TF'!J12:J99999,SUMMARY!A33&"*") -> 366.36949 | S33: =SUMIFS('PLAN BUDGET SAMI-TF'!BE12:BE99999,'PLAN BUDGET SAMI-TF'!D12:D99999,SUMMARY!D33,'PLAN BUDGET SAMI-TF'!J12:J99999,SUMMARY!A33&"*") -> 2824.6886 | T33: =SUMIFS('PLAN BUDGET SAMI-TF'!BF12:BF99999,'PLAN BUDGET SAMI-TF'!D12:D99999,SUMMARY!D33,'PLAN BUDGET SAMI-TF'!J12:J99999,SUMMARY!A33&"*") -> 209.23531 | U33: =SUMIFS('PLAN BUDGET SAMI-TF'!BG12:BG99999,'PLAN BUDGET SAMI-TF'!D12:D99999,SUMMARY!D33,'PLAN BUDGET SAMI-TF'!J12:J99999,SUMMARY!A33&"*") -> 131.38031 | V33: =SUMIFS('PLAN BUDGET SAMI-TF'!BH12:BH99999,'PLAN BUDGET SAMI-TF'!D12:D99999,SUMMARY!D33,'PLAN BUDGET SAMI-TF'!J12:J99999,SUMMARY!A33&"*") -> 131.38031 | W33: =SUMIFS('PLAN BUDGET SAMI-TF'!BI12:BI99999,'PLAN BUDGET SAMI-TF'!D12:D99999,SUMMARY!D33,'PLAN BUDGET SAMI-TF'!J12:J99999,SUMMARY!A33&"*") -> 209.23531 | X33: =SUMIFS('PLAN BUDGET SAMI-TF'!BJ12:BJ99999,'PLAN BUDGET SAMI-TF'!D12:D99999,SUMMARY!D33,'PLAN BUDGET SAMI-TF'!J12:J99999,SUMMARY!A33&"*") -> 366.36949 | Y33: =SUMIFS('PLAN BUDGET SAMI-TF'!BK12:BK99999,'PLAN BUDGET SAMI-TF'!D12:D99999,SUMMARY!D33,'PLAN BUDGET SAMI-TF'!J12:J99999,SUMMARY!A33&"*") -> 2656.4775 | Z33: =SUMIFS('PLAN BUDGET SAMI-TF'!BL12:BL99999,'PLAN BUDGET SAMI-TF'!D12:D99999,SUMMARY!D33,'PLAN BUDGET SAMI-TF'!J12:J99999,SUMMARY!A33&"*") -> 209.23531 | AA33: =SUMIFS('PLAN BUDGET SAMI-TF'!BM12:BM99999,'PLAN BUDGET SAMI-TF'!D12:D99999,SUMMARY!D33,'PLAN BUDGET SAMI-TF'!J12:J99999,SUMMARY!A33&"*") -> 579.04656 | AB33: =SUMIFS('PLAN BUDGET SAMI-TF'!BN12:BN99999,'PLAN BUDGET SAMI-TF'!D12:D99999,SUMMARY!D33,'PLAN BUDGET SAMI-TF'!J12:J99999,SUMMARY!A33&"*") -> 131.38031 | AC33: =SUM(E33:P33) -> 7069 | AD33: =SUM(Q33:AB33) -> 8043.0228 | AF33: 5223 | AG33: 5977.7449 | AH33: =IFERROR((AC33-AF33)/AF33,1) -> 0.35343672 | AI33: =IFERROR((AD33-AG33)/AG33,1) -> 0.34549449 | AJ33: Di th 85 ada penambahan reward baru untuk skill kontes IL 2, penambahan qty untuk reward finish story
A34: RUTIN | D34: TRAINING MAGANG JEPANG | E34: =SUMIFS('PLAN BUDGET SAMI-TF'!AN12:AN99999,'PLAN BUDGET SAMI-TF'!D12:D99999,SUMMARY!D34,'PLAN BUDGET SAMI-TF'!J12:J99999,SUMMARY!A34&"*") -> 28 | F34: =SUMIFS('PLAN BUDGET SAMI-TF'!AO12:AO99999,'PLAN BUDGET SAMI-TF'!D12:D99999,SUMMARY!D34,'PLAN BUDGET SAMI-TF'!J12:J99999,SUMMARY!A34&"*") -> 20 | G34: =SUMIFS('PLAN BUDGET SAMI-TF'!AP12:AP99999,'PLAN BUDGET SAMI-TF'!D12:D99999,SUMMARY!D34,'PLAN BUDGET SAMI-TF'!J12:J99999,SUMMARY!A34&"*") -> 1 | H34: =SUMIFS('PLAN BUDGET SAMI-TF'!AQ12:AQ99999,'PLAN BUDGET SAMI-TF'!D12:D99999,SUMMARY!D34,'PLAN BUDGET SAMI-TF'!J12:J99999,SUMMARY!A34&"*") -> 15 | I34: =SUMIFS('PLAN BUDGET SAMI-TF'!AR12:AR99999,'PLAN BUDGET SAMI-TF'!D12:D99999,SUMMARY!D34,'PLAN BUDGET SAMI-TF'!J12:J99999,SUMMARY!A34&"*") -> 6 | J34: =SUMIFS('PLAN BUDGET SAMI-TF'!AS12:AS99999,'PLAN BUDGET SAMI-TF'!D12:D99999,SUMMARY!D34,'PLAN BUDGET SAMI-TF'!J12:J99999,SUMMARY!A34&"*") -> 24 | K34: =SUMIFS('PLAN BUDGET SAMI-TF'!AT12:AT99999,'PLAN BUDGET SAMI-TF'!D12:D99999,SUMMARY!D34,'PLAN BUDGET SAMI-TF'!J12:J99999,SUMMARY!A34&"*") -> 27 | L34: =SUMIFS('PLAN BUDGET SAMI-TF'!AU12:AU99999,'PLAN BUDGET SAMI-TF'!D12:D99999,SUMMARY!D34,'PLAN BUDGET SAMI-TF'!J12:J99999,SUMMARY!A34&"*") -> 5 | M34: =SUMIFS('PLAN BUDGET SAMI-TF'!AV12:AV99999,'PLAN BUDGET SAMI-TF'!D12:D99999,SUMMARY!D34,'PLAN BUDGET SAMI-TF'!J12:J99999,SUMMARY!A34&"*") -> 6 | N34: =SUMIFS('PLAN BUDGET SAMI-TF'!AW12:AW99999,'PLAN BUDGET SAMI-TF'!D12:D99999,SUMMARY!D34,'PLAN BUDGET SAMI-TF'!J12:J99999,SUMMARY!A34&"*") -> 0 | O34: =SUMIFS('PLAN BUDGET SAMI-TF'!AX12:AX99999,'PLAN BUDGET SAMI-TF'!D12:D99999,SUMMARY!D34,'PLAN BUDGET SAMI-TF'!J12:J99999,SUMMARY!A34&"*") -> 1 | P34: =SUMIFS('PLAN BUDGET SAMI-TF'!AY12:AY99999,'PLAN BUDGET SAMI-TF'!D12:D99999,SUMMARY!D34,'PLAN BUDGET SAMI-TF'!J12:J99999,SUMMARY!A34&"*") -> 0 | Q34: =SUMIFS('PLAN BUDGET SAMI-TF'!BC12:BC99999,'PLAN BUDGET SAMI-TF'!D12:D99999,SUMMARY!D34,'PLAN BUDGET SAMI-TF'!J12:J99999,SUMMARY!A34&"*") -> 1366.5271 | R34: =SUMIFS('PLAN BUDGET SAMI-TF'!BD12:BD99999,'PLAN BUDGET SAMI-TF'!D12:D99999,SUMMARY!D34,'PLAN BUDGET SAMI-TF'!J12:J99999,SUMMARY!A34&"*") -> 324.39583 | S34: =SUMIFS('PLAN BUDGET SAMI-TF'!BE12:BE99999,'PLAN BUDGET SAMI-TF'!D12:D99999,SUMMARY!D34,'PLAN BUDGET SAMI-TF'!J12:J99999,SUMMARY!A34&"*") -> 64.879167 | T34: =SUMIFS('PLAN BUDGET SAMI-TF'!BF12:BF99999,'PLAN BUDGET SAMI-TF'!D12:D99999,SUMMARY!D34,'PLAN BUDGET SAMI-TF'!J12:J99999,SUMMARY!A34&"*") -> 162.19792 | U34: =SUMIFS('PLAN BUDGET SAMI-TF'!BG12:BG99999,'PLAN BUDGET SAMI-TF'!D12:D99999,SUMMARY!D34,'PLAN BUDGET SAMI-TF'!J12:J99999,SUMMARY!A34&"*") -> 51.903333 | V34: =SUMIFS('PLAN BUDGET SAMI-TF'!BH12:BH99999,'PLAN BUDGET SAMI-TF'!D12:D99999,SUMMARY!D34,'PLAN BUDGET SAMI-TF'!J12:J99999,SUMMARY!A34&"*") -> 324.39583 | W34: =SUMIFS('PLAN BUDGET SAMI-TF'!BI12:BI99999,'PLAN BUDGET SAMI-TF'!D12:D99999,SUMMARY!D34,'PLAN BUDGET SAMI-TF'!J12:J99999,SUMMARY!A34&"*") -> 793.55814 | X34: =SUMIFS('PLAN BUDGET SAMI-TF'!BJ12:BJ99999,'PLAN BUDGET SAMI-TF'!D12:D99999,SUMMARY!D34,'PLAN BUDGET SAMI-TF'!J12:J99999,SUMMARY!A34&"*") -> 0 | Y34: =SUMIFS('PLAN BUDGET SAMI-TF'!BK12:BK99999,'PLAN BUDGET SAMI-TF'!D12:D99999,SUMMARY!D34,'PLAN BUDGET SAMI-TF'!J12:J99999,SUMMARY!A34&"*") -> 0 | Z34: =SUMIFS('PLAN BUDGET SAMI-TF'!BL12:BL99999,'PLAN BUDGET SAMI-TF'!D12:D99999,SUMMARY!D34,'PLAN BUDGET SAMI-TF'!J12:J99999,SUMMARY!A34&"*") -> 0 | AA34: =SUMIFS('PLAN BUDGET SAMI-TF'!BM12:BM99999,'PLAN BUDGET SAMI-TF'!D12:D99999,SUMMARY!D34,'PLAN BUDGET SAMI-TF'!J12:J99999,SUMMARY!A34&"*") -> 162.19792 | AB34: =SUMIFS('PLAN BUDGET SAMI-TF'!BN12:BN99999,'PLAN BUDGET SAMI-TF'!D12:D99999,SUMMARY!D34,'PLAN BUDGET SAMI-TF'!J12:J99999,SUMMARY!A34&"*") -> 0 | AC34: =SUM(E34:P34) -> 133 | AD34: =SUM(Q34:AB34) -> 3250.0552 | AF34: 49 | AG34: 2318.6754 | AH34: =IFERROR((AC34-AF34)/AF34,1) -> 1.7142857 | AI34: =IFERROR((AD34-AG34)/AG34,1) -> 0.40168616 | AJ34: Di th 85 part name training magang Jepang digunakan untuk magang Jepang operator, management & developmen
A35: RUTIN | D35: FORM | E35: =SUMIFS('PLAN BUDGET SAMI-TF'!AN12:AN99999,'PLAN BUDGET SAMI-TF'!D12:D99999,SUMMARY!D35,'PLAN BUDGET SAMI-TF'!J12:J99999,SUMMARY!A35&"*") -> 0 | F35: =SUMIFS('PLAN BUDGET SAMI-TF'!AO12:AO99999,'PLAN BUDGET SAMI-TF'!D12:D99999,SUMMARY!D35,'PLAN BUDGET SAMI-TF'!J12:J99999,SUMMARY!A35&"*") -> 0 | G35: =SUMIFS('PLAN BUDGET SAMI-TF'!AP12:AP99999,'PLAN BUDGET SAMI-TF'!D12:D99999,SUMMARY!D35,'PLAN BUDGET SAMI-TF'!J12:J99999,SUMMARY!A35&"*") -> 2 | H35: =SUMIFS('PLAN BUDGET SAMI-TF'!AQ12:AQ99999,'PLAN BUDGET SAMI-TF'!D12:D99999,SUMMARY!D35,'PLAN BUDGET SAMI-TF'!J12:J99999,SUMMARY!A35&"*") -> 1 | I35: =SUMIFS('PLAN BUDGET SAMI-TF'!AR12:AR99999,'PLAN BUDGET SAMI-TF'!D12:D99999,SUMMARY!D35,'PLAN BUDGET SAMI-TF'!J12:J99999,SUMMARY!A35&"*") -> 0 | J35: =SUMIFS('PLAN BUDGET SAMI-TF'!AS12:AS99999,'PLAN BUDGET SAMI-TF'!D12:D99999,SUMMARY!D35,'PLAN BUDGET SAMI-TF'!J12:J99999,SUMMARY!A35&"*") -> 0 | K35: =SUMIFS('PLAN BUDGET SAMI-TF'!AT12:AT99999,'PLAN BUDGET SAMI-TF'!D12:D99999,SUMMARY!D35,'PLAN BUDGET SAMI-TF'!J12:J99999,SUMMARY!A35&"*") -> 0 | L35: =SUMIFS('PLAN BUDGET SAMI-TF'!AU12:AU99999,'PLAN BUDGET SAMI-TF'!D12:D99999,SUMMARY!D35,'PLAN BUDGET SAMI-TF'!J12:J99999,SUMMARY!A35&"*") -> 0 | M35: =SUMIFS('PLAN BUDGET SAMI-TF'!AV12:AV99999,'PLAN BUDGET SAMI-TF'!D12:D99999,SUMMARY!D35,'PLAN BUDGET SAMI-TF'!J12:J99999,SUMMARY!A35&"*") -> 0 | N35: =SUMIFS('PLAN BUDGET SAMI-TF'!AW12:AW99999,'PLAN BUDGET SAMI-TF'!D12:D99999,SUMMARY!D35,'PLAN BUDGET SAMI-TF'!J12:J99999,SUMMARY!A35&"*") -> 1 | O35: =SUMIFS('PLAN BUDGET SAMI-TF'!AX12:AX99999,'PLAN BUDGET SAMI-TF'!D12:D99999,SUMMARY!D35,'PLAN BUDGET SAMI-TF'!J12:J99999,SUMMARY!A35&"*") -> 0 | P35: =SUMIFS('PLAN BUDGET SAMI-TF'!AY12:AY99999,'PLAN BUDGET SAMI-TF'!D12:D99999,SUMMARY!D35,'PLAN BUDGET SAMI-TF'!J12:J99999,SUMMARY!A35&"*") -> 0 | Q35: =SUMIFS('PLAN BUDGET SAMI-TF'!BC12:BC99999,'PLAN BUDGET SAMI-TF'!D12:D99999,SUMMARY!D35,'PLAN BUDGET SAMI-TF'!J12:J99999,SUMMARY!A35&"*") -> 0 | R35: =SUMIFS('PLAN BUDGET SAMI-TF'!BD12:BD99999,'PLAN BUDGET SAMI-TF'!D12:D99999,SUMMARY!D35,'PLAN BUDGET SAMI-TF'!J12:J99999,SUMMARY!A35&"*") -> 0 | S35: =SUMIFS('PLAN BUDGET SAMI-TF'!BE12:BE99999,'PLAN BUDGET SAMI-TF'!D12:D99999,SUMMARY!D35,'PLAN BUDGET SAMI-TF'!J12:J99999,SUMMARY!A35&"*") -> 25.318699 | T35: =SUMIFS('PLAN BUDGET SAMI-TF'!BF12:BF99999,'PLAN BUDGET SAMI-TF'!D12:D99999,SUMMARY!D35,'PLAN BUDGET SAMI-TF'!J12:J99999,SUMMARY!A35&"*") -> 12.65935 | U35: =SUMIFS('PLAN BUDGET SAMI-TF'!BG12:BG99999,'PLAN BUDGET SAMI-TF'!D12:D99999,SUMMARY!D35,'PLAN BUDGET SAMI-TF'!J12:J99999,SUMMARY!A35&"*") -> 0 | V35: =SUMIFS('PLAN BUDGET SAMI-TF'!BH12:BH99999,'PLAN BUDGET SAMI-TF'!D12:D99999,SUMMARY!D35,'PLAN BUDGET SAMI-TF'!J12:J99999,SUMMARY!A35&"*") -> 0 | W35: =SUMIFS('PLAN BUDGET SAMI-TF'!BI12:BI99999,'PLAN BUDGET SAMI-TF'!D12:D99999,SUMMARY!D35,'PLAN BUDGET SAMI-TF'!J12:J99999,SUMMARY!A35&"*") -> 0 | X35: =SUMIFS('PLAN BUDGET SAMI-TF'!BJ12:BJ99999,'PLAN BUDGET SAMI-TF'!D12:D99999,SUMMARY!D35,'PLAN BUDGET SAMI-TF'!J12:J99999,SUMMARY!A35&"*") -> 0 | Y35: =SUMIFS('PLAN BUDGET SAMI-TF'!BK12:BK99999,'PLAN BUDGET SAMI-TF'!D12:D99999,SUMMARY!D35,'PLAN BUDGET SAMI-TF'!J12:J99999,SUMMARY!A35&"*") -> 0 | Z35: =SUMIFS('PLAN BUDGET SAMI-TF'!BL12:BL99999,'PLAN BUDGET SAMI-TF'!D12:D99999,SUMMARY!D35,'PLAN BUDGET SAMI-TF'!J12:J99999,SUMMARY!A35&"*") -> 12.65935 | AA35: =SUMIFS('PLAN BUDGET SAMI-TF'!BM12:BM99999,'PLAN BUDGET SAMI-TF'!D12:D99999,SUMMARY!D35,'PLAN BUDGET SAMI-TF'!J12:J99999,SUMMARY!A35&"*") -> 0 | AB35: =SUMIFS('PLAN BUDGET SAMI-TF'!BN12:BN99999,'PLAN BUDGET SAMI-TF'!D12:D99999,SUMMARY!D35,'PLAN BUDGET SAMI-TF'!J12:J99999,SUMMARY!A35&"*") -> 0 | AC35: =SUM(E35:P35) -> 4 | AD35: =SUM(Q35:AB35) -> 50.637398 | AF35: 3 | AG35: 37.978049 | AH35: =IFERROR((AC35-AF35)/AF35,1) -> 0.33333333 | AI35: =IFERROR((AD35-AG35)/AG35,1) -> 0.33333333 | AJ35: Di th 85 penambahan form daftar hadir QCC
A36: RUTIN | D36: ISI BALLPOINT | E36: =SUMIFS('PLAN BUDGET SAMI-TF'!AN12:AN99999,'PLAN BUDGET SAMI-TF'!D12:D99999,SUMMARY!D36,'PLAN BUDGET SAMI-TF'!J12:J99999,SUMMARY!A36&"*") -> 0 | F36: =SUMIFS('PLAN BUDGET SAMI-TF'!AO12:AO99999,'PLAN BUDGET SAMI-TF'!D12:D99999,SUMMARY!D36,'PLAN BUDGET SAMI-TF'!J12:J99999,SUMMARY!A36&"*") -> 0 | G36: =SUMIFS('PLAN BUDGET SAMI-TF'!AP12:AP99999,'PLAN BUDGET SAMI-TF'!D12:D99999,SUMMARY!D36,'PLAN BUDGET SAMI-TF'!J12:J99999,SUMMARY!A36&"*") -> 12 | H36: =SUMIFS('PLAN BUDGET SAMI-TF'!AQ12:AQ99999,'PLAN BUDGET SAMI-TF'!D12:D99999,SUMMARY!D36,'PLAN BUDGET SAMI-TF'!J12:J99999,SUMMARY!A36&"*") -> 0 | I36: =SUMIFS('PLAN BUDGET SAMI-TF'!AR12:AR99999,'PLAN BUDGET SAMI-TF'!D12:D99999,SUMMARY!D36,'PLAN BUDGET SAMI-TF'!J12:J99999,SUMMARY!A36&"*") -> 0 | J36: =SUMIFS('PLAN BUDGET SAMI-TF'!AS12:AS99999,'PLAN BUDGET SAMI-TF'!D12:D99999,SUMMARY!D36,'PLAN BUDGET SAMI-TF'!J12:J99999,SUMMARY!A36&"*") -> 12 | K36: =SUMIFS('PLAN BUDGET SAMI-TF'!AT12:AT99999,'PLAN BUDGET SAMI-TF'!D12:D99999,SUMMARY!D36,'PLAN BUDGET SAMI-TF'!J12:J99999,SUMMARY!A36&"*") -> 0 | L36: =SUMIFS('PLAN BUDGET SAMI-TF'!AU12:AU99999,'PLAN BUDGET SAMI-TF'!D12:D99999,SUMMARY!D36,'PLAN BUDGET SAMI-TF'!J12:J99999,SUMMARY!A36&"*") -> 0 | M36: =SUMIFS('PLAN BUDGET SAMI-TF'!AV12:AV99999,'PLAN BUDGET SAMI-TF'!D12:D99999,SUMMARY!D36,'PLAN BUDGET SAMI-TF'!J12:J99999,SUMMARY!A36&"*") -> 12 | N36: =SUMIFS('PLAN BUDGET SAMI-TF'!AW12:AW99999,'PLAN BUDGET SAMI-TF'!D12:D99999,SUMMARY!D36,'PLAN BUDGET SAMI-TF'!J12:J99999,SUMMARY!A36&"*") -> 0 | O36: =SUMIFS('PLAN BUDGET SAMI-TF'!AX12:AX99999,'PLAN BUDGET SAMI-TF'!D12:D99999,SUMMARY!D36,'PLAN BUDGET SAMI-TF'!J12:J99999,SUMMARY!A36&"*") -> 0 | P36: =SUMIFS('PLAN BUDGET SAMI-TF'!AY12:AY99999,'PLAN BUDGET SAMI-TF'!D12:D99999,SUMMARY!D36,'PLAN BUDGET SAMI-TF'!J12:J99999,SUMMARY!A36&"*") -> 6 | Q36: =SUMIFS('PLAN BUDGET SAMI-TF'!BC12:BC99999,'PLAN BUDGET SAMI-TF'!D12:D99999,SUMMARY!D36,'PLAN BUDGET SAMI-TF'!J12:J99999,SUMMARY!A36&"*") -> 0 | R36: =SUMIFS('PLAN BUDGET SAMI-TF'!BD12:BD99999,'PLAN BUDGET SAMI-TF'!D12:D99999,SUMMARY!D36,'PLAN BUDGET SAMI-TF'!J12:J99999,SUMMARY!A36&"*") -> 0 | S36: =SUMIFS('PLAN BUDGET SAMI-TF'!BE12:BE99999,'PLAN BUDGET SAMI-TF'!D12:D99999,SUMMARY!D36,'PLAN BUDGET SAMI-TF'!J12:J99999,SUMMARY!A36&"*") -> 0.68436444 | T36: =SUMIFS('PLAN BUDGET SAMI-TF'!BF12:BF99999,'PLAN BUDGET SAMI-TF'!D12:D99999,SUMMARY!D36,'PLAN BUDGET SAMI-TF'!J12:J99999,SUMMARY!A36&"*") -> 0 | U36: =SUMIFS('PLAN BUDGET SAMI-TF'!BG12:BG99999,'PLAN BUDGET SAMI-TF'!D12:D99999,SUMMARY!D36,'PLAN BUDGET SAMI-TF'!J12:J99999,SUMMARY!A36&"*") -> 0 | V36: =SUMIFS('PLAN BUDGET SAMI-TF'!BH12:BH99999,'PLAN BUDGET SAMI-TF'!D12:D99999,SUMMARY!D36,'PLAN BUDGET SAMI-TF'!J12:J99999,SUMMARY!A36&"*") -> 0.68436444 | W36: =SUMIFS('PLAN BUDGET SAMI-TF'!BI12:BI99999,'PLAN BUDGET SAMI-TF'!D12:D99999,SUMMARY!D36,'PLAN BUDGET SAMI-TF'!J12:J99999,SUMMARY!A36&"*") -> 0 | X36: =SUMIFS('PLAN BUDGET SAMI-TF'!BJ12:BJ99999,'PLAN BUDGET SAMI-TF'!D12:D99999,SUMMARY!D36,'PLAN BUDGET SAMI-TF'!J12:J99999,SUMMARY!A36&"*") -> 0 | Y36: =SUMIFS('PLAN BUDGET SAMI-TF'!BK12:BK99999,'PLAN BUDGET SAMI-TF'!D12:D99999,SUMMARY!D36,'PLAN BUDGET SAMI-TF'!J12:J99999,SUMMARY!A36&"*") -> 0.68436444 | Z36: =SUMIFS('PLAN BUDGET SAMI-TF'!BL12:BL99999,'PLAN BUDGET SAMI-TF'!D12:D99999,SUMMARY!D36,'PLAN BUDGET SAMI-TF'!J12:J99999,SUMMARY!A36&"*") -> 0 | AA36: =SUMIFS('PLAN BUDGET SAMI-TF'!BM12:BM99999,'PLAN BUDGET SAMI-TF'!D12:D99999,SUMMARY!D36,'PLAN BUDGET SAMI-TF'!J12:J99999,SUMMARY!A36&"*") -> 0 | AB36: =SUMIFS('PLAN BUDGET SAMI-TF'!BN12:BN99999,'PLAN BUDGET SAMI-TF'!D12:D99999,SUMMARY!D36,'PLAN BUDGET SAMI-TF'!J12:J99999,SUMMARY!A36&"*") -> 0.34218222 | AC36: =SUM(E36:P36) -> 42 | AD36: =SUM(Q36:AB36) -> 2.3952755 | AF36: 42 | AG36: 2.2361475 | AH36: =IFERROR((AC36-AF36)/AF36,1) -> 0 | AI36: =IFERROR((AD36-AG36)/AG36,1) -> 0.071161685 | AJ36: Ada kenaikan harga
A37: RUTIN | D37: LOCAL TRANSPORT | E37: =SUMIFS('PLAN BUDGET SAMI-TF'!AN12:AN99999,'PLAN BUDGET SAMI-TF'!D12:D99999,SUMMARY!D37,'PLAN BUDGET SAMI-TF'!J12:J99999,SUMMARY!A37&"*") -> 0 | F37: =SUMIFS('PLAN BUDGET SAMI-TF'!AO12:AO99999,'PLAN BUDGET SAMI-TF'!D12:D99999,SUMMARY!D37,'PLAN BUDGET SAMI-TF'!J12:J99999,SUMMARY!A37&"*") -> 0 | G37: =SUMIFS('PLAN BUDGET SAMI-TF'!AP12:AP99999,'PLAN BUDGET SAMI-TF'!D12:D99999,SUMMARY!D37,'PLAN BUDGET SAMI-TF'!J12:J99999,SUMMARY!A37&"*") -> 14 | H37: =SUMIFS('PLAN BUDGET SAMI-TF'!AQ12:AQ99999,'PLAN BUDGET SAMI-TF'!D12:D99999,SUMMARY!D37,'PLAN BUDGET SAMI-TF'!J12:J99999,SUMMARY!A37&"*") -> 0 | I37: =SUMIFS('PLAN BUDGET SAMI-TF'!AR12:AR99999,'PLAN BUDGET SAMI-TF'!D12:D99999,SUMMARY!D37,'PLAN BUDGET SAMI-TF'!J12:J99999,SUMMARY!A37&"*") -> 0 | J37: =SUMIFS('PLAN BUDGET SAMI-TF'!AS12:AS99999,'PLAN BUDGET SAMI-TF'!D12:D99999,SUMMARY!D37,'PLAN BUDGET SAMI-TF'!J12:J99999,SUMMARY!A37&"*") -> 0 | K37: =SUMIFS('PLAN BUDGET SAMI-TF'!AT12:AT99999,'PLAN BUDGET SAMI-TF'!D12:D99999,SUMMARY!D37,'PLAN BUDGET SAMI-TF'!J12:J99999,SUMMARY!A37&"*") -> 0 | L37: =SUMIFS('PLAN BUDGET SAMI-TF'!AU12:AU99999,'PLAN BUDGET SAMI-TF'!D12:D99999,SUMMARY!D37,'PLAN BUDGET SAMI-TF'!J12:J99999,SUMMARY!A37&"*") -> 0 | M37: =SUMIFS('PLAN BUDGET SAMI-TF'!AV12:AV99999,'PLAN BUDGET SAMI-TF'!D12:D99999,SUMMARY!D37,'PLAN BUDGET SAMI-TF'!J12:J99999,SUMMARY!A37&"*") -> 0 | N37: =SUMIFS('PLAN BUDGET SAMI-TF'!AW12:AW99999,'PLAN BUDGET SAMI-TF'!D12:D99999,SUMMARY!D37,'PLAN BUDGET SAMI-TF'!J12:J99999,SUMMARY!A37&"*") -> 0 | O37: =SUMIFS('PLAN BUDGET SAMI-TF'!AX12:AX99999,'PLAN BUDGET SAMI-TF'!D12:D99999,SUMMARY!D37,'PLAN BUDGET SAMI-TF'!J12:J99999,SUMMARY!A37&"*") -> 0 | P37: =SUMIFS('PLAN BUDGET SAMI-TF'!AY12:AY99999,'PLAN BUDGET SAMI-TF'!D12:D99999,SUMMARY!D37,'PLAN BUDGET SAMI-TF'!J12:J99999,SUMMARY!A37&"*") -> 0 | Q37: =SUMIFS('PLAN BUDGET SAMI-TF'!BC12:BC99999,'PLAN BUDGET SAMI-TF'!D12:D99999,SUMMARY!D37,'PLAN BUDGET SAMI-TF'!J12:J99999,SUMMARY!A37&"*") -> 0 | R37: =SUMIFS('PLAN BUDGET SAMI-TF'!BD12:BD99999,'PLAN BUDGET SAMI-TF'!D12:D99999,SUMMARY!D37,'PLAN BUDGET SAMI-TF'!J12:J99999,SUMMARY!A37&"*") -> 0 | S37: =SUMIFS('PLAN BUDGET SAMI-TF'!BE12:BE99999,'PLAN BUDGET SAMI-TF'!D12:D99999,SUMMARY!D37,'PLAN BUDGET SAMI-TF'!J12:J99999,SUMMARY!A37&"*") -> 588 | T37: =SUMIFS('PLAN BUDGET SAMI-TF'!BF12:BF99999,'PLAN BUDGET SAMI-TF'!D12:D99999,SUMMARY!D37,'PLAN BUDGET SAMI-TF'!J12:J99999,SUMMARY!A37&"*") -> 0 | U37: =SUMIFS('PLAN BUDGET SAMI-TF'!BG12:BG99999,'PLAN BUDGET SAMI-TF'!D12:D99999,SUMMARY!D37,'PLAN BUDGET SAMI-TF'!J12:J99999,SUMMARY!A37&"*") -> 0 | V37: =SUMIFS('PLAN BUDGET SAMI-TF'!BH12:BH99999,'PLAN BUDGET SAMI-TF'!D12:D99999,SUMMARY!D37,'PLAN BUDGET SAMI-TF'!J12:J99999,SUMMARY!A37&"*") -> 0 | W37: =SUMIFS('PLAN BUDGET SAMI-TF'!BI12:BI99999,'PLAN BUDGET SAMI-TF'!D12:D99999,SUMMARY!D37,'PLAN BUDGET SAMI-TF'!J12:J99999,SUMMARY!A37&"*") -> 0 | X37: =SUMIFS('PLAN BUDGET SAMI-TF'!BJ12:BJ99999,'PLAN BUDGET SAMI-TF'!D12:D99999,SUMMARY!D37,'PLAN BUDGET SAMI-TF'!J12:J99999,SUMMARY!A37&"*") -> 0 | Y37: =SUMIFS('PLAN BUDGET SAMI-TF'!BK12:BK99999,'PLAN BUDGET SAMI-TF'!D12:D99999,SUMMARY!D37,'PLAN BUDGET SAMI-TF'!J12:J99999,SUMMARY!A37&"*") -> 0 | Z37: =SUMIFS('PLAN BUDGET SAMI-TF'!BL12:BL99999,'PLAN BUDGET SAMI-TF'!D12:D99999,SUMMARY!D37,'PLAN BUDGET SAMI-TF'!J12:J99999,SUMMARY!A37&"*") -> 0 | AA37: =SUMIFS('PLAN BUDGET SAMI-TF'!BM12:BM99999,'PLAN BUDGET SAMI-TF'!D12:D99999,SUMMARY!D37,'PLAN BUDGET SAMI-TF'!J12:J99999,SUMMARY!A37&"*") -> 0 | AB37: =SUMIFS('PLAN BUDGET SAMI-TF'!BN12:BN99999,'PLAN BUDGET SAMI-TF'!D12:D99999,SUMMARY!D37,'PLAN BUDGET SAMI-TF'!J12:J99999,SUMMARY!A37&"*") -> 0 | AC37: =SUM(E37:P37) -> 14 | AD37: =SUM(Q37:AB37) -> 588 | AF37: 0 | AG37: 0 | AH37: =IFERROR((AC37-AF37)/AF37,1) -> 1 | AI37: =IFERROR((AD37-AG37)/AG37,1) -> 1 | AJ37: New item di th 85
A38: RUTIN | D38: PERJALANAN DINAS | E38: =SUMIFS('PLAN BUDGET SAMI-TF'!AN12:AN99999,'PLAN BUDGET SAMI-TF'!D12:D99999,SUMMARY!D38,'PLAN BUDGET SAMI-TF'!J12:J99999,SUMMARY!A38&"*") -> 2 | F38: =SUMIFS('PLAN BUDGET SAMI-TF'!AO12:AO99999,'PLAN BUDGET SAMI-TF'!D12:D99999,SUMMARY!D38,'PLAN BUDGET SAMI-TF'!J12:J99999,SUMMARY!A38&"*") -> 3 | G38: =SUMIFS('PLAN BUDGET SAMI-TF'!AP12:AP99999,'PLAN BUDGET SAMI-TF'!D12:D99999,SUMMARY!D38,'PLAN BUDGET SAMI-TF'!J12:J99999,SUMMARY!A38&"*") -> 17 | H38: =SUMIFS('PLAN BUDGET SAMI-TF'!AQ12:AQ99999,'PLAN BUDGET SAMI-TF'!D12:D99999,SUMMARY!D38,'PLAN BUDGET SAMI-TF'!J12:J99999,SUMMARY!A38&"*") -> 0 | I38: =SUMIFS('PLAN BUDGET SAMI-TF'!AR12:AR99999,'PLAN BUDGET SAMI-TF'!D12:D99999,SUMMARY!D38,'PLAN BUDGET SAMI-TF'!J12:J99999,SUMMARY!A38&"*") -> 13 | J38: =SUMIFS('PLAN BUDGET SAMI-TF'!AS12:AS99999,'PLAN BUDGET SAMI-TF'!D12:D99999,SUMMARY!D38,'PLAN BUDGET SAMI-TF'!J12:J99999,SUMMARY!A38&"*") -> 0 | K38: =SUMIFS('PLAN BUDGET SAMI-TF'!AT12:AT99999,'PLAN BUDGET SAMI-TF'!D12:D99999,SUMMARY!D38,'PLAN BUDGET SAMI-TF'!J12:J99999,SUMMARY!A38&"*") -> 1 | L38: =SUMIFS('PLAN BUDGET SAMI-TF'!AU12:AU99999,'PLAN BUDGET SAMI-TF'!D12:D99999,SUMMARY!D38,'PLAN BUDGET SAMI-TF'!J12:J99999,SUMMARY!A38&"*") -> 0 | M38: =SUMIFS('PLAN BUDGET SAMI-TF'!AV12:AV99999,'PLAN BUDGET SAMI-TF'!D12:D99999,SUMMARY!D38,'PLAN BUDGET SAMI-TF'!J12:J99999,SUMMARY!A38&"*") -> 0 | N38: =SUMIFS('PLAN BUDGET SAMI-TF'!AW12:AW99999,'PLAN BUDGET SAMI-TF'!D12:D99999,SUMMARY!D38,'PLAN BUDGET SAMI-TF'!J12:J99999,SUMMARY!A38&"*") -> 0 | O38: =SUMIFS('PLAN BUDGET SAMI-TF'!AX12:AX99999,'PLAN BUDGET SAMI-TF'!D12:D99999,SUMMARY!D38,'PLAN BUDGET SAMI-TF'!J12:J99999,SUMMARY!A38&"*") -> 0 | P38: =SUMIFS('PLAN BUDGET SAMI-TF'!AY12:AY99999,'PLAN BUDGET SAMI-TF'!D12:D99999,SUMMARY!D38,'PLAN BUDGET SAMI-TF'!J12:J99999,SUMMARY!A38&"*") -> 4 | Q38: =SUMIFS('PLAN BUDGET SAMI-TF'!BC12:BC99999,'PLAN BUDGET SAMI-TF'!D12:D99999,SUMMARY!D38,'PLAN BUDGET SAMI-TF'!J12:J99999,SUMMARY!A38&"*") -> 3164.8374 | R38: =SUMIFS('PLAN BUDGET SAMI-TF'!BD12:BD99999,'PLAN BUDGET SAMI-TF'!D12:D99999,SUMMARY!D38,'PLAN BUDGET SAMI-TF'!J12:J99999,SUMMARY!A38&"*") -> 1582.4187 | S38: =SUMIFS('PLAN BUDGET SAMI-TF'!BE12:BE99999,'PLAN BUDGET SAMI-TF'!D12:D99999,SUMMARY!D38,'PLAN BUDGET SAMI-TF'!J12:J99999,SUMMARY!A38&"*") -> 2177.4081 | T38: =SUMIFS('PLAN BUDGET SAMI-TF'!BF12:BF99999,'PLAN BUDGET SAMI-TF'!D12:D99999,SUMMARY!D38,'PLAN BUDGET SAMI-TF'!J12:J99999,SUMMARY!A38&"*") -> 0 | U38: =SUMIFS('PLAN BUDGET SAMI-TF'!BG12:BG99999,'PLAN BUDGET SAMI-TF'!D12:D99999,SUMMARY!D38,'PLAN BUDGET SAMI-TF'!J12:J99999,SUMMARY!A38&"*") -> 1715.3419 | V38: =SUMIFS('PLAN BUDGET SAMI-TF'!BH12:BH99999,'PLAN BUDGET SAMI-TF'!D12:D99999,SUMMARY!D38,'PLAN BUDGET SAMI-TF'!J12:J99999,SUMMARY!A38&"*") -> 0 | W38: =SUMIFS('PLAN BUDGET SAMI-TF'!BI12:BI99999,'PLAN BUDGET SAMI-TF'!D12:D99999,SUMMARY!D38,'PLAN BUDGET SAMI-TF'!J12:J99999,SUMMARY!A38&"*") -> 2215.3862 | X38: =SUMIFS('PLAN BUDGET SAMI-TF'!BJ12:BJ99999,'PLAN BUDGET SAMI-TF'!D12:D99999,SUMMARY!D38,'PLAN BUDGET SAMI-TF'!J12:J99999,SUMMARY!A38&"*") -> 0 | Y38: =SUMIFS('PLAN BUDGET SAMI-TF'!BK12:BK99999,'PLAN BUDGET SAMI-TF'!D12:D99999,SUMMARY!D38,'PLAN BUDGET SAMI-TF'!J12:J99999,SUMMARY!A38&"*") -> 0 | Z38: =SUMIFS('PLAN BUDGET SAMI-TF'!BL12:BL99999,'PLAN BUDGET SAMI-TF'!D12:D99999,SUMMARY!D38,'PLAN BUDGET SAMI-TF'!J12:J99999,SUMMARY!A38&"*") -> 0 | AA38: =SUMIFS('PLAN BUDGET SAMI-TF'!BM12:BM99999,'PLAN BUDGET SAMI-TF'!D12:D99999,SUMMARY!D38,'PLAN BUDGET SAMI-TF'!J12:J99999,SUMMARY!A38&"*") -> 0 | AB38: =SUMIFS('PLAN BUDGET SAMI-TF'!BN12:BN99999,'PLAN BUDGET SAMI-TF'!D12:D99999,SUMMARY!D38,'PLAN BUDGET SAMI-TF'!J12:J99999,SUMMARY!A38&"*") -> 411.08073 | AC38: =SUM(E38:P38) -> 40 | AD38: =SUM(Q38:AB38) -> 11266.473 | AF38: 35 | AG38: 449.40691 | AH38: =IFERROR((AC38-AF38)/AF38,1) -> 0.14285714 | AI38: =IFERROR((AD38-AG38)/AG38,1) -> 24.069648 | AJ38: Di th 85 ada plan benchmark ke museum (new)
A39: RUTIN | D39: MMT | E39: =SUMIFS('PLAN BUDGET SAMI-TF'!AN12:AN99999,'PLAN BUDGET SAMI-TF'!D12:D99999,SUMMARY!D39,'PLAN BUDGET SAMI-TF'!J12:J99999,SUMMARY!A39&"*") -> 0 | F39: =SUMIFS('PLAN BUDGET SAMI-TF'!AO12:AO99999,'PLAN BUDGET SAMI-TF'!D12:D99999,SUMMARY!D39,'PLAN BUDGET SAMI-TF'!J12:J99999,SUMMARY!A39&"*") -> 15 | G39: =SUMIFS('PLAN BUDGET SAMI-TF'!AP12:AP99999,'PLAN BUDGET SAMI-TF'!D12:D99999,SUMMARY!D39,'PLAN BUDGET SAMI-TF'!J12:J99999,SUMMARY!A39&"*") -> 0 | H39: =SUMIFS('PLAN BUDGET SAMI-TF'!AQ12:AQ99999,'PLAN BUDGET SAMI-TF'!D12:D99999,SUMMARY!D39,'PLAN BUDGET SAMI-TF'!J12:J99999,SUMMARY!A39&"*") -> 15 | I39: =SUMIFS('PLAN BUDGET SAMI-TF'!AR12:AR99999,'PLAN BUDGET SAMI-TF'!D12:D99999,SUMMARY!D39,'PLAN BUDGET SAMI-TF'!J12:J99999,SUMMARY!A39&"*") -> 0 | J39: =SUMIFS('PLAN BUDGET SAMI-TF'!AS12:AS99999,'PLAN BUDGET SAMI-TF'!D12:D99999,SUMMARY!D39,'PLAN BUDGET SAMI-TF'!J12:J99999,SUMMARY!A39&"*") -> 15 | K39: =SUMIFS('PLAN BUDGET SAMI-TF'!AT12:AT99999,'PLAN BUDGET SAMI-TF'!D12:D99999,SUMMARY!D39,'PLAN BUDGET SAMI-TF'!J12:J99999,SUMMARY!A39&"*") -> 0 | L39: =SUMIFS('PLAN BUDGET SAMI-TF'!AU12:AU99999,'PLAN BUDGET SAMI-TF'!D12:D99999,SUMMARY!D39,'PLAN BUDGET SAMI-TF'!J12:J99999,SUMMARY!A39&"*") -> 15 | M39: =SUMIFS('PLAN BUDGET SAMI-TF'!AV12:AV99999,'PLAN BUDGET SAMI-TF'!D12:D99999,SUMMARY!D39,'PLAN BUDGET SAMI-TF'!J12:J99999,SUMMARY!A39&"*") -> 0 | N39: =SUMIFS('PLAN BUDGET SAMI-TF'!AW12:AW99999,'PLAN BUDGET SAMI-TF'!D12:D99999,SUMMARY!D39,'PLAN BUDGET SAMI-TF'!J12:J99999,SUMMARY!A39&"*") -> 15 | O39: =SUMIFS('PLAN BUDGET SAMI-TF'!AX12:AX99999,'PLAN BUDGET SAMI-TF'!D12:D99999,SUMMARY!D39,'PLAN BUDGET SAMI-TF'!J12:J99999,SUMMARY!A39&"*") -> 12 | P39: =SUMIFS('PLAN BUDGET SAMI-TF'!AY12:AY99999,'PLAN BUDGET SAMI-TF'!D12:D99999,SUMMARY!D39,'PLAN BUDGET SAMI-TF'!J12:J99999,SUMMARY!A39&"*") -> 15 | Q39: =SUMIFS('PLAN BUDGET SAMI-TF'!BC12:BC99999,'PLAN BUDGET SAMI-TF'!D12:D99999,SUMMARY!D39,'PLAN BUDGET SAMI-TF'!J12:J99999,SUMMARY!A39&"*") -> 0 | R39: =SUMIFS('PLAN BUDGET SAMI-TF'!BD12:BD99999,'PLAN BUDGET SAMI-TF'!D12:D99999,SUMMARY!D39,'PLAN BUDGET SAMI-TF'!J12:J99999,SUMMARY!A39&"*") -> 21.362652 | S39: =SUMIFS('PLAN BUDGET SAMI-TF'!BE12:BE99999,'PLAN BUDGET SAMI-TF'!D12:D99999,SUMMARY!D39,'PLAN BUDGET SAMI-TF'!J12:J99999,SUMMARY!A39&"*") -> 0 | T39: =SUMIFS('PLAN BUDGET SAMI-TF'!BF12:BF99999,'PLAN BUDGET SAMI-TF'!D12:D99999,SUMMARY!D39,'PLAN BUDGET SAMI-TF'!J12:J99999,SUMMARY!A39&"*") -> 21.362652 | U39: =SUMIFS('PLAN BUDGET SAMI-TF'!BG12:BG99999,'PLAN BUDGET SAMI-TF'!D12:D99999,SUMMARY!D39,'PLAN BUDGET SAMI-TF'!J12:J99999,SUMMARY!A39&"*") -> 0 | V39: =SUMIFS('PLAN BUDGET SAMI-TF'!BH12:BH99999,'PLAN BUDGET SAMI-TF'!D12:D99999,SUMMARY!D39,'PLAN BUDGET SAMI-TF'!J12:J99999,SUMMARY!A39&"*") -> 21.362652 | W39: =SUMIFS('PLAN BUDGET SAMI-TF'!BI12:BI99999,'PLAN BUDGET SAMI-TF'!D12:D99999,SUMMARY!D39,'PLAN BUDGET SAMI-TF'!J12:J99999,SUMMARY!A39&"*") -> 0 | X39: =SUMIFS('PLAN BUDGET SAMI-TF'!BJ12:BJ99999,'PLAN BUDGET SAMI-TF'!D12:D99999,SUMMARY!D39,'PLAN BUDGET SAMI-TF'!J12:J99999,SUMMARY!A39&"*") -> 21.362652 | Y39: =SUMIFS('PLAN BUDGET SAMI-TF'!BK12:BK99999,'PLAN BUDGET SAMI-TF'!D12:D99999,SUMMARY!D39,'PLAN BUDGET SAMI-TF'!J12:J99999,SUMMARY!A39&"*") -> 0 | Z39: =SUMIFS('PLAN BUDGET SAMI-TF'!BL12:BL99999,'PLAN BUDGET SAMI-TF'!D12:D99999,SUMMARY!D39,'PLAN BUDGET SAMI-TF'!J12:J99999,SUMMARY!A39&"*") -> 21.362652 | AA39: =SUMIFS('PLAN BUDGET SAMI-TF'!BM12:BM99999,'PLAN BUDGET SAMI-TF'!D12:D99999,SUMMARY!D39,'PLAN BUDGET SAMI-TF'!J12:J99999,SUMMARY!A39&"*") -> 18.989024 | AB39: =SUMIFS('PLAN BUDGET SAMI-TF'!BN12:BN99999,'PLAN BUDGET SAMI-TF'!D12:D99999,SUMMARY!D39,'PLAN BUDGET SAMI-TF'!J12:J99999,SUMMARY!A39&"*") -> 21.362652 | AC39: =SUM(E39:P39) -> 102 | AD39: =SUM(Q39:AB39) -> 147.16494 | AF39: 197 | AG39: 282.46174 | AH39: =IFERROR((AC39-AF39)/AF39,1) -> -0.4822335 | AI39: =IFERROR((AD39-AG39)/AG39,1) -> -0.4789916 | AJ39: Di th 84 ada penggantian revisi design ID tempat sampah, di th 85 untuk penggantian jika ada yang rusak
A40: RUTIN | D40: PITA | E40: =SUMIFS('PLAN BUDGET SAMI-TF'!AN12:AN99999,'PLAN BUDGET SAMI-TF'!D12:D99999,SUMMARY!D40,'PLAN BUDGET SAMI-TF'!J12:J99999,SUMMARY!A40&"*") -> 0 | F40: =SUMIFS('PLAN BUDGET SAMI-TF'!AO12:AO99999,'PLAN BUDGET SAMI-TF'!D12:D99999,SUMMARY!D40,'PLAN BUDGET SAMI-TF'!J12:J99999,SUMMARY!A40&"*") -> 3 | G40: =SUMIFS('PLAN BUDGET SAMI-TF'!AP12:AP99999,'PLAN BUDGET SAMI-TF'!D12:D99999,SUMMARY!D40,'PLAN BUDGET SAMI-TF'!J12:J99999,SUMMARY!A40&"*") -> 0 | H40: =SUMIFS('PLAN BUDGET SAMI-TF'!AQ12:AQ99999,'PLAN BUDGET SAMI-TF'!D12:D99999,SUMMARY!D40,'PLAN BUDGET SAMI-TF'!J12:J99999,SUMMARY!A40&"*") -> 0 | I40: =SUMIFS('PLAN BUDGET SAMI-TF'!AR12:AR99999,'PLAN BUDGET SAMI-TF'!D12:D99999,SUMMARY!D40,'PLAN BUDGET SAMI-TF'!J12:J99999,SUMMARY!A40&"*") -> 0 | J40: =SUMIFS('PLAN BUDGET SAMI-TF'!AS12:AS99999,'PLAN BUDGET SAMI-TF'!D12:D99999,SUMMARY!D40,'PLAN BUDGET SAMI-TF'!J12:J99999,SUMMARY!A40&"*") -> 0 | K40: =SUMIFS('PLAN BUDGET SAMI-TF'!AT12:AT99999,'PLAN BUDGET SAMI-TF'!D12:D99999,SUMMARY!D40,'PLAN BUDGET SAMI-TF'!J12:J99999,SUMMARY!A40&"*") -> 3 | L40: =SUMIFS('PLAN BUDGET SAMI-TF'!AU12:AU99999,'PLAN BUDGET SAMI-TF'!D12:D99999,SUMMARY!D40,'PLAN BUDGET SAMI-TF'!J12:J99999,SUMMARY!A40&"*") -> 0 | M40: =SUMIFS('PLAN BUDGET SAMI-TF'!AV12:AV99999,'PLAN BUDGET SAMI-TF'!D12:D99999,SUMMARY!D40,'PLAN BUDGET SAMI-TF'!J12:J99999,SUMMARY!A40&"*") -> 0 | N40: =SUMIFS('PLAN BUDGET SAMI-TF'!AW12:AW99999,'PLAN BUDGET SAMI-TF'!D12:D99999,SUMMARY!D40,'PLAN BUDGET SAMI-TF'!J12:J99999,SUMMARY!A40&"*") -> 0 | O40: =SUMIFS('PLAN BUDGET SAMI-TF'!AX12:AX99999,'PLAN BUDGET SAMI-TF'!D12:D99999,SUMMARY!D40,'PLAN BUDGET SAMI-TF'!J12:J99999,SUMMARY!A40&"*") -> 0 | P40: =SUMIFS('PLAN BUDGET SAMI-TF'!AY12:AY99999,'PLAN BUDGET SAMI-TF'!D12:D99999,SUMMARY!D40,'PLAN BUDGET SAMI-TF'!J12:J99999,SUMMARY!A40&"*") -> 0 | Q40: =SUMIFS('PLAN BUDGET SAMI-TF'!BC12:BC99999,'PLAN BUDGET SAMI-TF'!D12:D99999,SUMMARY!D40,'PLAN BUDGET SAMI-TF'!J12:J99999,SUMMARY!A40&"*") -> 0 | R40: =SUMIFS('PLAN BUDGET SAMI-TF'!BD12:BD99999,'PLAN BUDGET SAMI-TF'!D12:D99999,SUMMARY!D40,'PLAN BUDGET SAMI-TF'!J12:J99999,SUMMARY!A40&"*") -> 2.724925 | S40: =SUMIFS('PLAN BUDGET SAMI-TF'!BE12:BE99999,'PLAN BUDGET SAMI-TF'!D12:D99999,SUMMARY!D40,'PLAN BUDGET SAMI-TF'!J12:J99999,SUMMARY!A40&"*") -> 0 | T40: =SUMIFS('PLAN BUDGET SAMI-TF'!BF12:BF99999,'PLAN BUDGET SAMI-TF'!D12:D99999,SUMMARY!D40,'PLAN BUDGET SAMI-TF'!J12:J99999,SUMMARY!A40&"*") -> 0 | U40: =SUMIFS('PLAN BUDGET SAMI-TF'!BG12:BG99999,'PLAN BUDGET SAMI-TF'!D12:D99999,SUMMARY!D40,'PLAN BUDGET SAMI-TF'!J12:J99999,SUMMARY!A40&"*") -> 0 | V40: =SUMIFS('PLAN BUDGET SAMI-TF'!BH12:BH99999,'PLAN BUDGET SAMI-TF'!D12:D99999,SUMMARY!D40,'PLAN BUDGET SAMI-TF'!J12:J99999,SUMMARY!A40&"*") -> 0 | W40: =SUMIFS('PLAN BUDGET SAMI-TF'!BI12:BI99999,'PLAN BUDGET SAMI-TF'!D12:D99999,SUMMARY!D40,'PLAN BUDGET SAMI-TF'!J12:J99999,SUMMARY!A40&"*") -> 2.724925 | X40: =SUMIFS('PLAN BUDGET SAMI-TF'!BJ12:BJ99999,'PLAN BUDGET SAMI-TF'!D12:D99999,SUMMARY!D40,'PLAN BUDGET SAMI-TF'!J12:J99999,SUMMARY!A40&"*") -> 0 | Y40: =SUMIFS('PLAN BUDGET SAMI-TF'!BK12:BK99999,'PLAN BUDGET SAMI-TF'!D12:D99999,SUMMARY!D40,'PLAN BUDGET SAMI-TF'!J12:J99999,SUMMARY!A40&"*") -> 0 | Z40: =SUMIFS('PLAN BUDGET SAMI-TF'!BL12:BL99999,'PLAN BUDGET SAMI-TF'!D12:D99999,SUMMARY!D40,'PLAN BUDGET SAMI-TF'!J12:J99999,SUMMARY!A40&"*") -> 0 | AA40: =SUMIFS('PLAN BUDGET SAMI-TF'!BM12:BM99999,'PLAN BUDGET SAMI-TF'!D12:D99999,SUMMARY!D40,'PLAN BUDGET SAMI-TF'!J12:J99999,SUMMARY!A40&"*") -> 0 | AB40: =SUMIFS('PLAN BUDGET SAMI-TF'!BN12:BN99999,'PLAN BUDGET SAMI-TF'!D12:D99999,SUMMARY!D40,'PLAN BUDGET SAMI-TF'!J12:J99999,SUMMARY!A40&"*") -> 0 | AC40: =SUM(E40:P40) -> 6 | AD40: =SUM(Q40:AB40) -> 5.44985 | AF40: 9 | AG40: 8.2564278 | AH40: =IFERROR((AC40-AF40)/AF40,1) -> -0.33333333 | AI40: =IFERROR((AD40-AG40)/AG40,1) -> -0.3399264 | AJ40: Di th 85 untuk penggantian pita yang rusak
A41: RUTIN | D41: PLASTIK | E41: =SUMIFS('PLAN BUDGET SAMI-TF'!AN12:AN99999,'PLAN BUDGET SAMI-TF'!D12:D99999,SUMMARY!D41,'PLAN BUDGET SAMI-TF'!J12:J99999,SUMMARY!A41&"*") -> 175 | F41: =SUMIFS('PLAN BUDGET SAMI-TF'!AO12:AO99999,'PLAN BUDGET SAMI-TF'!D12:D99999,SUMMARY!D41,'PLAN BUDGET SAMI-TF'!J12:J99999,SUMMARY!A41&"*") -> 1 | G41: =SUMIFS('PLAN BUDGET SAMI-TF'!AP12:AP99999,'PLAN BUDGET SAMI-TF'!D12:D99999,SUMMARY!D41,'PLAN BUDGET SAMI-TF'!J12:J99999,SUMMARY!A41&"*") -> 125 | H41: =SUMIFS('PLAN BUDGET SAMI-TF'!AQ12:AQ99999,'PLAN BUDGET SAMI-TF'!D12:D99999,SUMMARY!D41,'PLAN BUDGET SAMI-TF'!J12:J99999,SUMMARY!A41&"*") -> 0 | I41: =SUMIFS('PLAN BUDGET SAMI-TF'!AR12:AR99999,'PLAN BUDGET SAMI-TF'!D12:D99999,SUMMARY!D41,'PLAN BUDGET SAMI-TF'!J12:J99999,SUMMARY!A41&"*") -> 175 | J41: =SUMIFS('PLAN BUDGET SAMI-TF'!AS12:AS99999,'PLAN BUDGET SAMI-TF'!D12:D99999,SUMMARY!D41,'PLAN BUDGET SAMI-TF'!J12:J99999,SUMMARY!A41&"*") -> 0 | K41: =SUMIFS('PLAN BUDGET SAMI-TF'!AT12:AT99999,'PLAN BUDGET SAMI-TF'!D12:D99999,SUMMARY!D41,'PLAN BUDGET SAMI-TF'!J12:J99999,SUMMARY!A41&"*") -> 125 | L41: =SUMIFS('PLAN BUDGET SAMI-TF'!AU12:AU99999,'PLAN BUDGET SAMI-TF'!D12:D99999,SUMMARY!D41,'PLAN BUDGET SAMI-TF'!J12:J99999,SUMMARY!A41&"*") -> 0 | M41: =SUMIFS('PLAN BUDGET SAMI-TF'!AV12:AV99999,'PLAN BUDGET SAMI-TF'!D12:D99999,SUMMARY!D41,'PLAN BUDGET SAMI-TF'!J12:J99999,SUMMARY!A41&"*") -> 175 | N41: =SUMIFS('PLAN BUDGET SAMI-TF'!AW12:AW99999,'PLAN BUDGET SAMI-TF'!D12:D99999,SUMMARY!D41,'PLAN BUDGET SAMI-TF'!J12:J99999,SUMMARY!A41&"*") -> 0 | O41: =SUMIFS('PLAN BUDGET SAMI-TF'!AX12:AX99999,'PLAN BUDGET SAMI-TF'!D12:D99999,SUMMARY!D41,'PLAN BUDGET SAMI-TF'!J12:J99999,SUMMARY!A41&"*") -> 125 | P41: =SUMIFS('PLAN BUDGET SAMI-TF'!AY12:AY99999,'PLAN BUDGET SAMI-TF'!D12:D99999,SUMMARY!D41,'PLAN BUDGET SAMI-TF'!J12:J99999,SUMMARY!A41&"*") -> 0 | Q41: =SUMIFS('PLAN BUDGET SAMI-TF'!BC12:BC99999,'PLAN BUDGET SAMI-TF'!D12:D99999,SUMMARY!D41,'PLAN BUDGET SAMI-TF'!J12:J99999,SUMMARY!A41&"*") -> 20.152102 | R41: =SUMIFS('PLAN BUDGET SAMI-TF'!BD12:BD99999,'PLAN BUDGET SAMI-TF'!D12:D99999,SUMMARY!D41,'PLAN BUDGET SAMI-TF'!J12:J99999,SUMMARY!A41&"*") -> 0.21494468 | S41: =SUMIFS('PLAN BUDGET SAMI-TF'!BE12:BE99999,'PLAN BUDGET SAMI-TF'!D12:D99999,SUMMARY!D41,'PLAN BUDGET SAMI-TF'!J12:J99999,SUMMARY!A41&"*") -> 12.667262 | T41: =SUMIFS('PLAN BUDGET SAMI-TF'!BF12:BF99999,'PLAN BUDGET SAMI-TF'!D12:D99999,SUMMARY!D41,'PLAN BUDGET SAMI-TF'!J12:J99999,SUMMARY!A41&"*") -> 0 | U41: =SUMIFS('PLAN BUDGET SAMI-TF'!BG12:BG99999,'PLAN BUDGET SAMI-TF'!D12:D99999,SUMMARY!D41,'PLAN BUDGET SAMI-TF'!J12:J99999,SUMMARY!A41&"*") -> 20.152102 | V41: =SUMIFS('PLAN BUDGET SAMI-TF'!BH12:BH99999,'PLAN BUDGET SAMI-TF'!D12:D99999,SUMMARY!D41,'PLAN BUDGET SAMI-TF'!J12:J99999,SUMMARY!A41&"*") -> 0 | W41: =SUMIFS('PLAN BUDGET SAMI-TF'!BI12:BI99999,'PLAN BUDGET SAMI-TF'!D12:D99999,SUMMARY!D41,'PLAN BUDGET SAMI-TF'!J12:J99999,SUMMARY!A41&"*") -> 12.667262 | X41: =SUMIFS('PLAN BUDGET SAMI-TF'!BJ12:BJ99999,'PLAN BUDGET SAMI-TF'!D12:D99999,SUMMARY!D41,'PLAN BUDGET SAMI-TF'!J12:J99999,SUMMARY!A41&"*") -> 0 | Y41: =SUMIFS('PLAN BUDGET SAMI-TF'!BK12:BK99999,'PLAN BUDGET SAMI-TF'!D12:D99999,SUMMARY!D41,'PLAN BUDGET SAMI-TF'!J12:J99999,SUMMARY!A41&"*") -> 20.152102 | Z41: =SUMIFS('PLAN BUDGET SAMI-TF'!BL12:BL99999,'PLAN BUDGET SAMI-TF'!D12:D99999,SUMMARY!D41,'PLAN BUDGET SAMI-TF'!J12:J99999,SUMMARY!A41&"*") -> 0 | AA41: =SUMIFS('PLAN BUDGET SAMI-TF'!BM12:BM99999,'PLAN BUDGET SAMI-TF'!D12:D99999,SUMMARY!D41,'PLAN BUDGET SAMI-TF'!J12:J99999,SUMMARY!A41&"*") -> 12.667262 | AB41: =SUMIFS('PLAN BUDGET SAMI-TF'!BN12:BN99999,'PLAN BUDGET SAMI-TF'!D12:D99999,SUMMARY!D41,'PLAN BUDGET SAMI-TF'!J12:J99999,SUMMARY!A41&"*") -> 0 | AC41: =SUM(E41:P41) -> 901 | AD41: =SUM(Q41:AB41) -> 98.673036 | AF41: 2097 | AG41: 204.62908 | AH41: =IFERROR((AC41-AF41)/AF41,1) -> -0.57033858 | AI41: =IFERROR((AD41-AG41)/AG41,1) -> -0.51779564 | AJ41: Di th 84 ada additional plastik ID card karena ada kenaikan jumlah NEOP
A42: RUTIN | D42: STRECTH FILM | E42: =SUMIFS('PLAN BUDGET SAMI-TF'!AN12:AN99999,'PLAN BUDGET SAMI-TF'!D12:D99999,SUMMARY!D42,'PLAN BUDGET SAMI-TF'!J12:J99999,SUMMARY!A42&"*") -> 0 | F42: =SUMIFS('PLAN BUDGET SAMI-TF'!AO12:AO99999,'PLAN BUDGET SAMI-TF'!D12:D99999,SUMMARY!D42,'PLAN BUDGET SAMI-TF'!J12:J99999,SUMMARY!A42&"*") -> 0 | G42: =SUMIFS('PLAN BUDGET SAMI-TF'!AP12:AP99999,'PLAN BUDGET SAMI-TF'!D12:D99999,SUMMARY!D42,'PLAN BUDGET SAMI-TF'!J12:J99999,SUMMARY!A42&"*") -> 0 | H42: =SUMIFS('PLAN BUDGET SAMI-TF'!AQ12:AQ99999,'PLAN BUDGET SAMI-TF'!D12:D99999,SUMMARY!D42,'PLAN BUDGET SAMI-TF'!J12:J99999,SUMMARY!A42&"*") -> 0 | I42: =SUMIFS('PLAN BUDGET SAMI-TF'!AR12:AR99999,'PLAN BUDGET SAMI-TF'!D12:D99999,SUMMARY!D42,'PLAN BUDGET SAMI-TF'!J12:J99999,SUMMARY!A42&"*") -> 0 | J42: =SUMIFS('PLAN BUDGET SAMI-TF'!AS12:AS99999,'PLAN BUDGET SAMI-TF'!D12:D99999,SUMMARY!D42,'PLAN BUDGET SAMI-TF'!J12:J99999,SUMMARY!A42&"*") -> 0 | K42: =SUMIFS('PLAN BUDGET SAMI-TF'!AT12:AT99999,'PLAN BUDGET SAMI-TF'!D12:D99999,SUMMARY!D42,'PLAN BUDGET SAMI-TF'!J12:J99999,SUMMARY!A42&"*") -> 0 | L42: =SUMIFS('PLAN BUDGET SAMI-TF'!AU12:AU99999,'PLAN BUDGET SAMI-TF'!D12:D99999,SUMMARY!D42,'PLAN BUDGET SAMI-TF'!J12:J99999,SUMMARY!A42&"*") -> 0 | M42: =SUMIFS('PLAN BUDGET SAMI-TF'!AV12:AV99999,'PLAN BUDGET SAMI-TF'!D12:D99999,SUMMARY!D42,'PLAN BUDGET SAMI-TF'!J12:J99999,SUMMARY!A42&"*") -> 1 | N42: =SUMIFS('PLAN BUDGET SAMI-TF'!AW12:AW99999,'PLAN BUDGET SAMI-TF'!D12:D99999,SUMMARY!D42,'PLAN BUDGET SAMI-TF'!J12:J99999,SUMMARY!A42&"*") -> 0 | O42: =SUMIFS('PLAN BUDGET SAMI-TF'!AX12:AX99999,'PLAN BUDGET SAMI-TF'!D12:D99999,SUMMARY!D42,'PLAN BUDGET SAMI-TF'!J12:J99999,SUMMARY!A42&"*") -> 0 | P42: =SUMIFS('PLAN BUDGET SAMI-TF'!AY12:AY99999,'PLAN BUDGET SAMI-TF'!D12:D99999,SUMMARY!D42,'PLAN BUDGET SAMI-TF'!J12:J99999,SUMMARY!A42&"*") -> 0 | Q42: =SUMIFS('PLAN BUDGET SAMI-TF'!BC12:BC99999,'PLAN BUDGET SAMI-TF'!D12:D99999,SUMMARY!D42,'PLAN BUDGET SAMI-TF'!J12:J99999,SUMMARY!A42&"*") -> 0 | R42: =SUMIFS('PLAN BUDGET SAMI-TF'!BD12:BD99999,'PLAN BUDGET SAMI-TF'!D12:D99999,SUMMARY!D42,'PLAN BUDGET SAMI-TF'!J12:J99999,SUMMARY!A42&"*") -> 0 | S42: =SUMIFS('PLAN BUDGET SAMI-TF'!BE12:BE99999,'PLAN BUDGET SAMI-TF'!D12:D99999,SUMMARY!D42,'PLAN BUDGET SAMI-TF'!J12:J99999,SUMMARY!A42&"*") -> 0 | T42: =SUMIFS('PLAN BUDGET SAMI-TF'!BF12:BF99999,'PLAN BUDGET SAMI-TF'!D12:D99999,SUMMARY!D42,'PLAN BUDGET SAMI-TF'!J12:J99999,SUMMARY!A42&"*") -> 0 | U42: =SUMIFS('PLAN BUDGET SAMI-TF'!BG12:BG99999,'PLAN BUDGET SAMI-TF'!D12:D99999,SUMMARY!D42,'PLAN BUDGET SAMI-TF'!J12:J99999,SUMMARY!A42&"*") -> 0 | V42: =SUMIFS('PLAN BUDGET SAMI-TF'!BH12:BH99999,'PLAN BUDGET SAMI-TF'!D12:D99999,SUMMARY!D42,'PLAN BUDGET SAMI-TF'!J12:J99999,SUMMARY!A42&"*") -> 0 | W42: =SUMIFS('PLAN BUDGET SAMI-TF'!BI12:BI99999,'PLAN BUDGET SAMI-TF'!D12:D99999,SUMMARY!D42,'PLAN BUDGET SAMI-TF'!J12:J99999,SUMMARY!A42&"*") -> 0 | X42: =SUMIFS('PLAN BUDGET SAMI-TF'!BJ12:BJ99999,'PLAN BUDGET SAMI-TF'!D12:D99999,SUMMARY!D42,'PLAN BUDGET SAMI-TF'!J12:J99999,SUMMARY!A42&"*") -> 0 | Y42: =SUMIFS('PLAN BUDGET SAMI-TF'!BK12:BK99999,'PLAN BUDGET SAMI-TF'!D12:D99999,SUMMARY!D42,'PLAN BUDGET SAMI-TF'!J12:J99999,SUMMARY!A42&"*") -> 3.1648374 | Z42: =SUMIFS('PLAN BUDGET SAMI-TF'!BL12:BL99999,'PLAN BUDGET SAMI-TF'!D12:D99999,SUMMARY!D42,'PLAN BUDGET SAMI-TF'!J12:J99999,SUMMARY!A42&"*") -> 0 | AA42: =SUMIFS('PLAN BUDGET SAMI-TF'!BM12:BM99999,'PLAN BUDGET SAMI-TF'!D12:D99999,SUMMARY!D42,'PLAN BUDGET SAMI-TF'!J12:J99999,SUMMARY!A42&"*") -> 0 | AB42: =SUMIFS('PLAN BUDGET SAMI-TF'!BN12:BN99999,'PLAN BUDGET SAMI-TF'!D12:D99999,SUMMARY!D42,'PLAN BUDGET SAMI-TF'!J12:J99999,SUMMARY!A42&"*") -> 0 | AC42: =SUM(E42:P42) -> 1 | AD42: =SUM(Q42:AB42) -> 3.1648374 | AF42: 0 | AG42: 0 | AH42: =IFERROR((AC42-AF42)/AF42,1) -> 1 | AI42: =IFERROR((AD42-AG42)/AG42,1) -> 1 | AJ42: New item di th 85
A43: RUTIN | D43: UPD | E43: =SUMIFS('PLAN BUDGET SAMI-TF'!AN12:AN99999,'PLAN BUDGET SAMI-TF'!D12:D99999,SUMMARY!D43,'PLAN BUDGET SAMI-TF'!J12:J99999,SUMMARY!A43&"*") -> 2 | F43: =SUMIFS('PLAN BUDGET SAMI-TF'!AO12:AO99999,'PLAN BUDGET SAMI-TF'!D12:D99999,SUMMARY!D43,'PLAN BUDGET SAMI-TF'!J12:J99999,SUMMARY!A43&"*") -> 2 | G43: =SUMIFS('PLAN BUDGET SAMI-TF'!AP12:AP99999,'PLAN BUDGET SAMI-TF'!D12:D99999,SUMMARY!D43,'PLAN BUDGET SAMI-TF'!J12:J99999,SUMMARY!A43&"*") -> 18 | H43: =SUMIFS('PLAN BUDGET SAMI-TF'!AQ12:AQ99999,'PLAN BUDGET SAMI-TF'!D12:D99999,SUMMARY!D43,'PLAN BUDGET SAMI-TF'!J12:J99999,SUMMARY!A43&"*") -> 2 | I43: =SUMIFS('PLAN BUDGET SAMI-TF'!AR12:AR99999,'PLAN BUDGET SAMI-TF'!D12:D99999,SUMMARY!D43,'PLAN BUDGET SAMI-TF'!J12:J99999,SUMMARY!A43&"*") -> 32 | J43: =SUMIFS('PLAN BUDGET SAMI-TF'!AS12:AS99999,'PLAN BUDGET SAMI-TF'!D12:D99999,SUMMARY!D43,'PLAN BUDGET SAMI-TF'!J12:J99999,SUMMARY!A43&"*") -> 2 | K43: =SUMIFS('PLAN BUDGET SAMI-TF'!AT12:AT99999,'PLAN BUDGET SAMI-TF'!D12:D99999,SUMMARY!D43,'PLAN BUDGET SAMI-TF'!J12:J99999,SUMMARY!A43&"*") -> 2 | L43: =SUMIFS('PLAN BUDGET SAMI-TF'!AU12:AU99999,'PLAN BUDGET SAMI-TF'!D12:D99999,SUMMARY!D43,'PLAN BUDGET SAMI-TF'!J12:J99999,SUMMARY!A43&"*") -> 2 | M43: =SUMIFS('PLAN BUDGET SAMI-TF'!AV12:AV99999,'PLAN BUDGET SAMI-TF'!D12:D99999,SUMMARY!D43,'PLAN BUDGET SAMI-TF'!J12:J99999,SUMMARY!A43&"*") -> 2 | N43: =SUMIFS('PLAN BUDGET SAMI-TF'!AW12:AW99999,'PLAN BUDGET SAMI-TF'!D12:D99999,SUMMARY!D43,'PLAN BUDGET SAMI-TF'!J12:J99999,SUMMARY!A43&"*") -> 2 | O43: =SUMIFS('PLAN BUDGET SAMI-TF'!AX12:AX99999,'PLAN BUDGET SAMI-TF'!D12:D99999,SUMMARY!D43,'PLAN BUDGET SAMI-TF'!J12:J99999,SUMMARY!A43&"*") -> 2 | P43: =SUMIFS('PLAN BUDGET SAMI-TF'!AY12:AY99999,'PLAN BUDGET SAMI-TF'!D12:D99999,SUMMARY!D43,'PLAN BUDGET SAMI-TF'!J12:J99999,SUMMARY!A43&"*") -> 14 | Q43: =SUMIFS('PLAN BUDGET SAMI-TF'!BC12:BC99999,'PLAN BUDGET SAMI-TF'!D12:D99999,SUMMARY!D43,'PLAN BUDGET SAMI-TF'!J12:J99999,SUMMARY!A43&"*") -> 2.1520894 | R43: =SUMIFS('PLAN BUDGET SAMI-TF'!BD12:BD99999,'PLAN BUDGET SAMI-TF'!D12:D99999,SUMMARY!D43,'PLAN BUDGET SAMI-TF'!J12:J99999,SUMMARY!A43&"*") -> 2.1520894 | S43: =SUMIFS('PLAN BUDGET SAMI-TF'!BE12:BE99999,'PLAN BUDGET SAMI-TF'!D12:D99999,SUMMARY!D43,'PLAN BUDGET SAMI-TF'!J12:J99999,SUMMARY!A43&"*") -> 914.15209 | T43: =SUMIFS('PLAN BUDGET SAMI-TF'!BF12:BF99999,'PLAN BUDGET SAMI-TF'!D12:D99999,SUMMARY!D43,'PLAN BUDGET SAMI-TF'!J12:J99999,SUMMARY!A43&"*") -> 2.1520894 | U43: =SUMIFS('PLAN BUDGET SAMI-TF'!BG12:BG99999,'PLAN BUDGET SAMI-TF'!D12:D99999,SUMMARY!D43,'PLAN BUDGET SAMI-TF'!J12:J99999,SUMMARY!A43&"*") -> 75.576317 | V43: =SUMIFS('PLAN BUDGET SAMI-TF'!BH12:BH99999,'PLAN BUDGET SAMI-TF'!D12:D99999,SUMMARY!D43,'PLAN BUDGET SAMI-TF'!J12:J99999,SUMMARY!A43&"*") -> 2.1520894 | W43: =SUMIFS('PLAN BUDGET SAMI-TF'!BI12:BI99999,'PLAN BUDGET SAMI-TF'!D12:D99999,SUMMARY!D43,'PLAN BUDGET SAMI-TF'!J12:J99999,SUMMARY!A43&"*") -> 2.1520894 | X43: =SUMIFS('PLAN BUDGET SAMI-TF'!BJ12:BJ99999,'PLAN BUDGET SAMI-TF'!D12:D99999,SUMMARY!D43,'PLAN BUDGET SAMI-TF'!J12:J99999,SUMMARY!A43&"*") -> 2.1520894 | Y43: =SUMIFS('PLAN BUDGET SAMI-TF'!BK12:BK99999,'PLAN BUDGET SAMI-TF'!D12:D99999,SUMMARY!D43,'PLAN BUDGET SAMI-TF'!J12:J99999,SUMMARY!A43&"*") -> 2.1520894 | Z43: =SUMIFS('PLAN BUDGET SAMI-TF'!BL12:BL99999,'PLAN BUDGET SAMI-TF'!D12:D99999,SUMMARY!D43,'PLAN BUDGET SAMI-TF'!J12:J99999,SUMMARY!A43&"*") -> 2.1520894 | AA43: =SUMIFS('PLAN BUDGET SAMI-TF'!BM12:BM99999,'PLAN BUDGET SAMI-TF'!D12:D99999,SUMMARY!D43,'PLAN BUDGET SAMI-TF'!J12:J99999,SUMMARY!A43&"*") -> 2.1520894 | AB43: =SUMIFS('PLAN BUDGET SAMI-TF'!BN12:BN99999,'PLAN BUDGET SAMI-TF'!D12:D99999,SUMMARY!D43,'PLAN BUDGET SAMI-TF'!J12:J99999,SUMMARY!A43&"*") -> 30.635626 | AC43: =SUM(E43:P43) -> 82 | AD43: =SUM(Q43:AB43) -> 1039.7328 | AF43: 48 | AG43: 1339.7778 | AH43: =IFERROR((AC43-AF43)/AF43,1) -> 0.70833333 | AI43: =IFERROR((AD43-AG43)/AG43,1) -> -0.2239513 | AJ43: Di th 85 ada plan benchmark ke museum (new) & benchmark ke SUAI
A44: RUTIN | D44: BIAYA AUDIT LICENSE OLS | E44: =SUMIFS('PLAN BUDGET SAMI-TF'!AN12:AN99999,'PLAN BUDGET SAMI-TF'!D12:D99999,SUMMARY!D44,'PLAN BUDGET SAMI-TF'!J12:J99999,SUMMARY!A44&"*") -> 0 | F44: =SUMIFS('PLAN BUDGET SAMI-TF'!AO12:AO99999,'PLAN BUDGET SAMI-TF'!D12:D99999,SUMMARY!D44,'PLAN BUDGET SAMI-TF'!J12:J99999,SUMMARY!A44&"*") -> 0 | G44: =SUMIFS('PLAN BUDGET SAMI-TF'!AP12:AP99999,'PLAN BUDGET SAMI-TF'!D12:D99999,SUMMARY!D44,'PLAN BUDGET SAMI-TF'!J12:J99999,SUMMARY!A44&"*") -> 0 | H44: =SUMIFS('PLAN BUDGET SAMI-TF'!AQ12:AQ99999,'PLAN BUDGET SAMI-TF'!D12:D99999,SUMMARY!D44,'PLAN BUDGET SAMI-TF'!J12:J99999,SUMMARY!A44&"*") -> 0 | I44: =SUMIFS('PLAN BUDGET SAMI-TF'!AR12:AR99999,'PLAN BUDGET SAMI-TF'!D12:D99999,SUMMARY!D44,'PLAN BUDGET SAMI-TF'!J12:J99999,SUMMARY!A44&"*") -> 0 | J44: =SUMIFS('PLAN BUDGET SAMI-TF'!AS12:AS99999,'PLAN BUDGET SAMI-TF'!D12:D99999,SUMMARY!D44,'PLAN BUDGET SAMI-TF'!J12:J99999,SUMMARY!A44&"*") -> 0 | K44: =SUMIFS('PLAN BUDGET SAMI-TF'!AT12:AT99999,'PLAN BUDGET SAMI-TF'!D12:D99999,SUMMARY!D44,'PLAN BUDGET SAMI-TF'!J12:J99999,SUMMARY!A44&"*") -> 0 | L44: =SUMIFS('PLAN BUDGET SAMI-TF'!AU12:AU99999,'PLAN BUDGET SAMI-TF'!D12:D99999,SUMMARY!D44,'PLAN BUDGET SAMI-TF'!J12:J99999,SUMMARY!A44&"*") -> 0 | M44: =SUMIFS('PLAN BUDGET SAMI-TF'!AV12:AV99999,'PLAN BUDGET SAMI-TF'!D12:D99999,SUMMARY!D44,'PLAN BUDGET SAMI-TF'!J12:J99999,SUMMARY!A44&"*") -> 0 | N44: =SUMIFS('PLAN BUDGET SAMI-TF'!AW12:AW99999,'PLAN BUDGET SAMI-TF'!D12:D99999,SUMMARY!D44,'PLAN BUDGET SAMI-TF'!J12:J99999,SUMMARY!A44&"*") -> 0 | O44: =SUMIFS('PLAN BUDGET SAMI-TF'!AX12:AX99999,'PLAN BUDGET SAMI-TF'!D12:D99999,SUMMARY!D44,'PLAN BUDGET SAMI-TF'!J12:J99999,SUMMARY!A44&"*") -> 4 | P44: =SUMIFS('PLAN BUDGET SAMI-TF'!AY12:AY99999,'PLAN BUDGET SAMI-TF'!D12:D99999,SUMMARY!D44,'PLAN BUDGET SAMI-TF'!J12:J99999,SUMMARY!A44&"*") -> 0 | Q44: =SUMIFS('PLAN BUDGET SAMI-TF'!BC12:BC99999,'PLAN BUDGET SAMI-TF'!D12:D99999,SUMMARY!D44,'PLAN BUDGET SAMI-TF'!J12:J99999,SUMMARY!A44&"*") -> 0 | R44: =SUMIFS('PLAN BUDGET SAMI-TF'!BD12:BD99999,'PLAN BUDGET SAMI-TF'!D12:D99999,SUMMARY!D44,'PLAN BUDGET SAMI-TF'!J12:J99999,SUMMARY!A44&"*") -> 0 | S44: =SUMIFS('PLAN BUDGET SAMI-TF'!BE12:BE99999,'PLAN BUDGET SAMI-TF'!D12:D99999,SUMMARY!D44,'PLAN BUDGET SAMI-TF'!J12:J99999,SUMMARY!A44&"*") -> 0 | T44: =SUMIFS('PLAN BUDGET SAMI-TF'!BF12:BF99999,'PLAN BUDGET SAMI-TF'!D12:D99999,SUMMARY!D44,'PLAN BUDGET SAMI-TF'!J12:J99999,SUMMARY!A44&"*") -> 0 | U44: =SUMIFS('PLAN BUDGET SAMI-TF'!BG12:BG99999,'PLAN BUDGET SAMI-TF'!D12:D99999,SUMMARY!D44,'PLAN BUDGET SAMI-TF'!J12:J99999,SUMMARY!A44&"*") -> 0 | V44: =SUMIFS('PLAN BUDGET SAMI-TF'!BH12:BH99999,'PLAN BUDGET SAMI-TF'!D12:D99999,SUMMARY!D44,'PLAN BUDGET SAMI-TF'!J12:J99999,SUMMARY!A44&"*") -> 0 | W44: =SUMIFS('PLAN BUDGET SAMI-TF'!BI12:BI99999,'PLAN BUDGET SAMI-TF'!D12:D99999,SUMMARY!D44,'PLAN BUDGET SAMI-TF'!J12:J99999,SUMMARY!A44&"*") -> 0 | X44: =SUMIFS('PLAN BUDGET SAMI-TF'!BJ12:BJ99999,'PLAN BUDGET SAMI-TF'!D12:D99999,SUMMARY!D44,'PLAN BUDGET SAMI-TF'!J12:J99999,SUMMARY!A44&"*") -> 0 | Y44: =SUMIFS('PLAN BUDGET SAMI-TF'!BK12:BK99999,'PLAN BUDGET SAMI-TF'!D12:D99999,SUMMARY!D44,'PLAN BUDGET SAMI-TF'!J12:J99999,SUMMARY!A44&"*") -> 0 | Z44: =SUMIFS('PLAN BUDGET SAMI-TF'!BL12:BL99999,'PLAN BUDGET SAMI-TF'!D12:D99999,SUMMARY!D44,'PLAN BUDGET SAMI-TF'!J12:J99999,SUMMARY!A44&"*") -> 0 | AA44: =SUMIFS('PLAN BUDGET SAMI-TF'!BM12:BM99999,'PLAN BUDGET SAMI-TF'!D12:D99999,SUMMARY!D44,'PLAN BUDGET SAMI-TF'!J12:J99999,SUMMARY!A44&"*") -> 741.72185 | AB44: =SUMIFS('PLAN BUDGET SAMI-TF'!BN12:BN99999,'PLAN BUDGET SAMI-TF'!D12:D99999,SUMMARY!D44,'PLAN BUDGET SAMI-TF'!J12:J99999,SUMMARY!A44&"*") -> 0 | AC44: =SUM(E44:P44) -> 4 | AD44: =SUM(Q44:AB44) -> 741.72185 | AF44: 0 | AG44: 0 | AH44: =IFERROR((AC44-AF44)/AF44,1) -> 1 | AI44: =IFERROR((AD44-AG44)/AG44,1) -> 1 | AJ44: New item di th 85
A45: RUTIN | D45: BOARD MARKER | E45: =SUMIFS('PLAN BUDGET SAMI-TF'!AN12:AN99999,'PLAN BUDGET SAMI-TF'!D12:D99999,SUMMARY!D45,'PLAN BUDGET SAMI-TF'!J12:J99999,SUMMARY!A45&"*") -> 8 | F45: =SUMIFS('PLAN BUDGET SAMI-TF'!AO12:AO99999,'PLAN BUDGET SAMI-TF'!D12:D99999,SUMMARY!D45,'PLAN BUDGET SAMI-TF'!J12:J99999,SUMMARY!A45&"*") -> 0 | G45: =SUMIFS('PLAN BUDGET SAMI-TF'!AP12:AP99999,'PLAN BUDGET SAMI-TF'!D12:D99999,SUMMARY!D45,'PLAN BUDGET SAMI-TF'!J12:J99999,SUMMARY!A45&"*") -> 0 | H45: =SUMIFS('PLAN BUDGET SAMI-TF'!AQ12:AQ99999,'PLAN BUDGET SAMI-TF'!D12:D99999,SUMMARY!D45,'PLAN BUDGET SAMI-TF'!J12:J99999,SUMMARY!A45&"*") -> 0 | I45: =SUMIFS('PLAN BUDGET SAMI-TF'!AR12:AR99999,'PLAN BUDGET SAMI-TF'!D12:D99999,SUMMARY!D45,'PLAN BUDGET SAMI-TF'!J12:J99999,SUMMARY!A45&"*") -> 8 | J45: =SUMIFS('PLAN BUDGET SAMI-TF'!AS12:AS99999,'PLAN BUDGET SAMI-TF'!D12:D99999,SUMMARY!D45,'PLAN BUDGET SAMI-TF'!J12:J99999,SUMMARY!A45&"*") -> 0 | K45: =SUMIFS('PLAN BUDGET SAMI-TF'!AT12:AT99999,'PLAN BUDGET SAMI-TF'!D12:D99999,SUMMARY!D45,'PLAN BUDGET SAMI-TF'!J12:J99999,SUMMARY!A45&"*") -> 0 | L45: =SUMIFS('PLAN BUDGET SAMI-TF'!AU12:AU99999,'PLAN BUDGET SAMI-TF'!D12:D99999,SUMMARY!D45,'PLAN BUDGET SAMI-TF'!J12:J99999,SUMMARY!A45&"*") -> 0 | M45: =SUMIFS('PLAN BUDGET SAMI-TF'!AV12:AV99999,'PLAN BUDGET SAMI-TF'!D12:D99999,SUMMARY!D45,'PLAN BUDGET SAMI-TF'!J12:J99999,SUMMARY!A45&"*") -> 8 | N45: =SUMIFS('PLAN BUDGET SAMI-TF'!AW12:AW99999,'PLAN BUDGET SAMI-TF'!D12:D99999,SUMMARY!D45,'PLAN BUDGET SAMI-TF'!J12:J99999,SUMMARY!A45&"*") -> 0 | O45: =SUMIFS('PLAN BUDGET SAMI-TF'!AX12:AX99999,'PLAN BUDGET SAMI-TF'!D12:D99999,SUMMARY!D45,'PLAN BUDGET SAMI-TF'!J12:J99999,SUMMARY!A45&"*") -> 0 | P45: =SUMIFS('PLAN BUDGET SAMI-TF'!AY12:AY99999,'PLAN BUDGET SAMI-TF'!D12:D99999,SUMMARY!D45,'PLAN BUDGET SAMI-TF'!J12:J99999,SUMMARY!A45&"*") -> 0 | Q45: =SUMIFS('PLAN BUDGET SAMI-TF'!BC12:BC99999,'PLAN BUDGET SAMI-TF'!D12:D99999,SUMMARY!D45,'PLAN BUDGET SAMI-TF'!J12:J99999,SUMMARY!A45&"*") -> 3.0103933 | R45: =SUMIFS('PLAN BUDGET SAMI-TF'!BD12:BD99999,'PLAN BUDGET SAMI-TF'!D12:D99999,SUMMARY!D45,'PLAN BUDGET SAMI-TF'!J12:J99999,SUMMARY!A45&"*") -> 0 | S45: =SUMIFS('PLAN BUDGET SAMI-TF'!BE12:BE99999,'PLAN BUDGET SAMI-TF'!D12:D99999,SUMMARY!D45,'PLAN BUDGET SAMI-TF'!J12:J99999,SUMMARY!A45&"*") -> 0 | T45: =SUMIFS('PLAN BUDGET SAMI-TF'!BF12:BF99999,'PLAN BUDGET SAMI-TF'!D12:D99999,SUMMARY!D45,'PLAN BUDGET SAMI-TF'!J12:J99999,SUMMARY!A45&"*") -> 0 | U45: =SUMIFS('PLAN BUDGET SAMI-TF'!BG12:BG99999,'PLAN BUDGET SAMI-TF'!D12:D99999,SUMMARY!D45,'PLAN BUDGET SAMI-TF'!J12:J99999,SUMMARY!A45&"*") -> 3.0103933 | V45: =SUMIFS('PLAN BUDGET SAMI-TF'!BH12:BH99999,'PLAN BUDGET SAMI-TF'!D12:D99999,SUMMARY!D45,'PLAN BUDGET SAMI-TF'!J12:J99999,SUMMARY!A45&"*") -> 0 | W45: =SUMIFS('PLAN BUDGET SAMI-TF'!BI12:BI99999,'PLAN BUDGET SAMI-TF'!D12:D99999,SUMMARY!D45,'PLAN BUDGET SAMI-TF'!J12:J99999,SUMMARY!A45&"*") -> 0 | X45: =SUMIFS('PLAN BUDGET SAMI-TF'!BJ12:BJ99999,'PLAN BUDGET SAMI-TF'!D12:D99999,SUMMARY!D45,'PLAN BUDGET SAMI-TF'!J12:J99999,SUMMARY!A45&"*") -> 0 | Y45: =SUMIFS('PLAN BUDGET SAMI-TF'!BK12:BK99999,'PLAN BUDGET SAMI-TF'!D12:D99999,SUMMARY!D45,'PLAN BUDGET SAMI-TF'!J12:J99999,SUMMARY!A45&"*") -> 3.0103933 | Z45: =SUMIFS('PLAN BUDGET SAMI-TF'!BL12:BL99999,'PLAN BUDGET SAMI-TF'!D12:D99999,SUMMARY!D45,'PLAN BUDGET SAMI-TF'!J12:J99999,SUMMARY!A45&"*") -> 0 | AA45: =SUMIFS('PLAN BUDGET SAMI-TF'!BM12:BM99999,'PLAN BUDGET SAMI-TF'!D12:D99999,SUMMARY!D45,'PLAN BUDGET SAMI-TF'!J12:J99999,SUMMARY!A45&"*") -> 0 | AB45: =SUMIFS('PLAN BUDGET SAMI-TF'!BN12:BN99999,'PLAN BUDGET SAMI-TF'!D12:D99999,SUMMARY!D45,'PLAN BUDGET SAMI-TF'!J12:J99999,SUMMARY!A45&"*") -> 0 | AC45: =SUM(E45:P45) -> 24 | AD45: =SUM(Q45:AB45) -> 9.03118 | AF45: 24 | AG45: 9.3983011 | AH45: =IFERROR((AC45-AF45)/AF45,1) -> 0 | AI45: =IFERROR((AD45-AG45)/AG45,1) -> -0.0390625 | AJ45: Ada penurunan harga
A46: RUTIN | D46: CHECKSHEET | E46: =SUMIFS('PLAN BUDGET SAMI-TF'!AN12:AN99999,'PLAN BUDGET SAMI-TF'!D12:D99999,SUMMARY!D46,'PLAN BUDGET SAMI-TF'!J12:J99999,SUMMARY!A46&"*") -> 5 | F46: =SUMIFS('PLAN BUDGET SAMI-TF'!AO12:AO99999,'PLAN BUDGET SAMI-TF'!D12:D99999,SUMMARY!D46,'PLAN BUDGET SAMI-TF'!J12:J99999,SUMMARY!A46&"*") -> 4 | G46: =SUMIFS('PLAN BUDGET SAMI-TF'!AP12:AP99999,'PLAN BUDGET SAMI-TF'!D12:D99999,SUMMARY!D46,'PLAN BUDGET SAMI-TF'!J12:J99999,SUMMARY!A46&"*") -> 5 | H46: =SUMIFS('PLAN BUDGET SAMI-TF'!AQ12:AQ99999,'PLAN BUDGET SAMI-TF'!D12:D99999,SUMMARY!D46,'PLAN BUDGET SAMI-TF'!J12:J99999,SUMMARY!A46&"*") -> 5 | I46: =SUMIFS('PLAN BUDGET SAMI-TF'!AR12:AR99999,'PLAN BUDGET SAMI-TF'!D12:D99999,SUMMARY!D46,'PLAN BUDGET SAMI-TF'!J12:J99999,SUMMARY!A46&"*") -> 4 | J46: =SUMIFS('PLAN BUDGET SAMI-TF'!AS12:AS99999,'PLAN BUDGET SAMI-TF'!D12:D99999,SUMMARY!D46,'PLAN BUDGET SAMI-TF'!J12:J99999,SUMMARY!A46&"*") -> 5 | K46: =SUMIFS('PLAN BUDGET SAMI-TF'!AT12:AT99999,'PLAN BUDGET SAMI-TF'!D12:D99999,SUMMARY!D46,'PLAN BUDGET SAMI-TF'!J12:J99999,SUMMARY!A46&"*") -> 5 | L46: =SUMIFS('PLAN BUDGET SAMI-TF'!AU12:AU99999,'PLAN BUDGET SAMI-TF'!D12:D99999,SUMMARY!D46,'PLAN BUDGET SAMI-TF'!J12:J99999,SUMMARY!A46&"*") -> 5 | M46: =SUMIFS('PLAN BUDGET SAMI-TF'!AV12:AV99999,'PLAN BUDGET SAMI-TF'!D12:D99999,SUMMARY!D46,'PLAN BUDGET SAMI-TF'!J12:J99999,SUMMARY!A46&"*") -> 4 | N46: =SUMIFS('PLAN BUDGET SAMI-TF'!AW12:AW99999,'PLAN BUDGET SAMI-TF'!D12:D99999,SUMMARY!D46,'PLAN BUDGET SAMI-TF'!J12:J99999,SUMMARY!A46&"*") -> 6 | O46: =SUMIFS('PLAN BUDGET SAMI-TF'!AX12:AX99999,'PLAN BUDGET SAMI-TF'!D12:D99999,SUMMARY!D46,'PLAN BUDGET SAMI-TF'!J12:J99999,SUMMARY!A46&"*") -> 4 | P46: =SUMIFS('PLAN BUDGET SAMI-TF'!AY12:AY99999,'PLAN BUDGET SAMI-TF'!D12:D99999,SUMMARY!D46,'PLAN BUDGET SAMI-TF'!J12:J99999,SUMMARY!A46&"*") -> 4 | Q46: =SUMIFS('PLAN BUDGET SAMI-TF'!BC12:BC99999,'PLAN BUDGET SAMI-TF'!D12:D99999,SUMMARY!D46,'PLAN BUDGET SAMI-TF'!J12:J99999,SUMMARY!A46&"*") -> 25.318699 | R46: =SUMIFS('PLAN BUDGET SAMI-TF'!BD12:BD99999,'PLAN BUDGET SAMI-TF'!D12:D99999,SUMMARY!D46,'PLAN BUDGET SAMI-TF'!J12:J99999,SUMMARY!A46&"*") -> 18.989024 | S46: =SUMIFS('PLAN BUDGET SAMI-TF'!BE12:BE99999,'PLAN BUDGET SAMI-TF'!D12:D99999,SUMMARY!D46,'PLAN BUDGET SAMI-TF'!J12:J99999,SUMMARY!A46&"*") -> 23.73628 | T46: =SUMIFS('PLAN BUDGET SAMI-TF'!BF12:BF99999,'PLAN BUDGET SAMI-TF'!D12:D99999,SUMMARY!D46,'PLAN BUDGET SAMI-TF'!J12:J99999,SUMMARY!A46&"*") -> 23.73628 | U46: =SUMIFS('PLAN BUDGET SAMI-TF'!BG12:BG99999,'PLAN BUDGET SAMI-TF'!D12:D99999,SUMMARY!D46,'PLAN BUDGET SAMI-TF'!J12:J99999,SUMMARY!A46&"*") -> 18.989024 | V46: =SUMIFS('PLAN BUDGET SAMI-TF'!BH12:BH99999,'PLAN BUDGET SAMI-TF'!D12:D99999,SUMMARY!D46,'PLAN BUDGET SAMI-TF'!J12:J99999,SUMMARY!A46&"*") -> 23.73628 | W46: =SUMIFS('PLAN BUDGET SAMI-TF'!BI12:BI99999,'PLAN BUDGET SAMI-TF'!D12:D99999,SUMMARY!D46,'PLAN BUDGET SAMI-TF'!J12:J99999,SUMMARY!A46&"*") -> 25.318699 | X46: =SUMIFS('PLAN BUDGET SAMI-TF'!BJ12:BJ99999,'PLAN BUDGET SAMI-TF'!D12:D99999,SUMMARY!D46,'PLAN BUDGET SAMI-TF'!J12:J99999,SUMMARY!A46&"*") -> 24.685732 | Y46: =SUMIFS('PLAN BUDGET SAMI-TF'!BK12:BK99999,'PLAN BUDGET SAMI-TF'!D12:D99999,SUMMARY!D46,'PLAN BUDGET SAMI-TF'!J12:J99999,SUMMARY!A46&"*") -> 18.989024 | Z46: =SUMIFS('PLAN BUDGET SAMI-TF'!BL12:BL99999,'PLAN BUDGET SAMI-TF'!D12:D99999,SUMMARY!D46,'PLAN BUDGET SAMI-TF'!J12:J99999,SUMMARY!A46&"*") -> 28.483537 | AA46: =SUMIFS('PLAN BUDGET SAMI-TF'!BM12:BM99999,'PLAN BUDGET SAMI-TF'!D12:D99999,SUMMARY!D46,'PLAN BUDGET SAMI-TF'!J12:J99999,SUMMARY!A46&"*") -> 18.989024 | AB46: =SUMIFS('PLAN BUDGET SAMI-TF'!BN12:BN99999,'PLAN BUDGET SAMI-TF'!D12:D99999,SUMMARY!D46,'PLAN BUDGET SAMI-TF'!J12:J99999,SUMMARY!A46&"*") -> 18.989024 | AC46: =SUM(E46:P46) -> 56 | AD46: =SUM(Q46:AB46) -> 269.96063 | AF46: 56 | AG46: 268.81774 | AH46: =IFERROR((AC46-AF46)/AF46,1) -> 0 | AI46: =IFERROR((AD46-AG46)/AG46,1) -> 0.0042515277 | AJ46: Ada kenaikan harga
A47: RUTIN | D47: KURSI | E47: =SUMIFS('PLAN BUDGET SAMI-TF'!AN12:AN99999,'PLAN BUDGET SAMI-TF'!D12:D99999,SUMMARY!D47,'PLAN BUDGET SAMI-TF'!J12:J99999,SUMMARY!A47&"*") -> 50 | F47: =SUMIFS('PLAN BUDGET SAMI-TF'!AO12:AO99999,'PLAN BUDGET SAMI-TF'!D12:D99999,SUMMARY!D47,'PLAN BUDGET SAMI-TF'!J12:J99999,SUMMARY!A47&"*") -> 0 | G47: =SUMIFS('PLAN BUDGET SAMI-TF'!AP12:AP99999,'PLAN BUDGET SAMI-TF'!D12:D99999,SUMMARY!D47,'PLAN BUDGET SAMI-TF'!J12:J99999,SUMMARY!A47&"*") -> 0 | H47: =SUMIFS('PLAN BUDGET SAMI-TF'!AQ12:AQ99999,'PLAN BUDGET SAMI-TF'!D12:D99999,SUMMARY!D47,'PLAN BUDGET SAMI-TF'!J12:J99999,SUMMARY!A47&"*") -> 0 | I47: =SUMIFS('PLAN BUDGET SAMI-TF'!AR12:AR99999,'PLAN BUDGET SAMI-TF'!D12:D99999,SUMMARY!D47,'PLAN BUDGET SAMI-TF'!J12:J99999,SUMMARY!A47&"*") -> 0 | J47: =SUMIFS('PLAN BUDGET SAMI-TF'!AS12:AS99999,'PLAN BUDGET SAMI-TF'!D12:D99999,SUMMARY!D47,'PLAN BUDGET SAMI-TF'!J12:J99999,SUMMARY!A47&"*") -> 0 | K47: =SUMIFS('PLAN BUDGET SAMI-TF'!AT12:AT99999,'PLAN BUDGET SAMI-TF'!D12:D99999,SUMMARY!D47,'PLAN BUDGET SAMI-TF'!J12:J99999,SUMMARY!A47&"*") -> 50 | L47: =SUMIFS('PLAN BUDGET SAMI-TF'!AU12:AU99999,'PLAN BUDGET SAMI-TF'!D12:D99999,SUMMARY!D47,'PLAN BUDGET SAMI-TF'!J12:J99999,SUMMARY!A47&"*") -> 0 | M47: =SUMIFS('PLAN BUDGET SAMI-TF'!AV12:AV99999,'PLAN BUDGET SAMI-TF'!D12:D99999,SUMMARY!D47,'PLAN BUDGET SAMI-TF'!J12:J99999,SUMMARY!A47&"*") -> 0 | N47: =SUMIFS('PLAN BUDGET SAMI-TF'!AW12:AW99999,'PLAN BUDGET SAMI-TF'!D12:D99999,SUMMARY!D47,'PLAN BUDGET SAMI-TF'!J12:J99999,SUMMARY!A47&"*") -> 0 | O47: =SUMIFS('PLAN BUDGET SAMI-TF'!AX12:AX99999,'PLAN BUDGET SAMI-TF'!D12:D99999,SUMMARY!D47,'PLAN BUDGET SAMI-TF'!J12:J99999,SUMMARY!A47&"*") -> 0 | P47: =SUMIFS('PLAN BUDGET SAMI-TF'!AY12:AY99999,'PLAN BUDGET SAMI-TF'!D12:D99999,SUMMARY!D47,'PLAN BUDGET SAMI-TF'!J12:J99999,SUMMARY!A47&"*") -> 0 | Q47: =SUMIFS('PLAN BUDGET SAMI-TF'!BC12:BC99999,'PLAN BUDGET SAMI-TF'!D12:D99999,SUMMARY!D47,'PLAN BUDGET SAMI-TF'!J12:J99999,SUMMARY!A47&"*") -> 486.59375 | R47: =SUMIFS('PLAN BUDGET SAMI-TF'!BD12:BD99999,'PLAN BUDGET SAMI-TF'!D12:D99999,SUMMARY!D47,'PLAN BUDGET SAMI-TF'!J12:J99999,SUMMARY!A47&"*") -> 0 | S47: =SUMIFS('PLAN BUDGET SAMI-TF'!BE12:BE99999,'PLAN BUDGET SAMI-TF'!D12:D99999,SUMMARY!D47,'PLAN BUDGET SAMI-TF'!J12:J99999,SUMMARY!A47&"*") -> 0 | T47: =SUMIFS('PLAN BUDGET SAMI-TF'!BF12:BF99999,'PLAN BUDGET SAMI-TF'!D12:D99999,SUMMARY!D47,'PLAN BUDGET SAMI-TF'!J12:J99999,SUMMARY!A47&"*") -> 0 | U47: =SUMIFS('PLAN BUDGET SAMI-TF'!BG12:BG99999,'PLAN BUDGET SAMI-TF'!D12:D99999,SUMMARY!D47,'PLAN BUDGET SAMI-TF'!J12:J99999,SUMMARY!A47&"*") -> 0 | V47: =SUMIFS('PLAN BUDGET SAMI-TF'!BH12:BH99999,'PLAN BUDGET SAMI-TF'!D12:D99999,SUMMARY!D47,'PLAN BUDGET SAMI-TF'!J12:J99999,SUMMARY!A47&"*") -> 0 | W47: =SUMIFS('PLAN BUDGET SAMI-TF'!BI12:BI99999,'PLAN BUDGET SAMI-TF'!D12:D99999,SUMMARY!D47,'PLAN BUDGET SAMI-TF'!J12:J99999,SUMMARY!A47&"*") -> 486.59375 | X47: =SUMIFS('PLAN BUDGET SAMI-TF'!BJ12:BJ99999,'PLAN BUDGET SAMI-TF'!D12:D99999,SUMMARY!D47,'PLAN BUDGET SAMI-TF'!J12:J99999,SUMMARY!A47&"*") -> 0 | Y47: =SUMIFS('PLAN BUDGET SAMI-TF'!BK12:BK99999,'PLAN BUDGET SAMI-TF'!D12:D99999,SUMMARY!D47,'PLAN BUDGET SAMI-TF'!J12:J99999,SUMMARY!A47&"*") -> 0 | Z47: =SUMIFS('PLAN BUDGET SAMI-TF'!BL12:BL99999,'PLAN BUDGET SAMI-TF'!D12:D99999,SUMMARY!D47,'PLAN BUDGET SAMI-TF'!J12:J99999,SUMMARY!A47&"*") -> 0 | AA47: =SUMIFS('PLAN BUDGET SAMI-TF'!BM12:BM99999,'PLAN BUDGET SAMI-TF'!D12:D99999,SUMMARY!D47,'PLAN BUDGET SAMI-TF'!J12:J99999,SUMMARY!A47&"*") -> 0 | AB47: =SUMIFS('PLAN BUDGET SAMI-TF'!BN12:BN99999,'PLAN BUDGET SAMI-TF'!D12:D99999,SUMMARY!D47,'PLAN BUDGET SAMI-TF'!J12:J99999,SUMMARY!A47&"*") -> 0 | AC47: =SUM(E47:P47) -> 100 | AD47: =SUM(Q47:AB47) -> 973.1875 | AF47: 100 | AG47: 949.45122 | AH47: =IFERROR((AC47-AF47)/AF47,1) -> 0 | AI47: =IFERROR((AD47-AG47)/AG47,1) -> 0.025 | AJ47: Ada kenaikan harga
A48: RUTIN | D48: MAP | E48: =SUMIFS('PLAN BUDGET SAMI-TF'!AN12:AN99999,'PLAN BUDGET SAMI-TF'!D12:D99999,SUMMARY!D48,'PLAN BUDGET SAMI-TF'!J12:J99999,SUMMARY!A48&"*") -> 0 | F48: =SUMIFS('PLAN BUDGET SAMI-TF'!AO12:AO99999,'PLAN BUDGET SAMI-TF'!D12:D99999,SUMMARY!D48,'PLAN BUDGET SAMI-TF'!J12:J99999,SUMMARY!A48&"*") -> 0 | G48: =SUMIFS('PLAN BUDGET SAMI-TF'!AP12:AP99999,'PLAN BUDGET SAMI-TF'!D12:D99999,SUMMARY!D48,'PLAN BUDGET SAMI-TF'!J12:J99999,SUMMARY!A48&"*") -> 0 | H48: =SUMIFS('PLAN BUDGET SAMI-TF'!AQ12:AQ99999,'PLAN BUDGET SAMI-TF'!D12:D99999,SUMMARY!D48,'PLAN BUDGET SAMI-TF'!J12:J99999,SUMMARY!A48&"*") -> 0 | I48: =SUMIFS('PLAN BUDGET SAMI-TF'!AR12:AR99999,'PLAN BUDGET SAMI-TF'!D12:D99999,SUMMARY!D48,'PLAN BUDGET SAMI-TF'!J12:J99999,SUMMARY!A48&"*") -> 6 | J48: =SUMIFS('PLAN BUDGET SAMI-TF'!AS12:AS99999,'PLAN BUDGET SAMI-TF'!D12:D99999,SUMMARY!D48,'PLAN BUDGET SAMI-TF'!J12:J99999,SUMMARY!A48&"*") -> 0 | K48: =SUMIFS('PLAN BUDGET SAMI-TF'!AT12:AT99999,'PLAN BUDGET SAMI-TF'!D12:D99999,SUMMARY!D48,'PLAN BUDGET SAMI-TF'!J12:J99999,SUMMARY!A48&"*") -> 0 | L48: =SUMIFS('PLAN BUDGET SAMI-TF'!AU12:AU99999,'PLAN BUDGET SAMI-TF'!D12:D99999,SUMMARY!D48,'PLAN BUDGET SAMI-TF'!J12:J99999,SUMMARY!A48&"*") -> 0 | M48: =SUMIFS('PLAN BUDGET SAMI-TF'!AV12:AV99999,'PLAN BUDGET SAMI-TF'!D12:D99999,SUMMARY!D48,'PLAN BUDGET SAMI-TF'!J12:J99999,SUMMARY!A48&"*") -> 0 | N48: =SUMIFS('PLAN BUDGET SAMI-TF'!AW12:AW99999,'PLAN BUDGET SAMI-TF'!D12:D99999,SUMMARY!D48,'PLAN BUDGET SAMI-TF'!J12:J99999,SUMMARY!A48&"*") -> 0 | O48: =SUMIFS('PLAN BUDGET SAMI-TF'!AX12:AX99999,'PLAN BUDGET SAMI-TF'!D12:D99999,SUMMARY!D48,'PLAN BUDGET SAMI-TF'!J12:J99999,SUMMARY!A48&"*") -> 0 | P48: =SUMIFS('PLAN BUDGET SAMI-TF'!AY12:AY99999,'PLAN BUDGET SAMI-TF'!D12:D99999,SUMMARY!D48,'PLAN BUDGET SAMI-TF'!J12:J99999,SUMMARY!A48&"*") -> 0 | Q48: =SUMIFS('PLAN BUDGET SAMI-TF'!BC12:BC99999,'PLAN BUDGET SAMI-TF'!D12:D99999,SUMMARY!D48,'PLAN BUDGET SAMI-TF'!J12:J99999,SUMMARY!A48&"*") -> 0 | R48: =SUMIFS('PLAN BUDGET SAMI-TF'!BD12:BD99999,'PLAN BUDGET SAMI-TF'!D12:D99999,SUMMARY!D48,'PLAN BUDGET SAMI-TF'!J12:J99999,SUMMARY!A48&"*") -> 0 | S48: =SUMIFS('PLAN BUDGET SAMI-TF'!BE12:BE99999,'PLAN BUDGET SAMI-TF'!D12:D99999,SUMMARY!D48,'PLAN BUDGET SAMI-TF'!J12:J99999,SUMMARY!A48&"*") -> 0 | T48: =SUMIFS('PLAN BUDGET SAMI-TF'!BF12:BF99999,'PLAN BUDGET SAMI-TF'!D12:D99999,SUMMARY!D48,'PLAN BUDGET SAMI-TF'!J12:J99999,SUMMARY!A48&"*") -> 0 | U48: =SUMIFS('PLAN BUDGET SAMI-TF'!BG12:BG99999,'PLAN BUDGET SAMI-TF'!D12:D99999,SUMMARY!D48,'PLAN BUDGET SAMI-TF'!J12:J99999,SUMMARY!A48&"*") -> 0.71854468 | V48: =SUMIFS('PLAN BUDGET SAMI-TF'!BH12:BH99999,'PLAN BUDGET SAMI-TF'!D12:D99999,SUMMARY!D48,'PLAN BUDGET SAMI-TF'!J12:J99999,SUMMARY!A48&"*") -> 0 | W48: =SUMIFS('PLAN BUDGET SAMI-TF'!BI12:BI99999,'PLAN BUDGET SAMI-TF'!D12:D99999,SUMMARY!D48,'PLAN BUDGET SAMI-TF'!J12:J99999,SUMMARY!A48&"*") -> 0 | X48: =SUMIFS('PLAN BUDGET SAMI-TF'!BJ12:BJ99999,'PLAN BUDGET SAMI-TF'!D12:D99999,SUMMARY!D48,'PLAN BUDGET SAMI-TF'!J12:J99999,SUMMARY!A48&"*") -> 0 | Y48: =SUMIFS('PLAN BUDGET SAMI-TF'!BK12:BK99999,'PLAN BUDGET SAMI-TF'!D12:D99999,SUMMARY!D48,'PLAN BUDGET SAMI-TF'!J12:J99999,SUMMARY!A48&"*") -> 0 | Z48: =SUMIFS('PLAN BUDGET SAMI-TF'!BL12:BL99999,'PLAN BUDGET SAMI-TF'!D12:D99999,SUMMARY!D48,'PLAN BUDGET SAMI-TF'!J12:J99999,SUMMARY!A48&"*") -> 0 | AA48: =SUMIFS('PLAN BUDGET SAMI-TF'!BM12:BM99999,'PLAN BUDGET SAMI-TF'!D12:D99999,SUMMARY!D48,'PLAN BUDGET SAMI-TF'!J12:J99999,SUMMARY!A48&"*") -> 0 | AB48: =SUMIFS('PLAN BUDGET SAMI-TF'!BN12:BN99999,'PLAN BUDGET SAMI-TF'!D12:D99999,SUMMARY!D48,'PLAN BUDGET SAMI-TF'!J12:J99999,SUMMARY!A48&"*") -> 0 | AC48: =SUM(E48:P48) -> 6 | AD48: =SUM(Q48:AB48) -> 0.71854468 | AF48: 0 | AG48: 0 | AH48: =IFERROR((AC48-AF48)/AF48,1) -> 1 | AI48: =IFERROR((AD48-AG48)/AG48,1) -> 1 | AJ48: New item di th 85
A49: RUTIN | D49: BATERAI | E49: =SUMIFS('PLAN BUDGET SAMI-TF'!AN12:AN99999,'PLAN BUDGET SAMI-TF'!D12:D99999,SUMMARY!D49,'PLAN BUDGET SAMI-TF'!J12:J99999,SUMMARY!A49&"*") -> 1 | F49: =SUMIFS('PLAN BUDGET SAMI-TF'!AO12:AO99999,'PLAN BUDGET SAMI-TF'!D12:D99999,SUMMARY!D49,'PLAN BUDGET SAMI-TF'!J12:J99999,SUMMARY!A49&"*") -> 1 | G49: =SUMIFS('PLAN BUDGET SAMI-TF'!AP12:AP99999,'PLAN BUDGET SAMI-TF'!D12:D99999,SUMMARY!D49,'PLAN BUDGET SAMI-TF'!J12:J99999,SUMMARY!A49&"*") -> 0 | H49: =SUMIFS('PLAN BUDGET SAMI-TF'!AQ12:AQ99999,'PLAN BUDGET SAMI-TF'!D12:D99999,SUMMARY!D49,'PLAN BUDGET SAMI-TF'!J12:J99999,SUMMARY!A49&"*") -> 1 | I49: =SUMIFS('PLAN BUDGET SAMI-TF'!AR12:AR99999,'PLAN BUDGET SAMI-TF'!D12:D99999,SUMMARY!D49,'PLAN BUDGET SAMI-TF'!J12:J99999,SUMMARY!A49&"*") -> 0 | J49: =SUMIFS('PLAN BUDGET SAMI-TF'!AS12:AS99999,'PLAN BUDGET SAMI-TF'!D12:D99999,SUMMARY!D49,'PLAN BUDGET SAMI-TF'!J12:J99999,SUMMARY!A49&"*") -> 2 | K49: =SUMIFS('PLAN BUDGET SAMI-TF'!AT12:AT99999,'PLAN BUDGET SAMI-TF'!D12:D99999,SUMMARY!D49,'PLAN BUDGET SAMI-TF'!J12:J99999,SUMMARY!A49&"*") -> 0 | L49: =SUMIFS('PLAN BUDGET SAMI-TF'!AU12:AU99999,'PLAN BUDGET SAMI-TF'!D12:D99999,SUMMARY!D49,'PLAN BUDGET SAMI-TF'!J12:J99999,SUMMARY!A49&"*") -> 0 | M49: =SUMIFS('PLAN BUDGET SAMI-TF'!AV12:AV99999,'PLAN BUDGET SAMI-TF'!D12:D99999,SUMMARY!D49,'PLAN BUDGET SAMI-TF'!J12:J99999,SUMMARY!A49&"*") -> 0 | N49: =SUMIFS('PLAN BUDGET SAMI-TF'!AW12:AW99999,'PLAN BUDGET SAMI-TF'!D12:D99999,SUMMARY!D49,'PLAN BUDGET SAMI-TF'!J12:J99999,SUMMARY!A49&"*") -> 1 | O49: =SUMIFS('PLAN BUDGET SAMI-TF'!AX12:AX99999,'PLAN BUDGET SAMI-TF'!D12:D99999,SUMMARY!D49,'PLAN BUDGET SAMI-TF'!J12:J99999,SUMMARY!A49&"*") -> 1 | P49: =SUMIFS('PLAN BUDGET SAMI-TF'!AY12:AY99999,'PLAN BUDGET SAMI-TF'!D12:D99999,SUMMARY!D49,'PLAN BUDGET SAMI-TF'!J12:J99999,SUMMARY!A49&"*") -> 1 | Q49: =SUMIFS('PLAN BUDGET SAMI-TF'!BC12:BC99999,'PLAN BUDGET SAMI-TF'!D12:D99999,SUMMARY!D49,'PLAN BUDGET SAMI-TF'!J12:J99999,SUMMARY!A49&"*") -> 3.1015406 | R49: =SUMIFS('PLAN BUDGET SAMI-TF'!BD12:BD99999,'PLAN BUDGET SAMI-TF'!D12:D99999,SUMMARY!D49,'PLAN BUDGET SAMI-TF'!J12:J99999,SUMMARY!A49&"*") -> 3.1064145 | S49: =SUMIFS('PLAN BUDGET SAMI-TF'!BE12:BE99999,'PLAN BUDGET SAMI-TF'!D12:D99999,SUMMARY!D49,'PLAN BUDGET SAMI-TF'!J12:J99999,SUMMARY!A49&"*") -> 0 | T49: =SUMIFS('PLAN BUDGET SAMI-TF'!BF12:BF99999,'PLAN BUDGET SAMI-TF'!D12:D99999,SUMMARY!D49,'PLAN BUDGET SAMI-TF'!J12:J99999,SUMMARY!A49&"*") -> 0.61524914 | U49: =SUMIFS('PLAN BUDGET SAMI-TF'!BG12:BG99999,'PLAN BUDGET SAMI-TF'!D12:D99999,SUMMARY!D49,'PLAN BUDGET SAMI-TF'!J12:J99999,SUMMARY!A49&"*") -> 0 | V49: =SUMIFS('PLAN BUDGET SAMI-TF'!BH12:BH99999,'PLAN BUDGET SAMI-TF'!D12:D99999,SUMMARY!D49,'PLAN BUDGET SAMI-TF'!J12:J99999,SUMMARY!A49&"*") -> 6.2079551 | W49: =SUMIFS('PLAN BUDGET SAMI-TF'!BI12:BI99999,'PLAN BUDGET SAMI-TF'!D12:D99999,SUMMARY!D49,'PLAN BUDGET SAMI-TF'!J12:J99999,SUMMARY!A49&"*") -> 0 | X49: =SUMIFS('PLAN BUDGET SAMI-TF'!BJ12:BJ99999,'PLAN BUDGET SAMI-TF'!D12:D99999,SUMMARY!D49,'PLAN BUDGET SAMI-TF'!J12:J99999,SUMMARY!A49&"*") -> 0 | Y49: =SUMIFS('PLAN BUDGET SAMI-TF'!BK12:BK99999,'PLAN BUDGET SAMI-TF'!D12:D99999,SUMMARY!D49,'PLAN BUDGET SAMI-TF'!J12:J99999,SUMMARY!A49&"*") -> 0 | Z49: =SUMIFS('PLAN BUDGET SAMI-TF'!BL12:BL99999,'PLAN BUDGET SAMI-TF'!D12:D99999,SUMMARY!D49,'PLAN BUDGET SAMI-TF'!J12:J99999,SUMMARY!A49&"*") -> 3.1064145 | AA49: =SUMIFS('PLAN BUDGET SAMI-TF'!BM12:BM99999,'PLAN BUDGET SAMI-TF'!D12:D99999,SUMMARY!D49,'PLAN BUDGET SAMI-TF'!J12:J99999,SUMMARY!A49&"*") -> 3.1015406 | AB49: =SUMIFS('PLAN BUDGET SAMI-TF'!BN12:BN99999,'PLAN BUDGET SAMI-TF'!D12:D99999,SUMMARY!D49,'PLAN BUDGET SAMI-TF'!J12:J99999,SUMMARY!A49&"*") -> 0.61524914 | AC49: =SUM(E49:P49) -> 8 | AD49: =SUM(Q49:AB49) -> 19.854364 | AF49: 8 | AG49: 19.820934 | AH49: =IFERROR((AC49-AF49)/AF49,1) -> 0 | AI49: =IFERROR((AD49-AG49)/AG49,1) -> 0.0016866096 | AJ49: Ada kenaikan harga
A50: RUTIN | D50: DEKORASI QCC | E50: =SUMIFS('PLAN BUDGET SAMI-TF'!AN12:AN99999,'PLAN BUDGET SAMI-TF'!D12:D99999,SUMMARY!D50,'PLAN BUDGET SAMI-TF'!J12:J99999,SUMMARY!A50&"*") -> 0 | F50: =SUMIFS('PLAN BUDGET SAMI-TF'!AO12:AO99999,'PLAN BUDGET SAMI-TF'!D12:D99999,SUMMARY!D50,'PLAN BUDGET SAMI-TF'!J12:J99999,SUMMARY!A50&"*") -> 1 | G50: =SUMIFS('PLAN BUDGET SAMI-TF'!AP12:AP99999,'PLAN BUDGET SAMI-TF'!D12:D99999,SUMMARY!D50,'PLAN BUDGET SAMI-TF'!J12:J99999,SUMMARY!A50&"*") -> 0 | H50: =SUMIFS('PLAN BUDGET SAMI-TF'!AQ12:AQ99999,'PLAN BUDGET SAMI-TF'!D12:D99999,SUMMARY!D50,'PLAN BUDGET SAMI-TF'!J12:J99999,SUMMARY!A50&"*") -> 0 | I50: =SUMIFS('PLAN BUDGET SAMI-TF'!AR12:AR99999,'PLAN BUDGET SAMI-TF'!D12:D99999,SUMMARY!D50,'PLAN BUDGET SAMI-TF'!J12:J99999,SUMMARY!A50&"*") -> 0 | J50: =SUMIFS('PLAN BUDGET SAMI-TF'!AS12:AS99999,'PLAN BUDGET SAMI-TF'!D12:D99999,SUMMARY!D50,'PLAN BUDGET SAMI-TF'!J12:J99999,SUMMARY!A50&"*") -> 0 | K50: =SUMIFS('PLAN BUDGET SAMI-TF'!AT12:AT99999,'PLAN BUDGET SAMI-TF'!D12:D99999,SUMMARY!D50,'PLAN BUDGET SAMI-TF'!J12:J99999,SUMMARY!A50&"*") -> 1 | L50: =SUMIFS('PLAN BUDGET SAMI-TF'!AU12:AU99999,'PLAN BUDGET SAMI-TF'!D12:D99999,SUMMARY!D50,'PLAN BUDGET SAMI-TF'!J12:J99999,SUMMARY!A50&"*") -> 0 | M50: =SUMIFS('PLAN BUDGET SAMI-TF'!AV12:AV99999,'PLAN BUDGET SAMI-TF'!D12:D99999,SUMMARY!D50,'PLAN BUDGET SAMI-TF'!J12:J99999,SUMMARY!A50&"*") -> 0 | N50: =SUMIFS('PLAN BUDGET SAMI-TF'!AW12:AW99999,'PLAN BUDGET SAMI-TF'!D12:D99999,SUMMARY!D50,'PLAN BUDGET SAMI-TF'!J12:J99999,SUMMARY!A50&"*") -> 0 | O50: =SUMIFS('PLAN BUDGET SAMI-TF'!AX12:AX99999,'PLAN BUDGET SAMI-TF'!D12:D99999,SUMMARY!D50,'PLAN BUDGET SAMI-TF'!J12:J99999,SUMMARY!A50&"*") -> 0 | P50: =SUMIFS('PLAN BUDGET SAMI-TF'!AY12:AY99999,'PLAN BUDGET SAMI-TF'!D12:D99999,SUMMARY!D50,'PLAN BUDGET SAMI-TF'!J12:J99999,SUMMARY!A50&"*") -> 0 | Q50: =SUMIFS('PLAN BUDGET SAMI-TF'!BC12:BC99999,'PLAN BUDGET SAMI-TF'!D12:D99999,SUMMARY!D50,'PLAN BUDGET SAMI-TF'!J12:J99999,SUMMARY!A50&"*") -> 0 | R50: =SUMIFS('PLAN BUDGET SAMI-TF'!BD12:BD99999,'PLAN BUDGET SAMI-TF'!D12:D99999,SUMMARY!D50,'PLAN BUDGET SAMI-TF'!J12:J99999,SUMMARY!A50&"*") -> 50.637398 | S50: =SUMIFS('PLAN BUDGET SAMI-TF'!BE12:BE99999,'PLAN BUDGET SAMI-TF'!D12:D99999,SUMMARY!D50,'PLAN BUDGET SAMI-TF'!J12:J99999,SUMMARY!A50&"*") -> 0 | T50: =SUMIFS('PLAN BUDGET SAMI-TF'!BF12:BF99999,'PLAN BUDGET SAMI-TF'!D12:D99999,SUMMARY!D50,'PLAN BUDGET SAMI-TF'!J12:J99999,SUMMARY!A50&"*") -> 0 | U50: =SUMIFS('PLAN BUDGET SAMI-TF'!BG12:BG99999,'PLAN BUDGET SAMI-TF'!D12:D99999,SUMMARY!D50,'PLAN BUDGET SAMI-TF'!J12:J99999,SUMMARY!A50&"*") -> 0 | V50: =SUMIFS('PLAN BUDGET SAMI-TF'!BH12:BH99999,'PLAN BUDGET SAMI-TF'!D12:D99999,SUMMARY!D50,'PLAN BUDGET SAMI-TF'!J12:J99999,SUMMARY!A50&"*") -> 0 | W50: =SUMIFS('PLAN BUDGET SAMI-TF'!BI12:BI99999,'PLAN BUDGET SAMI-TF'!D12:D99999,SUMMARY!D50,'PLAN BUDGET SAMI-TF'!J12:J99999,SUMMARY!A50&"*") -> 50.637398 | X50: =SUMIFS('PLAN BUDGET SAMI-TF'!BJ12:BJ99999,'PLAN BUDGET SAMI-TF'!D12:D99999,SUMMARY!D50,'PLAN BUDGET SAMI-TF'!J12:J99999,SUMMARY!A50&"*") -> 0 | Y50: =SUMIFS('PLAN BUDGET SAMI-TF'!BK12:BK99999,'PLAN BUDGET SAMI-TF'!D12:D99999,SUMMARY!D50,'PLAN BUDGET SAMI-TF'!J12:J99999,SUMMARY!A50&"*") -> 0 | Z50: =SUMIFS('PLAN BUDGET SAMI-TF'!BL12:BL99999,'PLAN BUDGET SAMI-TF'!D12:D99999,SUMMARY!D50,'PLAN BUDGET SAMI-TF'!J12:J99999,SUMMARY!A50&"*") -> 0 | AA50: =SUMIFS('PLAN BUDGET SAMI-TF'!BM12:BM99999,'PLAN BUDGET SAMI-TF'!D12:D99999,SUMMARY!D50,'PLAN BUDGET SAMI-TF'!J12:J99999,SUMMARY!A50&"*") -> 0 | AB50: =SUMIFS('PLAN BUDGET SAMI-TF'!BN12:BN99999,'PLAN BUDGET SAMI-TF'!D12:D99999,SUMMARY!D50,'PLAN BUDGET SAMI-TF'!J12:J99999,SUMMARY!A50&"*") -> 0 | AC50: =SUM(E50:P50) -> 2 | AD50: =SUM(Q50:AB50) -> 101.2748 | AF50: 0 | AG50: 0 | AH50: =IFERROR((AC50-AF50)/AF50,1) -> 1 | AI50: =IFERROR((AD50-AG50)/AG50,1) -> 1 | AJ50: New item di th 85
