Workbook

Sheet 78
A2: Now day
A4: NO | B4: BIDANG | C4: NOW DAY
C5: Jml regulasi | D5: Identifikasi | F5: Evaluasi | H5: Implementasi
D6: Jml | E6: % | F6: Jml | G6: % | H6: Jml | I6: %
A7: 1 | B7: CORPORATE MATTERS | C7: ='Detail COMPLIANCE FIELD'!G15 -> 0 | D7: =C7 -> 0 | E7: 1 | F7: ='Detail COMPLIANCE FIELD'!I15 -> 0 | G7: 1 | H7: ='Detail COMPLIANCE FIELD'!K15 -> 0 | I7: 1
A8: 2 | B8: LABOR & HUMAN RIGHTS | C8: ='Detail COMPLIANCE FIELD'!G16 -> 99 | D8: =C8 -> 99 | E8: =D8/C8 -> 1 | F8: ='Detail COMPLIANCE FIELD'!I16 -> 99 | G8: =F8/C8 -> 1 | H8: ='Detail COMPLIANCE FIELD'!K16 -> 98 | I8: =H8/C8 -> 0.98989899
A9: 3 | B9: INTELLECTUAL PROPERTY | C9: ='Detail COMPLIANCE FIELD'!G17 -> 126 | D9: =C9 -> 126 | E9: =D9/C9 -> 1 | F9: ='Detail COMPLIANCE FIELD'!I17 -> 126 | G9: =F9/C9 -> 1 | H9: ='Detail COMPLIANCE FIELD'!K17 -> 122 | I9: =H9/C9 -> 0.96825397
A10: 4 | B10: FAIR TRADING | C10: ='Detail COMPLIANCE FIELD'!G18 -> 7 | D10: =C10 -> 7 | E10: =D10/C10 -> 1 | F10: ='Detail COMPLIANCE FIELD'!I18 -> 7 | G10: =F10/C10 -> 1 | H10: ='Detail COMPLIANCE FIELD'!K18 -> 7 | I10: =H10/C10 -> 1
A11: 5 | B11: SAFETY & HEALTH | C11: ='Detail COMPLIANCE FIELD'!G19 -> 6 | D11: =C11 -> 6 | E11: =D11/C11 -> 1 | F11: ='Detail COMPLIANCE FIELD'!I19 -> 6 | G11: =F11/C11 -> 1 | H11: ='Detail COMPLIANCE FIELD'!K19 -> 6 | I11: =H11/C11 -> 1
A12: 6 | B12: ENVIRONMENT | C12: ='Detail COMPLIANCE FIELD'!G20 -> 37 | D12: =C12 -> 37 | E12: =D12/C12 -> 1 | F12: ='Detail COMPLIANCE FIELD'!I20 -> 37 | G12: =F12/C12 -> 1 | H12: ='Detail COMPLIANCE FIELD'!K20 -> 37 | I12: =H12/C12 -> 1
B13: TOTAL | C13: =SUM(C7:C12) -> 275 | D13: =SUM(D7:D12) -> 275 | E13: =D13/C13 -> 1 | F13: =SUM(F7:F12) -> 275 | G13: =F13/C13 -> 1 | H13: =SUM(H7:H12) -> 270 | I13: =H13/C13 -> 0.98181818
A15: 7 | B15: EXIM MANAGEMENT | C15: ='Detail COMPLIANCE FIELD'!G21 -> 56 | D15: =C15 -> 56 | E15: =D15/C15 -> 1 | F15: ='Detail COMPLIANCE FIELD'!I21 -> 56 | G15: =F15/C15 -> 1 | H15: ='Detail COMPLIANCE FIELD'!K21 -> 56 | I15: =H15/C15 -> 1
A16: 8 | B16: FINANCE ACCOUNTING | C16: ='Detail COMPLIANCE FIELD'!G22 -> 123 | D16: =C16 -> 123 | E16: =D16/C16 -> 1 | F16: ='Detail COMPLIANCE FIELD'!I22 -> 123 | G16: =F16/C16 -> 1 | H16: ='Detail COMPLIANCE FIELD'!K22 -> 116 | I16: =H16/C16 -> 0.94308943
B17: TOTAL | C17: =SUM(C15:C16)+C13 -> 454 | D17: =SUM(D15:D16)+D13 -> 454 | E17: =D17/C17 -> 1 | F17: =SUM(F15:F16)+F13 -> 454 | G17: =F17/C17 -> 1 | H17: =SUM(H15:H16)+H13 -> 442 | I17: =H17/C17 -> 0.97356828
A18: PT. SEMARANG AUTOCOMP MANUFACTURING INDONESIA
A19: KEPATUHAN TERHADAP PERATURAN PERUNDANGAN
A22: NO | B22: BIDANG | C22: 43282 | J22: 43313 | Q22: 43344
C23: Jml regulasi | D23: Identifikasi | F23: Evaluasi | H23: Implementasi | J23: Jml regulasi | K23: Identifikasi | M23: Evaluasi | O23: Implementasi | Q23: Jml regulasi | R23: Identifikasi | T23: Evaluasi | V23: Implementasi
D24: Jml | E24: % | F24: Jml | G24: % | H24: Jml | I24: % | K24: Jml | L24: % | M24: Jml | N24: % | O24: Jml | P24: % | R24: Jml | S24: % | T24: Jml | U24: % | V24: Jml | W24: %
A25: 1 | B25: CORPORATE MATTERS | C25: 22 | D25: 22 | E25: =D25/C25 -> 1 | F25: 22 | G25: =F25/C25 -> 1 | H25: 20 | I25: =H25/C25 -> 0.90909091 | J25: 48 | K25: 48 | L25: =K25/J25 -> 1 | M25: 27 | N25: =M25/J25 -> 0.5625 | O25: 20 | P25: =O25/J25 -> 0.41666667 | Q25: 48 | R25: 48 | S25: =R25/Q25 -> 1 | T25: 27 | U25: =T25/Q25 -> 0.5625 | V25: 25 | W25: =V25/Q25 -> 0.52083333
A26: 2 | B26: LABOR & HUMAN RIGHTS | C26: 21 | D26: 21 | E26: =D26/C26 -> 1 | F26: 0 | G26: =F26/C26 -> 0 | H26: 0 | I26: =H26/C26 -> 0 | J26: 41 | K26: 41 | L26: =K26/J26 -> 1 | M26: 11 | N26: =M26/J26 -> 0.26829268 | O26: 11 | P26: =O26/J26 -> 0.26829268 | Q26: 36 | R26: 36 | S26: =R26/Q26 -> 1 | T26: 11 | U26: =T26/Q26 -> 0.30555556 | V26: 11 | W26: =V26/Q26 -> 0.30555556
A27: 3 | B27: INTELLECTUAL PROPERTY | C27: 2 | D27: 2 | E27: =D27/C27 -> 1 | F27: 2 | G27: =F27/C27 -> 1 | H27: 0 | I27: =H27/C27 -> 0 | J27: 2 | K27: 2 | L27: =K27/J27 -> 1 | M27: 2 | N27: =M27/J27 -> 1 | O27: 2 | P27: =O27/J27 -> 1 | Q27: 2 | R27: 2 | S27: =R27/Q27 -> 1 | T27: 2 | U27: =T27/Q27 -> 1 | V27: 2 | W27: =V27/Q27 -> 1
A28: 4 | B28: FAIR TRADING | C28: 2 | D28: 2 | E28: =D28/C28 -> 1 | F28: 2 | G28: =F28/C28 -> 1 | H28: 0 | I28: =H28/C28 -> 0 | J28: 2 | K28: 2 | L28: =K28/J28 -> 1 | M28: 2 | N28: =M28/J28 -> 1 | O28: 0 | P28: =O28/J28 -> 0 | Q28: 2 | R28: 2 | S28: =R28/Q28 -> 1 | T28: 2 | U28: =T28/Q28 -> 1 | V28: 2 | W28: =V28/Q28 -> 1
A29: 6 | B29: ENVIRONMENT | C29: 50 | D29: 50 | E29: =D29/C29 -> 1 | F29: 50 | G29: =F29/C29 -> 1 | H29: 49 | I29: =H29/C29 -> 0.98 | J29: 57 | K29: 57 | L29: =K29/J29 -> 1 | M29: 50 | N29: =M29/J29 -> 0.87719298 | O29: 49 | P29: =O29/J29 -> 0.85964912 | Q29: 57 | R29: 57 | S29: =R29/Q29 -> 1 | T29: 50 | U29: =T29/Q29 -> 0.87719298 | V29: 49 | W29: =V29/Q29 -> 0.85964912
A30: 7 | B30: SAFETY & HEALTH | C30: 27 | D30: 27 | E30: =D30/C30 -> 1 | F30: 27 | G30: =F30/C30 -> 1 | H30: 27 | I30: =H30/C30 -> 1 | J30: 27 | K30: 27 | L30: =K30/J30 -> 1 | M30: 27 | N30: =M30/J30 -> 1 | O30: 27 | P30: =O30/J30 -> 1 | Q30: 27 | R30: 27 | S30: =R30/Q30 -> 1 | T30: 27 | U30: =T30/Q30 -> 1 | V30: 27 | W30: =V30/Q30 -> 1
B31: TOTAL | C31: =SUM(C25:C30) -> 124 | D31: =SUM(D25:D30) -> 124 | E31: =D31/C31 -> 1 | F31: =SUM(F25:F30) -> 103 | G31: =F31/C31 -> 0.83064516 | H31: =SUM(H25:H30) -> 96 | I31: =H31/C31 -> 0.77419355 | J31: =SUM(J25:J30) -> 177 | K31: =SUM(K25:K30) -> 177 | L31: =K31/J31 -> 1 | M31: =SUM(M25:M30) -> 119 | N31: =M31/J31 -> 0.67231638 | O31: =SUM(O25:O30) -> 109 | P31: =O31/J31 -> 0.61581921 | Q31: =SUM(Q25:Q30) -> 172 | R31: =SUM(R25:R30) -> 172 | S31: =R31/Q31 -> 1 | T31: =SUM(T25:T30) -> 119 | U31: =SUM(U25:U30) -> 4.7452485 | V31: =SUM(V25:V30) -> 116 | W31: =V31/Q31 -> 0.6744186
A33: 5 | B33: EXIM MANAGEMENT | C33: 21 | D33: 21 | E33: =D33/C33 -> 1 | F33: 0 | G33: =F33/C33 -> 0 | H33: 0 | I33: =H33/C33 -> 0 | J33: 21 | K33: 21 | L33: =K33/J33 -> 1 | M33: 0 | N33: =M33/J33 -> 0 | O33: 0 | P33: =O33/J33 -> 0 | Q33: 21 | R33: 21 | S33: =R33/Q33 -> 1 | T33: 0 | U33: =T33/Q33 -> 0 | V33: 0 | W33: =V33/Q33 -> 0
A34: 8 | B34: FINANCE ACCOUNTING | C34: 19 | D34: 19 | E34: =D34/C34 -> 1 | F34: 0 | G34: =F34/C34 -> 0 | H34: 0 | I34: =H34/C34 -> 0 | J34: 19 | K34: 19 | L34: =K34/J34 -> 1 | M34: 0 | N34: =M34/J34 -> 0 | O34: 0 | P34: =O34/J34 -> 0 | Q34: 19 | R34: 19 | S34: =R34/Q34 -> 1 | T34: 0 | U34: =T34/Q34 -> 0 | V34: 0 | W34: =V34/Q34 -> 0
B35: TOTAL | C35: =SUM(C33:C34)+C31 -> 164 | D35: =SUM(D33:D34)+D31 -> 164 | E35: =D35/C35 -> 1 | F35: =SUM(F33:F34)+F31 -> 103 | G35: =F35/C35 -> 0.62804878 | H35: =SUM(H33:H34)+H31 -> 96 | I35: =H35/C35 -> 0.58536585 | J35: =SUM(J33:J34)+J31 -> 217 | K35: =SUM(K33:K34)+K31 -> 217 | L35: =K35/J35 -> 1 | M35: =SUM(M33:M34)+M31 -> 119 | N35: =M35/J35 -> 0.5483871 | O35: =SUM(O33:O34)+O31 -> 109 | P35: =O35/J35 -> 0.50230415 | Q35: =SUM(Q33:Q34)+Q31 -> 212 | R35: =SUM(R33:R34)+R31 -> 212 | S35: =R35/Q35 -> 1 | T35: =SUM(T33:T34)+T31 -> 119 | U35: =T35/Q35 -> 0.56132075 | V35: =SUM(V33:V34)+V31 -> 116 | W35: =V35/Q35 -> 0.54716981
A38: NO | B38: BIDANG | C38: 43374 | J38: 43405 | Q38: 43435
C39: Jml regulasi | D39: Identifikasi | F39: Evaluasi | H39: Implementasi | J39: Jml regulasi | K39: Identifikasi | M39: Evaluasi | O39: Implementasi | Q39: Jml regulasi | R39: Identifikasi | T39: Evaluasi | V39: Implementasi
D40: Jml | E40: % | F40: Jml | G40: % | H40: Jml | I40: % | K40: Jml | L40: % | M40: Jml | N40: % | O40: Jml | P40: % | R40: Jml | S40: % | T40: Jml | U40: % | V40: Jml | W40: %
A41: 1 | B41: CORPORATE MATTERS | C41: 58 | D41: 58 | E41: =D41/C41 -> 1 | F41: 27 | G41: =F41/C41 -> 0.46551724 | H41: 25 | I41: =H41/C41 -> 0.43103448 | J41: 53 | K41: 53 | L41: =K41/J41 -> 1 | M41: 38 | N41: =M41/J41 -> 0.71698113 | O41: 37 | P41: =O41/J41 -> 0.69811321 | Q41: 54 | R41: 54 | S41: =R41/Q41 -> 1 | T41: 54 | U41: =T41/Q41 -> 1 | V41: 53 | W41: =V41/Q41 -> 0.98148148
A42: 2 | B42: LABOR & HUMAN RIGHTS | C42: 39 | D42: 39 | E42: =D42/C42 -> 1 | F42: 22 | G42: =F42/C42 -> 0.56410256 | H42: 22 | I42: =H42/C42 -> 0.56410256 | J42: 42 | K42: 42 | L42: =K42/J42 -> 1 | M42: 22 | N42: =M42/J42 -> 0.52380952 | O42: 22 | P42: =O42/J42 -> 0.52380952 | Q42: 45 | R42: 45 | S42: =R42/Q42 -> 1 | T42: 37 | U42: =T42/Q42 -> 0.82222222 | V42: 35 | W42: =V42/Q42 -> 0.77777778
A43: 3 | B43: INTELLECTUAL PROPERTY | C43: 2 | D43: 2 | E43: =D43/C43 -> 1 | F43: 2 | G43: =F43/C43 -> 1 | H43: 2 | I43: =H43/C43 -> 1 | J43: 2 | K43: 2 | L43: =K43/J43 -> 1 | M43: 2 | N43: =M43/J43 -> 1 | O43: 2 | P43: =O43/J43 -> 1 | Q43: 2 | R43: 2 | S43: =R43/Q43 -> 1 | T43: 2 | U43: =T43/Q43 -> 1 | V43: 2 | W43: =V43/Q43 -> 1
A44: 7 | B44: SAFETY & HEALTH | C44: 27 | D44: 27 | E44: =D44/C44 -> 1 | F44: 27 | G44: =F44/C44 -> 1 | H44: 27 | I44: =H44/C44 -> 1 | J44: 27 | K44: 27 | L44: =K44/J44 -> 1 | M44: 27 | N44: =M44/J44 -> 1 | O44: 27 | P44: =O44/J44 -> 1 | Q44: 25 | R44: 25 | S44: =R44/Q44 -> 1 | T44: 25 | U44: =T44/Q44 -> 1 | V44: 23 | W44: =V44/Q44 -> 0.92
A45: 4 | B45: FAIR TRADING | C45: 2 | D45: 2 | E45: =D45/C45 -> 1 | F45: 2 | G45: =F45/C45 -> 1 | H45: 2 | I45: =H45/C45 -> 1 | J45: 2 | K45: 2 | L45: =K45/J45 -> 1 | M45: 2 | N45: =M45/J45 -> 1 | O45: 2 | P45: =O45/J45 -> 1 | Q45: 2 | R45: 2 | S45: =R45/Q45 -> 1 | T45: 2 | U45: =T45/Q45 -> 1 | V45: 2 | W45: =V45/Q45 -> 1
A46: 6 | B46: ENVIRONMENT | C46: 57 | D46: 57 | E46: =D46/C46 -> 1 | F46: 50 | G46: =F46/C46 -> 0.87719298 | H46: 49 | I46: =H46/C46 -> 0.85964912 | J46: 57 | K46: 57 | L46: =K46/J46 -> 1 | M46: 50 | N46: =M46/J46 -> 0.87719298 | O46: 49 | P46: =O46/J46 -> 0.85964912 | Q46: 57 | R46: 57 | S46: =R46/Q46 -> 1 | T46: 50 | U46: =T46/Q46 -> 0.87719298 | V46: 49 | W46: =V46/Q46 -> 0.85964912
B47: TOTAL | C47: =SUM(C45:C46)+C43 -> 61 | D47: =SUM(D45:D46)+D43 -> 61 | E47: =D47/C47 -> 1 | F47: =SUM(F45:F46)+F43 -> 54 | G47: =F47/C47 -> 0.8852459 | H47: =SUM(H45:H46)+H43 -> 53 | I47: =H47/C47 -> 0.86885246 | J47: =SUM(J45:J46)+J43 -> 61 | K47: =SUM(K45:K46)+K43 -> 61 | L47: =K47/J47 -> 1 | M47: =SUM(M45:M46)+M43 -> 54 | N47: =M47/J47 -> 0.8852459 | O47: =SUM(O45:O46)+O43 -> 53 | P47: =O47/J47 -> 0.86885246 | Q47: =SUM(Q45:Q46)+Q43 -> 61 | R47: =SUM(R45:R46)+R43 -> 61 | S47: =R47/Q47 -> 1 | T47: =SUM(T45:T46)+T43 -> 54 | U47: =T47/Q47 -> 0.8852459 | V47: =SUM(V45:V46)+V43 -> 53 | W47: =V47/Q47 -> 0.86885246
A49: 5 | B49: EXIM MANAGEMENT | C49: 21 | D49: 21 | E49: =D49/C49 -> 1 | F49: 0 | G49: =F49/C49 -> 0 | H49: 0 | I49: =H49/C49 -> 0 | J49: 21 | K49: 21 | L49: =K49/J49 -> 1 | M49: 0 | N49: =M49/J49 -> 0 | O49: 0 | P49: =O49/J49 -> 0 | Q49: 21 | R49: 21 | S49: =R49/Q49 -> 1 | T49: 0 | U49: =T49/Q49 -> 0 | V49: 0 | W49: =V49/Q49 -> 0
A50: 8 | B50: FINANCE ACCOUNTING | C50: 19 | D50: 19 | E50: =D50/C50 -> 1 | F50: 0 | G50: =F50/C50 -> 0 | H50: 0 | I50: =H50/C50 -> 0 | J50: 19 | K50: 19 | L50: =K50/J50 -> 1 | M50: 3 | N50: =M50/J50 -> 0.15789474 | O50: 3 | P50: =O50/J50 -> 0.15789474 | Q50: 19 | R50: 19 | S50: =R50/Q50 -> 1 | T50: 3 | U50: =T50/Q50 -> 0.15789474 | V50: 3 | W50: =V50/Q50 -> 0.15789474
B51: TOTAL | C51: =SUM(C49:C50)+C47 -> 101 | D51: =SUM(D49:D50)+D47 -> 101 | E51: =D51/C51 -> 1 | F51: =SUM(F49:F50)+F47 -> 54 | G51: =F51/C51 -> 0.53465347 | H51: =SUM(H49:H50)+H47 -> 53 | I51: =H51/C51 -> 0.52475248 | J51: =SUM(J49:J50)+J47 -> 101 | K51: =SUM(K49:K50)+K47 -> 101 | L51: =K51/J51 -> 1 | M51: =SUM(M49:M50)+M47 -> 57 | N51: =M51/J51 -> 0.56435644 | O51: =SUM(O49:O50)+O47 -> 56 | P51: =O51/J51 -> 0.55445545 | Q51: =SUM(Q49:Q50)+Q47 -> 101 | R51: =SUM(R49:R50)+R47 -> 101 | S51: =R51/Q51 -> 1 | T51: =SUM(T49:T50)+T47 -> 57 | U51: =T51/Q51 -> 0.56435644 | V51: =SUM(V49:V50)+V47 -> 56 | W51: =V51/Q51 -> 0.55445545
A54: NO | B54: BIDANG | C54: 43466 | J54: 43497 | Q54: 43525
C55: Jml regulasi | D55: Identifikasi | F55: Evaluasi | H55: Implementasi | J55: Jml regulasi | K55: Identifikasi | M55: Evaluasi | O55: Implementasi | Q55: Jml regulasi | R55: Identifikasi | T55: Evaluasi | V55: Implementasi
D56: Jml | E56: % | F56: Jml | G56: % | H56: Jml | I56: % | K56: Jml | L56: % | M56: Jml | N56: % | O56: Jml | P56: % | R56: Jml | S56: % | T56: Jml | U56: % | V56: Jml | W56: %
A57: 1 | B57: COMPLIANCE IN GENERAL (1) | E57: 1 | F57: 0 | G57: 1 | H57: 0 | I57: 1 | J57: 0 | K57: 0 | L57: 1 | M57: 0 | N57: 1 | O57: 0 | P57: 1 | Q57: 0 | R57: 0 | S57: 1 | T57: 0 | U57: 1 | V57: 0 | W57: 1
A58: 2 | B58: LABOR & HUMAN RIGHTS (3) | E58: 1 | F58: 45 | G58: 0.97826087 | H58: 43 | I58: 0.93478261 | J58: 51 | K58: 51 | L58: =K58/J58 -> 1 | M58: 45 | N58: =M58/J58 -> 0.88235294 | O58: 43 | P58: =O58/J58 -> 0.84313725 | Q58: 51 | R58: 51 | S58: =R58/Q58 -> 1 | T58: 45 | U58: =T58/Q58 -> 0.88235294 | V58: 43 | W58: =V58/Q58 -> 0.84313725
A59: 3 | B59: INTELLECTUAL PROPERTY (4) | E59: 1 | F59: 5 | G59: 1 | H59: 5 | I59: 1 | J59: 5 | K59: 5 | L59: =K59/J59 -> 1 | M59: 5 | N59: =M59/J59 -> 1 | O59: 5 | P59: =O59/J59 -> 1 | Q59: 5 | R59: 5 | S59: =R59/Q59 -> 1 | T59: 5 | U59: =T59/Q59 -> 1 | V59: 5 | W59: =V59/Q59 -> 1
A60: 4 | B60: FAIR TRADING (5) | E60: 1 | F60: 2 | G60: 0.66666667 | H60: 2 | I60: 0.66666667 | J60: 3 | K60: 3 | L60: =K60/J60 -> 1 | M60: 2 | N60: =M60/J60 -> 0.66666667 | O60: 2 | P60: =O60/J60 -> 0.66666667 | Q60: 3 | R60: 3 | S60: =R60/Q60 -> 1 | T60: 2 | U60: =T60/Q60 -> 0.66666667 | V60: 2 | W60: =V60/Q60 -> 0.66666667
A61: 7 | B61: ENVIRONMENT, SAFETY & HEALTH (8) | E61: 1 | F61: 80 | G61: 1 | H61: 76 | I61: 0.95 | J61: 82 | K61: 82 | L61: =K61/J61 -> 1 | M61: 80 | N61: =M61/J61 -> 0.97560976 | O61: 76 | P61: =O61/J61 -> 0.92682927 | Q61: 82 | R61: 82 | S61: =R61/Q61 -> 1 | T61: 80 | U61: =T61/Q61 -> 0.97560976 | V61: 76 | W61: =V61/Q61 -> 0.92682927
A62: 6 | B62: COMPANY /BUSINESS OPERATIONS & LICENSE (2) | C62: 54 | D62: 54 | E62: 1 | F62: 54 | G62: 1 | H62: 53 | I62: 0.98148148 | J62: 55 | K62: 55 | L62: =K62/J62 -> 1 | M62: 54 | N62: =M62/J62 -> 0.98181818 | O62: 53 | P62: =O62/J62 -> 0.96363636 | Q62: 55 | R62: 55 | S62: =R62/Q62 -> 1 | T62: 54 | U62: =T62/Q62 -> 0.98181818 | V62: 53 | W62: =V62/Q62 -> 0.96363636
B63: TOTAL | C63: 188 | D63: 188 | E63: 1 | F63: 186 | G63: 0.9893617 | H63: 179 | I63: 0.95212766 | J63: =SUM(J57:J62) -> 196 | K63: =SUM(K57:K62) -> 196 | L63: =K63/J63 -> 1 | M63: =SUM(M57:M62) -> 186 | N63: =M63/J63 -> 0.94897959 | O63: =SUM(O57:O62) -> 179 | P63: =O63/J63 -> 0.91326531 | Q63: =SUM(Q57:Q62) -> 196 | R63: =SUM(R57:R62) -> 196 | S63: =R63/Q63 -> 1 | T63: =SUM(T57:T62) -> 186 | U63: =T63/Q63 -> 0.94897959 | V63: =SUM(V57:V62) -> 179 | W63: =V63/Q63 -> 0.91326531
A65: 5 | B65: EXIM MANAGEMENT (6) | E65: 1 | F65: 0 | G65: 0 | H65: 0 | I65: 0 | J65: 35 | K65: 35 | L65: =K65/J65 -> 1 | M65: 23 | N65: =M65/J65 -> 0.65714286 | O65: 22 | P65: =O65/J65 -> 0.62857143 | Q65: 35 | R65: 35 | S65: =R65/Q65 -> 1 | T65: 23 | U65: =T65/Q65 -> 0.65714286 | V65: 22 | W65: =V65/Q65 -> 0.62857143
A66: 8 | B66: ACCOUNTING /FINANCE (7) | E66: 1 | F66: 3 | G66: 0.15 | H66: 3 | I66: 0.15 | J66: 20 | K66: 20 | L66: =K66/J66 -> 1 | M66: 3 | N66: =M66/J66 -> 0.15 | O66: 3 | P66: =O66/J66 -> 0.15 | Q66: 20 | R66: 20 | S66: =R66/Q66 -> 1 | T66: 3 | U66: =T66/Q66 -> 0.15 | V66: 3 | W66: =V66/Q66 -> 0.15
B67: TOTAL | C67: 228 | D67: 228 | E67: 1 | F67: 189 | G67: 0.82894737 | H67: 182 | I67: 0.79824561 | J67: =SUM(J65:J66)+J63 -> 251 | K67: =SUM(K65:K66)+K63 -> 251 | L67: =K67/J67 -> 1 | M67: =SUM(M65:M66)+M63 -> 212 | N67: =M67/J67 -> 0.84462151 | O67: =SUM(O65:O66)+O63 -> 204 | P67: =O67/J67 -> 0.812749 | Q67: =SUM(Q65:Q66)+Q63 -> 251 | R67: =SUM(R65:R66)+R63 -> 251 | S67: =R67/Q67 -> 1 | T67: =SUM(T65:T66)+T63 -> 212 | U67: =T67/Q67 -> 0.84462151 | V67: =SUM(V65:V66)+V63 -> 204 | W67: =V67/Q67 -> 0.812749
A70: NO | B70: BIDANG | C70: 43556 | J70: 43586 | Q70: 43617
C71: Jml regulasi | D71: Identifikasi | F71: Evaluasi | H71: Implementasi | J71: Jml regulasi | K71: Identifikasi | M71: Evaluasi | O71: Implementasi | Q71: Jml regulasi | R71: Identifikasi | T71: Evaluasi | V71: Implementasi
D72: Jml | E72: % | F72: Jml | G72: % | H72: Jml | I72: % | K72: Jml | L72: % | M72: Jml | N72: % | O72: Jml | P72: % | R72: Jml | S72: % | T72: Jml | U72: % | V72: Jml | W72: %
A73: 1 | B73: COMPLIANCE IN GENERAL (1) | C73: 0 | D73: 0 | E73: 1 | F73: 0 | G73: 1 | H73: 0 | I73: 1 | J73: 0 | K73: 0 | L73: 1 | M73: 0 | N73: 1 | O73: 0 | P73: 1 | Q73: 0 | R73: 0 | S73: 1 | T73: 0 | U73: 1 | V73: 0 | W73: 1
A74: 2 | B74: LABOR & HUMAN RIGHTS (3) | C74: 51 | D74: 51 | E74: =D74/C74 -> 1 | F74: 45 | G74: =F74/C74 -> 0.88235294 | H74: 43 | I74: =H74/C74 -> 0.84313725 | J74: 52 | K74: 52 | L74: =K74/J74 -> 1 | M74: 45 | N74: =M74/J74 -> 0.86538462 | O74: 43 | P74: =O74/J74 -> 0.82692308 | Q74: 52 | R74: 52 | S74: =R74/Q74 -> 1 | T74: 45 | U74: =T74/Q74 -> 0.86538462 | V74: 45 | W74: =V74/Q74 -> 0.86538462
A75: 3 | B75: INTELLECTUAL PROPERTY (4) | C75: 5 | D75: 5 | E75: =D75/C75 -> 1 | F75: 5 | G75: =F75/C75 -> 1 | H75: 5 | I75: =H75/C75 -> 1 | J75: 5 | K75: 5 | L75: =K75/J75 -> 1 | M75: 5 | N75: =M75/J75 -> 1 | O75: 5 | P75: =O75/J75 -> 1 | Q75: 5 | R75: 5 | S75: =R75/Q75 -> 1 | T75: 5 | U75: =T75/Q75 -> 1 | V75: 5 | W75: =V75/Q75 -> 1
A76: 4 | B76: FAIR TRADING (5) | C76: 3 | D76: 3 | E76: =D76/C76 -> 1 | F76: 2 | G76: =F76/C76 -> 0.66666667 | H76: 2 | I76: =H76/C76 -> 0.66666667 | J76: 3 | K76: 3 | L76: =K76/J76 -> 1 | M76: 2 | N76: =M76/J76 -> 0.66666667 | O76: 2 | P76: =O76/J76 -> 0.66666667 | Q76: 3 | R76: 3 | S76: =R76/Q76 -> 1 | T76: 2 | U76: =T76/Q76 -> 0.66666667 | V76: 2 | W76: =V76/Q76 -> 0.66666667
A77: 7 | B77: ENVIRONMENT, SAFETY & HEALTH (8) | C77: 82 | D77: 82 | E77: =D77/C77 -> 1 | F77: 80 | G77: =F77/C77 -> 0.97560976 | H77: 76 | I77: =H77/C77 -> 0.92682927 | J77: 82 | K77: 82 | L77: =K77/J77 -> 1 | M77: 80 | N77: =M77/J77 -> 0.97560976 | O77: 76 | P77: =O77/J77 -> 0.92682927 | Q77: 82 | R77: 82 | S77: =R77/Q77 -> 1 | T77: 80 | U77: =T77/Q77 -> 0.97560976 | V77: 77 | W77: =V77/Q77 -> 0.93902439
A78: 6 | B78: COMPANY /BUSINESS OPERATIONS & LICENSE (2) | C78: 55 | D78: 55 | E78: =D78/C78 -> 1 | F78: 54 | G78: =F78/C78 -> 0.98181818 | H78: 53 | I78: =H78/C78 -> 0.96363636 | J78: 55 | K78: 55 | L78: =K78/J78 -> 1 | M78: 54 | N78: =M78/J78 -> 0.98181818 | O78: 53 | P78: =O78/J78 -> 0.96363636 | Q78: 57 | R78: 57 | S78: =R78/Q78 -> 1 | T78: 56 | U78: =T78/Q78 -> 0.98245614 | V78: 55 | W78: =V78/Q78 -> 0.96491228
B79: TOTAL | C79: =SUM(C73:C78) -> 196 | D79: =SUM(D73:D78) -> 196 | E79: =D79/C79 -> 1 | F79: =SUM(F73:F78) -> 186 | G79: =F79/C79 -> 0.94897959 | H79: =SUM(H73:H78) -> 179 | I79: =H79/C79 -> 0.91326531 | J79: =SUM(J73:J78) -> 197 | K79: =SUM(K73:K78) -> 197 | L79: =K79/J79 -> 1 | M79: =SUM(M73:M78) -> 186 | N79: =M79/J79 -> 0.94416244 | O79: =SUM(O73:O78) -> 179 | P79: =O79/J79 -> 0.90862944 | Q79: =SUM(Q73:Q78) -> 199 | R79: =SUM(R73:R78) -> 199 | S79: =R79/Q79 -> 1 | T79: =SUM(T73:T78) -> 188 | U79: =T79/Q79 -> 0.94472362 | V79: =SUM(V73:V78) -> 184 | W79: =V79/Q79 -> 0.92462312
A81: 5 | B81: EXIM MANAGEMENT (6) | C81: 35 | D81: 35 | E81: =D81/C81 -> 1 | F81: 23 | G81: =F81/C81 -> 0.65714286 | H81: 22 | I81: =H81/C81 -> 0.62857143 | J81: 35 | K81: 35 | L81: =K81/J81 -> 1 | M81: 23 | N81: =M81/J81 -> 0.65714286 | O81: 22 | P81: =O81/J81 -> 0.62857143 | Q81: 35 | R81: 35 | S81: =R81/Q81 -> 1 | T81: 23 | U81: =T81/Q81 -> 0.65714286 | V81: 22 | W81: =V81/Q81 -> 0.62857143
A82: 8 | B82: ACCOUNTING /FINANCE (7) | C82: 20 | D82: 20 | E82: =D82/C82 -> 1 | F82: 3 | G82: =F82/C82 -> 0.15 | H82: 3 | I82: =H82/C82 -> 0.15 | J82: 20 | K82: 20 | L82: =K82/J82 -> 1 | M82: 3 | N82: =M82/J82 -> 0.15 | O82: 3 | P82: =O82/J82 -> 0.15 | Q82: 20 | R82: 20 | S82: =R82/Q82 -> 1 | T82: 3 | U82: =T82/Q82 -> 0.15 | V82: 3 | W82: =V82/Q82 -> 0.15
B83: TOTAL | C83: =SUM(C81:C82)+C79 -> 251 | D83: =SUM(D81:D82)+D79 -> 251 | E83: =D83/C83 -> 1 | F83: =SUM(F81:F82)+F79 -> 212 | G83: =F83/C83 -> 0.84462151 | H83: =SUM(H81:H82)+H79 -> 204 | I83: =H83/C83 -> 0.812749 | J83: =SUM(J81:J82)+J79 -> 252 | K83: =SUM(K81:K82)+K79 -> 252 | L83: =K83/J83 -> 1 | M83: =SUM(M81:M82)+M79 -> 212 | N83: =M83/J83 -> 0.84126984 | O83: =SUM(O81:O82)+O79 -> 204 | P83: =O83/J83 -> 0.80952381 | Q83: =SUM(Q81:Q82)+Q79 -> 254 | R83: =SUM(R81:R82)+R79 -> 254 | S83: =R83/Q83 -> 1 | T83: =SUM(T81:T82)+T79 -> 214 | U83: =T83/Q83 -> 0.84251969 | V83: =SUM(V81:V82)+V79 -> 209 | W83: =V83/Q83 -> 0.82283465

Sheet 79
A2: Now day
A4: NO | B4: BIDANG | C4: NOW DAY
C5: Jml regulasi | D5: Identifikasi | F5: Evaluasi | H5: Implementasi
D6: Jml | E6: % | F6: Jml | G6: % | H6: Jml | I6: %
A7: 1 | B7: COMPLIANCE IN GENERAL (1) | C7: ='Detail COMPLIANCE FIELD'!G15 -> 0 | D7: =C7 -> 0 | E7: 1 | F7: ='Detail COMPLIANCE FIELD'!I15 -> 0 | G7: 1 | H7: ='Detail COMPLIANCE FIELD'!K15 -> 0 | I7: 1
A8: 2 | B8: LABOR & HUMAN RIGHTS (3) | C8: ='Detail COMPLIANCE FIELD'!G16 -> 99 | D8: =C8 -> 99 | E8: =D8/C8 -> 1 | F8: ='Detail COMPLIANCE FIELD'!I16 -> 99 | G8: =F8/C8 -> 1 | H8: ='Detail COMPLIANCE FIELD'!K16 -> 98 | I8: =H8/C8 -> 0.98989899
A9: 3 | B9: INTELLECTUAL PROPERTY (4) | C9: ='Detail COMPLIANCE FIELD'!G17 -> 126 | D9: =C9 -> 126 | E9: =D9/C9 -> 1 | F9: ='Detail COMPLIANCE FIELD'!I17 -> 126 | G9: =F9/C9 -> 1 | H9: ='Detail COMPLIANCE FIELD'!K17 -> 122 | I9: =H9/C9 -> 0.96825397
A10: 4 | B10: FAIR TRADING (5) | C10: ='Detail COMPLIANCE FIELD'!G18 -> 7 | D10: =C10 -> 7 | E10: =D10/C10 -> 1 | F10: ='Detail COMPLIANCE FIELD'!I18 -> 7 | G10: =F10/C10 -> 1 | H10: ='Detail COMPLIANCE FIELD'!K18 -> 7 | I10: =H10/C10 -> 1
A11: 5 | B11: ENVIRONMENT, SAFETY & HEALTH (8) | C11: ='Detail COMPLIANCE FIELD'!G19 -> 6 | D11: =C11 -> 6 | E11: =D11/C11 -> 1 | F11: ='Detail COMPLIANCE FIELD'!I19 -> 6 | G11: =F11/C11 -> 1 | H11: ='Detail COMPLIANCE FIELD'!K19 -> 6 | I11: =H11/C11 -> 1
A12: 6 | B12: COMPANY /BUSINESS OPERATIONS & LICENSE (2) | C12: ='Detail COMPLIANCE FIELD'!G20 -> 37 | D12: =C12 -> 37 | E12: =D12/C12 -> 1 | F12: ='Detail COMPLIANCE FIELD'!I20 -> 37 | G12: =F12/C12 -> 1 | H12: ='Detail COMPLIANCE FIELD'!K20 -> 37 | I12: =H12/C12 -> 1
B13: TOTAL | C13: =SUM(C7:C12) -> 275 | D13: =SUM(D7:D12) -> 275 | E13: =D13/C13 -> 1 | F13: =SUM(F7:F12) -> 275 | G13: =F13/C13 -> 1 | H13: =SUM(H7:H12) -> 270 | I13: =H13/C13 -> 0.98181818
A15: 7 | B15: EXIM MANAGEMENT (6) | C15: ='Detail COMPLIANCE FIELD'!G21 -> 56 | D15: =C15 -> 56 | E15: =D15/C15 -> 1 | F15: ='Detail COMPLIANCE FIELD'!I21 -> 56 | G15: =F15/C15 -> 1 | H15: ='Detail COMPLIANCE FIELD'!K21 -> 56 | I15: =H15/C15 -> 1
A16: 8 | B16: ACCOUNTING /FINANCE (7) | C16: ='Detail COMPLIANCE FIELD'!G22 -> 123 | D16: =C16 -> 123 | E16: =D16/C16 -> 1 | F16: ='Detail COMPLIANCE FIELD'!I22 -> 123 | G16: =F16/C16 -> 1 | H16: ='Detail COMPLIANCE FIELD'!K22 -> 116 | I16: =H16/C16 -> 0.94308943
B17: TOTAL | C17: =SUM(C15:C16)+C13 -> 454 | D17: =SUM(D15:D16)+D13 -> 454 | E17: =D17/C17 -> 1 | F17: =SUM(F15:F16)+F13 -> 454 | G17: =F17/C17 -> 1 | H17: =SUM(H15:H16)+H13 -> 442 | I17: =H17/C17 -> 0.97356828
A18: PT. SEMARANG AUTOCOMP MANUFACTURING INDONESIA
A19: KEPATUHAN TERHADAP PERATURAN PERUNDANGAN
A21: NO | B21: BIDANG | C21: 43647 | J21: 43678 | Q21: 43709
C22: Jml regulasi | D22: Identifikasi | F22: Evaluasi | H22: Implementasi | J22: Jml regulasi | K22: Identifikasi | M22: Evaluasi | O22: Implementasi | Q22: Jml regulasi | R22: Identifikasi | T22: Evaluasi | V22: Implementasi
D23: Jml | E23: % | F23: Jml | G23: % | H23: Jml | I23: % | K23: Jml | L23: % | M23: Jml | N23: % | O23: Jml | P23: % | R23: Jml | S23: % | T23: Jml | U23: % | V23: Jml | W23: %
A24: 1 | B24: COMPLIANCE IN GENERAL (1) | C24: 0 | D24: 0 | E24: =D24/C24 -> #DIV/0! | F24: 0 | G24: =F24/C24 -> #DIV/0! | H24: 0 | I24: =H24/C24 -> #DIV/0! | J24: 0 | K24: 0 | L24: =K24/J24 -> #DIV/0! | M24: 0 | N24: =M24/J24 -> #DIV/0! | O24: 0 | P24: =O24/J24 -> #DIV/0! | Q24: 0 | R24: 0 | S24: =R24/Q24 -> #DIV/0! | T24: 0 | U24: =T24/Q24 -> #DIV/0! | V24: 0 | W24: =V24/Q24 -> #DIV/0!
A25: 2 | B25: LABOR & HUMAN RIGHTS (3) | C25: 50 | D25: 50 | E25: =D25/C25 -> 1 | F25: 47 | G25: =F25/C25 -> 0.94 | H25: 47 | I25: =H25/C25 -> 0.94 | J25: 51 | K25: 51 | L25: =K25/J25 -> 1 | M25: 47 | N25: =M25/J25 -> 0.92156863 | O25: 47 | P25: =O25/J25 -> 0.92156863 | Q25: 52 | R25: 52 | S25: =R25/Q25 -> 1 | T25: 52 | U25: =T25/Q25 -> 1 | V25: 51 | W25: =V25/Q25 -> 0.98076923
B26: a. HR | Q26: 31 | R26: 31 | S26: =R26/Q26 -> 1 | T26: 31 | U26: =T26/Q26 -> 1 | V26: 31 | W26: =V26/Q26 -> 1
B27: b. Expat | Q27: 20 | R27: 20 | S27: =R27/Q27 -> 1 | T27: 20 | U27: =T27/Q27 -> 1 | V27: 19 | W27: =V27/Q27 -> 0.95
B28: c. TRN | Q28: 1 | R28: 1 | S28: =R28/Q28 -> 1 | T28: 1 | U28: =T28/Q28 -> 1 | V28: 1 | W28: =V28/Q28 -> 1
A29: 3 | B29: INTELLECTUAL PROPERTY (4) | C29: 5 | D29: 5 | E29: =D29/C29 -> 1 | F29: 5 | G29: =F29/C29 -> 1 | H29: 5 | I29: =H29/C29 -> 1 | J29: 5 | K29: 5 | L29: =K29/J29 -> 1 | M29: 5 | N29: =M29/J29 -> 1 | O29: 5 | P29: =O29/J29 -> 1 | Q29: 6 | R29: 6 | S29: =R29/Q29 -> 1 | T29: 6 | U29: =T29/Q29 -> 1 | V29: 6 | W29: =V29/Q29 -> 1
A30: 4 | B30: FAIR TRADING (5) | C30: 3 | D30: 3 | E30: =D30/C30 -> 1 | F30: 2 | G30: =F30/C30 -> 0.66666667 | H30: 2 | I30: =H30/C30 -> 0.66666667 | J30: 3 | K30: 3 | L30: =K30/J30 -> 1 | M30: 2 | N30: =M30/J30 -> 0.66666667 | O30: 2 | P30: =O30/J30 -> 0.66666667 | Q30: 3 | R30: 3 | S30: =R30/Q30 -> 1 | T30: 3 | U30: =T30/Q30 -> 1 | V30: 3 | W30: =V30/Q30 -> 1
A31: 6 | B31: ENVIRONMENT, SAFETY & HEALTH (8) | C31: 76 | D31: 76 | E31: =D31/C31 -> 1 | F31: 73 | G31: =F31/C31 -> 0.96052632 | H31: 70 | I31: =H31/C31 -> 0.92105263 | J31: 109 | K31: 109 | L31: =K31/J31 -> 1 | M31: 75 | N31: =M31/J31 -> 0.68807339 | O31: 70 | P31: =O31/J31 -> 0.64220183 | Q31: 109 | R31: 109 | S31: =R31/Q31 -> 1 | T31: 79 | U31: =T31/Q31 -> 0.72477064 | V31: 75 | W31: =V31/Q31 -> 0.68807339
B32: a. Safety & Health | Q32: 24 | R32: 24 | S32: =R32/Q32 -> 1 | T32: 24 | U32: =T32/Q32 -> 1 | V32: 23 | W32: =V32/Q32 -> 0.95833333
B33: b. Environment | Q33: 77 | R33: 77 | S33: =R33/Q33 -> 1 | T33: 53 | U33: =T33/Q33 -> 0.68831169 | V33: 52 | W33: =V33/Q33 -> 0.67532468
B34: c. SoC | Q34: 8 | R34: 8 | S34: =R34/Q34 -> 1 | T34: 2 | U34: =T34/Q34 -> 0.25 | V34: 0 | W34: =V34/Q34 -> 0
A35: 7 | B35: COMPANY /BUSINESS OPERATIONS & LICENSE (2) | C35: 46 | D35: 46 | E35: =D35/C35 -> 1 | F35: 45 | G35: =F35/C35 -> 0.97826087 | H35: 44 | I35: =H35/C35 -> 0.95652174 | J35: 52 | K35: 52 | L35: =K35/J35 -> 1 | M35: 46 | N35: =M35/J35 -> 0.88461538 | O35: 44 | P35: =O35/J35 -> 0.84615385 | Q35: 51 | R35: 51 | S35: =R35/Q35 -> 1 | T35: 51 | U35: =T35/Q35 -> 1 | V35: 46 | W35: =V35/Q35 -> 0.90196078
B36: TOTAL | C36: =SUM(C24:C35) -> 180 | D36: =SUM(D24:D35) -> 180 | E36: =D36/C36 -> 1 | F36: =SUM(F24:F35) -> 172 | G36: =F36/C36 -> 0.95555556 | H36: =SUM(H24:H35) -> 168 | I36: =H36/C36 -> 0.93333333 | J36: =SUM(J24:J35) -> 220 | K36: =SUM(K24:K35) -> 220 | L36: =K36/J36 -> 1 | M36: =SUM(M24:M35) -> 175 | N36: =M36/J36 -> 0.79545455 | O36: =SUM(O24:O35) -> 168 | P36: =O36/J36 -> 0.76363636 | Q36: =Q24+Q25+Q29+Q30+Q31+Q35 -> 221 | R36: =R24+R25+R29+R30+R31+R35 -> 221 | S36: =R36/Q36 -> 1 | T36: =T24+T25+T29+T30+T31+T35 -> 191 | U36: =T36/Q36 -> 0.86425339 | V36: =V24+V25+V29+V30+V31+V35 -> 181 | W36: =V36/Q36 -> 0.81900452
A38: 5 | B38: EXIM MANAGEMENT (6) | C38: 25 | D38: 25 | E38: =D38/C38 -> 1 | F38: 23 | G38: =F38/C38 -> 0.92 | H38: 23 | I38: =H38/C38 -> 0.92 | J38: 65 | K38: 65 | L38: =K38/J38 -> 1 | M38: 23 | N38: =M38/J38 -> 0.35384615 | O38: 23 | P38: =O38/J38 -> 0.35384615 | Q38: 65 | R38: 65 | S38: =R38/Q38 -> 1 | T38: 23 | U38: =T38/Q38 -> 0.35384615 | V38: 23 | W38: =V38/Q38 -> 0.35384615
A39: 8 | B39: ACCOUNTING /FINANCE (7) | C39: 20 | D39: 20 | E39: =D39/C39 -> 1 | F39: 3 | G39: =F39/C39 -> 0.15 | H39: 3 | I39: =H39/C39 -> 0.15 | J39: 33 | K39: 33 | L39: =K39/J39 -> 1 | M39: 18 | N39: =M39/J39 -> 0.54545455 | O39: 17 | P39: =O39/J39 -> 0.51515152 | Q39: 33 | R39: 33 | S39: =R39/Q39 -> 1 | T39: 18 | U39: =T39/Q39 -> 0.54545455 | V39: 17 | W39: =V39/Q39 -> 0.51515152
B40: TOTAL | C40: =SUM(C38:C39)+C36 -> 225 | D40: =SUM(D38:D39)+D36 -> 225 | E40: =D40/C40 -> 1 | F40: =SUM(F38:F39)+F36 -> 198 | G40: =F40/C40 -> 0.88 | H40: =SUM(H38:H39)+H36 -> 194 | I40: =H40/C40 -> 0.86222222 | J40: =SUM(J38:J39)+J36 -> 318 | K40: =SUM(K38:K39)+K36 -> 318 | L40: =K40/J40 -> 1 | M40: =SUM(M38:M39)+M36 -> 216 | N40: =M40/J40 -> 0.67924528 | O40: =SUM(O38:O39)+O36 -> 208 | P40: =O40/J40 -> 0.65408805 | Q40: =SUM(Q38:Q39)+Q36 -> 319 | R40: =SUM(R38:R39)+R36 -> 319 | S40: =R40/Q40 -> 1 | T40: =SUM(T38:T39)+T36 -> 232 | U40: =T40/Q40 -> 0.72727273 | V40: =SUM(V38:V39)+V36 -> 221 | W40: =V40/Q40 -> 0.69278997
A43: NO | B43: BIDANG | C43: 43739 | J43: 43770 | Q43: 43800
C44: Jml regulasi | D44: Identifikasi | F44: Evaluasi | H44: Implementasi | J44: Jml regulasi | K44: Identifikasi | M44: Evaluasi | O44: Implementasi | Q44: Jml regulasi | R44: Identifikasi | T44: Evaluasi | V44: Implementasi
D45: Jml | E45: % | F45: Jml | G45: % | H45: Jml | I45: % | K45: Jml | L45: % | M45: Jml | N45: % | O45: Jml | P45: % | R45: Jml | S45: % | T45: Jml | U45: % | V45: Jml | W45: %
A46: 1 | B46: COMPLIANCE IN GENERAL (1) | C46: 0 | D46: 0 | E46: =D46/C46 -> #DIV/0! | F46: 0 | G46: =F46/C46 -> #DIV/0! | H46: 0 | I46: =H46/C46 -> #DIV/0! | J46: 0 | K46: 0 | L46: =K46/J46 -> #DIV/0! | M46: 0 | N46: =M46/J46 -> #DIV/0! | O46: 0 | P46: =O46/J46 -> #DIV/0! | Q46: 0 | R46: 0 | S46: =R46/Q46 -> #DIV/0! | T46: 0 | U46: =T46/Q46 -> #DIV/0! | V46: 0 | W46: =V46/Q46 -> #DIV/0!
A47: 2 | B47: LABOR & HUMAN RIGHTS (3) | C47: 53 | D47: 53 | E47: =D47/C47 -> 1 | F47: 53 | G47: =F47/C47 -> 1 | H47: 53 | I47: =H47/C47 -> 1 | J47: 55 | K47: 55 | L47: =K47/J47 -> 1 | M47: 55 | N47: =M47/J47 -> 1 | O47: 55 | P47: =O47/J47 -> 1 | Q47: 58 | R47: 58 | S47: =R47/Q47 -> 1 | T47: 55 | U47: =T47/Q47 -> 0.94827586 | V47: 55 | W47: =V47/Q47 -> 0.94827586
B48: a. HR | C48: 32 | D48: 32 | E48: =D48/C48 -> 1 | F48: 32 | G48: =F48/C48 -> 1 | H48: 32 | I48: =H48/C48 -> 1 | J48: 34 | K48: 34 | L48: =K48/J48 -> 1 | M48: 34 | N48: =M48/J48 -> 1 | O48: 34 | P48: =O48/J48 -> 1 | Q48: 35 | R48: 35 | S48: =R48/Q48 -> 1 | T48: 34 | U48: =T48/Q48 -> 0.97142857 | V48: 34 | W48: =V48/Q48 -> 0.97142857
B49: b. Expat | C49: 20 | D49: 20 | E49: =D49/C49 -> 1 | F49: 20 | G49: =F49/C49 -> 1 | H49: 20 | I49: =H49/C49 -> 1 | J49: 20 | K49: 20 | L49: =K49/J49 -> 1 | M49: 20 | N49: =M49/J49 -> 1 | O49: 20 | P49: =O49/J49 -> 1 | Q49: 22 | R49: 22 | S49: =R49/Q49 -> 1 | T49: 20 | U49: =T49/Q49 -> 0.90909091 | V49: 20 | W49: =V49/Q49 -> 0.90909091
B50: c. TRN | C50: 1 | D50: 1 | E50: =D50/C50 -> 1 | F50: 1 | G50: =F50/C50 -> 1 | H50: 1 | I50: =H50/C50 -> 1 | J50: 1 | K50: 1 | L50: =K50/J50 -> 1 | M50: 1 | N50: =M50/J50 -> 1 | O50: 1 | P50: =O50/J50 -> 1 | Q50: 1 | R50: 1 | S50: =R50/Q50 -> 1 | T50: 1 | U50: =T50/Q50 -> 1 | V50: 1 | W50: =V50/Q50 -> 1
A51: 3 | B51: INTELLECTUAL PROPERTY (4) | C51: 6 | D51: 6 | E51: =D51/C51 -> 1 | F51: 6 | G51: =F51/C51 -> 1 | H51: 6 | I51: =H51/C51 -> 1 | J51: 6 | K51: 6 | L51: =K51/J51 -> 1 | M51: 6 | N51: =M51/J51 -> 1 | O51: 6 | P51: =O51/J51 -> 1 | Q51: 6 | R51: 6 | S51: =R51/Q51 -> 1 | T51: 6 | U51: =T51/Q51 -> 1 | V51: 6 | W51: =V51/Q51 -> 1
A52: 7 | B52: FAIR TRADING (5) | C52: 3 | D52: 3 | E52: =D52/C52 -> 1 | F52: 3 | G52: =F52/C52 -> 1 | H52: 3 | I52: =H52/C52 -> 1 | J52: 3 | K52: 3 | L52: =K52/J52 -> 1 | M52: 3 | N52: =M52/J52 -> 1 | O52: 3 | P52: =O52/J52 -> 1 | Q52: 3 | R52: 3 | S52: =R52/Q52 -> 1 | T52: 3 | U52: =T52/Q52 -> 1 | V52: 3 | W52: =V52/Q52 -> 1
A53: 4 | B53: ENVIRONMENT, SAFETY & HEALTH (8) | C53: 102 | D53: 102 | E53: =D53/C53 -> 1 | F53: 94 | G53: =F53/C53 -> 0.92156863 | H53: 86 | I53: =H53/C53 -> 0.84313725 | J53: 102 | K53: 102 | L53: =K53/J53 -> 1 | M53: 94 | N53: =M53/J53 -> 0.92156863 | O53: 86 | P53: =O53/J53 -> 0.84313725 | Q53: 102 | R53: 102 | S53: =R53/Q53 -> 1 | T53: 94 | U53: =T53/Q53 -> 0.92156863 | V53: 86 | W53: =V53/Q53 -> 0.84313725
B54: a. Safety & Health | C54: 31 | D54: 31 | E54: =D54/C54 -> 1 | F54: 31 | G54: =F54/C54 -> 1 | H54: 27 | I54: =H54/C54 -> 0.87096774 | J54: 31 | K54: 31 | L54: =K54/J54 -> 1 | M54: 31 | N54: =M54/J54 -> 1 | O54: 27 | P54: =O54/J54 -> 0.87096774 | Q54: 31 | R54: 31 | S54: =R54/Q54 -> 1 | T54: 31 | U54: =T54/Q54 -> 1 | V54: 27 | W54: =V54/Q54 -> 0.87096774
B55: b. Environment | C55: 63 | D55: 63 | E55: =D55/C55 -> 1 | F55: 61 | G55: =F55/C55 -> 0.96825397 | H55: 59 | I55: =H55/C55 -> 0.93650794 | J55: 63 | K55: 63 | L55: =K55/J55 -> 1 | M55: 61 | N55: =M55/J55 -> 0.96825397 | O55: 59 | P55: =O55/J55 -> 0.93650794 | Q55: 63 | R55: 63 | S55: =R55/Q55 -> 1 | T55: 61 | U55: =T55/Q55 -> 0.96825397 | V55: 59 | W55: =V55/Q55 -> 0.93650794
B56: c. SoC | C56: 8 | D56: 8 | E56: =D56/C56 -> 1 | F56: 2 | G56: =F56/C56 -> 0.25 | H56: 0 | I56: =H56/C56 -> 0 | J56: 8 | K56: 8 | L56: =K56/J56 -> 1 | M56: 2 | N56: =M56/J56 -> 0.25 | O56: 0 | P56: =O56/J56 -> 0 | Q56: 8 | R56: 8 | S56: =R56/Q56 -> 1 | T56: 2 | U56: =T56/Q56 -> 0.25 | V56: 0 | W56: =V56/Q56 -> 0
A57: 6 | B57: COMPANY /BUSINESS OPERATIONS & LICENSE (2) | C57: 53 | D57: 53 | E57: =D57/C57 -> 1 | F57: 53 | G57: =F57/C57 -> 1 | H57: 50 | I57: =H57/C57 -> 0.94339623 | J57: 54 | K57: 54 | L57: =K57/J57 -> 1 | M57: 54 | N57: =M57/J57 -> 1 | O57: 52 | P57: =O57/J57 -> 0.96296296 | Q57: 54 | R57: 54 | S57: =R57/Q57 -> 1 | T57: 54 | U57: =T57/Q57 -> 1 | V57: 54 | W57: =V57/Q57 -> 1
B58: TOTAL | C58: =C46+C47+C51+C52+C53+C57 -> 217 | D58: =D46+D47+D51+D52+D53+D57 -> 217 | E58: =D58/C58 -> 1 | F58: =F46+F47+F51+F52+F53+F57 -> 209 | G58: =F58/C58 -> 0.96313364 | H58: =H46+H47+H51+H52+H53+H57 -> 198 | I58: =H58/C58 -> 0.9124424 | J58: =J46+J47+J51+J52+J53+J57 -> 220 | K58: =K46+K47+K51+K52+K53+K57 -> 220 | L58: =K58/J58 -> 1 | M58: =M46+M47+M51+M52+M53+M57 -> 212 | N58: =M58/J58 -> 0.96363636 | O58: =O46+O47+O51+O52+O53+O57 -> 202 | P58: =O58/J58 -> 0.91818182 | Q58: =Q46+Q47+Q51+Q52+Q53+Q57 -> 223 | R58: =R46+R47+R51+R52+R53+R57 -> 223 | S58: =R58/Q58 -> 1 | T58: =T46+T47+T51+T52+T53+T57 -> 212 | U58: =T58/Q58 -> 0.95067265 | V58: =V46+V47+V51+V52+V53+V57 -> 204 | W58: =V58/Q58 -> 0.91479821
A60: 5 | B60: EXIM MANAGEMENT (6) | C60: 39 | D60: 39 | E60: =D60/C60 -> 1 | F60: 39 | G60: =F60/C60 -> 1 | H60: 39 | I60: =H60/C60 -> 1 | J60: 39 | K60: 39 | L60: =K60/J60 -> 1 | M60: 39 | N60: =M60/J60 -> 1 | O60: 39 | P60: =O60/J60 -> 1 | Q60: 39 | R60: 39 | S60: =R60/Q60 -> 1 | T60: 39 | U60: =T60/Q60 -> 1 | V60: 39 | W60: =V60/Q60 -> 1
A61: 8 | B61: ACCOUNTING /FINANCE (7) | C61: 24 | D61: 24 | E61: =D61/C61 -> 1 | F61: 18 | G61: =F61/C61 -> 0.75 | H61: 17 | I61: =H61/C61 -> 0.70833333 | J61: 24 | K61: 24 | L61: =K61/J61 -> 1 | M61: 18 | N61: =M61/J61 -> 0.75 | O61: 17 | P61: =O61/J61 -> 0.70833333 | Q61: 24 | R61: 24 | S61: =R61/Q61 -> 1 | T61: 18 | U61: =T61/Q61 -> 0.75 | V61: 17 | W61: =V61/Q61 -> 0.70833333
B62: TOTAL | C62: =SUM(C60:C61)+C58 -> 280 | D62: =SUM(D60:D61)+D58 -> 280 | E62: =D62/C62 -> 1 | F62: =SUM(F60:F61)+F58 -> 266 | G62: =F62/C62 -> 0.95 | H62: =SUM(H60:H61)+H58 -> 254 | I62: =H62/C62 -> 0.90714286 | J62: =SUM(J60:J61)+J58 -> 283 | K62: =SUM(K60:K61)+K58 -> 283 | L62: =K62/J62 -> 1 | M62: =SUM(M60:M61)+M58 -> 269 | N62: =M62/J62 -> 0.95053004 | O62: =SUM(O60:O61)+O58 -> 258 | P62: =O62/J62 -> 0.91166078 | Q62: =SUM(Q60:Q61)+Q58 -> 286 | R62: =SUM(R60:R61)+R58 -> 286 | S62: =R62/Q62 -> 1 | T62: =SUM(T60:T61)+T58 -> 269 | U62: =T62/Q62 -> 0.94055944 | V62: =SUM(V60:V61)+V58 -> 260 | W62: =V62/Q62 -> 0.90909091
A65: NO | B65: BIDANG | C65: 43831 | J65: 43862 | Q65: 43891
C66: Jml regulasi | D66: Identifikasi | F66: Evaluasi | H66: Implementasi | J66: Jml regulasi | K66: Identifikasi | M66: Evaluasi | O66: Implementasi | Q66: Jml regulasi | R66: Identifikasi | T66: Evaluasi | V66: Implementasi
D67: Jml | E67: % | F67: Jml | G67: % | H67: Jml | I67: % | K67: Jml | L67: % | M67: Jml | N67: % | O67: Jml | P67: % | R67: Jml | S67: % | T67: Jml | U67: % | V67: Jml | W67: %
A68: 1 | B68: COMPLIANCE IN GENERAL (1) | C68: 0 | D68: 0 | E68: =D68/C68 -> #DIV/0! | F68: 0 | G68: =F68/C68 -> #DIV/0! | H68: 0 | I68: =H68/C68 -> #DIV/0! | J68: 0 | K68: 0 | L68: =K68/J68 -> #DIV/0! | M68: 0 | N68: =M68/J68 -> #DIV/0! | O68: 0 | P68: =O68/J68 -> #DIV/0! | Q68: 0 | R68: 0 | S68: =R68/Q68 -> #DIV/0! | T68: 0 | U68: =T68/Q68 -> #DIV/0! | V68: 0 | W68: =V68/Q68 -> #DIV/0!
A69: 2 | B69: LABOR & HUMAN RIGHTS (3) | C69: 58 | D69: 58 | E69: =D69/C69 -> 1 | F69: 55 | G69: =F69/C69 -> 0.94827586 | H69: 55 | I69: =H69/C69 -> 0.94827586 | J69: 58 | K69: 58 | L69: =K69/J69 -> 1 | M69: 56 | N69: =M69/J69 -> 0.96551724 | O69: 56 | P69: =O69/J69 -> 0.96551724 | Q69: 59 | R69: 59 | S69: =R69/Q69 -> 1 | T69: 57 | U69: =T69/Q69 -> 0.96610169 | V69: 57 | W69: =V69/Q69 -> 0.96610169
B70: a. HR | C70: 35 | D70: 35 | E70: =D70/C70 -> 1 | F70: 34 | G70: =F70/C70 -> 0.97142857 | H70: 34 | I70: =H70/C70 -> 0.97142857 | J70: 35 | K70: 35 | L70: =K70/J70 -> 1 | M70: 35 | N70: =M70/J70 -> 1 | O70: 35 | P70: =O70/J70 -> 1 | Q70: 35 | R70: 35 | S70: =R70/Q70 -> 1 | T70: 35 | U70: =T70/Q70 -> 1 | V70: 35 | W70: =V70/Q70 -> 1
B71: b. Expat | C71: 22 | D71: 22 | E71: =D71/C71 -> 1 | F71: 20 | G71: =F71/C71 -> 0.90909091 | H71: 20 | I71: =H71/C71 -> 0.90909091 | J71: 22 | K71: 22 | L71: =K71/J71 -> 1 | M71: 20 | N71: =M71/J71 -> 0.90909091 | O71: 20 | P71: =O71/J71 -> 0.90909091 | Q71: 23 | R71: 23 | S71: =R71/Q71 -> 1 | T71: 21 | U71: =T71/Q71 -> 0.91304348 | V71: 21 | W71: =V71/Q71 -> 0.91304348
B72: c. TRN | C72: 1 | D72: 1 | E72: =D72/C72 -> 1 | F72: 1 | G72: =F72/C72 -> 1 | H72: 1 | I72: =H72/C72 -> 1 | J72: 1 | K72: 1 | L72: =K72/J72 -> 1 | M72: 1 | N72: =M72/J72 -> 1 | O72: 1 | P72: =O72/J72 -> 1 | Q72: 1 | R72: 1 | S72: =R72/Q72 -> 1 | T72: 1 | U72: =T72/Q72 -> 1 | V72: 1 | W72: =V72/Q72 -> 1
A73: 3 | B73: INTELLECTUAL PROPERTY (4) | C73: 5 | D73: 5 | E73: =D73/C73 -> 1 | F73: 5 | G73: =F73/C73 -> 1 | H73: 5 | I73: =H73/C73 -> 1 | J73: 5 | K73: 5 | L73: =K73/J73 -> 1 | M73: 5 | N73: =M73/J73 -> 1 | O73: 5 | P73: =O73/J73 -> 1 | Q73: 5 | R73: 5 | S73: =R73/Q73 -> 1 | T73: 5 | U73: =T73/Q73 -> 1 | V73: 5 | W73: =V73/Q73 -> 1
A74: 4 | B74: FAIR TRADING (5) | C74: 3 | D74: 3 | E74: =D74/C74 -> 1 | F74: 3 | G74: =F74/C74 -> 1 | H74: 3 | I74: =H74/C74 -> 1 | J74: 3 | K74: 3 | L74: =K74/J74 -> 1 | M74: 3 | N74: =M74/J74 -> 1 | O74: 3 | P74: =O74/J74 -> 1 | Q74: 3 | R74: 3 | S74: =R74/Q74 -> 1 | T74: 3 | U74: =T74/Q74 -> 1 | V74: 3 | W74: =V74/Q74 -> 1
A75: 7 | B75: ENVIRONMENT, SAFETY & HEALTH (8) | C75: 102 | D75: 102 | E75: =D75/C75 -> 1 | F75: 94 | G75: =F75/C75 -> 0.92156863 | H75: 87 | I75: =H75/C75 -> 0.85294118 | J75: 102 | K75: 102 | L75: =K75/J75 -> 1 | M75: 94 | N75: =M75/J75 -> 0.92156863 | O75: 88 | P75: =O75/J75 -> 0.8627451 | Q75: 102 | R75: 102 | S75: =R75/Q75 -> 1 | T75: 99 | U75: =T75/Q75 -> 0.97058824 | V75: 93 | W75: =V75/Q75 -> 0.91176471
B76: a. Safety & Health | C76: 31 | D76: 31 | E76: =D76/C76 -> 1 | F76: 31 | G76: =F76/C76 -> 1 | H76: 27 | I76: =H76/C76 -> 0.87096774 | J76: 31 | K76: 31 | L76: =K76/J76 -> 1 | M76: 31 | N76: =M76/J76 -> 1 | O76: 27 | P76: =O76/J76 -> 0.87096774 | Q76: 31 | R76: 31 | S76: =R76/Q76 -> 1 | T76: 31 | U76: =T76/Q76 -> 1 | V76: 27 | W76: =V76/Q76 -> 0.87096774
B77: b. Environment | C77: 63 | D77: 63 | E77: =D77/C77 -> 1 | F77: 61 | G77: =F77/C77 -> 0.96825397 | H77: 59 | I77: =H77/C77 -> 0.93650794 | J77: 63 | K77: 63 | L77: =K77/J77 -> 1 | M77: 61 | N77: =M77/J77 -> 0.96825397 | O77: 59 | P77: =O77/J77 -> 0.93650794 | Q77: 63 | R77: 63 | S77: =R77/Q77 -> 1 | T77: 60 | U77: =T77/Q77 -> 0.95238095 | V77: 58 | W77: =V77/Q77 -> 0.92063492
B78: c. SoC | C78: 8 | D78: 8 | E78: =D78/C78 -> 1 | F78: 2 | G78: =F78/C78 -> 0.25 | H78: 1 | I78: =H78/C78 -> 0.125 | J78: 8 | K78: 8 | L78: =K78/J78 -> 1 | M78: 2 | N78: =M78/J78 -> 0.25 | O78: 2 | P78: =O78/J78 -> 0.25 | Q78: 8 | R78: 8 | S78: =R78/Q78 -> 1 | T78: 8 | U78: =T78/Q78 -> 1 | V78: 8 | W78: =V78/Q78 -> 1
A79: 6 | B79: COMPANY /BUSINESS OPERATIONS & LICENSE (2) | C79: 54 | D79: 54 | E79: =D79/C79 -> 1 | F79: 54 | G79: =F79/C79 -> 1 | H79: 52 | I79: =H79/C79 -> 0.96296296 | J79: 54 | K79: 54 | L79: =K79/J79 -> 1 | M79: 54 | N79: =M79/J79 -> 1 | O79: 52 | P79: =O79/J79 -> 0.96296296 | Q79: 54 | R79: 54 | S79: =R79/Q79 -> 1 | T79: 54 | U79: =T79/Q79 -> 1 | V79: 52 | W79: =V79/Q79 -> 0.96296296
B80: TOTAL | C80: =C68+C69+C73+C74+C75+C79 -> 222 | D80: =D68+D69+D73+D74+D75+D79 -> 222 | E80: =D80/C80 -> 1 | F80: =F68+F69+F73+F74+F75+F79 -> 211 | G80: =F80/C80 -> 0.95045045 | H80: =H68+H69+H73+H74+H75+H79 -> 202 | I80: =H80/C80 -> 0.90990991 | J80: =J68+J69+J73+J74+J75+J79 -> 222 | K80: =K68+K69+K73+K74+K75+K79 -> 222 | L80: =K80/J80 -> 1 | M80: =M68+M69+M73+M74+M75+M79 -> 212 | N80: =M80/J80 -> 0.95495495 | O80: =O68+O69+O73+O74+O75+O79 -> 204 | P80: =O80/J80 -> 0.91891892 | Q80: =Q68+Q69+Q73+Q74+Q75+Q79 -> 223 | R80: =R68+R69+R73+R74+R75+R79 -> 223 | S80: =R80/Q80 -> 1 | T80: =T68+T69+T73+T74+T75+T79 -> 218 | U80: =T80/Q80 -> 0.97757848 | V80: =V68+V69+V73+V74+V75+V79 -> 210 | W80: =V80/Q80 -> 0.94170404
A82: 5 | B82: EXIM MANAGEMENT (6) | C82: 39 | D82: 39 | E82: =D82/C82 -> 1 | F82: 39 | G82: =F82/C82 -> 1 | H82: 39 | I82: =H82/C82 -> 1 | J82: 11 | K82: 11 | L82: =K82/J82 -> 1 | M82: 11 | N82: =M82/J82 -> 1 | O82: 11 | P82: =O82/J82 -> 1 | Q82: 11 | R82: 11 | S82: =R82/Q82 -> 1 | T82: 11 | U82: =T82/Q82 -> 1 | V82: 11 | W82: =V82/Q82 -> 1
A83: 8 | B83: ACCOUNTING /FINANCE (7) | C83: 21 | D83: 21 | E83: =D83/C83 -> 1 | F83: 21 | G83: =F83/C83 -> 1 | H83: 19 | I83: =H83/C83 -> 0.9047619 | J83: 21 | K83: 21 | L83: =K83/J83 -> 1 | M83: 21 | N83: =M83/J83 -> 1 | O83: 19 | P83: =O83/J83 -> 0.9047619 | Q83: 21 | R83: 21 | S83: =R83/Q83 -> 1 | T83: 21 | U83: =T83/Q83 -> 1 | V83: 21 | W83: =V83/Q83 -> 1
B84: TOTAL | C84: =SUM(C82:C83)+C80 -> 282 | D84: =SUM(D82:D83)+D80 -> 282 | E84: =D84/C84 -> 1 | F84: =SUM(F82:F83)+F80 -> 271 | G84: =F84/C84 -> 0.96099291 | H84: =SUM(H82:H83)+H80 -> 260 | I84: =H84/C84 -> 0.92198582 | J84: =SUM(J82:J83)+J80 -> 254 | K84: =SUM(K82:K83)+K80 -> 254 | L84: =K84/J84 -> 1 | M84: =SUM(M82:M83)+M80 -> 244 | N84: =M84/J84 -> 0.96062992 | O84: =SUM(O82:O83)+O80 -> 234 | P84: =O84/J84 -> 0.92125984 | Q84: =SUM(Q82:Q83)+Q80 -> 255 | R84: =SUM(R82:R83)+R80 -> 255 | S84: =R84/Q84 -> 1 | T84: =SUM(T82:T83)+T80 -> 250 | U84: =T84/Q84 -> 0.98039216 | V84: =SUM(V82:V83)+V80 -> 242 | W84: =V84/Q84 -> 0.94901961
A87: NO | B87: BIDANG | C87: 43922 | J87: 43952 | Q87: 43983
C88: Jml regulasi | D88: Identifikasi | F88: Evaluasi | H88: Implementasi | J88: Jml regulasi | K88: Identifikasi | M88: Evaluasi | O88: Implementasi | Q88: Jml regulasi | R88: Identifikasi | T88: Evaluasi | V88: Implementasi
D89: Jml | E89: % | F89: Jml | G89: % | H89: Jml | I89: % | K89: Jml | L89: % | M89: Jml | N89: % | O89: Jml | P89: % | R89: Jml | S89: % | T89: Jml | U89: % | V89: Jml | W89: %
A90: 1 | B90: COMPLIANCE IN GENERAL (1) | C90: 0 | D90: 0 | E90: =D90/C90 -> #DIV/0! | F90: 0 | G90: =F90/C90 -> #DIV/0! | H90: 0 | I90: =H90/C90 -> #DIV/0! | J90: 0 | K90: 0 | L90: =K90/J90 -> #DIV/0! | M90: 0 | N90: =M90/J90 -> #DIV/0! | O90: 0 | P90: =O90/J90 -> #DIV/0! | Q90: 0 | R90: 0 | S90: =R90/Q90 -> #DIV/0! | T90: 0 | U90: =T90/Q90 -> #DIV/0! | V90: 0 | W90: =V90/Q90 -> #DIV/0!
A91: 2 | B91: LABOR & HUMAN RIGHTS (3) | C91: 58 | D91: 58 | E91: =D91/C91 -> 1 | F91: 58 | G91: =F91/C91 -> 1 | H91: 58 | I91: =H91/C91 -> 1 | J91: 59 | K91: 59 | L91: =K91/J91 -> 1 | M91: 58 | N91: =M91/J91 -> 0.98305085 | O91: 58 | P91: =O91/J91 -> 0.98305085 | Q91: 60 | R91: 60 | S91: =R91/Q91 -> 1 | T91: 58 | U91: =T91/Q91 -> 0.96666667 | V91: 58 | W91: =V91/Q91 -> 0.96666667
B92: a. HR | C92: 35 | D92: 35 | E92: =D92/C92 -> 1 | F92: 35 | G92: =F92/C92 -> 1 | H92: 35 | I92: =H92/C92 -> 1 | J92: 36 | K92: 36 | L92: =K92/J92 -> 1 | M92: 35 | N92: =M92/J92 -> 0.97222222 | O92: 35 | P92: =O92/J92 -> 0.97222222 | Q92: 37 | R92: 37 | S92: =R92/Q92 -> 1 | T92: 35 | U92: =T92/Q92 -> 0.94594595 | V92: 35 | W92: =V92/Q92 -> 0.94594595
B93: b. Expat | C93: 22 | D93: 22 | E93: =D93/C93 -> 1 | F93: 22 | G93: =F93/C93 -> 1 | H93: 22 | I93: =H93/C93 -> 1 | J93: 22 | K93: 22 | L93: =K93/J93 -> 1 | M93: 22 | N93: =M93/J93 -> 1 | O93: 22 | P93: =O93/J93 -> 1 | Q93: 22 | R93: 22 | S93: =R93/Q93 -> 1 | T93: 22 | U93: =T93/Q93 -> 1 | V93: 22 | W93: =V93/Q93 -> 1
B94: c. TRN | C94: 1 | D94: 1 | E94: =D94/C94 -> 1 | F94: 1 | G94: =F94/C94 -> 1 | H94: 1 | I94: =H94/C94 -> 1 | J94: 1 | K94: 1 | L94: =K94/J94 -> 1 | M94: 1 | N94: =M94/J94 -> 1 | O94: 1 | P94: =O94/J94 -> 1 | Q94: 1 | R94: 1 | S94: =R94/Q94 -> 1 | T94: 1 | U94: =T94/Q94 -> 1 | V94: 1 | W94: =V94/Q94 -> 1
A95: 3 | B95: INTELLECTUAL PROPERTY (4) | C95: 5 | D95: 5 | E95: =D95/C95 -> 1 | F95: 5 | G95: =F95/C95 -> 1 | H95: 5 | I95: =H95/C95 -> 1 | J95: 5 | K95: 5 | L95: =K95/J95 -> 1 | M95: 5 | N95: =M95/J95 -> 1 | O95: 5 | P95: =O95/J95 -> 1 | Q95: 5 | R95: 5 | S95: =R95/Q95 -> 1 | T95: 5 | U95: =T95/Q95 -> 1 | V95: 5 | W95: =V95/Q95 -> 1
A96: 4 | B96: FAIR TRADING (5) | C96: 3 | D96: 3 | E96: =D96/C96 -> 1 | F96: 3 | G96: =F96/C96 -> 1 | H96: 3 | I96: =H96/C96 -> 1 | J96: 3 | K96: 3 | L96: =K96/J96 -> 1 | M96: 3 | N96: =M96/J96 -> 1 | O96: 3 | P96: =O96/J96 -> 1 | Q96: 3 | R96: 3 | S96: =R96/Q96 -> 1 | T96: 3 | U96: =T96/Q96 -> 1 | V96: 3 | W96: =V96/Q96 -> 1
A97: 7 | B97: ENVIRONMENT, SAFETY & HEALTH (8) | C97: 102 | D97: 102 | E97: =D97/C97 -> 1 | F97: 102 | G97: =F97/C97 -> 1 | H97: 96 | I97: =H97/C97 -> 0.94117647 | J97: 102 | K97: 102 | L97: =K97/J97 -> 1 | M97: 102 | N97: =M97/J97 -> 1 | O97: 96 | P97: =O97/J97 -> 0.94117647 | Q97: 102 | R97: 102 | S97: =R97/Q97 -> 1 | T97: 102 | U97: =T97/Q97 -> 1 | V97: 96 | W97: =V97/Q97 -> 0.94117647
B98: a. Safety & Health | C98: 31 | D98: 31 | E98: =D98/C98 -> 1 | F98: 31 | G98: =F98/C98 -> 1 | H98: 27 | I98: =H98/C98 -> 0.87096774 | J98: 31 | K98: 31 | L98: =K98/J98 -> 1 | M98: 31 | N98: =M98/J98 -> 1 | O98: 27 | P98: =O98/J98 -> 0.87096774 | Q98: 31 | R98: 31 | S98: =R98/Q98 -> 1 | T98: 31 | U98: =T98/Q98 -> 1 | V98: 27 | W98: =V98/Q98 -> 0.87096774
B99: b. Environment | C99: 63 | D99: 63 | E99: =D99/C99 -> 1 | F99: 63 | G99: =F99/C99 -> 1 | H99: 61 | I99: =H99/C99 -> 0.96825397 | J99: 63 | K99: 63 | L99: =K99/J99 -> 1 | M99: 63 | N99: =M99/J99 -> 1 | O99: 61 | P99: =O99/J99 -> 0.96825397 | Q99: 63 | R99: 63 | S99: =R99/Q99 -> 1 | T99: 63 | U99: =T99/Q99 -> 1 | V99: 61 | W99: =V99/Q99 -> 0.96825397
B100: c. SoC | C100: 8 | D100: 8 | E100: =D100/C100 -> 1 | F100: 8 | G100: =F100/C100 -> 1 | H100: 8 | I100: =H100/C100 -> 1 | J100: 8 | K100: 8 | L100: =K100/J100 -> 1 | M100: 8 | N100: =M100/J100 -> 1 | O100: 8 | P100: =O100/J100 -> 1 | Q100: 8 | R100: 8 | S100: =R100/Q100 -> 1 | T100: 8 | U100: =T100/Q100 -> 1 | V100: 8 | W100: =V100/Q100 -> 1
A101: 6 | B101: COMPANY /BUSINESS OPERATIONS & LICENSE (2) | C101: 54 | D101: 54 | E101: =D101/C101 -> 1 | F101: 54 | G101: =F101/C101 -> 1 | H101: 52 | I101: =H101/C101 -> 0.96296296 | J101: 54 | K101: 54 | L101: =K101/J101 -> 1 | M101: 54 | N101: =M101/J101 -> 1 | O101: 53 | P101: =O101/J101 -> 0.98148148 | Q101: 54 | R101: 54 | S101: =R101/Q101 -> 1 | T101: 54 | U101: =T101/Q101 -> 1 | V101: 53 | W101: =V101/Q101 -> 0.98148148
B102: TOTAL | C102: =C90+C91+C95+C96+C97+C101 -> 222 | D102: =D90+D91+D95+D96+D97+D101 -> 222 | E102: =D102/C102 -> 1 | F102: =F90+F91+F95+F96+F97+F101 -> 222 | G102: =F102/C102 -> 1 | H102: =H90+H91+H95+H96+H97+H101 -> 214 | I102: =H102/C102 -> 0.96396396 | J102: =J90+J91+J95+J96+J97+J101 -> 223 | K102: =K90+K91+K95+K96+K97+K101 -> 223 | L102: =K102/J102 -> 1 | M102: =M90+M91+M95+M96+M97+M101 -> 222 | N102: =M102/J102 -> 0.9955157 | O102: =O90+O91+O95+O96+O97+O101 -> 215 | P102: =O102/J102 -> 0.96412556 | Q102: =Q90+Q91+Q95+Q96+Q97+Q101 -> 224 | R102: =R90+R91+R95+R96+R97+R101 -> 224 | S102: =R102/Q102 -> 1 | T102: =T90+T91+T95+T96+T97+T101 -> 222 | U102: =T102/Q102 -> 0.99107143 | V102: =V90+V91+V95+V96+V97+V101 -> 215 | W102: =V102/Q102 -> 0.95982143
A104: 5 | B104: EXIM MANAGEMENT (6) | C104: 11 | D104: 11 | E104: =D104/C104 -> 1 | F104: 11 | G104: =F104/C104 -> 1 | H104: 11 | I104: =H104/C104 -> 1 | J104: 11 | K104: 11 | L104: =K104/J104 -> 1 | M104: 11 | N104: =M104/J104 -> 1 | O104: 11 | P104: =O104/J104 -> 1 | Q104: 11 | R104: 11 | S104: =R104/Q104 -> 1 | T104: 11 | U104: =T104/Q104 -> 1 | V104: 11 | W104: =V104/Q104 -> 1
A105: 8 | B105: ACCOUNTING /FINANCE (7) | C105: 21 | D105: 21 | E105: =D105/C105 -> 1 | F105: 21 | G105: =F105/C105 -> 1 | H105: 21 | I105: =H105/C105 -> 1 | J105: 21 | K105: 21 | L105: =K105/J105 -> 1 | M105: 21 | N105: =M105/J105 -> 1 | O105: 21 | P105: =O105/J105 -> 1 | Q105: 21 | R105: 21 | S105: =R105/Q105 -> 1 | T105: 21 | U105: =T105/Q105 -> 1 | V105: 21 | W105: =V105/Q105 -> 1
B106: TOTAL | C106: =SUM(C104:C105)+C102 -> 254 | D106: =SUM(D104:D105)+D102 -> 254 | E106: =D106/C106 -> 1 | F106: =SUM(F104:F105)+F102 -> 254 | G106: =F106/C106 -> 1 | H106: =SUM(H104:H105)+H102 -> 246 | I106: =H106/C106 -> 0.96850394 | J106: =SUM(J104:J105)+J102 -> 255 | K106: =SUM(K104:K105)+K102 -> 255 | L106: =K106/J106 -> 1 | M106: =SUM(M104:M105)+M102 -> 254 | N106: =M106/J106 -> 0.99607843 | O106: =SUM(O104:O105)+O102 -> 247 | P106: =O106/J106 -> 0.96862745 | Q106: =SUM(Q104:Q105)+Q102 -> 256 | R106: =SUM(R104:R105)+R102 -> 256 | S106: =R106/Q106 -> 1 | T106: =SUM(T104:T105)+T102 -> 254 | U106: =T106/Q106 -> 0.9921875 | V106: =SUM(V104:V105)+V102 -> 247 | W106: =V106/Q106 -> 0.96484375

Sheet 80
A2: Now day
A4: NO | B4: BIDANG | C4: NOW DAY
C5: Jml regulasi | D5: Identifikasi | F5: Evaluasi | H5: Implementasi
D6: Jml | E6: % | F6: Jml | G6: % | H6: Jml | I6: %
A7: 1 | B7: COMPLIANCE IN GENERAL (1) | C7: ='Detail COMPLIANCE FIELD'!G15 -> 0 | D7: =C7 -> 0 | E7: 1 | F7: ='Detail COMPLIANCE FIELD'!I15 -> 0 | G7: 1 | H7: ='Detail COMPLIANCE FIELD'!K15 -> 0 | I7: 1
A8: 2 | B8: LABOR & HUMAN RIGHTS (3) | C8: ='Detail COMPLIANCE FIELD'!G16 -> 99 | D8: =C8 -> 99 | E8: =D8/C8 -> 1 | F8: ='Detail COMPLIANCE FIELD'!I16 -> 99 | G8: =F8/C8 -> 1 | H8: ='Detail COMPLIANCE FIELD'!K16 -> 98 | I8: =H8/C8 -> 0.98989899
A9: 3 | B9: INTELLECTUAL PROPERTY (4) | C9: ='Detail COMPLIANCE FIELD'!G17 -> 126 | D9: =C9 -> 126 | E9: =D9/C9 -> 1 | F9: ='Detail COMPLIANCE FIELD'!I17 -> 126 | G9: =F9/C9 -> 1 | H9: ='Detail COMPLIANCE FIELD'!K17 -> 122 | I9: =H9/C9 -> 0.96825397
A10: 4 | B10: FAIR TRADING (5) | C10: ='Detail COMPLIANCE FIELD'!G18 -> 7 | D10: =C10 -> 7 | E10: =D10/C10 -> 1 | F10: ='Detail COMPLIANCE FIELD'!I18 -> 7 | G10: =F10/C10 -> 1 | H10: ='Detail COMPLIANCE FIELD'!K18 -> 7 | I10: =H10/C10 -> 1
A11: 5 | B11: ENVIRONMENT, SAFETY & HEALTH (8) | C11: ='Detail COMPLIANCE FIELD'!G19 -> 6 | D11: =C11 -> 6 | E11: =D11/C11 -> 1 | F11: ='Detail COMPLIANCE FIELD'!I19 -> 6 | G11: =F11/C11 -> 1 | H11: ='Detail COMPLIANCE FIELD'!K19 -> 6 | I11: =H11/C11 -> 1
A12: 6 | B12: COMPANY /BUSINESS OPERATIONS & LICENSE (2) | C12: ='Detail COMPLIANCE FIELD'!G20 -> 37 | D12: =C12 -> 37 | E12: =D12/C12 -> 1 | F12: ='Detail COMPLIANCE FIELD'!I20 -> 37 | G12: =F12/C12 -> 1 | H12: ='Detail COMPLIANCE FIELD'!K20 -> 37 | I12: =H12/C12 -> 1
B13: TOTAL | C13: =SUM(C7:C12) -> 275 | D13: =SUM(D7:D12) -> 275 | E13: =D13/C13 -> 1 | F13: =SUM(F7:F12) -> 275 | G13: =F13/C13 -> 1 | H13: =SUM(H7:H12) -> 270 | I13: =H13/C13 -> 0.98181818
A15: 7 | B15: EXIM MANAGEMENT (6) | C15: ='Detail COMPLIANCE FIELD'!G21 -> 56 | D15: =C15 -> 56 | E15: =D15/C15 -> 1 | F15: ='Detail COMPLIANCE FIELD'!I21 -> 56 | G15: =F15/C15 -> 1 | H15: ='Detail COMPLIANCE FIELD'!K21 -> 56 | I15: =H15/C15 -> 1
A16: 8 | B16: ACCOUNTING /FINANCE (7) | C16: ='Detail COMPLIANCE FIELD'!G22 -> 123 | D16: =C16 -> 123 | E16: =D16/C16 -> 1 | F16: ='Detail COMPLIANCE FIELD'!I22 -> 123 | G16: =F16/C16 -> 1 | H16: ='Detail COMPLIANCE FIELD'!K22 -> 116 | I16: =H16/C16 -> 0.94308943
B17: TOTAL | C17: =SUM(C15:C16)+C13 -> 454 | D17: =SUM(D15:D16)+D13 -> 454 | E17: =D17/C17 -> 1 | F17: =SUM(F15:F16)+F13 -> 454 | G17: =F17/C17 -> 1 | H17: =SUM(H15:H16)+H13 -> 442 | I17: =H17/C17 -> 0.97356828
A18: PT. SEMARANG AUTOCOMP MANUFACTURING INDONESIA
A19: KEPATUHAN TERHADAP PERATURAN PERUNDANGAN
A21: NO | B21: BIDANG | C21: 44013 | J21: 44044 | Q21: 44075
C22: Jml regulasi | D22: Identifikasi | F22: Evaluasi | H22: Implementasi | J22: Jml regulasi | K22: Identifikasi | M22: Evaluasi | O22: Implementasi | Q22: Jml regulasi | R22: Identifikasi | T22: Evaluasi | V22: Implementasi
D23: Jml | E23: % | F23: Jml | G23: % | H23: Jml | I23: % | K23: Jml | L23: % | M23: Jml | N23: % | O23: Jml | P23: % | R23: Jml | S23: % | T23: Jml | U23: % | V23: Jml | W23: %
A24: 1 | B24: COMPLIANCE IN GENERAL (1) | C24: 0 | D24: 0 | E24: =D24/C24 -> #DIV/0! | F24: 0 | G24: =F24/C24 -> #DIV/0! | H24: 0 | I24: =H24/C24 -> #DIV/0! | J24: 0 | K24: 0 | L24: =K24/J24 -> #DIV/0! | M24: 0 | N24: =M24/J24 -> #DIV/0! | O24: 0 | P24: =O24/J24 -> #DIV/0! | Q24: 0 | R24: 0 | S24: =R24/Q24 -> #DIV/0! | T24: 0 | U24: =T24/Q24 -> #DIV/0! | V24: 0 | W24: =V24/Q24 -> #DIV/0!
A25: 2 | B25: LABOR & HUMAN RIGHTS (3) | C25: 61 | D25: 61 | E25: =D25/C25 -> 1 | F25: 57 | G25: =F25/C25 -> 0.93442623 | H25: 57 | I25: =H25/C25 -> 0.93442623 | J25: 62 | K25: 62 | L25: =K25/J25 -> 1 | M25: 62 | N25: =M25/J25 -> 1 | O25: 58 | P25: =O25/J25 -> 0.93548387 | Q25: 62 | R25: 62 | S25: =R25/Q25 -> 1 | T25: 62 | U25: =T25/Q25 -> 1 | V25: 62 | W25: =V25/Q25 -> 1
B26: a. HR | C26: 38 | D26: 38 | E26: =D26/C26 -> 1 | F26: 35 | G26: =F26/C26 -> 0.92105263 | H26: 35 | I26: =H26/C26 -> 0.92105263 | J26: 39 | K26: 39 | L26: =K26/J26 -> 1 | M26: 39 | N26: =M26/J26 -> 1 | O26: 35 | P26: =O26/J26 -> 0.8974359 | Q26: 39 | R26: 39 | S26: =R26/Q26 -> 1 | T26: 39 | U26: =T26/Q26 -> 1 | V26: 39 | W26: =V26/Q26 -> 1
B27: b. Expat | C27: 22 | D27: 22 | E27: =D27/C27 -> 1 | F27: 21 | G27: =F27/C27 -> 0.95454545 | H27: 21 | I27: =H27/C27 -> 0.95454545 | J27: 22 | K27: 22 | L27: =K27/J27 -> 1 | M27: 22 | N27: =M27/J27 -> 1 | O27: 21 | P27: =O27/J27 -> 0.95454545 | Q27: 22 | R27: 22 | S27: =R27/Q27 -> 1 | T27: 22 | U27: =T27/Q27 -> 1 | V27: 22 | W27: =V27/Q27 -> 1
B28: c. TRN | C28: 1 | D28: 1 | E28: =D28/C28 -> 1 | F28: 1 | G28: =F28/C28 -> 1 | H28: 1 | I28: =H28/C28 -> 1 | J28: 1 | K28: 1 | L28: =K28/J28 -> 1 | M28: 1 | N28: =M28/J28 -> 1 | O28: 1 | P28: =O28/J28 -> 1 | Q28: 1 | R28: 1 | S28: =R28/Q28 -> 1 | T28: 1 | U28: =T28/Q28 -> 1 | V28: 1 | W28: =V28/Q28 -> 1
A29: 3 | B29: INTELLECTUAL PROPERTY (4) | C29: 5 | D29: 5 | E29: =D29/C29 -> 1 | F29: 5 | G29: =F29/C29 -> 1 | H29: 5 | I29: =H29/C29 -> 1 | J29: 5 | K29: 5 | L29: =K29/J29 -> 1 | M29: 5 | N29: =M29/J29 -> 1 | O29: 5 | P29: =O29/J29 -> 1 | Q29: 5 | R29: 5 | S29: =R29/Q29 -> 1 | T29: 5 | U29: =T29/Q29 -> 1 | V29: 5 | W29: =V29/Q29 -> 1
A30: 4 | B30: FAIR TRADING (5) | C30: 3 | D30: 3 | E30: =D30/C30 -> 1 | F30: 3 | G30: =F30/C30 -> 1 | H30: 3 | I30: =H30/C30 -> 1 | J30: 3 | K30: 3 | L30: =K30/J30 -> 1 | M30: 3 | N30: =M30/J30 -> 1 | O30: 3 | P30: =O30/J30 -> 1 | Q30: 3 | R30: 3 | S30: =R30/Q30 -> 1 | T30: 3 | U30: =T30/Q30 -> 1 | V30: 3 | W30: =V30/Q30 -> 1
A31: 6 | B31: ENVIRONMENT, SAFETY & HEALTH (8) | C31: 100 | D31: 100 | E31: =D31/C31 -> 1 | F31: 97 | G31: =F31/C31 -> 0.97 | H31: 91 | I31: =H31/C31 -> 0.91 | J31: 102 | K31: 102 | L31: =K31/J31 -> 1 | M31: 102 | N31: =M31/J31 -> 1 | O31: 92 | P31: =O31/J31 -> 0.90196078 | Q31: 105 | R31: 105 | S31: =R31/Q31 -> 1 | T31: 105 | U31: =T31/Q31 -> 1 | V31: 99 | W31: =V31/Q31 -> 0.94285714
B32: a. Safety & Health | C32: 30 | D32: 30 | E32: =D32/C32 -> 1 | F32: 29 | G32: =F32/C32 -> 0.96666667 | H32: 25 | I32: =H32/C32 -> 0.83333333 | J32: 31 | K32: 31 | L32: =K32/J32 -> 1 | M32: 31 | N32: =M32/J32 -> 1 | O32: 26 | P32: =O32/J32 -> 0.83870968 | Q32: 34 | R32: 34 | S32: =R32/Q32 -> 1 | T32: 34 | U32: =T32/Q32 -> 1 | V32: 30 | W32: =V32/Q32 -> 0.88235294
B33: b. Environment | C33: 61 | D33: 61 | E33: =D33/C33 -> 1 | F33: 60 | G33: =F33/C33 -> 0.98360656 | H33: 58 | I33: =H33/C33 -> 0.95081967 | J33: 62 | K33: 62 | L33: =K33/J33 -> 1 | M33: 62 | N33: =M33/J33 -> 1 | O33: 58 | P33: =O33/J33 -> 0.93548387 | Q33: 62 | R33: 62 | S33: =R33/Q33 -> 1 | T33: 62 | U33: =T33/Q33 -> 1 | V33: 60 | W33: =V33/Q33 -> 0.96774194
B34: c. SoC | C34: 9 | D34: 9 | E34: =D34/C34 -> 1 | F34: 8 | G34: =F34/C34 -> 0.88888889 | H34: 8 | I34: =H34/C34 -> 0.88888889 | J34: 9 | K34: 9 | L34: =K34/J34 -> 1 | M34: 9 | N34: =M34/J34 -> 1 | O34: 8 | P34: =O34/J34 -> 0.88888889 | Q34: 9 | R34: 9 | S34: =R34/Q34 -> 1 | T34: 9 | U34: =T34/Q34 -> 1 | V34: 9 | W34: =V34/Q34 -> 1
A35: 7 | B35: COMPANY /BUSINESS OPERATIONS & LICENSE (2) | C35: 54 | D35: 54 | E35: =D35/C35 -> 1 | F35: 50 | G35: =F35/C35 -> 0.92592593 | H35: 49 | I35: =H35/C35 -> 0.90740741 | J35: 62 | K35: 62 | L35: =K35/J35 -> 1 | M35: 62 | N35: =M35/J35 -> 1 | O35: 49 | P35: =O35/J35 -> 0.79032258 | Q35: 63 | R35: 63 | S35: =R35/Q35 -> 1 | T35: 63 | U35: =T35/Q35 -> 1 | V35: 54 | W35: =V35/Q35 -> 0.85714286
B36: TOTAL | C36: =C24+C25+C29+C30+C31+C35 -> 223 | D36: =D24+D25+D29+D30+D31+D35 -> 223 | E36: =D36/C36 -> 1 | F36: =F24+F25+F29+F30+F31+F35 -> 212 | G36: =F36/C36 -> 0.95067265 | H36: =H24+H25+H29+H30+H31+H35 -> 205 | I36: =H36/C36 -> 0.91928251 | J36: =J24+J25+J29+J30+J31+J35 -> 234 | K36: =K24+K25+K29+K30+K31+K35 -> 234 | L36: =K36/J36 -> 1 | M36: =M24+M25+M29+M30+M31+M35 -> 234 | N36: =M36/J36 -> 1 | O36: =O24+O25+O29+O30+O31+O35 -> 207 | P36: =O36/J36 -> 0.88461538 | Q36: =Q24+Q25+Q29+Q30+Q31+Q35 -> 238 | R36: =R24+R25+R29+R30+R31+R35 -> 238 | S36: =R36/Q36 -> 1 | T36: =T24+T25+T29+T30+T31+T35 -> 238 | U36: =T36/Q36 -> 1 | V36: =V24+V25+V29+V30+V31+V35 -> 223 | W36: =V36/Q36 -> 0.93697479
A38: 5 | B38: EXIM MANAGEMENT (6) | C38: 13 | D38: 13 | E38: =D38/C38 -> 1 | F38: 11 | G38: =F38/C38 -> 0.84615385 | H38: 11 | I38: =H38/C38 -> 0.84615385 | J38: 15 | K38: 15 | L38: =K38/J38 -> 1 | M38: 15 | N38: =M38/J38 -> 1 | O38: 11 | P38: =O38/J38 -> 0.73333333 | Q38: 15 | R38: 15 | S38: =R38/Q38 -> 1 | T38: 15 | U38: =T38/Q38 -> 1 | V38: 11 | W38: =V38/Q38 -> 0.73333333
A39: 8 | B39: ACCOUNTING /FINANCE (7) | C39: 21 | D39: 21 | E39: =D39/C39 -> 1 | F39: 19 | G39: =F39/C39 -> 0.9047619 | H39: 19 | I39: =H39/C39 -> 0.9047619 | J39: 26 | K39: 26 | L39: =K39/J39 -> 1 | M39: 26 | N39: =M39/J39 -> 1 | O39: 19 | P39: =O39/J39 -> 0.73076923 | Q39: 26 | R39: 26 | S39: =R39/Q39 -> 1 | T39: 26 | U39: =T39/Q39 -> 1 | V39: 26 | W39: =V39/Q39 -> 1
B40: TOTAL | C40: =SUM(C38:C39)+C36 -> 257 | D40: =SUM(D38:D39)+D36 -> 257 | E40: =D40/C40 -> 1 | F40: =SUM(F38:F39)+F36 -> 242 | G40: =F40/C40 -> 0.94163424 | H40: =SUM(H38:H39)+H36 -> 235 | I40: =H40/C40 -> 0.91439689 | J40: =SUM(J38:J39)+J36 -> 275 | K40: =SUM(K38:K39)+K36 -> 275 | L40: =K40/J40 -> 1 | M40: =SUM(M38:M39)+M36 -> 275 | N40: =M40/J40 -> 1 | O40: =SUM(O38:O39)+O36 -> 237 | P40: =O40/J40 -> 0.86181818 | Q40: =SUM(Q38:Q39)+Q36 -> 279 | R40: =SUM(R38:R39)+R36 -> 279 | S40: =R40/Q40 -> 1 | T40: =SUM(T38:T39)+T36 -> 279 | U40: =T40/Q40 -> 1 | V40: =SUM(V38:V39)+V36 -> 260 | W40: =V40/Q40 -> 0.93189964
A43: NO | B43: BIDANG | C43: 44105 | J43: 44136 | Q43: 44166
C44: Jml regulasi | D44: Identifikasi | F44: Evaluasi | H44: Implementasi | J44: Jml regulasi | K44: Identifikasi | M44: Evaluasi | O44: Implementasi | Q44: Jml regulasi | R44: Identifikasi | T44: Evaluasi | V44: Implementasi
D45: Jml | E45: % | F45: Jml | G45: % | H45: Jml | I45: % | K45: Jml | L45: % | M45: Jml | N45: % | O45: Jml | P45: % | R45: Jml | S45: % | T45: Jml | U45: % | V45: Jml | W45: %
A46: 1 | B46: COMPLIANCE IN GENERAL (1) | C46: 0 | D46: 0 | E46: =D46/C46 -> #DIV/0! | F46: 0 | G46: =F46/C46 -> #DIV/0! | H46: 0 | I46: =H46/C46 -> #DIV/0! | J46: 0 | K46: 0 | L46: =K46/J46 -> #DIV/0! | M46: 0 | N46: =M46/J46 -> #DIV/0! | O46: 0 | P46: =O46/J46 -> #DIV/0! | Q46: 0 | R46: 0 | S46: =R46/Q46 -> #DIV/0! | T46: 0 | U46: =T46/Q46 -> #DIV/0! | V46: 0 | W46: =V46/Q46 -> #DIV/0!
A47: 2 | B47: LABOR & HUMAN RIGHTS (3) | C47: 64 | D47: 64 | E47: =D47/C47 -> 1 | F47: 64 | G47: =F47/C47 -> 1 | H47: 63 | I47: =H47/C47 -> 0.984375 | J47: 65 | K47: 65 | L47: =K47/J47 -> 1 | M47: 65 | N47: =M47/J47 -> 1 | O47: 64 | P47: =O47/J47 -> 0.98461538 | Q47: 65 | R47: 65 | S47: =R47/Q47 -> 1 | T47: 65 | U47: =T47/Q47 -> 1 | V47: 64 | W47: =V47/Q47 -> 0.98461538
B48: a. HR | C48: 39 | D48: 39 | E48: =D48/C48 -> 1 | F48: 39 | G48: =F48/C48 -> 1 | H48: 39 | I48: =H48/C48 -> 1 | J48: 40 | K48: 40 | L48: =K48/J48 -> 1 | M48: 40 | N48: =M48/J48 -> 1 | O48: 40 | P48: =O48/J48 -> 1 | Q48: 40 | R48: 40 | S48: =R48/Q48 -> 1 | T48: 40 | U48: =T48/Q48 -> 1 | V48: 40 | W48: =V48/Q48 -> 1
B49: b. Expat | C49: 24 | D49: 24 | E49: =D49/C49 -> 1 | F49: 24 | G49: =F49/C49 -> 1 | H49: 23 | I49: =H49/C49 -> 0.95833333 | J49: 24 | K49: 24 | L49: =K49/J49 -> 1 | M49: 24 | N49: =M49/J49 -> 1 | O49: 23 | P49: =O49/J49 -> 0.95833333 | Q49: 24 | R49: 24 | S49: =R49/Q49 -> 1 | T49: 24 | U49: =T49/Q49 -> 1 | V49: 23 | W49: =V49/Q49 -> 0.95833333
B50: c. TRN | C50: 1 | D50: 1 | E50: =D50/C50 -> 1 | F50: 1 | G50: =F50/C50 -> 1 | H50: 1 | I50: =H50/C50 -> 1 | J50: 1 | K50: 1 | L50: =K50/J50 -> 1 | M50: 1 | N50: =M50/J50 -> 1 | O50: 1 | P50: =O50/J50 -> 1 | Q50: 1 | R50: 1 | S50: =R50/Q50 -> 1 | T50: 1 | U50: =T50/Q50 -> 1 | V50: 1 | W50: =V50/Q50 -> 1
A51: 3 | B51: INTELLECTUAL PROPERTY (4) | C51: 5 | D51: 5 | E51: =D51/C51 -> 1 | F51: 5 | G51: =F51/C51 -> 1 | H51: 5 | I51: =H51/C51 -> 1 | J51: 5 | K51: 5 | L51: =K51/J51 -> 1 | M51: 5 | N51: =M51/J51 -> 1 | O51: 5 | P51: =O51/J51 -> 1 | Q51: 5 | R51: 5 | S51: =R51/Q51 -> 1 | T51: 5 | U51: =T51/Q51 -> 1 | V51: 5 | W51: =V51/Q51 -> 1
A52: 7 | B52: FAIR TRADING (5) | C52: 3 | D52: 3 | E52: =D52/C52 -> 1 | F52: 3 | G52: =F52/C52 -> 1 | H52: 3 | I52: =H52/C52 -> 1 | J52: 3 | K52: 3 | L52: =K52/J52 -> 1 | M52: 3 | N52: =M52/J52 -> 1 | O52: 3 | P52: =O52/J52 -> 1 | Q52: 3 | R52: 3 | S52: =R52/Q52 -> 1 | T52: 3 | U52: =T52/Q52 -> 1 | V52: 3 | W52: =V52/Q52 -> 1
A53: 4 | B53: ENVIRONMENT, SAFETY & HEALTH (8) | C53: 106 | D53: 106 | E53: =D53/C53 -> 1 | F53: 106 | G53: =F53/C53 -> 1 | H53: 99 | I53: =H53/C53 -> 0.93396226 | J53: 107 | K53: 107 | L53: =K53/J53 -> 1 | M53: 107 | N53: =M53/J53 -> 1 | O53: 100 | P53: =O53/J53 -> 0.93457944 | Q53: 107 | R53: 107 | S53: =R53/Q53 -> 1 | T53: 107 | U53: =T53/Q53 -> 1 | V53: 100 | W53: =V53/Q53 -> 0.93457944
B54: a. Safety & Health | C54: 35 | D54: 35 | E54: =D54/C54 -> 1 | F54: 35 | G54: =F54/C54 -> 1 | H54: 30 | I54: =H54/C54 -> 0.85714286 | J54: 35 | K54: 35 | L54: =K54/J54 -> 1 | M54: 35 | N54: =M54/J54 -> 1 | O54: 30 | P54: =O54/J54 -> 0.85714286 | Q54: 35 | R54: 35 | S54: =R54/Q54 -> 1 | T54: 35 | U54: =T54/Q54 -> 1 | V54: 30 | W54: =V54/Q54 -> 0.85714286
B55: b. Environment | C55: 62 | D55: 62 | E55: =D55/C55 -> 1 | F55: 62 | G55: =F55/C55 -> 1 | H55: 60 | I55: =H55/C55 -> 0.96774194 | J55: 63 | K55: 63 | L55: =K55/J55 -> 1 | M55: 63 | N55: =M55/J55 -> 1 | O55: 61 | P55: =O55/J55 -> 0.96825397 | Q55: 63 | R55: 63 | S55: =R55/Q55 -> 1 | T55: 63 | U55: =T55/Q55 -> 1 | V55: 61 | W55: =V55/Q55 -> 0.96825397
B56: c. SoC | C56: 9 | D56: 9 | E56: =D56/C56 -> 1 | F56: 9 | G56: =F56/C56 -> 1 | H56: 9 | I56: =H56/C56 -> 1 | J56: 9 | K56: 9 | L56: =K56/J56 -> 1 | M56: 9 | N56: =M56/J56 -> 1 | O56: 9 | P56: =O56/J56 -> 1 | Q56: 9 | R56: 9 | S56: =R56/Q56 -> 1 | T56: 9 | U56: =T56/Q56 -> 1 | V56: 9 | W56: =V56/Q56 -> 1
A57: 6 | B57: COMPANY /BUSINESS OPERATIONS & LICENSE (2) | C57: 63 | D57: 63 | E57: =D57/C57 -> 1 | F57: 63 | G57: =F57/C57 -> 1 | H57: 54 | I57: =H57/C57 -> 0.85714286 | J57: 66 | K57: 66 | L57: =K57/J57 -> 1 | M57: 66 | N57: =M57/J57 -> 1 | O57: 57 | P57: =O57/J57 -> 0.86363636 | Q57: 66 | R57: 66 | S57: =R57/Q57 -> 1 | T57: 66 | U57: =T57/Q57 -> 1 | V57: 57 | W57: =V57/Q57 -> 0.86363636
B58: TOTAL | C58: =C46+C47+C51+C52+C53+C57 -> 241 | D58: =D46+D47+D51+D52+D53+D57 -> 241 | E58: =D58/C58 -> 1 | F58: =F46+F47+F51+F52+F53+F57 -> 241 | G58: =F58/C58 -> 1 | H58: =H46+H47+H51+H52+H53+H57 -> 224 | I58: =H58/C58 -> 0.92946058 | J58: =J46+J47+J51+J52+J53+J57 -> 246 | K58: =K46+K47+K51+K52+K53+K57 -> 246 | L58: =K58/J58 -> 1 | M58: =M46+M47+M51+M52+M53+M57 -> 246 | N58: =M58/J58 -> 1 | O58: =O46+O47+O51+O52+O53+O57 -> 229 | P58: =O58/J58 -> 0.93089431 | Q58: =Q46+Q47+Q51+Q52+Q53+Q57 -> 246 | R58: =R46+R47+R51+R52+R53+R57 -> 246 | S58: =R58/Q58 -> 1 | T58: =T46+T47+T51+T52+T53+T57 -> 246 | U58: =T58/Q58 -> 1 | V58: =V46+V47+V51+V52+V53+V57 -> 229 | W58: =V58/Q58 -> 0.93089431
A60: 5 | B60: EXIM MANAGEMENT (6) | C60: 13 | D60: 13 | E60: =D60/C60 -> 1 | F60: 13 | G60: =F60/C60 -> 1 | H60: 13 | I60: =H60/C60 -> 1 | J60: 13 | K60: 13 | L60: =K60/J60 -> 1 | M60: 13 | N60: =M60/J60 -> 1 | O60: 13 | P60: =O60/J60 -> 1 | Q60: 13 | R60: 13 | S60: =R60/Q60 -> 1 | T60: 13 | U60: =T60/Q60 -> 1 | V60: 13 | W60: =V60/Q60 -> 1
A61: 8 | B61: ACCOUNTING /FINANCE (7) | C61: 26 | D61: 26 | E61: =D61/C61 -> 1 | F61: 26 | G61: =F61/C61 -> 1 | H61: 26 | I61: =H61/C61 -> 1 | J61: 26 | K61: 26 | L61: =K61/J61 -> 1 | M61: 26 | N61: =M61/J61 -> 1 | O61: 26 | P61: =O61/J61 -> 1 | Q61: 26 | R61: 26 | S61: =R61/Q61 -> 1 | T61: 26 | U61: =T61/Q61 -> 1 | V61: 26 | W61: =V61/Q61 -> 1
B62: TOTAL | C62: =SUM(C60:C61)+C58 -> 280 | D62: =SUM(D60:D61)+D58 -> 280 | E62: =D62/C62 -> 1 | F62: =SUM(F60:F61)+F58 -> 280 | G62: =F62/C62 -> 1 | H62: =SUM(H60:H61)+H58 -> 263 | I62: =H62/C62 -> 0.93928571 | J62: =SUM(J60:J61)+J58 -> 285 | K62: =SUM(K60:K61)+K58 -> 285 | L62: =K62/J62 -> 1 | M62: =SUM(M60:M61)+M58 -> 285 | N62: =M62/J62 -> 1 | O62: =SUM(O60:O61)+O58 -> 268 | P62: =O62/J62 -> 0.94035088 | Q62: =SUM(Q60:Q61)+Q58 -> 285 | R62: =SUM(R60:R61)+R58 -> 285 | S62: =R62/Q62 -> 1 | T62: =SUM(T60:T61)+T58 -> 285 | U62: =T62/Q62 -> 1 | V62: =SUM(V60:V61)+V58 -> 268 | W62: =V62/Q62 -> 0.94035088
A65: NO | B65: BIDANG | C65: 44197 | J65: 44228 | Q65: 44256
C66: Jml regulasi | D66: Identifikasi | F66: Evaluasi | H66: Implementasi | J66: Jml regulasi | K66: Identifikasi | M66: Evaluasi | O66: Implementasi | Q66: Jml regulasi | R66: Identifikasi | T66: Evaluasi | V66: Implementasi
D67: Jml | E67: % | F67: Jml | G67: % | H67: Jml | I67: % | K67: Jml | L67: % | M67: Jml | N67: % | O67: Jml | P67: % | R67: Jml | S67: % | T67: Jml | U67: % | V67: Jml | W67: %
A68: 1 | B68: COMPLIANCE IN GENERAL (1) | C68: 0 | D68: 0 | E68: =D68/C68 -> #DIV/0! | F68: 0 | G68: =F68/C68 -> #DIV/0! | H68: 0 | I68: =H68/C68 -> #DIV/0! | J68: 0 | K68: 0 | L68: =K68/J68 -> #DIV/0! | M68: 0 | N68: =M68/J68 -> #DIV/0! | O68: 0 | P68: =O68/J68 -> #DIV/0! | Q68: 0 | R68: 0 | S68: =R68/Q68 -> #DIV/0! | T68: 0 | U68: =T68/Q68 -> #DIV/0! | V68: 0 | W68: =V68/Q68 -> #DIV/0!
A69: 2 | B69: LABOR & HUMAN RIGHTS (3) | C69: 66 | D69: 66 | E69: =D69/C69 -> 1 | F69: 66 | G69: =F69/C69 -> 1 | H69: 65 | I69: =H69/C69 -> 0.98484848 | J69: 66 | K69: 66 | L69: =K69/J69 -> 1 | M69: 66 | N69: =M69/J69 -> 1 | O69: 66 | P69: =O69/J69 -> 1 | Q69: 70 | R69: 70 | S69: =R69/Q69 -> 1 | T69: 70 | U69: =T69/Q69 -> 1 | V69: 70 | W69: =V69/Q69 -> 1
B70: a. HR | C70: 41 | D70: 41 | E70: =D70/C70 -> 1 | F70: 41 | G70: =F70/C70 -> 1 | H70: 41 | I70: =H70/C70 -> 1 | J70: 41 | K70: 41 | L70: =K70/J70 -> 1 | M70: 41 | N70: =M70/J70 -> 1 | O70: 41 | P70: =O70/J70 -> 1 | Q70: 44 | R70: 44 | S70: =R70/Q70 -> 1 | T70: 44 | U70: =T70/Q70 -> 1 | V70: 44 | W70: =V70/Q70 -> 1
B71: b. Expat | C71: 24 | D71: 24 | E71: =D71/C71 -> 1 | F71: 24 | G71: =F71/C71 -> 1 | H71: 23 | I71: =H71/C71 -> 0.95833333 | J71: 24 | K71: 24 | L71: =K71/J71 -> 1 | M71: 24 | N71: =M71/J71 -> 1 | O71: 24 | P71: =O71/J71 -> 1 | Q71: 25 | R71: 25 | S71: =R71/Q71 -> 1 | T71: 25 | U71: =T71/Q71 -> 1 | V71: 25 | W71: =V71/Q71 -> 1
B72: c. TRN | C72: 1 | D72: 1 | E72: =D72/C72 -> 1 | F72: 1 | G72: =F72/C72 -> 1 | H72: 1 | I72: =H72/C72 -> 1 | J72: 1 | K72: 1 | L72: =K72/J72 -> 1 | M72: 1 | N72: =M72/J72 -> 1 | O72: 1 | P72: =O72/J72 -> 1 | Q72: 1 | R72: 1 | S72: =R72/Q72 -> 1 | T72: 1 | U72: =T72/Q72 -> 1 | V72: 1 | W72: =V72/Q72 -> 1
A73: 3 | B73: INTELLECTUAL PROPERTY (4) | C73: 5 | D73: 5 | E73: =D73/C73 -> 1 | F73: 5 | G73: =F73/C73 -> 1 | H73: 5 | I73: =H73/C73 -> 1 | J73: 5 | K73: 5 | L73: =K73/J73 -> 1 | M73: 5 | N73: =M73/J73 -> 1 | O73: 5 | P73: =O73/J73 -> 1 | Q73: 5 | R73: 5 | S73: =R73/Q73 -> 1 | T73: 5 | U73: =T73/Q73 -> 1 | V73: 5 | W73: =V73/Q73 -> 1
A74: 4 | B74: FAIR TRADING (5) | C74: 3 | D74: 3 | E74: =D74/C74 -> 1 | F74: 3 | G74: =F74/C74 -> 1 | H74: 3 | I74: =H74/C74 -> 1 | J74: 3 | K74: 3 | L74: =K74/J74 -> 1 | M74: 3 | N74: =M74/J74 -> 1 | O74: 3 | P74: =O74/J74 -> 1 | Q74: 4 | R74: 4 | S74: =R74/Q74 -> 1 | T74: 4 | U74: =T74/Q74 -> 1 | V74: 4 | W74: =V74/Q74 -> 1
A75: 7 | B75: ENVIRONMENT, SAFETY & HEALTH (8) | C75: 107 | D75: 107 | E75: =D75/C75 -> 1 | F75: 107 | G75: =F75/C75 -> 1 | H75: 100 | I75: =H75/C75 -> 0.93457944 | J75: 107 | K75: 107 | L75: =K75/J75 -> 1 | M75: 107 | N75: =M75/J75 -> 1 | O75: 100 | P75: =O75/J75 -> 0.93457944 | Q75: 105 | R75: 105 | S75: =R75/Q75 -> 1 | T75: 105 | U75: =T75/Q75 -> 1 | V75: 98 | W75: =V75/Q75 -> 0.93333333
B76: a. Safety & Health | C76: 35 | D76: 35 | E76: =D76/C76 -> 1 | F76: 35 | G76: =F76/C76 -> 1 | H76: 30 | I76: =H76/C76 -> 0.85714286 | J76: 35 | K76: 35 | L76: =K76/J76 -> 1 | M76: 35 | N76: =M76/J76 -> 1 | O76: 30 | P76: =O76/J76 -> 0.85714286 | Q76: 35 | R76: 35 | S76: =R76/Q76 -> 1 | T76: 35 | U76: =T76/Q76 -> 1 | V76: 30 | W76: =V76/Q76 -> 0.85714286
B77: b. Environment | C77: 63 | D77: 63 | E77: =D77/C77 -> 1 | F77: 63 | G77: =F77/C77 -> 1 | H77: 61 | I77: =H77/C77 -> 0.96825397 | J77: 63 | K77: 63 | L77: =K77/J77 -> 1 | M77: 63 | N77: =M77/J77 -> 1 | O77: 61 | P77: =O77/J77 -> 0.96825397 | Q77: 61 | R77: 61 | S77: =R77/Q77 -> 1 | T77: 61 | U77: =T77/Q77 -> 1 | V77: 59 | W77: =V77/Q77 -> 0.96721311
B78: c. SoC | C78: 9 | D78: 9 | E78: =D78/C78 -> 1 | F78: 9 | G78: =F78/C78 -> 1 | H78: 9 | I78: =H78/C78 -> 1 | J78: 9 | K78: 9 | L78: =K78/J78 -> 1 | M78: 9 | N78: =M78/J78 -> 1 | O78: 9 | P78: =O78/J78 -> 1 | Q78: 9 | R78: 9 | S78: =R78/Q78 -> 1 | T78: 9 | U78: =T78/Q78 -> 1 | V78: 9 | W78: =V78/Q78 -> 1
A79: 6 | B79: COMPANY /BUSINESS OPERATIONS & LICENSE (2) | C79: 67 | D79: 67 | E79: =D79/C79 -> 1 | F79: 67 | G79: =F79/C79 -> 1 | H79: 58 | I79: =H79/C79 -> 0.86567164 | J79: 69 | K79: 69 | L79: =K79/J79 -> 1 | M79: 69 | N79: =M79/J79 -> 1 | O79: 60 | P79: =O79/J79 -> 0.86956522 | Q79: 77 | R79: 77 | S79: =R79/Q79 -> 1 | T79: 77 | U79: =T79/Q79 -> 1 | V79: 65 | W79: =V79/Q79 -> 0.84415584
B80: TOTAL | C80: =C68+C69+C73+C74+C75+C79 -> 248 | D80: =D68+D69+D73+D74+D75+D79 -> 248 | E80: =D80/C80 -> 1 | F80: =F68+F69+F73+F74+F75+F79 -> 248 | G80: =F80/C80 -> 1 | H80: =H68+H69+H73+H74+H75+H79 -> 231 | I80: =H80/C80 -> 0.93145161 | J80: =J68+J69+J73+J74+J75+J79 -> 250 | K80: =K68+K69+K73+K74+K75+K79 -> 250 | L80: =K80/J80 -> 1 | M80: =M68+M69+M73+M74+M75+M79 -> 250 | N80: =M80/J80 -> 1 | O80: =O68+O69+O73+O74+O75+O79 -> 234 | P80: =O80/J80 -> 0.936 | Q80: =Q68+Q69+Q73+Q74+Q75+Q79 -> 261 | R80: =R68+R69+R73+R74+R75+R79 -> 261 | S80: =R80/Q80 -> 1 | T80: =T68+T69+T73+T74+T75+T79 -> 261 | U80: =T80/Q80 -> 1 | V80: =V68+V69+V73+V74+V75+V79 -> 242 | W80: =V80/Q80 -> 0.92720307
A82: 5 | B82: EXIM MANAGEMENT (6) | C82: 13 | D82: 13 | E82: =D82/C82 -> 1 | F82: 13 | G82: =F82/C82 -> 1 | H82: 13 | I82: =H82/C82 -> 1 | J82: 13 | K82: 13 | L82: =K82/J82 -> 1 | M82: 13 | N82: =M82/J82 -> 1 | O82: 13 | P82: =O82/J82 -> 1 | Q82: 13 | R82: 13 | S82: =R82/Q82 -> 1 | T82: 13 | U82: =T82/Q82 -> 1 | V82: 13 | W82: =V82/Q82 -> 1
A83: 8 | B83: ACCOUNTING /FINANCE (7) | C83: 27 | D83: 27 | E83: =D83/C83 -> 1 | F83: 27 | G83: =F83/C83 -> 1 | H83: 27 | I83: =H83/C83 -> 1 | J83: 27 | K83: 27 | L83: =K83/J83 -> 1 | M83: 27 | N83: =M83/J83 -> 1 | O83: 27 | P83: =O83/J83 -> 1 | Q83: 29 | R83: 29 | S83: =R83/Q83 -> 1 | T83: 29 | U83: =T83/Q83 -> 1 | V83: 29 | W83: =V83/Q83 -> 1
B84: TOTAL | C84: =SUM(C82:C83)+C80 -> 288 | D84: =SUM(D82:D83)+D80 -> 288 | E84: =D84/C84 -> 1 | F84: =SUM(F82:F83)+F80 -> 288 | G84: =F84/C84 -> 1 | H84: =SUM(H82:H83)+H80 -> 271 | I84: =H84/C84 -> 0.94097222 | J84: =SUM(J82:J83)+J80 -> 290 | K84: =SUM(K82:K83)+K80 -> 290 | L84: =K84/J84 -> 1 | M84: =SUM(M82:M83)+M80 -> 290 | N84: =M84/J84 -> 1 | O84: =SUM(O82:O83)+O80 -> 274 | P84: =O84/J84 -> 0.94482759 | Q84: =SUM(Q82:Q83)+Q80 -> 303 | R84: =SUM(R82:R83)+R80 -> 303 | S84: =R84/Q84 -> 1 | T84: =SUM(T82:T83)+T80 -> 303 | U84: =T84/Q84 -> 1 | V84: =SUM(V82:V83)+V80 -> 284 | W84: =V84/Q84 -> 0.93729373
A87: NO | B87: BIDANG | C87: 44287 | J87: 44317 | Q87: 44348
C88: Jml regulasi | D88: Identifikasi | F88: Evaluasi | H88: Implementasi | J88: Jml regulasi | K88: Identifikasi | M88: Evaluasi | O88: Implementasi | Q88: Jml regulasi | R88: Identifikasi | T88: Evaluasi | V88: Implementasi
D89: Jml | E89: % | F89: Jml | G89: % | H89: Jml | I89: % | K89: Jml | L89: % | M89: Jml | N89: % | O89: Jml | P89: % | R89: Jml | S89: % | T89: Jml | U89: % | V89: Jml | W89: %
A90: 1 | B90: COMPLIANCE IN GENERAL (1) | C90: 0 | D90: 0 | E90: =D90/C90 -> #DIV/0! | F90: 0 | G90: =F90/C90 -> #DIV/0! | H90: 0 | I90: =H90/C90 -> #DIV/0! | J90: 0 | K90: 0 | L90: =K90/J90 -> #DIV/0! | M90: 0 | N90: =M90/J90 -> #DIV/0! | O90: 0 | P90: =O90/J90 -> #DIV/0! | Q90: 0 | R90: 0 | S90: =R90/Q90 -> #DIV/0! | T90: 0 | U90: =T90/Q90 -> #DIV/0! | V90: 0 | W90: =V90/Q90 -> #DIV/0!
A91: 2 | B91: LABOR & HUMAN RIGHTS (3) | C91: 76 | D91: 76 | E91: =D91/C91 -> 1 | F91: 76 | G91: =F91/C91 -> 1 | H91: 76 | I91: =H91/C91 -> 1 | J91: 77 | K91: 77 | L91: =K91/J91 -> 1 | M91: 77 | N91: =M91/J91 -> 1 | O91: 77 | P91: =O91/J91 -> 1 | Q91: 81 | R91: 81 | S91: =R91/Q91 -> 1 | T91: 81 | U91: =T91/Q91 -> 1 | V91: 81 | W91: =V91/Q91 -> 1
B92: a. HR | C92: 49 | D92: 49 | E92: =D92/C92 -> 1 | F92: 49 | G92: =F92/C92 -> 1 | H92: 49 | I92: =H92/C92 -> 1 | J92: 49 | K92: 49 | L92: =K92/J92 -> 1 | M92: 49 | N92: =M92/J92 -> 1 | O92: 49 | P92: =O92/J92 -> 1 | Q92: 53 | R92: 53 | S92: =R92/Q92 -> 1 | T92: 53 | U92: =T92/Q92 -> 1 | V92: 53 | W92: =V92/Q92 -> 1
B93: b. Expat | C93: 26 | D93: 26 | E93: =D93/C93 -> 1 | F93: 26 | G93: =F93/C93 -> 1 | H93: 26 | I93: =H93/C93 -> 1 | J93: 27 | K93: 27 | L93: =K93/J93 -> 1 | M93: 27 | N93: =M93/J93 -> 1 | O93: 27 | P93: =O93/J93 -> 1 | Q93: 27 | R93: 27 | S93: =R93/Q93 -> 1 | T93: 27 | U93: =T93/Q93 -> 1 | V93: 27 | W93: =V93/Q93 -> 1
B94: c. TRN | C94: 1 | D94: 1 | E94: =D94/C94 -> 1 | F94: 1 | G94: =F94/C94 -> 1 | H94: 1 | I94: =H94/C94 -> 1 | J94: 1 | K94: 1 | L94: =K94/J94 -> 1 | M94: 1 | N94: =M94/J94 -> 1 | O94: 1 | P94: =O94/J94 -> 1 | Q94: 1 | R94: 1 | S94: =R94/Q94 -> 1 | T94: 1 | U94: =T94/Q94 -> 1 | V94: 1 | W94: =V94/Q94 -> 1
A95: 3 | B95: INTELLECTUAL PROPERTY (4) | C95: 5 | D95: 5 | E95: =D95/C95 -> 1 | F95: 5 | G95: =F95/C95 -> 1 | H95: 5 | I95: =H95/C95 -> 1 | J95: 5 | K95: 5 | L95: =K95/J95 -> 1 | M95: 5 | N95: =M95/J95 -> 1 | O95: 5 | P95: =O95/J95 -> 1 | Q95: 5 | R95: 5 | S95: =R95/Q95 -> 1 | T95: 5 | U95: =T95/Q95 -> 1 | V95: 5 | W95: =V95/Q95 -> 1
A96: 4 | B96: FAIR TRADING (5) | C96: 4 | D96: 4 | E96: =D96/C96 -> 1 | F96: 4 | G96: =F96/C96 -> 1 | H96: 4 | I96: =H96/C96 -> 1 | J96: 4 | K96: 4 | L96: =K96/J96 -> 1 | M96: 4 | N96: =M96/J96 -> 1 | O96: 4 | P96: =O96/J96 -> 1 | Q96: 4 | R96: 4 | S96: =R96/Q96 -> 1 | T96: 4 | U96: =T96/Q96 -> 1 | V96: 4 | W96: =V96/Q96 -> 1
A97: 7 | B97: ENVIRONMENT, SAFETY & HEALTH (8) | C97: 105 | D97: 105 | E97: =D97/C97 -> 1 | F97: 105 | G97: =F97/C97 -> 1 | H97: 98 | I97: =H97/C97 -> 0.93333333 | J97: 105 | K97: 105 | L97: =K97/J97 -> 1 | M97: 105 | N97: =M97/J97 -> 1 | O97: 98 | P97: =O97/J97 -> 0.93333333 | Q97: 102 | R97: 102 | S97: =R97/Q97 -> 1 | T97: 102 | U97: =T97/Q97 -> 1 | V97: 98 | W97: =V97/Q97 -> 0.96078431
B98: a. Safety & Health | C98: 35 | D98: 35 | E98: =D98/C98 -> 1 | F98: 35 | G98: =F98/C98 -> 1 | H98: 30 | I98: =H98/C98 -> 0.85714286 | J98: 35 | K98: 35 | L98: =K98/J98 -> 1 | M98: 35 | N98: =M98/J98 -> 1 | O98: 30 | P98: =O98/J98 -> 0.85714286 | Q98: 35 | R98: 35 | S98: =R98/Q98 -> 1 | T98: 35 | U98: =T98/Q98 -> 1 | V98: 32 | W98: =V98/Q98 -> 0.91428571
B99: b. Environment | C99: 61 | D99: 61 | E99: =D99/C99 -> 1 | F99: 61 | G99: =F99/C99 -> 1 | H99: 59 | I99: =H99/C99 -> 0.96721311 | J99: 61 | K99: 61 | L99: =K99/J99 -> 1 | M99: 61 | N99: =M99/J99 -> 1 | O99: 59 | P99: =O99/J99 -> 0.96721311 | Q99: 58 | R99: 58 | S99: =R99/Q99 -> 1 | T99: 58 | U99: =T99/Q99 -> 1 | V99: 57 | W99: =V99/Q99 -> 0.98275862
B100: c. SoC | C100: 9 | D100: 9 | E100: =D100/C100 -> 1 | F100: 9 | G100: =F100/C100 -> 1 | H100: 9 | I100: =H100/C100 -> 1 | J100: 9 | K100: 9 | L100: =K100/J100 -> 1 | M100: 9 | N100: =M100/J100 -> 1 | O100: 9 | P100: =O100/J100 -> 1 | Q100: 9 | R100: 9 | S100: =R100/Q100 -> 1 | T100: 9 | U100: =T100/Q100 -> 1 | V100: 9 | W100: =V100/Q100 -> 1
A101: 6 | B101: COMPANY /BUSINESS OPERATIONS & LICENSE (2) | C101: 80 | D101: 80 | E101: =D101/C101 -> 1 | F101: 80 | G101: =F101/C101 -> 1 | H101: 68 | I101: =H101/C101 -> 0.85 | J101: 80 | K101: 80 | L101: =K101/J101 -> 1 | M101: 80 | N101: =M101/J101 -> 1 | O101: 68 | P101: =O101/J101 -> 0.85 | Q101: 78 | R101: 78 | S101: =R101/Q101 -> 1 | T101: 78 | U101: =T101/Q101 -> 1 | V101: 69 | W101: =V101/Q101 -> 0.88461538
B102: TOTAL | C102: =C90+C91+C95+C96+C97+C101 -> 270 | D102: =D90+D91+D95+D96+D97+D101 -> 270 | E102: =D102/C102 -> 1 | F102: =F90+F91+F95+F96+F97+F101 -> 270 | G102: =F102/C102 -> 1 | H102: =H90+H91+H95+H96+H97+H101 -> 251 | I102: =H102/C102 -> 0.92962963 | J102: =J90+J91+J95+J96+J97+J101 -> 271 | K102: =K90+K91+K95+K96+K97+K101 -> 271 | L102: =K102/J102 -> 1 | M102: =M90+M91+M95+M96+M97+M101 -> 271 | N102: =M102/J102 -> 1 | O102: =O90+O91+O95+O96+O97+O101 -> 252 | P102: =O102/J102 -> 0.9298893 | Q102: =Q90+Q91+Q95+Q96+Q97+Q101 -> 270 | R102: =R90+R91+R95+R96+R97+R101 -> 270 | S102: =R102/Q102 -> 1 | T102: =T90+T91+T95+T96+T97+T101 -> 270 | U102: =T102/Q102 -> 1 | V102: =V90+V91+V95+V96+V97+V101 -> 257 | W102: =V102/Q102 -> 0.95185185
A104: 5 | B104: EXIM MANAGEMENT (6) | C104: 13 | D104: 13 | E104: =D104/C104 -> 1 | F104: 13 | G104: =F104/C104 -> 1 | H104: 13 | I104: =H104/C104 -> 1 | J104: 13 | K104: 13 | L104: =K104/J104 -> 1 | M104: 13 | N104: =M104/J104 -> 1 | O104: 13 | P104: =O104/J104 -> 1 | Q104: 14 | R104: 14 | S104: =R104/Q104 -> 1 | T104: 14 | U104: =T104/Q104 -> 1 | V104: 14 | W104: =V104/Q104 -> 1
A105: 8 | B105: ACCOUNTING /FINANCE (7) | C105: 31 | D105: 31 | E105: =D105/C105 -> 1 | F105: 31 | G105: =F105/C105 -> 1 | H105: 31 | I105: =H105/C105 -> 1 | J105: 31 | K105: 31 | L105: =K105/J105 -> 1 | M105: 31 | N105: =M105/J105 -> 1 | O105: 31 | P105: =O105/J105 -> 1 | Q105: 32 | R105: 32 | S105: =R105/Q105 -> 1 | T105: 32 | U105: =T105/Q105 -> 1 | V105: 32 | W105: =V105/Q105 -> 1
B106: TOTAL | C106: =SUM(C104:C105)+C102 -> 314 | D106: =SUM(D104:D105)+D102 -> 314 | E106: =D106/C106 -> 1 | F106: =SUM(F104:F105)+F102 -> 314 | G106: =F106/C106 -> 1 | H106: =SUM(H104:H105)+H102 -> 295 | I106: =H106/C106 -> 0.93949045 | J106: =SUM(J104:J105)+J102 -> 315 | K106: =SUM(K104:K105)+K102 -> 315 | L106: =K106/J106 -> 1 | M106: =SUM(M104:M105)+M102 -> 315 | N106: =M106/J106 -> 1 | O106: =SUM(O104:O105)+O102 -> 296 | P106: =O106/J106 -> 0.93968254 | Q106: =SUM(Q104:Q105)+Q102 -> 316 | R106: =SUM(R104:R105)+R102 -> 316 | S106: =R106/Q106 -> 1 | T106: =SUM(T104:T105)+T102 -> 316 | U106: =T106/Q106 -> 1 | V106: =SUM(V104:V105)+V102 -> 303 | W106: =V106/Q106 -> 0.95886076

Sheet 81
A2: Now day
A4: NO | B4: BIDANG | C4: NOW DAY
C5: Jml regulasi | D5: Identifikasi | F5: Evaluasi | H5: Implementasi
D6: Jml | E6: % | F6: Jml | G6: % | H6: Jml | I6: %
A7: 1 | B7: COMPLIANCE IN GENERAL (1) | C7: ='Detail COMPLIANCE FIELD'!G15 -> 0 | D7: =C7 -> 0 | E7: 1 | F7: ='Detail COMPLIANCE FIELD'!I15 -> 0 | G7: 1 | H7: ='Detail COMPLIANCE FIELD'!K15 -> 0 | I7: 1
A8: 2 | B8: LABOR & HUMAN RIGHTS (3) | C8: ='Detail COMPLIANCE FIELD'!G16 -> 99 | D8: =C8 -> 99 | E8: =D8/C8 -> 1 | F8: ='Detail COMPLIANCE FIELD'!I16 -> 99 | G8: =F8/C8 -> 1 | H8: ='Detail COMPLIANCE FIELD'!K16 -> 98 | I8: =H8/C8 -> 0.98989899
A9: 3 | B9: INTELLECTUAL PROPERTY (4) | C9: ='Detail COMPLIANCE FIELD'!G17 -> 126 | D9: =C9 -> 126 | E9: =D9/C9 -> 1 | F9: ='Detail COMPLIANCE FIELD'!I17 -> 126 | G9: =F9/C9 -> 1 | H9: ='Detail COMPLIANCE FIELD'!K17 -> 122 | I9: =H9/C9 -> 0.96825397
A10: 4 | B10: FAIR TRADING (5) | C10: ='Detail COMPLIANCE FIELD'!G18 -> 7 | D10: =C10 -> 7 | E10: =D10/C10 -> 1 | F10: ='Detail COMPLIANCE FIELD'!I18 -> 7 | G10: =F10/C10 -> 1 | H10: ='Detail COMPLIANCE FIELD'!K18 -> 7 | I10: =H10/C10 -> 1
A11: 5 | B11: ENVIRONMENT, SAFETY & HEALTH (8) | C11: ='Detail COMPLIANCE FIELD'!G19 -> 6 | D11: =C11 -> 6 | E11: =D11/C11 -> 1 | F11: ='Detail COMPLIANCE FIELD'!I19 -> 6 | G11: =F11/C11 -> 1 | H11: ='Detail COMPLIANCE FIELD'!K19 -> 6 | I11: =H11/C11 -> 1
A12: 6 | B12: COMPANY /BUSINESS OPERATIONS & LICENSE (2) | C12: ='Detail COMPLIANCE FIELD'!G20 -> 37 | D12: =C12 -> 37 | E12: =D12/C12 -> 1 | F12: ='Detail COMPLIANCE FIELD'!I20 -> 37 | G12: =F12/C12 -> 1 | H12: ='Detail COMPLIANCE FIELD'!K20 -> 37 | I12: =H12/C12 -> 1
B13: TOTAL | C13: =SUM(C7:C12) -> 275 | D13: =SUM(D7:D12) -> 275 | E13: =D13/C13 -> 1 | F13: =SUM(F7:F12) -> 275 | G13: =F13/C13 -> 1 | H13: =SUM(H7:H12) -> 270 | I13: =H13/C13 -> 0.98181818
A15: 7 | B15: EXIM MANAGEMENT (6) | C15: ='Detail COMPLIANCE FIELD'!G21 -> 56 | D15: =C15 -> 56 | E15: =D15/C15 -> 1 | F15: ='Detail COMPLIANCE FIELD'!I21 -> 56 | G15: =F15/C15 -> 1 | H15: ='Detail COMPLIANCE FIELD'!K21 -> 56 | I15: =H15/C15 -> 1
A16: 8 | B16: ACCOUNTING /FINANCE (7) | C16: ='Detail COMPLIANCE FIELD'!G22 -> 123 | D16: =C16 -> 123 | E16: =D16/C16 -> 1 | F16: ='Detail COMPLIANCE FIELD'!I22 -> 123 | G16: =F16/C16 -> 1 | H16: ='Detail COMPLIANCE FIELD'!K22 -> 116 | I16: =H16/C16 -> 0.94308943
B17: TOTAL | C17: =SUM(C15:C16)+C13 -> 454 | D17: =SUM(D15:D16)+D13 -> 454 | E17: =D17/C17 -> 1 | F17: =SUM(F15:F16)+F13 -> 454 | G17: =F17/C17 -> 1 | H17: =SUM(H15:H16)+H13 -> 442 | I17: =H17/C17 -> 0.97356828
A18: PT. SEMARANG AUTOCOMP MANUFACTURING INDONESIA
A19: KEPATUHAN TERHADAP PERATURAN PERUNDANGAN
A21: NO | B21: BIDANG | C21: 44378 | J21: 44409 | Q21: 44440
C22: Jml regulasi | D22: Identifikasi | F22: Evaluasi | H22: Implementasi | J22: Jml regulasi | K22: Identifikasi | M22: Evaluasi | O22: Implementasi | Q22: Jml regulasi | R22: Identifikasi | T22: Evaluasi | V22: Implementasi
D23: Jml | E23: % | F23: Jml | G23: % | H23: Jml | I23: % | K23: Jml | L23: % | M23: Jml | N23: % | O23: Jml | P23: % | R23: Jml | S23: % | T23: Jml | U23: % | V23: Jml | W23: %
A24: 1 | B24: COMPLIANCE IN GENERAL (1) | C24: 0 | D24: 0 | E24: =D24/C24 -> #DIV/0! | F24: 0 | G24: =F24/C24 -> #DIV/0! | H24: 0 | I24: =H24/C24 -> #DIV/0! | J24: 0 | K24: 0 | L24: =K24/J24 -> #DIV/0! | M24: 0 | N24: =M24/J24 -> #DIV/0! | O24: 0 | P24: =O24/J24 -> #DIV/0! | Q24: 0 | R24: 0 | S24: =R24/Q24 -> #DIV/0! | T24: 0 | U24: =T24/Q24 -> #DIV/0! | V24: 0 | W24: =V24/Q24 -> #DIV/0!
A25: 2 | B25: LABOR & HUMAN RIGHTS (3) | C25: 81 | D25: 81 | E25: =D25/C25 -> 1 | F25: 81 | G25: =F25/C25 -> 1 | H25: 81 | I25: =H25/C25 -> 1 | J25: 82 | K25: 82 | L25: =K25/J25 -> 1 | M25: 82 | N25: =M25/J25 -> 1 | O25: 82 | P25: =O25/J25 -> 1 | Q25: 82 | R25: 82 | S25: =R25/Q25 -> 1 | T25: 82 | U25: =T25/Q25 -> 1 | V25: 82 | W25: =V25/Q25 -> 1
B26: a. HR | C26: 53 | D26: 53 | E26: =D26/C26 -> 1 | F26: 53 | G26: =F26/C26 -> 1 | H26: 53 | I26: =H26/C26 -> 1 | J26: 54 | K26: 54 | L26: =K26/J26 -> 1 | M26: 54 | N26: =M26/J26 -> 1 | O26: 54 | P26: =O26/J26 -> 1 | Q26: 54 | R26: 54 | S26: =R26/Q26 -> 1 | T26: 54 | U26: =T26/Q26 -> 1 | V26: 54 | W26: =V26/Q26 -> 1
B27: b. Expat | C27: 27 | D27: 27 | E27: =D27/C27 -> 1 | F27: 27 | G27: =F27/C27 -> 1 | H27: 27 | I27: =H27/C27 -> 1 | J27: 27 | K27: 27 | L27: =K27/J27 -> 1 | M27: 27 | N27: =M27/J27 -> 1 | O27: 27 | P27: =O27/J27 -> 1 | Q27: 27 | R27: 27 | S27: =R27/Q27 -> 1 | T27: 27 | U27: =T27/Q27 -> 1 | V27: 27 | W27: =V27/Q27 -> 1
B28: c. TRN | C28: 1 | D28: 1 | E28: =D28/C28 -> 1 | F28: 1 | G28: =F28/C28 -> 1 | H28: 1 | I28: =H28/C28 -> 1 | J28: 1 | K28: 1 | L28: =K28/J28 -> 1 | M28: 1 | N28: =M28/J28 -> 1 | O28: 1 | P28: =O28/J28 -> 1 | Q28: 1 | R28: 1 | S28: =R28/Q28 -> 1 | T28: 1 | U28: =T28/Q28 -> 1 | V28: 1 | W28: =V28/Q28 -> 1
A29: 3 | B29: INTELLECTUAL PROPERTY (4) | C29: 5 | D29: 5 | E29: =D29/C29 -> 1 | F29: 5 | G29: =F29/C29 -> 1 | H29: 5 | I29: =H29/C29 -> 1 | J29: 5 | K29: 5 | L29: =K29/J29 -> 1 | M29: 5 | N29: =M29/J29 -> 1 | O29: 5 | P29: =O29/J29 -> 1 | Q29: 5 | R29: 5 | S29: =R29/Q29 -> 1 | T29: 5 | U29: =T29/Q29 -> 1 | V29: 5 | W29: =V29/Q29 -> 1
A30: 4 | B30: FAIR TRADING (5) | C30: 5 | D30: 5 | E30: =D30/C30 -> 1 | F30: 5 | G30: =F30/C30 -> 1 | H30: 5 | I30: =H30/C30 -> 1 | J30: 5 | K30: 5 | L30: =K30/J30 -> 1 | M30: 5 | N30: =M30/J30 -> 1 | O30: 5 | P30: =O30/J30 -> 1 | Q30: 5 | R30: 5 | S30: =R30/Q30 -> 1 | T30: 5 | U30: =T30/Q30 -> 1 | V30: 5 | W30: =V30/Q30 -> 1
A31: 6 | B31: ENVIRONMENT, SAFETY & HEALTH (8) | C31: 104 | D31: 104 | E31: =D31/C31 -> 1 | F31: 104 | G31: =F31/C31 -> 1 | H31: 99 | I31: =H31/C31 -> 0.95192308 | J31: 104 | K31: 104 | L31: =K31/J31 -> 1 | M31: 104 | N31: =M31/J31 -> 1 | O31: 100 | P31: =O31/J31 -> 0.96153846 | Q31: 104 | R31: 104 | S31: =R31/Q31 -> 1 | T31: 104 | U31: =T31/Q31 -> 1 | V31: 98 | W31: =V31/Q31 -> 0.94230769
B32: a. Safety & Health | C32: 35 | D32: 35 | E32: =D32/C32 -> 1 | F32: 35 | G32: =F32/C32 -> 1 | H32: 32 | I32: =H32/C32 -> 0.91428571 | J32: 35 | K32: 35 | L32: =K32/J32 -> 1 | M32: 35 | N32: =M32/J32 -> 1 | O32: 32 | P32: =O32/J32 -> 0.91428571 | Q32: 35 | R32: 35 | S32: =R32/Q32 -> 1 | T32: 35 | U32: =T32/Q32 -> 1 | V32: 30 | W32: =V32/Q32 -> 0.85714286
B33: b. Environment | C33: 60 | D33: 60 | E33: =D33/C33 -> 1 | F33: 60 | G33: =F33/C33 -> 1 | H33: 58 | I33: =H33/C33 -> 0.96666667 | J33: 60 | K33: 60 | L33: =K33/J33 -> 1 | M33: 60 | N33: =M33/J33 -> 1 | O33: 59 | P33: =O33/J33 -> 0.98333333 | Q33: 60 | R33: 60 | S33: =R33/Q33 -> 1 | T33: 60 | U33: =T33/Q33 -> 1 | V33: 59 | W33: =V33/Q33 -> 0.98333333
B34: c. SoC | C34: 9 | D34: 9 | E34: =D34/C34 -> 1 | F34: 9 | G34: =F34/C34 -> 1 | H34: 9 | I34: =H34/C34 -> 1 | J34: 9 | K34: 9 | L34: =K34/J34 -> 1 | M34: 9 | N34: =M34/J34 -> 1 | O34: 9 | P34: =O34/J34 -> 1 | Q34: 9 | R34: 9 | S34: =R34/Q34 -> 1 | T34: 9 | U34: =T34/Q34 -> 1 | V34: 9 | W34: =V34/Q34 -> 1
A35: 7 | B35: COMPANY /BUSINESS OPERATIONS & LICENSE (2) | C35: 79 | D35: 79 | E35: =D35/C35 -> 1 | F35: 79 | G35: =F35/C35 -> 1 | H35: 70 | I35: =H35/C35 -> 0.88607595 | J35: 81 | K35: 81 | L35: =K35/J35 -> 1 | M35: 81 | N35: =M35/J35 -> 1 | O35: 72 | P35: =O35/J35 -> 0.88888889 | Q35: 81 | R35: 81 | S35: =R35/Q35 -> 1 | T35: 81 | U35: =T35/Q35 -> 1 | V35: 72 | W35: =V35/Q35 -> 0.88888889
B36: TOTAL | C36: =C24+C25+C29+C30+C31+C35 -> 274 | D36: =D24+D25+D29+D30+D31+D35 -> 274 | E36: =D36/C36 -> 1 | F36: =F24+F25+F29+F30+F31+F35 -> 274 | G36: =F36/C36 -> 1 | H36: =H24+H25+H29+H30+H31+H35 -> 260 | I36: =H36/C36 -> 0.94890511 | J36: =J24+J25+J29+J30+J31+J35 -> 277 | K36: =K24+K25+K29+K30+K31+K35 -> 277 | L36: =K36/J36 -> 1 | M36: =M24+M25+M29+M30+M31+M35 -> 277 | N36: =M36/J36 -> 1 | O36: =O24+O25+O29+O30+O31+O35 -> 264 | P36: =O36/J36 -> 0.95306859 | Q36: =Q24+Q25+Q29+Q30+Q31+Q35 -> 277 | R36: =R24+R25+R29+R30+R31+R35 -> 277 | S36: =R36/Q36 -> 1 | T36: =T24+T25+T29+T30+T31+T35 -> 277 | U36: =T36/Q36 -> 1 | V36: =V24+V25+V29+V30+V31+V35 -> 262 | W36: =V36/Q36 -> 0.94584838
A38: 5 | B38: EXIM MANAGEMENT (6) | C38: 15 | D38: 15 | E38: =D38/C38 -> 1 | F38: 15 | G38: =F38/C38 -> 1 | H38: 15 | I38: =H38/C38 -> 1 | J38: 16 | K38: 16 | L38: =K38/J38 -> 1 | M38: 16 | N38: =M38/J38 -> 1 | O38: 16 | P38: =O38/J38 -> 1 | Q38: 16 | R38: 16 | S38: =R38/Q38 -> 1 | T38: 16 | U38: =T38/Q38 -> 1 | V38: 16 | W38: =V38/Q38 -> 1
A39: 8 | B39: ACCOUNTING /FINANCE (7) | C39: 33 | D39: 33 | E39: =D39/C39 -> 1 | F39: 33 | G39: =F39/C39 -> 1 | H39: 33 | I39: =H39/C39 -> 1 | J39: 33 | K39: 33 | L39: =K39/J39 -> 1 | M39: 33 | N39: =M39/J39 -> 1 | O39: 33 | P39: =O39/J39 -> 1 | Q39: 33 | R39: 33 | S39: =R39/Q39 -> 1 | T39: 33 | U39: =T39/Q39 -> 1 | V39: 33 | W39: =V39/Q39 -> 1
B40: TOTAL | C40: =SUM(C38:C39)+C36 -> 322 | D40: =SUM(D38:D39)+D36 -> 322 | E40: =D40/C40 -> 1 | F40: =SUM(F38:F39)+F36 -> 322 | G40: =F40/C40 -> 1 | H40: =SUM(H38:H39)+H36 -> 308 | I40: =H40/C40 -> 0.95652174 | J40: =SUM(J38:J39)+J36 -> 326 | K40: =SUM(K38:K39)+K36 -> 326 | L40: =K40/J40 -> 1 | M40: =SUM(M38:M39)+M36 -> 326 | N40: =M40/J40 -> 1 | O40: =SUM(O38:O39)+O36 -> 313 | P40: =O40/J40 -> 0.9601227 | Q40: =SUM(Q38:Q39)+Q36 -> 326 | R40: =SUM(R38:R39)+R36 -> 326 | S40: =R40/Q40 -> 1 | T40: =SUM(T38:T39)+T36 -> 326 | U40: =T40/Q40 -> 1 | V40: =SUM(V38:V39)+V36 -> 311 | W40: =V40/Q40 -> 0.95398773
A43: NO | B43: BIDANG | C43: 44470 | J43: 44501 | Q43: 44531
C44: Jml regulasi | D44: Identifikasi | F44: Evaluasi | H44: Implementasi | J44: Jml regulasi | K44: Identifikasi | M44: Evaluasi | O44: Implementasi | Q44: Jml regulasi | R44: Identifikasi | T44: Evaluasi | V44: Implementasi
D45: Jml | E45: % | F45: Jml | G45: % | H45: Jml | I45: % | K45: Jml | L45: % | M45: Jml | N45: % | O45: Jml | P45: % | R45: Jml | S45: % | T45: Jml | U45: % | V45: Jml | W45: %
A46: 1 | B46: COMPLIANCE IN GENERAL (1) | C46: 0 | D46: 0 | E46: =D46/C46 -> #DIV/0! | F46: 0 | G46: =F46/C46 -> #DIV/0! | H46: 0 | I46: =H46/C46 -> #DIV/0! | L46: =K46/J46 -> #DIV/0! | N46: =M46/J46 -> #DIV/0! | P46: =O46/J46 -> #DIV/0! | Q46: 0 | R46: 0 | S46: =R46/Q46 -> #DIV/0! | T46: 0 | U46: =T46/Q46 -> #DIV/0! | V46: 0 | W46: =V46/Q46 -> #DIV/0!
A47: 2 | B47: LABOR & HUMAN RIGHTS (3) | C47: 87 | D47: 87 | E47: =D47/C47 -> 1 | F47: 87 | G47: =F47/C47 -> 1 | H47: 87 | I47: =H47/C47 -> 1 | L47: =K47/J47 -> #DIV/0! | N47: =M47/J47 -> #DIV/0! | P47: =O47/J47 -> #DIV/0! | Q47: 90 | R47: 90 | S47: =R47/Q47 -> 1 | T47: 87 | U47: =T47/Q47 -> 0.96666667 | V47: 87 | W47: =V47/Q47 -> 0.96666667
B48: a. HR | C48: 55 | D48: 55 | E48: =D48/C48 -> 1 | F48: 55 | G48: =F48/C48 -> 1 | H48: 55 | I48: =H48/C48 -> 1 | L48: =K48/J48 -> #DIV/0! | N48: =M48/J48 -> #DIV/0! | P48: =O48/J48 -> #DIV/0! | Q48: 58 | R48: 58 | S48: =R48/Q48 -> 1 | T48: 55 | U48: =T48/Q48 -> 0.94827586 | V48: 55 | W48: =V48/Q48 -> 0.94827586
B49: b. Expat | C49: 31 | D49: 31 | E49: =D49/C49 -> 1 | F49: 31 | G49: =F49/C49 -> 1 | H49: 31 | I49: =H49/C49 -> 1 | L49: =K49/J49 -> #DIV/0! | N49: =M49/J49 -> #DIV/0! | P49: =O49/J49 -> #DIV/0! | Q49: 31 | R49: 31 | S49: =R49/Q49 -> 1 | T49: 31 | U49: =T49/Q49 -> 1 | V49: 31 | W49: =V49/Q49 -> 1
B50: c. TRN | C50: 1 | D50: 1 | E50: =D50/C50 -> 1 | F50: 1 | G50: =F50/C50 -> 1 | H50: 1 | I50: =H50/C50 -> 1 | L50: =K50/J50 -> #DIV/0! | N50: =M50/J50 -> #DIV/0! | P50: =O50/J50 -> #DIV/0! | Q50: 1 | R50: 1 | S50: =R50/Q50 -> 1 | T50: 1 | U50: =T50/Q50 -> 1 | V50: 1 | W50: =V50/Q50 -> 1
A51: 3 | B51: INTELLECTUAL PROPERTY (4) | C51: 5 | D51: 5 | E51: =D51/C51 -> 1 | F51: 5 | G51: =F51/C51 -> 1 | H51: 5 | I51: =H51/C51 -> 1 | L51: =K51/J51 -> #DIV/0! | N51: =M51/J51 -> #DIV/0! | P51: =O51/J51 -> #DIV/0! | Q51: 5 | R51: 5 | S51: =R51/Q51 -> 1 | T51: 5 | U51: =T51/Q51 -> 1 | V51: 5 | W51: =V51/Q51 -> 1
A52: 7 | B52: FAIR TRADING (5) | C52: 5 | D52: 5 | E52: =D52/C52 -> 1 | F52: 5 | G52: =F52/C52 -> 1 | H52: 5 | I52: =H52/C52 -> 1 | L52: =K52/J52 -> #DIV/0! | N52: =M52/J52 -> #DIV/0! | P52: =O52/J52 -> #DIV/0! | Q52: 5 | R52: 5 | S52: =R52/Q52 -> 1 | T52: 5 | U52: =T52/Q52 -> 1 | V52: 5 | W52: =V52/Q52 -> 1
A53: 4 | B53: ENVIRONMENT, SAFETY & HEALTH (8) | C53: 104 | D53: 104 | E53: =D53/C53 -> 1 | F53: 104 | G53: =F53/C53 -> 1 | H53: 98 | I53: =H53/C53 -> 0.94230769 | L53: =K53/J53 -> #DIV/0! | N53: =M53/J53 -> #DIV/0! | P53: =O53/J53 -> #DIV/0! | Q53: 106 | R53: 106 | S53: =R53/Q53 -> 1 | T53: 106 | U53: =T53/Q53 -> 1 | V53: 101 | W53: =V53/Q53 -> 0.95283019
B54: a. Safety & Health | C54: 35 | D54: 35 | E54: =D54/C54 -> 1 | F54: 35 | G54: =F54/C54 -> 1 | H54: 30 | I54: =H54/C54 -> 0.85714286 | L54: =K54/J54 -> #DIV/0! | N54: =M54/J54 -> #DIV/0! | P54: =O54/J54 -> #DIV/0! | Q54: 37 | R54: 37 | S54: =R54/Q54 -> 1 | T54: 37 | U54: =T54/Q54 -> 1 | V54: 33 | W54: =V54/Q54 -> 0.89189189
B55: b. Environment | C55: 60 | D55: 60 | E55: =D55/C55 -> 1 | F55: 60 | G55: =F55/C55 -> 1 | H55: 59 | I55: =H55/C55 -> 0.98333333 | L55: =K55/J55 -> #DIV/0! | N55: =M55/J55 -> #DIV/0! | P55: =O55/J55 -> #DIV/0! | Q55: 59 | R55: 59 | S55: =R55/Q55 -> 1 | T55: 59 | U55: =T55/Q55 -> 1 | V55: 58 | W55: =V55/Q55 -> 0.98305085
B56: c. SoC | C56: 9 | D56: 9 | E56: =D56/C56 -> 1 | F56: 9 | G56: =F56/C56 -> 1 | H56: 9 | I56: =H56/C56 -> 1 | L56: =K56/J56 -> #DIV/0! | N56: =M56/J56 -> #DIV/0! | P56: =O56/J56 -> #DIV/0! | Q56: 10 | R56: 10 | S56: =R56/Q56 -> 1 | T56: 10 | U56: =T56/Q56 -> 1 | V56: 10 | W56: =V56/Q56 -> 1
A57: 6 | B57: COMPANY /BUSINESS OPERATIONS & LICENSE (2) | C57: 81 | D57: 81 | E57: =D57/C57 -> 1 | F57: 81 | G57: =F57/C57 -> 1 | H57: 72 | I57: =H57/C57 -> 0.88888889 | L57: =K57/J57 -> #DIV/0! | N57: =M57/J57 -> #DIV/0! | P57: =O57/J57 -> #DIV/0! | Q57: 83 | R57: 83 | S57: =R57/Q57 -> 1 | T57: 81 | U57: =T57/Q57 -> 0.97590361 | V57: 72 | W57: =V57/Q57 -> 0.86746988
B58: TOTAL | C58: =C46+C47+C51+C52+C53+C57 -> 282 | D58: =D46+D47+D51+D52+D53+D57 -> 282 | E58: =D58/C58 -> 1 | F58: =F46+F47+F51+F52+F53+F57 -> 282 | G58: =F58/C58 -> 1 | H58: =H46+H47+H51+H52+H53+H57 -> 267 | I58: =H58/C58 -> 0.94680851 | J58: =J46+J47+J51+J52+J53+J57 -> 0 | K58: =K46+K47+K51+K52+K53+K57 -> 0 | L58: =K58/J58 -> #DIV/0! | M58: =M46+M47+M51+M52+M53+M57 -> 0 | N58: =M58/J58 -> #DIV/0! | O58: =O46+O47+O51+O52+O53+O57 -> 0 | P58: =O58/J58 -> #DIV/0! | Q58: =Q46+Q47+Q51+Q52+Q53+Q57 -> 289 | R58: =R46+R47+R51+R52+R53+R57 -> 289 | S58: =R58/Q58 -> 1 | T58: =T46+T47+T51+T52+T53+T57 -> 284 | U58: =T58/Q58 -> 0.98269896 | V58: =V46+V47+V51+V52+V53+V57 -> 270 | W58: =V58/Q58 -> 0.93425606
A60: 5 | B60: EXIM MANAGEMENT (6) | C60: 16 | D60: 16 | E60: =D60/C60 -> 1 | F60: 16 | G60: =F60/C60 -> 1 | H60: 16 | I60: =H60/C60 -> 1 | L60: =K60/J60 -> #DIV/0! | N60: =M60/J60 -> #DIV/0! | P60: =O60/J60 -> #DIV/0! | Q60: 18 | R60: 18 | S60: =R60/Q60 -> 1 | T60: 16 | U60: =T60/Q60 -> 0.88888889 | V60: 16 | W60: =V60/Q60 -> 0.88888889
A61: 8 | B61: ACCOUNTING /FINANCE (7) | C61: 33 | D61: 33 | E61: =D61/C61 -> 1 | F61: 33 | G61: =F61/C61 -> 1 | H61: 33 | I61: =H61/C61 -> 1 | L61: =K61/J61 -> #DIV/0! | N61: =M61/J61 -> #DIV/0! | P61: =O61/J61 -> #DIV/0! | Q61: 35 | R61: 35 | S61: =R61/Q61 -> 1 | T61: 34 | U61: =T61/Q61 -> 0.97142857 | V61: 34 | W61: =V61/Q61 -> 0.97142857
B62: TOTAL | C62: =SUM(C60:C61)+C58 -> 331 | D62: =SUM(D60:D61)+D58 -> 331 | E62: =D62/C62 -> 1 | F62: =SUM(F60:F61)+F58 -> 331 | G62: =F62/C62 -> 1 | H62: =SUM(H60:H61)+H58 -> 316 | I62: =H62/C62 -> 0.95468278 | J62: =SUM(J60:J61)+J58 -> 0 | K62: =SUM(K60:K61)+K58 -> 0 | L62: =K62/J62 -> #DIV/0! | M62: =SUM(M60:M61)+M58 -> 0 | N62: =M62/J62 -> #DIV/0! | O62: =SUM(O60:O61)+O58 -> 0 | P62: =O62/J62 -> #DIV/0! | Q62: =SUM(Q60:Q61)+Q58 -> 342 | R62: =SUM(R60:R61)+R58 -> 342 | S62: =R62/Q62 -> 1 | T62: =SUM(T60:T61)+T58 -> 334 | U62: =T62/Q62 -> 0.97660819 | V62: =SUM(V60:V61)+V58 -> 320 | W62: =V62/Q62 -> 0.93567251
A65: NO | B65: BIDANG | C65: 44562 | J65: 44593 | Q65: 44621
C66: Jml regulasi | D66: Identifikasi | F66: Evaluasi | H66: Implementasi | J66: Jml regulasi | K66: Identifikasi | M66: Evaluasi | O66: Implementasi | Q66: Jml regulasi | R66: Identifikasi | T66: Evaluasi | V66: Implementasi
D67: Jml | E67: % | F67: Jml | G67: % | H67: Jml | I67: % | K67: Jml | L67: % | M67: Jml | N67: % | O67: Jml | P67: % | R67: Jml | S67: % | T67: Jml | U67: % | V67: Jml | W67: %
A68: 1 | B68: COMPLIANCE IN GENERAL (1) | C68: 0 | D68: 0 | E68: =D68/C68 -> #DIV/0! | F68: 0 | G68: =F68/C68 -> #DIV/0! | H68: 0 | I68: =H68/C68 -> #DIV/0! | J68: 0 | K68: 0 | L68: =K68/J68 -> #DIV/0! | M68: 0 | N68: =M68/J68 -> #DIV/0! | O68: 0 | P68: =O68/J68 -> #DIV/0! | Q68: 0 | R68: 0 | S68: =R68/Q68 -> #DIV/0! | T68: 0 | U68: =T68/Q68 -> #DIV/0! | V68: 0 | W68: =V68/Q68 -> #DIV/0!
A69: 2 | B69: LABOR & HUMAN RIGHTS (3) | C69: 91 | D69: 91 | E69: =D69/C69 -> 1 | F69: 90 | G69: =F69/C69 -> 0.98901099 | H69: 89 | I69: =H69/C69 -> 0.97802198 | J69: 79 | K69: 79 | L69: =K69/J69 -> 1 | M69: 78 | N69: =M69/J69 -> 0.98734177 | O69: 76 | P69: =O69/J69 -> 0.96202532 | Q69: 79 | R69: 79 | S69: =R69/Q69 -> 1 | T69: 79 | U69: =T69/Q69 -> 1 | V69: 78 | W69: =V69/Q69 -> 0.98734177
B70: a. HR | C70: 59 | D70: 59 | E70: =D70/C70 -> 1 | F70: 58 | G70: =F70/C70 -> 0.98305085 | H70: 57 | I70: =H70/C70 -> 0.96610169 | J70: 47 | K70: 47 | L70: =K70/J70 -> 1 | M70: 46 | N70: =M70/J70 -> 0.9787234 | O70: 44 | P70: =O70/J70 -> 0.93617021 | Q70: 47 | R70: 47 | S70: =R70/Q70 -> 1 | T70: 47 | U70: =T70/Q70 -> 1 | V70: 46 | W70: =V70/Q70 -> 0.9787234
B71: b. Expat | C71: 31 | D71: 31 | E71: =D71/C71 -> 1 | F71: 31 | G71: =F71/C71 -> 1 | H71: 31 | I71: =H71/C71 -> 1 | J71: 31 | K71: 31 | L71: =K71/J71 -> 1 | M71: 31 | N71: =M71/J71 -> 1 | O71: 31 | P71: =O71/J71 -> 1 | Q71: 31 | R71: 31 | S71: =R71/Q71 -> 1 | T71: 31 | U71: =T71/Q71 -> 1 | V71: 31 | W71: =V71/Q71 -> 1
B72: c. TRN | C72: 1 | D72: 1 | E72: =D72/C72 -> 1 | F72: 1 | G72: =F72/C72 -> 1 | H72: 1 | I72: =H72/C72 -> 1 | J72: 1 | K72: 1 | L72: =K72/J72 -> 1 | M72: 1 | N72: =M72/J72 -> 1 | O72: 1 | P72: =O72/J72 -> 1 | Q72: 1 | R72: 1 | S72: =R72/Q72 -> 1 | T72: 1 | U72: =T72/Q72 -> 1 | V72: 1 | W72: =V72/Q72 -> 1
A73: 3 | B73: INTELLECTUAL PROPERTY (4) | C73: 5 | D73: 5 | E73: =D73/C73 -> 1 | F73: 5 | G73: =F73/C73 -> 1 | H73: 5 | I73: =H73/C73 -> 1 | J73: 5 | K73: 5 | L73: =K73/J73 -> 1 | M73: 5 | N73: =M73/J73 -> 1 | O73: 5 | P73: =O73/J73 -> 1 | Q73: 5 | R73: 5 | S73: =R73/Q73 -> 1 | T73: 5 | U73: =T73/Q73 -> 1 | V73: 5 | W73: =V73/Q73 -> 1
A74: 4 | B74: FAIR TRADING (5) | C74: 5 | D74: 5 | E74: =D74/C74 -> 1 | F74: 5 | G74: =F74/C74 -> 1 | H74: 5 | I74: =H74/C74 -> 1 | J74: 5 | K74: 5 | L74: =K74/J74 -> 1 | M74: 5 | N74: =M74/J74 -> 1 | O74: 5 | P74: =O74/J74 -> 1 | Q74: 5 | R74: 5 | S74: =R74/Q74 -> 1 | T74: 5 | U74: =T74/Q74 -> 1 | V74: 5 | W74: =V74/Q74 -> 1
A75: 7 | B75: ENVIRONMENT, SAFETY & HEALTH (8) | C75: 106 | D75: 106 | E75: =D75/C75 -> 1 | F75: 106 | G75: =F75/C75 -> 1 | H75: 101 | I75: =H75/C75 -> 0.95283019 | J75: 106 | K75: 106 | L75: =K75/J75 -> 1 | M75: 106 | N75: =M75/J75 -> 1 | O75: 96 | P75: =O75/J75 -> 0.90566038 | Q75: 106 | R75: 106 | S75: =R75/Q75 -> 1 | T75: 106 | U75: =T75/Q75 -> 1 | V75: 96 | W75: =V75/Q75 -> 0.90566038
B76: a. Safety & Health | C76: 37 | D76: 37 | E76: =D76/C76 -> 1 | F76: 37 | G76: =F76/C76 -> 1 | H76: 33 | I76: =H76/C76 -> 0.89189189 | J76: 37 | K76: 37 | L76: =K76/J76 -> 1 | M76: 37 | N76: =M76/J76 -> 1 | O76: 32 | P76: =O76/J76 -> 0.86486486 | Q76: 37 | R76: 37 | S76: =R76/Q76 -> 1 | T76: 37 | U76: =T76/Q76 -> 1 | V76: 32 | W76: =V76/Q76 -> 0.86486486
B77: b. Environment | C77: 59 | D77: 59 | E77: =D77/C77 -> 1 | F77: 59 | G77: =F77/C77 -> 1 | H77: 58 | I77: =H77/C77 -> 0.98305085 | J77: 59 | K77: 59 | L77: =K77/J77 -> 1 | M77: 59 | N77: =M77/J77 -> 1 | O77: 54 | P77: =O77/J77 -> 0.91525424 | Q77: 59 | R77: 59 | S77: =R77/Q77 -> 1 | T77: 59 | U77: =T77/Q77 -> 1 | V77: 54 | W77: =V77/Q77 -> 0.91525424
B78: c. SoC | C78: 10 | D78: 10 | E78: =D78/C78 -> 1 | F78: 10 | G78: =F78/C78 -> 1 | H78: 10 | I78: =H78/C78 -> 1 | J78: 10 | K78: 10 | L78: =K78/J78 -> 1 | M78: 10 | N78: =M78/J78 -> 1 | O78: 10 | P78: =O78/J78 -> 1 | Q78: 10 | R78: 10 | S78: =R78/Q78 -> 1 | T78: 10 | U78: =T78/Q78 -> 1 | V78: 10 | W78: =V78/Q78 -> 1
A79: 6 | B79: COMPANY /BUSINESS OPERATIONS & LICENSE (2) | C79: 83 | D79: 83 | E79: =D79/C79 -> 1 | F79: 82 | G79: =F79/C79 -> 0.98795181 | H79: 72 | I79: =H79/C79 -> 0.86746988 | J79: 79 | K79: 79 | L79: =K79/J79 -> 1 | M79: 79 | N79: =M79/J79 -> 1 | O79: 69 | P79: =O79/J79 -> 0.87341772 | Q79: 80 | R79: 80 | S79: =R79/Q79 -> 1 | T79: 80 | U79: =T79/Q79 -> 1 | V79: 72 | W79: =V79/Q79 -> 0.9
B80: TOTAL | C80: =C68+C69+C73+C74+C75+C79 -> 290 | D80: =D68+D69+D73+D74+D75+D79 -> 290 | E80: =D80/C80 -> 1 | F80: =F68+F69+F73+F74+F75+F79 -> 288 | G80: =F80/C80 -> 0.99310345 | H80: =H68+H69+H73+H74+H75+H79 -> 272 | I80: =H80/C80 -> 0.93793103 | J80: =J68+J69+J73+J74+J75+J79 -> 274 | K80: =K68+K69+K73+K74+K75+K79 -> 274 | L80: =K80/J80 -> 1 | M80: =M68+M69+M73+M74+M75+M79 -> 273 | N80: =M80/J80 -> 0.99635036 | O80: =O68+O69+O73+O74+O75+O79 -> 251 | P80: =O80/J80 -> 0.91605839 | Q80: =Q68+Q69+Q73+Q74+Q75+Q79 -> 275 | R80: =R68+R69+R73+R74+R75+R79 -> 275 | S80: =R80/Q80 -> 1 | T80: =T68+T69+T73+T74+T75+T79 -> 275 | U80: =T80/Q80 -> 1 | V80: =V68+V69+V73+V74+V75+V79 -> 256 | W80: =V80/Q80 -> 0.93090909
A82: 5 | B82: EXIM MANAGEMENT (6) | C82: 18 | D82: 18 | E82: =D82/C82 -> 1 | F82: 16 | G82: =F82/C82 -> 0.88888889 | H82: 16 | I82: =H82/C82 -> 0.88888889 | J82: 17 | K82: 17 | L82: =K82/J82 -> 1 | M82: 16 | N82: =M82/J82 -> 0.94117647 | O82: 15 | P82: =O82/J82 -> 0.88235294 | Q82: 16 | R82: 16 | S82: =R82/Q82 -> 1 | T82: 16 | U82: =T82/Q82 -> 1 | V82: 15 | W82: =V82/Q82 -> 0.9375
A83: 8 | B83: ACCOUNTING /FINANCE (7) | C83: 41 | D83: 41 | E83: =D83/C83 -> 1 | F83: 34 | G83: =F83/C83 -> 0.82926829 | H83: 34 | I83: =H83/C83 -> 0.82926829 | J83: 34 | K83: 34 | L83: =K83/J83 -> 1 | M83: 34 | N83: =M83/J83 -> 1 | O83: 34 | P83: =O83/J83 -> 1 | Q83: 34 | R83: 34 | S83: =R83/Q83 -> 1 | T83: 34 | U83: =T83/Q83 -> 1 | V83: 34 | W83: =V83/Q83 -> 1
B84: TOTAL | C84: =SUM(C82:C83)+C80 -> 349 | D84: =SUM(D82:D83)+D80 -> 349 | E84: =D84/C84 -> 1 | F84: =SUM(F82:F83)+F80 -> 338 | G84: =F84/C84 -> 0.96848138 | H84: =SUM(H82:H83)+H80 -> 322 | I84: =H84/C84 -> 0.9226361 | J84: =SUM(J82:J83)+J80 -> 325 | K84: =SUM(K82:K83)+K80 -> 325 | L84: =K84/J84 -> 1 | M84: =SUM(M82:M83)+M80 -> 323 | N84: =M84/J84 -> 0.99384615 | O84: =SUM(O82:O83)+O80 -> 300 | P84: =O84/J84 -> 0.92307692 | Q84: =SUM(Q82:Q83)+Q80 -> 325 | R84: =SUM(R82:R83)+R80 -> 325 | S84: =R84/Q84 -> 1 | T84: =SUM(T82:T83)+T80 -> 325 | U84: =T84/Q84 -> 1 | V84: =SUM(V82:V83)+V80 -> 305 | W84: =V84/Q84 -> 0.93846154
A87: NO | B87: BIDANG | C87: 44652 | J87: 44682 | Q87: 44713
C88: Jml regulasi | D88: Identifikasi | F88: Evaluasi | H88: Implementasi | J88: Jml regulasi | K88: Identifikasi | M88: Evaluasi | O88: Implementasi | Q88: Jml regulasi | R88: Identifikasi | T88: Evaluasi | V88: Implementasi
D89: Jml | E89: % | F89: Jml | G89: % | H89: Jml | I89: % | K89: Jml | L89: % | M89: Jml | N89: % | O89: Jml | P89: % | R89: Jml | S89: % | T89: Jml | U89: % | V89: Jml | W89: %
A90: 1 | B90: COMPLIANCE IN GENERAL (1) | C90: 0 | D90: 0 | E90: =D90/C90 -> #DIV/0! | F90: 0 | G90: =F90/C90 -> #DIV/0! | H90: 0 | I90: =H90/C90 -> #DIV/0! | J90: 0 | K90: 0 | L90: =K90/J90 -> #DIV/0! | M90: 0 | N90: =M90/J90 -> #DIV/0! | O90: 0 | P90: =O90/J90 -> #DIV/0! | Q90: 0 | R90: 0 | S90: =R90/Q90 -> #DIV/0! | T90: 0 | U90: =T90/Q90 -> #DIV/0! | V90: 0 | W90: =V90/Q90 -> #DIV/0!
A91: 2 | B91: LABOR & HUMAN RIGHTS (3) | C91: 82 | D91: 82 | E91: =D91/C91 -> 1 | F91: 82 | G91: =F91/C91 -> 1 | H91: 81 | I91: =H91/C91 -> 0.98780488 | J91: 83 | K91: 83 | L91: =K91/J91 -> 1 | M91: 82 | N91: =M91/J91 -> 0.98795181 | O91: 75 | P91: =O91/J91 -> 0.90361446 | Q91: 82 | R91: 82 | S91: =R91/Q91 -> 1 | T91: 82 | U91: =T91/Q91 -> 1 | V91: 75 | W91: =V91/Q91 -> 0.91463415
B92: a. HR | C92: 50 | D92: 50 | E92: =D92/C92 -> 1 | F92: 50 | G92: =F92/C92 -> 1 | H92: 49 | I92: =H92/C92 -> 0.98 | J92: 50 | K92: 50 | L92: =K92/J92 -> 1 | M92: 50 | N92: =M92/J92 -> 1 | O92: 47 | P92: =O92/J92 -> 0.94 | Q92: 50 | R92: 50 | S92: =R92/Q92 -> 1 | T92: 50 | U92: =T92/Q92 -> 1 | V92: 47 | W92: =V92/Q92 -> 0.94
B93: b. Expat | C93: 31 | D93: 31 | E93: =D93/C93 -> 1 | F93: 31 | G93: =F93/C93 -> 1 | H93: 31 | I93: =H93/C93 -> 1 | J93: 32 | K93: 32 | L93: =K93/J93 -> 1 | M93: 31 | N93: =M93/J93 -> 0.96875 | O93: 27 | P93: =O93/J93 -> 0.84375 | Q93: 31 | R93: 31 | S93: =R93/Q93 -> 1 | T93: 31 | U93: =T93/Q93 -> 1 | V93: 27 | W93: =V93/Q93 -> 0.87096774
B94: c. TRN | C94: 1 | D94: 1 | E94: =D94/C94 -> 1 | F94: 1 | G94: =F94/C94 -> 1 | H94: 1 | I94: =H94/C94 -> 1 | J94: 1 | K94: 1 | L94: =K94/J94 -> 1 | M94: 1 | N94: =M94/J94 -> 1 | O94: 1 | P94: =O94/J94 -> 1 | Q94: 1 | R94: 1 | S94: =R94/Q94 -> 1 | T94: 1 | U94: =T94/Q94 -> 1 | V94: 1 | W94: =V94/Q94 -> 1
A95: 3 | B95: INTELLECTUAL PROPERTY (4) | C95: 5 | D95: 5 | E95: =D95/C95 -> 1 | F95: 5 | G95: =F95/C95 -> 1 | H95: 5 | I95: =H95/C95 -> 1 | J95: 5 | K95: 5 | L95: =K95/J95 -> 1 | M95: 5 | N95: =M95/J95 -> 1 | O95: 5 | P95: =O95/J95 -> 1 | Q95: 5 | R95: 5 | S95: =R95/Q95 -> 1 | T95: 5 | U95: =T95/Q95 -> 1 | V95: 5 | W95: =V95/Q95 -> 1
A96: 4 | B96: FAIR TRADING (5) | C96: 6 | D96: 6 | E96: =D96/C96 -> 1 | F96: 6 | G96: =F96/C96 -> 1 | H96: 5 | I96: =H96/C96 -> 0.83333333 | J96: 6 | K96: 6 | L96: =K96/J96 -> 1 | M96: 6 | N96: =M96/J96 -> 1 | O96: 5 | P96: =O96/J96 -> 0.83333333 | Q96: 6 | R96: 6 | S96: =R96/Q96 -> 1 | T96: 6 | U96: =T96/Q96 -> 1 | V96: 6 | W96: =V96/Q96 -> 1
A97: 7 | B97: ENVIRONMENT, SAFETY & HEALTH (8) | C97: 106 | D97: 106 | E97: =D97/C97 -> 1 | F97: 106 | G97: =F97/C97 -> 1 | H97: 96 | I97: =H97/C97 -> 0.90566038 | J97: 106 | K97: 106 | L97: =K97/J97 -> 1 | M97: 106 | N97: =M97/J97 -> 1 | O97: 96 | P97: =O97/J97 -> 0.90566038 | Q97: 104 | R97: 104 | S97: =R97/Q97 -> 1 | T97: 104 | U97: =T97/Q97 -> 1 | V97: 95 | W97: =V97/Q97 -> 0.91346154
B98: a. Safety & Health | C98: 37 | D98: 37 | E98: =D98/C98 -> 1 | F98: 37 | G98: =F98/C98 -> 1 | H98: 32 | I98: =H98/C98 -> 0.86486486 | J98: 37 | K98: 37 | L98: =K98/J98 -> 1 | M98: 37 | N98: =M98/J98 -> 1 | O98: 32 | P98: =O98/J98 -> 0.86486486 | Q98: 37 | R98: 37 | S98: =R98/Q98 -> 1 | T98: 37 | U98: =T98/Q98 -> 1 | V98: 32 | W98: =V98/Q98 -> 0.86486486
B99: b. Environment | C99: 59 | D99: 59 | E99: =D99/C99 -> 1 | F99: 59 | G99: =F99/C99 -> 1 | H99: 54 | I99: =H99/C99 -> 0.91525424 | J99: 59 | K99: 59 | L99: =K99/J99 -> 1 | M99: 59 | N99: =M99/J99 -> 1 | O99: 54 | P99: =O99/J99 -> 0.91525424 | Q99: 57 | R99: 57 | S99: =R99/Q99 -> 1 | T99: 57 | U99: =T99/Q99 -> 1 | V99: 53 | W99: =V99/Q99 -> 0.92982456
B100: c. SoC | C100: 10 | D100: 10 | E100: =D100/C100 -> 1 | F100: 10 | G100: =F100/C100 -> 1 | H100: 10 | I100: =H100/C100 -> 1 | J100: 10 | K100: 10 | L100: =K100/J100 -> 1 | M100: 10 | N100: =M100/J100 -> 1 | O100: 10 | P100: =O100/J100 -> 1 | Q100: 10 | R100: 10 | S100: =R100/Q100 -> 1 | T100: 10 | U100: =T100/Q100 -> 1 | V100: 10 | W100: =V100/Q100 -> 1
A101: 6 | B101: COMPANY /BUSINESS OPERATIONS & LICENSE (2) | C101: 80 | D101: 80 | E101: =D101/C101 -> 1 | F101: 80 | G101: =F101/C101 -> 1 | H101: 72 | I101: =H101/C101 -> 0.9 | J101: 81 | K101: 81 | L101: =K101/J101 -> 1 | M101: 80 | N101: =M101/J101 -> 0.98765432 | O101: 72 | P101: =O101/J101 -> 0.88888889 | Q101: 79 | R101: 79 | S101: =R101/Q101 -> 1 | T101: 79 | U101: =T101/Q101 -> 1 | V101: 71 | W101: =V101/Q101 -> 0.89873418
B102: TOTAL | C102: =C90+C91+C95+C96+C97+C101 -> 279 | D102: =D90+D91+D95+D96+D97+D101 -> 279 | E102: =D102/C102 -> 1 | F102: =F90+F91+F95+F96+F97+F101 -> 279 | G102: =F102/C102 -> 1 | H102: =H90+H91+H95+H96+H97+H101 -> 259 | I102: =H102/C102 -> 0.92831541 | J102: =J90+J91+J95+J96+J97+J101 -> 281 | K102: =K90+K91+K95+K96+K97+K101 -> 281 | L102: =K102/J102 -> 1 | M102: =M90+M91+M95+M96+M97+M101 -> 279 | N102: =M102/J102 -> 0.99288256 | O102: =O90+O91+O95+O96+O97+O101 -> 253 | P102: =O102/J102 -> 0.90035587 | Q102: =Q90+Q91+Q95+Q96+Q97+Q101 -> 276 | R102: =R90+R91+R95+R96+R97+R101 -> 276 | S102: =R102/Q102 -> 1 | T102: =T90+T91+T95+T96+T97+T101 -> 276 | U102: =T102/Q102 -> 1 | V102: =V90+V91+V95+V96+V97+V101 -> 252 | W102: =V102/Q102 -> 0.91304348
A104: 5 | B104: EXIM MANAGEMENT (6) | C104: 18 | D104: 18 | E104: =D104/C104 -> 1 | F104: 18 | G104: =F104/C104 -> 1 | H104: 17 | I104: =H104/C104 -> 0.94444444 | J104: 19 | K104: 19 | L104: =K104/J104 -> 1 | M104: 18 | N104: =M104/J104 -> 0.94736842 | O104: 17 | P104: =O104/J104 -> 0.89473684 | Q104: 18 | R104: 18 | S104: =R104/Q104 -> 1 | T104: 18 | U104: =T104/Q104 -> 1 | V104: 18 | W104: =V104/Q104 -> 1
A105: 8 | B105: ACCOUNTING /FINANCE (7) | C105: 34 | D105: 34 | E105: =D105/C105 -> 1 | F105: 34 | G105: =F105/C105 -> 1 | H105: 34 | I105: =H105/C105 -> 1 | J105: 35 | K105: 35 | L105: =K105/J105 -> 1 | M105: 34 | N105: =M105/J105 -> 0.97142857 | O105: 34 | P105: =O105/J105 -> 0.97142857 | Q105: 35 | R105: 35 | S105: =R105/Q105 -> 1 | T105: 35 | U105: =T105/Q105 -> 1 | V105: 35 | W105: =V105/Q105 -> 1
B106: TOTAL | C106: =SUM(C104:C105)+C102 -> 331 | D106: =SUM(D104:D105)+D102 -> 331 | E106: =D106/C106 -> 1 | F106: =SUM(F104:F105)+F102 -> 331 | G106: =F106/C106 -> 1 | H106: =SUM(H104:H105)+H102 -> 310 | I106: =H106/C106 -> 0.93655589 | J106: =SUM(J104:J105)+J102 -> 335 | K106: =SUM(K104:K105)+K102 -> 335 | L106: =K106/J106 -> 1 | M106: =SUM(M104:M105)+M102 -> 331 | N106: =M106/J106 -> 0.9880597 | O106: =SUM(O104:O105)+O102 -> 304 | P106: =O106/J106 -> 0.90746269 | Q106: =SUM(Q104:Q105)+Q102 -> 329 | R106: =SUM(R104:R105)+R102 -> 329 | S106: =R106/Q106 -> 1 | T106: =SUM(T104:T105)+T102 -> 329 | U106: =T106/Q106 -> 1 | V106: =SUM(V104:V105)+V102 -> 305 | W106: =V106/Q106 -> 0.92705167

Sheet 82
A2: Now day
A4: NO | B4: BIDANG | C4: NOW DAY
C5: Jml regulasi | D5: Identifikasi | F5: Evaluasi | H5: Implementasi
D6: Jml | E6: % | F6: Jml | G6: % | H6: Jml | I6: %
A7: 1 | B7: COMPLIANCE IN GENERAL (1) | C7: ='Detail COMPLIANCE FIELD'!G15 -> 0 | D7: =C7 -> 0 | E7: 1 | F7: ='Detail COMPLIANCE FIELD'!I15 -> 0 | G7: 1 | H7: ='Detail COMPLIANCE FIELD'!K15 -> 0 | I7: 1
A8: 2 | B8: LABOR & HUMAN RIGHTS (3) | C8: ='Detail COMPLIANCE FIELD'!G17 -> 126 | D8: =C8 -> 126 | E8: =D8/C8 -> 1 | F8: ='Detail COMPLIANCE FIELD'!I17 -> 126 | G8: =F8/C8 -> 1 | H8: ='Detail COMPLIANCE FIELD'!K17 -> 122 | I8: =H8/C8 -> 0.96825397
A9: 3 | B9: INTELLECTUAL PROPERTY (4) | C9: ='Detail COMPLIANCE FIELD'!G18 -> 7 | D9: =C9 -> 7 | E9: =D9/C9 -> 1 | F9: ='Detail COMPLIANCE FIELD'!I18 -> 7 | G9: =F9/C9 -> 1 | H9: ='Detail COMPLIANCE FIELD'!K18 -> 7 | I9: =H9/C9 -> 1
A10: 4 | B10: FAIR TRADING (5) | C10: ='Detail COMPLIANCE FIELD'!G19 -> 6 | D10: =C10 -> 6 | E10: =D10/C10 -> 1 | F10: ='Detail COMPLIANCE FIELD'!I19 -> 6 | G10: =F10/C10 -> 1 | H10: ='Detail COMPLIANCE FIELD'!K19 -> 6 | I10: =H10/C10 -> 1
A11: 5 | B11: ENVIRONMENT, SAFETY & HEALTH (8) | C11: ='Detail COMPLIANCE FIELD'!G22 -> 123 | D11: =C11 -> 123 | E11: =D11/C11 -> 1 | F11: ='Detail COMPLIANCE FIELD'!I22 -> 123 | G11: =F11/C11 -> 1 | H11: ='Detail COMPLIANCE FIELD'!K22 -> 116 | I11: =H11/C11 -> 0.94308943
A12: 6 | B12: COMPANY /BUSINESS OPERATIONS & LICENSE (2) | C12: ='Detail COMPLIANCE FIELD'!G16 -> 99 | D12: =C12 -> 99 | E12: =D12/C12 -> 1 | F12: ='Detail COMPLIANCE FIELD'!I16 -> 99 | G12: =F12/C12 -> 1 | H12: ='Detail COMPLIANCE FIELD'!K16 -> 98 | I12: =H12/C12 -> 0.98989899
B13: TOTAL | C13: =SUM(C7:C12) -> 361 | D13: =SUM(D7:D12) -> 361 | E13: =D13/C13 -> 1 | F13: =SUM(F7:F12) -> 361 | G13: =F13/C13 -> 1 | H13: =SUM(H7:H12) -> 349 | I13: =H13/C13 -> 0.966759
A15: 7 | B15: EXIM MANAGEMENT (6) | C15: ='Detail COMPLIANCE FIELD'!G20 -> 37 | D15: =C15 -> 37 | E15: =D15/C15 -> 1 | F15: ='Detail COMPLIANCE FIELD'!I20 -> 37 | G15: =F15/C15 -> 1 | H15: ='Detail COMPLIANCE FIELD'!K20 -> 37 | I15: =H15/C15 -> 1
A16: 8 | B16: ACCOUNTING /FINANCE (7) | C16: ='Detail COMPLIANCE FIELD'!G21 -> 56 | D16: =C16 -> 56 | E16: =D16/C16 -> 1 | F16: ='Detail COMPLIANCE FIELD'!I21 -> 56 | G16: =F16/C16 -> 1 | H16: ='Detail COMPLIANCE FIELD'!K21 -> 56 | I16: =H16/C16 -> 1
B17: TOTAL | C17: =SUM(C15:C16)+C13 -> 454 | D17: =SUM(D15:D16)+D13 -> 454 | E17: =D17/C17 -> 1 | F17: =SUM(F15:F16)+F13 -> 454 | G17: =F17/C17 -> 1 | H17: =SUM(H15:H16)+H13 -> 442 | I17: =H17/C17 -> 0.97356828
A18: PT. SEMARANG AUTOCOMP MANUFACTURING INDONESIA
A19: KEPATUHAN TERHADAP PERATURAN PERUNDANGAN
A21: NO | B21: BIDANG | C21: 44743 | J21: 44774 | Q21: 44805
C22: Jml regulasi | D22: Identifikasi | F22: Evaluasi | H22: Implementasi | J22: Jml regulasi | K22: Identifikasi | M22: Evaluasi | O22: Implementasi | Q22: Jml regulasi | R22: Identifikasi | T22: Evaluasi | V22: Implementasi
D23: Jml | E23: % | F23: Jml | G23: % | H23: Jml | I23: % | K23: Jml | L23: % | M23: Jml | N23: % | O23: Jml | P23: % | R23: Jml | S23: % | T23: Jml | U23: % | V23: Jml | W23: %
A24: 1 | B24: COMPLIANCE IN GENERAL (1) | C24: 0 | D24: 0 | E24: #DIV/0! | F24: 0 | G24: #DIV/0! | H24: 0 | I24: #DIV/0! | J24: 0 | K24: 0 | L24: =K24/J24 -> #DIV/0! | M24: 0 | N24: =M24/J24 -> #DIV/0! | O24: 0 | P24: =O24/J24 -> #DIV/0! | Q24: 0 | R24: 0 | S24: =R24/Q24 -> #DIV/0! | T24: 0 | U24: =T24/Q24 -> #DIV/0! | V24: 0 | W24: =V24/Q24 -> #DIV/0!
A25: 2 | B25: LABOR & HUMAN RIGHTS (3) | C25: 82 | D25: 82 | E25: 1 | F25: 82 | G25: 1 | H25: 75 | I25: 0.91463415 | J25: 82 | K25: 82 | L25: 1 | M25: 82 | N25: 1 | O25: 75 | P25: 0.91463415 | Q25: 85 | R25: 85 | S25: =R25/Q25 -> 1 | T25: 85 | U25: =T25/Q25 -> 1 | V25: 79 | W25: =V25/Q25 -> 0.92941176
B26: a. HR | C26: 50 | D26: 50 | E26: 1 | F26: 50 | G26: 1 | H26: 47 | I26: 0.94 | J26: 50 | K26: 50 | L26: 1 | M26: 50 | N26: 1 | O26: 47 | P26: 0.94 | Q26: 52 | R26: 52 | S26: =R26/Q26 -> 1 | T26: 52 | U26: =T26/Q26 -> 1 | V26: 50 | W26: =V26/Q26 -> 0.96153846
B27: b. Expat | C27: 31 | D27: 31 | E27: 1 | F27: 31 | G27: 1 | H27: 27 | I27: 0.87096774 | J27: 31 | K27: 31 | L27: 1 | M27: 31 | N27: 1 | O27: 27 | P27: 0.87096774 | Q27: 32 | R27: 32 | S27: =R27/Q27 -> 1 | T27: 32 | U27: =T27/Q27 -> 1 | V27: 28 | W27: =V27/Q27 -> 0.875
B28: c. TRN | C28: 1 | D28: 1 | E28: 1 | F28: 1 | G28: 1 | H28: 1 | I28: 1 | J28: 1 | K28: 1 | L28: 1 | M28: 1 | N28: 1 | O28: 1 | P28: 1 | Q28: 1 | R28: 1 | S28: =R28/Q28 -> 1 | T28: 1 | U28: =T28/Q28 -> 1 | V28: 1 | W28: =V28/Q28 -> 1
A29: 3 | B29: INTELLECTUAL PROPERTY (4) | C29: 5 | D29: 5 | E29: 1 | F29: 5 | G29: 1 | H29: 5 | I29: 1 | J29: 5 | K29: 5 | L29: =K29/J29 -> 1 | M29: 5 | N29: =M29/J29 -> 1 | O29: 5 | P29: =O29/J29 -> 1 | Q29: 5 | R29: 5 | S29: =R29/Q29 -> 1 | T29: 5 | U29: =T29/Q29 -> 1 | V29: 5 | W29: =V29/Q29 -> 1
A30: 4 | B30: FAIR TRADING (5) | C30: 6 | D30: 6 | E30: 1 | F30: 6 | G30: 1 | H30: 6 | I30: 1 | J30: 6 | K30: 6 | L30: =K30/J30 -> 1 | M30: 6 | N30: =M30/J30 -> 1 | O30: 6 | P30: =O30/J30 -> 1 | Q30: 6 | R30: 6 | S30: =R30/Q30 -> 1 | T30: 6 | U30: =T30/Q30 -> 1 | V30: 6 | W30: =V30/Q30 -> 1
A31: 6 | B31: ENVIRONMENT, SAFETY & HEALTH (8) | C31: 104 | D31: 104 | E31: 1 | F31: 104 | G31: 1 | H31: 95 | I31: 0.91346154 | J31: 104 | K31: 104 | L31: 1 | M31: 104 | N31: 1 | O31: 95 | P31: 0.91346154 | Q31: 104 | R31: 104 | S31: 1 | T31: 104 | U31: 1 | V31: 95 | W31: 0.91346154
B32: a. Safety & Health | C32: 37 | D32: 37 | E32: 1 | F32: 37 | G32: 1 | H32: 32 | I32: 0.86486486 | J32: 37 | K32: 37 | L32: 1 | M32: 37 | N32: 1 | O32: 32 | P32: 0.86486486 | Q32: 37 | R32: 37 | S32: 1 | T32: 37 | U32: 1 | V32: 32 | W32: 0.86486486
B33: b. Environment | C33: 57 | D33: 57 | E33: 1 | F33: 57 | G33: 1 | H33: 53 | I33: 0.92982456 | J33: 57 | K33: 57 | L33: 1 | M33: 57 | N33: 1 | O33: 53 | P33: 0.92982456 | Q33: 57 | R33: 57 | S33: 1 | T33: 57 | U33: 1 | V33: 53 | W33: 0.92982456
B34: c. SoC | C34: 10 | D34: 10 | E34: 1 | F34: 10 | G34: 1 | H34: 10 | I34: 1 | J34: 10 | K34: 10 | L34: 1 | M34: 10 | N34: 1 | O34: 10 | P34: 1 | Q34: 10 | R34: 10 | S34: 1 | T34: 10 | U34: 1 | V34: 10 | W34: 1
A35: 7 | B35: COMPANY /BUSINESS OPERATIONS & LICENSE (2) | C35: 79 | D35: 79 | E35: 1 | F35: 79 | G35: 1 | H35: 71 | I35: 0.89873418 | J35: 79 | K35: 79 | L35: 1 | M35: 79 | N35: 1 | O35: 71 | P35: 0.89873418 | Q35: 80 | R35: 80 | S35: =R35/Q35 -> 1 | T35: 79 | U35: =T35/Q35 -> 0.9875 | V35: 71 | W35: =V35/Q35 -> 0.8875
B36: TOTAL | C36: 276 | D36: 276 | E36: 1 | F36: 276 | G36: 1 | H36: 252 | I36: 0.91304348 | J36: =J24+J25+J29+J30+J31+J35 -> 276 | K36: =K24+K25+K29+K30+K31+K35 -> 276 | L36: =K36/J36 -> 1 | M36: =M24+M25+M29+M30+M31+M35 -> 276 | N36: =M36/J36 -> 1 | O36: =O24+O25+O29+O30+O31+O35 -> 252 | P36: =O36/J36 -> 0.91304348 | Q36: =Q24+Q25+Q29+Q30+Q31+Q35 -> 280 | R36: =R24+R25+R29+R30+R31+R35 -> 280 | S36: =R36/Q36 -> 1 | T36: =T24+T25+T29+T30+T31+T35 -> 279 | U36: =T36/Q36 -> 0.99642857 | V36: =V24+V25+V29+V30+V31+V35 -> 256 | W36: =V36/Q36 -> 0.91428571
A38: 5 | B38: EXIM MANAGEMENT (6) | C38: 18 | D38: 18 | E38: 1 | F38: 18 | G38: 0.94736842 | H38: 18 | I38: 0.94736842 | J38: 18 | K38: 18 | L38: 1 | M38: 18 | N38: 0.94736842 | O38: 18 | P38: 0.94736842 | Q38: 19 | R38: 19 | S38: =R38/Q38 -> 1 | T38: 18 | U38: =T38/Q38 -> 0.94736842 | V38: 18 | W38: =V38/Q38 -> 0.94736842
A39: 8 | B39: ACCOUNTING /FINANCE (7) | C39: 36 | D39: 36 | E39: 1 | F39: 36 | G39: 0.97222222 | H39: 36 | I39: 0.97222222 | J39: 37 | K39: 37 | L39: =K39/J39 -> 1 | M39: 37 | N39: =M39/J39 -> 1 | O39: 37 | P39: =O39/J39 -> 1 | Q39: 38 | R39: 38 | S39: =R39/Q39 -> 1 | T39: 37 | U39: =T39/Q39 -> 0.97368421 | V39: 37 | W39: =V39/Q39 -> 0.97368421
B40: TOTAL | C40: =SUM(C38:C39)+C36 -> 330 | D40: =SUM(D38:D39)+D36 -> 330 | E40: =D40/C40 -> 1 | F40: =SUM(F38:F39)+F36 -> 330 | G40: =F40/C40 -> 1 | H40: =SUM(H38:H39)+H36 -> 306 | I40: =H40/C40 -> 0.92727273 | J40: =SUM(J38:J39)+J36 -> 331 | K40: =SUM(K38:K39)+K36 -> 331 | L40: =K40/J40 -> 1 | M40: =SUM(M38:M39)+M36 -> 331 | N40: =M40/J40 -> 1 | O40: =SUM(O38:O39)+O36 -> 307 | P40: =O40/J40 -> 0.92749245 | Q40: =SUM(Q38:Q39)+Q36 -> 337 | R40: =SUM(R38:R39)+R36 -> 337 | S40: =R40/Q40 -> 1 | T40: =SUM(T38:T39)+T36 -> 334 | U40: =T40/Q40 -> 0.99109792 | V40: =SUM(V38:V39)+V36 -> 311 | W40: =V40/Q40 -> 0.92284866
A43: NO | B43: BIDANG | C43: 44835 | J43: 44866 | Q43: 44896
C44: Jml regulasi | D44: Identifikasi | F44: Evaluasi | H44: Implementasi | J44: Jml regulasi | K44: Identifikasi | M44: Evaluasi | O44: Implementasi | Q44: Jml regulasi | R44: Identifikasi | T44: Evaluasi | V44: Implementasi
D45: Jml | E45: % | F45: Jml | G45: % | H45: Jml | I45: % | K45: Jml | L45: % | M45: Jml | N45: % | O45: Jml | P45: % | R45: Jml | S45: % | T45: Jml | U45: % | V45: Jml | W45: %
A46: 1 | B46: COMPLIANCE IN GENERAL (1) | C46: 0 | D46: 0 | E46: #DIV/0! | F46: 0 | G46: #DIV/0! | H46: 0 | I46: #DIV/0! | J46: 0 | K46: 0 | L46: #DIV/0! | M46: 0 | N46: #DIV/0! | O46: 0 | P46: #DIV/0! | S46: =R46/Q46 -> #DIV/0! | U46: =T46/Q46 -> #DIV/0! | W46: =V46/Q46 -> #DIV/0!
A47: 2 | B47: LABOR & HUMAN RIGHTS (3) | C47: 91 | D47: 91 | E47: =D47/C47 -> 1 | F47: 91 | G47: =F47/C47 -> 1 | H47: 85 | I47: =H47/C47 -> 0.93406593 | J47: 94 | K47: 94 | L47: =K47/J47 -> 1 | M47: 94 | N47: =M47/J47 -> 1 | O47: 88 | P47: =O47/J47 -> 0.93617021 | S47: =R47/Q47 -> #DIV/0! | U47: =T47/Q47 -> #DIV/0! | W47: =V47/Q47 -> #DIV/0!
B48: a. HR | C48: 54 | D48: 54 | E48: =D48/C48 -> 1 | F48: 54 | G48: =F48/C48 -> 1 | H48: 52 | I48: =H48/C48 -> 0.96296296 | J48: 55 | K48: 55 | L48: =K48/J48 -> 1 | M48: 55 | N48: =M48/J48 -> 1 | O48: 53 | P48: =O48/J48 -> 0.96363636 | S48: =R48/Q48 -> #DIV/0! | U48: =T48/Q48 -> #DIV/0! | W48: =V48/Q48 -> #DIV/0!
B49: b. Expat | C49: 36 | D49: 36 | E49: =D49/C49 -> 1 | F49: 36 | G49: =F49/C49 -> 1 | H49: 32 | I49: =H49/C49 -> 0.88888889 | J49: 38 | K49: 38 | L49: =K49/J49 -> 1 | M49: 38 | N49: =M49/J49 -> 1 | O49: 34 | P49: =O49/J49 -> 0.89473684 | S49: =R49/Q49 -> #DIV/0! | U49: =T49/Q49 -> #DIV/0! | W49: =V49/Q49 -> #DIV/0!
B50: c. TRN | C50: 1 | D50: 1 | E50: =D50/C50 -> 1 | F50: 1 | G50: =F50/C50 -> 1 | H50: 1 | I50: =H50/C50 -> 1 | J50: 1 | K50: 1 | L50: =K50/J50 -> 1 | M50: 1 | N50: =M50/J50 -> 1 | O50: 1 | P50: =O50/J50 -> 1 | S50: =R50/Q50 -> #DIV/0! | U50: =T50/Q50 -> #DIV/0! | W50: =V50/Q50 -> #DIV/0!
A51: 3 | B51: INTELLECTUAL PROPERTY (4) | C51: 5 | D51: 5 | E51: =D51/C51 -> 1 | F51: 5 | G51: =F51/C51 -> 1 | H51: 5 | I51: =H51/C51 -> 1 | J51: 5 | K51: 5 | L51: =K51/J51 -> 1 | M51: 5 | N51: =M51/J51 -> 1 | O51: 5 | P51: =O51/J51 -> 1 | S51: =R51/Q51 -> #DIV/0! | U51: =T51/Q51 -> #DIV/0! | W51: =V51/Q51 -> #DIV/0!
A52: 7 | B52: FAIR TRADING (5) | C52: 6 | D52: 6 | E52: =D52/C52 -> 1 | F52: 6 | G52: =F52/C52 -> 1 | H52: 6 | I52: =H52/C52 -> 1 | J52: 6 | K52: 6 | L52: =K52/J52 -> 1 | M52: 6 | N52: =M52/J52 -> 1 | O52: 6 | P52: =O52/J52 -> 1 | S52: =R52/Q52 -> #DIV/0! | U52: =T52/Q52 -> #DIV/0! | W52: =V52/Q52 -> #DIV/0!
A53: 4 | B53: ENVIRONMENT, SAFETY & HEALTH (8) | C53: 105 | D53: 105 | E53: =D53/C53 -> 1 | F53: 105 | G53: =F53/C53 -> 1 | H53: 95 | I53: =H53/C53 -> 0.9047619 | J53: 107 | K53: 107 | L53: =K53/J53 -> 1 | M53: 107 | N53: =M53/J53 -> 1 | O53: 96 | P53: =O53/J53 -> 0.89719626 | S53: =R53/Q53 -> #DIV/0! | U53: =T53/Q53 -> #DIV/0! | W53: =V53/Q53 -> #DIV/0!
B54: a. Safety & Health | C54: 38 | D54: 38 | E54: =D54/C54 -> 1 | F54: 38 | G54: =F54/C54 -> 1 | H54: 32 | I54: =H54/C54 -> 0.84210526 | J54: 39 | K54: 39 | L54: =K54/J54 -> 1 | M54: 39 | N54: =M54/J54 -> 1 | O54: 33 | P54: =O54/J54 -> 0.84615385 | S54: =R54/Q54 -> #DIV/0! | U54: =T54/Q54 -> #DIV/0! | W54: =V54/Q54 -> #DIV/0!
B55: b. Environment | C55: 57 | D55: 57 | E55: =D55/C55 -> 1 | F55: 57 | G55: =F55/C55 -> 1 | H55: 53 | I55: =H55/C55 -> 0.92982456 | J55: 58 | K55: 58 | L55: =K55/J55 -> 1 | M55: 58 | N55: =M55/J55 -> 1 | O55: 53 | P55: =O55/J55 -> 0.9137931 | S55: =R55/Q55 -> #DIV/0! | U55: =T55/Q55 -> #DIV/0! | W55: =V55/Q55 -> #DIV/0!
B56: c. SoC | C56: 10 | D56: 10 | E56: 1 | F56: 10 | G56: 1 | H56: 10 | I56: 1 | J56: 10 | K56: 10 | L56: 1 | M56: 10 | N56: 1 | O56: 10 | P56: 1 | S56: =R56/Q56 -> #DIV/0! | U56: =T56/Q56 -> #DIV/0! | W56: =V56/Q56 -> #DIV/0!
A57: 6 | B57: COMPANY /BUSINESS OPERATIONS & LICENSE (2) | C57: 82 | D57: 82 | E57: =D57/C57 -> 1 | F57: 81 | G57: =F57/C57 -> 0.98780488 | H57: 73 | I57: =H57/C57 -> 0.8902439 | J57: 84 | K57: 84 | L57: =K57/J57 -> 1 | M57: 83 | N57: =M57/J57 -> 0.98809524 | O57: 75 | P57: =O57/J57 -> 0.89285714 | S57: =R57/Q57 -> #DIV/0! | U57: =T57/Q57 -> #DIV/0! | W57: =V57/Q57 -> #DIV/0!
B58: TOTAL | C58: =C46+C47+C51+C52+C53+C57 -> 289 | D58: =D46+D47+D51+D52+D53+D57 -> 289 | E58: =D58/C58 -> 1 | F58: =F46+F47+F51+F52+F53+F57 -> 288 | G58: =F58/C58 -> 0.99653979 | H58: =H46+H47+H51+H52+H53+H57 -> 264 | I58: =H58/C58 -> 0.91349481 | J58: =J46+J47+J51+J52+J53+J57 -> 296 | K58: =K46+K47+K51+K52+K53+K57 -> 296 | L58: =K58/J58 -> 1 | M58: =M46+M47+M51+M52+M53+M57 -> 295 | N58: =M58/J58 -> 0.99662162 | O58: =O46+O47+O51+O52+O53+O57 -> 270 | P58: =O58/J58 -> 0.91216216 | Q58: =Q46+Q47+Q51+Q52+Q53+Q57 -> 0 | R58: =R46+R47+R51+R52+R53+R57 -> 0 | S58: =R58/Q58 -> #DIV/0! | T58: =T46+T47+T51+T52+T53+T57 -> 0 | U58: =T58/Q58 -> #DIV/0! | V58: =V46+V47+V51+V52+V53+V57 -> 0 | W58: =V58/Q58 -> #DIV/0!
A60: 5 | B60: EXIM MANAGEMENT (6) | C60: 19 | D60: 19 | E60: =D60/C60 -> 1 | F60: 18 | G60: =F60/C60 -> 0.94736842 | H60: 18 | I60: =H60/C60 -> 0.94736842 | J60: 19 | K60: 19 | L60: =K60/J60 -> 1 | M60: 18 | N60: =M60/J60 -> 0.94736842 | O60: 18 | P60: =O60/J60 -> 0.94736842 | S60: =R60/Q60 -> #DIV/0! | U60: =T60/Q60 -> #DIV/0! | W60: =V60/Q60 -> #DIV/0!
A61: 8 | B61: ACCOUNTING /FINANCE (7) | C61: 39 | D61: 39 | E61: =D61/C61 -> 1 | F61: 37 | G61: =F61/C61 -> 0.94871795 | H61: 37 | I61: =H61/C61 -> 0.94871795 | J61: 39 | K61: 39 | L61: =K61/J61 -> 1 | M61: 37 | N61: =M61/J61 -> 0.94871795 | O61: 37 | P61: =O61/J61 -> 0.94871795 | S61: =R61/Q61 -> #DIV/0! | U61: =T61/Q61 -> #DIV/0! | W61: =V61/Q61 -> #DIV/0!
B62: TOTAL | C62: =SUM(C60:C61)+C58 -> 347 | D62: =SUM(D60:D61)+D58 -> 347 | E62: =D62/C62 -> 1 | F62: =SUM(F60:F61)+F58 -> 343 | G62: =F62/C62 -> 0.98847262 | H62: =SUM(H60:H61)+H58 -> 319 | I62: =H62/C62 -> 0.91930836 | J62: =SUM(J60:J61)+J58 -> 354 | K62: =SUM(K60:K61)+K58 -> 354 | L62: =K62/J62 -> 1 | M62: =SUM(M60:M61)+M58 -> 350 | N62: =M62/J62 -> 0.98870056 | O62: =SUM(O60:O61)+O58 -> 325 | P62: =O62/J62 -> 0.9180791 | Q62: =SUM(Q60:Q61)+Q58 -> 0 | R62: =SUM(R60:R61)+R58 -> 0 | S62: =R62/Q62 -> #DIV/0! | T62: =SUM(T60:T61)+T58 -> 0 | U62: =T62/Q62 -> #DIV/0! | V62: =SUM(V60:V61)+V58 -> 0 | W62: =V62/Q62 -> #DIV/0!
A65: NO | B65: BIDANG | C65: 44927 | J65: 44958 | Q65: 44986
C66: Jml regulasi | D66: Identifikasi | F66: Evaluasi | H66: Implementasi | J66: Jml regulasi | K66: Identifikasi | M66: Evaluasi | O66: Implementasi | Q66: Jml regulasi | R66: Identifikasi | T66: Evaluasi | V66: Implementasi
D67: Jml | E67: % | F67: Jml | G67: % | H67: Jml | I67: % | K67: Jml | L67: % | M67: Jml | N67: % | O67: Jml | P67: % | R67: Jml | S67: % | T67: Jml | U67: % | V67: Jml | W67: %
A68: 1 | B68: COMPLIANCE IN GENERAL (1) | E68: =D68/C68 -> #DIV/0! | G68: =F68/C68 -> #DIV/0! | I68: =H68/C68 -> #DIV/0! | L68: =K68/J68 -> #DIV/0! | N68: =M68/J68 -> #DIV/0! | P68: =O68/J68 -> #DIV/0! | S68: =R68/Q68 -> #DIV/0! | U68: =T68/Q68 -> #DIV/0! | W68: =V68/Q68 -> #DIV/0!
A69: 2 | B69: LABOR & HUMAN RIGHTS (3) | E69: =D69/C69 -> #DIV/0! | G69: =F69/C69 -> #DIV/0! | I69: =H69/C69 -> #DIV/0! | L69: =K69/J69 -> #DIV/0! | N69: =M69/J69 -> #DIV/0! | P69: =O69/J69 -> #DIV/0! | S69: =R69/Q69 -> #DIV/0! | U69: =T69/Q69 -> #DIV/0! | W69: =V69/Q69 -> #DIV/0!
B70: a. HR | E70: =D70/C70 -> #DIV/0! | G70: =F70/C70 -> #DIV/0! | I70: =H70/C70 -> #DIV/0! | L70: =K70/J70 -> #DIV/0! | N70: =M70/J70 -> #DIV/0! | P70: =O70/J70 -> #DIV/0! | S70: =R70/Q70 -> #DIV/0! | U70: =T70/Q70 -> #DIV/0! | W70: =V70/Q70 -> #DIV/0!
B71: b. Expat | E71: =D71/C71 -> #DIV/0! | G71: =F71/C71 -> #DIV/0! | I71: =H71/C71 -> #DIV/0! | L71: =K71/J71 -> #DIV/0! | N71: =M71/J71 -> #DIV/0! | P71: =O71/J71 -> #DIV/0! | S71: =R71/Q71 -> #DIV/0! | U71: =T71/Q71 -> #DIV/0! | W71: =V71/Q71 -> #DIV/0!
B72: c. TRN | E72: =D72/C72 -> #DIV/0! | G72: =F72/C72 -> #DIV/0! | I72: =H72/C72 -> #DIV/0! | L72: =K72/J72 -> #DIV/0! | N72: =M72/J72 -> #DIV/0! | P72: =O72/J72 -> #DIV/0! | S72: =R72/Q72 -> #DIV/0! | U72: =T72/Q72 -> #DIV/0! | W72: =V72/Q72 -> #DIV/0!
A73: 3 | B73: INTELLECTUAL PROPERTY (4) | E73: =D73/C73 -> #DIV/0! | G73: =F73/C73 -> #DIV/0! | I73: =H73/C73 -> #DIV/0! | L73: =K73/J73 -> #DIV/0! | N73: =M73/J73 -> #DIV/0! | P73: =O73/J73 -> #DIV/0! | S73: =R73/Q73 -> #DIV/0! | U73: =T73/Q73 -> #DIV/0! | W73: =V73/Q73 -> #DIV/0!
A74: 4 | B74: FAIR TRADING (5) | E74: =D74/C74 -> #DIV/0! | G74: =F74/C74 -> #DIV/0! | I74: =H74/C74 -> #DIV/0! | L74: =K74/J74 -> #DIV/0! | N74: =M74/J74 -> #DIV/0! | P74: =O74/J74 -> #DIV/0! | S74: =R74/Q74 -> #DIV/0! | U74: =T74/Q74 -> #DIV/0! | W74: =V74/Q74 -> #DIV/0!
A75: 7 | B75: ENVIRONMENT, SAFETY & HEALTH (8) | E75: =D75/C75 -> #DIV/0! | G75: =F75/C75 -> #DIV/0! | I75: =H75/C75 -> #DIV/0! | L75: =K75/J75 -> #DIV/0! | N75: =M75/J75 -> #DIV/0! | P75: =O75/J75 -> #DIV/0! | S75: =R75/Q75 -> #DIV/0! | U75: =T75/Q75 -> #DIV/0! | W75: =V75/Q75 -> #DIV/0!
B76: a. Safety & Health | E76: =D76/C76 -> #DIV/0! | G76: =F76/C76 -> #DIV/0! | I76: =H76/C76 -> #DIV/0! | L76: =K76/J76 -> #DIV/0! | N76: =M76/J76 -> #DIV/0! | P76: =O76/J76 -> #DIV/0! | S76: =R76/Q76 -> #DIV/0! | U76: =T76/Q76 -> #DIV/0! | W76: =V76/Q76 -> #DIV/0!
B77: b. Environment | E77: =D77/C77 -> #DIV/0! | G77: =F77/C77 -> #DIV/0! | I77: =H77/C77 -> #DIV/0! | L77: =K77/J77 -> #DIV/0! | N77: =M77/J77 -> #DIV/0! | P77: =O77/J77 -> #DIV/0! | S77: =R77/Q77 -> #DIV/0! | U77: =T77/Q77 -> #DIV/0! | W77: =V77/Q77 -> #DIV/0!
B78: c. SoC | E78: =D78/C78 -> #DIV/0! | G78: =F78/C78 -> #DIV/0! | I78: =H78/C78 -> #DIV/0! | L78: =K78/J78 -> #DIV/0! | N78: =M78/J78 -> #DIV/0! | P78: =O78/J78 -> #DIV/0! | S78: =R78/Q78 -> #DIV/0! | U78: =T78/Q78 -> #DIV/0! | W78: =V78/Q78 -> #DIV/0!
A79: 6 | B79: COMPANY /BUSINESS OPERATIONS & LICENSE (2) | E79: =D79/C79 -> #DIV/0! | G79: =F79/C79 -> #DIV/0! | I79: =H79/C79 -> #DIV/0! | L79: =K79/J79 -> #DIV/0! | N79: =M79/J79 -> #DIV/0! | P79: =O79/J79 -> #DIV/0! | S79: =R79/Q79 -> #DIV/0! | U79: =T79/Q79 -> #DIV/0! | W79: =V79/Q79 -> #DIV/0!
B80: TOTAL | C80: =C68+C69+C73+C74+C75+C79 -> 0 | D80: =D68+D69+D73+D74+D75+D79 -> 0 | E80: =D80/C80 -> #DIV/0! | F80: =F68+F69+F73+F74+F75+F79 -> 0 | G80: =F80/C80 -> #DIV/0! | H80: =H68+H69+H73+H74+H75+H79 -> 0 | I80: =H80/C80 -> #DIV/0! | J80: =J68+J69+J73+J74+J75+J79 -> 0 | K80: =K68+K69+K73+K74+K75+K79 -> 0 | L80: =K80/J80 -> #DIV/0! | M80: =M68+M69+M73+M74+M75+M79 -> 0 | N80: =M80/J80 -> #DIV/0! | O80: =O68+O69+O73+O74+O75+O79 -> 0 | P80: =O80/J80 -> #DIV/0! | Q80: =Q68+Q69+Q73+Q74+Q75+Q79 -> 0 | R80: =R68+R69+R73+R74+R75+R79 -> 0 | S80: =R80/Q80 -> #DIV/0! | T80: =T68+T69+T73+T74+T75+T79 -> 0 | U80: =T80/Q80 -> #DIV/0! | V80: =V68+V69+V73+V74+V75+V79 -> 0 | W80: =V80/Q80 -> #DIV/0!
A82: 5 | B82: EXIM MANAGEMENT (6) | E82: =D82/C82 -> #DIV/0! | G82: =F82/C82 -> #DIV/0! | I82: =H82/C82 -> #DIV/0! | L82: =K82/J82 -> #DIV/0! | N82: =M82/J82 -> #DIV/0! | P82: =O82/J82 -> #DIV/0! | S82: =R82/Q82 -> #DIV/0! | U82: =T82/Q82 -> #DIV/0! | W82: =V82/Q82 -> #DIV/0!
A83: 8 | B83: ACCOUNTING /FINANCE (7) | E83: =D83/C83 -> #DIV/0! | G83: =F83/C83 -> #DIV/0! | I83: =H83/C83 -> #DIV/0! | L83: =K83/J83 -> #DIV/0! | N83: =M83/J83 -> #DIV/0! | P83: =O83/J83 -> #DIV/0! | S83: =R83/Q83 -> #DIV/0! | U83: =T83/Q83 -> #DIV/0! | W83: =V83/Q83 -> #DIV/0!
B84: TOTAL | C84: =SUM(C82:C83)+C80 -> 0 | D84: =SUM(D82:D83)+D80 -> 0 | E84: =D84/C84 -> #DIV/0! | F84: =SUM(F82:F83)+F80 -> 0 | G84: =F84/C84 -> #DIV/0! | H84: =SUM(H82:H83)+H80 -> 0 | I84: =H84/C84 -> #DIV/0! | J84: =SUM(J82:J83)+J80 -> 0 | K84: =SUM(K82:K83)+K80 -> 0 | L84: =K84/J84 -> #DIV/0! | M84: =SUM(M82:M83)+M80 -> 0 | N84: =M84/J84 -> #DIV/0! | O84: =SUM(O82:O83)+O80 -> 0 | P84: =O84/J84 -> #DIV/0! | Q84: =SUM(Q82:Q83)+Q80 -> 0 | R84: =SUM(R82:R83)+R80 -> 0 | S84: =R84/Q84 -> #DIV/0! | T84: =SUM(T82:T83)+T80 -> 0 | U84: =T84/Q84 -> #DIV/0! | V84: =SUM(V82:V83)+V80 -> 0 | W84: =V84/Q84 -> #DIV/0!
A87: NO | B87: BIDANG | C87: 45017 | J87: 45047 | Q87: 45078
C88: Jml regulasi | D88: Identifikasi | F88: Evaluasi | H88: Implementasi | J88: Jml regulasi | K88: Identifikasi | M88: Evaluasi | O88: Implementasi | Q88: Jml regulasi | R88: Identifikasi | T88: Evaluasi | V88: Implementasi
D89: Jml | E89: % | F89: Jml | G89: % | H89: Jml | I89: % | K89: Jml | L89: % | M89: Jml | N89: % | O89: Jml | P89: % | R89: Jml | S89: % | T89: Jml | U89: % | V89: Jml | W89: %
A90: 1 | B90: COMPLIANCE IN GENERAL (1) | E90: =D90/C90 -> #DIV/0! | G90: =F90/C90 -> #DIV/0! | I90: =H90/C90 -> #DIV/0! | L90: =K90/J90 -> #DIV/0! | N90: =M90/J90 -> #DIV/0! | P90: =O90/J90 -> #DIV/0! | S90: =R90/Q90 -> #DIV/0! | U90: =T90/Q90 -> #DIV/0! | W90: =V90/Q90 -> #DIV/0!
A91: 2 | B91: LABOR & HUMAN RIGHTS (3) | E91: =D91/C91 -> #DIV/0! | G91: =F91/C91 -> #DIV/0! | I91: =H91/C91 -> #DIV/0! | L91: =K91/J91 -> #DIV/0! | N91: =M91/J91 -> #DIV/0! | P91: =O91/J91 -> #DIV/0! | S91: =R91/Q91 -> #DIV/0! | U91: =T91/Q91 -> #DIV/0! | W91: =V91/Q91 -> #DIV/0!
B92: a. HR | E92: =D92/C92 -> #DIV/0! | G92: =F92/C92 -> #DIV/0! | I92: =H92/C92 -> #DIV/0! | L92: =K92/J92 -> #DIV/0! | N92: =M92/J92 -> #DIV/0! | P92: =O92/J92 -> #DIV/0! | S92: =R92/Q92 -> #DIV/0! | U92: =T92/Q92 -> #DIV/0! | W92: =V92/Q92 -> #DIV/0!
B93: b. Expat | E93: =D93/C93 -> #DIV/0! | G93: =F93/C93 -> #DIV/0! | I93: =H93/C93 -> #DIV/0! | L93: =K93/J93 -> #DIV/0! | N93: =M93/J93 -> #DIV/0! | P93: =O93/J93 -> #DIV/0! | S93: =R93/Q93 -> #DIV/0! | U93: =T93/Q93 -> #DIV/0! | W93: =V93/Q93 -> #DIV/0!
B94: c. TRN | E94: =D94/C94 -> #DIV/0! | G94: =F94/C94 -> #DIV/0! | I94: =H94/C94 -> #DIV/0! | L94: =K94/J94 -> #DIV/0! | N94: =M94/J94 -> #DIV/0! | P94: =O94/J94 -> #DIV/0! | S94: =R94/Q94 -> #DIV/0! | U94: =T94/Q94 -> #DIV/0! | W94: =V94/Q94 -> #DIV/0!
A95: 3 | B95: INTELLECTUAL PROPERTY (4) | E95: =D95/C95 -> #DIV/0! | G95: =F95/C95 -> #DIV/0! | I95: =H95/C95 -> #DIV/0! | L95: =K95/J95 -> #DIV/0! | N95: =M95/J95 -> #DIV/0! | P95: =O95/J95 -> #DIV/0! | S95: =R95/Q95 -> #DIV/0! | U95: =T95/Q95 -> #DIV/0! | W95: =V95/Q95 -> #DIV/0!
A96: 4 | B96: FAIR TRADING (5) | E96: =D96/C96 -> #DIV/0! | G96: =F96/C96 -> #DIV/0! | I96: =H96/C96 -> #DIV/0! | L96: =K96/J96 -> #DIV/0! | N96: =M96/J96 -> #DIV/0! | P96: =O96/J96 -> #DIV/0! | S96: =R96/Q96 -> #DIV/0! | U96: =T96/Q96 -> #DIV/0! | W96: =V96/Q96 -> #DIV/0!
A97: 7 | B97: ENVIRONMENT, SAFETY & HEALTH (8) | E97: =D97/C97 -> #DIV/0! | G97: =F97/C97 -> #DIV/0! | I97: =H97/C97 -> #DIV/0! | L97: =K97/J97 -> #DIV/0! | N97: =M97/J97 -> #DIV/0! | P97: =O97/J97 -> #DIV/0! | S97: =R97/Q97 -> #DIV/0! | U97: =T97/Q97 -> #DIV/0! | W97: =V97/Q97 -> #DIV/0!
B98: a. Safety & Health | E98: =D98/C98 -> #DIV/0! | G98: =F98/C98 -> #DIV/0! | I98: =H98/C98 -> #DIV/0! | L98: =K98/J98 -> #DIV/0! | N98: =M98/J98 -> #DIV/0! | P98: =O98/J98 -> #DIV/0! | S98: =R98/Q98 -> #DIV/0! | U98: =T98/Q98 -> #DIV/0! | W98: =V98/Q98 -> #DIV/0!
B99: b. Environment | E99: =D99/C99 -> #DIV/0! | G99: =F99/C99 -> #DIV/0! | I99: =H99/C99 -> #DIV/0! | L99: =K99/J99 -> #DIV/0! | N99: =M99/J99 -> #DIV/0! | P99: =O99/J99 -> #DIV/0! | S99: =R99/Q99 -> #DIV/0! | U99: =T99/Q99 -> #DIV/0! | W99: =V99/Q99 -> #DIV/0!
B100: c. SoC | E100: =D100/C100 -> #DIV/0! | G100: =F100/C100 -> #DIV/0! | I100: =H100/C100 -> #DIV/0! | L100: =K100/J100 -> #DIV/0! | N100: =M100/J100 -> #DIV/0! | P100: =O100/J100 -> #DIV/0! | S100: =R100/Q100 -> #DIV/0! | U100: =T100/Q100 -> #DIV/0! | W100: =V100/Q100 -> #DIV/0!
A101: 6 | B101: COMPANY /BUSINESS OPERATIONS & LICENSE (2) | E101: =D101/C101 -> #DIV/0! | G101: =F101/C101 -> #DIV/0! | I101: =H101/C101 -> #DIV/0! | L101: =K101/J101 -> #DIV/0! | N101: =M101/J101 -> #DIV/0! | P101: =O101/J101 -> #DIV/0! | S101: =R101/Q101 -> #DIV/0! | U101: =T101/Q101 -> #DIV/0! | W101: =V101/Q101 -> #DIV/0!
B102: TOTAL | C102: =C90+C91+C95+C96+C97+C101 -> 0 | D102: =D90+D91+D95+D96+D97+D101 -> 0 | E102: =D102/C102 -> #DIV/0! | F102: =F90+F91+F95+F96+F97+F101 -> 0 | G102: =F102/C102 -> #DIV/0! | H102: =H90+H91+H95+H96+H97+H101 -> 0 | I102: =H102/C102 -> #DIV/0! | J102: =J90+J91+J95+J96+J97+J101 -> 0 | K102: =K90+K91+K95+K96+K97+K101 -> 0 | L102: =K102/J102 -> #DIV/0! | M102: =M90+M91+M95+M96+M97+M101 -> 0 | N102: =M102/J102 -> #DIV/0! | O102: =O90+O91+O95+O96+O97+O101 -> 0 | P102: =O102/J102 -> #DIV/0! | Q102: =Q90+Q91+Q95+Q96+Q97+Q101 -> 0 | R102: =R90+R91+R95+R96+R97+R101 -> 0 | S102: =R102/Q102 -> #DIV/0! | T102: =T90+T91+T95+T96+T97+T101 -> 0 | U102: =T102/Q102 -> #DIV/0! | V102: =V90+V91+V95+V96+V97+V101 -> 0 | W102: =V102/Q102 -> #DIV/0!
A104: 5 | B104: EXIM MANAGEMENT (6) | E104: =D104/C104 -> #DIV/0! | G104: =F104/C104 -> #DIV/0! | I104: =H104/C104 -> #DIV/0! | L104: =K104/J104 -> #DIV/0! | N104: =M104/J104 -> #DIV/0! | P104: =O104/J104 -> #DIV/0! | S104: =R104/Q104 -> #DIV/0! | U104: =T104/Q104 -> #DIV/0! | W104: =V104/Q104 -> #DIV/0!
A105: 8 | B105: ACCOUNTING /FINANCE (7) | E105: =D105/C105 -> #DIV/0! | G105: =F105/C105 -> #DIV/0! | I105: =H105/C105 -> #DIV/0! | L105: =K105/J105 -> #DIV/0! | N105: =M105/J105 -> #DIV/0! | P105: =O105/J105 -> #DIV/0! | S105: =R105/Q105 -> #DIV/0! | U105: =T105/Q105 -> #DIV/0! | W105: =V105/Q105 -> #DIV/0!
B106: TOTAL | C106: =SUM(C104:C105)+C102 -> 0 | D106: =SUM(D104:D105)+D102 -> 0 | E106: =D106/C106 -> #DIV/0! | F106: =SUM(F104:F105)+F102 -> 0 | G106: =F106/C106 -> #DIV/0! | H106: =SUM(H104:H105)+H102 -> 0 | I106: =H106/C106 -> #DIV/0! | J106: =SUM(J104:J105)+J102 -> 0 | K106: =SUM(K104:K105)+K102 -> 0 | L106: =K106/J106 -> #DIV/0! | M106: =SUM(M104:M105)+M102 -> 0 | N106: =M106/J106 -> #DIV/0! | O106: =SUM(O104:O105)+O102 -> 0 | P106: =O106/J106 -> #DIV/0! | Q106: =SUM(Q104:Q105)+Q102 -> 0 | R106: =SUM(R104:R105)+R102 -> 0 | S106: =R106/Q106 -> #DIV/0! | T106: =SUM(T104:T105)+T102 -> 0 | U106: =T106/Q106 -> #DIV/0! | V106: =SUM(V104:V105)+V102 -> 0 | W106: =V106/Q106 -> #DIV/0!

Sheet 83
A2: Now day
A4: NO | B4: BIDANG | C4: NOW DAY
C5: Jml regulasi | D5: Identifikasi | F5: Evaluasi | H5: Implementasi
D6: Jml | E6: % | F6: Jml | G6: % | H6: Jml | I6: %
A7: 1 | B7: COMPLIANCE IN GENERAL (1) | C7: ='Detail COMPLIANCE FIELD'!G15 -> 0 | D7: =C7 -> 0 | E7: 1 | F7: ='Detail COMPLIANCE FIELD'!I15 -> 0 | G7: 1 | H7: ='Detail COMPLIANCE FIELD'!K15 -> 0 | I7: 1
A8: 2 | B8: LABOR & HUMAN RIGHTS (3) | C8: ='Detail COMPLIANCE FIELD'!G17 -> 126 | D8: =C8 -> 126 | E8: =D8/C8 -> 1 | F8: ='Detail COMPLIANCE FIELD'!I17 -> 126 | G8: =F8/C8 -> 1 | H8: ='Detail COMPLIANCE FIELD'!K17 -> 122 | I8: =H8/C8 -> 0.96825397
A9: 3 | B9: INTELLECTUAL PROPERTY (4) | C9: ='Detail COMPLIANCE FIELD'!G18 -> 7 | D9: =C9 -> 7 | E9: =D9/C9 -> 1 | F9: ='Detail COMPLIANCE FIELD'!I18 -> 7 | G9: =F9/C9 -> 1 | H9: ='Detail COMPLIANCE FIELD'!K18 -> 7 | I9: =H9/C9 -> 1
A10: 4 | B10: FAIR TRADING (5) | C10: ='Detail COMPLIANCE FIELD'!G19 -> 6 | D10: =C10 -> 6 | E10: =D10/C10 -> 1 | F10: ='Detail COMPLIANCE FIELD'!I19 -> 6 | G10: =F10/C10 -> 1 | H10: ='Detail COMPLIANCE FIELD'!K19 -> 6 | I10: =H10/C10 -> 1
A11: 5 | B11: ENVIRONMENT, SAFETY & HEALTH (8) | C11: ='Detail COMPLIANCE FIELD'!G22 -> 123 | D11: =C11 -> 123 | E11: =D11/C11 -> 1 | F11: ='Detail COMPLIANCE FIELD'!I22 -> 123 | G11: =F11/C11 -> 1 | H11: ='Detail COMPLIANCE FIELD'!K22 -> 116 | I11: =H11/C11 -> 0.94308943
A12: 6 | B12: COMPANY /BUSINESS OPERATIONS & LICENSE (2) | C12: ='Detail COMPLIANCE FIELD'!G16 -> 99 | D12: =C12 -> 99 | E12: =D12/C12 -> 1 | F12: ='Detail COMPLIANCE FIELD'!I16 -> 99 | G12: =F12/C12 -> 1 | H12: ='Detail COMPLIANCE FIELD'!K16 -> 98 | I12: =H12/C12 -> 0.98989899
B13: TOTAL | C13: =SUM(C7:C12) -> 361 | D13: =SUM(D7:D12) -> 361 | E13: =D13/C13 -> 1 | F13: =SUM(F7:F12) -> 361 | G13: =F13/C13 -> 1 | H13: =SUM(H7:H12) -> 349 | I13: =H13/C13 -> 0.966759
A15: 7 | B15: EXIM MANAGEMENT (6) | C15: ='Detail COMPLIANCE FIELD'!G20 -> 37 | D15: =C15 -> 37 | E15: =D15/C15 -> 1 | F15: ='Detail COMPLIANCE FIELD'!I20 -> 37 | G15: =F15/C15 -> 1 | H15: ='Detail COMPLIANCE FIELD'!K20 -> 37 | I15: =H15/C15 -> 1
A16: 8 | B16: ACCOUNTING /FINANCE (7) | C16: ='Detail COMPLIANCE FIELD'!G21 -> 56 | D16: =C16 -> 56 | E16: =D16/C16 -> 1 | F16: ='Detail COMPLIANCE FIELD'!I21 -> 56 | G16: =F16/C16 -> 1 | H16: ='Detail COMPLIANCE FIELD'!K21 -> 56 | I16: =H16/C16 -> 1
B17: TOTAL | C17: =SUM(C15:C16)+C13 -> 454 | D17: =SUM(D15:D16)+D13 -> 454 | E17: =D17/C17 -> 1 | F17: =SUM(F15:F16)+F13 -> 454 | G17: =F17/C17 -> 1 | H17: =SUM(H15:H16)+H13 -> 442 | I17: =H17/C17 -> 0.97356828
A18: PT. SEMARANG AUTOCOMP MANUFACTURING INDONESIA
A19: KEPATUHAN TERHADAP PERATURAN PERUNDANGAN
A21: NO | B21: BIDANG | C21: 45108 | J21: 45139 | Q21: 45170
C22: Jml regulasi | D22: Identifikasi | F22: Evaluasi | H22: Implementasi | J22: Jml regulasi | K22: Identifikasi | M22: Evaluasi | O22: Implementasi | Q22: Jml regulasi | R22: Identifikasi | T22: Evaluasi | V22: Implementasi
D23: Jml | E23: % | F23: Jml | G23: % | H23: Jml | I23: % | K23: Jml | L23: % | M23: Jml | N23: % | O23: Jml | P23: % | R23: Jml | S23: % | T23: Jml | U23: % | V23: Jml | W23: %
A24: 1 | B24: COMPLIANCE IN GENERAL (1) | C24: 0 | D24: 0 | E24: #DIV/0! | F24: 0 | G24: #DIV/0! | H24: 0 | I24: #DIV/0! | J24: 0 | K24: 0 | L24: #DIV/0! | M24: 0 | N24: #DIV/0! | O24: 0 | P24: #DIV/0! | S24: =R24/Q24 -> #DIV/0! | U24: =T24/Q24 -> #DIV/0! | W24: =V24/Q24 -> #DIV/0!
A25: 2 | B25: LABOR & HUMAN RIGHTS (3) | C25: 106 | D25: 106 | E25: 1 | F25: 103 | G25: 1 | H25: 95 | I25: 0.91463415 | J25: 107 | K25: 107 | L25: 1 | M25: 103 | N25: 1 | O25: 95 | P25: 0.91463415 | S25: =R25/Q25 -> #DIV/0! | U25: =T25/Q25 -> #DIV/0! | W25: =V25/Q25 -> #DIV/0!
B26: a. HR | C26: 60 | D26: 60 | E26: 1 | F26: 59 | G26: 1 | H26: 57 | I26: 0.94 | J26: 60 | K26: 60 | L26: 1 | M26: 59 | N26: 1 | O26: 57 | P26: 0.94 | S26: =R26/Q26 -> #DIV/0! | U26: =T26/Q26 -> #DIV/0! | W26: =V26/Q26 -> #DIV/0!
B27: b. Expat | C27: 45 | D27: 45 | E27: 1 | F27: 43 | G27: 1 | H27: 37 | I27: 0.87096774 | J27: 46 | K27: 46 | L27: 1 | M27: 43 | N27: 1 | O27: 37 | P27: 0.87096774 | S27: =R27/Q27 -> #DIV/0! | U27: =T27/Q27 -> #DIV/0! | W27: =V27/Q27 -> #DIV/0!
B28: c. TRN | C28: 1 | D28: 1 | E28: 1 | F28: 1 | G28: 1 | H28: 1 | I28: 1 | J28: 1 | K28: 1 | L28: 1 | M28: 1 | N28: 1 | O28: 1 | P28: 1 | S28: =R28/Q28 -> #DIV/0! | U28: =T28/Q28 -> #DIV/0! | W28: =V28/Q28 -> #DIV/0!
A29: 3 | B29: INTELLECTUAL PROPERTY (4) | C29: 5 | D29: 5 | E29: 1 | F29: 5 | G29: 1 | H29: 5 | I29: 1 | J29: 5 | K29: 5 | L29: =K29/J29 -> 1 | M29: 5 | N29: =M29/J29 -> 1 | O29: 5 | P29: =O29/J29 -> 1 | S29: =R29/Q29 -> #DIV/0! | U29: =T29/Q29 -> #DIV/0! | W29: =V29/Q29 -> #DIV/0!
A30: 4 | B30: FAIR TRADING (5) | C30: 6 | D30: 6 | E30: 1 | F30: 6 | G30: 1 | H30: 6 | I30: 1 | J30: 6 | K30: 6 | L30: =K30/J30 -> 1 | M30: 6 | N30: =M30/J30 -> 1 | O30: 6 | P30: =O30/J30 -> 1 | S30: =R30/Q30 -> #DIV/0! | U30: =T30/Q30 -> #DIV/0! | W30: =V30/Q30 -> #DIV/0!
A31: 6 | B31: ENVIRONMENT, SAFETY & HEALTH (8) | C31: 111 | D31: 111 | E31: 1 | F31: 111 | G31: 1 | H31: 104 | I31: 0.91346154 | J31: 113 | K31: 113 | L31: 1 | M31: 111 | N31: 1 | O31: 104 | P31: 0.91346154 | S31: 1 | U31: 1 | W31: 0.91346154
B32: a. Safety & Health | C32: 41 | D32: 41 | E32: 1 | F32: 41 | G32: 1 | H32: 37 | I32: 0.86486486 | J32: 41 | K32: 41 | L32: 1 | M32: 41 | N32: 1 | O32: 37 | P32: 0.86486486 | S32: 1 | U32: 1 | W32: 0.86486486
B33: b. Environment | C33: 60 | D33: 60 | E33: 1 | F33: 60 | G33: 1 | H33: 57 | I33: 0.92982456 | J33: 62 | K33: 62 | L33: 1 | M33: 60 | N33: 1 | O33: 57 | P33: 0.92982456 | S33: 1 | U33: 1 | W33: 0.92982456
B34: c. SoC | C34: 10 | D34: 10 | E34: 1 | F34: 10 | G34: 1 | H34: 10 | I34: 1 | J34: 10 | K34: 10 | L34: 1 | M34: 10 | N34: 1 | O34: 10 | P34: 1 | S34: 1 | U34: 1 | W34: 1
A35: 7 | B35: COMPANY /BUSINESS OPERATIONS & LICENSE (2) | C35: 91 | D35: 91 | E35: 1 | F35: 89 | G35: 1 | H35: 89 | I35: 0.89873418 | J35: 91 | K35: 91 | L35: 1 | M35: 89 | N35: 1 | O35: 89 | P35: 0.89873418 | S35: =R35/Q35 -> #DIV/0! | U35: =T35/Q35 -> #DIV/0! | W35: =V35/Q35 -> #DIV/0!
B36: TOTAL | C36: =C24+C25+C29+C30+C31+C35 -> 319 | D36: =D24+D25+D29+D30+D31+D35 -> 319 | E36: =D36/C36 -> 1 | F36: =F24+F25+F29+F30+F31+F35 -> 314 | G36: =F36/C36 -> 0.98432602 | H36: =H24+H25+H29+H30+H31+H35 -> 299 | I36: =H36/C36 -> 0.93730408 | J36: =J24+J25+J29+J30+J31+J35 -> 322 | K36: =K24+K25+K29+K30+K31+K35 -> 322 | L36: =K36/J36 -> 1 | M36: =M24+M25+M29+M30+M31+M35 -> 314 | N36: =M36/J36 -> 0.97515528 | O36: =O24+O25+O29+O30+O31+O35 -> 299 | P36: =O36/J36 -> 0.92857143 | Q36: =Q24+Q25+Q29+Q30+Q31+Q35 -> 0 | R36: =R24+R25+R29+R30+R31+R35 -> 0 | S36: =R36/Q36 -> #DIV/0! | T36: =T24+T25+T29+T30+T31+T35 -> 0 | U36: =T36/Q36 -> #DIV/0! | V36: =V24+V25+V29+V30+V31+V35 -> 0 | W36: =V36/Q36 -> #DIV/0!
A38: 5 | B38: EXIM MANAGEMENT (6) | C38: 23 | D38: 23 | E38: 1 | F38: 19 | G38: 0.94736842 | H38: 19 | I38: 0.94736842 | J38: 23 | K38: 23 | L38: 1 | M38: 19 | N38: 0.94736842 | O38: 19 | P38: 0.94736842 | S38: =R38/Q38 -> #DIV/0! | U38: =T38/Q38 -> #DIV/0! | W38: =V38/Q38 -> #DIV/0!
A39: 8 | B39: ACCOUNTING /FINANCE (7) | C39: 44 | D39: 44 | E39: 1 | F39: 38 | G39: 0.97222222 | H39: 38 | I39: 0.97222222 | J39: 44 | K39: 44 | L39: 1 | M39: 38 | N39: 0.97222222 | O39: 38 | P39: 0.97222222 | S39: =R39/Q39 -> #DIV/0! | U39: =T39/Q39 -> #DIV/0! | W39: =V39/Q39 -> #DIV/0!
B40: TOTAL | C40: =SUM(C38:C39)+C36 -> 386 | D40: =SUM(D38:D39)+D36 -> 386 | E40: =D40/C40 -> 1 | F40: =SUM(F38:F39)+F36 -> 371 | G40: =F40/C40 -> 0.9611399 | H40: =SUM(H38:H39)+H36 -> 356 | I40: =H40/C40 -> 0.92227979 | J40: =SUM(J38:J39)+J36 -> 389 | K40: =SUM(K38:K39)+K36 -> 389 | L40: =K40/J40 -> 1 | M40: =SUM(M38:M39)+M36 -> 371 | N40: =M40/J40 -> 0.95372751 | O40: =SUM(O38:O39)+O36 -> 356 | P40: =O40/J40 -> 0.9151671 | Q40: =SUM(Q38:Q39)+Q36 -> 0 | R40: =SUM(R38:R39)+R36 -> 0 | S40: =R40/Q40 -> #DIV/0! | T40: =SUM(T38:T39)+T36 -> 0 | U40: =T40/Q40 -> #DIV/0! | V40: =SUM(V38:V39)+V36 -> 0 | W40: =V40/Q40 -> #DIV/0!
A43: NO | B43: BIDANG | C43: 45200 | J43: 45231 | Q43: 45261
C44: Jml regulasi | D44: Identifikasi | F44: Evaluasi | H44: Implementasi | J44: Jml regulasi | K44: Identifikasi | M44: Evaluasi | O44: Implementasi | Q44: Jml regulasi | R44: Identifikasi | T44: Evaluasi | V44: Implementasi
D45: Jml | E45: % | F45: Jml | G45: % | H45: Jml | I45: % | K45: Jml | L45: % | M45: Jml | N45: % | O45: Jml | P45: % | R45: Jml | S45: % | T45: Jml | U45: % | V45: Jml | W45: %
A46: 1 | B46: COMPLIANCE IN GENERAL (1) | E46: #DIV/0! | G46: #DIV/0! | I46: #DIV/0! | L46: #DIV/0! | N46: #DIV/0! | P46: #DIV/0! | S46: =R46/Q46 -> #DIV/0! | U46: =T46/Q46 -> #DIV/0! | W46: =V46/Q46 -> #DIV/0!
A47: 2 | B47: LABOR & HUMAN RIGHTS (3) | E47: =D47/C47 -> #DIV/0! | G47: =F47/C47 -> #DIV/0! | I47: =H47/C47 -> #DIV/0! | L47: =K47/J47 -> #DIV/0! | N47: =M47/J47 -> #DIV/0! | P47: =O47/J47 -> #DIV/0! | S47: =R47/Q47 -> #DIV/0! | U47: =T47/Q47 -> #DIV/0! | W47: =V47/Q47 -> #DIV/0!
B48: a. HR | E48: =D48/C48 -> #DIV/0! | G48: =F48/C48 -> #DIV/0! | I48: =H48/C48 -> #DIV/0! | L48: =K48/J48 -> #DIV/0! | N48: =M48/J48 -> #DIV/0! | P48: =O48/J48 -> #DIV/0! | S48: =R48/Q48 -> #DIV/0! | U48: =T48/Q48 -> #DIV/0! | W48: =V48/Q48 -> #DIV/0!
B49: b. Expat | E49: =D49/C49 -> #DIV/0! | G49: =F49/C49 -> #DIV/0! | I49: =H49/C49 -> #DIV/0! | L49: =K49/J49 -> #DIV/0! | N49: =M49/J49 -> #DIV/0! | P49: =O49/J49 -> #DIV/0! | S49: =R49/Q49 -> #DIV/0! | U49: =T49/Q49 -> #DIV/0! | W49: =V49/Q49 -> #DIV/0!
B50: c. TRN | E50: =D50/C50 -> #DIV/0! | G50: =F50/C50 -> #DIV/0! | I50: =H50/C50 -> #DIV/0! | L50: =K50/J50 -> #DIV/0! | N50: =M50/J50 -> #DIV/0! | P50: =O50/J50 -> #DIV/0! | S50: =R50/Q50 -> #DIV/0! | U50: =T50/Q50 -> #DIV/0! | W50: =V50/Q50 -> #DIV/0!
A51: 3 | B51: INTELLECTUAL PROPERTY (4) | E51: =D51/C51 -> #DIV/0! | G51: =F51/C51 -> #DIV/0! | I51: =H51/C51 -> #DIV/0! | L51: =K51/J51 -> #DIV/0! | N51: =M51/J51 -> #DIV/0! | P51: =O51/J51 -> #DIV/0! | S51: =R51/Q51 -> #DIV/0! | U51: =T51/Q51 -> #DIV/0! | W51: =V51/Q51 -> #DIV/0!
A52: 7 | B52: FAIR TRADING (5) | E52: =D52/C52 -> #DIV/0! | G52: =F52/C52 -> #DIV/0! | I52: =H52/C52 -> #DIV/0! | L52: =K52/J52 -> #DIV/0! | N52: =M52/J52 -> #DIV/0! | P52: =O52/J52 -> #DIV/0! | S52: =R52/Q52 -> #DIV/0! | U52: =T52/Q52 -> #DIV/0! | W52: =V52/Q52 -> #DIV/0!
A53: 4 | B53: ENVIRONMENT, SAFETY & HEALTH (8) | E53: =D53/C53 -> #DIV/0! | G53: =F53/C53 -> #DIV/0! | I53: =H53/C53 -> #DIV/0! | L53: =K53/J53 -> #DIV/0! | N53: =M53/J53 -> #DIV/0! | P53: =O53/J53 -> #DIV/0! | S53: =R53/Q53 -> #DIV/0! | U53: =T53/Q53 -> #DIV/0! | W53: =V53/Q53 -> #DIV/0!
B54: a. Safety & Health | E54: =D54/C54 -> #DIV/0! | G54: =F54/C54 -> #DIV/0! | I54: =H54/C54 -> #DIV/0! | L54: =K54/J54 -> #DIV/0! | N54: =M54/J54 -> #DIV/0! | P54: =O54/J54 -> #DIV/0! | S54: =R54/Q54 -> #DIV/0! | U54: =T54/Q54 -> #DIV/0! | W54: =V54/Q54 -> #DIV/0!
B55: b. Environment | E55: =D55/C55 -> #DIV/0! | G55: =F55/C55 -> #DIV/0! | I55: =H55/C55 -> #DIV/0! | L55: =K55/J55 -> #DIV/0! | N55: =M55/J55 -> #DIV/0! | P55: =O55/J55 -> #DIV/0! | S55: =R55/Q55 -> #DIV/0! | U55: =T55/Q55 -> #DIV/0! | W55: =V55/Q55 -> #DIV/0!
B56: c. SoC | E56: 1 | G56: 1 | I56: 1 | L56: 1 | N56: 1 | P56: 1 | S56: =R56/Q56 -> #DIV/0! | U56: =T56/Q56 -> #DIV/0! | W56: =V56/Q56 -> #DIV/0!
A57: 6 | B57: COMPANY /BUSINESS OPERATIONS & LICENSE (2) | E57: =D57/C57 -> #DIV/0! | G57: =F57/C57 -> #DIV/0! | I57: =H57/C57 -> #DIV/0! | L57: =K57/J57 -> #DIV/0! | N57: =M57/J57 -> #DIV/0! | P57: =O57/J57 -> #DIV/0! | S57: =R57/Q57 -> #DIV/0! | U57: =T57/Q57 -> #DIV/0! | W57: =V57/Q57 -> #DIV/0!
B58: TOTAL | C58: =C46+C47+C51+C52+C53+C57 -> 0 | D58: =D46+D47+D51+D52+D53+D57 -> 0 | E58: =D58/C58 -> #DIV/0! | F58: =F46+F47+F51+F52+F53+F57 -> 0 | G58: =F58/C58 -> #DIV/0! | H58: =H46+H47+H51+H52+H53+H57 -> 0 | I58: =H58/C58 -> #DIV/0! | J58: =J46+J47+J51+J52+J53+J57 -> 0 | K58: =K46+K47+K51+K52+K53+K57 -> 0 | L58: =K58/J58 -> #DIV/0! | M58: =M46+M47+M51+M52+M53+M57 -> 0 | N58: =M58/J58 -> #DIV/0! | O58: =O46+O47+O51+O52+O53+O57 -> 0 | P58: =O58/J58 -> #DIV/0! | Q58: =Q46+Q47+Q51+Q52+Q53+Q57 -> 0 | R58: =R46+R47+R51+R52+R53+R57 -> 0 | S58: =R58/Q58 -> #DIV/0! | T58: =T46+T47+T51+T52+T53+T57 -> 0 | U58: =T58/Q58 -> #DIV/0! | V58: =V46+V47+V51+V52+V53+V57 -> 0 | W58: =V58/Q58 -> #DIV/0!
A60: 5 | B60: EXIM MANAGEMENT (6) | E60: =D60/C60 -> #DIV/0! | G60: =F60/C60 -> #DIV/0! | I60: =H60/C60 -> #DIV/0! | L60: =K60/J60 -> #DIV/0! | N60: =M60/J60 -> #DIV/0! | P60: =O60/J60 -> #DIV/0! | S60: =R60/Q60 -> #DIV/0! | U60: =T60/Q60 -> #DIV/0! | W60: =V60/Q60 -> #DIV/0!
A61: 8 | B61: ACCOUNTING /FINANCE (7) | E61: =D61/C61 -> #DIV/0! | G61: =F61/C61 -> #DIV/0! | I61: =H61/C61 -> #DIV/0! | L61: =K61/J61 -> #DIV/0! | N61: =M61/J61 -> #DIV/0! | P61: =O61/J61 -> #DIV/0! | S61: =R61/Q61 -> #DIV/0! | U61: =T61/Q61 -> #DIV/0! | W61: =V61/Q61 -> #DIV/0!
B62: TOTAL | C62: =SUM(C60:C61)+C58 -> 0 | D62: =SUM(D60:D61)+D58 -> 0 | E62: =D62/C62 -> #DIV/0! | F62: =SUM(F60:F61)+F58 -> 0 | G62: =F62/C62 -> #DIV/0! | H62: =SUM(H60:H61)+H58 -> 0 | I62: =H62/C62 -> #DIV/0! | J62: =SUM(J60:J61)+J58 -> 0 | K62: =SUM(K60:K61)+K58 -> 0 | L62: =K62/J62 -> #DIV/0! | M62: =SUM(M60:M61)+M58 -> 0 | N62: =M62/J62 -> #DIV/0! | O62: =SUM(O60:O61)+O58 -> 0 | P62: =O62/J62 -> #DIV/0! | Q62: =SUM(Q60:Q61)+Q58 -> 0 | R62: =SUM(R60:R61)+R58 -> 0 | S62: =R62/Q62 -> #DIV/0! | T62: =SUM(T60:T61)+T58 -> 0 | U62: =T62/Q62 -> #DIV/0! | V62: =SUM(V60:V61)+V58 -> 0 | W62: =V62/Q62 -> #DIV/0!
A65: NO | B65: BIDANG | C65: 45292 | J65: 45323 | Q65: 45352
C66: Jml regulasi | D66: Identifikasi | F66: Evaluasi | H66: Implementasi | J66: Jml regulasi | K66: Identifikasi | M66: Evaluasi | O66: Implementasi | Q66: Jml regulasi | R66: Identifikasi | T66: Evaluasi | V66: Implementasi
D67: Jml | E67: % | F67: Jml | G67: % | H67: Jml | I67: % | K67: Jml | L67: % | M67: Jml | N67: % | O67: Jml | P67: % | R67: Jml | S67: % | T67: Jml | U67: % | V67: Jml | W67: %
A68: 1 | B68: COMPLIANCE IN GENERAL (1) | E68: =D68/C68 -> #DIV/0! | G68: =F68/C68 -> #DIV/0! | I68: =H68/C68 -> #DIV/0! | L68: =K68/J68 -> #DIV/0! | N68: =M68/J68 -> #DIV/0! | P68: =O68/J68 -> #DIV/0! | S68: =R68/Q68 -> #DIV/0! | U68: =T68/Q68 -> #DIV/0! | W68: =V68/Q68 -> #DIV/0!
A69: 2 | B69: LABOR & HUMAN RIGHTS (3) | E69: =D69/C69 -> #DIV/0! | G69: =F69/C69 -> #DIV/0! | I69: =H69/C69 -> #DIV/0! | L69: =K69/J69 -> #DIV/0! | N69: =M69/J69 -> #DIV/0! | P69: =O69/J69 -> #DIV/0! | S69: =R69/Q69 -> #DIV/0! | U69: =T69/Q69 -> #DIV/0! | W69: =V69/Q69 -> #DIV/0!
B70: a. HR | E70: =D70/C70 -> #DIV/0! | G70: =F70/C70 -> #DIV/0! | I70: =H70/C70 -> #DIV/0! | L70: =K70/J70 -> #DIV/0! | N70: =M70/J70 -> #DIV/0! | P70: =O70/J70 -> #DIV/0! | S70: =R70/Q70 -> #DIV/0! | U70: =T70/Q70 -> #DIV/0! | W70: =V70/Q70 -> #DIV/0!
B71: b. Expat | E71: =D71/C71 -> #DIV/0! | G71: =F71/C71 -> #DIV/0! | I71: =H71/C71 -> #DIV/0! | L71: =K71/J71 -> #DIV/0! | N71: =M71/J71 -> #DIV/0! | P71: =O71/J71 -> #DIV/0! | S71: =R71/Q71 -> #DIV/0! | U71: =T71/Q71 -> #DIV/0! | W71: =V71/Q71 -> #DIV/0!
B72: c. TRN | E72: =D72/C72 -> #DIV/0! | G72: =F72/C72 -> #DIV/0! | I72: =H72/C72 -> #DIV/0! | L72: =K72/J72 -> #DIV/0! | N72: =M72/J72 -> #DIV/0! | P72: =O72/J72 -> #DIV/0! | S72: =R72/Q72 -> #DIV/0! | U72: =T72/Q72 -> #DIV/0! | W72: =V72/Q72 -> #DIV/0!
A73: 3 | B73: INTELLECTUAL PROPERTY (4) | E73: =D73/C73 -> #DIV/0! | G73: =F73/C73 -> #DIV/0! | I73: =H73/C73 -> #DIV/0! | L73: =K73/J73 -> #DIV/0! | N73: =M73/J73 -> #DIV/0! | P73: =O73/J73 -> #DIV/0! | S73: =R73/Q73 -> #DIV/0! | U73: =T73/Q73 -> #DIV/0! | W73: =V73/Q73 -> #DIV/0!
A74: 4 | B74: FAIR TRADING (5) | E74: =D74/C74 -> #DIV/0! | G74: =F74/C74 -> #DIV/0! | I74: =H74/C74 -> #DIV/0! | L74: =K74/J74 -> #DIV/0! | N74: =M74/J74 -> #DIV/0! | P74: =O74/J74 -> #DIV/0! | S74: =R74/Q74 -> #DIV/0! | U74: =T74/Q74 -> #DIV/0! | W74: =V74/Q74 -> #DIV/0!
A75: 7 | B75: ENVIRONMENT, SAFETY & HEALTH (8) | E75: =D75/C75 -> #DIV/0! | G75: =F75/C75 -> #DIV/0! | I75: =H75/C75 -> #DIV/0! | L75: =K75/J75 -> #DIV/0! | N75: =M75/J75 -> #DIV/0! | P75: =O75/J75 -> #DIV/0! | S75: =R75/Q75 -> #DIV/0! | U75: =T75/Q75 -> #DIV/0! | W75: =V75/Q75 -> #DIV/0!
B76: a. Safety & Health | E76: =D76/C76 -> #DIV/0! | G76: =F76/C76 -> #DIV/0! | I76: =H76/C76 -> #DIV/0! | L76: =K76/J76 -> #DIV/0! | N76: =M76/J76 -> #DIV/0! | P76: =O76/J76 -> #DIV/0! | S76: =R76/Q76 -> #DIV/0! | U76: =T76/Q76 -> #DIV/0! | W76: =V76/Q76 -> #DIV/0!
B77: b. Environment | E77: =D77/C77 -> #DIV/0! | G77: =F77/C77 -> #DIV/0! | I77: =H77/C77 -> #DIV/0! | L77: =K77/J77 -> #DIV/0! | N77: =M77/J77 -> #DIV/0! | P77: =O77/J77 -> #DIV/0! | S77: =R77/Q77 -> #DIV/0! | U77: =T77/Q77 -> #DIV/0! | W77: =V77/Q77 -> #DIV/0!
B78: c. SoC | E78: =D78/C78 -> #DIV/0! | G78: =F78/C78 -> #DIV/0! | I78: =H78/C78 -> #DIV/0! | L78: =K78/J78 -> #DIV/0! | N78: =M78/J78 -> #DIV/0! | P78: =O78/J78 -> #DIV/0! | S78: =R78/Q78 -> #DIV/0! | U78: =T78/Q78 -> #DIV/0! | W78: =V78/Q78 -> #DIV/0!
A79: 6 | B79: COMPANY /BUSINESS OPERATIONS & LICENSE (2) | E79: =D79/C79 -> #DIV/0! | G79: =F79/C79 -> #DIV/0! | I79: =H79/C79 -> #DIV/0! | L79: =K79/J79 -> #DIV/0! | N79: =M79/J79 -> #DIV/0! | P79: =O79/J79 -> #DIV/0! | S79: =R79/Q79 -> #DIV/0! | U79: =T79/Q79 -> #DIV/0! | W79: =V79/Q79 -> #DIV/0!
B80: TOTAL | C80: =C68+C69+C73+C74+C75+C79 -> 0 | D80: =D68+D69+D73+D74+D75+D79 -> 0 | E80: =D80/C80 -> #DIV/0! | F80: =F68+F69+F73+F74+F75+F79 -> 0 | G80: =F80/C80 -> #DIV/0! | H80: =H68+H69+H73+H74+H75+H79 -> 0 | I80: =H80/C80 -> #DIV/0! | J80: =J68+J69+J73+J74+J75+J79 -> 0 | K80: =K68+K69+K73+K74+K75+K79 -> 0 | L80: =K80/J80 -> #DIV/0! | M80: =M68+M69+M73+M74+M75+M79 -> 0 | N80: =M80/J80 -> #DIV/0! | O80: =O68+O69+O73+O74+O75+O79 -> 0 | P80: =O80/J80 -> #DIV/0! | Q80: =Q68+Q69+Q73+Q74+Q75+Q79 -> 0 | R80: =R68+R69+R73+R74+R75+R79 -> 0 | S80: =R80/Q80 -> #DIV/0! | T80: =T68+T69+T73+T74+T75+T79 -> 0 | U80: =T80/Q80 -> #DIV/0! | V80: =V68+V69+V73+V74+V75+V79 -> 0 | W80: =V80/Q80 -> #DIV/0!
A82: 5 | B82: EXIM MANAGEMENT (6) | E82: =D82/C82 -> #DIV/0! | G82: =F82/C82 -> #DIV/0! | I82: =H82/C82 -> #DIV/0! | L82: =K82/J82 -> #DIV/0! | N82: =M82/J82 -> #DIV/0! | P82: =O82/J82 -> #DIV/0! | S82: =R82/Q82 -> #DIV/0! | U82: =T82/Q82 -> #DIV/0! | W82: =V82/Q82 -> #DIV/0!
A83: 8 | B83: ACCOUNTING /FINANCE (7) | E83: =D83/C83 -> #DIV/0! | G83: =F83/C83 -> #DIV/0! | I83: =H83/C83 -> #DIV/0! | L83: =K83/J83 -> #DIV/0! | N83: =M83/J83 -> #DIV/0! | P83: =O83/J83 -> #DIV/0! | S83: =R83/Q83 -> #DIV/0! | U83: =T83/Q83 -> #DIV/0! | W83: =V83/Q83 -> #DIV/0!
B84: TOTAL | C84: =SUM(C82:C83)+C80 -> 0 | D84: =SUM(D82:D83)+D80 -> 0 | E84: =D84/C84 -> #DIV/0! | F84: =SUM(F82:F83)+F80 -> 0 | G84: =F84/C84 -> #DIV/0! | H84: =SUM(H82:H83)+H80 -> 0 | I84: =H84/C84 -> #DIV/0! | J84: =SUM(J82:J83)+J80 -> 0 | K84: =SUM(K82:K83)+K80 -> 0 | L84: =K84/J84 -> #DIV/0! | M84: =SUM(M82:M83)+M80 -> 0 | N84: =M84/J84 -> #DIV/0! | O84: =SUM(O82:O83)+O80 -> 0 | P84: =O84/J84 -> #DIV/0! | Q84: =SUM(Q82:Q83)+Q80 -> 0 | R84: =SUM(R82:R83)+R80 -> 0 | S84: =R84/Q84 -> #DIV/0! | T84: =SUM(T82:T83)+T80 -> 0 | U84: =T84/Q84 -> #DIV/0! | V84: =SUM(V82:V83)+V80 -> 0 | W84: =V84/Q84 -> #DIV/0!
A87: NO | B87: BIDANG | C87: 45383 | J87: 45413 | Q87: 45444
C88: Jml regulasi | D88: Identifikasi | F88: Evaluasi | H88: Implementasi | J88: Jml regulasi | K88: Identifikasi | M88: Evaluasi | O88: Implementasi | Q88: Jml regulasi | R88: Identifikasi | T88: Evaluasi | V88: Implementasi
D89: Jml | E89: % | F89: Jml | G89: % | H89: Jml | I89: % | K89: Jml | L89: % | M89: Jml | N89: % | O89: Jml | P89: % | R89: Jml | S89: % | T89: Jml | U89: % | V89: Jml | W89: %
A90: 1 | B90: COMPLIANCE IN GENERAL (1) | E90: =D90/C90 -> #DIV/0! | G90: =F90/C90 -> #DIV/0! | I90: =H90/C90 -> #DIV/0! | L90: =K90/J90 -> #DIV/0! | N90: =M90/J90 -> #DIV/0! | P90: =O90/J90 -> #DIV/0! | S90: =R90/Q90 -> #DIV/0! | U90: =T90/Q90 -> #DIV/0! | W90: =V90/Q90 -> #DIV/0!
A91: 2 | B91: LABOR & HUMAN RIGHTS (3) | E91: =D91/C91 -> #DIV/0! | G91: =F91/C91 -> #DIV/0! | I91: =H91/C91 -> #DIV/0! | L91: =K91/J91 -> #DIV/0! | N91: =M91/J91 -> #DIV/0! | P91: =O91/J91 -> #DIV/0! | S91: =R91/Q91 -> #DIV/0! | U91: =T91/Q91 -> #DIV/0! | W91: =V91/Q91 -> #DIV/0!
B92: a. HR | E92: =D92/C92 -> #DIV/0! | G92: =F92/C92 -> #DIV/0! | I92: =H92/C92 -> #DIV/0! | L92: =K92/J92 -> #DIV/0! | N92: =M92/J92 -> #DIV/0! | P92: =O92/J92 -> #DIV/0! | S92: =R92/Q92 -> #DIV/0! | U92: =T92/Q92 -> #DIV/0! | W92: =V92/Q92 -> #DIV/0!
B93: b. Expat | E93: =D93/C93 -> #DIV/0! | G93: =F93/C93 -> #DIV/0! | I93: =H93/C93 -> #DIV/0! | L93: =K93/J93 -> #DIV/0! | N93: =M93/J93 -> #DIV/0! | P93: =O93/J93 -> #DIV/0! | S93: =R93/Q93 -> #DIV/0! | U93: =T93/Q93 -> #DIV/0! | W93: =V93/Q93 -> #DIV/0!
B94: c. TRN | E94: =D94/C94 -> #DIV/0! | G94: =F94/C94 -> #DIV/0! | I94: =H94/C94 -> #DIV/0! | L94: =K94/J94 -> #DIV/0! | N94: =M94/J94 -> #DIV/0! | P94: =O94/J94 -> #DIV/0! | S94: =R94/Q94 -> #DIV/0! | U94: =T94/Q94 -> #DIV/0! | W94: =V94/Q94 -> #DIV/0!
A95: 3 | B95: INTELLECTUAL PROPERTY (4) | E95: =D95/C95 -> #DIV/0! | G95: =F95/C95 -> #DIV/0! | I95: =H95/C95 -> #DIV/0! | L95: =K95/J95 -> #DIV/0! | N95: =M95/J95 -> #DIV/0! | P95: =O95/J95 -> #DIV/0! | S95: =R95/Q95 -> #DIV/0! | U95: =T95/Q95 -> #DIV/0! | W95: =V95/Q95 -> #DIV/0!
A96: 4 | B96: FAIR TRADING (5) | E96: =D96/C96 -> #DIV/0! | G96: =F96/C96 -> #DIV/0! | I96: =H96/C96 -> #DIV/0! | L96: =K96/J96 -> #DIV/0! | N96: =M96/J96 -> #DIV/0! | P96: =O96/J96 -> #DIV/0! | S96: =R96/Q96 -> #DIV/0! | U96: =T96/Q96 -> #DIV/0! | W96: =V96/Q96 -> #DIV/0!
A97: 7 | B97: ENVIRONMENT, SAFETY & HEALTH (8) | E97: =D97/C97 -> #DIV/0! | G97: =F97/C97 -> #DIV/0! | I97: =H97/C97 -> #DIV/0! | L97: =K97/J97 -> #DIV/0! | N97: =M97/J97 -> #DIV/0! | P97: =O97/J97 -> #DIV/0! | S97: =R97/Q97 -> #DIV/0! | U97: =T97/Q97 -> #DIV/0! | W97: =V97/Q97 -> #DIV/0!
B98: a. Safety & Health | E98: =D98/C98 -> #DIV/0! | G98: =F98/C98 -> #DIV/0! | I98: =H98/C98 -> #DIV/0! | L98: =K98/J98 -> #DIV/0! | N98: =M98/J98 -> #DIV/0! | P98: =O98/J98 -> #DIV/0! | S98: =R98/Q98 -> #DIV/0! | U98: =T98/Q98 -> #DIV/0! | W98: =V98/Q98 -> #DIV/0!
B99: b. Environment | E99: =D99/C99 -> #DIV/0! | G99: =F99/C99 -> #DIV/0! | I99: =H99/C99 -> #DIV/0! | L99: =K99/J99 -> #DIV/0! | N99: =M99/J99 -> #DIV/0! | P99: =O99/J99 -> #DIV/0! | S99: =R99/Q99 -> #DIV/0! | U99: =T99/Q99 -> #DIV/0! | W99: =V99/Q99 -> #DIV/0!
B100: c. SoC | E100: =D100/C100 -> #DIV/0! | G100: =F100/C100 -> #DIV/0! | I100: =H100/C100 -> #DIV/0! | L100: =K100/J100 -> #DIV/0! | N100: =M100/J100 -> #DIV/0! | P100: =O100/J100 -> #DIV/0! | S100: =R100/Q100 -> #DIV/0! | U100: =T100/Q100 -> #DIV/0! | W100: =V100/Q100 -> #DIV/0!
A101: 6 | B101: COMPANY /BUSINESS OPERATIONS & LICENSE (2) | E101: =D101/C101 -> #DIV/0! | G101: =F101/C101 -> #DIV/0! | I101: =H101/C101 -> #DIV/0! | L101: =K101/J101 -> #DIV/0! | N101: =M101/J101 -> #DIV/0! | P101: =O101/J101 -> #DIV/0! | S101: =R101/Q101 -> #DIV/0! | U101: =T101/Q101 -> #DIV/0! | W101: =V101/Q101 -> #DIV/0!
B102: TOTAL | C102: =C90+C91+C95+C96+C97+C101 -> 0 | D102: =D90+D91+D95+D96+D97+D101 -> 0 | E102: =D102/C102 -> #DIV/0! | F102: =F90+F91+F95+F96+F97+F101 -> 0 | G102: =F102/C102 -> #DIV/0! | H102: =H90+H91+H95+H96+H97+H101 -> 0 | I102: =H102/C102 -> #DIV/0! | J102: =J90+J91+J95+J96+J97+J101 -> 0 | K102: =K90+K91+K95+K96+K97+K101 -> 0 | L102: =K102/J102 -> #DIV/0! | M102: =M90+M91+M95+M96+M97+M101 -> 0 | N102: =M102/J102 -> #DIV/0! | O102: =O90+O91+O95+O96+O97+O101 -> 0 | P102: =O102/J102 -> #DIV/0! | Q102: =Q90+Q91+Q95+Q96+Q97+Q101 -> 0 | R102: =R90+R91+R95+R96+R97+R101 -> 0 | S102: =R102/Q102 -> #DIV/0! | T102: =T90+T91+T95+T96+T97+T101 -> 0 | U102: =T102/Q102 -> #DIV/0! | V102: =V90+V91+V95+V96+V97+V101 -> 0 | W102: =V102/Q102 -> #DIV/0!
A104: 5 | B104: EXIM MANAGEMENT (6) | E104: =D104/C104 -> #DIV/0! | G104: =F104/C104 -> #DIV/0! | I104: =H104/C104 -> #DIV/0! | L104: =K104/J104 -> #DIV/0! | N104: =M104/J104 -> #DIV/0! | P104: =O104/J104 -> #DIV/0! | S104: =R104/Q104 -> #DIV/0! | U104: =T104/Q104 -> #DIV/0! | W104: =V104/Q104 -> #DIV/0!
A105: 8 | B105: ACCOUNTING /FINANCE (7) | E105: =D105/C105 -> #DIV/0! | G105: =F105/C105 -> #DIV/0! | I105: =H105/C105 -> #DIV/0! | L105: =K105/J105 -> #DIV/0! | N105: =M105/J105 -> #DIV/0! | P105: =O105/J105 -> #DIV/0! | S105: =R105/Q105 -> #DIV/0! | U105: =T105/Q105 -> #DIV/0! | W105: =V105/Q105 -> #DIV/0!
B106: TOTAL | C106: =SUM(C104:C105)+C102 -> 0 | D106: =SUM(D104:D105)+D102 -> 0 | E106: =D106/C106 -> #DIV/0! | F106: =SUM(F104:F105)+F102 -> 0 | G106: =F106/C106 -> #DIV/0! | H106: =SUM(H104:H105)+H102 -> 0 | I106: =H106/C106 -> #DIV/0! | J106: =SUM(J104:J105)+J102 -> 0 | K106: =SUM(K104:K105)+K102 -> 0 | L106: =K106/J106 -> #DIV/0! | M106: =SUM(M104:M105)+M102 -> 0 | N106: =M106/J106 -> #DIV/0! | O106: =SUM(O104:O105)+O102 -> 0 | P106: =O106/J106 -> #DIV/0! | Q106: =SUM(Q104:Q105)+Q102 -> 0 | R106: =SUM(R104:R105)+R102 -> 0 | S106: =R106/Q106 -> #DIV/0! | T106: =SUM(T104:T105)+T102 -> 0 | U106: =T106/Q106 -> #DIV/0! | V106: =SUM(V104:V105)+V102 -> 0 | W106: =V106/Q106 -> #DIV/0!

Sheet Detail COMPLIANCE FIELD
B1: PT Semarang Autocomp Manufacturing Indonesia
I3: No. Doc : LA-RDP-07
I4: No.Rev : 01
I5: Tanggal Eff : 1 Jan 2018
C9: RINGKASAN DAFTAR PERATURAN
AN12: Month | AO12: 45108 | AP12: 45139 | AQ12: 45170 | AR12: 45200 | AS12: 45231 | AT12: 45261 | AU12: 45292 | AV12: 45323 | AW12: 45352 | AX12: 45383 | AY12: 45413 | AZ12: 45444
B13: No | C13: COMPLIANCE FIELD コンプライアンスフィールド | E13: PIC 担当者 | G13: STATUS 法律のステータス | I13: EVALUASI 評価 | K13: IMPLEMENTASI 実行 | AN13: Qty | AO13: =COUNTIFS($K$35:$K$620,AO12) -> 4 | AP13: =COUNTIFS($K$35:$K$620,AP12) -> 8 | AQ13: =COUNTIFS($K$35:$K$620,AQ12) -> 26 | AR13: =COUNTIFS($K$35:$K$620,AR12) -> 8 | AS13: =COUNTIFS($K$35:$K$620,AS12) -> 5 | AT13: =COUNTIFS($K$35:$K$620,AT12) -> 9 | AU13: =COUNTIFS($K$35:$K$620,AU12) -> 8 | AV13: =COUNTIFS($K$35:$K$620,AV12) -> 6 | ... AZ13: =COUNTIFS($K$35:$K$620,AZ12) -> 0
G14: Active 有効 | H14: No Active 無効 | I14: SUDAH 評価済 | J14: BELUM 未評価 | K14: OK | L14: NOK
B15: 1 | C15: COMPLIANCE IN GENERAL (1) | E15: FYH/STI | G15: =COUNTIFS($C$35:$C$620,$C15,$M$35:$M$620,G$14) -> 0 | H15: =COUNTIFS($C$35:$C$620,$C15,$M$35:$M$620,H$14) -> 0 | I15: =COUNTIFS($C$35:$C$620,$C15,$P$35:$P$620,I$14) -> 0 | J15: =COUNTIFS($C$35:$C$620,$C15,$P$35:$P$620,J$14) -> 0 | K15: =COUNTIFS($C$35:$C$620,$C15,$AB$35:$AB$620,K$14) -> 0 | L15: =COUNTIFS($C$35:$C$620,$C15,$AB$35:$AB$620,L$14) -> 0 | AN15: Month | AO15: 44743 | AP15: 44774 | AQ15: 44805 | AR15: 44835 | AS15: 44866 | AT15: 44896 | AU15: 44927 | AV15: 44958 | AW15: 44986 | AX15: 45017 | AY15: 45047 | AZ15: 45078
B16: 2 | C16: COMPANY /BUSINESS OPERATIONS & LICENSE (2) | E16: FYH/STI | G16: =COUNTIFS($C$35:$C$620,$C16,$M$35:$M$620,G$14) -> 99 | H16: =COUNTIFS($C$35:$C$620,$C16,$M$35:$M$620,H$14) -> 39 | I16: =COUNTIFS($C$35:$C$620,$C16,$P$35:$P$620,I$14) -> 99 | J16: =COUNTIFS($C$35:$C$620,$C16,$P$35:$P$620,J$14) -> 0 | K16: =COUNTIFS($C$35:$C$620,$C16,$AB$35:$AB$620,K$14) -> 98 | L16: =COUNTIFS($C$35:$C$620,$C16,$AB$35:$AB$620,L$14) -> 1 | AN16: Qty | AO16: =COUNTIFS($K$35:$K$620,AO15) -> 1 | AP16: =COUNTIFS($K$35:$K$620,AP15) -> 1 | AQ16: =COUNTIFS($K$35:$K$620,AQ15) -> 7 | AR16: =COUNTIFS($K$35:$K$620,AR15) -> 10 | AS16: =COUNTIFS($K$35:$K$620,AS15) -> 7 | AT16: =COUNTIFS($K$35:$K$620,AT15) -> 9 | AU16: =COUNTIFS($K$35:$K$620,AU15) -> 7 | AV16: =COUNTIFS($K$35:$K$620,AV15) -> 1 | ... AZ16: =COUNTIFS($K$35:$K$620,AZ15) -> 4
B17: 3 | C17: LABOR & HUMAN RIGHTS (3) | E17: FAD/FYH/NDP/DAP | G17: =COUNTIFS($C$35:$C$620,$C17,$M$35:$M$620,G$14) -> 126 | H17: =COUNTIFS($C$35:$C$620,$C17,$M$35:$M$620,H$14) -> 35 | I17: =COUNTIFS($C$35:$C$620,$C17,$P$35:$P$620,I$14) -> 126 | J17: =COUNTIFS($C$35:$C$620,$C17,$P$35:$P$620,J$14) -> 0 | K17: =COUNTIFS($C$35:$C$620,$C17,$AB$35:$AB$620,K$14) -> 122 | L17: =COUNTIFS($C$35:$C$620,$C17,$AB$35:$AB$620,L$14) -> 4
B18: 4 | C18: INTELLECTUAL PROPERTY (4) | E18: AKA | G18: =COUNTIFS($C$35:$C$620,$C18,$M$35:$M$620,G$14) -> 7 | H18: =COUNTIFS($C$35:$C$620,$C18,$M$35:$M$620,H$14) -> 0 | I18: =COUNTIFS($C$35:$C$620,$C18,$P$35:$P$620,I$14) -> 7 | J18: =COUNTIFS($C$35:$C$620,$C18,$P$35:$P$620,J$14) -> 0 | K18: =COUNTIFS($C$35:$C$620,$C18,$AB$35:$AB$620,K$14) -> 7 | L18: =COUNTIFS($C$35:$C$620,$C18,$AB$35:$AB$620,L$14) -> 0 | AN18: Month | AO18: 44378 | AP18: 44409 | AQ18: 44440 | AR18: 44470 | AS18: 44501 | AT18: 44531 | AU18: 44562 | AV18: 44593 | AW18: 44621 | AX18: 44652 | AY18: 44682 | AZ18: 44713
B19: 5 | C19: FAIR TRADING (5) | E19: AWI | G19: =COUNTIFS($C$35:$C$620,$C19,$M$35:$M$620,G$14) -> 6 | H19: =COUNTIFS($C$35:$C$620,$C19,$M$35:$M$620,H$14) -> 0 | I19: =COUNTIFS($C$35:$C$620,$C19,$P$35:$P$620,I$14) -> 6 | J19: =COUNTIFS($C$35:$C$620,$C19,$P$35:$P$620,J$14) -> 0 | K19: =COUNTIFS($C$35:$C$620,$C19,$AB$35:$AB$620,K$14) -> 6 | L19: =COUNTIFS($C$35:$C$620,$C19,$AB$35:$AB$620,L$14) -> 0 | AN19: Qty | AO19: =COUNTIFS($K$35:$K$620,AO18) -> 5 | AP19: =COUNTIFS($K$35:$K$620,AP18) -> 5 | AQ19: =COUNTIFS($K$35:$K$620,AQ18) -> 0 | AR19: =COUNTIFS($K$35:$K$620,AR18) -> 6 | AS19: =COUNTIFS($K$35:$K$620,AS18) -> 3 | AT19: =COUNTIFS($K$35:$K$620,AT18) -> 7 | AU19: =COUNTIFS($K$35:$K$620,AU18) -> 1 | AV19: =COUNTIFS($K$35:$K$620,AV18) -> 4 | ... AZ19: =COUNTIFS($K$35:$K$620,AZ18) -> 2
B20: 6 | C20: EXIM MANAGEMENT (6) | E20: YYS | G20: =COUNTIFS($C$35:$C$620,$C20,$M$35:$M$620,G$14) -> 37 | H20: =COUNTIFS($C$35:$C$620,$C20,$M$35:$M$620,H$14) -> 11 | I20: =COUNTIFS($C$35:$C$620,$C20,$P$35:$P$620,I$14) -> 37 | J20: =COUNTIFS($C$35:$C$620,$C20,$P$35:$P$620,J$14) -> 0 | K20: =COUNTIFS($C$35:$C$620,$C20,$AB$35:$AB$620,K$14) -> 37 | L20: =COUNTIFS($C$35:$C$620,$C20,$AB$35:$AB$620,L$14) -> 0
B21: 7 | C21: ACCOUNTING /FINANCE (7) | E21: BRI | G21: =COUNTIFS($C$35:$C$620,$C21,$M$35:$M$620,G$14) -> 56 | H21: =COUNTIFS($C$35:$C$620,$C21,$M$35:$M$620,H$14) -> 4 | I21: =COUNTIFS($C$35:$C$620,$C21,$P$35:$P$620,I$14) -> 56 | J21: =COUNTIFS($C$35:$C$620,$C21,$P$35:$P$620,J$14) -> 0 | K21: =COUNTIFS($C$35:$C$620,$C21,$AB$35:$AB$620,K$14) -> 56 | L21: =COUNTIFS($C$35:$C$620,$C21,$AB$35:$AB$620,L$14) -> 0 | AN21: Month | AO21: 44013 | AP21: 44044 | AQ21: 44075 | AR21: 44105 | AS21: 44136 | AT21: 44166 | AU21: 44197 | AV21: 44228 | AW21: 44256 | AX21: 44287 | AY21: 44317 | AZ21: 44348
B22: 8 | C22: ENVIRONMENT, SAFETY & HEALTH (8) | E22: JAW/ANG | G22: =COUNTIFS($C$35:$C$620,$C22,$M$35:$M$620,G$14) -> 123 | H22: =COUNTIFS($C$35:$C$620,$C22,$M$35:$M$620,H$14) -> 34 | I22: =COUNTIFS($C$35:$C$620,$C22,$P$35:$P$620,I$14) -> 123 | J22: =COUNTIFS($C$35:$C$620,$C22,$P$35:$P$620,J$14) -> 0 | K22: =COUNTIFS($C$35:$C$620,$C22,$AB$35:$AB$620,K$14) -> 116 | L22: =COUNTIFS($C$35:$C$620,$C22,$AB$35:$AB$620,L$14) -> 7 | AN22: Qty | AO22: =COUNTIFS($K$35:$K$620,AO21) -> 12 | AP22: =COUNTIFS($K$35:$K$620,AP21) -> 19 | AQ22: =COUNTIFS($K$35:$K$620,AQ21) -> 3 | AR22: =COUNTIFS($K$35:$K$620,AR21) -> 3 | AS22: =COUNTIFS($K$35:$K$620,AS21) -> 5 | AT22: =COUNTIFS($K$35:$K$620,AT21) -> 0 | AU22: =COUNTIFS($K$35:$K$620,AU21) -> 5 | AV22: =COUNTIFS($K$35:$K$620,AV21) -> 2 | ... AZ22: =COUNTIFS($K$35:$K$620,AZ21) -> 13
B23: TOTAL | G23: =SUM(G15:G22) -> 454 | H23: =SUM(H15:H22) -> 123 | I23: =SUM(I15:I22) -> 454 | J23: =SUM(J15:J22) -> 0 | K23: =SUM(K15:K22) -> 442 | L23: =SUM(L15:L22) -> 12
AN24: Month | AO24: 43282 | AP24: 43313 | AQ24: 43344 | AR24: 43374 | AS24: 43405 | AT24: 43435 | AU24: 43466 | AV24: 43497 | AW24: 43525 | AX24: 43556 | AY24: 43586 | AZ24: 43617
AN25: Qty | AO25: =COUNTIFS($K$35:$K$620,AO24) -> 74 | AP25: =COUNTIFS($K$35:$K$620,AP24) -> 8 | AQ25: =COUNTIFS($K$35:$K$620,AQ24) -> 26 | AR25: =COUNTIFS($K$35:$K$620,AR24) -> 14 | AS25: =COUNTIFS($K$35:$K$620,AS24) -> 3 | AT25: =COUNTIFS($K$35:$K$620,AT24) -> 6 | AU25: =COUNTIFS($K$35:$K$620,AU24) -> 6 | AV25: =COUNTIFS($K$35:$K$620,AV24) -> 12 | ... AZ25: =COUNTIFS($K$35:$K$620,AZ24) -> 2
AN27: Month | AO27: 43647 | AP27: 43678 | AQ27: 43709 | AR27: 43739 | AS27: 43770 | AT27: 43800 | AU27: 43831 | AV27: 43862 | AW27: 43891 | AX27: 43922 | AY27: 43952 | AZ27: 43983
AN28: Qty | AO28: =COUNTIFS($K$35:$K$620,AO27) -> 0 | AP28: =COUNTIFS($K$35:$K$620,AP27) -> 38 | AQ28: =COUNTIFS($K$35:$K$620,AQ27) -> 2 | AR28: =COUNTIFS($K$35:$K$620,AR27) -> 10 | AS28: =COUNTIFS($K$35:$K$620,AS27) -> 3 | AT28: =COUNTIFS($K$35:$K$620,AT27) -> 4 | AU28: =COUNTIFS($K$35:$K$620,AU27) -> 0 | AV28: =COUNTIFS($K$35:$K$620,AV27) -> 2 | ... AZ28: =COUNTIFS($K$35:$K$620,AZ27) -> 0
AC29: Print Date:
AC30: =NOW() -> 45400.622
A31: IDENTIFIKASI 法律の把握 | P31: EVALUASI 評価 | AA31: IMPLEMENTASI 実行
A32: NO | B32: C/S | C32: COMPLIANCE FIELD コンプライアンスフィールド | D32: ITEM FIELD 項目 | E32: JENIS PERATURAN 法律 | F32: TAHUN 年 | G32: NAMA PERATURAN タイトル | H32: OBJECT 法律対象 | I32: PUBLISHED DATE 公布日 | J32: EFFECTIVE DATE 実行日 | K32: ADD ON LIST (M-Y) リスト表に追加日 | L32: REASON 理由 | M32: STATUS ステータス | N32: LINGKUP HUKUM 適用範囲 | O32: Sumber Informasi 情報提供者 | P32: EVALUASI REGULASI 法律の評価 | Q32: BAGIAN PERATURAN TERKAIT 該当条項 | R32: SANKSI 制裁 | S32: ANALISA RESIKO リスク解析 | W32: BOBOT PENERAPAN | AA32: PENERAPAN DI SAMI SAMIでの実行 | AB32: EVALUASI PERNERAPAN 実行の評価 | AC32: RENCANA TINDAKAN (JIKA N.OK) 対応計画 （N-OKの場合） | AD32: DUE DATE 締切 | AE32: PIC 担当者
S33: SANKSI (a) 制裁 (a) | T33: KASUS (b) 事件 (b) | U33: NILAI (a+b) 評価点 (a+b) | V33: STATUS ステータス | W33: TOTAL | X33: OK | Y33: NOK | Z33: BOBOT
A34: 1 | B34: 2 | C34: 3 | D34: 4 | E34: 5 | F34: 6 | G34: 7 | H34: 8 | I34: 9 | J34: 10 | K34: 11 | L34: 12 | M34: 13 | N34: 14 | O34: 15 | P34: 16 | Q34: 17 | R34: 18 | S34: 19 | T34: 20 | U34: 21 | V34: 22 | AA34: 23 | AB34: 24 | AC34: 25 | AD34: 26 | AE34: 27
A35: 1 | B35: Ada | C35: COMPANY /BUSINESS OPERATIONS & LICENSE (2) | E35: UU | F35: 1960 | G35: Undang-Undang Nomor 5 Tahun 1960 | H35: Peraturan Dasar Pokok-Pokok Agraria | I35: 22183 | J35: 22183 | K35: 42917 | M35: Active 有効 | N35: N | O35: Affiliate | P35: SUDAH 評価済 | Q35: Pasal 15 Memelihara tanah, termasuk menambah kesuburannya serta mencegah kerusakannya adalah kewajiban tiap-tiap orang, badan hukum atau instansi yang mempunyai hubungan hukum dengan tanah itu, dengan memperhatikan pihak yang ekonomis lemah. Pasal 35 1) Hak guna-bangunan adalah hak untuk mendirikan dan mempunyai bangunan-bangunan atas tanah yang bukan miliknya sendiri, dengan jangka waktu paling lama 30 tahun. (2) Atas permintaan pemegang hak dan dengan mengingat keperluan serta keadaan bangunan bangunannya, jangka waktu tersebut dalam ayat (1) dapat diperpanjang dengan waktu paling lama 20 tahun. (3) Hak guna-bangunan dapat beralih dan dialihkan kepada pihak lain. | R35: Pasal 52 (1) Barangsiapa dengan sengaja melanggar ketentuan dalam pasal 15 dipidana dengan hukuman kurungan selama-lamanya 3 bulan dan/atau denda setinggi-tingginya Rp10.000,- (2) Peraturan Pemerintah dan peraturan perundangan yang dimaksud dalam pasal 19, 22, 24, 26, ayat (1), 46, 47, 48, 49, ayat (3) dan 50 ayat (2) dapat memberikan ancaman pidana atas pelanggaran peraturannya dengan hukuman kurungan selama-lamanya 3 bulan dan/atau denda setinggi-tingginya Rp10.000,-. (3) Tindak pidana dalam ayat (1) dan (2) pasal ini adalah pelanggaran. | S35: 3 | T35: 1 | U35: =S35+T35 -> 4 | V35: =IF(SUM(S35:T35)>5,"HIGH",IF(SUM(S35:T35)>3,"MEDIUM",IF(SUM(S35:T35)>=0,"LOW"))) -> MEDIUM | W35: =+X35+Y35 -> 1 | X35: 1 | Y35: 0 | Z35: =+X35/W35 -> 1 | AA35: Pembuatan kompos, biopori dan penanaman pohon HGB masih berlaku sampai tahun 2032 HGB no. 100, 101, 102, 103, 104, 105, 106, 107, 108, 109, 110 | AB35: OK
A36: 2 | C36: COMPANY /BUSINESS OPERATIONS & LICENSE (2) | E36: UU | F36: 1982 | G36: Undang-Undang Nomor 3 Tahun 1982 | H36: Wajib Daftar Perusahaan | I36: 29983 | J36: 29983 | K36: 42917 | L36: dicabut UU No. 11 Tahun 2020 tentang Cipta Kerja | M36: No Active 無効 | N36: N | O36: Affiliate | Q36: Pasal 5 (1) Setiap perusahaan wajib didaftarkan dalam Daftar Perusahaan. | R36: Pasal 32 (1) Barang siapa yang menurut Undang-undang ini dan atau peraturan pelaksanaannya diwajibkan mendaftarkan perusahaannya dalam Daftar Perusahaan yang dengan sengaja atau karena kelalaiannya tidak memenuhi kewajibannya diancam dengan pidana penjara selama-lamanya 3 (tiga) bulan atau pidana denda setinggi-tingginya Rp3.000.000,- (tiga juta rupiah). (2) Tindak pidana sebagaimana dimaksud dalam ayat (1) pasal ini merupakan kejahatan. Pasal 33 (1) Barang siapa melakukan atau menyuruh melakukan pendaftaran secara keliru atau tidak lengkap dalam Daftar Perusahaan diancam dengan pidana kurungan selama-lamanya 3 (tiga) bulan atau pidana denda setinggi-tingginya Rp1.500.000,- (satu juta lima ratus ribu rupiah). (2) Tindak pidana tersebut dalam ayat (1) pasal ini merupakan pelanggaran. Pasal 34 (1) Barang siapa tidak memenuhi kewajibannya menurut Undang-undang ini dan atau peraturan-peraturan pelaksanaannya untuk menghadap atau menolak untuk menyerahkan atau mengajukan sesuatu persyaratan dan atau keterangan lain untuk keperluan pendaftaran dalam Daftar Perusahaan diancam dengan pidana kurungan selama-lamanya 2 (dua) bulan atau pidana denda setinggi-tingginya Rp1.000.000,- (satu juta rupiah). (2) Tindak pidana sebagaimana dimaksud dalam ayat (1) pasal ini merupakan pelanggaran. Pasal 35 (1) Apabila tindak pidana sebagaimana, dimaksud dalam Pasal-pasal 32, 33 dan 34 Undang-undang ini dilakukan oleh suatu badan hukum, penuntutan pidana dikenakan dan pidana dijatuhkan terhadap pengurus atau pemegang kuasa dari badan hukum itu. (2) Ketentuan ayat (1) pasal ini diperlakukan sama terhadap badan hukum yang bertindak sebagai atau pemegang kuasa dari suatu badan hukum lain. f. tidak menyetorkan pajak yang telah dipotong atau dipungut sehingga dapat menimbulkan kerugian pada negara, dipidana dengan pidana penjara selama-lamanya tiga tahun dan /atau denda setinggi-tingginya sebesar empat kali jumlah pajak yang terhutang yang kurang atau yang tidak dibayar. (2) Ancaman dana sebagaimana dimaksud dalam ayat (1) dilipatkan dua apabila seseorang melakukan lagi tindak pidana di bidang perpajakan sebelum lewat satu tahun, terhitung sejak selesainya menjalani sebagian atau seluruh pidana penjara yang dijatuhkan. Pasal 43 Ketentuan sebagaimana dimaksud dalam Pasal 38 dan Pasal 39, berlaku juga bagi wakil, kuasa, atau pegawai dari Wajib Pajak. | S36: 2 | T36: 1 | U36: =S36+T36 -> 3 | V36: =IF(SUM(S36:T36)>5,"HIGH",IF(SUM(S36:T36)>3,"MEDIUM",IF(SUM(S36:T36)>=0,"LOW"))) -> LOW | AA36: TDP no. 11.01.1.29.04381 IUI no. 28/33/T/INDUSTRI/2004
A37: 3 | B37: Ada | C37: COMPANY /BUSINESS OPERATIONS & LICENSE (2) | E37: UU | F37: 1985 | G37: Undang-Undang Nomor 12 Tahun 1985 | H37: Pajak Bumi dan Bangunan | I37: 31408 | J37: 31413 | K37: 42917 | L37: diubah Undang-Undang Nomor 12 Tahun 1994 | M37: Active 有効 | N37: N | O37: Affiliate | P37: SUDAH 評価済 | Q37: Pasal 7 Besarnya pajak yang terhutang dihitung dengan cara mengalikan tarif pajak dengan Nilai Jual Kena Pajak. | R37: Pasal 24 Barang siapa karena kealpaannya: a. tidak mengembalikan/menyampaikan Surat Pemberitahuan Obyek Pajak kepada Direktorat Jenderal Pajak; b. menyampaikan Surat Pemberitahuan Obyek Pajak, tetapi isinya tidak benar atau tidak lengkap dan/atau melampirkan keterangan yang tidak benar; sehingga menimbulkan kerugian pada Negara, dipidana dengan pidana kurungan selama-lamanya 6 (enam) bulan atau denda setinggi-tingginya sebesar 2 (dua) kali pajak yang terhutang. Pasal 25 (1). Barang siapa dengan sengaja: a. tidak mengembalikan/menyampaikan Surat Pemberitahuan Obyek Pajak kepada Direktorat Jenderal Pajak; b. menyampaikan Surat Pemberitahuan Obyek Pajak, tetapi isinya tidak benar atau tidak lengkap dan/atau melampirkan keterangan yang tidak benar; c. memperlihatkan surat palsu atau dipalsukan atau dokumen lain yang palsu atau dipalsukan seolaholah benar; d. tidak memperlihatkan atau tidak meminjamkan surat atau dokumen lainnya; e. tidak menunjukkan data atau tidak menyampaikan keterangan yang diperlukan; sehingga menimbulkan kerugian pada Negara, dipidana dengan pidana penjara selama-lamanya 2 (dua) tahun atau denda setinggi-tingginya sebesar 5 (lima) kali pajak yang terhutang. (2). Terhadap bukan Wajib Pajak yang bersangkutan yang melakukan tindakan sebagaimana dimaksud dalam ayat (1) huruf d dan huruf e, dipidana dengan pidana kurungan selama-lamanya 1 (satu) tahun atau denda setinggi-tingginya Rp. 2.000.000,- (dua juta rupiah). (3). Ancaman pidana sebagaimana dimaksud dalam ayat (1) dilipatkan dua apabila seseorang melakukan lagi tindak pidana di bidang perpajakan sebelum lewat 1 (satu) tahun, terhitung sejak selesainya menjalani sebagian atau seluruh pidana penjara yang dijatuhkan atau sejak dibayarkan denda. | S37: 2 | T37: 1 | U37: =S37+T37 -> 3 | V37: =IF(SUM(S37:T37)>5,"HIGH",IF(SUM(S37:T37)>3,"MEDIUM",IF(SUM(S37:T37)>=0,"LOW"))) -> LOW | AA37: Bukti pembayaran PBB | AB37: OK
A38: 4 | B38: Ada | C38: COMPANY /BUSINESS OPERATIONS & LICENSE (2) | E38: UU | F38: 1994 | G38: Undang-Undang Nomor 12 Tahun 1994 | H38: Perubahan Atas Undang-Undang Nomor 12 Tahun 1985 Tentang Pajak Bumi Dan Bangunan | I38: 34647 | J38: 34700 | K38: 43282 | M38: Active 有効 | N38: N | O38: Affiliate | P38: SUDAH 評価済 | Q38: Pasal 3 (3). Besarnya Nilai Jual Objek Pajak Tidak Kena Pajak ditetapkan sebesar Rp.8.000.000,00 (delapan juta rupiah) untuk setiap Wajib Pajak. | R38: Sama dengan Undang-undang No. 12 Tahun 1985 | S38: 2 | T38: 1 | U38: =S38+T38 -> 3 | V38: =IF(SUM(S38:T38)>5,"HIGH",IF(SUM(S38:T38)>3,"MEDIUM",IF(SUM(S38:T38)>=0,"LOW"))) -> LOW | AA38: Bukti pembayaran PBB | AB38: OK
A39: 5 | C39: COMPANY /BUSINESS OPERATIONS & LICENSE (2) | E39: UU | F39: 2002 | G39: Undang-Undang Nomor 28 Tahun 2002 | H39: Bangunan Gedung | I39: 37606 | J39: 37971 | K39: 42917 | L39: diubah Undang-Undang Nomor 11 Tahun 2020 (dicabut) --> Peraturan Pemerintah Pengganti Undang-Undang Nomor 2 Tahun 2022 | M39: Active 有効 | N39: N | O39: Affiliate | P39: SUDAH 評価済 | Q39: Pasal 7 (1) Setiap bangunan gedung harus memenuhi persyaratan administratif dan persyaratan teknis sesuai dengan fungsi bangunan gedung. (2) Persyaratan administratif bangunan gedung sebagaimana dimaksud dalam ayat (1) meliputi persyaratan status hak atas tanah, status kepemilikan bangunan gedung, dan izin mendirikan bangunan. Pasal 17 (1) Persyaratan keselamatan bangunan gedung sebagaimana dimaksud dalam Pasal 16 ayat (1) meliputi persyaratan kemampuan bangunan gedung untuk mendukung beban muatan, serta kemampuan bangunan gedung dalam mencegah dan menanggulangi bahaya kebakaran dan bahaya petir. Pasal 30 (1) Akses evakuasi dalam keadaan darurat sebagaimana dimaksud dalam Pasal 27 ayat (2) harus disediakan di dalam bangunan gedung meliputi sistem peringatan bahaya bagi pengguna, pintu keluar darurat, dan jalur evakuasi apabila terjadi bencana kebakaran dan/atau bencana lainnya, kecuali rumah tinggal. Pasal 31 (1) Penyediaan fasilitas dan aksesibilitas bagi penyandang cacat dan lanjut usia sebagaimana dimaksud dalam Pasal 27 ayat (2) merupakan keharusan bagi semua bangunan gedung, kecuali rumah tinggal. | R39: Pasal 44 Setiap pemilik dan/atau pengguna yang tidak memenuhi kewajiban pemenuhan fungsi, dan/atau persyaratan, dan/atau penyelenggaraan bangunan gedung sebagaimana dimaksud dalam undang-undang ini dikenai sanksi administratif dan/atau sanksi pidana. Pasal 45 (1) Sanksi administratif sebagaimana dimaksud dalam Pasal 44 dapat berupa: a. peringatan tertulis, b. pembatasan kegiatan pembangunan, c. penghentian sementara atau tetap pada pekerjaan pelaksanaan pembangunan, d. penghentian sementara atau tetap pada pemanfaatan bangunan gedung; e. pembekuan izin mendirikan bangunan gedung; f. pencabutan izin mendirikan bangunan gedung; g. pembekuan sertifikat laik fungsi bangunan gedung; h. pencabutan sertifikat laik fungsi bangunan gedung; atau i. perintah pembongkaran bangunan gedung. (2) Selain pengenaan sanksi administratif sebagaimana dimaksud dalam ayat (1) dapat dikenai sanksi denda paling banyak 10% (sepuluh per seratus) dari nilai bangunan yang sedang atau telah dibangun. (3) Jenis pengenaan sanksi sebagaimana dimaksud dalam ayat (1) dan ayat (2) ditentukan oleh berat dan ringannya pelanggaran yang dilakukan. (4) Ketentuan mengenai tata cara pengenaan sanksi sebagaimana dimaksud dalam ayat (1), ayat (2), dan ayat (3) diatur lebih lanjut dengan Peraturan Pemerintah. Pasal 46 (1) Setiap pemilik dan/atau pengguna bangunan gedung yang tidak memenuhi ketentuan dalam undang-undang ini, diancam dengan pidana penjara paling lama 3 (tiga) tahun dan/atau denda paling banyak 10% (sepuluh per seratus) dari nilai bangunan, jika karenanya mengakibatkan kerugian harta benda orang lain. (2) Setiap pemilik dan/atau pengguna bangunan gedung yang tidak memenuhi ketentuan dalam undang-undang ini, diancam dengan pidana penjara paling lama 4 (empat) tahun dan/atau denda paling banyak 15% (lima belas per seratus) dari nilai bangunan gedung, jika karenanya mengakibatkan kecelakaan bagi orang lain yang mengakibatkan cacat seumur hidup. (3) Setiap pemilik dan/atau pengguna bangunan gedung yang tidak memenuhi ketentuan dalam undang-undang ini, diancam dengan pidana penjara paling lama 5 (lima) tahun dan/atau denda paling banyak 20% (dua puluh per seratus) dari nilai bangunan gedung, jika karenanya mengakibatkan hilangnya nyawa orang lain. (4) Dalam proses peradilan atas tindakan sebagaimana dimaksud dalam ayat (1), ayat (2), dan ayat (3) hakim memperhatikan pertimbangan dari tim ahli bangunan gedung. (5) Ketentuan mengenai tata cara pengenaan sanksi sebagaimana dimaksud dalam ayat (1), ayat (2), dan ayat (3) diatur lebih lanjut dengan Peraturan Pemerintah. Pasal 47 (1) Setiap orang atau badan yang karena kelalaiannya melanggar ketentuan yang telah ditetapkan dalam undang-undang ini sehingga mengakibatkan bangunan tidak laik fungsi dapat dipidana kurungan dan/atau pidana denda. (2) Pidana kurungan dan/atau pidana denda sebagaimana dimaksud dalam ayat (1) meliputi: a. pidana kurungan paling lama 1 (satu) tahun dan/atau pidana denda paling banyak 1% (satu per seratus) dari nilai bangunan gedung jika karenanya mengakibatkan kerugian harta benda orang lain; b. pidana kurungan paling lama 2 (dua) tahun dan/atau pidana denda paling banyak 2% (dua per seratus) dari nilai bangunan gedung jika karenanya mengakibatkan kecelakaan bagi orang lain sehingga menimbulkan cacat seumur hidup c. pidana kurungan paling lama 3 (tiga) tahun dan/atau pidana denda paling banyak 3% (tiga per seratus) dari nilai bangunan gedung jika karenanya mengakibatkan hilangnya nyawa orang lain. (3) Ketentuan mengenai tata cara pengenaan sanksi sebagaimana dimaksud dalam ayat (1) dan ayat (2) diatur lebih lanjut dengan Peraturan Pemerintah. | S39: 3 | T39: 1 | U39: =S39+T39 -> 4 | V39: =IF(SUM(S39:T39)>5,"HIGH",IF(SUM(S39:T39)>3,"MEDIUM",IF(SUM(S39:T39)>=0,"LOW"))) -> MEDIUM | AA39: HGB no. 100, 101, 102, 103, 104, 105, 106, 107, 108, 109, 110 IMB no. 648.1/448/2002 IMB no. 6441/1522/BPPT/IX/2016 IMB no. 644,4/1957/DPM-PTSP/XI/2017 Gedung: IMB Petir : sertifikasi penangkal petir Ada akses khusus penyandang cacat diarea kantin dan parkir kendaraan | AB39: OK
A40: 6 | C40: COMPANY /BUSINESS OPERATIONS & LICENSE (2) | E40: UU | F40: 2007 | G40: Undang-Undang Nomor 40 Tahun 2007 | H40: Perseroan Terbatas | I40: 39310 | J40: 39310 | K40: 42917 | L40: dicabut sebagian Putusan Mahkamah Konstitusi Nomor 84/PUU-XI/2013 diubah Undang-Undang Nomor 11 Tahun 2020 (dicabut) --> Peraturan Pemerintah Pengganti Undang-Undang Nomor 2 Tahun 2022 | M40: Active 有効 | N40: N | O40: Affiliate | P40: SUDAH 評価済 | Q40: Pasal 3 (1) Pemegang saham Perseroan tidak bertanggung jawab secara pribadi atas perikatan yang dibuat atas nama Perseroan dan tidak bertanggung jawab atas kerugian Perseroan melebihi saham yang dimiliki. (2) Ketentuan sebagaimana dimaksud pada ayat (1) tidak berlaku apabila: a. persyaratan Perseroan sebagai badan hukum belum atau tidak terpenuhi; b. pemegang saham yang bersangkutan baik langsung maupun tidak langsung dengan itikad buruk memanfaatkan Perseroan untuk kepentingan pribadi; c. pemegang saham yang bersangkutan terlibat dalam perbuatan melawan hukum yang dilakukan oleh Perseroan; atau d. pemegang saham yang bersangkutan baik langsung maupun tidak langsung secara melawan hukum menggunakan kekayaan Perseroan, yang mengakibatkan kekayaan Perseroan menjadi tidak cukup untuk melunasi utang Perseroan. Pasal 7 (1) Perseroan didirikan oleh 2 (dua) orang atau lebih dengan akta notaris yang dibuat dalam bahasa Indonesia. (2) Setiap pendiri Perseroan wajib mengambil bagian saham pada saat Perseroan didirikan. (3) Ketentuan sebagaimana dimaksud pada ayat (2) tidak berlaku dalam rangka Peleburan. (4) Perseroan memperoleh status badan hukum pada tanggal diterbitkannya Keputusan Menteri mengenai pengesahan badan hukum Perseroan. (5) Setelah Perseroan memperoleh status badan hukum dan pemegang saham menjadi kurang dari 2 (dua) orang, dalam jangka waktu paling lama 6 (enam) bulan terhitung sejak keadaan tersebut pemegang saham yang bersangkutan wajib mengalihkan sebagian sahamnya kepada orang lain atau Perseroan mengeluarkan saham baru kepada orang lain. Pasal 15 (1) Anggaran dasar sebagaimana dimaksud dalam Pasal 8 ayat (1) memuat sekurang-kurangnya: a. nama dan tempat kedudukan Perseroan; b. maksud dan tujuan serta kegiatan usaha Perseroan; c. jangka waktu berdirinya Perseroan; d. besarnya jumlah modal dasar, modal ditempatkan, dan modal disetor; e. jumlah saham, klasifikasi saham apabila ada berikut jumlah saham untuk tiap klasifikasi, hak-hak yang melekat pada setiap saham, dan nilai nominal setiap saham; f. nama jabatan dan jumlah anggota Direksi dan Dewan Komisaris; g. penetapan tempat dan tata cara penyelenggaraan RUPS; h. tata cara pengangkatan, penggantian, pemberhentian anggota Direksi dan Dewan Komisaris; i. tata cara penggunaan laba dan pembagian dividen. Pasal 18 Perseroan harus mempunyai maksud dan tujuan serta kegiatan usaha yang dicantumkan dalam anggaran dasar Perseroan sesuai dengan ketentuan peraturan perundang-undangan. Pasal 21 (1) Perubahan anggaran dasar tertentu harus mendapat persetujuan Menteri. (2) Perubahan anggaran dasar tertentu sebagaimana dimaksud pada ayat (1) meliputi: a. nama Perseroan dan/atau tempat kedudukan Perseroan; b. maksud dan tujuan serta kegiatan usaha Perseroan; c. jangka waktu berdirinya Perseroan; d. besarnya modal dasar; e. pengurangan modal ditempatkan dan disetor; dan/atau f. status Perseroan yang tertutup menjadi Perseroan Terbuka atau sebaliknya. Pasal 32 (1) Modal dasar Perseroan paling sedikit Rp 50.000.000,00 (lima puluh juta rupiah). Pasal 34 (1) Penyetoran atas modal saham dapat dilakukan dalam bentuk uang dan/atau dalam bentuk lainnya. (2) Dalam hal penyetoran modal saham dilakukan dalam bentuk lain sebagaimana dimaksud pada ayat (1), penilaian setoran modal saham ditentukan berdasarkan nilai wajar yang ditetapkan sesuai dengan harga pasar atau oleh ahli yang tidak terafiliasi dengan Perseroan. (3) Penyetoran saham dalam bentuk benda tidak bergerak harus diumumkan dalam 1 (satu) Surat Kabar atau lebih, dalam jangka waktu 14 (empat belas) hari setelah akta pendirian ditandatangani atau setelah RUPS memutuskan penyetoran saham tersebut. Pasal 42 (1) Keputusan RUPS untuk penambahan modal dasar adalah sah apabila dilakukan dengan memperhatikan persyaratan kuorum dan jumlah suara setuju untuk perubahan anggaran dasar sesuai dengan ketentuan dalam Undang-Undang ini dan/atau anggaran dasar. (2) Keputusan RUPS untuk penambahan modal ditempatkan dan disetor dalam batas modal dasar adalah sah apabila dilakukan dengan kuorum kehadiran lebih dari 1/2 (satu perdua) bagian dari seluruh jumlah saham dengan hak suara dan disetujui oleh lebih dari 1/2 (satu perdua) bagian dari jumlah seluruh suara yang dikeluarkan, kecuali ditentukan lebih besar dalam anggaran dasar . (3) Penambahan modal sebagaimana dimaksud pada ayat (2) wajib diberitahukan kepada Menteri untuk dicatat dalam daftar Perseroan. Pasal 49 (1) Nilai saham harus dicantumkan dalam mata uang rupiah. Pasal 68 (1) Direksi wajib menyerahkan laporan keuangan Perseroan kepada akuntan publik untuk diaudit apabila: a. kegiatan usaha Perseroan adalah menghimpun dan/ atau mengelola dana masyarakat; b. Perseroan menerbitkan surat pengakuan utang kepada masyarakat; c. Perseroan merupakan Perseroan Terbuka; d. Perseroan merupakan persero; e. Perseroan mempunyai aset dan/atau jumlah peredaran usaha dengan jumlah nilai paling sedikit Rp50.000.000.000,00 (lima puluh miliar rupiah); atau f. diwajibkan oleh peraturan perundang-undangan. Pasal 70 (1) Perseroan wajib menyisihkan jumlah tertentu dari laba bersih setiap tahun buku untuk cadangan. (2) Kewajiban penyisihan untuk cadangan sebagaimana dimaksud pada ayat (1) berlaku apabila Perseroan mempunyai saldo laba yang positif. (3) Penyisihan laba bersih sebagaimana dimaksud pada ayat (1) dilakukan sampai cadangan mencapai paling sedikit 20 % (dua puluh persen) dari jumlah modal yang ditempatkan dan disetor. (4) Cadangan sebagaimana dimaksud pada ayat (1) yang belum mencapai jumlah sebagaimana dimaksud pada ayat (3) hanya boleh dipergunakan untuk menutup kerugian yang tidak dapat dipenuhi oleh cadangan lain. Pasal 74 (1) Perseroan yang menjalankan kegiatan usahanya di bidang dan/atau berkaitan dengan sumber daya alam wajib melaksanakan Tanggung Jawab Sosial dan Lingkungan. Pasal 78 (2) RUPS tahunan wajib diadakan dalam jangka waktu paling lambat 6 (enam) bulan setelah tahun buku berakhir. Pasal 90 (1) Setiap penyelenggaraan RUPS, risalah RUPS wajib dibuat dan ditandatangani oleh ketua rapat dan paling sedikit 1 (satu) orang pemegang saham yang ditunjuk dari dan oleh peserta RUPS. (2) Tanda tangan sebagaimana dimaksud pada ayat (1) tidak disyaratkan apabila risalah RUPS tersebut dibuat dengan akta notaris. Pasal 92 (3) Direksi Perseroan terdiri atas 1 (satu) orang anggota Direksi atau lebih. Pasal 108 (3) Dewan Komisaris terdiri atas 1 (satu) orang anggota atau lebih. | S40: 1 | T40: 1 | U40: =S40+T40 -> 2 | V40: =IF(SUM(S40:T40)>5,"HIGH",IF(SUM(S40:T40)>3,"MEDIUM",IF(SUM(S40:T40)>=0,"LOW"))) -> LOW | AA40: - Akta no. 2 tanggal 7 Januari 2002 - SK Kemenkumham No. C.03916HT.01.01.TH.2002 - Akta no. 2 tanggal 7 Januari 2002 Rp 51.725.000.000 - Audit oleh akuntan public "Deloitte" - Pelaksanaan CSR 2kali dalam setahun - Jumlah direksi 3 orang tertera dalam Akta no. 2 tanggal 7 Juli 2017 - Jumlah dewan komisaris 2 orang tertera dalam Akta no. 2 tanggal 7 Juli 2017 | AB40: OK
A41: 7 | C41: COMPANY /BUSINESS OPERATIONS & LICENSE (2) | E41: UU | F41: 2007 | G41: Undang-Undang Nomor 25 Tahun 2007 | H41: Penanaman Modal | I41: 39198 | J41: 39198 | K41: 42917 | L41: dicabut sebagian Putusan Mahkamah Konstitusi Nomor 21-22/PUU-V/2007 diubah Undang-Undang Nomor 11 Tahun 2020 (dicabut) --> Peraturan Pemerintah Pengganti Undang-Undang Nomor 2 Tahun 2022 | M41: Active 有効 | N41: N | O41: Affiliate | P41: SUDAH 評価済 | Q41: Pasal 5 (2) Penanaman modal asing wajib dalam bentuk perseroan terbatas berdasarkan hukum Indonesia dan berkedudukan di dalam wilayah negara Republik Indonesia, kecuali ditentukan lain oleh undang-undang. Pasal 15 Setiap penanam modal berkewajiban: b. melaksanakan tanggung jawab sosial perusahaan; c. membuat laporan tentang kegiatan penanaman modal dan menyampaikannya kepada Badan Koordinasi Penanaman Modal; Pasal 33 (1) Penanam modal dalam negeri dan penanam modal asing yang melakukan penanaman modal dalam bentuk perseoran terbatas dilarang membuat perjanjian dan/atau pernyataan yang menegaskan bahwa kepemilikan saham dalam perseroan terbatas untuk dan atas nama orang lain. (2) Dalam hal penanam modal dalam negeri dan penanam modal asing membuat perjanjian dan/atau pernyataan sebagaimana dimaksud pada ayat (1), perjanjian dan/atau pernyataan itu dinyatakan batal demi hukum. (3) Dalam hal penanam modal yang melaksanakan kegiatan usaha berdasarkan perjanjian atau kontrak kerja sama dengan Pemerintah melakukan kejahatan korporasi berupa tindak pidana perpajakan, penggelembungan biaya pemulihan, dan bentuk penggelembungan biaya lainnya untuk memperkecil keuntungan yang mengakibatkan kerugian negara berdasarkan temuan atau pemeriksaan oleh pihak pejabat yang berwenang dan telah mendapat putusan pengadilan yang berkekuatan hukum tetap, Pemerintah mengakhiri perjanjian atau kontrak kerja sama dengan penanam modal yang bersangkutan. | R41: Pasal 34 (1) Badan usaha atau usaha perseorangan sebagaimana dimaksud dalam Pasal 5 yang tidak memenuhi kewajiban sebagaimana ditentukan dalam Pasal 15 dapat dikenai sanksi administratif berupa: a. peringatan tertulis; b. pembatasan kegiatan usaha; c. pembekuan kegiatan usaha dan/atau fasilitas penanaman modal; atau d. pencabutan kegiatan usaha dan/atau fasilitas penanaman modal. (2) Sanksi administratif sebagaimana dimaksud pada ayat (1) diberikan oleh instansi atau lembaga yang berwenang sesuai dengan ketentuan peraturan perundangundangan. (3) Selain dikenai sanksi administratif, badan usaha atau usaha perseorangan dapat dikenai sanksi lainnya sesuai dengan ketentuan peraturan perundang-undangan. | S41: 2 | T41: 1 | U41: =S41+T41 -> 3 | V41: =IF(SUM(S41:T41)>5,"HIGH",IF(SUM(S41:T41)>3,"MEDIUM",IF(SUM(S41:T41)>=0,"LOW"))) -> LOW | AA41: Akta no. 2 tanggal 7 Januari 2002 Pelaksanaan CSR 2kali dalam setahun LKPM dilaporkan ke BKPM secara online | AB41: OK
A42: 8 | C42: COMPANY /BUSINESS OPERATIONS & LICENSE (2) | E42: UU | F42: 2009 | G42: Undang-Undang Nomor 28 Tahun 2009 | H42: Pajak Daerah dan Retribusi Daerah | I42: 40071 | J42: 40179 | K42: 43252 | L42: Dicabut sebagian Putusan MK Nomor 80/PUU-XV/2017 diubah Undang-Undang Nomor 11 Tahun 2020 dicabut Undang-Undang Nomor 1 Tahun 2022 | M42: No Active 無効 | N42: N | O42: Sosialiasi Bapenda Jateng | Q42: Pasal 52 (1) Objek Pajak Penerangan Jalan adalah penggunaan tenaga listrik, baik yang dihasilkan sendiri maupun yang diperoleh dari sumber lain. (2) Listrik yang dihasilkan sendiri sebagaimana dimaksud pada ayat (1) meliputi seluruh pembangkit listrik. Pasal 55 (3) Penggunaan tenaga listrik yang dihasilkan sendiri, tarif Pajak Penerangan Jalan ditetapkan paling tinggi sebesar 1,5% (satu koma lima persen). Pasal 67 (1) Objek Pajak Air Tanah adalah pengambilan dan/atau pemanfaatan Air Tanah. | R42: Pasal 100 (1) Kepala Daerah dapat menerbitkan STPD jika: a. pajak dalam tahun berjalan tidak atau kurang dibayar; b. dari hasil penelitian SPTPD terdapat kekurangan pembayaran sebagai akibat salah tulis dan/atau salah hitung; c. Wajib Pajak dikenakan sanksi administratif berupa bunga dan/atau denda. (2) Jumlah kekurangan pajak yang terutang dalam STPD sebagaimana dimaksud pada ayat (1) huruf a dan huruf b ditambah dengan sanksi administratif berupa bunga sebesar 2% (dua persen) setiap bulan untuk paling lama 15 (lima belas) bulan sejak saat terutangnya pajak. (3) SKPD yang tidak atau kurang dibayar setelah jatuh tempo pembayaran dikenakan sanksi administratif berupa bunga sebesar 2% (dua persen) sebulan dan ditagih melalui STPD. | S42: 2 | T42: 2 | U42: =S42+T42 -> 4 | V42: =IF(SUM(S42:T42)>5,"HIGH",IF(SUM(S42:T42)>3,"MEDIUM",IF(SUM(S42:T42)>=0,"LOW"))) -> MEDIUM | AA42: - NPWPD ABT : P.2.9021776.16.02 - NPWPD PPJ : P.2.0110065.16.02 - Pajak air tanah sudah rutin tiap bulan max. Tgl 10
